Workbook
Name Account_Details: 'GL '!$A$1:$N$7
Name Katie___Item_Record: 'Item Master'!$A$1:$X$1997
Name Katie___Item_Record_1: 'Item Master'!$A$1:$X$2115

Sheet Cover Sheet
B1: JUUL LABS, INC.
B2: MONTH/YEAR: | C2: 43404
B3: GL#: | C3: 220950
B4: ACCOUNT: | C4: 220950 Accrued Freight/Fulfillment
B5: CURRENCY: | C5: GBP
B6: Prepared by: | C6: Matt Osborn | E6: Account Description
B7: Date: | C7: =TODAY() -> 43436 | E7: Accruals for freight costs - should reverse the following period
B8: Reviewed by: | C8: Phil Foyn
B9: Date:
B11: Description | C11: Amount | D11: Preparer Comment
B12: GL balance | C12: -353895.25
B13: Detailed breakdown | C13: =-Recon!D10 -> -353895.25 | D13: #FQ-220950 | G13: All reversed (see breakdown tab) in September 2018
B14: Difference | C14: =C12-C13 -> -0.0037060335
B16: Reconciling Items:
B18: Total Reconciling Items | C18: =SUM(C17:C17) -> 0
B20: Difference | C20: =C18+C14 -> -0.0037060335
B23: MoM Trending Analysis | D23: Amount | E23: Explanation (If over $100k or 10%)
B24: Prior Month Balance | D24: -173185.65 | E24: June/July and Aug Freight inbound costs plus Arvato WH costs
B25: MoM Difference | D25: =C12-D24 -> -180709.6
B26: MoM % Change | D26: =D25/D24 -> 1.0434444
A31: # | B31: Review Comment / Action Item | D31: Comment Date | E31: Preparer Response | G31: Response Date | H31: Status
A32: 1
A33: 2
A34: 3
A35: 4
A36: 5

Sheet Recon
A4: Description | B4: Type | C4: Ref | D4: Amount
A5: Freight In Expense Accrual OCt 2018 | B5: Accrual | C5: 1 | D5: =-'Trial Balance'!E120 -> 58433.106 | F5: Net Capitalized Balance after Reclass AP Invoices JNL from Inventory/Connor Group
A6: ACCR.ARVATO-Oct18 (75% of £160k Inv 94623882) | B6: Accrual | C6: 2 | D6: 120862.5 | F6: 75% accrual of Inv 94623882 - UK Mgt neogotiating lower fees/Pick Pack Rate
A7: ACCR>Avarto - Aug 18 & Sept 18 | B7: Accrual | C7: 3 | D7: 133500 | F7: Aug & Sept Inv not yet agreed. Pick Pack rate under negotiation
A8: ACCR>>Flexport International LLC USD>>pick up date 14.08.2018 freight charges-Oct 18 | B8: Accrual | C8: 4 | D8: 25803.05
A9: ACCR>>Flexport International LLC USD>>Pickup date Aug 30.2018 freight charges-Oct 18 | B9: Accrual | C9: 5 | D9: 15296.59
D10: =SUM(D5:D9) -> 353895.25
E36: =D8 -> 25803.05 | R36: =D9 -> 15296.59

Sheet GL 
A1: Title: | B1: Account Details
A2: Company: | B2: JuulUK
A3: Date: | B3: 02 Dec 2018 08:52 AM GMT+00:00
A5: Parameters
A6: Company: | B6: <Empty>
A7: Branch (Dynamic): | B7: PLOOM
A8: Ledger (Dynamic): | B8: ACTUAL
A9: From Period: | B9: 102018
A10: To Period: | B10: 102018
A11: Account: | B11: 220950
A12: Subaccount (Dynamic): | B12: <Empty>
A13: From Date (Dynamic): | B13: <Empty>
A14: Period Start Date: | B14: 01/10/2018 00:00:00
A15: To Date (Dynamic): | B15: <Empty>
A16: Period End Date: | B16: 31/10/2018 00:00:00
A17: Show Summary (Dynamic): | B17: FALSE
... A24: Ending Balance: | B24: -353895.25
A26: Selected | B26: Module | C26: Batch Number | D26: Tran. Date | E26: Period | F26: Description | G26: Ref. Number | H26: Account | I26: Subaccount | J26: Beg. Balance | K26: Debit Amount | L26: Credit Amount | M26: Ending Balance | N26: Reclass. Batch Number
B27: GL | C27: GL03-00029508 | D27: 43374 | E27: 10-2018 | F27: Freight In Expense Accrual Sep 2018 | H27: 220950 | I27: INTUK-CRP-6000-JUL | J27: -173185.65 | K27: 84836.85 | L27: 0 | M27: -88348.8
B28: GL | C28: GL03-00029595 | D28: 43374 | E28: 10-2018 | F28: Arvato Invoice Sept 18 - montlhy fixed fee | G28: Accrue Stampli | H28: 220950 | I28: INTUK-CRP-6000-JUL | J28: -88348.8 | K28: 15674.4 | L28: 0 | M28: -72674.4
B29: GL | C29: GL03-00029595 | D29: 43374 | E29: 10-2018 | F29: Re-Accrue Arvato - August 18 as inovice not yet received | G29: Accrue Stampli | H29: 220950 | I29: INTUK-CRP-6000-JUL | J29: -72674.4 | K29: 22000 | L29: 0 | M29: -50674.4
B30: GL | C30: GL03-00029595 | D30: 43374 | E30: 10-2018 | F30: Re-Accrue Arvato - August 18 as inovice not yet received | G30: Accrue Stampli | H30: 220950 | I30: INTUK-CRP-6000-JUL | J30: -50674.4 | K30: 15674.4 | L30: 0 | M30: -35000
B31: GL | C31: GL03-00029595 | D31: 43374 | E31: 10-2018 | F31: Re-Accrue Arvato - August 18 as inovice not yet received | G31: Accrue Stampli | H31: 220950 | I31: INTUK-CRP-6000-JUL | J31: -35000 | K31: 35000 | L31: 0 | M31: 0
B32: GL | C32: GL03-00032748 | D32: 43404 | E32: 10-2018 | F32: Freight In Expense Accrual OCt 2018 | H32: 220950 | I32: INTUK-CRP-6000-JUL | J32: 0 | K32: 0 | L32: 58433.11 | M32: -58433.11
B33: GL | C33: GL03-00032455 | D33: 43404 | E33: 10-2018 | F33: ACCR.ARVATO-Oct18 (75% of £160k Inv 94623882) | G33: ACCR.ARVATO | H33: 220950 | I33: INTUK-CRP-4600-JUL | J33: -58433.11 | K33: 0 | L33: 120862.5 | M33: -179295.61
B34: GL | C34: GL03-00032463 | D34: 43404 | E34: 10-2018 | F34: ACCR>Avarto - Aug 18 & Sept 18 | G34: ACCR.ARVATO | H34: 220950 | I34: INTUK-CRP-4600-JUL | J34: -179295.61 | K34: 0 | L34: 133500 | M34: -312795.61
B35: GL | C35: GL03-00032723 | D35: 43404 | E35: 10-2018 | F35: ACCR>>Flexport International LLC USD>>pick up date 14.08.2018 freight charges-Oct 18 | G35: FLEX-382035-1 | H35: 220950 | I35: INTUK-CRP-6000-JUL | J35: -312795.61 | K35: 0 | L35: 25803.05 | M35: -338598.66
B36: GL | C36: GL03-00032723 | D36: 43404 | E36: 10-2018 | F36: ACCR>>Flexport International LLC USD>>Pickup date Aug 30.2018 freight charges-Oct 18 | G36: FLEX-403093-1 | H36: 220950 | I36: INTUK-CRP-6000-JUL | J36: -338598.66 | K36: 0 | L36: 15296.59 | M36: -353895.25

Sheet JE
A1: Account | B1: Description | C1: Subaccount | D1: Ref. Number | E1: Quantity | F1: UOM | G1: Debit Amount | H1: Credit Amount | I1: Transaction Description | J1: Reclass. Batch Number
A2: 515000 | B2: Freight Inbound | C2: INTUK-CRP-4100-JUL | E2: 0 | G2: =-'Trial Balance'!E120 -> 58433.106 | H2: 0 | I2: Freight In Expense Accrual OCt 2018
A3: 220950 | B3: Accrued Freight/Fulfillment | C3: INTUK-CRP-6000-JUL | E3: 0 | G3: =-H2 -> 0 | H3: =G2 -> 58433.106 | I3: Freight In Expense Accrual OCt 2018

Sheet Trial Balance
A1: Trial Balance Summary | D1: Ledger: | E1: ACTUAL | F1: Page: | G1: 1 of 3 | I1: Original Data
A2: Company: | B2: JuulUK | F2: Date: | G2: 43404.861
A3: User: | B3: Karen.Fu | D3: Fin. Period: | E3: 10-2018
A5: Account | B5: Type | C5: Description | D5: Beginning Balance | E5: Debit | F5: Credit | G5: Ending Balance
A6: 112000 | B6: A | C6: MUFG - GBP | D6: 1279489.1 | E6: 3127446.9 | F6: 3700921.7 | G6: 706014.3
A7: 112001 | B7: A | C7: MUFG - EUR | D7: 1234260.6 | E7: 545373.61 | F7: 671530.21 | G7: 1108104
A8: 119000 | B8: A | C8: Undeposited/Cash in Transit | D8: -80456.98 | E8: 491293.93 | F8: 609808.34 | G8: -198971.39
A9: 121100 | B9: A | C9: Trade Accounts Receivable | D9: 611662.61 | E9: 2673802.8 | F9: 1106470.2 | G9: 2178995.1
A10: 123220 | B10: A | C10: VAT Input | D10: 546725.49 | E10: 165232.74 | F10: 7014.01 | G10: 704944.22
A11: 130100 | B11: A | C11: Prepaid Sales & Marketing | D11: 257335 | E11: 237540 | F11: 19795 | G11: 475080
A12: 130600 | B12: A | C12: Prepaid Other | D12: 390347.72 | E12: 2537807 | F12: 120853.17 | G12: 2807301.5
A13: 130650 | B13: A | C13: Clearing Account - Prepaid | D13: 2475599.8 | E13: 31728.69 | F13: 2507348 | G13: -19.49
A14: 141000 | B14: A | C14: Inventory - Finished Products | D14: 1708008.5 | E14: 1604724.6 | F14: 1099013.1 | G14: 2213720
A15: 150300 | B15: A | C15: Computer HW and Equipment | D15: -4781.77 | E15: 14141.41 | F15: 0.01 | G15: 9359.63
A16: 180100 | B16: A | C16: Intercompany Clearing Account | D16: -45.91 | E16: 12109.15 | F16: 0 | G16: 12063.24
A17: 191000 | B17: A | C17: Deposits - Long Term | D17: 1185798.8 | E17: 0 | F17: 71254.97 | G17: 1114543.8
... A106: 821200 | B106: E | C106: Unrealized (gain) loss - currency conversion | D106: 34852.06 | E106: 0 | F106: 0 | G106: 34852.06
C107: Total: | D107: =SUM(D46) -> 68763.55 | E107: =SUM(E46) -> 91883.09 | F107: =SUM(F46) -> 84836.85 | G107: =SUM(G46) -> 75809.79
C109: Account Integration:
C111: AP Invoices from Oct 2018 Shipments | E111: =E46 -> 91883.09 | F111: =F46 -> 84836.85
C112: Net Activity | E112: =E111-F111 -> 7046.24
C114: Shipments Oct 2018 | E114: ='UK Freight Rate'!D9 -> 65479.346
C116: Delta to be Expensed against Freight Capitalization (due to first month to Accrue) | E116: =E114-E112 -> 58433.106
C117: Sep Capitilized Freight | E117: 0
C118: Net Capitalized Balance after Expense | E118: =E117-E116 -> -58433.106
C119: Plus AP Invoices in Inv FG Adjustments | E119: 0
C120: Net Capitalized Balance after Reclass AP Invoices | E120: =E119+E118 -> -58433.106

Sheet UK Freight Rate
B2: Freight In Rates | C2: Current Month | D2: 43404
B4: Inventory Type | C4: Freight Per Unit | D4: Amount to be Expensed
B5: BK | C5: 0.5982425 | D5: =SUMIFS('Shipments UK'!N:N,'Shipments UK'!M:M,'UK Freight Rate'!B5) -> 4926.9816
B6: SK | C6: 0.60750386 | D6: =SUMIFS('Shipments UK'!N:N,'Shipments UK'!M:M,'UK Freight Rate'!B6) -> 30207.813
B7: RK | C7: 0.10367549 | D7: =SUMIFS('Shipments UK'!N:N,'Shipments UK'!M:M,'UK Freight Rate'!B7) -> 29055.147
B8: ACC | C8: 0.1900678 | D8: =SUMIFS('Shipments UK'!N:N,'Shipments UK'!M:M,'UK Freight Rate'!B8) -> 1289.4048
B9: Total | D9: =SUM(D5:D8) -> 65479.346

Sheet Shipments UK
J1: 1 day shipment est | K1: =SUMIF($M:$M,"BK",$L:$L) -> 8235.76 | L1: =(SUMIF($M$7:$M$100114,M1,$L$7:$L$100017)/25)*1 -> 316.76 | M1: BK | N1: =IF(M1="","",IFERROR(VLOOKUP(M1,'UK Freight Rate'!$B$5:$C$8,2,0)*L1,0)) -> 189.49929
J2: 1 day shipment est | K2: =SUMIF($M:$M,"RK",$L:$L) -> 280250.88 | L2: =(SUMIF($M$7:$M$100114,M2,$L$7:$L$100017)/25)*1 -> 1912.48 | M2: SK | N2: =IF(M2="","",IFERROR(VLOOKUP(M2,'UK Freight Rate'!$B$5:$C$8,2,0)*L2,0)) -> 1161.839
J3: 1 day shipment est | K3: =SUMIF($M:$M,"SK",$L:$L) -> 49724.48 | L3: =(SUMIF($M$7:$M$100114,M3,$L$7:$L$100017)/25)*1 -> 10778.88 | M3: RK | N3: =IF(M3="","",IFERROR(VLOOKUP(M3,'UK Freight Rate'!$B$5:$C$8,2,0)*L3,0)) -> 1117.5056
J4: 1 day shipment est | K4: =SUMIF($M:$M,"Acc",$L:$L) -> 6783.92 | L4: =(SUMIF($M$7:$M$100114,M4,$L$7:$L$100017)/25)*1 -> 260.92 | M4: Acc | N4: =IF(M4="","",IFERROR(VLOOKUP(M4,'UK Freight Rate'!$B$5:$C$8,2,0)*L4,0)) -> 49.592491
A6: Inventory ID | B6: Type | C6: Ref. Nbr. | D6: Operation | E6: Order Status | F6: Order Number | G6: Customer ID | H6: Customer Name | I6: Warehouse | J6: UOM | K6: Order Qty. | L6: Shipped Qty. | M6: Item Master | N6: Amount to Expense Freight Inbound
A7: J1A2255 | B7: BO | C7: SH03-00009325 | D7: Issue | E7: Completed | F7: SO03-00009352 | G7: 03-00000082 | H7: Violet's Vapes Ltd | I7: ARVATO-BI | J7: EA | K7: 8 | L7: 8 | M7: =VLOOKUP(A7,'Item Master'!$A:$D,4,0) -> Acc | N7: =IFERROR((VLOOKUP(M7,'UK Freight Rate'!$B$4:$C$8,2,0)*L7),0) -> 1.5205424
A8: J1A2255 | B8: BO | C8: SH03-00009328 | D8: Issue | E8: Completed | F8: SO03-00009355 | G8: 03-00000096 | H8: Magnum News | I8: ARVATO-BI | J8: EA | K8: 8 | L8: 8 | M8: =VLOOKUP(A8,'Item Master'!$A:$D,4,0) -> Acc | N8: =IFERROR((VLOOKUP(M8,'UK Freight Rate'!$B$4:$C$8,2,0)*L8),0) -> 1.5205424
A9: J1A2255 | B9: BO | C9: SH03-00009330 | D9: Issue | E9: Completed | F9: SO03-00009357 | G9: 03-00000024 | H9: INTERNET EXPRESS UK LTD | I9: ARVATO-BI | J9: EA | K9: 16 | L9: 16 | M9: =VLOOKUP(A9,'Item Master'!$A:$D,4,0) -> Acc | N9: =IFERROR((VLOOKUP(M9,'UK Freight Rate'!$B$4:$C$8,2,0)*L9),0) -> 3.0410848
A10: J1A2255 | B10: BO | C10: SH03-00009336 | D10: Issue | E10: Completed | F10: SO03-00009364 | G10: 03-00000031 | H10: Hyde Vapes Ltd | I10: ARVATO-BI | J10: EA | K10: 8 | L10: 8 | M10: =VLOOKUP(A10,'Item Master'!$A:$D,4,0) -> Acc | N10: =IFERROR((VLOOKUP(M10,'UK Freight Rate'!$B$4:$C$8,2,0)*L10),0) -> 1.5205424
A11: J1A2255 | B11: BO | C11: SH03-00009346 | D11: Issue | E11: Completed | F11: SO03-00009376 | G11: 03-00000033 | H11: Shisha Vibe | I11: ARVATO-BI | J11: EA | K11: 8 | L11: 8 | M11: =VLOOKUP(A11,'Item Master'!$A:$D,4,0) -> Acc | N11: =IFERROR((VLOOKUP(M11,'UK Freight Rate'!$B$4:$C$8,2,0)*L11),0) -> 1.5205424
A12: J1A2255 | B12: BO | C12: SH03-00009348 | D12: Issue | E12: Completed | F12: SO03-00009377 | G12: 03-00000060 | H12: EZ Homeware t/a EZ Cloudz | I12: ARVATO-BI | J12: EA | K12: 8 | L12: 8 | M12: =VLOOKUP(A12,'Item Master'!$A:$D,4,0) -> Acc | N12: =IFERROR((VLOOKUP(M12,'UK Freight Rate'!$B$4:$C$8,2,0)*L12),0) -> 1.5205424
A13: J1A2255 | B13: BO | C13: SH03-00009356 | D13: Issue | E13: Completed | F13: SO03-00009385 | G13: 03-00000036 | H13: primary keys ltd | I13: ARVATO-BI | J13: EA | K13: 8 | L13: 8 | M13: =VLOOKUP(A13,'Item Master'!$A:$D,4,0) -> Acc | N13: =IFERROR((VLOOKUP(M13,'UK Freight Rate'!$B$4:$C$8,2,0)*L13),0) -> 1.5205424
A14: J1A2255 | B14: BO | C14: SH03-00009365 | D14: Issue | E14: Completed | F14: SO03-00009394 | G14: 03-00000112 | H14: Manchestervapeman LTD | I14: ARVATO-BI | J14: EA | K14: 8 | L14: 8 | M14: =VLOOKUP(A14,'Item Master'!$A:$D,4,0) -> Acc | N14: =IFERROR((VLOOKUP(M14,'UK Freight Rate'!$B$4:$C$8,2,0)*L14),0) -> 1.5205424
A15: J1A2255 | B15: BO | C15: SH03-00009369 | D15: Issue | E15: Completed | F15: SO03-00009398 | G15: 03-00000010 | H15: Noble Vaping | I15: ARVATO-BI | J15: EA | K15: 16 | L15: 16 | M15: =VLOOKUP(A15,'Item Master'!$A:$D,4,0) -> Acc | N15: =IFERROR((VLOOKUP(M15,'UK Freight Rate'!$B$4:$C$8,2,0)*L15),0) -> 3.0410848
A16: J1A2255 | B16: BO | C16: SH03-00009379 | D16: Issue | E16: Completed | F16: SO03-00009408 | G16: 03-00000083 | H16: Vapeliqs Ltd (T/A Vape&Bean) | I16: ARVATO-BI | J16: EA | K16: 8 | L16: 8 | M16: =VLOOKUP(A16,'Item Master'!$A:$D,4,0) -> Acc | N16: =IFERROR((VLOOKUP(M16,'UK Freight Rate'!$B$4:$C$8,2,0)*L16),0) -> 1.5205424
A17: J1A2255 | B17: BO | C17: SH03-00009382 | D17: Issue | E17: Completed | F17: SO03-00009411 | G17: 03-00000038 | H17: Vapourcore | I17: ARVATO-BI | J17: EA | K17: 48 | L17: 48 | M17: =VLOOKUP(A17,'Item Master'!$A:$D,4,0) -> Acc | N17: =IFERROR((VLOOKUP(M17,'UK Freight Rate'!$B$4:$C$8,2,0)*L17),0) -> 9.1232545
A18: J1A2255 | B18: BO | C18: SH03-00009383 | D18: Issue | E18: Completed | F18: SO03-00009412 | G18: 03-00000009 | H18: House of Vapes | I18: ARVATO-BI | J18: EA | K18: 48 | L18: 48 | M18: =VLOOKUP(A18,'Item Master'!$A:$D,4,0) -> Acc | N18: =IFERROR((VLOOKUP(M18,'UK Freight Rate'!$B$4:$C$8,2,0)*L18),0) -> 9.1232545
... A3030: MKT2222 | B3030: IO | C3030: SH03-00009925 | D3030: Issue | E3030: Completed | F3030: SO03-00009950 | G3030: 03-00000147 | H3030: the beautifull news | I3030: ARVATO-BI | J3030: EA | K3030: 1 | L3030: 1 | M3030: =VLOOKUP(A3030,'Item Master'!$A:$D,4,0) -> Expense | N3030: =IFERROR((VLOOKUP(M3030,'UK Freight Rate'!$B$4:$C$8,2,0)*L3030),0) -> 0

Sheet ACM Shipments
B1: Shipment Details by Inventory Item | G1: Start Date: | H1: 43374 | K1: Page: | L1: 1 of 70 | N1: Original Data
B2: Company: | C2: JuulUK | G2: End Date: | H2: 43404 | K2: Date: | L2: 43404.871
B3: User: | C3: Karen.Fu
B5: Inventory ID | D5: Item Description | H5: Subitem
A6: =VLOOKUP(B6,B:C,2,FALSE) -> 0 | B6: J1A2255 | D6: JUUL UK USB Charger
A7: Inventory ID | B7: Type | C7: Ref. Nbr. | D7: Operation | E7: Order Status | F7: Order Number | G7: Customer ID | H7: Customer Name | I7: Warehouse | J7: UOM | K7: Order Qty. | L7: Shipped Qty.
A8: =IF(B8="","",IF(B7="Type",B6,A7)) -> J1A2255 | B8: BO | C8: SH03-00009325 | D8: Issue | E8: Completed | F8: SO03-00009352 | G8: 03-00000082 | H8: Violet's Vapes Ltd | I8: ARVATO-BI | J8: EA | K8: 8 | L8: 8
A9: =IF(B9="","",IF(B8="Type",B7,A8)) -> J1A2255 | B9: BO | C9: SH03-00009328 | D9: Issue | E9: Completed | F9: SO03-00009355 | G9: 03-00000096 | H9: Magnum News | I9: ARVATO-BI | J9: EA | K9: 8 | L9: 8
A10: =IF(B10="","",IF(B9="Type",B8,A9)) -> J1A2255 | B10: BO | C10: SH03-00009330 | D10: Issue | E10: Completed | F10: SO03-00009357 | G10: 03-00000024 | H10: INTERNET EXPRESS UK LTD | I10: ARVATO-BI | J10: EA | K10: 16 | L10: 16
A11: =IF(B11="","",IF(B10="Type",B9,A10)) -> J1A2255 | B11: BO | C11: SH03-00009336 | D11: Issue | E11: Completed | F11: SO03-00009364 | G11: 03-00000031 | H11: Hyde Vapes Ltd | I11: ARVATO-BI | J11: EA | K11: 8 | L11: 8
A12: =IF(B12="","",IF(B11="Type",B10,A11)) -> J1A2255 | B12: BO | C12: SH03-00009346 | D12: Issue | E12: Completed | F12: SO03-00009376 | G12: 03-00000033 | H12: Shisha Vibe | I12: ARVATO-BI | J12: EA | K12: 8 | L12: 8
A13: =IF(B13="","",IF(B12="Type",B11,A12)) -> J1A2255 | B13: BO | C13: SH03-00009348 | D13: Issue | E13: Completed | F13: SO03-00009377 | G13: 03-00000060 | H13: EZ Homeware t/a EZ Cloudz | I13: ARVATO-BI | J13: EA | K13: 8 | L13: 8
A14: =IF(B14="","",IF(B13="Type",B12,A13)) -> J1A2255 | B14: BO | C14: SH03-00009356 | D14: Issue | E14: Completed | F14: SO03-00009385 | G14: 03-00000036 | H14: primary keys ltd | I14: ARVATO-BI | J14: EA | K14: 8 | L14: 8
A15: =IF(B15="","",IF(B14="Type",B13,A14)) -> J1A2255 | B15: BO | C15: SH03-00009365 | D15: Issue | E15: Completed | F15: SO03-00009394 | G15: 03-00000112 | H15: Manchestervapeman LTD | I15: ARVATO-BI | J15: EA | K15: 8 | L15: 8
A16: =IF(B16="","",IF(B15="Type",B14,A15)) -> J1A2255 | B16: BO | C16: SH03-00009369 | D16: Issue | E16: Completed | F16: SO03-00009398 | G16: 03-00000010 | H16: Noble Vaping | I16: ARVATO-BI | J16: EA | K16: 16 | L16: 16
A17: =IF(B17="","",IF(B16="Type",B15,A16)) -> J1A2255 | B17: BO | C17: SH03-00009379 | D17: Issue | E17: Completed | F17: SO03-00009408 | G17: 03-00000083 | H17: Vapeliqs Ltd (T/A Vape&Bean) | I17: ARVATO-BI | J17: EA | K17: 8 | L17: 8
A18: =IF(B18="","",IF(B17="Type",B16,A17)) -> J1A2255 | B18: BO | C18: SH03-00009382 | D18: Issue | E18: Completed | F18: SO03-00009411 | G18: 03-00000038 | H18: Vapourcore | I18: ARVATO-BI | J18: EA | K18: 48 | L18: 48
A19: =IF(B19="","",IF(B18="Type",B17,A18)) -> J1A2255 | B19: BO | C19: SH03-00009383 | D19: Issue | E19: Completed | F19: SO03-00009412 | G19: 03-00000009 | H19: House of Vapes | I19: ARVATO-BI | J19: EA | K19: 48 | L19: 48
... A166: =IF(B166="","",IF(B165="Type",B164,A165)) -> J1A2255 | B166: IO | C166: SH03-00009897 | D166: Issue | E166: Completed | F166: SO03-00009921 | G166: 03-00000004 | H166: Juul Labs UK | I166: ARVATO-BI | J166: EA | K166: 3 | L166: 3
A167: =IF(B167="","",IF(B166="Type",B165,A166)) | J167: Total: | K167: 6523 | L167: 6523
A168: =IF(B168="","",IF(B167="Type",B166,A167))
A169: =IF(B169="","",IF(B168="Type",B167,A168)) | B169: J1D2295 | D169: JUUL UK Starter Kit, 1.7%, 4 pods
A170: =IF(B170="","",IF(B169="Type",B168,A169)) | B170: Type | C170: Ref. Nbr. | D170: Operation | E170: Order Status | F170: Order Number | G170: Customer ID | H170: Customer Name | I170: Warehouse | J170: UOM | K170: Order Qty. | L170: Shipped Qty.
A171: =IF(B171="","",IF(B170="Type",B169,A170)) -> J1D2295 | B171: BO | C171: SH03-00009470 | D171: Issue | E171: Completed | F171: SO03-00008944 | G171: 03-00000070 | H171: Juice Sauz Ltd | I171: ARVATO-BI | J171: EA | K171: 100 | L171: 6
A172: =IF(B172="","",IF(B171="Type",B170,A171)) -> J1D2295 | B172: BO | C172: SH03-00009313 | D172: Issue | E172: Completed | F172: SO03-00009344 | G172: 03-00000009 | H172: House of Vapes | I172: ARVATO-BI | J172: EA | K172: 336 | L172: 336
A173: =IF(B173="","",IF(B172="Type",B171,A172)) -> J1D2295 | B173: BO | C173: SH03-00009312 | D173: Issue | E173: Completed | F173: SO03-00009345 | G173: 03-00000095 | H173: Root vapes | I173: ARVATO-BI | J173: EA | K173: 16 | L173: 16
A174: =IF(B174="","",IF(B173="Type",B172,A173)) -> J1D2295 | B174: BO | C174: SH03-00009314 | D174: Issue | E174: Completed | F174: SO03-00009346 | G174: 03-00000110 | H174: Mr Ecig | I174: ARVATO-BI | J174: EA | K174: 4 | L174: 4
A175: =IF(B175="","",IF(B174="Type",B173,A174)) -> J1D2295 | B175: BO | C175: SH03-00009315 | D175: Issue | E175: Completed | F175: SO03-00009347 | G175: 03-00000091 | H175: Gold Vape London | I175: ARVATO-BI | J175: EA | K175: 8 | L175: 8
A176: =IF(B176="","",IF(B175="Type",B174,A175)) -> J1D2295 | B176: BO | C176: SH03-00009316 | D176: Issue | E176: Completed | F176: SO03-00009348 | G176: 03-00000049 | H176: city confectionery ltd | I176: ARVATO-BI | J176: EA | K176: 8 | L176: 8
A177: =IF(B177="","",IF(B176="Type",B175,A176)) -> J1D2295 | B177: BO | C177: SH03-00009317 | D177: Issue | E177: Completed | F177: SO03-00009349 | G177: 03-00000021 | H177: Easy Tek LTD t/a Vape Superstore | I177: ARVATO-BI | J177: EA | K177: 72 | L177: 72
A178: =IF(B178="","",IF(B177="Type",B176,A177)) -> J1D2295 | B178: BO | C178: SH03-00009318 | D178: Issue | E178: Completed | F178: SO03-00009350 | G178: 03-00000021 | H178: Easy Tek LTD t/a Vape Superstore | I178: ARVATO-BI | J178: EA | K178: 24 | L178: 24
A179: =IF(B179="","",IF(B178="Type",B177,A178)) -> J1D2295 | B179: BO | C179: SH03-00009325 | D179: Issue | E179: Completed | F179: SO03-00009352 | G179: 03-00000082 | H179: Violet's Vapes Ltd | I179: ARVATO-BI | J179: EA | K179: 8 | L179: 8
A180: =IF(B180="","",IF(B179="Type",B178,A179)) -> J1D2295 | B180: BO | C180: SH03-00009326 | D180: Issue | E180: Completed | F180: SO03-00009353 | G180: 03-00000029 | H180: Hasumati UK Limited | I180: ARVATO-BI | J180: EA | K180: 8 | L180: 8
A181: =IF(B181="","",IF(B180="Type",B179,A180)) -> J1D2295 | B181: BO | C181: SH03-00009329 | D181: Issue | E181: Completed | F181: SO03-00009356 | G181: 03-00000032 | H181: Warwickshire Vape Ltd | I181: ARVATO-BI | J181: EA | K181: 24 | L181: 24
A182: =IF(B182="","",IF(B181="Type",B180,A181)) -> J1D2295 | B182: BO | C182: SH03-00009330 | D182: Issue | E182: Completed | F182: SO03-00009357 | G182: 03-00000024 | H182: INTERNET EXPRESS UK LTD | I182: ARVATO-BI | J182: EA | K182: 40 | L182: 40
... A671: =IF(B671="","",IF(B670="Type",B669,A670)) -> J1D2295 | B671: IO | C671: SH03-00009950 | D671: Issue | E671: Completed | F671: SO03-00009976 | G671: 03-00000178 | H671: online vapour ltd | I671: ARVATO-BI | J671: EA | K671: 4 | L671: 4
A672: =IF(B672="","",IF(B671="Type",B670,A671)) | J672: Total: | K672: 47906 | L672: 47812
A673: =IF(B673="","",IF(B672="Type",B671,A672))
A674: =IF(B674="","",IF(B673="Type",B672,A673)) | B674: J1D2349 | D674: JUUL UK Device Kit
A675: =IF(B675="","",IF(B674="Type",B673,A674)) | B675: Type | C675: Ref. Nbr. | D675: Operation | E675: Order Status | F675: Order Number | G675: Customer ID | H675: Customer Name | I675: Warehouse | J675: UOM | K675: Order Qty. | L675: Shipped Qty.
A676: =IF(B676="","",IF(B675="Type",B674,A675)) -> J1D2349 | B676: BO | C676: SH03-00009313 | D676: Issue | E676: Completed | F676: SO03-00009344 | G676: 03-00000009 | H676: House of Vapes | I676: ARVATO-BI | J676: EA | K676: 192 | L676: 192
A677: =IF(B677="","",IF(B676="Type",B675,A676)) -> J1D2349 | B677: BO | C677: SH03-00009316 | D677: Issue | E677: Completed | F677: SO03-00009348 | G677: 03-00000049 | H677: city confectionery ltd | I677: ARVATO-BI | J677: EA | K677: 24 | L677: 24
A678: =IF(B678="","",IF(B677="Type",B676,A677)) -> J1D2349 | B678: BO | C678: SH03-00009330 | D678: Issue | E678: Completed | F678: SO03-00009357 | G678: 03-00000024 | H678: INTERNET EXPRESS UK LTD | I678: ARVATO-BI | J678: EA | K678: 8 | L678: 8
A679: =IF(B679="","",IF(B678="Type",B677,A678)) -> J1D2349 | B679: BO | C679: SH03-00009331 | D679: Issue | E679: Completed | F679: SO03-00009358 | G679: 03-00000094 | H679: Shopecigarette ltd. | I679: ARVATO-BI | J679: EA | K679: 16 | L679: 16
A680: =IF(B680="","",IF(B679="Type",B678,A679)) -> J1D2349 | B680: BO | C680: SH03-00009347 | D680: Issue | E680: Completed | F680: SO03-00009375 | G680: 03-00000013 | H680: Evapo Ltd | I680: ARVATO-BI | J680: EA | K680: 96 | L680: 96
A681: =IF(B681="","",IF(B680="Type",B679,A680)) -> J1D2349 | B681: BO | C681: SH03-00009350 | D681: Issue | E681: Completed | F681: SO03-00009379 | G681: 03-00000065 | H681: Juice for Days LTD | I681: ARVATO-BI | J681: EA | K681: 8 | L681: 8
A682: =IF(B682="","",IF(B681="Type",B680,A681)) -> J1D2349 | B682: BO | C682: SH03-00009353 | D682: Issue | E682: Completed | F682: SO03-00009381 | G682: 03-00000044 | H682: VAPEHUT UK LTD | I682: ARVATO-BI | J682: EA | K682: 24 | L682: 24
A683: =IF(B683="","",IF(B682="Type",B681,A682)) -> J1D2349 | B683: BO | C683: SH03-00009356 | D683: Issue | E683: Completed | F683: SO03-00009385 | G683: 03-00000036 | H683: primary keys ltd | I683: ARVATO-BI | J683: EA | K683: 8 | L683: 8
A684: =IF(B684="","",IF(B683="Type",B682,A683)) -> J1D2349 | B684: BO | C684: SH03-00009358 | D684: Issue | E684: Completed | F684: SO03-00009387 | G684: 03-00000087 | H684: Essentials | I684: ARVATO-BI | J684: EA | K684: 40 | L684: 40
A685: =IF(B685="","",IF(B684="Type",B683,A684)) -> J1D2349 | B685: BO | C685: SH03-00009359 | D685: Issue | E685: Completed | F685: SO03-00009388 | G685: 03-00000111 | H685: V & M (Tolworth) Ltd | I685: ARVATO-BI | J685: EA | K685: 8 | L685: 8
A686: =IF(B686="","",IF(B685="Type",B684,A685)) -> J1D2349 | B686: BO | C686: SH03-00009365 | D686: Issue | E686: Completed | F686: SO03-00009394 | G686: 03-00000112 | H686: Manchestervapeman LTD | I686: ARVATO-BI | J686: EA | K686: 24 | L686: 24
A687: =IF(B687="","",IF(B686="Type",B685,A686)) -> J1D2349 | B687: BO | C687: SH03-00009366 | D687: Issue | E687: Completed | F687: SO03-00009395 | G687: 03-00000029 | H687: Hasumati UK Limited | I687: ARVATO-BI | J687: EA | K687: 8 | L687: 8
... A849: =IF(B849="","",IF(B848="Type",B847,A848)) -> J1D2349 | B849: IO | C849: SH03-00009941 | D849: Issue | E849: Completed | F849: SO03-00009970 | G849: 03-00000081 | H849: vape-57 | I849: ARVATO-BI | J849: EA | K849: 1 | L849: 1
A850: =IF(B850="","",IF(B849="Type",B848,A849)) | J850: Total: | K850: 4448 | L850: 4448
A851: =IF(B851="","",IF(B850="Type",B849,A850))
A852: =IF(B852="","",IF(B851="Type",B850,A851)) | B852: J1D2535 | D852: JUUL UK Device Kit Silver
A853: =IF(B853="","",IF(B852="Type",B851,A852)) | B853: Type | C853: Ref. Nbr. | D853: Operation | E853: Order Status | F853: Order Number | G853: Customer ID | H853: Customer Name | I853: Warehouse | J853: UOM | K853: Order Qty. | L853: Shipped Qty.
A854: =IF(B854="","",IF(B853="Type",B852,A853)) -> J1D2535 | B854: BO | C854: SH03-00009312 | D854: Issue | E854: Completed | F854: SO03-00009345 | G854: 03-00000095 | H854: Root vapes | I854: ARVATO-BI | J854: EA | K854: 8 | L854: 8
A855: =IF(B855="","",IF(B854="Type",B853,A854)) -> J1D2535 | B855: BO | C855: SH03-00009316 | D855: Issue | E855: Completed | F855: SO03-00009348 | G855: 03-00000049 | H855: city confectionery ltd | I855: ARVATO-BI | J855: EA | K855: 8 | L855: 8
A856: =IF(B856="","",IF(B855="Type",B854,A855)) -> J1D2535 | B856: BO | C856: SH03-00009327 | D856: Issue | E856: Completed | F856: SO03-00009354 | G856: 03-00000023 | H856: Vape Invaders LTD | I856: ARVATO-BI | J856: EA | K856: 16 | L856: 16
A857: =IF(B857="","",IF(B856="Type",B855,A856)) -> J1D2535 | B857: BO | C857: SH03-00009328 | D857: Issue | E857: Completed | F857: SO03-00009355 | G857: 03-00000096 | H857: Magnum News | I857: ARVATO-BI | J857: EA | K857: 8 | L857: 8
A858: =IF(B858="","",IF(B857="Type",B856,A857)) -> J1D2535 | B858: BO | C858: SH03-00009330 | D858: Issue | E858: Completed | F858: SO03-00009357 | G858: 03-00000024 | H858: INTERNET EXPRESS UK LTD | I858: ARVATO-BI | J858: EA | K858: 8 | L858: 8
A859: =IF(B859="","",IF(B858="Type",B857,A858)) -> J1D2535 | B859: BO | C859: SH03-00009335 | D859: Issue | E859: Completed | F859: SO03-00009363 | G859: 03-00000031 | H859: Hyde Vapes Ltd | I859: ARVATO-BI | J859: EA | K859: 8 | L859: 8
A860: =IF(B860="","",IF(B859="Type",B858,A859)) -> J1D2535 | B860: BO | C860: SH03-00009345 | D860: Issue | E860: Completed | F860: SO03-00009374 | G860: 03-00000098 | H860: EFF Marketing Ltd t/a Cigara | I860: ARVATO-BI | J860: EA | K860: 48 | L860: 48
A861: =IF(B861="","",IF(B860="Type",B859,A860)) -> J1D2535 | B861: BO | C861: SH03-00009347 | D861: Issue | E861: Completed | F861: SO03-00009375 | G861: 03-00000013 | H861: Evapo Ltd | I861: ARVATO-BI | J861: EA | K861: 96 | L861: 96
A862: =IF(B862="","",IF(B861="Type",B860,A861)) -> J1D2535 | B862: BO | C862: SH03-00009350 | D862: Issue | E862: Completed | F862: SO03-00009379 | G862: 03-00000065 | H862: Juice for Days LTD | I862: ARVATO-BI | J862: EA | K862: 16 | L862: 16
A863: =IF(B863="","",IF(B862="Type",B861,A862)) -> J1D2535 | B863: BO | C863: SH03-00009352 | D863: Issue | E863: Completed | F863: SO03-00009380 | G863: 03-00000022 | H863: 23rd Retail Ltd | I863: ARVATO-BI | J863: EA | K863: 8 | L863: 8
A864: =IF(B864="","",IF(B863="Type",B862,A863)) -> J1D2535 | B864: BO | C864: SH03-00009353 | D864: Issue | E864: Completed | F864: SO03-00009381 | G864: 03-00000044 | H864: VAPEHUT UK LTD | I864: ARVATO-BI | J864: EA | K864: 24 | L864: 24
A865: =IF(B865="","",IF(B864="Type",B863,A864)) -> J1D2535 | B865: BO | C865: SH03-00009356 | D865: Issue | E865: Completed | F865: SO03-00009385 | G865: 03-00000036 | H865: primary keys ltd | I865: ARVATO-BI | J865: EA | K865: 8 | L865: 8
... A983: =IF(B983="","",IF(B982="Type",B981,A982)) -> J1D2535 | B983: IO | C983: SH03-00009897 | D983: Issue | E983: Completed | F983: SO03-00009921 | G983: 03-00000004 | H983: Juul Labs UK | I983: ARVATO-BI | J983: EA | K983: 3 | L983: 3
A984: =IF(B984="","",IF(B983="Type",B982,A983)) | J984: Total: | K984: 3471 | L984: 3471
A985: =IF(B985="","",IF(B984="Type",B983,A984))
A986: =IF(B986="","",IF(B985="Type",B984,A985)) | B986: J1T2296 | D986: JUULpods UK Golden Tobacco 20mg/mL (4pack)
A987: =IF(B987="","",IF(B986="Type",B985,A986)) | B987: Type | C987: Ref. Nbr. | D987: Operation | E987: Order Status | F987: Order Number | G987: Customer ID | H987: Customer Name | I987: Warehouse | J987: UOM | K987: Order Qty. | L987: Shipped Qty.
A988: =IF(B988="","",IF(B987="Type",B986,A987)) -> J1T2296 | B988: BO | C988: SH03-00009313 | D988: Issue | E988: Completed | F988: SO03-00009344 | G988: 03-00000009 | H988: House of Vapes | I988: ARVATO-BI | J988: EA | K988: 528 | L988: 528
A989: =IF(B989="","",IF(B988="Type",B987,A988)) -> J1T2296 | B989: BO | C989: SH03-00009312 | D989: Issue | E989: Completed | F989: SO03-00009345 | G989: 03-00000095 | H989: Root vapes | I989: ARVATO-BI | J989: EA | K989: 8 | L989: 8
A990: =IF(B990="","",IF(B989="Type",B988,A989)) -> J1T2296 | B990: BO | C990: SH03-00009316 | D990: Issue | E990: Completed | F990: SO03-00009348 | G990: 03-00000049 | H990: city confectionery ltd | I990: ARVATO-BI | J990: EA | K990: 24 | L990: 24
A991: =IF(B991="","",IF(B990="Type",B989,A990)) -> J1T2296 | B991: BO | C991: SH03-00009317 | D991: Issue | E991: Completed | F991: SO03-00009349 | G991: 03-00000021 | H991: Easy Tek LTD t/a Vape Superstore | I991: ARVATO-BI | J991: EA | K991: 48 | L991: 48
A992: =IF(B992="","",IF(B991="Type",B990,A991)) -> J1T2296 | B992: BO | C992: SH03-00009325 | D992: Issue | E992: Completed | F992: SO03-00009352 | G992: 03-00000082 | H992: Violet's Vapes Ltd | I992: ARVATO-BI | J992: EA | K992: 8 | L992: 8
A993: =IF(B993="","",IF(B992="Type",B991,A992)) -> J1T2296 | B993: BO | C993: SH03-00009326 | D993: Issue | E993: Completed | F993: SO03-00009353 | G993: 03-00000029 | H993: Hasumati UK Limited | I993: ARVATO-BI | J993: EA | K993: 16 | L993: 16
A994: =IF(B994="","",IF(B993="Type",B992,A993)) -> J1T2296 | B994: BO | C994: SH03-00009329 | D994: Issue | E994: Completed | F994: SO03-00009356 | G994: 03-00000032 | H994: Warwickshire Vape Ltd | I994: ARVATO-BI | J994: EA | K994: 8 | L994: 8
A995: =IF(B995="","",IF(B994="Type",B993,A994)) -> J1T2296 | B995: BO | C995: SH03-00009330 | D995: Issue | E995: Completed | F995: SO03-00009357 | G995: 03-00000024 | H995: INTERNET EXPRESS UK LTD | I995: ARVATO-BI | J995: EA | K995: 24 | L995: 24
A996: =IF(B996="","",IF(B995="Type",B994,A995)) -> J1T2296 | B996: BO | C996: SH03-00009335 | D996: Issue | E996: Completed | F996: SO03-00009363 | G996: 03-00000031 | H996: Hyde Vapes Ltd | I996: ARVATO-BI | J996: EA | K996: 8 | L996: 8
A997: =IF(B997="","",IF(B996="Type",B995,A996)) -> J1T2296 | B997: BO | C997: SH03-00009336 | D997: Issue | E997: Completed | F997: SO03-00009364 | G997: 03-00000031 | H997: Hyde Vapes Ltd | I997: ARVATO-BI | J997: EA | K997: 8 | L997: 8
A998: =IF(B998="","",IF(B997="Type",B996,A997)) -> J1T2296 | B998: BO | C998: SH03-00009338 | D998: Issue | E998: Completed | F998: SO03-00009366 | G998: 03-00000007 | H998: Electronic Cigarettes Ltd | I998: ARVATO-BI | J998: EA | K998: 48 | L998: 48
A999: =IF(B999="","",IF(B998="Type",B997,A998)) -> J1T2296 | B999: BO | C999: SH03-00009340 | D999: Issue | E999: Completed | F999: SO03-00009367 | G999: 03-00000017 | H999: James J Fox | I999: ARVATO-BI | J999: EA | K999: 200 | L999: 200
... A1377: =IF(B1377="","",IF(B1376="Type",B1375,A1376)) -> J1T2296 | B1377: IO | C1377: SH03-00009946 | D1377: Issue | E1377: Completed | F1377: SO03-00009972 | G1377: 03-00000034 | H1377: els (bromley) ltd | I1377: ARVATO-BI | J1377: EA | K1377: 4 | L1377: 4
A1378: =IF(B1378="","",IF(B1377="Type",B1376,A1377)) | J1378: Total: | K1378: 73769 | L1378: 73769
A1379: =IF(B1379="","",IF(B1378="Type",B1377,A1378))
A1380: =IF(B1380="","",IF(B1379="Type",B1378,A1379)) | B1380: J1T2297 | D1380: JUULpods UK Glacier Mint 20mg/mL (4pack)
A1381: =IF(B1381="","",IF(B1380="Type",B1379,A1380)) | B1381: Type | C1381: Ref. Nbr. | D1381: Operation | E1381: Order Status | F1381: Order Number | G1381: Customer ID | H1381: Customer Name | I1381: Warehouse | J1381: UOM | K1381: Order Qty. | L1381: Shipped Qty.
A1382: =IF(B1382="","",IF(B1381="Type",B1380,A1381)) -> J1T2297 | B1382: BO | C1382: SH03-00009313 | D1382: Issue | E1382: Completed | F1382: SO03-00009344 | G1382: 03-00000009 | H1382: House of Vapes | I1382: ARVATO-BI | J1382: EA | K1382: 528 | L1382: 528
A1383: =IF(B1383="","",IF(B1382="Type",B1381,A1382)) -> J1T2297 | B1383: BO | C1383: SH03-00009312 | D1383: Issue | E1383: Completed | F1383: SO03-00009345 | G1383: 03-00000095 | H1383: Root vapes | I1383: ARVATO-BI | J1383: EA | K1383: 16 | L1383: 16
A1384: =IF(B1384="","",IF(B1383="Type",B1382,A1383)) -> J1T2297 | B1384: BO | C1384: SH03-00009316 | D1384: Issue | E1384: Completed | F1384: SO03-00009348 | G1384: 03-00000049 | H1384: city confectionery ltd | I1384: ARVATO-BI | J1384: EA | K1384: 16 | L1384: 16
A1385: =IF(B1385="","",IF(B1384="Type",B1383,A1384)) -> J1T2297 | B1385: BO | C1385: SH03-00009317 | D1385: Issue | E1385: Completed | F1385: SO03-00009349 | G1385: 03-00000021 | H1385: Easy Tek LTD t/a Vape Superstore | I1385: ARVATO-BI | J1385: EA | K1385: 48 | L1385: 48
A1386: =IF(B1386="","",IF(B1385="Type",B1384,A1385)) -> J1T2297 | B1386: BO | C1386: SH03-00009318 | D1386: Issue | E1386: Completed | F1386: SO03-00009350 | G1386: 03-00000021 | H1386: Easy Tek LTD t/a Vape Superstore | I1386: ARVATO-BI | J1386: EA | K1386: 48 | L1386: 48
A1387: =IF(B1387="","",IF(B1386="Type",B1385,A1386)) -> J1T2297 | B1387: BO | C1387: SH03-00009326 | D1387: Issue | E1387: Completed | F1387: SO03-00009353 | G1387: 03-00000029 | H1387: Hasumati UK Limited | I1387: ARVATO-BI | J1387: EA | K1387: 8 | L1387: 8
A1388: =IF(B1388="","",IF(B1387="Type",B1386,A1387)) -> J1T2297 | B1388: BO | C1388: SH03-00009328 | D1388: Issue | E1388: Completed | F1388: SO03-00009355 | G1388: 03-00000096 | H1388: Magnum News | I1388: ARVATO-BI | J1388: EA | K1388: 16 | L1388: 16
A1389: =IF(B1389="","",IF(B1388="Type",B1387,A1388)) -> J1T2297 | B1389: BO | C1389: SH03-00009329 | D1389: Issue | E1389: Completed | F1389: SO03-00009356 | G1389: 03-00000032 | H1389: Warwickshire Vape Ltd | I1389: ARVATO-BI | J1389: EA | K1389: 8 | L1389: 8
A1390: =IF(B1390="","",IF(B1389="Type",B1388,A1389)) -> J1T2297 | B1390: BO | C1390: SH03-00009330 | D1390: Issue | E1390: Completed | F1390: SO03-00009357 | G1390: 03-00000024 | H1390: INTERNET EXPRESS UK LTD | I1390: ARVATO-BI | J1390: EA | K1390: 32 | L1390: 32
...

Sheet Shipments UK_Raw Data
A1: Shipment Details by Inventory Item | F1: Start Date: | G1: 43344 | J1: Page: | K1: 1 of 66
A2: Company: | B2: JuulUK | F2: End Date: | G2: 43371 | J2: Date: | K2: 43371.707 | M2: Original Data
A3: User: | B3: Karen.Fu
A5: Inventory ID | C5: Item Description | G5: Subitem
A6: J1A2255 | C6: JUUL UK USB Charger
A7: Type | B7: Ref. Nbr. | C7: Operation | D7: Order Status | E7: Order Number | F7: Customer ID | G7: Customer Name | H7: Warehouse | I7: UOM | J7: Order Qty. | K7: Shipped Qty.
A8: BO | B8: SH03-00008146 | C8: Issue | D8: Completed | E8: SO03-00008191 | F8: 03-00000009 | G8: House of Vapes | H8: ARVATO-BI | I8: EA | J8: 24 | K8: 24
A9: BO | B9: SH03-00008644 | C9: Issue | D9: Completed | E9: SO03-00008686 | F9: 03-00000038 | G9: Vapourcore | H9: ARVATO-BI | I9: EA | J9: 24 | K9: 24
A10: BO | B10: SH03-00008647 | C10: Issue | D10: Completed | E10: SO03-00008689 | F10: 03-00000011 | G10: The London Vape Co | H10: ARVATO-BI | I10: EA | J10: 48 | K10: 48
A11: BO | B11: SH03-00008901 | C11: Issue | D11: Completed | E11: SO03-00008943 | F11: 03-00000029 | G11: Hasumati UK Limited | H11: ARVATO-BI | I11: EA | J11: 8 | K11: 8
A12: BO | B12: SH03-00008910 | C12: Issue | D12: Completed | E12: SO03-00008952 | F12: 03-00000072 | G12: Partica Kingston LTD trading as Vape Lords | H12: ARVATO-BI | I12: EA | J12: 8 | K12: 8
A13: BO | B13: SH03-00008911 | C13: Issue | D13: Completed | E13: SO03-00008953 | F13: 03-00000010 | G13: Noble Vaping | H13: ARVATO-BI | I13: EA | J13: 8 | K13: 8
A14: BO | B14: SH03-00008915 | C14: Issue | D14: Completed | E14: SO03-00008958 | F14: 03-00000047 | G14: Smk Vapes ltd Trading as Smokium | H14: ARVATO-BI | I14: EA | J14: 8 | K14: 8
A15: BO | B15: SH03-00008916 | C15: Issue | D15: Completed | E15: SO03-00008959 | F15: 03-00000073 | G15: Vape Club Ltd | H15: ARVATO-BI | I15: EA | J15: 80 | K15: 80
A16: BO | B16: SH03-00008923 | C16: Issue | D16: Completed | E16: SO03-00008966 | F16: 03-00000074 | G16: V & M (Teddington) Ltd | H16: ARVATO-BI | I16: EA | J16: 8 | K16: 8
A17: BO | B17: SH03-00008924 | C17: Issue | D17: Completed | E17: SO03-00008967 | F17: 03-00000075 | G17: Mobivape Worcester LTD | H17: ARVATO-BI | I17: EA | J17: 8 | K17: 8
A18: BO | B18: SH03-00008926 | C18: Issue | D18: Completed | E18: SO03-00008969 | F18: 03-00000048 | G18: The Eagle Vape Shop (Saras Fix Ltd) | H18: ARVATO-BI | I18: EA | J18: 8 | K18: 8
A19: BO | B19: SH03-00008928 | C19: Issue | D19: Completed | E19: SO03-00008970 | F19: 03-00000076 | G19: Vape Industries Ltd | H19: ARVATO-BI | I19: EA | J19: 8 | K19: 8
... A125: SO | B125: SH03-00008880 | C125: Issue | D125: Completed | E125: SO03-00008914 | F125: 03-00000016 | G125: JUUL UK B2C | H125: ARVATO-BI | I125: EA | J125: 2 | K125: 2
I126: Total: | J126: 1700 | K126: 1700
A128: J1D2295 | C128: JUUL UK Starter Kit, 1.7%, 4 pods
A129: Type | B129: Ref. Nbr. | C129: Operation | D129: Order Status | E129: Order Number | F129: Customer ID | G129: Customer Name | H129: Warehouse | I129: UOM | J129: Order Qty. | K129: Shipped Qty.
A130: BO | B130: SH03-00008144 | C130: Issue | D130: Completed | E130: SO03-00008189 | F130: 03-00000067 | G130: LUCID JUICES VAPE STORE | H130: ARVATO-BI | I130: EA | J130: 4 | K130: 4
A131: BO | B131: SH03-00008145 | C131: Issue | D131: Completed | E131: SO03-00008190 | F131: 03-00000068 | G131: VAPERS BOX LTD | H131: ARVATO-BI | I131: EA | J131: 24 | K131: 24
A132: BO | B132: SH03-00008146 | C132: Issue | D132: Completed | E132: SO03-00008191 | F132: 03-00000009 | G132: House of Vapes | H132: ARVATO-BI | I132: EA | J132: 48 | K132: 48
A133: BO | B133: SH03-00008147 | C133: Issue | D133: Completed | E133: SO03-00008192 | F133: 03-00000057 | G133: Vape Terrace limited | H133: ARVATO-BI | I133: EA | J133: 4 | K133: 4
A134: BO | B134: SH03-00008643 | C134: Issue | D134: Completed | E134: SO03-00008685 | F134: 03-00000017 | G134: James J Fox | H134: ARVATO-BI | I134: EA | J134: 80 | K134: 80
A135: BO | B135: SH03-00008644 | C135: Issue | D135: Completed | E135: SO03-00008686 | F135: 03-00000038 | G135: Vapourcore | H135: ARVATO-BI | I135: EA | J135: 144 | K135: 144
A136: BO | B136: SH03-00008645 | C136: Issue | D136: Completed | E136: SO03-00008687 | F136: 03-00000013 | G136: Evapo Ltd | H136: ARVATO-BI | I136: EA | J136: 408 | K136: 408
A137: BO | B137: SH03-00008646 | C137: Issue | D137: Completed | E137: SO03-00008688 | F137: 03-00000036 | G137: primary keys ltd | H137: ARVATO-BI | I137: EA | J137: 8 | K137: 8
A138: BO | B138: SH03-00008647 | C138: Issue | D138: Completed | E138: SO03-00008689 | F138: 03-00000011 | G138: The London Vape Co | H138: ARVATO-BI | I138: EA | J138: 48 | K138: 48
A139: BO | B139: SH03-00008906 | C139: Issue | D139: Back Order | E139: SO03-00008944 | F139: 03-00000070 | G139: Juice Sauz Ltd | H139: ARVATO-BI | I139: EA | J139: 100 | K139: 94
A140: BO | B140: SH03-00008907 | C140: Issue | D140: Completed | E140: SO03-00008949 | F140: 03-00000034 | G140: els (bromley) ltd | H140: ARVATO-BI | I140: EA | J140: 20 | K140: 20
A141: BO | B141: SH03-00008908 | C141: Issue | D141: Completed | E141: SO03-00008950 | F141: 03-00000071 | G141: Flamenco Ninja LTD | H141: ARVATO-BI | I141: EA | J141: 4 | K141: 4
... A808: SO | B808: SH03-00008892 | C808: Issue | D808: Completed | E808: SO03-00008926 | F808: 03-00000016 | G808: JUUL UK B2C | H808: ARVATO-BI | I808: EA | J808: 1 | K808: 1
I809: Total: | J809: 11936 | K809: 11930
A811: J1D2349 | C811: JUUL UK Device Kit
A812: Type | B812: Ref. Nbr. | C812: Operation | D812: Order Status | E812: Order Number | F812: Customer ID | G812: Customer Name | H812: Warehouse | I812: UOM | J812: Order Qty. | K812: Shipped Qty.
A813: BO | B813: SH03-00008146 | C813: Issue | D813: Completed | E813: SO03-00008191 | F813: 03-00000009 | G813: House of Vapes | H813: ARVATO-BI | I813: EA | J813: 24 | K813: 24
A814: BO | B814: SH03-00008644 | C814: Issue | D814: Completed | E814: SO03-00008686 | F814: 03-00000038 | G814: Vapourcore | H814: ARVATO-BI | I814: EA | J814: 144 | K814: 144
A815: BO | B815: SH03-00008645 | C815: Issue | D815: Completed | E815: SO03-00008687 | F815: 03-00000013 | G815: Evapo Ltd | H815: ARVATO-BI | I815: EA | J815: 48 | K815: 48
A816: BO | B816: SH03-00008646 | C816: Issue | D816: Completed | E816: SO03-00008688 | F816: 03-00000036 | G816: primary keys ltd | H816: ARVATO-BI | I816: EA | J816: 24 | K816: 24
A817: BO | B817: SH03-00008647 | C817: Issue | D817: Completed | E817: SO03-00008689 | F817: 03-00000011 | G817: The London Vape Co | H817: ARVATO-BI | I817: EA | J817: 48 | K817: 48
A818: BO | B818: SH03-00008648 | C818: Issue | D818: Completed | E818: SO03-00008690 | F818: 03-00000069 | G818: Venpa Services UK Ltd. T/A Vape Palace | H818: ARVATO-BI | I818: EA | J818: 32 | K818: 32
A819: BO | B819: SH03-00008901 | C819: Issue | D819: Completed | E819: SO03-00008943 | F819: 03-00000029 | G819: Hasumati UK Limited | H819: ARVATO-BI | I819: EA | J819: 8 | K819: 8
A820: BO | B820: SH03-00008909 | C820: Issue | D820: Completed | E820: SO03-00008951 | F820: 03-00000061 | G820: E1 Vapes Limited | H820: ARVATO-BI | I820: EA | J820: 8 | K820: 8
A821: BO | B821: SH03-00008910 | C821: Issue | D821: Completed | E821: SO03-00008952 | F821: 03-00000072 | G821: Partica Kingston LTD trading as Vape Lords | H821: ARVATO-BI | I821: EA | J821: 16 | K821: 16
A822: BO | B822: SH03-00008911 | C822: Issue | D822: Completed | E822: SO03-00008953 | F822: 03-00000010 | G822: Noble Vaping | H822: ARVATO-BI | I822: EA | J822: 8 | K822: 8
A823: BO | B823: SH03-00008912 | C823: Issue | D823: Completed | E823: SO03-00008954 | F823: 03-00000023 | G823: Vape Invaders LTD | H823: ARVATO-BI | I823: EA | J823: 16 | K823: 16
A824: BO | B824: SH03-00008914 | C824: Issue | D824: Completed | E824: SO03-00008955 | F824: 03-00000010 | G824: Noble Vaping | H824: ARVATO-BI | I824: EA | J824: 48 | K824: 48
... A1037: SO | B1037: SH03-00008879 | C1037: Issue | D1037: Completed | E1037: SO03-00008913 | F1037: 03-00000016 | G1037: JUUL UK B2C | H1037: ARVATO-BI | I1037: EA | J1037: 1 | K1037: 1
I1038: Total: | J1038: 4807 | K1038: 4807
A1040: J1D2535 | C1040: JUUL UK Device Kit Silver
A1041: Type | B1041: Ref. Nbr. | C1041: Operation | D1041: Order Status | E1041: Order Number | F1041: Customer ID | G1041: Customer Name | H1041: Warehouse | I1041: UOM | J1041: Order Qty. | K1041: Shipped Qty.
A1042: BO | B1042: SH03-00009121 | C1042: Issue | D1042: Completed | E1042: SO03-00009138 | F1042: 03-00000005 | G1042: Vaporized | H1042: ARVATO-BI | I1042: EA | J1042: 1056 | K1042: 1056
A1043: BO | B1043: SH03-00009111 | C1043: Issue | D1043: Completed | E1043: SO03-00009142 | F1043: 03-00000032 | G1043: Warwickshire Vape Ltd | H1043: ARVATO-BI | I1043: EA | J1043: 96 | K1043: 96
A1044: BO | B1044: SH03-00009112 | C1044: Issue | D1044: Completed | E1044: SO03-00009143 | F1044: 03-00000083 | G1044: Vapeliqs Ltd (T/A Vape&Bean) | H1044: ARVATO-BI | I1044: EA | J1044: 8 | K1044: 8
A1045: BO | B1045: SH03-00009113 | C1045: Issue | D1045: Completed | E1045: SO03-00009144 | F1045: 03-00000050 | G1045: J Noble and sons limited | H1045: ARVATO-BI | I1045: EA | J1045: 16 | K1045: 16
A1046: BO | B1046: SH03-00009114 | C1046: Issue | D1046: Completed | E1046: SO03-00009145 | F1046: 03-00000034 | G1046: els (bromley) ltd | H1046: ARVATO-BI | I1046: EA | J1046: 16 | K1046: 16
A1047: BO | B1047: SH03-00009116 | C1047: Issue | D1047: Completed | E1047: SO03-00009147 | F1047: 03-00000096 | G1047: Magnum News | H1047: ARVATO-BI | I1047: EA | J1047: 8 | K1047: 8
A1048: BO | B1048: SH03-00009122 | C1048: Issue | D1048: Completed | E1048: SO03-00009151 | F1048: 03-00000097 | G1048: VAPEHQ Ltd | H1048: ARVATO-BI | I1048: EA | J1048: 144 | K1048: 144
A1049: BO | B1049: SH03-00009123 | C1049: Issue | D1049: Completed | E1049: SO03-00009152 | F1049: 03-00000098 | G1049: EFF Marketing Ltd t/a Cigara | H1049: ARVATO-BI | I1049: EA | J1049: 48 | K1049: 48
A1050: BO | B1050: SH03-00009125 | C1050: Issue | D1050: Completed | E1050: SO03-00009159 | F1050: 03-00000017 | G1050: James J Fox | H1050: ARVATO-BI | I1050: EA | J1050: 320 | K1050: 320
A1051: BO | B1051: SH03-00009130 | C1051: Issue | D1051: Completed | E1051: SO03-00009162 | F1051: 03-00000006 | G1051: Vapouriz Group Ltd | H1051: ARVATO-BI | I1051: EA | J1051: 432 | K1051: 432
A1052: BO | B1052: SH03-00009127 | C1052: Issue | D1052: Completed | E1052: SO03-00009165 | F1052: 03-00000024 | G1052: INTERNET EXPRESS UK LTD | H1052: ARVATO-BI | I1052: EA | J1052: 24 | K1052: 24
A1053: BO | B1053: SH03-00009129 | C1053: Issue | D1053: Completed | E1053: SO03-00009168 | F1053: 03-00000031 | G1053: Hyde Vapes Ltd | H1053: ARVATO-BI | I1053: EA | J1053: 8 | K1053: 8
... A1100: IO | B1100: SH03-00009289 | C1100: Issue | D1100: Completed | E1100: SO03-00009324 | F1100: 03-00000004 | G1100: Juul Labs UK | H1100: ARVATO-BI | I1100: EA | J1100: 48 | K1100: 48
I1101: Total: | J1101: 4170 | K1101: 4170
A1103: J1T2296 | C1103: JUULpods UK Golden Tobacco 20mg/mL (4pack)
A1104: Type | B1104: Ref. Nbr. | C1104: Operation | D1104: Order Status | E1104: Order Number | F1104: Customer ID | G1104: Customer Name | H1104: Warehouse | I1104: UOM | J1104: Order Qty. | K1104: Shipped Qty.
A1105: BO | B1105: SH03-00008144 | C1105: Issue | D1105: Completed | E1105: SO03-00008189 | F1105: 03-00000067 | G1105: LUCID JUICES VAPE STORE | H1105: ARVATO-BI | I1105: EA | J1105: 8 | K1105: 8
A1106: BO | B1106: SH03-00008145 | C1106: Issue | D1106: Completed | E1106: SO03-00008190 | F1106: 03-00000068 | G1106: VAPERS BOX LTD | H1106: ARVATO-BI | I1106: EA | J1106: 32 | K1106: 32
A1107: BO | B1107: SH03-00008146 | C1107: Issue | D1107: Completed | E1107: SO03-00008191 | F1107: 03-00000009 | G1107: House of Vapes | H1107: ARVATO-BI | I1107: EA | J1107: 288 | K1107: 288
A1108: BO | B1108: SH03-00008643 | C1108: Issue | D1108: Completed | E1108: SO03-00008685 | F1108: 03-00000017 | G1108: James J Fox | H1108: ARVATO-BI | I1108: EA | J1108: 360 | K1108: 360
A1109: BO | B1109: SH03-00008644 | C1109: Issue | D1109: Completed | E1109: SO03-00008686 | F1109: 03-00000038 | G1109: Vapourcore | H1109: ARVATO-BI | I1109: EA | J1109: 192 | K1109: 192
A1110: BO | B1110: SH03-00008645 | C1110: Issue | D1110: Completed | E1110: SO03-00008687 | F1110: 03-00000013 | G1110: Evapo Ltd | H1110: ARVATO-BI | I1110: EA | J1110: 192 | K1110: 192
A1111: BO | B1111: SH03-00008646 | C1111: Issue | D1111: Completed | E1111: SO03-00008688 | F1111: 03-00000036 | G1111: primary keys ltd | H1111: ARVATO-BI | I1111: EA | J1111: 16 | K1111: 16
A1112: BO | B1112: SH03-00008647 | C1112: Issue | D1112: Completed | E1112: SO03-00008689 | F1112: 03-00000011 | G1112: The London Vape Co | H1112: ARVATO-BI | I1112: EA | J1112: 96 | K1112: 96
A1113: BO | B1113: SH03-00008648 | C1113: Issue | D1113: Completed | E1113: SO03-00008690 | F1113: 03-00000069 | G1113: Venpa Services UK Ltd. T/A Vape Palace | H1113: ARVATO-BI | I1113: EA | J1113: 32 | K1113: 32
A1114: BO | B1114: SH03-00008893 | C1114: Issue | D1114: Completed | E1114: SO03-00008935 | F1114: 03-00000022 | G1114: 23rd Retail Ltd | H1114: ARVATO-BI | I1114: EA | J1114: 40 | K1114: 40
A1115: BO | B1115: SH03-00008906 | C1115: Issue | D1115: Back Order | E1115: SO03-00008944 | F1115: 03-00000070 | G1115: Juice Sauz Ltd | H1115: ARVATO-BI | I1115: EA | J1115: 48 | K1115: 48
A1116: BO | B1116: SH03-00008908 | C1116: Issue | D1116: Completed | E1116: SO03-00008950 | F1116: 03-00000071 | G1116: Flamenco Ninja LTD | H1116: ARVATO-BI | I1116: EA | J1116: 8 | K1116: 8
... A1458: SO | B1458: SH03-00008891 | C1458: Issue | D1458: Completed | E1458: SO03-00008925 | F1458: 03-00000016 | G1458: JUUL UK B2C | H1458: ARVATO-BI | I1458: EA | J1458: 1 | K1458: 1
I1459: Total: | J1459: 13752 | K1459: 13752
A1461: J1T2297 | C1461: JUULpods UK Glacier Mint 20mg/mL (4pack)
A1462: Type | B1462: Ref. Nbr. | C1462: Operation | D1462: Order Status | E1462: Order Number | F1462: Customer ID | G1462: Customer Name | H1462: Warehouse | I1462: UOM | J1462: Order Qty. | K1462: Shipped Qty.
A1463: BO | B1463: SH03-00008144 | C1463: Issue | D1463: Completed | E1463: SO03-00008189 | F1463: 03-00000067 | G1463: LUCID JUICES VAPE STORE | H1463: ARVATO-BI | I1463: EA | J1463: 8 | K1463: 8
A1464: BO | B1464: SH03-00008145 | C1464: Issue | D1464: Completed | E1464: SO03-00008190 | F1464: 03-00000068 | G1464: VAPERS BOX LTD | H1464: ARVATO-BI | I1464: EA | J1464: 32 | K1464: 32
A1465: BO | B1465: SH03-00008146 | C1465: Issue | D1465: Completed | E1465: SO03-00008191 | F1465: 03-00000009 | G1465: House of Vapes | H1465: ARVATO-BI | I1465: EA | J1465: 288 | K1465: 288
A1466: BO | B1466: SH03-00008643 | C1466: Issue | D1466: Completed | E1466: SO03-00008685 | F1466: 03-00000017 | G1466: James J Fox | H1466: ARVATO-BI | I1466: EA | J1466: 320 | K1466: 320
A1467: BO | B1467: SH03-00008644 | C1467: Issue | D1467: Completed | E1467: SO03-00008686 | F1467: 03-00000038 | G1467: Vapourcore | H1467: ARVATO-BI | I1467: EA | J1467: 192 | K1467: 192
A1468: BO | B1468: SH03-00008645 | C1468: Issue | D1468: Completed | E1468: SO03-00008687 | F1468: 03-00000013 | G1468: Evapo Ltd | H1468: ARVATO-BI | I1468: EA | J1468: 480 | K1468: 480
A1469: BO | B1469: SH03-00008646 | C1469: Issue | D1469: Completed | E1469: SO03-00008688 | F1469: 03-00000036 | G1469: primary keys ltd | H1469: ARVATO-BI | I1469: EA | J1469: 16 | K1469: 16
A1470: BO | B1470: SH03-00008647 | C1470: Issue | D1470: Completed | E1470: SO03-00008689 | F1470: 03-00000011 | G1470: The London Vape Co | H1470: ARVATO-BI | I1470: EA | J1470: 48 | K1470: 48
A1471: BO | B1471: SH03-00008648 | C1471: Issue | D1471: Completed | E1471: SO03-00008690 | F1471: 03-00000069 | G1471: Venpa Services UK Ltd. T/A Vape Palace | H1471: ARVATO-BI | I1471: EA | J1471: 32 | K1471: 32
A1472: BO | B1472: SH03-00008901 | C1472: Issue | D1472: Completed | E1472: SO03-00008943 | F1472: 03-00000029 | G1472: Hasumati UK Limited | H1472: ARVATO-BI | I1472: EA | J1472: 8 | K1472: 8
A1473: BO | B1473: SH03-00008906 | C1473: Issue | D1473: Back Order | E1473: SO03-00008944 | F1473: 03-00000070 | G1473: Juice Sauz Ltd | H1473: ARVATO-BI | I1473: EA | J1473: 48 | K1473: 48
A1474: BO | B1474: SH03-00008908 | C1474: Issue | D1474: Completed | E1474: SO03-00008950 | F1474: 03-00000071 | G1474: Flamenco Ninja LTD | H1474: ARVATO-BI | I1474: EA | J1474: 8 | K1474: 8
... A1882: SO | B1882: SH03-00008891 | C1882: Issue | D1882: Completed | E1882: SO03-00008925 | F1882: 03-00000016 | G1882: JUUL UK B2C | H1882: ARVATO-BI | I1882: EA | J1882: 2 | K1882: 2
I1883: Total: | J1883: 14806 | K1883: 14806
...

Sheet Item Master
A1: Title: | B1: Katie - Item Record
A2: Company: | B2: Juul
A3: Date: | B3: 18 Oct 2018 10:15 AM GMT-08:00
C4: Manual Imput
A5: Item Code | B5: Status | C5: Clasification | D5: Inv Type | E5: Description | F5: Item Class | G5: Item Type | H5: Kit? | I5: Valuation Method | J5: Tax Category | K5: Post Class ID | L5: Lot / Serial Class | M5: Inventory Account | N5: Inventory Sub | O5: Expense Account | P5: Expense Sub | Q5: Sales Account | R5: Sales Sub ID | S5: PO Accrual Account | T5: PO Accrual Sub | U5: PPV Account | V5: PPV Sub ID | W5: Landed Cost V Account | X5: Landed Cost V Sub
A6: 1883 | B6: Active | C6: FG | D6: RK | E6: JUUL pod Tobacco 0% 2.8ml 4-pack | F6: J1C | G6: Finished Good | H6: False | I6: FIFO | J6: TAXABLE | K6: JUL | L6: LOTCONTROL | M6: 141000 | N6: HCORP-CRP-6000-JUL | O6: 511000 | P6: HCORP-CRP-4100-JUL | Q6: 410000 | R6: HCORP-CRP-4100-JUL | S6: 200100 | T6: HCORP-CRP-4100-JUL | U6: 514000 | V6: HCORP-CRP-4100-JUL | W6: 513000 | X6: HCORP-CRP-4600-CRP
A7: 35411 | B7: Active | C7: RM | D7: Pkg | E7: Bemis Top Lid | F7: INV ITEM | G7: Finished Good | H7: False | I7: FIFO | J7: TAXABLE | K7: CORP | L7: NOTTRACKED | M7: 140100 | N7: HCORP-CRP-6000-CRP | O7: 511000 | P7: HCORP-CRP-4100-CRP | Q7: 410000 | R7: HCORP-CRP-4100-CRP | S7: 200100 | T7: HCORP-CRP-4100-CRP | U7: 514000 | V7: HCORP-CRP-4600-JUL
A8: 175-00014 | B8: Active | C8: RM | D8: PCB | E8: J1 Flex PCB | F8: COMPONENTS | G8: Component Part | H8: False | I8: FIFO | J8: TAXABLE | K8: JUUL COM | L8: NOTTRACKED | M8: 143000 | N8: HCORP-CRP-6000-JUL | O8: 143000 | P8: HCORP-CRP-4100-JUL | Q8: 143000 | R8: HCORP-CRP-6000-JUL | S8: 200100 | T8: HCORP-CRP-6000-JUL | U8: 514000 | V8: HCORP-CRP-6000-JUL | W8: 514000 | X8: HCORP-CRP-6000-JUL
A9: 190-00001 | B9: Active | C9: RM | D9: Sensor | E9: Pressure Sensor_P/N TNM-15XXP-12-R | F9: COMPONENTS | G9: Component Part | H9: False | I9: FIFO | J9: TAXABLE | K9: JUUL COM | L9: NOTTRACKED | M9: 140100 | N9: HCORP-CRP-6000-JUL | O9: 140100 | P9: HCORP-CRP-4100-JUL | Q9: 140100 | R9: HCORP-CRP-6000-JUL | S9: 200100 | T9: HCORP-CRP-6000-JUL | U9: 140100 | V9: HCORP-CRP-6000-JUL | W9: 140100 | X9: HCORP-CRP-6000-JUL
A10: 190-00004 | B10: Active | C10: RM | D10: Sensor | E10: Pressure Sensor_MS583702BA01-50 | F10: COMPONENTS | G10: Component Part | H10: False | I10: FIFO | J10: TAXABLE | K10: JUUL COM | L10: NOTTRACKED | M10: 140100 | N10: HCORP-CRP-6000-JUL | O10: 143000 | P10: HCORP-CRP-4100-JUL | Q10: 143000 | R10: HCORP-CRP-6000-JUL | S10: 200100 | T10: HCORP-CRP-6000-JUL | U10: 514000 | V10: HCORP-CRP-6000-JUL | W10: 514000 | X10: HCORP-CRP-6000-JUL
A11: 310-00010 | B11: Active | C11: RM | D11: Coil | E11: Raw Material - Pod Coil | F11: COMPONENTS | G11: Component Part | H11: False | I11: FIFO | J11: TAXABLE | K11: JUUL COM | L11: NOTTRACKED | M11: 140100 | N11: HCORP-CRP-6000-JUL | O11: 511000 | P11: HCORP-CRP-4100-JUL | Q11: 410000 | R11: HCORP-CRP-4100-JUL | S11: 200100 | T11: HCORP-CRP-6000-JUL | U11: 514000 | V11: HCORP-CRP-6000-JUL
A12: 32901-15 | B12: Active | C12: RM | D12: Sensor | E12: Bemis Bottom Forming Plastic 15 mil | F12: INV ITEM | G12: Finished Good | H12: False | I12: FIFO | J12: TAXABLE | K12: CORP | L12: NOTTRACKED | M12: 140100 | N12: HCORP-CRP-6000-CRP | O12: 511000 | P12: HCORP-CRP-4100-CRP | Q12: 410000 | R12: HCORP-CRP-4100-CRP | S12: 200100 | T12: HCORP-CRP-4100-CRP | U12: 514000 | V12: HCORP-CRP-4600-JUL
A13: 345-00001-001 | B13: Active | C13: RM | D13: Liquid | E13: PL2520267E-5G Cool Mint 5% | F13: INV ITEM | G13: Component Part | H13: False | I13: FIFO | J13: TAXABLE | K13: JUUL COM | L13: NOTTRACKED | M13: 140100 | N13: HCORP-CRP-6000-JUL | O13: 511000 | P13: HCORP-CRP-4100-JUL | Q13: 410000 | R13: HCORP-CRP-4100-JUL | S13: 200100 | T13: HCORP-CRP-4100-JUL | U13: 514000 | V13: HCORP-CRP-4600-JUL
A14: 345-00002-001 | B14: Active | C14: RM | D14: Liquid | E14: PL2520538E-5G Crème Brulee 5% | F14: INV ITEM | G14: Component Part | H14: False | I14: FIFO | J14: TAXABLE | K14: JUUL COM | L14: NOTTRACKED | M14: 140100 | N14: HCORP-CRP-6000-JUL | O14: 511000 | P14: HCORP-CRP-4100-JUL | Q14: 410000 | R14: HCORP-CRP-4100-JUL | S14: 200100 | T14: HCORP-CRP-4100-JUL | U14: 514000 | V14: HCORP-CRP-4600-JUL
A15: 345-00003-001 | B15: Active | C15: RM | D15: Liquid | E15: PL2520543E-5G Fruit Medley 5% | F15: INV ITEM | G15: Finished Good | H15: False | I15: FIFO | J15: TAXABLE | K15: CORP | L15: NOTTRACKED | M15: 140100 | N15: HCORP-CRP-6000-CRP | O15: 511000 | P15: HCORP-CRP-4100-CRP | Q15: 410000 | R15: HCORP-CRP-4100-CRP | S15: 200100 | T15: HCORP-CRP-4100-CRP | U15: 514000 | V15: HCORP-CRP-4600-JUL
A16: 345-00004-001 | B16: Active | C16: RM | D16: Liquid | E16: PL2520542E-5G Virginia Tobacco 5% | F16: INV ITEM | G16: Component Part | H16: False | I16: FIFO | J16: TAXABLE | K16: JUUL COM | L16: NOTTRACKED | M16: 140100 | N16: HCORP-CRP-6000-JUL | O16: 511000 | P16: HCORP-CRP-4100-JUL | Q16: 410000 | R16: HCORP-CRP-4100-JUL | S16: 200100 | T16: HCORP-CRP-4100-JUL | U16: 514000 | V16: HCORP-CRP-4600-JUL
A17: 345-00005-001 | B17: Active | C17: RM | D17: Liquid | E17: PL2520357E-5G Mango 5% | F17: INV ITEM | G17: Component Part | H17: False | I17: FIFO | J17: TAXABLE | K17: JUUL COM | L17: NOTTRACKED | M17: 140100 | N17: HCORP-CRP-6000-JUL | O17: 511000 | P17: HCORP-CRP-4100-JUL | Q17: 410000 | R17: HCORP-CRP-4100-JUL | S17: 200100 | T17: HCORP-CRP-4600-JUL | U17: 514000 | V17: HCORP-CRP-4600-JUL
A18: 345-00006-001 | B18: Active | C18: RM | D18: Liquid | E18: Classic Tobacco 5% | F18: INV ITEM | G18: Finished Good | H18: False | I18: FIFO | J18: EXEMPT | K18: NSK ITEMS | L18: NOTTRACKED | M18: 140100 | N18: HCORP-CRP-6000-JUL | O18: 140100 | P18: HCORP-CRP-6000-JUL | Q18: 140100 | R18: HCORP-CRP-6000-JUL | S18: 200100 | T18: HCORP-CRP-6000-JUL | U18: 140100 | V18: HCORP-CRP-6000-JUL | W18: 513000 | X18: HCORP-CRP-5100-CRP
A19: 345-00007-001 | B19: Active | C19: RM | D19: Liquid | E19: Classic Menthol 5% | F19: INV ITEM | G19: Finished Good | H19: False | I19: FIFO | J19: EXEMPT | K19: NSK ITEMS | L19: NOTTRACKED | M19: 140100 | N19: HCORP-CRP-6000-JUL | O19: 140100 | P19: HCORP-CRP-6000-JUL | Q19: 140100 | R19: HCORP-CRP-6000-JUL | S19: 200100 | T19: HCORP-CRP-6000-JUL | U19: 140100 | V19: HCORP-CRP-6000-JUL | W19: 513000 | X19: HCORP-CRP-5100-CRP
A20: 345-00008-001 | B20: Active | C20: RM | D20: Liquid | E20: Lemon Tart (Poppyseed) 5% | F20: INV ITEM | G20: Finished Good | H20: False | I20: FIFO | J20: EXEMPT | K20: NSK ITEMS | L20: NOTTRACKED | M20: 140100 | N20: HCORP-CRP-6000-JUL | O20: 140100 | P20: HCORP-CRP-6000-JUL | Q20: 140100 | R20: HCORP-CRP-6000-JUL | S20: 200100 | T20: HCORP-CRP-6000-JUL | U20: 140100 | V20: HCORP-CRP-6000-JUL | W20: 513000 | X20: HCORP-CRP-5100-CRP
A21: 345-00009-001 | B21: Active | C21: RM | D21: Liquid | E21: E-LIQUID, MIMOSA, 5.0% | F21: INV ITEM | G21: Component Part | H21: False | I21: FIFO | J21: TAXABLE | K21: CORP | L21: NOTTRACKED | M21: 140100 | N21: HCORP-CRP-6000-JUL | O21: 143000 | P21: HCORP-CRP-6000-JUL | Q21: 143000 | R21: HCORP-CRP-6000-JUL | S21: 200100 | T21: HCORP-CRP-6000-JUL | U21: 514000 | V21: HCORP-CRP-4600-JUL
A22: 345-00010-001 | B22: Active | C22: RM | D22: Liquid | E22: PL2620375E-5G Cool Cucumber 5% | F22: INV ITEM | G22: Finished Good | H22: False | I22: FIFO | J22: TAXABLE | K22: CORP | L22: NOTTRACKED | M22: 140100 | N22: HCORP-CRP-6000-CRP | O22: 511000 | P22: HCORP-CRP-4100-CRP | Q22: 410000 | R22: HCORP-CRP-4100-CRP | S22: 200100 | T22: HCORP-CRP-4100-CRP | U22: 514000 | V22: HCORP-CRP-4600-JUL
A23: 345-00016-001 | B23: Active | C23: RM | D23: Liquid | E23: Creme Brulee 3% E-Liquid PL2521394E | F23: INV ITEM | G23: Finished Good | H23: False | I23: FIFO | J23: EXEMPT | K23: NSK ITEMS | L23: NOTTRACKED | M23: 140100 | N23: HCORP-CRP-6000-JUL | O23: 140100 | P23: HCORP-CRP-6000-JUL | Q23: 140100 | R23: HCORP-CRP-6000-JUL | S23: 200100 | T23: HCORP-CRP-6000-JUL | U23: 140100 | V23: HCORP-CRP-6000-JUL | W23: 513000 | X23: HCORP-CRP-5100-CRP
A24: 345-00017-001 | B24: Active | C24: RM | D24: Liquid | E24: Fruit Medley 3% E-Liquid PL2521391E | F24: INV ITEM | G24: Finished Good | H24: False | I24: FIFO | J24: EXEMPT | K24: NSK ITEMS | L24: NOTTRACKED | M24: 140100 | N24: HCORP-CRP-6000-JUL | O24: 140100 | P24: HCORP-CRP-6000-JUL | Q24: 140100 | R24: HCORP-CRP-6000-JUL | S24: 200100 | T24: HCORP-CRP-6000-JUL | U24: 140100 | V24: HCORP-CRP-6000-JUL | W24: 513000 | X24: HCORP-CRP-5100-CRP
A25: 345-00018-001 | B25: Active | C25: RM | D25: Liquid | E25: E-LIQUID, COOL MINT, 3% | F25: INV ITEM | G25: Finished Good | H25: False | I25: FIFO | J25: TAXABLE | K25: CORP | L25: NOTTRACKED | M25: 140100 | N25: HCORP-CRP-6000-JUL | O25: 143000 | P25: HCORP-CRP-6000-JUL | Q25: 143000 | R25: HCORP-CRP-6000-JUL | S25: 200100 | T25: HCORP-CRP-6000-JUL | U25: 514000 | V25: HCORP-CRP-4600-JUL
A26: 345-00019-001 | B26: Active | C26: RM | D26: Liquid | E26: E-LIQUID, VIRGINIA TOBACCO, 3% | F26: INV ITEM | G26: Finished Good | H26: False | I26: FIFO | J26: TAXABLE | K26: CORP | L26: NOTTRACKED | M26: 140100 | N26: HCORP-CRP-6000-JUL | O26: 143000 | P26: HCORP-CRP-6000-JUL | Q26: 143000 | R26: HCORP-CRP-6000-JUL | S26: 200100 | T26: HCORP-CRP-6000-JUL | U26: 514000 | V26: HCORP-CRP-4600-JUL
A27: 345-00020-001 | B27: Active | C27: RM | D27: Liquid | E27: Mango 3% E-Liquid PL2520358E | F27: INV ITEM | G27: Finished Good | H27: False | I27: FIFO | J27: EXEMPT | K27: NSK ITEMS | L27: NOTTRACKED | M27: 140100 | N27: HCORP-CRP-6000-JUL | O27: 140100 | P27: HCORP-CRP-6000-JUL | Q27: 140100 | R27: HCORP-CRP-6000-JUL | S27: 200100 | T27: HCORP-CRP-6000-JUL | U27: 140100 | V27: HCORP-CRP-6000-JUL | W27: 513000 | X27: HCORP-CRP-5100-CRP
A28: 345-00026 | B28: Active | C28: RM | D28: Liquid | E28: E-LIQUID, Apple Cran, 5.0% | F28: INV ITEM | G28: Component Part | H28: False | I28: FIFO | J28: TAXABLE | K28: CORP | L28: NOTTRACKED | M28: 140100 | N28: HCORP-CRP-6000-JUL | O28: 143000 | P28: HCORP-CRP-6000-JUL | Q28: 143000 | R28: HCORP-CRP-6000-JUL | S28: 200100 | T28: HCORP-CRP-6000-JUL | U28: 514000 | V28: HCORP-CRP-4600-JUL
A29: 345-00027 | B29: Active | C29: RM | D29: Liquid | E29: E-LIQUID, APPLE CRUMBLE, 5.0% | F29: INV ITEM | G29: Component Part | H29: False | I29: FIFO | J29: TAXABLE | K29: CORP | L29: NOTTRACKED | M29: 140100 | N29: HCORP-CRP-6000-JUL | O29: 143000 | P29: HCORP-CRP-6000-JUL | Q29: 143000 | R29: HCORP-CRP-6000-JUL | S29: 200100 | T29: HCORP-CRP-6000-JUL | U29: 514000 | V29: HCORP-CRP-4600-JUL
A30: 345-00028 | B30: Active | C30: RM | D30: Liquid | E30: TOBACCO MINT 5% E-LIQUID | F30: INV ITEM | G30: Component Part | H30: False | I30: FIFO | J30: TAXABLE | K30: CORP | L30: NOTTRACKED | M30: 140100 | N30: HCORP-CRP-6000-JUL | O30: 143000 | P30: HCORP-CRP-6000-JUL | Q30: 143000 | R30: HCORP-CRP-6000-JUL | S30: 200100 | T30: HCORP-CRP-6000-JUL | U30: 514000 | V30: HCORP-CRP-4600-JUL
A31: 345-00029 | B31: Active | C31: RM | D31: Liquid | E31: Tobacco Mango 5% E-LIQUID | F31: INV ITEM | G31: Component Part | H31: False | I31: FIFO | J31: TAXABLE | K31: CORP | L31: NOTTRACKED | M31: 140100 | N31: HCORP-CRP-6000-JUL | O31: 143000 | P31: HCORP-CRP-6000-JUL | Q31: 143000 | R31: HCORP-CRP-6000-JUL | S31: 200100 | T31: HCORP-CRP-6000-JUL | U31: 514000 | V31: HCORP-CRP-4600-JUL
A32: 345-00030 | B32: Active | C32: RM | D32: Liquid | E32: Tobacco COOKIE & CREAM 5% E-LIQUID | F32: INV ITEM | G32: Component Part | H32: False | I32: FIFO | J32: TAXABLE | K32: CORP | L32: NOTTRACKED | M32: 140100 | N32: HCORP-CRP-6000-JUL | O32: 143000 | P32: HCORP-CRP-6000-JUL | Q32: 143000 | R32: HCORP-CRP-6000-JUL | S32: 200100 | T32: HCORP-CRP-6000-JUL | U32: 514000 | V32: HCORP-CRP-4600-JUL
A33: 345-00031 | B33: Active | C33: RM | D33: Liquid | E33: Tobacco GREEN APPLE 5% E-LIQUID | F33: INV ITEM | G33: Component Part | H33: False | I33: FIFO | J33: TAXABLE | K33: CORP | L33: NOTTRACKED | M33: 140100 | N33: HCORP-CRP-6000-JUL | O33: 143000 | P33: HCORP-CRP-6000-JUL | Q33: 143000 | R33: HCORP-CRP-6000-JUL | S33: 200100 | T33: HCORP-CRP-6000-JUL | U33: 514000 | V33: HCORP-CRP-4600-JUL
A34: 345-00032 | B34: Active | C34: RM | D34: Liquid | E34: TOBACCO STRAWBERRY 5% E-LIQUID | F34: INV ITEM | G34: Component Part | H34: False | I34: FIFO | J34: TAXABLE | K34: CORP | L34: NOTTRACKED | M34: 140100 | N34: HCORP-CRP-6000-JUL | O34: 143000 | P34: HCORP-CRP-6000-JUL | Q34: 143000 | R34: HCORP-CRP-6000-JUL | S34: 200100 | T34: HCORP-CRP-6000-JUL | U34: 514000 | V34: HCORP-CRP-4600-JUL
A35: 345-00033 | B35: Active | C35: RM | D35: Liquid | E35: E-LIQUID, GINGER PEACH, 5.0% | F35: INV ITEM | G35: Component Part | H35: False | I35: FIFO | J35: TAXABLE | K35: CORP | L35: NOTTRACKED | M35: 140100 | N35: HCORP-CRP-6000-JUL | O35: 143000 | P35: HCORP-CRP-6000-JUL | Q35: 143000 | R35: HCORP-CRP-6000-JUL | S35: 200100 | T35: HCORP-CRP-6000-JUL | U35: 514000 | V35: HCORP-CRP-4600-JUL
A36: 345-00034 | B36: Active | C36: RM | D36: Liquid | E36: E-LIQUID, LEMON TEA, 5.0% | F36: INV ITEM | G36: Component Part | H36: False | I36: FIFO | J36: TAXABLE | K36: CORP | L36: NOTTRACKED | M36: 140100 | N36: HCORP-CRP-6000-JUL | O36: 143000 | P36: HCORP-CRP-6000-JUL | Q36: 143000 | R36: HCORP-CRP-6000-JUL | S36: 200100 | T36: HCORP-CRP-6000-JUL | U36: 514000 | V36: HCORP-CRP-4600-JUL
A37: 345-00035 | B37: Active | C37: RM | D37: Liquid | E37: E-LIQUID, SPICY WATERMELON, 5.0% | F37: INV ITEM | G37: Component Part | H37: False | I37: FIFO | J37: TAXABLE | K37: CORP | L37: NOTTRACKED | M37: 140100 | N37: HCORP-CRP-6000-JUL | O37: 143000 | P37: HCORP-CRP-6000-JUL | Q37: 143000 | R37: HCORP-CRP-6000-JUL | S37: 200100 | T37: HCORP-CRP-6000-JUL | U37: 514000 | V37: HCORP-CRP-4600-JUL
A38: 345-00036 | B38: Active | C38: RM | D38: Liquid | E38: E-LIQUID, Orange Twist (Old Fashioned), 5.0% | F38: INV ITEM | G38: Component Part | H38: False | I38: FIFO | J38: TAXABLE | K38: CORP | L38: NOTTRACKED | M38: 141000 | N38: HCORP-CRP-6000-CRP | O38: 511000 | P38: HCORP-CRP-4100-CRP | Q38: 410000 | R38: HCORP-CRP-4100-CRP | S38: 200100 | T38: HCORP-CRP-4100-CRP
A39: 345-00037 | B39: Active | C39: RM | D39: Liquid | E39: E-LIQUID, CINNAMON SPICE (CINNAMON SNAP), 5.0% | F39: INV ITEM | G39: Component Part | H39: False | I39: FIFO | J39: TAXABLE | K39: CORP | L39: NOTTRACKED | M39: 140100 | N39: HCORP-CRP-6000-JUL | O39: 143000 | P39: HCORP-CRP-6000-JUL | Q39: 143000 | R39: HCORP-CRP-6000-JUL | S39: 200100 | T39: HCORP-CRP-6000-JUL | U39: 514000 | V39: HCORP-CRP-4600-JUL
A40: 345-00038 | B40: Active | C40: RM | D40: Liquid | E40: E-LIQUID, CHAMOMILE TEA, 5.0% | F40: INV ITEM | G40: Component Part | H40: False | I40: FIFO | J40: TAXABLE | K40: CORP | L40: NOTTRACKED | M40: 140100 | N40: HCORP-CRP-6000-JUL | O40: 143000 | P40: HCORP-CRP-6000-JUL | Q40: 143000 | R40: HCORP-CRP-6000-JUL | S40: 200100 | T40: HCORP-CRP-6000-JUL | U40: 514000 | V40: HCORP-CRP-4600-JUL
A41: 345-00039 | B41: Active | C41: RM | D41: Liquid | E41: E-LIQUID, THAI TEA, 5.0% | F41: INV ITEM | G41: Component Part | H41: False | I41: FIFO | J41: TAXABLE | K41: CORP | L41: NOTTRACKED | M41: 140100 | N41: HCORP-CRP-6000-JUL | O41: 143000 | P41: HCORP-CRP-6000-JUL | Q41: 143000 | R41: HCORP-CRP-6000-JUL | S41: 200100 | T41: HCORP-CRP-6000-JUL | U41: 514000 | V41: HCORP-CRP-4600-JUL
A42: 345-00041 | B42: Active | C42: RM | D42: Liquid | E42: E-LIQUID, GUAVA LYCHEE, 5.0% | F42: INV ITEM | G42: Component Part | H42: False | I42: FIFO | J42: TAXABLE | K42: CORP | L42: NOTTRACKED | M42: 140100 | N42: HCORP-CRP-6000-JUL | O42: 143000 | P42: HCORP-CRP-6000-JUL | Q42: 143000 | R42: HCORP-CRP-6000-JUL | S42: 200100 | T42: HCORP-CRP-6000-JUL | U42: 514000 | V42: HCORP-CRP-4600-JUL
A43: 345-00042 | B43: Active | C43: RM | D43: Liquid | E43: E-LIQUID, UK GOLDEN TOBACCO, 20mg/mL | F43: INV ITEM | G43: Component Part | H43: False | I43: FIFO | J43: TAXABLE | K43: CORP | L43: NOTTRACKED | M43: 140100 | N43: HCORP-CRP-6000-JUL | O43: 143000 | P43: HCORP-CRP-6000-JUL | Q43: 143000 | R43: HCORP-CRP-6000-JUL | S43: 200100 | T43: HCORP-CRP-6000-JUL | U43: 514000 | V43: HCORP-CRP-4600-JUL
A44: 345-00043 | B44: Active | C44: RM | D44: Liquid | E44: E-LIQUID, UK GLACIER MINT,20mg/mL | F44: INV ITEM | G44: Component Part | H44: False | I44: FIFO | J44: TAXABLE | K44: CORP | L44: NOTTRACKED | M44: 140100 | N44: HCORP-CRP-6000-JUL | O44: 143000 | P44: HCORP-CRP-6000-JUL | Q44: 143000 | R44: HCORP-CRP-6000-JUL | S44: 200100 | T44: HCORP-CRP-6000-JUL | U44: 514000 | V44: HCORP-CRP-4600-JUL
A45: 345-00044 | B45: Active | C45: RM | D45: Liquid | E45: E-LIQUID, UK MANGO NECTAR, 20mg/mL | F45: INV ITEM | G45: Component Part | H45: False | I45: FIFO | J45: TAXABLE | K45: CORP | L45: NOTTRACKED | M45: 140100 | N45: HCORP-CRP-6000-JUL | O45: 143000 | P45: HCORP-CRP-6000-JUL | Q45: 143000 | R45: HCORP-CRP-6000-JUL | S45: 200100 | T45: HCORP-CRP-6000-JUL | U45: 514000 | V45: HCORP-CRP-4600-JUL
A46: 345-00045 | B46: Active | C46: RM | D46: Liquid | E46: E-LIQUID, UK ROYAL CRÈME, 20mg/mL | F46: INV ITEM | G46: Component Part | H46: False | I46: FIFO | J46: TAXABLE | K46: CORP | L46: NOTTRACKED | M46: 140100 | N46: HCORP-CRP-6000-JUL | O46: 143000 | P46: HCORP-CRP-6000-JUL | Q46: 143000 | R46: HCORP-CRP-6000-JUL | S46: 200100 | T46: HCORP-CRP-6000-JUL | U46: 514000 | V46: HCORP-CRP-4600-JUL
A47: 345-00046 | B47: Active | C47: RM | D47: Liquid | E47: E-LIQUID, UK APPLE ORCHARD,20mg/mL | F47: INV ITEM | G47: Component Part | H47: False | I47: FIFO | J47: TAXABLE | K47: CORP | L47: NOTTRACKED | M47: 140100 | N47: HCORP-CRP-6000-JUL | O47: 143000 | P47: HCORP-CRP-6000-JUL | Q47: 143000 | R47: HCORP-CRP-6000-JUL | S47: 200100 | T47: HCORP-CRP-6000-JUL | U47: 514000 | V47: HCORP-CRP-4600-JUL
A48: 345-00048 | B48: Active | C48: RM | D48: Liquid | E48: E-LIQUID, Mixed Berry, 5% | F48: INV ITEM | G48: Component Part | H48: False | I48: FIFO | J48: TAXABLE | K48: CORP | L48: NOTTRACKED | M48: 140100 | N48: HCORP-CRP-6000-JUL | O48: 143000 | P48: HCORP-CRP-6000-JUL | Q48: 143000 | R48: HCORP-CRP-6000-JUL | S48: 200100 | T48: HCORP-CRP-6000-JUL | U48: 514000 | V48: HCORP-CRP-4600-JUL
A49: 345-00049 | B49: Active | C49: RM | D49: Liquid | E49: E-LIQUID, Coco Mint, 5% | F49: INV ITEM | G49: Component Part | H49: False | I49: FIFO | J49: TAXABLE | K49: CORP | L49: NOTTRACKED | M49: 140100 | N49: HCORP-CRP-6000-JUL | O49: 143000 | P49: HCORP-CRP-6000-JUL | Q49: 143000 | R49: HCORP-CRP-6000-JUL | S49: 200100 | T49: HCORP-CRP-6000-JUL | U49: 514000 | V49: HCORP-CRP-4600-JUL
A50: 345-00050 | B50: Active | C50: RM | D50: Liquid | E50: E-LIQUID, PEAR TART, 5% | F50: INV ITEM | G50: Component Part | H50: False | I50: FIFO | J50: TAXABLE | K50: CORP | L50: NOTTRACKED | M50: 140100 | N50: HCORP-CRP-6000-JUL | O50: 143000 | P50: HCORP-CRP-6000-JUL | Q50: 143000 | R50: HCORP-CRP-6000-JUL | S50: 200100 | T50: HCORP-CRP-6000-JUL | U50: 514000 | V50: HCORP-CRP-4600-JUL
... A72: 455-00301 | B72: Active | C72: RM | D72: Pkg | E72: 5 Sided Sleeve | F72: INV ITEM | G72: Component Part | H72: False | I72: FIFO | J72: TAXABLE | K72: CORP | L72: NOTTRACKED | M72: 140100 | N72: HCORP-CRP-6000-JUL | O72: 511000 | P72: HCORP-CRP-6000-JUL | Q72: 410000 | R72: HCORP-CRP-4100-JUL | S72: 200100 | T72: HCORP-CRP-6000-JUL | U72: 514000 | V72: HCORP-CRP-4600-JUL
A73: C1-BLK | B73: Inactive | C73: Inactive | D73: Inactive | E73: Pax - Black | F73: P1D | G73: Finished Good | H73: False | I73: FIFO | J73: TAXABLE | K73: PAX | L73: NOTTRACKED | M73: 141000 | N73: HCORP-CRP-4100-PAX | O73: 511000 | P73: HCORP-CRP-4100-PAX | Q73: 410000 | R73: HCORP-CRP-4100-PAX | S73: 200100 | T73: HCORP-CRP-4100-PAX | U73: 514000
A74: C1-BLU | B74: Active | C74: Inactive | D74: Inactive | E74: Pax - Blue | F74: P1D | G74: Finished Good | H74: False | I74: FIFO | J74: TAXABLE | K74: PAX | L74: NOTTRACKED | M74: 141000 | N74: HCORP-CRP-4100-PAX | O74: 511000 | P74: HCORP-CRP-4100-PAX | Q74: 410000 | R74: HCORP-CRP-4100-PAX | S74: 200100 | T74: HCORP-CRP-4100-PAX | W74: 513000 | X74: HCORP-CRP-4600-CRP
A75: C1-GRN | B75: Active | C75: Inactive | D75: Inactive | E75: Pax - Green | F75: P1D | G75: Finished Good | H75: False | I75: FIFO | J75: TAXABLE | K75: PAX | L75: NOTTRACKED | M75: 141000 | N75: HCORP-CRP-4100-PAX | O75: 511000 | P75: HCORP-CRP-4100-PAX | Q75: 410000 | R75: HCORP-CRP-4100-PAX | S75: 200100 | T75: HCORP-CRP-4100-PAX | W75: 513000 | X75: HCORP-CRP-4600-CRP
A76: C1-J02 | B76: Active | C76: Inactive | D76: Inactive | E76: Pax - Packaged Cleaning Kit - Not in Use | F76: P1A | G76: Finished Good | H76: False | I76: FIFO | J76: TAXABLE | K76: PAX | L76: NOTTRACKED | M76: 141000 | N76: HCORP-CRP-4100-PAX | O76: 511000 | P76: HCORP-CRP-4100-PAX | Q76: 410000 | R76: HCORP-CRP-4100-PAX | S76: 200100 | T76: HCORP-CRP-4100-PAX | W76: 513000 | X76: HCORP-CRP-4600-CRP
A77: C1-J04 | B77: Active | C77: Inactive | D77: Inactive | E77: Pax - 3 Screens | F77: P1A | G77: Finished Good | H77: False | I77: FIFO | J77: TAXABLE | K77: PAX | L77: NOTTRACKED | M77: 141000 | N77: HCORP-CRP-4100-PAX | O77: 511000 | P77: HCORP-CRP-4100-PAX | Q77: 410000 | R77: HCORP-CRP-4100-PAX | S77: 200100 | T77: HCORP-CRP-4100-PAX | W77: 513000 | X77: HCORP-CRP-4600-CRP
A78: C1-J05 | B78: Active | C78: Inactive | D78: Inactive | E78: Pax - Mouthpiece | F78: P1A | G78: Finished Good | H78: False | I78: FIFO | J78: TAXABLE | K78: PAX | L78: NOTTRACKED | M78: 141000 | N78: HCORP-CRP-4100-PAX | O78: 511000 | P78: HCORP-CRP-4100-PAX | Q78: 410000 | R78: HCORP-CRP-4100-PAX | S78: 200100 | T78: HCORP-CRP-4100-PAX | W78: 513000 | X78: HCORP-CRP-4600-CRP
A79: C1-J07 | B79: Active | C79: Inactive | D79: Inactive | E79: Pax - Charging Dock | F79: P1A | G79: Finished Good | H79: False | I79: FIFO | J79: TAXABLE | K79: PAX | L79: NOTTRACKED | M79: 141000 | N79: HCORP-CRP-4100-PAX | O79: 511000 | P79: HCORP-CRP-4100-PAX | Q79: 410000 | R79: HCORP-CRP-4100-PAX | S79: 200100 | T79: HCORP-CRP-4100-PAX | W79: 513000 | X79: HCORP-CRP-4600-CRP
A80: C1-J09 | B80: Active | C80: Inactive | D80: Inactive | E80: Pax - 1 Lubricant Packet | F80: P1A | G80: Finished Good | H80: False | I80: FIFO | J80: TAXABLE | K80: PAX | L80: NOTTRACKED | M80: 141000 | N80: HCORP-CRP-4100-PAX | O80: 511000 | P80: HCORP-CRP-4100-PAX | Q80: 410000 | R80: HCORP-CRP-4100-PAX | S80: 200100 | T80: HCORP-CRP-4100-PAX | W80: 513000 | X80: HCORP-CRP-4600-CRP
A81: C1-J10 | B81: Active | C81: Inactive | D81: Inactive | E81: Pax - 5 Lubricant Packets | F81: P1A | G81: Finished Good | H81: False | I81: FIFO | J81: TAXABLE | K81: PAX | L81: NOTTRACKED | M81: 141000 | N81: HCORP-CRP-4100-PAX | O81: 511000 | P81: HCORP-CRP-4100-PAX | Q81: 410000 | R81: HCORP-CRP-4100-PAX | S81: 200100 | T81: HCORP-CRP-4100-PAX | W81: 513000 | X81: HCORP-CRP-4600-CRP
A82: C1-J11 | B82: Active | C82: Inactive | D82: Inactive | E82: Pax - Carrying Case | F82: P1A | G82: Finished Good | H82: False | I82: FIFO | J82: TAXABLE | K82: PAX | L82: NOTTRACKED | M82: 141000 | N82: HCORP-CRP-4100-PAX | O82: 511000 | P82: HCORP-CRP-4100-PAX | Q82: 410000 | R82: HCORP-CRP-4100-PAX | S82: 200100 | T82: HCORP-CRP-4100-PAX | W82: 513000 | X82: HCORP-CRP-4600-CRP
A83: C1-J12 | B83: Active | C83: Inactive | D83: Inactive | E83: Pax - Large Cleaning Kit | F83: P1A | G83: Finished Good | H83: False | I83: FIFO | J83: TAXABLE | K83: PAX | L83: NOTTRACKED | M83: 141000 | N83: HCORP-CRP-4100-PAX | O83: 511000 | P83: HCORP-CRP-4100-PAX | Q83: 410000 | R83: HCORP-CRP-4100-PAX | S83: 200100 | T83: HCORP-CRP-4100-PAX | W83: 513000 | X83: HCORP-CRP-4600-CRP
A84: C1-J13 | B84: Active | C84: Inactive | D84: Inactive | E84: Pax - Car Charger | F84: P1A | G84: Finished Good | H84: False | I84: FIFO | J84: TAXABLE | K84: PAX | L84: NOTTRACKED | M84: 141000 | N84: HCORP-CRP-4100-PAX | O84: 511000 | P84: HCORP-CRP-4100-PAX | Q84: 410000 | R84: HCORP-CRP-4100-PAX | S84: 200100 | T84: HCORP-CRP-4100-PAX | W84: 513000 | X84: HCORP-CRP-4600-CRP
A85: C1-J15 | B85: Active | C85: Inactive | D85: Inactive | E85: Pax - Bottled Lubricant | F85: P1A | G85: Finished Good | H85: False | I85: FIFO | J85: TAXABLE | K85: PAX | L85: NOTTRACKED | M85: 141000 | N85: HCORP-CRP-4100-PAX | O85: 511000 | P85: HCORP-CRP-4100-PAX | Q85: 410000 | R85: HCORP-CRP-4100-PAX | S85: 200100 | T85: HCORP-CRP-4100-PAX | W85: 513000 | X85: HCORP-CRP-4600-CRP
... A90: CARD DISPENSER | B90: Inactive | C90: Inactive | D90: Inactive | E90: Take Away Card Dispenser | F90: NSK ITEMS | G90: Finished Good | H90: False | I90: FIFO | J90: TAXABLE | K90: CORP | L90: NOTTRACKED | M90: 141000 | N90: HCORP-CRP-6000-CRP | O90: 511000 | P90: HCORP-CRP-4100-CRP | Q90: 410000 | R90: HCORP-CRP-4100-CRP | S90: 200100 | T90: HCORP-CRP-4100-CRP | W90: 513000 | X90: HCORP-CRP-4600-CRP
A91: COA-123100 | B91: Active | C91: Expense | D91: Expense | E91: Other Receivables | F91: COA ITEM | G91: Expense | H91: False | I91: Standard | J91: EXEMPT | K91: NSK ITEMS | M91: 123100 | N91: HCORP-CRP-6000-JUL | O91: 123100 | P91: HCORP-CRP-6000-JUL | S91: 200100 | T91: HCORP-CRP-6000-JUL
A92: COA-123200 | B92: Inactive | C92: Inactive | D92: Inactive | E92: VAT Receivable | F92: COA ITEM | G92: Expense | H92: False | I92: Standard | J92: EXEMPT | K92: NSK ITEMS | M92: 141000 | N92: HCORP-CRP-6000-CRP | O92: 123200 | P92: HCORP-CRP-3100-CRP | Q92: 410000 | R92: HCORP-CRP-4100-CRP | S92: 200100 | T92: HCORP-CRP-4100-CRP | U92: 514000 | V92: HCORP-CRP-5100-CRP
A93: COA-130100 | B93: Active | C93: Expense | D93: Expense | E93: Prepaid Sales & Marketing | F93: COA ITEM | G93: Expense | H93: False | I93: Standard | J93: EXEMPT | K93: NSK ITEMS | M93: 130100 | N93: HCORP-CRP-6000-JUL | O93: 130100 | P93: HCORP-CRP-6000-JUL | S93: 200100 | T93: HCORP-CRP-6000-JUL
A94: COA-130200 | B94: Active | C94: Expense | D94: Expense | E94: Prepaid Health Insurance | F94: COA ITEM | G94: Expense | H94: False | I94: Standard | J94: EXEMPT | K94: NSK ITEMS | M94: 130200 | N94: HCORP-CRP-6000-JUL | O94: 130200 | P94: HCORP-CRP-6000-JUL | S94: 200100 | T94: HCORP-CRP-4100-CRP
A95: COA-130300 | B95: Active | C95: Expense | D95: Expense | E95: Prepaid Business Insurance | F95: COA ITEM | G95: Expense | H95: False | I95: Standard | J95: EXEMPT | K95: NSK ITEMS | M95: 130300 | N95: HCORP-CRP-6000-JUL | O95: 130300 | P95: HCORP-CRP-6000-JUL | S95: 200100 | T95: HCORP-CRP-6000-JUL
A96: COA-130400 | B96: Active | C96: Expense | D96: Expense | E96: Prepaid HR | F96: COA ITEM | G96: Expense | H96: False | I96: Standard | J96: EXEMPT | K96: NSK ITEMS | M96: 141000 | N96: HCORP-CRP-6000-JUL | O96: 130400 | P96: HCORP-CRP-6000-JUL | S96: 200100 | T96: HCORP-CRP-6000-JUL
A97: COA-130500 | B97: Active | C97: Expense | D97: Expense | E97: Prepaid Software/Subscription | F97: COA ITEM | G97: Expense | H97: False | I97: Standard | J97: EXEMPT | K97: NSK ITEMS | M97: 141000 | N97: HCORP-CRP-6000-JUL | O97: 130500 | P97: HCORP-CRP-6000-JUL | S97: 200100 | T97: HCORP-CRP-6000-JUL
A98: COA-130550 | B98: Active | C98: Expense | D98: Expense | E98: Prepaid Legal | F98: COA ITEM | G98: Expense | H98: False | I98: Standard | J98: EXEMPT | K98: NSK ITEMS | M98: 141000 | N98: HCORP-CRP-6000-JUL | O98: 130550 | P98: HCORP-CRP-6000-JUL | S98: 200100 | T98: HCORP-CRP-6000-JUL
A99: COA-130600 | B99: Active | C99: Expense | D99: Expense | E99: Prepaid Other | F99: COA ITEM | G99: Expense | H99: False | I99: Standard | J99: EXEMPT | K99: NSK ITEMS | M99: 141000 | N99: HCORP-CRP-6000-JUL | O99: 130600 | P99: HCORP-CRP-6000-JUL | S99: 200100 | T99: HCORP-CRP-6000-JUL
A100: COA-130620 | B100: Active | C100: Expense | D100: Expense | E100: Prepaid Rent | F100: COA ITEM | G100: Expense | H100: False | I100: Standard | J100: EXEMPT | K100: NSK ITEMS | O100: 130620 | P100: HCORP-CRP-6000-JUL | S100: 200100 | T100: HCORP-CRP-6000-JUL
A101: COA-131100 | B101: Active | C101: Expense | D101: Expense | E101: Prepaid Trade Marketing Fixtures | F101: COA ITEM | G101: Expense | H101: False | I101: Standard | J101: EXEMPT | K101: NSK ITEMS | M101: 130110 | N101: NAUSA-STR-4100-JUL | O101: 130110 | P101: NAUSA-STR-4100-JUL | S101: 200100 | T101: NAUSA-STR-4100-JUL | U101: 514000 | V101: HCORP-CRP-6000-JUL
A102: COA-140100 | B102: Active | C102: Expense | D102: Expense | E102: Inventory - Raw Materials | F102: COA ITEM | G102: Expense | H102: False | I102: Standard | J102: EXEMPT | K102: NSK ITEMS | M102: 140100 | N102: HCORP-CRP-6000-JUL | O102: 140100 | P102: HCORP-CRP-6000-JUL | Q102: 410000 | R102: HCORP-CRP-4100-JUL | S102: 200100 | T102: HCORP-CRP-6000-JUL | U102: 514000 | V102: HCORP-CRP-4600-JUL
A103: COA-140100-USE | B103: Active | C103: Expense | D103: Expense | E103: Inventory - Raw Materials | F103: COA ITEM | G103: Expense | H103: False | I103: Standard | J103: EXEMPT | K103: NSK ITEMS | M103: 140100 | N103: HCORP-CRP-6000-JUL | O103: 140100 | P103: HCORP-CRP-6000-JUL | Q103: 410000 | R103: HCORP-CRP-4100-JUL | S103: 200100 | T103: HCORP-CRP-6000-JUL | U103: 514000 | V103: HCORP-CRP-4600-JUL
A104: COA-140200 | B104: Active | C104: Expense | D104: Expense | E104: Inventory - WIP | F104: COA ITEM | G104: Expense | H104: False | I104: Standard | J104: EXEMPT | K104: NSK ITEMS | M104: 140200 | N104: HCORP-CRP-6000-JUL | O104: 140200 | P104: HCORP-CRP-6000-JUL | Q104: 140200 | R104: HCORP-CRP-4100-JUL | S104: 200100 | T104: HCORP-CRP-6000-JUL | U104: 140200 | V104: HCORP-CRP-4600-JUL
A105: COA-150200 | B105: Active | C105: Expense | D105: Expense | E105: Tools, Machinery and Equipment | F105: COA ITEM | G105: Expense | H105: False | I105: Standard | J105: EXEMPT | K105: NSK ITEMS | M105: 141000 | N105: HCORP-CRP-6000-CRP | O105: 150200 | P105: HCORP-CRP-3200-CRP | Q105: 410000 | R105: HCORP-CRP-4100-CRP | S105: 200100 | T105: HCORP-CRP-4100-CRP | U105: 150200 | V105: HCORP-CRP-3200-CRP
A106: COA-150300 | B106: Active | C106: Expense | D106: Expense | E106: Computer HW and Equipment | F106: COA ITEM | G106: Expense | H106: False | I106: Standard | J106: EXEMPT | K106: NSK ITEMS | M106: 141000 | N106: HCORP-CRP-6000-CRP | O106: 150300 | P106: HCORP-CRP-3200-CRP | Q106: 410000 | R106: HCORP-CRP-4100-CRP | S106: 200100 | T106: HCORP-CRP-4100-CRP
A107: COA-151000 | B107: Active | C107: Expense | D107: Expense | E107: Capital in Progress (CIP) | F107: COA ITEM | G107: Expense | H107: False | I107: Standard | J107: EXEMPT | K107: NSK ITEMS | M107: 151000 | N107: HCORP-CRP-6000-JUL | O107: 151000 | P107: HCORP-CRP-6000-JUL | Q107: 410000 | R107: HCORP-CRP-4100-JUL | S107: 200100 | T107: HCORP-CRP-6000-JUL | U107: 151000 | V107: HCORP-CRP-6000-JUL
A108: COA-170100 | B108: Active | C108: Expense | D108: Expense | E108: Patents and Trademarks | F108: COA ITEM | G108: Expense | H108: False | I108: Standard | J108: EXEMPT | K108: NSK ITEMS | M108: 141000 | N108: HCORP-CRP-6000-CRP | O108: 170100 | P108: HCORP-CRP-3100-CRP | Q108: 410000 | R108: HCORP-CRP-4100-CRP | S108: 200100 | T108: HCORP-CRP-4100-CRP | U108: 170100 | V108: HCORP-CRP-3100-CRP
A109: COA-191000 | B109: Active | C109: Expense | D109: Expense | E109: Deposits - Long Term | F109: COA ITEM | G109: Expense | H109: False | I109: Standard | J109: EXEMPT | K109: NSK ITEMS | M109: 191000 | N109: HCORP-CRP-6200-CRP | O109: 191000 | P109: HCORP-CRP-6200-CRP | Q109: 410000 | R109: HCORP-CRP-5100-CRP | S109: 200100 | T109: HCORP-CRP-6200-CRP | U109: 514000 | V109: HCORP-CRP-6200-CRP
A110: COA-220300 | B110: Active | C110: Expense | D110: Expense | E110: Cost plus rebate | F110: COA ITEM | G110: Expense | H110: False | I110: Standard | J110: EXEMPT | K110: NSK ITEMS | M110: 141000 | N110: HCORP-CRP-6000-CRP | O110: 220300 | P110: HCORP-CRP-6300-CRP | Q110: 410000 | R110: HCORP-CRP-4100-CRP | S110: 200100 | T110: HCORP-CRP-4100-CRP | U110: 514000 | V110: HCORP-CRP-5100-CRP
A111: COA-220400 | B111: Active | C111: Expense | D111: Expense | E111: Accrued Customer Incentives | F111: COA ITEM | G111: Expense | H111: False | I111: Standard | J111: EXEMPT | K111: NSK ITEMS | M111: 220400 | N111: HCORP-STR-4100-JUL | O111: 220400 | P111: HCORP-STR-4100-JUL | Q111: 410000 | R111: HCORP-STR-4100-JUL | S111: 200100 | T111: HCORP-STR-4100-JUL | U111: 514000 | V111: HCORP-STR-4100-JUL
A112: COA-220950 | B112: Active | C112: Expense | D112: Expense | E112: Accrued Freight/Fulfillment | F112: COA ITEM | G112: Expense | H112: False | I112: Standard | J112: EXEMPT | K112: NSK ITEMS | M112: 220950 | N112: HCORP-CRP-6000-JUL | O112: 220950 | P112: HCORP-CRP-6000-JUL | Q112: 410000 | R112: HCORP-CRP-4100-JUL | S112: 200100 | T112: HCORP-CRP-6000-JUL | U112: 514000 | V112: HCORP-CRP-4600-JUL
A113: COA-251210 | B113: Active | C113: Expense | D113: Expense | E113: AFG Financing | F113: COA ITEM | G113: Expense | H113: False | I113: Standard | J113: EXEMPT | K113: NSK ITEMS | M113: 251210 | N113: HCORP-CRP-6000-JUL | O113: 251210 | P113: HCORP-CRP-6000-JUL | S113: 200100 | T113: HCORP-CRP-6000-JUL
A114: COA-492000 | B114: Active | C114: Expense | D114: Expense | E114: Sales Discounts and Rebates | F114: COA ITEM | G114: Expense | H114: False | I114: Standard | J114: EXEMPT | K114: NSK ITEMS | M114: 492000 | N114: HCORP-B2B-4100-JUL | O114: 492000 | P114: HCORP-B2B-4100-JUL | Q114: 410000 | R114: HCORP-B2B-4100-JUL | S114: 200100 | T114: HCORP-B2B-4100-JUL | U114: 514000 | V114: HCORP-B2B-4100-JUL
A115: COA-495000 | B115: Active | C115: Expense | D115: Expense | E115: Affiliate Commission | F115: COA ITEM | G115: Expense | H115: False | I115: Standard | J115: EXEMPT | K115: NSK ITEMS | M115: 495000 | N115: HCORP-B2C-5100-CRP | O115: 495000 | P115: HCORP-B2C-5100-CRP | Q115: 410000 | R115: HCORP-CRP-4100-CRP | S115: 200100 | T115: HCORP-CRP-4100-CRP | U115: 495000 | V115: HCORP-B2C-5100-CRP
A116: COA-497100 | B116: Active | C116: Expense | D116: Expense | E116: Slotting Fees | F116: COA ITEM | G116: Expense | H116: False | I116: Standard | J116: EXEMPT | K116: NSK ITEMS | M116: 497100 | N116: HCORP-STR-4100-JUL | O116: 497100 | P116: HCORP-STR-4100-JUL | Q116: 410000 | R116: HCORP-STR-4100-JUL | S116: 200100 | T116: HCORP-STR-4100-JUL | U116: 514000 | V116: HCORP-STR-4100-JUL
A117: COA-497300 | B117: Active | C117: Expense | D117: Expense | E117: Promotional Allowances | F117: COA ITEM | G117: Non-Stock Item | H117: False | I117: Standard | J117: EXEMPT | K117: NSK ITEMS | M117: 497300 | N117: HCORP-STR-4100-JUL | O117: 497300 | P117: HCORP-STR-4100-JUL | Q117: 410000 | R117: HCORP-STR-4100-JUL | S117: 200100 | T117: HCORP-STR-4100-JUL | U117: 514000
A118: COA-512000 | B118: Active | C118: Expense | D118: Expense | E118: Cost of Goods - Services | F118: COA ITEM | G118: Expense | H118: False | I118: Standard | J118: EXEMPT | K118: NSK ITEMS | M118: 220100 | N118: HCORP-CRP-6000-JUL | O118: 543000 | P118: HCORP-CRP-4600-JUL | S118: 200100 | T118: HCORP-CRP-6000-JUL
A119: COA-514000 | B119: Active | C119: Expense | D119: Expense | E119: Purchase Price Variance | F119: COA ITEM | G119: Expense | H119: False | I119: Standard | J119: EXEMPT | K119: NSK ITEMS | M119: 220100 | N119: HCORP-CRP-6000-JUL | O119: 514000 | P119: HCORP-CRP-4600-JUL | S119: 200100 | T119: HCORP-CRP-6000-JUL
A120: COA-521000 | B120: Active | C120: Expense | D120: Expense | E120: Warranty - cost of inventory | F120: COA ITEM | G120: Expense | H120: False | I120: Standard | J120: EXEMPT | K120: NSK ITEMS | M120: 250200 | N120: HCORP-CRP-4500-JUL | O120: 521000 | P120: HCORP-CRP-4500-JUL | S120: 200100 | T120: HCORP-CRP-5100-CRP
A121: COA-522000 | B121: Active | C121: Expense | D121: Expense | E121: Warranty - postage/freight | F121: COA ITEM | G121: Expense | H121: False | I121: Standard | J121: EXEMPT | K121: NSK ITEMS | M121: 220100 | N121: HCORP-CRP-6000-JUL | O121: 522000 | P121: HCORP-CRP-4500-JUL | S121: 200100 | T121: HCORP-CRP-6000-JUL
A122: COA-529000 | B122: Active | C122: Expense | D122: Expense | E122: Warranty - other | F122: COA ITEM | G122: Expense | H122: False | I122: Standard | J122: EXEMPT | K122: NSK ITEMS | M122: 220100 | N122: HCORP-CRP-6000-JUL | O122: 529000 | P122: HCORP-CRP-4500-JUL | S122: 200100 | T122: HCORP-CRP-6000-JUL
A123: COA-540010 | B123: Active | C123: Expense | D123: Expense | E123: Inventory Conditioning | F123: COA ITEM | G123: Expense | H123: False | I123: Standard | J123: EXEMPT | K123: NSK ITEMS | M123: 220100 | N123: HCORP-CRP-6000-JUL | O123: 540010 | P123: HCORP-CRP-4600-JUL | S123: 200100 | T123: HCORP-CRP-6000-JUL
A124: COA-541000 | B124: Active | C124: Expense | D124: Expense | E124: Inventory Adjustment | F124: COA ITEM | G124: Expense | H124: False | I124: Standard | J124: EXEMPT | K124: NSK ITEMS | M124: 220100 | N124: HCORP-CRP-6000-JUL | O124: 541000 | P124: HCORP-CRP-4600-JUL | S124: 200100 | T124: HCORP-CRP-6000-JUL
A125: COA-542000 | B125: Active | C125: Expense | D125: Expense | E125: Consumable Materials | F125: COA ITEM | G125: Expense | H125: False | I125: Standard | J125: EXEMPT | K125: NSK ITEMS | M125: 220100 | N125: HCORP-CRP-6000-JUL | O125: 542000 | P125: HCORP-CRP-4600-JUL | S125: 200100 | T125: HCORP-CRP-6000-JUL
...

Sheet JNL UK 1
A1: Account | B1: Description | C1: Subaccount | D1: Ref. Number | E1: Quantity | F1: UOM | G1: Debit Amount | H1: Credit Amount | I1: Transaction Description | J1: Reclass. Batch Number
A2: 531000 | B2: Freight Outbound | C2: INTUK-CRP-4600-JUL | D2: ACCR.ARVATO | G2: =193380/1.2*75% -> 120862.5 | I2: ACCR.ARVATO-Oct18 (75% of £160k Inv 94623882)
A3: 220950 | B3: Accrued Freight | C3: INTUK-CRP-4600-JUL | D3: ACCR.ARVATO | H3: =193380/1.2*75% -> 120862.5 | I3: ACCR.ARVATO-Oct18 (75% of £160k Inv 94623882)

Sheet Backup Jnl 1
A1: backup

Sheet JNL UK 2
A1: Account | B1: Description | C1: Subaccount | D1: Ref. Number | E1: Quantity | F1: UOM | G1: Debit Amount | H1: Credit Amount | I1: Transaction Description | J1: Reclass. Batch Number
A2: 531000 | B2: Freight Outbound | C2: INTUK-CRP-4600-JUL | D2: ACCR.ARVATO | G2: =76500+57000 -> 133500 | I2: ACCR>Avarto - Aug 18 & Sept 18
A3: 220950 | B3: Accrued Freight | C3: INTUK-CRP-4600-JUL | D3: ACCR.ARVATO | H3: =G2 -> 133500 | I3: ACCR>Avarto - Aug 18 & Sept 18

Sheet Backup Jnl2
