Workbook
Name EssAliasTable: "Default"
Name EssAliasTable: "Default"
Name EssAliasTable: "Default"
Name EssAliasTable: "Default"
Name EssAliasTable: "Misc Alias"
Name EssLatest: "Oct"
Name EssLatest: "Oct"
Name EssLatest: "Oct"
Name EssLatest: "Oct"
Name EssLatest: "Oct"
Name EssOptions: "A3100000000111000011001100020_08#missing00"
Name EssOptions: "A1100000000110000011001100020_08#missing00"
Name EssOptions: "A1100000000110000011001100020_08#missing00"
Name EssOptions: "A1100000000110000011001100020_08#missing00"
Name EssOptions: "A1100000000111001000001100020_08#missing00"
Name EssSamplingValue: 100
Name EssSamplingValue: 100
Name EssSamplingValue: 100
Name EssSamplingValue: 100
Name EssSamplingValue: 100

Sheet Pharm Demand
A1: Branded Pharmaceuticals
A2: FY13-16 Working Forecast
A3: Outfreight Expense object 7171
C4: NoCustomer | D4: NoCustomer | E4: NoCustomer | F4: NoCustomer | G4: NoCustomer | H4: NoCustomer | I4: NoCustomer | J4: NoCustomer | K4: NoCustomer | L4: NoCustomer | M4: NoCustomer | N4: NoCustomer | O4: NoCustomer | P4: NoCustomer | Q4: NoCustomer | R4: NoCustomer | S4: NoCustomer | T4: NoCustomer | U4: NoCustomer | V4: NoCustomer | W4: NoCustomer | X4: NoCustomer | Y4: NoCustomer | Z4: NoCustomer | AA4: NoCustomer | AB4: NoCustomer | AC4: NoCustomer | AD4: NoCustomer | AE4: NoCustomer | AF4: NoCustomer | AG4: NoCustomer | AH4: NoCustomer | AI4: NoCustomer | AJ4: NoCustomer | AK4: NoCustomer | AL4: NoCustomer | AM4: NoCustomer | AN4: NoCustomer | AO4: NoCustomer | AP4: NoCustomer | AQ4: NoCustomer | AR4: NoCustomer | AS4: NoCustomer | AT4: NoCustomer | AU4: NoCustomer | AV4: NoCustomer | AW4: NoCustomer | AX4: NoCustomer | AY4: NoCustomer | AZ4: NoCustomer | BA4: NoCustomer | BB4: NoCustomer
C5: FY13 Actuals | D5: FY13 Actuals | E5: FY13 Actuals | F5: FY13 Actuals | G5: Working Forecast | H5: Working Forecast | I5: Working Forecast | J5: Working Forecast | K5: Working Forecast | L5: Working Forecast | M5: Working Forecast | N5: Working Forecast | O5: Working Forecast | P5: Working Forecast Y2 | Q5: Working Forecast Y2 | R5: Working Forecast Y2 | S5: Working Forecast Y2 | T5: Working Forecast Y2 | U5: Working Forecast Y2 | V5: Working Forecast Y2 | W5: Working Forecast Y2 | X5: Working Forecast Y2 | Y5: Working Forecast Y2 | Z5: Working Forecast Y2 | AA5: Working Forecast Y2 | AB5: Working Forecast Y2 | AC5: Working Forecast Y3 | AD5: Working Forecast Y3 | AE5: Working Forecast Y3 | AF5: Working Forecast Y3 | AG5: Working Forecast Y3 | AH5: Working Forecast Y3 | AI5: Working Forecast Y3 | AJ5: Working Forecast Y3 | AK5: Working Forecast Y3 | AL5: Working Forecast Y3 | AM5: Working Forecast Y3 | AN5: Working Forecast Y3 | AO5: Working Forecast Y3 | AP5: Working Forecast Y4 | AQ5: Working Forecast Y4 | AR5: Working Forecast Y4 | AS5: Working Forecast Y4 | AT5: Working Forecast Y4 | AU5: Working Forecast Y4 | AV5: Working Forecast Y4 | AW5: Working Forecast Y4 | AX5: Working Forecast Y4 | AY5: Working Forecast Y4 | AZ5: Working Forecast Y4 | BA5: Working Forecast Y4 | BB5: Working Forecast Y4
C6: Oct | D6: Nov | E6: Dec | F6: Jan | G6: Feb | H6: Mar | I6: Apr | J6: May | K6: Jun | L6: Jul | M6: Aug | N6: Sep | O6: Full Year | P6: Oct | Q6: Nov | R6: Dec | S6: Jan | T6: Feb | U6: Mar | V6: Apr | W6: May | X6: Jun | Y6: Jul | Z6: Aug | AA6: Sep | AB6: Full Year | AC6: Oct | AD6: Nov | AE6: Dec | AF6: Jan | AG6: Feb | AH6: Mar | AI6: Apr | AJ6: May | AK6: Jun | AL6: Jul | AM6: Aug | AN6: Sep | AO6: Full Year | AP6: Oct | AQ6: Nov | AR6: Dec | AS6: Jan | AT6: Feb | AU6: Mar | AV6: Apr | AW6: May | AX6: Jun | AY6: Jul | AZ6: Aug | BA6: Sep | BB6: Full Year
A7: Tofranil PM | B7: Sales Volume | C7: 318.002 | D7: 366 | E7: 534.002 | F7: 240.001 | G7: 550 | H7: 427 | I7: 458 | J7: 519 | K7: 408 | L7: 417 | M7: 494 | N7: 409 | O7: 5140.005 | P7: 397 | Q7: 458 | R7: 369 | S7: 361 | T7: 455 | U7: 371 | V7: 363 | W7: 416 | X7: 372 | Y7: 328 | Z7: 433 | AA7: 338 | AB7: 4661 | AC7: 337 | AD7: 397 | AE7: 315 | AF7: 304 | AG7: 400 | AH7: 344 | AI7: 328 | AJ7: 394 | AK7: 340 | AL7: 306 | AM7: 420 | AN7: 305 | AO7: 4190 | AP7: 366 | AQ7: 288 | AR7: 333 | AS7: 318 | AT7: 319.9 | AU7: 0 | AV7: 0 | AW7: 0 | AX7: 0 | AY7: 0 | AZ7: 0 | BA7: 0 | BB7: 1624.9
A8: 157001000225 CNS Non-Promoted Products | B8: Sales Volume | C8: 4560.001 | D8: 5586 | E8: 7842.007 | F8: 3906.002 | G8: 6854.3664 | H8: 5216.7907 | I8: 5372.0602 | J8: 5657 | K8: 4658 | L8: 4404.9778 | M8: 4726.2286 | N8: 4379.6066 | O8: 63163.04 | P8: 5149.4472 | Q8: 5250 | R8: 4490 | S8: 4883.2164 | T8: 5406 | U8: 4653 | V8: 4929.7048 | W8: 5143 | X8: 4685 | Y8: 4817.455 | Z8: 5354 | AA8: 4703 | AB8: 59463.823 | AC8: 4487.7788 | AD8: 5192 | AE8: 4395 | AF8: 4240.5111 | AG8: 5214 | AH8: 4679 | AI8: 4479.0793 | AJ8: 5135 | AK8: 4615 | AL8: 4263.808 | AM8: 5339 | AN8: 4307 | AO8: 56347.177 | AP8: 4697.026 | AQ8: 4136 | AR8: 4428.6753 | AS8: 4407.6753 | AT8: 4580.542 | AU8: 0 | AV8: 0 | AW8: 0 | AX8: 0 | AY8: 0 | AZ8: 0 | BA8: 0 | BB8: 22249.919
A9: 157001000235 Tussicaps | B9: Sales Volume | C9: 0.003 | D9: 0.003 | E9: 0.004 | F9: 0.003 | G9: 0 | H9: 0 | I9: 0 | J9: 0 | K9: 0 | L9: 0 | M9: 0 | N9: 0 | O9: 0.013 | P9: 0 | Q9: 0 | R9: 0 | S9: 0 | T9: 0 | U9: 0 | V9: 0 | W9: 0 | X9: 0 | Y9: 0 | Z9: 0 | AA9: 0 | AB9: 0 | AC9: 0 | AD9: 0 | AE9: 0 | AF9: 0 | AG9: 0 | AH9: 0 | AI9: 0 | AJ9: 0 | AK9: 0 | AL9: 0 | AM9: 0 | AN9: 0 | AO9: 0 | AP9: 0 | AQ9: 0 | AR9: 0 | AS9: 0 | AT9: 0 | AU9: 0 | AV9: 0 | AW9: 0 | AX9: 0 | AY9: 0 | AZ9: 0 | BA9: 0 | BB9: 0
A10: 157001000251 Pennsaid | B10: Sales Volume | C10: 11375 | D10: 14904 | E10: 20832 | F10: 12336 | G10: 24822.336 | H10: 18185.67 | I10: 28840.783 | J10: 37678.116 | K10: 23860.657 | L10: 23733.018 | M10: 24234.107 | N10: 24178.99 | O10: 264980.68 | P10: 19865.442 | Q10: 13206.049 | R10: 8752.9776 | S10: 5680.648 | T10: 3720.4748 | U10: 2374.1937 | V10: 2378.3199 | W10: 2404.5662 | X10: 2432.8003 | Y10: 2447.6958 | Z10: 2471.9682 | AA10: 2483.7957 | AB10: 68218.931 | AC10: 2501.444 | AD10: 2148.9836 | AE10: 1355.2982 | AF10: 812.23332 | AG10: 461.23795 | AH10: 219.71459 | AI10: 54.786627 | AJ10: 0 | AK10: 0 | AL10: 0 | AM10: 0 | AN10: 0 | AO10: 7553.6983 | AP10: 0 | AQ10: 0 | AR10: 0 | AS10: 0 | AT10: 0 | AU10: 0 | AV10: 0 | AW10: 0 | AX10: 0 | AY10: 0 | AZ10: 0 | BA10: 0 | BB10: 0
A11: Pennsaid 2% Pump | B11: Sales Volume | C11: 0 | D11: 0 | E11: 0 | F11: 0 | G11: 0 | H11: 0 | I11: 0 | J11: 0 | K11: 0 | L11: 0 | M11: 0 | N11: 0 | O11: 0 | P11: 21739 | Q11: 15021.428 | R11: 13201 | S11: 21265 | T11: 24150.479 | U11: 18521 | V11: 22696 | W11: 24869.095 | X11: 19158 | Y11: 22395 | Z11: 26196 | AA11: 24197 | AB11: 253409 | AC11: 22513 | AD11: 22754.429 | AE11: 18905 | AF11: 16021 | AG11: 14294.979 | AH11: 13040 | AI11: 12113 | AJ11: 11582.387 | AK11: 11814 | AL11: 11977 | AM11: 12191.546 | AN11: 12340 | AO11: 179546.34 | AP11: 12360 | AQ11: 12890 | AR11: 12960 | AS11: 13336.667 | AT11: 13636.667 | AU11: 0 | AV11: 0 | AW11: 0 | AX11: 0 | AY11: 0 | AZ11: 0 | BA11: 0 | BB11: 65183.333
A12: Diclofenac 2% Pump | B12: Sales Volume | C12: 0 | D12: 0 | E12: 0 | F12: 0 | G12: 0 | H12: 0 | I12: 0 | J12: 0 | K12: 0 | L12: 0 | M12: 0 | N12: 0 | O12: 0 | P12: 0 | Q12: 0 | R12: 0 | S12: 0 | T12: 0 | U12: 0 | V12: 0 | W12: 0 | X12: 0 | Y12: 0 | Z12: 0 | AA12: 0 | AB12: 0 | AC12: 0 | AD12: 0 | AE12: 0 | AF12: 0 | AG12: 0 | AH12: 0 | AI12: 0 | AJ12: 0 | AK12: 0 | AL12: 0 | AM12: 0 | AN12: 0 | AO12: 0 | AP12: 0 | AQ12: 0 | AR12: 0 | AS12: 0 | AT12: 0 | AU12: 0 | AV12: 0 | AW12: 0 | AX12: 0 | AY12: 0 | AZ12: 0 | BA12: 0 | BB12: 0
A13: 157001000252 Exalgo | B13: Sales Volume | C13: 7524 | D13: 9864 | E13: 9396 | F13: 6120 | G13: 11671.249 | H13: 8920.1263 | I13: 7297 | J13: 9875 | K13: 6544 | L13: 6533.702 | M13: 10546.388 | N13: 8045.32 | O13: 102336.79 | P13: 7876 | Q13: 11616 | R13: 1936 | S13: 581 | T13: 1111 | U13: 466 | V13: 500 | W13: 660 | X13: 415 | Y13: 464 | Z13: 794 | AA13: 475 | AB13: 26894 | AC13: 517 | AD13: 809 | AE13: 516 | AF13: 511 | AG13: 829 | AH13: 555 | AI13: 606 | AJ13: 877 | AK13: 560 | AL13: 586 | AM13: 1021 | AN13: 562 | AO13: 7949 | AP13: 738 | AQ13: 833 | AR13: 710 | AS13: 799 | AT13: 746.66667 | AU13: 0 | AV13: 0 | AW13: 0 | AX13: 0 | AY13: 0 | AZ13: 0 | BA13: 0 | BB13: 3826.6667
A14: Exalgo 32 | B14: Sales Volume | C14: 408 | D14: 816 | E14: 1008 | F14: 660 | G14: 1204 | H14: 939 | I14: 1312 | J14: 2014 | K14: 1987 | L14: 2350 | M14: 3661 | N14: 3315 | O14: 19674 | P14: 3977 | Q14: 5070 | R14: 2018 | S14: 1817 | T14: 3074 | U14: 2173 | V14: 2299 | W14: 3095 | X14: 2289 | Y14: 2185 | Z14: 1555 | AA14: 330 | AB14: 29882 | AC14: 233 | AD14: 164 | AE14: 113 | AF14: 113 | AG14: 175 | AH14: 121 | AI14: 128 | AJ14: 179 | AK14: 119 | AL14: 121 | AM14: 202 | AN14: 116 | AO14: 1784 | AP14: 148 | AQ14: 161 | AR14: 145 | AS14: 157 | AT14: 150.33333 | AU14: 0 | AV14: 0 | AW14: 0 | AX14: 0 | AY14: 0 | AZ14: 0 | BA14: 0 | BB14: 761.33333
A15: Hydromorphone ER | B15: Sales Volume | C15: 0 | D15: 0 | E15: 0 | F15: 0 | G15: 0 | H15: 0 | I15: 0 | J15: 0 | K15: 0 | L15: 0 | M15: 0 | N15: 0 | O15: 0 | P15: 0 | Q15: 0 | R15: 0 | S15: 0 | T15: 0 | U15: 0 | V15: 1093 | W15: 925 | X15: 1280 | Y15: 2144 | Z15: 1957 | AA15: 2544 | AB15: 9943 | AC15: 3164 | AD15: 3919 | AE15: 3213 | AF15: 4192 | AG15: 3598 | AH15: 4390 | AI15: 4996 | AJ15: 3605 | AK15: 4253 | AL15: 5530 | AM15: 3797 | AN15: 3797 | AO15: 48454 | AP15: 3797 | AQ15: 4295.6727 | AR15: 4327.2545 | AS15: 4358.8364 | AT15: 4623.9636 | AU15: 0 | AV15: 0 | AW15: 0 | AX15: 0 | AY15: 0 | AZ15: 0 | BA15: 0 | BB15: 21402.727
A16: Hydromorphone ER 32 | B16: Sales Volume | C16: 0 | D16: 0 | E16: 0 | F16: 0 | G16: 0 | H16: 0 | I16: 0 | J16: 0 | K16: 0 | L16: 0 | M16: 0 | N16: 0 | O16: 0 | P16: 0 | Q16: 0 | R16: 0 | S16: 0 | T16: 0 | U16: 0 | V16: 0 | W16: 0 | X16: 0 | Y16: 439 | Z16: 401 | AA16: 521 | AB16: 1361 | AC16: 648 | AD16: -304 | AE16: 710 | AF16: 883 | AG16: 784 | AH16: 929 | AI16: 1013 | AJ16: 768 | AK16: 882 | AL16: 1085 | AM16: 784 | AN16: 784 | AO16: 8966 | AP16: 784 | AQ16: 863.54545 | AR16: 864.95455 | AS16: 866.36364 | AT16: 906.84091 | AU16: 0 | AV16: 0 | AW16: 0 | AX16: 0 | AY16: 0 | AZ16: 0 | BA16: 0 | BB16: 4285.7045
A17: Roxicodone | B17: Sales Volume | C17: 3660.001 | D17: 3168.002 | E17: 2856.003 | F17: 3360.002 | G17: 4296.3877 | H17: 3440.6208 | I17: 4050 | J17: 3713 | K17: 3183 | L17: 4644.4126 | M17: 3796.2723 | N17: 3504.4051 | O17: 43672.107 | P17: 4673.0539 | Q17: 3384 | R17: 3266 | S17: 4478.0539 | T17: 3602 | U17: 3438 | V17: 4306.0539 | W17: 3602 | X17: 3266 | Y17: 4658.0539 | Z17: 3422 | AA17: 3782 | AB17: 45877.216 | AC17: 3782.0539 | AD17: 3782 | AE17: 3782 | AF17: 3782.0539 | AG17: 3782 | AH17: 3782 | AI17: 3782.0539 | AJ17: 3782 | AK17: 3782 | AL17: 3782.0539 | AM17: 3782 | AN17: 3782 | AO17: 45384.216 | AP17: 3782.0539 | AQ17: 3782 | AR17: 3782 | AS17: 3825 | AT17: 3960.4 | AU17: 0 | AV17: 0 | AW17: 0 | AX17: 0 | AY17: 0 | AZ17: 0 | BA17: 0 | BB17: 19131.454
A18: Intrathecal Products | B18: Sales Volume | C18: 7250 | D18: 10491 | E18: 9054 | F18: 6636 | G18: 17083.557 | H18: 14938.892 | I18: 11629.425 | J18: 15474.276 | K18: 13551.781 | L18: 11930.898 | M18: 15774.678 | N18: 13890.919 | O18: 147705.43 | P18: 7070.4299 | Q18: 8793.7911 | R18: 7108.9912 | S18: 7144.9506 | T18: 8902.3882 | U18: 7268.5969 | V18: 7285.6559 | W18: 9017.4815 | X18: 7262.5929 | Y18: 7307.3013 | Z18: 9032.6988 | AA18: 7303.1218 | AB18: 93498 | AC18: 7288.9913 | AD18: 8594.4716 | AE18: 7288.9913 | AF18: 7552.7213 | AG18: 8891.1679 | AH18: 7617.7761 | AI18: 7974.9675 | AJ18: 9521.3797 | AK18: 8277.0077 | AL18: 8685.1542 | AM18: 10249.174 | AN18: 8945.3734 | AO18: 100887.18 | AP18: 0 | AQ18: 0 | AR18: 0 | AS18: 0 | AT18: 0 | AU18: 0 | AV18: 0 | AW18: 0 | AX18: 0 | AY18: 0 | AZ18: 0 | BA18: 0 | BB18: 0
... A22: Brand Pharmaceuticals | B22: Sales Volume | C22: 35095.008 | D22: 45195.006 | E22: 51522.018 | F22: 33258.009 | G22: 66481.897 | H22: 52068.099 | I22: 58959.269 | J22: 74930.391 | K22: 54192.438 | L22: 54014.008 | M22: 63232.674 | N22: 57723.24 | O22: 646672.06 | P22: 70747.373 | Q22: 62799.267 | R22: 41141.969 | S22: 46210.869 | T22: 50421.342 | U22: 39264.791 | V22: 59006.621 | W22: 76444.917 | X22: 80629.053 | Y22: 93586.224 | Z22: 104950.44 | AA22: 106942.75 | AB22: 832145.62 | AC22: 114352.95 | AD22: 126479.23 | AE22: 129758.3 | AF22: 160726.69 | AG22: 193895.72 | AH22: 224294.99 | AI22: 246701.64 | AJ22: 269681.76 | AK22: 291090.25 | AL22: 321647.22 | AM22: 351960.89 | AN22: 377977.51 | AO22: 2808567.2 | AP22: 378666.73 | AQ22: 395826.16 | AR22: 412767.12 | AS22: 450398.92 | AT22: 474793.84 | AU22: 0 | AV22: 0 | AW22: 0 | AX22: 0 | AY22: 0 | AZ22: 0 | BA22: 0 | BB22: 2112452.8
O23: =SUM(O7:O21) -> 646672.05 | AB23: =SUM(AB7:AB21) -> 832145.62 | AO23: =SUM(AO7:AO21) -> 2808567.2 | BB23: =SUM(BB7:BB21) -> 2112452.8
O24: =O23-O22 -> -0.005 | AB24: =AB23-AB22 -> 0 | AO24: =AO23-AO22 -> 0 | BB24: =BB23-BB22 -> 0
A25: Freight per bottle - use FY12 Actual average | B25: 0.1365
A26: Freight per bottle (from RMeisner/CGidcumb 3/29/11) | B26: 0.11
A30: Calculated Forecast | C30: Oct | D30: Nov | E30: Dec | F30: Jan | G30: Feb | H30: Mar | I30: Apr | J30: May | K30: Jun | L30: Jul | M30: Aug | N30: Sep | O30: FY13 | P30: Oct | Q30: Nov | R30: Dec | S30: Jan | T30: Feb | U30: Mar | V30: Apr | W30: May | X30: Jun | Y30: Jul | Z30: Aug | AA30: Sep | AB30: WF FY14 | AC30: Oct | AD30: Nov | AE30: Dec | AF30: Jan | AG30: Feb | AH30: Mar | AI30: Apr | AJ30: May | AK30: Jun | AL30: Jul | AM30: Aug | AN30: Sep | AO30: WF FY15 | AP30: Oct | AQ30: Nov | AR30: Dec | AS30: Jan | AT30: Feb | AU30: Mar | AV30: Apr | AW30: May | AX30: Jun | AY30: Jul | AZ30: Aug | BA30: Sep | BB30: WF FY16
A31: 157001150245 Tofranil-PM/ImipraPam Frt Exp | C31: ='Download COV'!D7 -> 0 | D31: ='Download COV'!E7 -> 0 | E31: ='Download COV'!F7 -> 42 | F31: ='Download COV'!G7 -> 46 | G31: =G7*$B$25 -> 75.075 | H31: =H7*$B$25 -> 58.2855 | I31: =I7*$B$25 -> 62.517 | J31: =J7*$B$25 -> 70.8435 | K31: =K7*$B$25 -> 55.692 | L31: =L7*$B$25 -> 56.9205 | M31: =M7*$B$25 -> 67.431 | N31: =N7*$B$25 -> 55.8285 | O31: =SUM(C31:N31) -> 590.593 | P31: =P7*$B$25 -> 54.1905 | Q31: =Q7*$B$25 -> 62.517 | R31: =R7*$B$25 -> 50.3685 | S31: =S7*$B$25 -> 49.2765 | T31: =T7*$B$25 -> 62.1075 | U31: =U7*$B$25 -> 50.6415 | V31: =V7*$B$25 -> 49.5495 | W31: =W7*$B$25 -> 56.784 | ... AA31: =AA7*$B$25 -> 46.137 | AB31: =SUM(P31:AA31) -> 636.2265 | AC31: =AC7*$B$25 -> 46.0005 | AD31: =AD7*$B$25 -> 54.1905 | AE31: =AE7*$B$25 -> 42.9975 | AF31: =AF7*$B$25 -> 41.496 | AG31: =AG7*$B$25 -> 54.6 | AH31: =AH7*$B$25 -> 46.956 | AI31: =AI7*$B$25 -> 44.772 | AJ31: =AJ7*$B$25 -> 53.781 | ... AN31: =AN7*$B$25 -> 41.6325 | AO31: =SUM(AC31:AN31) -> 571.935 | AP31: =AP7*$B$25 -> 49.959 | AQ31: =AQ7*$B$25 -> 39.312 | AR31: =AR7*$B$25 -> 45.4545 | AS31: =AS7*$B$25 -> 43.407 | AT31: =AT7*$B$25 -> 43.66635 | AU31: =AU7*$B$25 -> 0 | AV31: =AV7*$B$25 -> 0 | AW31: =AW7*$B$25 -> 0 | ... BA31: =BA7*$B$25 -> 0 | BB31: =SUM(AP31:BA31) -> 221.79885
A32: 157001150225 Frt Exp-CNS Non-Promoted Prod | C32: ='Download COV'!D8 -> 890 | D32: ='Download COV'!E8 -> 1055 | E32: ='Download COV'!F8 -> 605 | F32: ='Download COV'!G8 -> 751 | G32: =G8*$B$25 -> 935.62102 | H32: =H8*$B$25 -> 712.09193 | I32: =I8*$B$25 -> 733.28621 | J32: =J8*$B$25 -> 772.1805 | K32: =K8*$B$25 -> 635.817 | L32: =L8*$B$25 -> 601.27947 | M32: =M8*$B$25 -> 645.1302 | N32: =N8*$B$25 -> 597.8163 | O32: =SUM(C32:N32) -> 8934.2226 | P32: =P8*$B$25 -> 702.89955 | Q32: =Q8*$B$25 -> 716.625 | R32: =R8*$B$25 -> 612.885 | S32: =S8*$B$25 -> 666.55904 | T32: =T8*$B$25 -> 737.919 | U32: =U8*$B$25 -> 635.1345 | V32: =V8*$B$25 -> 672.9047 | W32: =W8*$B$25 -> 702.0195 | ... AA32: =AA8*$B$25 -> 641.9595 | AB32: =SUM(P32:AA32) -> 8116.8119 | AC32: =AC8*$B$25 -> 612.5818 | AD32: =AD8*$B$25 -> 708.708 | AE32: =AE8*$B$25 -> 599.9175 | AF32: =AF8*$B$25 -> 578.82977 | AG32: =AG8*$B$25 -> 711.711 | AH32: =AH8*$B$25 -> 638.6835 | AI32: =AI8*$B$25 -> 611.39432 | AJ32: =AJ8*$B$25 -> 700.9275 | ... AN32: =AN8*$B$25 -> 587.9055 | AO32: =SUM(AC32:AN32) -> 7691.3897 | AP32: =AP8*$B$25 -> 641.14405 | AQ32: =AQ8*$B$25 -> 564.564 | AR32: =AR8*$B$25 -> 604.51418 | AS32: =AS8*$B$25 -> 601.64768 | AT32: =AT8*$B$25 -> 625.24398 | AU32: =AU8*$B$25 -> 0 | AV32: =AV8*$B$25 -> 0 | AW32: =AW8*$B$25 -> 0 | ... BA32: =BA8*$B$25 -> 0 | BB32: =SUM(AP32:BA32) -> 3037.1139
A34: 157001150251 Pennsaid Frt Expense | C34: ='Download COV'!D10 -> 2075 | D34: ='Download COV'!E10 -> 2641 | E34: ='Download COV'!F10 -> 1565 | F34: ='Download COV'!G10 -> 2371 | G34: =G10*$B$25 -> 3388.2488 | H34: =H10*$B$25 -> 2482.3439 | I34: =I10*$B$25 -> 3936.7669 | J34: =J10*$B$25 -> 5143.0628 | K34: =K10*$B$25 -> 3256.9797 | L34: =L10*$B$25 -> 3239.557 | M34: =M10*$B$25 -> 3307.9556 | N34: =N10*$B$25 -> 3300.4321 | O34: =SUM(C34:N34) -> 36707.347 | P34: =P10*$B$25 -> 2711.6328 | Q34: =Q10*$B$25 -> 1802.6256 | R34: =R10*$B$25 -> 1194.7814 | S34: =S10*$B$25 -> 775.40845 | T34: =T10*$B$25 -> 507.84481 | U34: =U10*$B$25 -> 324.07744 | V34: =V10*$B$25 -> 324.64067 | W34: =W10*$B$25 -> 328.22328 | ... AA34: =AA10*$B$25 -> 339.03812 | AB34: =SUM(P34:AA34) -> 9311.8841 | AC34: =AC10*$B$25 -> 341.44711 | AD34: =AD10*$B$25 -> 293.33626 | AE34: =AE10*$B$25 -> 184.9982 | AF34: =AF10*$B$25 -> 110.86985 | AG34: =AG10*$B$25 -> 62.958981 | AH34: =AH10*$B$25 -> 29.991041 | AI34: =AI10*$B$25 -> 7.4783745 | AJ34: =AJ10*$B$25 -> 0 | ... AN34: =AN10*$B$25 -> 0 | AO34: =SUM(AC34:AN34) -> 1031.0798 | AP34: =AP10*$B$25 -> 0 | AQ34: =AQ10*$B$25 -> 0 | AR34: =AR10*$B$25 -> 0 | AS34: =AS10*$B$25 -> 0 | AT34: =AT10*$B$25 -> 0 | AU34: =AU10*$B$25 -> 0 | AV34: =AV10*$B$25 -> 0 | AW34: =AW10*$B$25 -> 0 | ... BA34: =BA10*$B$25 -> 0 | BB34: =SUM(AP34:BA34) -> 0
A35: 157001150255 Pennsaid 2% Pump Frt Expense | C35: ='Download COV'!D11 -> 0 | D35: ='Download COV'!E11 -> 0 | E35: ='Download COV'!F11 -> 0 | F35: ='Download COV'!G11 -> 0 | G35: =G11*$B$25 -> 0 | H35: =H11*$B$25 -> 0 | I35: =I11*$B$25 -> 0 | J35: =J11*$B$25 -> 0 | K35: =K11*$B$25 -> 0 | L35: =L11*$B$25 -> 0 | M35: =M11*$B$25 -> 0 | N35: =N11*$B$25 -> 0 | O35: =SUM(C35:N35) -> 0 | P35: =P11*$B$25 -> 2967.3735 | Q35: =Q11*$B$25 -> 2050.4249 | R35: =R11*$B$25 -> 1801.9365 | S35: =S11*$B$25 -> 2902.6725 | T35: =T11*$B$25 -> 3296.5404 | U35: =U11*$B$25 -> 2528.1165 | V35: =V11*$B$25 -> 3098.004 | W35: =W11*$B$25 -> 3394.6315 | ... AA35: =AA11*$B$25 -> 3302.8905 | AB35: =SUM(P35:AA35) -> 34590.329 | AC35: =AC11*$B$25 -> 3073.0245 | AD35: =AD11*$B$25 -> 3105.9795 | AE35: =AE11*$B$25 -> 2580.5325 | AF35: =AF11*$B$25 -> 2186.8665 | AG35: =AG11*$B$25 -> 1951.2646 | AH35: =AH11*$B$25 -> 1779.96 | AI35: =AI11*$B$25 -> 1653.4245 | AJ35: =AJ11*$B$25 -> 1580.9959 | ... AN35: =AN11*$B$25 -> 1684.41 | AO35: =SUM(AC35:AN35) -> 24508.076 | AP35: =AP11*$B$25 -> 1687.14 | AQ35: =AQ11*$B$25 -> 1759.485 | AR35: =AR11*$B$25 -> 1769.04 | AS35: =AS11*$B$25 -> 1820.455 | AT35: =AT11*$B$25 -> 1861.405 | AU35: =AU11*$B$25 -> 0 | AV35: =AV11*$B$25 -> 0 | AW35: =AW11*$B$25 -> 0 | ... BA35: =BA11*$B$25 -> 0 | BB35: =SUM(AP35:BA35) -> 8897.525
A36: 157001150256 Diclofenac 2% Pump Frt Exp | C36: ='Download COV'!D12 -> 0 | D36: ='Download COV'!E12 -> 0 | E36: ='Download COV'!F12 -> 0 | F36: ='Download COV'!G12 -> 0 | G36: =G12*$B$25 -> 0 | H36: =H12*$B$25 -> 0 | I36: =I12*$B$25 -> 0 | J36: =J12*$B$25 -> 0 | K36: =K12*$B$25 -> 0 | L36: =L12*$B$25 -> 0 | M36: =M12*$B$25 -> 0 | N36: =N12*$B$25 -> 0 | O36: =SUM(C36:N36) -> 0 | P36: =P12*$B$25 -> 0 | Q36: =Q12*$B$25 -> 0 | R36: =R12*$B$25 -> 0 | S36: =S12*$B$25 -> 0 | T36: =T12*$B$25 -> 0 | U36: =U12*$B$25 -> 0 | V36: =V12*$B$25 -> 0 | W36: =W12*$B$25 -> 0 | ... AA36: =AA12*$B$25 -> 0 | AB36: =SUM(P36:AA36) -> 0 | AC36: =AC12*$B$25 -> 0 | AD36: =AD12*$B$25 -> 0 | AE36: =AE12*$B$25 -> 0 | AF36: =AF12*$B$25 -> 0 | AG36: =AG12*$B$25 -> 0 | AH36: =AH12*$B$25 -> 0 | AI36: =AI12*$B$25 -> 0 | AJ36: =AJ12*$B$25 -> 0 | ... AN36: =AN12*$B$25 -> 0 | AO36: =SUM(AC36:AN36) -> 0 | AP36: =AP12*$B$25 -> 0 | AQ36: =AQ12*$B$25 -> 0 | AR36: =AR12*$B$25 -> 0 | AS36: =AS12*$B$25 -> 0 | AT36: =AT12*$B$25 -> 0 | AU36: =AU12*$B$25 -> 0 | AV36: =AV12*$B$25 -> 0 | AW36: =AW12*$B$25 -> 0 | ... BA36: =BA12*$B$25 -> 0 | BB36: =SUM(AP36:BA36) -> 0
A37: 157001150252 Exalgo Freight Exp | C37: ='Download COV'!D13 -> 1447 | D37: ='Download COV'!E13 -> 1893 | E37: ='Download COV'!F13 -> 705 | F37: ='Download COV'!G13 -> 1303 | G37: =SUM(G13:G14)*$B$25 -> 1757.4715 | H37: =SUM(H13:H14)*$B$25 -> 1345.7707 | I37: =SUM(I13:I14)*$B$25 -> 1175.1285 | J37: =SUM(J13:J14)*$B$25 -> 1622.8485 | K37: =SUM(K13:K14)*$B$25 -> 1164.4815 | L37: =SUM(L13:L14)*$B$25 -> 1212.6253 | M37: =SUM(M13:M14)*$B$25 -> 1939.3085 | N37: =SUM(N13:N14)*$B$25 -> 1550.6837 | O37: =SUM(C37:N37) -> 17116.318 | P37: =SUM(P13:P14)*$B$25 -> 1617.9345 | Q37: =SUM(Q13:Q14)*$B$25 -> 2277.639 | R37: =SUM(R13:R14)*$B$25 -> 539.721 | S37: =SUM(S13:S14)*$B$25 -> 327.327 | T37: =SUM(T13:T14)*$B$25 -> 571.2525 | U37: =SUM(U13:U14)*$B$25 -> 360.2235 | V37: =SUM(V13:V14)*$B$25 -> 382.0635 | W37: =SUM(W13:W14)*$B$25 -> 512.5575 | ... AA37: =SUM(AA13:AA14)*$B$25 -> 109.8825 | AB37: =SUM(P37:AA37) -> 7749.924 | AC37: =SUM(AC13:AC14)*$B$25 -> 102.375 | AD37: =SUM(AD13:AD14)*$B$25 -> 132.8145 | AE37: =SUM(AE13:AE14)*$B$25 -> 85.8585 | AF37: =SUM(AF13:AF14)*$B$25 -> 85.176 | AG37: =SUM(AG13:AG14)*$B$25 -> 137.046 | AH37: =SUM(AH13:AH14)*$B$25 -> 92.274 | AI37: =SUM(AI13:AI14)*$B$25 -> 100.191 | AJ37: =SUM(AJ13:AJ14)*$B$25 -> 144.144 | ... AN37: =SUM(AN13:AN14)*$B$25 -> 92.547 | AO37: =SUM(AC37:AN37) -> 1328.5545 | AP37: =SUM(AP13:AP14)*$B$25 -> 120.939 | AQ37: =SUM(AQ13:AQ14)*$B$25 -> 135.681 | AR37: =SUM(AR13:AR14)*$B$25 -> 116.7075 | AS37: =SUM(AS13:AS14)*$B$25 -> 130.494 | AT37: =SUM(AT13:AT14)*$B$25 -> 122.4405 | AU37: =SUM(AU13:AU14)*$B$25 -> 0 | AV37: =SUM(AV13:AV14)*$B$25 -> 0 | AW37: =SUM(AW13:AW14)*$B$25 -> 0 | ... BA37: =SUM(BA13:BA14)*$B$25 -> 0 | BB37: =SUM(AP37:BA37) -> 626.262
A39: 157001150258 Hydromorphone ER Frt Exp | C39: ='Download COV'!D15 -> 0 | D39: ='Download COV'!E15 -> 0 | E39: ='Download COV'!F15 -> 0 | F39: ='Download COV'!G15 -> 0 | G39: =SUM(G15:G16)*$B$25 -> 0 | H39: =SUM(H15:H16)*$B$25 -> 0 | I39: =SUM(I15:I16)*$B$25 -> 0 | J39: =SUM(J15:J16)*$B$25 -> 0 | K39: =SUM(K15:K16)*$B$25 -> 0 | L39: =SUM(L15:L16)*$B$25 -> 0 | M39: =SUM(M15:M16)*$B$25 -> 0 | N39: =SUM(N15:N16)*$B$25 -> 0 | O39: =SUM(C39:N39) -> 0 | P39: =SUM(P15:P16)*$B$25 -> 0 | Q39: =SUM(Q15:Q16)*$B$25 -> 0 | R39: =SUM(R15:R16)*$B$25 -> 0 | S39: =SUM(S15:S16)*$B$25 -> 0 | T39: =SUM(T15:T16)*$B$25 -> 0 | U39: =SUM(U15:U16)*$B$25 -> 0 | V39: =SUM(V15:V16)*$B$25 -> 149.1945 | W39: =SUM(W15:W16)*$B$25 -> 126.2625 | ... AA39: =SUM(AA15:AA16)*$B$25 -> 418.3725 | AB39: =SUM(P39:AA39) -> 1542.996 | AC39: =SUM(AC15:AC16)*$B$25 -> 520.338 | AD39: =SUM(AD15:AD16)*$B$25 -> 493.4475 | AE39: =SUM(AE15:AE16)*$B$25 -> 535.4895 | AF39: =SUM(AF15:AF16)*$B$25 -> 692.7375 | AG39: =SUM(AG15:AG16)*$B$25 -> 598.143 | AH39: =SUM(AH15:AH16)*$B$25 -> 726.0435 | AI39: =SUM(AI15:AI16)*$B$25 -> 820.2285 | AJ39: =SUM(AJ15:AJ16)*$B$25 -> 596.9145 | ... AN39: =SUM(AN15:AN16)*$B$25 -> 625.3065 | AO39: =SUM(AC39:AN39) -> 7837.83 | AP39: =SUM(AP15:AP16)*$B$25 -> 625.3065 | AQ39: =SUM(AQ15:AQ16)*$B$25 -> 704.23328 | AR39: =SUM(AR15:AR16)*$B$25 -> 708.73654 | AS39: =SUM(AS15:AS16)*$B$25 -> 713.2398 | AT39: =SUM(AT15:AT16)*$B$25 -> 754.95482 | AU39: =SUM(AU15:AU16)*$B$25 -> 0 | AV39: =SUM(AV15:AV16)*$B$25 -> 0 | AW39: =SUM(AW15:AW16)*$B$25 -> 0 | ... BA39: =SUM(BA15:BA16)*$B$25 -> 0 | BB39: =SUM(AP39:BA39) -> 3506.4709
A41: 157001150268 Roxicodone-Freight | C41: ='Download COV'!D17 -> 668 | D41: ='Download COV'!E17 -> 561 | E41: ='Download COV'!F17 -> 209 | F41: ='Download COV'!G17 -> 646 | G41: =G17*$B$25 -> 586.45692 | H41: =H17*$B$25 -> 469.64474 | I41: =I17*$B$25 -> 552.825 | J41: =J17*$B$25 -> 506.8245 | K41: =K17*$B$25 -> 434.4795 | L41: =L17*$B$25 -> 633.96232 | M41: =M17*$B$25 -> 518.19117 | N41: =N17*$B$25 -> 478.3513 | O41: =SUM(C41:N41) -> 6264.7354 | P41: =P17*$B$25 -> 637.87186 | Q41: =Q17*$B$25 -> 461.916 | R41: =R17*$B$25 -> 445.809 | S41: =S17*$B$25 -> 611.25436 | T41: =T17*$B$25 -> 491.673 | U41: =U17*$B$25 -> 469.287 | V41: =V17*$B$25 -> 587.77636 | W41: =W17*$B$25 -> 491.673 | ... AA41: =AA17*$B$25 -> 516.243 | AB41: =SUM(P41:AA41) -> 6262.2399 | AC41: =AC17*$B$25 -> 516.25036 | AD41: =AD17*$B$25 -> 516.243 | AE41: =AE17*$B$25 -> 516.243 | AF41: =AF17*$B$25 -> 516.25036 | AG41: =AG17*$B$25 -> 516.243 | AH41: =AH17*$B$25 -> 516.243 | AI41: =AI17*$B$25 -> 516.25036 | AJ41: =AJ17*$B$25 -> 516.243 | ... AN41: =AN17*$B$25 -> 516.243 | AO41: =SUM(AC41:AN41) -> 6194.9454 | AP41: =AP17*$B$25 -> 516.25036 | AQ41: =AQ17*$B$25 -> 516.243 | AR41: =AR17*$B$25 -> 516.243 | AS41: =AS17*$B$25 -> 522.1125 | AT41: =AT17*$B$25 -> 540.5946 | AU41: =AU17*$B$25 -> 0 | AV41: =AV17*$B$25 -> 0 | AW41: =AW17*$B$25 -> 0 | ... BA41: =BA17*$B$25 -> 0 | BB41: =SUM(AP41:BA41) -> 2611.4435
A42: 157210151269 Intrathecal-Freight-General | C42: =SUM('Download COV'!D18:D21) -> 0 | D42: =SUM('Download COV'!E18:E21) -> 0 | E42: =SUM('Download COV'!F18:F21) -> 0 | F42: =SUM('Download COV'!G18:G21) -> 25854.04 | G42: 3300 | H42: 2750 | I42: 2500 | J42: 2500 | K42: 2500 | L42: 2500 | M42: 2500 | N42: 2500 | O42: =SUM(C42:N42) -> 46904.04 | P42: 5000 | Q42: 5000 | R42: 5000 | S42: 5000 | T42: 5000 | U42: 5000 | V42: 5000 | W42: 5000 | X42: 5000 | Y42: 5000 | Z42: 5000 | AA42: 5000 | AB42: =SUM(P42:AA42) -> 60000 | AC42: =AC18*$B$25 -> 994.94731 | AD42: =AD18*$B$25 -> 1173.1454 | AE42: =AE18*$B$25 -> 994.94731 | AF42: =AF18*$B$25 -> 1030.9465 | AG42: =AG18*$B$25 -> 1213.6444 | AH42: =AH18*$B$25 -> 1039.8264 | AI42: =AI18*$B$25 -> 1088.5831 | AJ42: =AJ18*$B$25 -> 1299.6683 | ... AN42: =AN18*$B$25 -> 1221.0435 | AO42: =SUM(AC42:AN42) -> 13771.099 | AP42: =AP18*$B$25 -> 0 | AQ42: =AQ18*$B$25 -> 0 | AR42: =AR18*$B$25 -> 0 | AS42: =AS18*$B$25 -> 0 | AT42: =AT18*$B$25 -> 0 | AU42: =AU18*$B$25 -> 0 | AV42: =AV18*$B$25 -> 0 | AW42: =AW18*$B$25 -> 0 | ... BA42: =BA18*$B$25 -> 0 | BB42: =SUM(AP42:BA42) -> 0
A43: 157001150249 Hydrocodone/APAP GR | C43: ='Download COV'!D22 -> 0 | D43: ='Download COV'!E22 -> 0 | E43: ='Download COV'!F22 -> 0 | F43: ='Download COV'!G22 -> 0 | G43: =G19*$B$25 -> 0 | H43: =H19*$B$25 -> 0 | I43: =I19*$B$25 -> 0 | J43: =J19*$B$25 -> 0 | K43: =K19*$B$25 -> 0 | L43: =L19*$B$25 -> 0 | M43: =M19*$B$25 -> 0 | N43: =N19*$B$25 -> 0 | O43: =SUM(C43:N43) -> 0 | P43: =P19*$B$25 -> 0 | Q43: =Q19*$B$25 -> 0 | R43: =R19*$B$25 -> 0 | S43: =S19*$B$25 -> 0 | T43: =T19*$B$25 -> 0 | U43: =U19*$B$25 -> 0 | V43: =V19*$B$25 -> 0 | W43: =W19*$B$25 -> 0 | ... AA43: =AA19*$B$25 -> 0 | AB43: =SUM(P43:AA43) -> 0 | AC43: =AC19*$B$25 -> 0 | AD43: =AD19*$B$25 -> 0 | AE43: =AE19*$B$25 -> 0 | AF43: =AF19*$B$25 -> 3322.5465 | AG43: =AG19*$B$25 -> 6645.2295 | AH43: =AH19*$B$25 -> 9967.776 | AI43: =AI19*$B$25 -> 11710.608 | AJ43: =AJ19*$B$25 -> 13453.44 | ... AN43: =AN19*$B$25 -> 23043.657 | AO43: =SUM(AC43:AN43) -> 121579.32 | AP43: =AP19*$B$25 -> 24708.684 | AQ43: =AQ19*$B$25 -> 26919.029 | AR43: =AR19*$B$25 -> 29129.373 | AS43: =AS19*$B$25 -> 31381.214 | AT43: =AT19*$B$25 -> 33605.39 | AU43: =AU19*$B$25 -> 0 | AV43: =AV19*$B$25 -> 0 | AW43: =AW19*$B$25 -> 0 | ... BA43: =BA19*$B$25 -> 0 | BB43: =SUM(AP43:BA43) -> 145743.69
A44: 157001150250 Oxyocodone/APAP GR | C44: ='Download COV'!D23 -> 0 | D44: ='Download COV'!E23 -> 0 | E44: ='Download COV'!F23 -> 0 | F44: ='Download COV'!G23 -> 0 | G44: =G20*$B$25 -> 0 | H44: =H20*$B$25 -> 0 | I44: =I20*$B$25 -> 0 | J44: =J20*$B$25 -> 0 | K44: =K20*$B$25 -> 0 | L44: =L20*$B$25 -> 0 | M44: =M20*$B$25 -> 0 | N44: =N20*$B$25 -> 0 | O44: =SUM(C44:N44) -> 0 | P44: =P20*$B$25 -> 0 | Q44: =Q20*$B$25 -> 0 | R44: =R20*$B$25 -> 0 | S44: =S20*$B$25 -> 0 | T44: =T20*$B$25 -> 0 | U44: =U20*$B$25 -> 0 | V44: =V20*$B$25 -> 1795.7785 | W44: =W20*$B$25 -> 3591.6936 | ... AA44: =AA20*$B$25 -> 8226.2861 | AB44: =SUM(P44:AA44) -> 32614.989 | AC44: =AC20*$B$25 -> 9402.2125 | AD44: =AD20*$B$25 -> 10786.55 | AE44: =AE20*$B$25 -> 12171.024 | AF44: =AF20*$B$25 -> 13373.475 | AG44: =AG20*$B$25 -> 14575.926 | AH44: =AH20*$B$25 -> 15778.513 | AI44: =AI20*$B$25 -> 17121.843 | AJ44: =AJ20*$B$25 -> 18465.446 | ... AN44: =AN20*$B$25 -> 23781.185 | AO44: =SUM(AC44:AN44) -> 198855.19 | AP44: =AP20*$B$25 -> 23338.585 | AQ44: =AQ20*$B$25 -> 23391.724 | AR44: =AR20*$B$25 -> 23452.643 | AS44: =AS20*$B$25 -> 26266.883 | AT44: =AT20*$B$25 -> 27255.664 | AU44: =AU20*$B$25 -> 0 | AV44: =AV20*$B$25 -> 0 | AW44: =AW20*$B$25 -> 0 | ... BA44: =BA20*$B$25 -> 0 | BB44: =SUM(AP44:BA44) -> 123705.5
A45: Brands | B45: Total | C45: =SUM(C31:C44) -> 5080 | D45: =SUM(D31:D44) -> 6150 | E45: =SUM(E31:E44) -> 3126 | F45: =SUM(F31:F44) -> 30971.04 | G45: =SUM(G31:G44) -> 10042.873 | H45: =SUM(H31:H44) -> 7818.1368 | I45: =SUM(I31:I44) -> 8960.5236 | J45: =SUM(J31:J44) -> 10615.76 | ... BB45: =SUM(BB31:BB44) -> 288349.8
A48: Calculated Freight per Bottle | C48: Oct | D48: Nov | E48: Dec | F48: Jan | G48: Feb | H48: Mar | I48: Apr | J48: May | K48: =K30 -> Jun | L48: =L30 -> Jul | M48: =M30 -> Aug | N48: =N30 -> Sep | O48: YTD FY13 | P48: Oct | Q48: Nov | R48: Dec | S48: Jan | T48: Feb | U48: Mar | V48: Apr | W48: May | X48: Jun | Y48: Jul | Z48: Aug | AA48: Sep | AB48: =AB30 -> WF FY14 | AC48: Oct | AD48: Nov | AE48: Dec | AF48: Jan | AG48: Feb | AH48: Mar | AI48: Apr | AJ48: May | AK48: Jun | AL48: Jul | AM48: Aug | AN48: Sep | AO48: =AO30 -> WF FY15 | AP48: Oct | AQ48: Nov | AR48: Dec | AS48: Jan | AT48: Feb | AU48: Mar | AV48: Apr | AW48: May | AX48: Jun | AY48: Jul | AZ48: Aug | BA48: Sep | BB48: =BB30 -> WF FY16
A49: 157001150245 Tofranil-PM/ImipraPam Frt Exp | C49: =IF(ISERROR(C31/C7)=TRUE,0,(C31/C7)) -> 0 | D49: =IF(ISERROR(D31/D7)=TRUE,0,(D31/D7)) -> 0 | E49: =IF(ISERROR(E31/E7)=TRUE,0,(E31/E7)) -> 0.078651391 | F49: =IF(ISERROR(F31/F7)=TRUE,0,(F31/F7)) -> 0.19166587 | G49: =IF(ISERROR(G31/G7)=TRUE,0,(G31/G7)) -> 0.1365 | H49: =IF(ISERROR(H31/H7)=TRUE,0,(H31/H7)) -> 0.1365 | I49: =IF(ISERROR(I31/I7)=TRUE,0,(I31/I7)) -> 0.1365 | J49: =IF(ISERROR(J31/J7)=TRUE,0,(J31/J7)) -> 0.1365 | ... N49: =IF(ISERROR(N31/N7)=TRUE,0,(N31/N7)) -> 0.1365 | O49: =IF(ISERROR(SUM(C31:N31)/(SUM(C7:N7)))=TRUE,0,(SUM(C31:N31)/(SUM(C7:N7)))) -> 0.11490125 | P49: =IF(ISERROR(P31/P7)=TRUE,0,(P31/P7)) -> 0.1365 | Q49: =IF(ISERROR(Q31/Q7)=TRUE,0,(Q31/Q7)) -> 0.1365 | R49: =IF(ISERROR(R31/R7)=TRUE,0,(R31/R7)) -> 0.1365 | S49: =IF(ISERROR(S31/S7)=TRUE,0,(S31/S7)) -> 0.1365 | T49: =IF(ISERROR(T31/T7)=TRUE,0,(T31/T7)) -> 0.1365 | U49: =IF(ISERROR(U31/U7)=TRUE,0,(U31/U7)) -> 0.1365 | V49: =IF(ISERROR(V31/V7)=TRUE,0,(V31/V7)) -> 0.1365 | W49: =IF(ISERROR(W31/W7)=TRUE,0,(W31/W7)) -> 0.1365 | ... BB49: =IF(ISERROR(BB31/BB7)=TRUE,0,(BB31/BB7)) -> 0.1365
A50: 157001150225 Frt Exp-CNS Non-Promoted Prod | C50: =IF(ISERROR(C32/C8)=TRUE,0,(C32/C8)) -> 0.1951754 | D50: =IF(ISERROR(D32/D8)=TRUE,0,(D32/D8)) -> 0.18886502 | E50: =IF(ISERROR(E32/E8)=TRUE,0,(E32/E8)) -> 0.077148618 | F50: =IF(ISERROR(F32/F8)=TRUE,0,(F32/F8)) -> 0.19226821 | G50: =IF(ISERROR(G32/G8)=TRUE,0,(G32/G8)) -> 0.1365 | H50: =IF(ISERROR(H32/H8)=TRUE,0,(H32/H8)) -> 0.1365 | I50: =IF(ISERROR(I32/I8)=TRUE,0,(I32/I8)) -> 0.1365 | J50: =IF(ISERROR(J32/J8)=TRUE,0,(J32/J8)) -> 0.1365 | ... N50: =IF(ISERROR(N32/N8)=TRUE,0,(N32/N8)) -> 0.1365 | O50: =IF(ISERROR(SUM(C32:N32)/(SUM(C8:N8)))=TRUE,0,(SUM(C32:N32)/(SUM(C8:N8)))) -> 0.141447 | P50: =IF(ISERROR(P32/P8)=TRUE,0,(P32/P8)) -> 0.1365 | Q50: =IF(ISERROR(Q32/Q8)=TRUE,0,(Q32/Q8)) -> 0.1365 | R50: =IF(ISERROR(R32/R8)=TRUE,0,(R32/R8)) -> 0.1365 | S50: =IF(ISERROR(S32/S8)=TRUE,0,(S32/S8)) -> 0.1365 | T50: =IF(ISERROR(T32/T8)=TRUE,0,(T32/T8)) -> 0.1365 | U50: =IF(ISERROR(U32/U8)=TRUE,0,(U32/U8)) -> 0.1365 | V50: =IF(ISERROR(V32/V8)=TRUE,0,(V32/V8)) -> 0.1365 | W50: =IF(ISERROR(W32/W8)=TRUE,0,(W32/W8)) -> 0.1365 | ... BB50: =IF(ISERROR(BB32/BB8)=TRUE,0,(BB32/BB8)) -> 0.1365
A52: 157001150251 Pennsaid Frt Expense | C52: =IF(ISERROR(C34/C10)=TRUE,0,(C34/C10)) -> 0.18241758 | D52: =IF(ISERROR(D34/D10)=TRUE,0,(D34/D10)) -> 0.17720075 | E52: =IF(ISERROR(E34/E10)=TRUE,0,(E34/E10)) -> 0.075124808 | F52: =IF(ISERROR(F34/F10)=TRUE,0,(F34/F10)) -> 0.19220169 | G52: =IF(ISERROR(G34/G10)=TRUE,0,(G34/G10)) -> 0.1365 | H52: =IF(ISERROR(H34/H10)=TRUE,0,(H34/H10)) -> 0.1365 | I52: =IF(ISERROR(I34/I10)=TRUE,0,(I34/I10)) -> 0.1365 | J52: =IF(ISERROR(J34/J10)=TRUE,0,(J34/J10)) -> 0.1365 | ... N52: =IF(ISERROR(N34/N10)=TRUE,0,(N34/N10)) -> 0.1365 | O52: =IF(ISERROR(SUM(C34:N34)/(SUM(C10:N10)))=TRUE,0,(SUM(C34:N34)/(SUM(C10:N10)))) -> 0.13852839 | P52: =IF(ISERROR(P34/P10)=TRUE,0,(P34/P10)) -> 0.1365 | Q52: =IF(ISERROR(Q34/Q10)=TRUE,0,(Q34/Q10)) -> 0.1365 | R52: =IF(ISERROR(R34/R10)=TRUE,0,(R34/R10)) -> 0.1365 | S52: =IF(ISERROR(S34/S10)=TRUE,0,(S34/S10)) -> 0.1365 | T52: =IF(ISERROR(T34/T10)=TRUE,0,(T34/T10)) -> 0.1365 | U52: =IF(ISERROR(U34/U10)=TRUE,0,(U34/U10)) -> 0.1365 | V52: =IF(ISERROR(V34/V10)=TRUE,0,(V34/V10)) -> 0.1365 | W52: =IF(ISERROR(W34/W10)=TRUE,0,(W34/W10)) -> 0.1365 | ... BB52: =IF(ISERROR(BB34/BB10)=TRUE,0,(BB34/BB10)) -> 0
A53: 157001150255 Pennsaid 2% Pump Frt Expense | C53: =IF(ISERROR(C35/C11)=TRUE,0,(C35/C11)) -> 0 | D53: =IF(ISERROR(D35/D11)=TRUE,0,(D35/D11)) -> 0 | E53: =IF(ISERROR(E35/E11)=TRUE,0,(E35/E11)) -> 0 | F53: =IF(ISERROR(F35/F11)=TRUE,0,(F35/F11)) -> 0 | G53: =IF(ISERROR(G35/G11)=TRUE,0,(G35/G11)) -> 0 | H53: =IF(ISERROR(H35/H11)=TRUE,0,(H35/H11)) -> 0 | I53: =IF(ISERROR(I35/I11)=TRUE,0,(I35/I11)) -> 0 | J53: =IF(ISERROR(J35/J11)=TRUE,0,(J35/J11)) -> 0 | ... N53: =IF(ISERROR(N35/N11)=TRUE,0,(N35/N11)) -> 0 | O53: =IF(ISERROR(SUM(C35:N35)/(SUM(C11:N11)))=TRUE,0,(SUM(C35:N35)/(SUM(C11:N11)))) -> 0 | P53: =IF(ISERROR(P35/P11)=TRUE,0,(P35/P11)) -> 0.1365 | Q53: =IF(ISERROR(Q35/Q11)=TRUE,0,(Q35/Q11)) -> 0.1365 | R53: =IF(ISERROR(R35/R11)=TRUE,0,(R35/R11)) -> 0.1365 | S53: =IF(ISERROR(S35/S11)=TRUE,0,(S35/S11)) -> 0.1365 | T53: =IF(ISERROR(T35/T11)=TRUE,0,(T35/T11)) -> 0.1365 | U53: =IF(ISERROR(U35/U11)=TRUE,0,(U35/U11)) -> 0.1365 | V53: =IF(ISERROR(V35/V11)=TRUE,0,(V35/V11)) -> 0.1365 | W53: =IF(ISERROR(W35/W11)=TRUE,0,(W35/W11)) -> 0.1365 | ... BB53: =IF(ISERROR(BB35/BB11)=TRUE,0,(BB35/BB11)) -> 0.1365
A54: 157001150256 Diclofenac 2% Pump Frt Exp | C54: =IF(ISERROR(C36/C12)=TRUE,0,(C36/C12)) -> 0 | D54: =IF(ISERROR(D36/D12)=TRUE,0,(D36/D12)) -> 0 | E54: =IF(ISERROR(E36/E12)=TRUE,0,(E36/E12)) -> 0 | F54: =IF(ISERROR(F36/F12)=TRUE,0,(F36/F12)) -> 0 | G54: =IF(ISERROR(G36/G12)=TRUE,0,(G36/G12)) -> 0 | H54: =IF(ISERROR(H36/H12)=TRUE,0,(H36/H12)) -> 0 | I54: =IF(ISERROR(I36/I12)=TRUE,0,(I36/I12)) -> 0 | J54: =IF(ISERROR(J36/J12)=TRUE,0,(J36/J12)) -> 0 | ... N54: =IF(ISERROR(N36/N12)=TRUE,0,(N36/N12)) -> 0 | O54: =IF(ISERROR(SUM(C36:N36)/(SUM(C12:N12)))=TRUE,0,(SUM(C36:N36)/(SUM(C12:N12)))) -> 0 | P54: =IF(ISERROR(P36/P12)=TRUE,0,(P36/P12)) -> 0 | Q54: =IF(ISERROR(Q36/Q12)=TRUE,0,(Q36/Q12)) -> 0 | R54: =IF(ISERROR(R36/R12)=TRUE,0,(R36/R12)) -> 0 | S54: =IF(ISERROR(S36/S12)=TRUE,0,(S36/S12)) -> 0 | T54: =IF(ISERROR(T36/T12)=TRUE,0,(T36/T12)) -> 0 | U54: =IF(ISERROR(U36/U12)=TRUE,0,(U36/U12)) -> 0 | V54: =IF(ISERROR(V36/V12)=TRUE,0,(V36/V12)) -> 0 | W54: =IF(ISERROR(W36/W12)=TRUE,0,(W36/W12)) -> 0 | ... BB54: =IF(ISERROR(BB36/BB12)=TRUE,0,(BB36/BB12)) -> 0
A55: 157001150252 Exalgo Freight Exp | C55: =IF(ISERROR(C37/C13)=TRUE,0,(C37/C13)) -> 0.19231792 | D55: =IF(ISERROR(D37/D13)=TRUE,0,(D37/D13)) -> 0.19190998 | E55: =IF(ISERROR(E37/E13)=TRUE,0,(E37/E13)) -> 0.075031928 | F55: =IF(ISERROR(F37/F13)=TRUE,0,(F37/F13)) -> 0.2129085 | G55: =IF(ISERROR(G37/G13)=TRUE,0,(G37/G13)) -> 0.15058127 | H55: =IF(ISERROR(H37/H13)=TRUE,0,(H37/H13)) -> 0.15086902 | I55: =IF(ISERROR(I37/I13)=TRUE,0,(I37/I13)) -> 0.16104269 | J55: =IF(ISERROR(J37/J13)=TRUE,0,(J37/J13)) -> 0.16433909 | ... N55: =IF(ISERROR(N37/N13)=TRUE,0,(N37/N13)) -> 0.19274357 | O55: =IF(ISERROR(SUM(C37:N37)/(SUM(C13:N13)))=TRUE,0,(SUM(C37:N37)/(SUM(C13:N13)))) -> 0.1672548 | P55: =IF(ISERROR(P37/P13)=TRUE,0,(P37/P13)) -> 0.20542591 | Q55: =IF(ISERROR(Q37/Q13)=TRUE,0,(Q37/Q13)) -> 0.19607774 | R55: =IF(ISERROR(R37/R13)=TRUE,0,(R37/R13)) -> 0.27878151 | S55: =IF(ISERROR(S37/S13)=TRUE,0,(S37/S13)) -> 0.56338554 | T55: =IF(ISERROR(T37/T13)=TRUE,0,(T37/T13)) -> 0.51417867 | U55: =IF(ISERROR(U37/U13)=TRUE,0,(U37/U13)) -> 0.7730118 | V55: =IF(ISERROR(V37/V13)=TRUE,0,(V37/V13)) -> 0.764127 | W55: =IF(ISERROR(W37/W13)=TRUE,0,(W37/W13)) -> 0.77660227 | ... BB55: =IF(ISERROR(BB37/BB13)=TRUE,0,(BB37/BB13)) -> 0.16365732
A57: 157001150258 Hydromorphone ER Frt Exp | C57: =IF(ISERROR(C39/C15)=TRUE,0,(C39/C15)) -> 0 | D57: =IF(ISERROR(D39/D15)=TRUE,0,(D39/D15)) -> 0 | E57: =IF(ISERROR(E39/E15)=TRUE,0,(E39/E15)) -> 0 | F57: =IF(ISERROR(F39/F15)=TRUE,0,(F39/F15)) -> 0 | G57: =IF(ISERROR(G39/G15)=TRUE,0,(G39/G15)) -> 0 | H57: =IF(ISERROR(H39/H15)=TRUE,0,(H39/H15)) -> 0 | I57: =IF(ISERROR(I39/I15)=TRUE,0,(I39/I15)) -> 0 | J57: =IF(ISERROR(J39/J15)=TRUE,0,(J39/J15)) -> 0 | ... N57: =IF(ISERROR(N39/N15)=TRUE,0,(N39/N15)) -> 0 | O57: =IF(ISERROR(SUM(C39:N39)/(SUM(C15:N15)))=TRUE,0,(SUM(C39:N39)/(SUM(C15:N15)))) -> 0 | P57: =IF(ISERROR(P39/P15)=TRUE,0,(P39/P15)) -> 0 | Q57: =IF(ISERROR(Q39/Q15)=TRUE,0,(Q39/Q15)) -> 0 | R57: =IF(ISERROR(R39/R15)=TRUE,0,(R39/R15)) -> 0 | S57: =IF(ISERROR(S39/S15)=TRUE,0,(S39/S15)) -> 0 | T57: =IF(ISERROR(T39/T15)=TRUE,0,(T39/T15)) -> 0 | U57: =IF(ISERROR(U39/U15)=TRUE,0,(U39/U15)) -> 0 | V57: =IF(ISERROR(V39/V15)=TRUE,0,(V39/V15)) -> 0.1365 | W57: =IF(ISERROR(W39/W15)=TRUE,0,(W39/W15)) -> 0.1365 | ... BB57: =IF(ISERROR(BB39/BB15)=TRUE,0,(BB39/BB15)) -> 0.1638329
A59: 157001150268 Roxicodone-Freight | C59: =IF(ISERROR(C41/C17)=TRUE,0,(C41/C17)) -> 0.18251361 | D59: =IF(ISERROR(D41/D17)=TRUE,0,(D41/D17)) -> 0.17708322 | E59: =IF(ISERROR(E41/E17)=TRUE,0,(E41/E17)) -> 0.073179195 | F59: =IF(ISERROR(F41/F17)=TRUE,0,(F41/F17)) -> 0.19226179 | G59: =IF(ISERROR(G41/G17)=TRUE,0,(G41/G17)) -> 0.1365 | H59: =IF(ISERROR(H41/H17)=TRUE,0,(H41/H17)) -> 0.1365 | I59: =IF(ISERROR(I41/I17)=TRUE,0,(I41/I17)) -> 0.1365 | J59: =IF(ISERROR(J41/J17)=TRUE,0,(J41/J17)) -> 0.1365 | ... N59: =IF(ISERROR(N41/N17)=TRUE,0,(N41/N17)) -> 0.1365 | O59: =IF(ISERROR(SUM(C41:N41)/(SUM(C17:N17)))=TRUE,0,(SUM(C41:N41)/(SUM(C17:N17)))) -> 0.14344935 | P59: =IF(ISERROR(P41/P17)=TRUE,0,(P41/P17)) -> 0.1365 | Q59: =IF(ISERROR(Q41/Q17)=TRUE,0,(Q41/Q17)) -> 0.1365 | R59: =IF(ISERROR(R41/R17)=TRUE,0,(R41/R17)) -> 0.1365 | S59: =IF(ISERROR(S41/S17)=TRUE,0,(S41/S17)) -> 0.1365 | T59: =IF(ISERROR(T41/T17)=TRUE,0,(T41/T17)) -> 0.1365 | U59: =IF(ISERROR(U41/U17)=TRUE,0,(U41/U17)) -> 0.1365 | V59: =IF(ISERROR(V41/V17)=TRUE,0,(V41/V17)) -> 0.1365 | W59: =IF(ISERROR(W41/W17)=TRUE,0,(W41/W17)) -> 0.1365 | ... BB59: =IF(ISERROR(BB41/BB17)=TRUE,0,(BB41/BB17)) -> 0.1365
A60: 157210151269 Intrathecal-Freight-General | C60: =IF(ISERROR(C42/C18)=TRUE,0,(C42/C18)) -> 0 | D60: =IF(ISERROR(D42/D18)=TRUE,0,(D42/D18)) -> 0 | E60: =IF(ISERROR(E42/E18)=TRUE,0,(E42/E18)) -> 0 | F60: =IF(ISERROR(F42/F18)=TRUE,0,(F42/F18)) -> 3.8960277 | G60: =IF(ISERROR(G42/G18)=TRUE,0,(G42/G18)) -> 0.1931682 | H60: =IF(ISERROR(H42/H18)=TRUE,0,(H42/H18)) -> 0.18408327 | I60: =IF(ISERROR(I42/I18)=TRUE,0,(I42/I18)) -> 0.21497193 | J60: =IF(ISERROR(J42/J18)=TRUE,0,(J42/J18)) -> 0.16155845 | ... N60: =IF(ISERROR(N42/N18)=TRUE,0,(N42/N18)) -> 0.17997369 | O60: =IF(ISERROR(SUM(C42:N42)/(SUM(C18:N18)))=TRUE,0,(SUM(C42:N42)/(SUM(C18:N18)))) -> 0.31755123 | P60: =IF(ISERROR(P42/P18)=TRUE,0,(P42/P18)) -> 0.70717058 | Q60: =IF(ISERROR(Q42/Q18)=TRUE,0,(Q42/Q18)) -> 0.56858298 | R60: =IF(ISERROR(R42/R18)=TRUE,0,(R42/R18)) -> 0.70333467 | S60: =IF(ISERROR(S42/S18)=TRUE,0,(S42/S18)) -> 0.6997949 | T60: =IF(ISERROR(T42/T18)=TRUE,0,(T42/T18)) -> 0.56164704 | U60: =IF(ISERROR(U42/U18)=TRUE,0,(U42/U18)) -> 0.68789067 | V60: =IF(ISERROR(V42/V18)=TRUE,0,(V42/V18)) -> 0.68628001 | W60: =IF(ISERROR(W42/W18)=TRUE,0,(W42/W18)) -> 0.55447854 | ... BB60: =IF(ISERROR(BB42/BB18)=TRUE,0,(BB42/BB18)) -> 0
A61: 157001150249 Hydrocodone/APAP GR | C61: =IF(ISERROR(C43/C19)=TRUE,0,(C43/C19)) -> 0 | D61: =IF(ISERROR(D43/D19)=TRUE,0,(D43/D19)) -> 0 | E61: =IF(ISERROR(E43/E19)=TRUE,0,(E43/E19)) -> 0 | F61: =IF(ISERROR(F43/F19)=TRUE,0,(F43/F19)) -> 0 | G61: =IF(ISERROR(G43/G19)=TRUE,0,(G43/G19)) -> 0 | H61: =IF(ISERROR(H43/H19)=TRUE,0,(H43/H19)) -> 0 | I61: =IF(ISERROR(I43/I19)=TRUE,0,(I43/I19)) -> 0 | J61: =IF(ISERROR(J43/J19)=TRUE,0,(J43/J19)) -> 0 | ... N61: =IF(ISERROR(N43/N19)=TRUE,0,(N43/N19)) -> 0 | O61: =IF(ISERROR(SUM(C43:N43)/(SUM(C19:N19)))=TRUE,0,(SUM(C43:N43)/(SUM(C19:N19)))) -> 0 | P61: =IF(ISERROR(P43/P19)=TRUE,0,(P43/P19)) -> 0 | Q61: =IF(ISERROR(Q43/Q19)=TRUE,0,(Q43/Q19)) -> 0 | R61: =IF(ISERROR(R43/R19)=TRUE,0,(R43/R19)) -> 0 | S61: =IF(ISERROR(S43/S19)=TRUE,0,(S43/S19)) -> 0 | T61: =IF(ISERROR(T43/T19)=TRUE,0,(T43/T19)) -> 0 | U61: =IF(ISERROR(U43/U19)=TRUE,0,(U43/U19)) -> 0 | V61: =IF(ISERROR(V43/V19)=TRUE,0,(V43/V19)) -> 0 | W61: =IF(ISERROR(W43/W19)=TRUE,0,(W43/W19)) -> 0 | ... BB61: =IF(ISERROR(BB43/BB19)=TRUE,0,(BB43/BB19)) -> 0.1365
A62: 157001150250 Oxyocodone/APAP GR | C62: =IF(ISERROR(C44/C20)=TRUE,0,(C44/C20)) -> 0 | D62: =IF(ISERROR(D44/D20)=TRUE,0,(D44/D20)) -> 0 | E62: =IF(ISERROR(E44/E20)=TRUE,0,(E44/E20)) -> 0 | F62: =IF(ISERROR(F44/F20)=TRUE,0,(F44/F20)) -> 0 | G62: =IF(ISERROR(G44/G20)=TRUE,0,(G44/G20)) -> 0 | H62: =IF(ISERROR(H44/H20)=TRUE,0,(H44/H20)) -> 0 | I62: =IF(ISERROR(I44/I20)=TRUE,0,(I44/I20)) -> 0 | J62: =IF(ISERROR(J44/J20)=TRUE,0,(J44/J20)) -> 0 | ... N62: =IF(ISERROR(N44/N20)=TRUE,0,(N44/N20)) -> 0 | O62: =IF(ISERROR(SUM(C44:N44)/(SUM(C20:N20)))=TRUE,0,(SUM(C44:N44)/(SUM(C20:N20)))) -> 0 | P62: =IF(ISERROR(P44/P20)=TRUE,0,(P44/P20)) -> 0 | Q62: =IF(ISERROR(Q44/Q20)=TRUE,0,(Q44/Q20)) -> 0 | R62: =IF(ISERROR(R44/R20)=TRUE,0,(R44/R20)) -> 0 | S62: =IF(ISERROR(S44/S20)=TRUE,0,(S44/S20)) -> 0 | T62: =IF(ISERROR(T44/T20)=TRUE,0,(T44/T20)) -> 0 | U62: =IF(ISERROR(U44/U20)=TRUE,0,(U44/U20)) -> 0 | V62: =IF(ISERROR(V44/V20)=TRUE,0,(V44/V20)) -> 0.1365 | W62: =IF(ISERROR(W44/W20)=TRUE,0,(W44/W20)) -> 0.1365 | ... BB62: =IF(ISERROR(BB44/BB20)=TRUE,0,(BB44/BB20)) -> 0.1365
A63: Brands | B63: Total | C63: =IF(ISERROR(C45/C22)=TRUE,0,(C45/C22)) -> 0.14474993 | D63: =IF(ISERROR(D45/D22)=TRUE,0,(D45/D22)) -> 0.13607698 | E63: =IF(ISERROR(E45/E22)=TRUE,0,(E45/E22)) -> 0.060673089 | F63: =IF(ISERROR(F45/F22)=TRUE,0,(F45/F22)) -> 0.93123554 | G63: =IF(ISERROR(G45/G22)=TRUE,0,(G45/G22)) -> 0.15106177 | H63: =IF(ISERROR(H45/H22)=TRUE,0,(H45/H22)) -> 0.15015215 | I63: =IF(ISERROR(I45/I22)=TRUE,0,(I45/I22)) -> 0.1519782 | J63: =IF(ISERROR(J45/J22)=TRUE,0,(J45/J22)) -> 0.14167495 | ... N63: =IF(ISERROR(N45/N22)=TRUE,0,(N45/N22)) -> 0.14696181 | O63: =IF(ISERROR(SUM(C45:N45)/(SUM(C22:N22)))=TRUE,0,(SUM(C45:N45)/(SUM(C22:N22)))) -> 0.18017982 | P63: =IF(ISERROR(P45/P22)=TRUE,0,(P45/P22)) -> 0.19353231 | Q63: =IF(ISERROR(Q45/Q22)=TRUE,0,(Q45/Q22)) -> 0.19700465 | R63: =IF(ISERROR(R45/R22)=TRUE,0,(R45/R22)) -> 0.23444433 | S63: =IF(ISERROR(S45/S22)=TRUE,0,(S45/S22)) -> 0.22359454 | T63: =IF(ISERROR(T45/T22)=TRUE,0,(T45/T22)) -> 0.21156393 | U63: =IF(ISERROR(U45/U22)=TRUE,0,(U45/U22)) -> 0.23857202 | V63: =IF(ISERROR(V45/V22)=TRUE,0,(V45/V22)) -> 0.20438235 | W63: =IF(ISERROR(W45/W22)=TRUE,0,(W45/W22)) -> 0.18580496 | ... BB63: =IF(ISERROR(BB45/BB22)=TRUE,0,(BB45/BB22)) -> 0.1365

Sheet Pharm Demand b4
A1: Outfreight Expense - 7171
C2: FY10 Working Forecast
C3: Oct | D3: Nov | E3: Dec | F3: Jan | G3: Feb | H3: Mar | I3: Apr | J3: May | K3: Jun | L3: Jul | M3: Aug | N3: Sep | O3: Full Year
A4: 157001000211 Hydrocodone Products | B4: Sales Volume | C4: 1345130 | D4: 1471821 | E4: 1346264 | F4: 1200818 | G4: 1728087 | H4: 1336101 | I4: 1408275 | J4: 1720179 | K4: 1431618 | L4: 1436689 | M4: 1701222 | N4: 1472273 | O4: 17598477
A5: 157001000210 Oxycodone Products | B5: Sales Volume | C5: 568180.11 | D5: 724518.11 | E5: 557520.11 | F5: 477505.07 | G5: 697911.07 | H5: 477342.07 | I5: 516738.48 | J5: 690798.48 | K5: 520504.48 | L5: 537789.11 | M5: 689765.11 | N5: 565202.11 | O5: 7023774.3
A6: 157001000244 Oxycodone APAP Products | B6: Sales Volume | C6: 817000 | D6: 903185 | E6: 791936 | F6: 724054 | G6: 1015560 | H6: 783302 | I6: 826298 | J6: 1027937 | K6: 839548 | L6: 842285 | M6: 995584 | N6: 860878 | O6: 10427567
A7: 157001000222 ADHD | B7: Sales Volume | C7: 147710 | D7: 157485 | E7: 139903 | F7: 120838 | G7: 174345 | H7: 135215 | I7: 141377 | J7: 169676 | K7: 141415 | L7: 140762 | M7: 163700 | N7: 141123 | O7: 1773549
A8: 157001000227 Oxycodone ER | B8: Sales Volume | C8: 0 | D8: 0 | E8: 0 | F8: 0 | G8: 0 | H8: 0 | I8: 0 | J8: 0 | K8: 0 | L8: 0 | M8: 0 | N8: 0 | O8: 0
A9: Morphine ER | B9: Sales Volume | C9: 129558 | D9: 171034 | E9: 130265 | F9: 131991 | G9: 180135 | H9: 128773 | I9: 135659 | J9: 177744 | K9: 137777 | L9: 138205 | M9: 176268 | N9: 147382 | O9: 1784791
A10: Hydromorphone | B10: Sales Volume | C10: 66453.709 | D10: 94070.588 | E10: 253332.41 | F10: 152406 | G10: 208176 | H10: 148950 | I10: 157051 | J10: 205966 | K10: 159794 | L10: 160438 | M10: 204801 | N10: 171401 | O10: 1982839.7
A11: Methadone Generic | B11: Sales Volume | C11: 386382 | D11: 503539 | E11: 380155 | F11: 380399 | G11: 514297 | H11: 364256 | I11: 379759 | J11: 491787 | K11: 377625 | L11: 374752 | M11: 472544 | N11: 391042 | O11: 5016537
A12: APAP/Codeine | B12: Sales Volume | C12: 87117 | D12: 93644 | E12: 80868 | F12: 71566 | G12: 100949 | H12: 77147 | I12: 80078 | J12: 95666 | K12: 75598 | L12: 78061 | M12: 91650 | N12: 76961 | O12: 1009305
A13: APAP/Propoxyphene | B13: Sales Volume | C13: 0 | D13: 0 | E13: 0 | F13: 0 | G13: 0 | H13: 0 | I13: 0 | J13: 0 | K13: 0 | L13: 0 | M13: 0 | N13: 0 | O13: 0
A14: Fentanyl Lozenge | B14: Sales Volume | C14: 0 | D14: 31802 | E14: 14095 | F14: 13762 | G14: 19153 | H14: 13618 | I14: 14238 | J14: 18507 | K14: 14238 | L14: 14170 | M14: 17935 | N14: 14878 | O14: 186396
A15: Fentanyl Patch | B15: Sales Volume | C15: 0 | D15: 0 | E15: 0 | F15: 0 | G15: 0 | H15: 0 | I15: 114361 | J15: 148669 | K15: 114361 | L15: 113817 | M15: 144066 | N15: 119508 | O15: 754782
... A26: International | B26: Sales Volume | C26: 19000 | D26: 0 | E26: 0 | F26: 0 | G26: 0 | H26: 26000 | I26: 17200 | J26: 0 | K26: 800 | L26: 0 | M26: 0 | N26: 25400 | O26: 88400
O27: =SUM(O4:O26) -> 50288941
A28: Freight per bottle for INTL | B28: 1.7 | C28: (FY10 forecast estimate)
A29: Freight per bottle, except AT | B29: =0.09*1.07*1.052 -> 0.1013076 | C29: (FY09 forecast = .09 + 7% inflation increase + 5% addl per JC)
A30: Freight per bottle for AT | B30: =3.45*1.07*1.052 -> 3.883458 | C30: (FY09 forecast = 3.45 + 7% inflation increase + 5% addl per JC)
A31: Freight for Fentanyl Lozenge and Patch | B31: 50% of bgt | C31: (estimate) | P31: FYI only
O32: FY10 | P32: FY09
A33: 157001150211 Frt Exp-Hydrocodone Products | B33: Dollars | C33: =C4*$B$29 -> 136271.89 | D33: =D4*$B$29 -> 149106.65 | E33: =E4*$B$29 -> 136386.77 | F33: =F4*$B$29 -> 121651.99 | G33: =G4*$B$29 -> 175068.35 | H33: =H4*$B$29 -> 135357.19 | I33: =I4*$B$29 -> 142668.96 | J33: =J4*$B$29 -> 174267.21 | ... M33: =M4*$B$29 -> 172346.72 | N33: =N4*$B$29-2372 -> 146780.44 | O33: =SUM(C33:N33) -> 1780487.5 | P33: 1604044.2
A34: 157001150210 Frt Exp-Oxycodone Products | B34: Dollars | C34: =C5*$B$29 -> 57560.964 | D34: =D5*$B$29 -> 73399.191 | E34: =E5*$B$29 -> 56481.025 | F34: =F5*$B$29 -> 48374.893 | G34: =G5*$B$29 -> 70703.696 | H34: =H5*$B$29 -> 48358.38 | I34: =I5*$B$29 -> 52349.535 | J34: =J5*$B$29 -> 69983.136 | ... N34: =N5*$B$29 -> 57259.269 | O34: =SUM(C34:N34) -> 711561.72 | P34: 939784.42
A35: 157001150244 Oxycodone APAP-Frt Exp | B35: Dollars | C35: =C6*$B$29 -> 82768.309 | D35: =D6*$B$29 -> 91499.505 | E35: =E6*$B$29 -> 80229.136 | F35: =F6*$B$29 -> 73352.173 | G35: =G6*$B$29 -> 102883.95 | H35: =H6*$B$29 -> 79354.446 | I35: =I6*$B$29 -> 83710.267 | J35: =J6*$B$29 -> 104137.83 | ... N35: =N6*$B$29 -> 87213.484 | O35: =SUM(C35:N35) -> 1056391.8 | P35: 1010573.7
A36: 157001150222 Frt Exp-ADHD | B36: Dollars | C36: =C7*$B$29 -> 14964.146 | D36: =D7*$B$29 -> 15954.427 | E36: =E7*$B$29 -> 14173.237 | F36: =F7*$B$29 -> 12241.808 | G36: =G7*$B$29 -> 17662.474 | H36: =H7*$B$29 -> 13698.307 | I36: =I7*$B$29 -> 14322.565 | J36: =J7*$B$29 -> 17189.468 | ... N36: =N7*$B$29 -> 14296.832 | O36: =SUM(C36:N36) -> 179673.99 | P36: 173266.69
A37: 157001150227 Oxycodone ER Products Freight | B37: Dollars | C37: =C8*$B$29 -> 0 | D37: =D8*$B$29 -> 0 | E37: =E8*$B$29 -> 0 | F37: =F8*$B$29 -> 0 | G37: =G8*$B$29 -> 0 | H37: =H8*$B$29 -> 0 | I37: =I8*$B$29 -> 0 | J37: =J8*$B$29 -> 0 | ... N37: =N8*$B$29 -> 0 | O37: =SUM(C37:N37) -> 0 | P37: 118511
A38: 157001150229 Morphine ER-Frt Exp | B38: Dollars | C38: =C9*$B$29 -> 13125.21 | D38: =D9*$B$29 -> 17327.044 | E38: =E9*$B$29 -> 13196.835 | F38: =F9*$B$29 -> 13371.691 | G38: =G9*$B$29 -> 18249.045 | H38: =H9*$B$29 -> 13045.684 | I38: =I9*$B$29 -> 13743.288 | J38: =J9*$B$29 -> 18006.818 | ... N38: =N9*$B$29 -> 14930.917 | O38: =SUM(C38:N38) -> 180812.89 | P38: 172797.05
A39: 157001150230 Hydromorphone-Frt Exp | B39: Dollars | C39: =C10*$B$29 -> 6732.2658 | D39: =D10*$B$29 -> 9530.0655 | E39: =E10*$B$29 -> 25664.499 | F39: =F10*$B$29 -> 15439.886 | G39: =G10*$B$29 -> 21089.811 | H39: =H10*$B$29 -> 15089.767 | I39: =I10*$B$29 -> 15910.46 | J39: =J10*$B$29 -> 20865.921 | ... N39: =N10*$B$29 -> 17364.224 | O39: =SUM(C39:N39) -> 200876.73 | P39: 191280.17
A40: 157001150231 Methadone Generics-Frt Exp | B40: Dollars | C40: =C11*$B$29 -> 39143.433 | D40: =D11*$B$29 -> 51012.328 | E40: =E11*$B$29 -> 38512.591 | F40: =F11*$B$29 -> 38537.31 | G40: =G11*$B$29 -> 52102.195 | H40: =H11*$B$29 -> 36901.901 | I40: =I11*$B$29 -> 38472.473 | J40: =J11*$B$29 -> 49821.761 | ... N40: =N11*$B$29 -> 39615.527 | O40: =SUM(C40:N40) -> 508213.32 | P40: 510997.11
A41: 157001150232 APAP Codeine-Frt Exp | B41: Dollars | C41: =C12*$B$29 -> 8825.6142 | D41: =D12*$B$29 -> 9486.8489 | E41: =E12*$B$29 -> 8192.543 | F41: =F12*$B$29 -> 7250.1797 | G41: =G12*$B$29 -> 10226.901 | H41: =H12*$B$29 -> 7815.5774 | I41: =I12*$B$29 -> 8112.51 | J41: =J12*$B$29 -> 9691.6929 | ... N41: =N12*$B$29 -> 7796.7342 | O41: =SUM(C41:N41) -> 102250.27 | P41: 103658.43
A42: 157001150233 APAP Propoxyphene-Frt Exp | B42: Dollars | C42: =C13*$B$29 -> 0 | D42: =D13*$B$29 -> 0 | E42: =E13*$B$29 -> 0 | F42: =F13*$B$29 -> 0 | G42: =G13*$B$29 -> 0 | H42: =H13*$B$29 -> 0 | I42: =I13*$B$29 -> 0 | J42: =J13*$B$29 -> 0 | ... N42: =N13*$B$29 -> 0 | O42: =SUM(C42:N42) -> 0 | P42: 51178.92
A43: 157001150234 Fentanyl Lozenge-Frt Exp | B43: Dollars | C43: 0 | D43: =44323*0.5 -> 22161.5 | E43: =31586*0.5 -> 15793 | F43: =32279*0.5 -> 16139.5 | G43: =32092*0.5 -> 16046 | H43: =31905*0.5 -> 15952.5 | I43: =31720*0.5 -> 15860 | J43: =31535*0.5 -> 15767.5 | K43: =31157*0.5 -> 15578.5 | L43: =31024*0.5 -> 15512 | M43: =30891*0.5 -> 15445.5 | N43: =30759*0.5 -> 15379.5 | O43: =SUM(C43:N43) -> 179635.5 | P43: 0
A44: 157001150236 Fentanyl Patch-Frt Exp | B44: Dollars | C44: 0 | D44: 0 | E44: 0 | F44: 0 | G44: 0 | H44: 0 | I44: =36813*0.5 -> 18406.5 | J44: =36813*0.5 -> 18406.5 | K44: =36813*0.5 -> 18406.5 | L44: =36813*0.5 -> 18406.5 | M44: =36813*0.5 -> 18406.5 | N44: =36813*0.5 -> 18406.5 | O44: =SUM(C44:N44) -> 110439 | P44: 0
A45: 157001150209 FREIGHT | B45: Dollars | C45: =C16*$B$29 -> 11874.061 | D45: =D16*$B$29 -> 14066.256 | E45: =E16*$B$29 -> 11486.357 | F45: =F16*$B$29 -> 10742.861 | G45: =G16*$B$29 -> 15063.528 | H45: =H16*$B$29 -> 11199.859 | I45: =I16*$B$29 -> 11765.561 | J45: =J16*$B$29 -> 14754.54 | ... N45: =N16*$B$29 -> 7509.4258 | O45: =SUM(C45:N45) -> 136425.58 | P45: 231446.72
A46: 157001150226 Zydus Freight Expense | B46: Dollars | C46: =C17*$B$29 -> 0 | D46: =D17*$B$29 -> 0 | E46: =E17*$B$29 -> 0 | F46: =F17*$B$29 -> 0 | G46: =G17*$B$29 -> 0 | H46: =H17*$B$29 -> 0 | I46: =I17*$B$29 -> 0 | J46: =J17*$B$29 -> 0 | ... N46: =N17*$B$29 -> 0 | O46: =SUM(C46:N46) -> 0 | P46: 59307.39
A47: 157001150246 Restoril/Temazepam Frt Expense | B47: Dollars | C47: =C18*$B$29 -> 725.76765 | D47: =D18*$B$29 -> 922.91224 | E47: =E18*$B$29 -> 669.64324 | F47: =F18*$B$29 -> 639.65619 | G47: =G18*$B$29 -> 949.55613 | H47: =H18*$B$29 -> 650.19218 | I47: =I18*$B$29 -> 664.27393 | J47: =J18*$B$29 -> 547.16235 | ... N47: =N18*$B$29 -> 404.92648 | O47: =SUM(C47:N47) -> 7435.9778 | P47: 14092.33
A48: 157001150245 Tofranil-PM/ImipraPam Frt Exp | B48: Dollars | C48: =C19*$B$29 -> 1104.8607 | D48: =D19*$B$29 -> 1285.4921 | E48: =E19*$B$29 -> 1046.8114 | F48: =F19*$B$29 -> 1005.174 | G48: =G19*$B$29 -> 1382.1396 | H48: =H19*$B$29 -> 1102.2267 | I48: =I19*$B$29 -> 1104.8607 | J48: =J19*$B$29 -> 1331.7897 | ... N48: =N19*$B$29 -> 1154.4001 | O48: =SUM(C48:N48) -> 14062.001 | P48: 13397.13
A49: 157001150225 Frt Exp-CNS Non-Promoted Prod | B49: Dollars | C49: =C20*$B$29 -> 700.64336 | D49: =D20*$B$29 -> 814.31049 | E49: =E20*$B$29 -> 651.30656 | F49: =F20*$B$29 -> 618.78682 | G49: =G20*$B$29 -> 839.33347 | H49: =H20*$B$29 -> 656.06802 | I49: =I20*$B$29 -> 646.34249 | J49: =J20*$B$29 -> 774.4966 | ... N49: =N20*$B$29 -> 629.1202 | O49: =SUM(C49:N49) -> 8318.1644 | P49: 10716.3
A50: 157001150224 Frt Exp-Other Brand Products | B50: Dollars | C50: =C21*$B$29 -> 85.199692 | D50: =D21*$B$29 -> 79.425158 | E50: =E21*$B$29 -> 54.706104 | F50: =F21*$B$29 -> 47.209342 | G50: =G21*$B$29 -> 61.493713 | H50: =H21*$B$29 -> 47.108034 | I50: =I21*$B$29 -> 46.905419 | J50: =J21*$B$29 -> 56.630948 | ... N50: =N21*$B$29 -> 49.134186 | O50: =SUM(C50:N50) -> 678.25438 | P50: 1534.96
A51: 157001150235 Tussicaps-Frt Exp | B51: Dollars | C51: =C22*$B$29 -> 323.29852 | D51: =D22*$B$29 -> 376.74158 | E51: =E22*$B$29 -> 546.25986 | F51: =F22*$B$29 -> 793.92523 | G51: =G22*$B$29 -> 1088.5501 | H51: =H22*$B$29 -> 804.08551 | I51: =I22*$B$29 -> 796.82196 | J51: =J22*$B$29 -> 660.31472 | ... N51: =N22*$B$29 -> 668.7085 | O51: =SUM(C51:N51) -> 7457.5279 | P51: 13407.381
A52: 157001150251 Pennsaid Frt Expense | B52: Dollars | C52: =C23*$B$29 -> 0 | D52: =D23*$B$29 -> 0 | E52: =E23*$B$29 -> 0 | F52: =F23*$B$29 -> 0 | G52: =G23*$B$29 -> 5084.5271 | H52: =H23*$B$29 -> 127.54627 | I52: =I23*$B$29 -> 381.52442 | J52: =J23*$B$29 -> 822.11117 | ... N52: =N23*$B$29 -> 1645.742 | O52: =SUM(C52:N52) -> 11778.123 | P52: 0
A53: 157001150252 Exalgo Freight Exp | B53: Dollars | C53: =C24*$B$29 -> 0 | D53: =D24*$B$29 -> 0 | E53: =E24*$B$29 -> 0 | F53: =F24*$B$29 -> 0 | G53: =G24*$B$29 -> 2836.6128 | H53: =H24*$B$29 -> 0 | I53: =I24*$B$29 -> 1148.9295 | J53: =J24*$B$29 -> 226.92902 | ... N53: =N24*$B$29 -> 292.17112 | O53: =SUM(C53:N53) -> 5115.3246 | P53: 0
A54: 157001150221 Frt Exp-ADDICTION TREATMENT | B54: Dollars | C54: =C25*$B$30 -> 224902.7 | D54: =D25*$B$30 -> 288047.73 | E54: =E25*$B$30 -> 224479.41 | F54: =F25*$B$30 -> 223834.75 | G54: =G25*$B$30 -> 281139.06 | H54: =H25*$B$30 -> 216883.36 | I54: =I25*$B$30 -> 218413.44 | J54: =J25*$B$30 -> 292894.29 | ... N54: =N25*$B$30 -> 230098.77 | O54: =SUM(C54:N54) -> 2930072.9 | P54: 2471843.5
A55: 161001151653 Europe Export Dosage Narc | B55: Dollars | C55: 0 | D55: 0 | E55: 0 | F55: 0 | G55: 0 | H55: 0 | I55: 0 | J55: 0 | K55: 0 | L55: 0 | M55: 0 | N55: 0 | O55: =SUM(C55:N55) -> 0 | P55: -1173.8
A56: 161001151654 China Export Dosage Narc | B56: Dollars | C56: =C26*$B$28 -> 32300 | D56: =D26*$B$28 -> 0 | E56: =E26*$B$28 -> 0 | F56: =F26*$B$28 -> 0 | G56: =G26*$B$28 -> 0 | H56: =H26*$B$28 -> 44200 | I56: =I26*$B$28 -> 29240 | J56: =J26*$B$28 -> 0 | ... N56: =N26*$B$28 -> 43180 | O56: =SUM(C56:N56) -> 150280 | P56: 118297.66
A57: 161001151632 DOSAGE NARC Freight | B57: Dollars | C57: 0 | D57: 0 | E57: 0 | F57: 0 | G57: 0 | H57: 0 | I57: 0 | J57: 0 | K57: 0 | L57: 0 | M57: 0 | N57: 0 | O57: =SUM(C57:N57) -> 0 | P57: 1036.97
A58: 166012150000 Hobart Production Freight | B58: Dollars | C58: =#REF! -> #REF! | D58: =#REF! -> #REF! | E58: =#REF! -> #REF! | F58: =#REF! -> #REF! | G58: =#REF! -> #REF! | H58: =#REF! -> #REF! | I58: =#REF! -> #REF! | J58: =#REF! -> #REF! | ... N58: =#REF! -> #REF! | O58: 72000 | P58: 82545.68
B59: Total | C59: =SUM(C33:C58) -> #REF! | D59: =SUM(D33:D58) -> #REF! | E59: =SUM(E33:E58) -> #REF! | F59: =SUM(F33:F58) -> #REF! | G59: =SUM(G33:G58) -> #REF! | H59: =SUM(H33:H58) -> #REF! | I59: =SUM(I33:I58) -> #REF! | J59: =SUM(J33:J58) -> #REF! | ... P59: =SUM(P33:P58) -> 7892543.9

Sheet Upload to COV
C2: LC
C3: Input
C4: FY 2013 | D4: FY 2013 | E4: FY 2013 | F4: FY 2013 | G4: FY 2013 | H4: FY 2013 | I4: FY 2013 | J4: FY 2013 | K4: FY 2013 | L4: FY 2013 | M4: FY 2013 | N4: FY 2013 | O4: FY 2013 | P4: FY 2014 | Q4: FY 2014 | R4: FY 2014 | S4: FY 2014 | T4: FY 2014 | U4: FY 2014 | V4: FY 2014 | W4: FY 2014 | X4: FY 2014 | Y4: FY 2014 | Z4: FY 2014 | AA4: FY 2014 | AB4: FY 2014 | AC4: FY 2015 | AD4: FY 2015 | AE4: FY 2015 | AF4: FY 2015 | AG4: FY 2015 | AH4: FY 2015 | AI4: FY 2015 | AJ4: FY 2015 | AK4: FY 2015 | AL4: FY 2015 | AM4: FY 2015 | AN4: FY 2015 | AO4: FY 2015 | AP4: FY 2016 | AQ4: FY 2016 | AR4: FY 2016 | AS4: FY 2016 | AT4: FY 2016 | AU4: FY 2016 | AV4: FY 2016 | AW4: FY 2016 | AX4: FY 2016 | AY4: FY 2016 | AZ4: FY 2016 | BA4: FY 2016 | BB4: FY 2016
C5: Working Forecast | D5: Working Forecast | E5: Working Forecast | F5: Working Forecast | G5: Working Forecast | H5: Working Forecast | I5: Working Forecast | J5: Working Forecast | K5: Working Forecast | L5: Working Forecast | M5: Working Forecast | N5: Working Forecast | O5: Working Forecast | P5: Working Forecast | Q5: Working Forecast | R5: Working Forecast | S5: Working Forecast | T5: Working Forecast | U5: Working Forecast | V5: Working Forecast | W5: Working Forecast | X5: Working Forecast | Y5: Working Forecast | Z5: Working Forecast | AA5: Working Forecast | AB5: Working Forecast | AC5: Working Forecast | AD5: Working Forecast | AE5: Working Forecast | AF5: Working Forecast | AG5: Working Forecast | AH5: Working Forecast | AI5: Working Forecast | AJ5: Working Forecast | AK5: Working Forecast | AL5: Working Forecast | AM5: Working Forecast | AN5: Working Forecast | AO5: Working Forecast | AP5: Working Forecast | AQ5: Working Forecast | AR5: Working Forecast | AS5: Working Forecast | AT5: Working Forecast | AU5: Working Forecast | AV5: Working Forecast | AW5: Working Forecast | AX5: Working Forecast | AY5: Working Forecast | AZ5: Working Forecast | BA5: Working Forecast | BB5: Working Forecast
C6: Oct | D6: Nov | E6: Dec | F6: Jan | G6: Feb | H6: Mar | I6: Apr | J6: May | K6: Jun | L6: Jul | M6: Aug | N6: Sep | O6: Annual | P6: Oct | Q6: Nov | R6: Dec | S6: Jan | T6: Feb | U6: Mar | V6: Apr | W6: May | X6: Jun | Y6: Jul | Z6: Aug | AA6: Sep | AB6: Annual | AC6: Oct | AD6: Nov | AE6: Dec | AF6: Jan | AG6: Feb | AH6: Mar | AI6: Apr | AJ6: May | AK6: Jun | AL6: Jul | AM6: Aug | AN6: Sep | AO6: Annual | AP6: Oct | AQ6: Nov | AR6: Dec | AS6: Jan | AT6: Feb | AU6: Mar | AV6: Apr | AW6: May | AX6: Jun | AY6: Jul | AZ6: Aug | BA6: Sep | BB6: Annual
A7: ='Pharm Demand'!A31 -> 157001150245 Tofranil-PM/ImipraPam Frt Exp | B7: 7171i | C7: ='Pharm Demand'!C31 -> 0 | D7: ='Pharm Demand'!D31 -> 0 | E7: ='Pharm Demand'!E31 -> 42 | F7: ='Pharm Demand'!F31 -> 46 | G7: ='Pharm Demand'!G31 -> 75.075 | H7: ='Pharm Demand'!H31 -> 58.2855 | I7: ='Pharm Demand'!I31 -> 62.517 | J7: ='Pharm Demand'!J31 -> 70.8435 | ... N7: ='Pharm Demand'!N31 -> 55.8285 | O7: =SUM(C7:N7) -> 590.593 | P7: ='Pharm Demand'!P31 -> 54.1905 | Q7: ='Pharm Demand'!Q31 -> 62.517 | R7: ='Pharm Demand'!R31 -> 50.3685 | S7: ='Pharm Demand'!S31 -> 49.2765 | T7: ='Pharm Demand'!T31 -> 62.1075 | U7: ='Pharm Demand'!U31 -> 50.6415 | V7: ='Pharm Demand'!V31 -> 49.5495 | W7: ='Pharm Demand'!W31 -> 56.784 | ... AA7: ='Pharm Demand'!AA31 -> 46.137 | AB7: =SUM(P7:AA7) -> 636.2265 | AC7: ='Pharm Demand'!AC31 -> 46.0005 | AD7: ='Pharm Demand'!AD31 -> 54.1905 | AE7: ='Pharm Demand'!AE31 -> 42.9975 | AF7: ='Pharm Demand'!AF31 -> 41.496 | AG7: ='Pharm Demand'!AG31 -> 54.6 | AH7: ='Pharm Demand'!AH31 -> 46.956 | AI7: ='Pharm Demand'!AI31 -> 44.772 | AJ7: ='Pharm Demand'!AJ31 -> 53.781 | ... AN7: ='Pharm Demand'!AN31 -> 41.6325 | AO7: =SUM(AC7:AN7) -> 571.935 | AP7: ='Pharm Demand'!AP31 -> 49.959 | AQ7: ='Pharm Demand'!AQ31 -> 39.312 | AR7: ='Pharm Demand'!AR31 -> 45.4545 | AS7: ='Pharm Demand'!AS31 -> 43.407 | AT7: ='Pharm Demand'!AT31 -> 43.66635 | AU7: ='Pharm Demand'!AU31 -> 0 | AV7: ='Pharm Demand'!AV31 -> 0 | AW7: ='Pharm Demand'!AW31 -> 0 | ... BA7: ='Pharm Demand'!BA31 -> 0 | BB7: =SUM(AP7:BA7) -> 221.79885
A8: ='Pharm Demand'!A32 -> 157001150225 Frt Exp-CNS Non-Promoted Prod | B8: 7171i | C8: ='Pharm Demand'!C32 -> 890 | D8: ='Pharm Demand'!D32 -> 1055 | E8: ='Pharm Demand'!E32 -> 605 | F8: ='Pharm Demand'!F32 -> 751 | G8: ='Pharm Demand'!G32 -> 935.62102 | H8: ='Pharm Demand'!H32 -> 712.09193 | I8: ='Pharm Demand'!I32 -> 733.28621 | J8: ='Pharm Demand'!J32 -> 772.1805 | ... N8: ='Pharm Demand'!N32 -> 597.8163 | O8: =SUM(C8:N8) -> 8934.2226 | P8: ='Pharm Demand'!P32 -> 702.89955 | Q8: ='Pharm Demand'!Q32 -> 716.625 | R8: ='Pharm Demand'!R32 -> 612.885 | S8: ='Pharm Demand'!S32 -> 666.55904 | T8: ='Pharm Demand'!T32 -> 737.919 | U8: ='Pharm Demand'!U32 -> 635.1345 | V8: ='Pharm Demand'!V32 -> 672.9047 | W8: ='Pharm Demand'!W32 -> 702.0195 | ... AA8: ='Pharm Demand'!AA32 -> 641.9595 | AB8: =SUM(P8:AA8) -> 8116.8119 | AC8: ='Pharm Demand'!AC32 -> 612.5818 | AD8: ='Pharm Demand'!AD32 -> 708.708 | AE8: ='Pharm Demand'!AE32 -> 599.9175 | AF8: ='Pharm Demand'!AF32 -> 578.82977 | AG8: ='Pharm Demand'!AG32 -> 711.711 | AH8: ='Pharm Demand'!AH32 -> 638.6835 | AI8: ='Pharm Demand'!AI32 -> 611.39432 | AJ8: ='Pharm Demand'!AJ32 -> 700.9275 | ... AN8: ='Pharm Demand'!AN32 -> 587.9055 | AO8: =SUM(AC8:AN8) -> 7691.3897 | AP8: ='Pharm Demand'!AP32 -> 641.14405 | AQ8: ='Pharm Demand'!AQ32 -> 564.564 | AR8: ='Pharm Demand'!AR32 -> 604.51418 | AS8: ='Pharm Demand'!AS32 -> 601.64768 | AT8: ='Pharm Demand'!AT32 -> 625.24398 | AU8: ='Pharm Demand'!AU32 -> 0 | AV8: ='Pharm Demand'!AV32 -> 0 | AW8: ='Pharm Demand'!AW32 -> 0 | ... BA8: ='Pharm Demand'!BA32 -> 0 | BB8: =SUM(AP8:BA8) -> 3037.1139
A10: 157001150251 Pennsaid Frt Expense | B10: 7171i | C10: ='Pharm Demand'!C34 -> 2075 | D10: ='Pharm Demand'!D34 -> 2641 | E10: ='Pharm Demand'!E34 -> 1565 | F10: ='Pharm Demand'!F34 -> 2371 | G10: ='Pharm Demand'!G34 -> 3388.2488 | H10: ='Pharm Demand'!H34 -> 2482.3439 | I10: ='Pharm Demand'!I34 -> 3936.7669 | J10: ='Pharm Demand'!J34 -> 5143.0628 | ... N10: ='Pharm Demand'!N34 -> 3300.4321 | O10: =SUM(C10:N10) -> 36707.347 | P10: ='Pharm Demand'!P34 -> 2711.6328 | Q10: ='Pharm Demand'!Q34 -> 1802.6256 | R10: ='Pharm Demand'!R34 -> 1194.7814 | S10: ='Pharm Demand'!S34 -> 775.40845 | T10: ='Pharm Demand'!T34 -> 507.84481 | U10: ='Pharm Demand'!U34 -> 324.07744 | V10: ='Pharm Demand'!V34 -> 324.64067 | W10: ='Pharm Demand'!W34 -> 328.22328 | ... AA10: ='Pharm Demand'!AA34 -> 339.03812 | AB10: =SUM(P10:AA10) -> 9311.8841 | AC10: ='Pharm Demand'!AC34 -> 341.44711 | AD10: ='Pharm Demand'!AD34 -> 293.33626 | AE10: ='Pharm Demand'!AE34 -> 184.9982 | AF10: ='Pharm Demand'!AF34 -> 110.86985 | AG10: ='Pharm Demand'!AG34 -> 62.958981 | AH10: ='Pharm Demand'!AH34 -> 29.991041 | AI10: ='Pharm Demand'!AI34 -> 7.4783745 | AJ10: ='Pharm Demand'!AJ34 -> 0 | ... AN10: ='Pharm Demand'!AN34 -> 0 | AO10: =SUM(AC10:AN10) -> 1031.0798 | AP10: ='Pharm Demand'!AP34 -> 0 | AQ10: ='Pharm Demand'!AQ34 -> 0 | AR10: ='Pharm Demand'!AR34 -> 0 | AS10: ='Pharm Demand'!AS34 -> 0 | AT10: ='Pharm Demand'!AT34 -> 0 | AU10: ='Pharm Demand'!AU34 -> 0 | AV10: ='Pharm Demand'!AV34 -> 0 | AW10: ='Pharm Demand'!AW34 -> 0 | ... BA10: ='Pharm Demand'!BA34 -> 0 | BB10: =SUM(AP10:BA10) -> 0
A11: 157001150255 Pennsaid 2% Pump Frt Expense | B11: 7171i | C11: ='Pharm Demand'!C35 -> 0 | D11: ='Pharm Demand'!D35 -> 0 | E11: ='Pharm Demand'!E35 -> 0 | F11: ='Pharm Demand'!F35 -> 0 | G11: ='Pharm Demand'!G35 -> 0 | H11: ='Pharm Demand'!H35 -> 0 | I11: ='Pharm Demand'!I35 -> 0 | J11: ='Pharm Demand'!J35 -> 0 | ... N11: ='Pharm Demand'!N35 -> 0 | O11: =SUM(C11:N11) -> 0 | P11: ='Pharm Demand'!P35 -> 2967.3735 | Q11: ='Pharm Demand'!Q35 -> 2050.4249 | R11: ='Pharm Demand'!R35 -> 1801.9365 | S11: ='Pharm Demand'!S35 -> 2902.6725 | T11: ='Pharm Demand'!T35 -> 3296.5404 | U11: ='Pharm Demand'!U35 -> 2528.1165 | V11: ='Pharm Demand'!V35 -> 3098.004 | W11: ='Pharm Demand'!W35 -> 3394.6315 | ... AA11: ='Pharm Demand'!AA35 -> 3302.8905 | AB11: =SUM(P11:AA11) -> 34590.329 | AC11: ='Pharm Demand'!AC35 -> 3073.0245 | AD11: ='Pharm Demand'!AD35 -> 3105.9795 | AE11: ='Pharm Demand'!AE35 -> 2580.5325 | AF11: ='Pharm Demand'!AF35 -> 2186.8665 | AG11: ='Pharm Demand'!AG35 -> 1951.2646 | AH11: ='Pharm Demand'!AH35 -> 1779.96 | AI11: ='Pharm Demand'!AI35 -> 1653.4245 | AJ11: ='Pharm Demand'!AJ35 -> 1580.9959 | ... AN11: ='Pharm Demand'!AN35 -> 1684.41 | AO11: =SUM(AC11:AN11) -> 24508.076 | AP11: ='Pharm Demand'!AP35 -> 1687.14 | AQ11: ='Pharm Demand'!AQ35 -> 1759.485 | AR11: ='Pharm Demand'!AR35 -> 1769.04 | AS11: ='Pharm Demand'!AS35 -> 1820.455 | AT11: ='Pharm Demand'!AT35 -> 1861.405 | AU11: ='Pharm Demand'!AU35 -> 0 | AV11: ='Pharm Demand'!AV35 -> 0 | AW11: ='Pharm Demand'!AW35 -> 0 | ... BA11: ='Pharm Demand'!BA35 -> 0 | BB11: =SUM(AP11:BA11) -> 8897.525
A12: 157001150256 Diclofenac 2% Pump Frt Exp | B12: 7171i | C12: ='Pharm Demand'!C36 -> 0 | D12: ='Pharm Demand'!D36 -> 0 | E12: ='Pharm Demand'!E36 -> 0 | F12: ='Pharm Demand'!F36 -> 0 | G12: ='Pharm Demand'!G36 -> 0 | H12: ='Pharm Demand'!H36 -> 0 | I12: ='Pharm Demand'!I36 -> 0 | J12: ='Pharm Demand'!J36 -> 0 | ... N12: ='Pharm Demand'!N36 -> 0 | O12: =SUM(C12:N12) -> 0 | P12: ='Pharm Demand'!P36 -> 0 | Q12: ='Pharm Demand'!Q36 -> 0 | R12: ='Pharm Demand'!R36 -> 0 | S12: ='Pharm Demand'!S36 -> 0 | T12: ='Pharm Demand'!T36 -> 0 | U12: ='Pharm Demand'!U36 -> 0 | V12: ='Pharm Demand'!V36 -> 0 | W12: ='Pharm Demand'!W36 -> 0 | ... AA12: ='Pharm Demand'!AA36 -> 0 | AB12: =SUM(P12:AA12) -> 0 | AC12: ='Pharm Demand'!AC36 -> 0 | AD12: ='Pharm Demand'!AD36 -> 0 | AE12: ='Pharm Demand'!AE36 -> 0 | AF12: ='Pharm Demand'!AF36 -> 0 | AG12: ='Pharm Demand'!AG36 -> 0 | AH12: ='Pharm Demand'!AH36 -> 0 | AI12: ='Pharm Demand'!AI36 -> 0 | AJ12: ='Pharm Demand'!AJ36 -> 0 | ... AN12: ='Pharm Demand'!AN36 -> 0 | AO12: =SUM(AC12:AN12) -> 0 | AP12: ='Pharm Demand'!AP36 -> 0 | AQ12: ='Pharm Demand'!AQ36 -> 0 | AR12: ='Pharm Demand'!AR36 -> 0 | AS12: ='Pharm Demand'!AS36 -> 0 | AT12: ='Pharm Demand'!AT36 -> 0 | AU12: ='Pharm Demand'!AU36 -> 0 | AV12: ='Pharm Demand'!AV36 -> 0 | AW12: ='Pharm Demand'!AW36 -> 0 | ... BA12: ='Pharm Demand'!BA36 -> 0 | BB12: =SUM(AP12:BA12) -> 0
A13: 157001150252 Exalgo Freight Exp | B13: 7171i | C13: ='Pharm Demand'!C37 -> 1447 | D13: ='Pharm Demand'!D37 -> 1893 | E13: ='Pharm Demand'!E37 -> 705 | F13: ='Pharm Demand'!F37 -> 1303 | G13: ='Pharm Demand'!G37 -> 1757.4715 | H13: ='Pharm Demand'!H37 -> 1345.7707 | I13: ='Pharm Demand'!I37 -> 1175.1285 | J13: ='Pharm Demand'!J37 -> 1622.8485 | ... N13: ='Pharm Demand'!N37 -> 1550.6837 | O13: =SUM(C13:N13) -> 17116.318 | P13: ='Pharm Demand'!P37 -> 1617.9345 | Q13: ='Pharm Demand'!Q37 -> 2277.639 | R13: ='Pharm Demand'!R37 -> 539.721 | S13: ='Pharm Demand'!S37 -> 327.327 | T13: ='Pharm Demand'!T37 -> 571.2525 | U13: ='Pharm Demand'!U37 -> 360.2235 | V13: ='Pharm Demand'!V37 -> 382.0635 | W13: ='Pharm Demand'!W37 -> 512.5575 | ... AA13: ='Pharm Demand'!AA37 -> 109.8825 | AB13: =SUM(P13:AA13) -> 7749.924 | AC13: ='Pharm Demand'!AC37 -> 102.375 | AD13: ='Pharm Demand'!AD37 -> 132.8145 | AE13: ='Pharm Demand'!AE37 -> 85.8585 | AF13: ='Pharm Demand'!AF37 -> 85.176 | AG13: ='Pharm Demand'!AG37 -> 137.046 | AH13: ='Pharm Demand'!AH37 -> 92.274 | AI13: ='Pharm Demand'!AI37 -> 100.191 | AJ13: ='Pharm Demand'!AJ37 -> 144.144 | ... AN13: ='Pharm Demand'!AN37 -> 92.547 | AO13: =SUM(AC13:AN13) -> 1328.5545 | AP13: ='Pharm Demand'!AP37 -> 120.939 | AQ13: ='Pharm Demand'!AQ37 -> 135.681 | AR13: ='Pharm Demand'!AR37 -> 116.7075 | AS13: ='Pharm Demand'!AS37 -> 130.494 | AT13: ='Pharm Demand'!AT37 -> 122.4405 | AU13: ='Pharm Demand'!AU37 -> 0 | AV13: ='Pharm Demand'!AV37 -> 0 | AW13: ='Pharm Demand'!AW37 -> 0 | ... BA13: ='Pharm Demand'!BA37 -> 0 | BB13: =SUM(AP13:BA13) -> 626.262
A15: 157001150258 Hydromorphone ER Frt Exp | B15: 7171i | C15: ='Pharm Demand'!C39 -> 0 | D15: ='Pharm Demand'!D39 -> 0 | E15: ='Pharm Demand'!E39 -> 0 | F15: ='Pharm Demand'!F39 -> 0 | G15: ='Pharm Demand'!G39 -> 0 | H15: ='Pharm Demand'!H39 -> 0 | I15: ='Pharm Demand'!I39 -> 0 | J15: ='Pharm Demand'!J39 -> 0 | ... N15: ='Pharm Demand'!N39 -> 0 | O15: =SUM(C15:N15) -> 0 | P15: ='Pharm Demand'!P39 -> 0 | Q15: ='Pharm Demand'!Q39 -> 0 | R15: ='Pharm Demand'!R39 -> 0 | S15: ='Pharm Demand'!S39 -> 0 | T15: ='Pharm Demand'!T39 -> 0 | U15: ='Pharm Demand'!U39 -> 0 | V15: ='Pharm Demand'!V39 -> 149.1945 | W15: ='Pharm Demand'!W39 -> 126.2625 | ... AA15: ='Pharm Demand'!AA39 -> 418.3725 | AB15: =SUM(P15:AA15) -> 1542.996 | AC15: ='Pharm Demand'!AC39 -> 520.338 | AD15: ='Pharm Demand'!AD39 -> 493.4475 | AE15: ='Pharm Demand'!AE39 -> 535.4895 | AF15: ='Pharm Demand'!AF39 -> 692.7375 | AG15: ='Pharm Demand'!AG39 -> 598.143 | AH15: ='Pharm Demand'!AH39 -> 726.0435 | AI15: ='Pharm Demand'!AI39 -> 820.2285 | AJ15: ='Pharm Demand'!AJ39 -> 596.9145 | ... AN15: ='Pharm Demand'!AN39 -> 625.3065 | AO15: =SUM(AC15:AN15) -> 7837.83 | AP15: ='Pharm Demand'!AP39 -> 625.3065 | AQ15: ='Pharm Demand'!AQ39 -> 704.23328 | AR15: ='Pharm Demand'!AR39 -> 708.73654 | AS15: ='Pharm Demand'!AS39 -> 713.2398 | AT15: ='Pharm Demand'!AT39 -> 754.95482 | AU15: ='Pharm Demand'!AU39 -> 0 | AV15: ='Pharm Demand'!AV39 -> 0 | AW15: ='Pharm Demand'!AW39 -> 0 | ... BA15: ='Pharm Demand'!BA39 -> 0 | BB15: =SUM(AP15:BA15) -> 3506.4709
A17: 157001150268 Roxicodone-Freight | B17: 7171i | C17: ='Pharm Demand'!C41 -> 668 | D17: ='Pharm Demand'!D41 -> 561 | E17: ='Pharm Demand'!E41 -> 209 | F17: ='Pharm Demand'!F41 -> 646 | G17: ='Pharm Demand'!G41 -> 586.45692 | H17: ='Pharm Demand'!H41 -> 469.64474 | I17: ='Pharm Demand'!I41 -> 552.825 | J17: ='Pharm Demand'!J41 -> 506.8245 | ... N17: ='Pharm Demand'!N41 -> 478.3513 | O17: =SUM(C17:N17) -> 6264.7354 | P17: ='Pharm Demand'!P41 -> 637.87186 | Q17: ='Pharm Demand'!Q41 -> 461.916 | R17: ='Pharm Demand'!R41 -> 445.809 | S17: ='Pharm Demand'!S41 -> 611.25436 | T17: ='Pharm Demand'!T41 -> 491.673 | U17: ='Pharm Demand'!U41 -> 469.287 | V17: ='Pharm Demand'!V41 -> 587.77636 | W17: ='Pharm Demand'!W41 -> 491.673 | ... AA17: ='Pharm Demand'!AA41 -> 516.243 | AB17: =SUM(P17:AA17) -> 6262.2399 | AC17: ='Pharm Demand'!AC41 -> 516.25036 | AD17: ='Pharm Demand'!AD41 -> 516.243 | AE17: ='Pharm Demand'!AE41 -> 516.243 | AF17: ='Pharm Demand'!AF41 -> 516.25036 | AG17: ='Pharm Demand'!AG41 -> 516.243 | AH17: ='Pharm Demand'!AH41 -> 516.243 | AI17: ='Pharm Demand'!AI41 -> 516.25036 | AJ17: ='Pharm Demand'!AJ41 -> 516.243 | ... AN17: ='Pharm Demand'!AN41 -> 516.243 | AO17: =SUM(AC17:AN17) -> 6194.9454 | AP17: ='Pharm Demand'!AP41 -> 516.25036 | AQ17: ='Pharm Demand'!AQ41 -> 516.243 | AR17: ='Pharm Demand'!AR41 -> 516.243 | AS17: ='Pharm Demand'!AS41 -> 522.1125 | AT17: ='Pharm Demand'!AT41 -> 540.5946 | AU17: ='Pharm Demand'!AU41 -> 0 | AV17: ='Pharm Demand'!AV41 -> 0 | AW17: ='Pharm Demand'!AW41 -> 0 | ... BA17: ='Pharm Demand'!BA41 -> 0 | BB17: =SUM(AP17:BA17) -> 2611.4435
A18: 157001150269 Intrathecal-Freight | B18: 7171i | C18: 0 | D18: 0 | E18: 0 | F18: 0 | G18: 0 | H18: 0 | I18: 0 | J18: 0 | K18: 0 | L18: 0 | M18: 0 | N18: 0 | O18: 0 | P18: 0 | Q18: 0 | R18: 0 | S18: 0 | T18: 0 | U18: 0 | V18: 0 | W18: 0 | X18: 0 | Y18: 0 | Z18: 0 | AA18: 0 | AB18: 0 | AC18: 0 | AD18: 0 | AE18: 0 | AF18: 0 | AG18: 0 | AH18: 0 | AI18: 0 | AJ18: 0 | AK18: 0 | AL18: 0 | AM18: 0 | AN18: 0 | AO18: 0 | AP18: 0 | AQ18: 0 | AR18: 0 | AS18: 0 | AT18: 0 | AU18: 0 | AV18: 0 | AW18: 0 | AX18: 0 | AY18: 0 | AZ18: 0 | BA18: 0 | BB18: 0
A19: 157210151269 Intrathecal-Freight-General | B19: 7171i | C19: ='Pharm Demand'!C42 -> 0 | D19: ='Pharm Demand'!D42 -> 0 | E19: ='Pharm Demand'!E42 -> 0 | F19: ='Pharm Demand'!F42 -> 25854.04 | G19: ='Pharm Demand'!G42 -> 3300 | H19: ='Pharm Demand'!H42 -> 2750 | I19: ='Pharm Demand'!I42 -> 2500 | J19: ='Pharm Demand'!J42 -> 2500 | ... N19: ='Pharm Demand'!N42 -> 2500 | O19: =SUM(C19:N19) -> 46904.04 | P19: ='Pharm Demand'!P42 -> 5000 | Q19: ='Pharm Demand'!Q42 -> 5000 | R19: ='Pharm Demand'!R42 -> 5000 | S19: ='Pharm Demand'!S42 -> 5000 | T19: ='Pharm Demand'!T42 -> 5000 | U19: ='Pharm Demand'!U42 -> 5000 | V19: ='Pharm Demand'!V42 -> 5000 | W19: ='Pharm Demand'!W42 -> 5000 | ... AA19: ='Pharm Demand'!AA42 -> 5000 | AB19: =SUM(P19:AA19) -> 60000 | AC19: ='Pharm Demand'!AC42 -> 994.94731 | AD19: ='Pharm Demand'!AD42 -> 1173.1454 | AE19: ='Pharm Demand'!AE42 -> 994.94731 | AF19: ='Pharm Demand'!AF42 -> 1030.9465 | AG19: ='Pharm Demand'!AG42 -> 1213.6444 | AH19: ='Pharm Demand'!AH42 -> 1039.8264 | AI19: ='Pharm Demand'!AI42 -> 1088.5831 | AJ19: ='Pharm Demand'!AJ42 -> 1299.6683 | ... AN19: ='Pharm Demand'!AN42 -> 1221.0435 | AO19: =SUM(AC19:AN19) -> 13771.099 | AP19: ='Pharm Demand'!AP42 -> 0 | AQ19: ='Pharm Demand'!AQ42 -> 0 | AR19: ='Pharm Demand'!AR42 -> 0 | AS19: ='Pharm Demand'!AS42 -> 0 | AT19: ='Pharm Demand'!AT42 -> 0 | AU19: ='Pharm Demand'!AU42 -> 0 | AV19: ='Pharm Demand'!AV42 -> 0 | AW19: ='Pharm Demand'!AW42 -> 0 | ... BA19: ='Pharm Demand'!BA42 -> 0 | BB19: =SUM(AP19:BA19) -> 0
A20: 168210151269 Intrathecal-Freight-General | B20: 7171i | O20: =SUM(C20:N20) -> 0 | AB20: =SUM(P20:AA20) -> 0 | AO20: =SUM(AC20:AN20) -> 0 | BB20: =SUM(AP20:BA20) -> 0
A21: 168210152000 Intrathecal-2000 mcg/mi | B21: 7171i | O21: =SUM(C21:N21) -> 0 | AB21: =SUM(P21:AA21) -> 0 | AO21: =SUM(AC21:AN21) -> 0 | BB21: =SUM(AP21:BA21) -> 0
A22: 157001150249 Hydrocodone/APAP GR | B22: 7171i | C22: ='Pharm Demand'!C43 -> 0 | D22: ='Pharm Demand'!D43 -> 0 | E22: ='Pharm Demand'!E43 -> 0 | F22: ='Pharm Demand'!F43 -> 0 | G22: ='Pharm Demand'!G43 -> 0 | H22: ='Pharm Demand'!H43 -> 0 | I22: ='Pharm Demand'!I43 -> 0 | J22: ='Pharm Demand'!J43 -> 0 | ... N22: ='Pharm Demand'!N43 -> 0 | O22: =SUM(C22:N22) -> 0 | P22: ='Pharm Demand'!P43 -> 0 | Q22: ='Pharm Demand'!Q43 -> 0 | R22: ='Pharm Demand'!R43 -> 0 | S22: ='Pharm Demand'!S43 -> 0 | T22: ='Pharm Demand'!T43 -> 0 | U22: ='Pharm Demand'!U43 -> 0 | V22: ='Pharm Demand'!V43 -> 0 | W22: ='Pharm Demand'!W43 -> 0 | ... AA22: ='Pharm Demand'!AA43 -> 0 | AB22: =SUM(P22:AA22) -> 0 | AC22: ='Pharm Demand'!AC43 -> 0 | AD22: ='Pharm Demand'!AD43 -> 0 | AE22: ='Pharm Demand'!AE43 -> 0 | AF22: ='Pharm Demand'!AF43 -> 3322.5465 | AG22: ='Pharm Demand'!AG43 -> 6645.2295 | AH22: ='Pharm Demand'!AH43 -> 9967.776 | AI22: ='Pharm Demand'!AI43 -> 11710.608 | AJ22: ='Pharm Demand'!AJ43 -> 13453.44 | ... AN22: ='Pharm Demand'!AN43 -> 23043.657 | AO22: =SUM(AC22:AN22) -> 121579.32 | AP22: ='Pharm Demand'!AP43 -> 24708.684 | AQ22: ='Pharm Demand'!AQ43 -> 26919.029 | AR22: ='Pharm Demand'!AR43 -> 29129.373 | AS22: ='Pharm Demand'!AS43 -> 31381.214 | AT22: ='Pharm Demand'!AT43 -> 33605.39 | AU22: ='Pharm Demand'!AU43 -> 0 | AV22: ='Pharm Demand'!AV43 -> 0 | AW22: ='Pharm Demand'!AW43 -> 0 | ... BA22: ='Pharm Demand'!BA43 -> 0 | BB22: =SUM(AP22:BA22) -> 145743.69
A23: ='Pharm Demand'!A44 -> 157001150250 Oxyocodone/APAP GR | B23: 7171i | C23: ='Pharm Demand'!C44 -> 0 | D23: ='Pharm Demand'!D44 -> 0 | E23: ='Pharm Demand'!E44 -> 0 | F23: ='Pharm Demand'!F44 -> 0 | G23: ='Pharm Demand'!G44 -> 0 | H23: ='Pharm Demand'!H44 -> 0 | I23: ='Pharm Demand'!I44 -> 0 | J23: ='Pharm Demand'!J44 -> 0 | ... N23: ='Pharm Demand'!N44 -> 0 | O23: =SUM(C23:N23) -> 0 | P23: ='Pharm Demand'!P44 -> 0 | Q23: ='Pharm Demand'!Q44 -> 0 | R23: ='Pharm Demand'!R44 -> 0 | S23: ='Pharm Demand'!S44 -> 0 | T23: ='Pharm Demand'!T44 -> 0 | U23: ='Pharm Demand'!U44 -> 0 | V23: ='Pharm Demand'!V44 -> 1795.7785 | W23: ='Pharm Demand'!W44 -> 3591.6936 | ... AA23: ='Pharm Demand'!AA44 -> 8226.2861 | AB23: =SUM(P23:AA23) -> 32614.989 | AC23: ='Pharm Demand'!AC44 -> 9402.2125 | AD23: ='Pharm Demand'!AD44 -> 10786.55 | AE23: ='Pharm Demand'!AE44 -> 12171.024 | AF23: ='Pharm Demand'!AF44 -> 13373.475 | AG23: ='Pharm Demand'!AG44 -> 14575.926 | AH23: ='Pharm Demand'!AH44 -> 15778.513 | AI23: ='Pharm Demand'!AI44 -> 17121.843 | AJ23: ='Pharm Demand'!AJ44 -> 18465.446 | ... AN23: ='Pharm Demand'!AN44 -> 23781.185 | AO23: =SUM(AC23:AN23) -> 198855.19 | AP23: ='Pharm Demand'!AP44 -> 23338.585 | AQ23: ='Pharm Demand'!AQ44 -> 23391.724 | AR23: ='Pharm Demand'!AR44 -> 23452.643 | AS23: ='Pharm Demand'!AS44 -> 26266.883 | AT23: ='Pharm Demand'!AT44 -> 27255.664 | AU23: ='Pharm Demand'!AU44 -> 0 | AV23: ='Pharm Demand'!AV44 -> 0 | AW23: ='Pharm Demand'!AW44 -> 0 | ... BA23: ='Pharm Demand'!BA44 -> 0 | BB23: =SUM(AP23:BA23) -> 123705.5
A26: 157001150245 Tofranil-PM/ImipraPam Frt Exp | B26: 7165i | C26: ='Download COV'!D26 -> 0 | D26: ='Download COV'!E26 -> 0 | E26: ='Download COV'!F26 -> 66 | F26: ='Download COV'!G26 -> 33 | G26: =G7*$B45 -> 18.76875 | H26: =H7*$B45 -> 14.571375 | I26: =I7*$B45 -> 15.62925 | J26: =J7*$B45 -> 17.710875 | K26: =K7*$B45 -> 13.923 | L26: =L7*$B45 -> 14.230125 | M26: =M7*$B45 -> 16.85775 | N26: =N7*$B45 -> 13.957125 | O26: =SUM(C26:N26) -> 224.64825 | P26: =P7*$B45 -> 13.547625 | Q26: =Q7*$B45 -> 15.62925 | R26: =R7*$B45 -> 12.592125 | S26: =S7*$B45 -> 12.319125 | T26: =T7*$B45 -> 15.526875 | U26: =U7*$B45 -> 12.660375 | V26: =V7*$B45 -> 12.387375 | W26: =W7*$B45 -> 14.196 | ... AA26: =AA7*$B45 -> 11.53425 | AB26: =SUM(P26:AA26) -> 159.05663 | AC26: =AC7*$B45 -> 11.500125 | AD26: =AD7*$B45 -> 13.547625 | AE26: =AE7*$B45 -> 10.749375 | AF26: =AF7*$B45 -> 10.374 | AG26: =AG7*$B45 -> 13.65 | AH26: =AH7*$B45 -> 11.739 | AI26: =AI7*$B45 -> 11.193 | AJ26: =AJ7*$B45 -> 13.44525 | ... AN26: =AN7*$B45 -> 10.408125 | AO26: =SUM(AC26:AN26) -> 142.98375 | AP26: =AP7*$B45 -> 12.48975 | AQ26: =AQ7*$B45 -> 9.828 | AR26: =AR7*$B45 -> 11.363625 | AS26: =AS7*$B45 -> 10.85175 | AT26: =AT7*$B45 -> 10.916588 | AU26: =AU7*$B45 -> 0 | AV26: =AV7*$B45 -> 0 | AW26: =AW7*$B45 -> 0 | ... BA26: =BA7*$B45 -> 0 | BB26: =SUM(AP26:BA26) -> 55.449713
A27: 157001150225 Frt Exp-CNS Non-Promoted Prod | B27: 7165i | C27: ='Download COV'!D27 -> 197 | D27: ='Download COV'!E27 -> 516 | E27: ='Download COV'!F27 -> 869 | F27: ='Download COV'!G27 -> 305 | G27: =G8*$B46 -> 233.90525 | H27: =H8*$B46 -> 178.02298 | I27: =I8*$B46 -> 183.32155 | J27: =J8*$B46 -> 193.04513 | K27: =K8*$B46 -> 158.95425 | L27: =L8*$B46 -> 150.31987 | M27: =M8*$B46 -> 161.28255 | N27: =N8*$B46 -> 149.45408 | O27: =SUM(C27:N27) -> 3295.3057 | P27: =P8*$B46 -> 175.72489 | Q27: =Q8*$B46 -> 179.15625 | R27: =R8*$B46 -> 153.22125 | S27: =S8*$B46 -> 166.63976 | T27: =T8*$B46 -> 184.47975 | U27: =U8*$B46 -> 158.78363 | V27: =V8*$B46 -> 168.22618 | W27: =W8*$B46 -> 175.50488 | ... AA27: =AA8*$B46 -> 160.48988 | AB27: =SUM(P27:AA27) -> 2029.203 | AC27: =AC8*$B46 -> 153.14545 | AD27: =AD8*$B46 -> 177.177 | AE27: =AE8*$B46 -> 149.97938 | AF27: =AF8*$B46 -> 144.70744 | AG27: =AG8*$B46 -> 177.92775 | AH27: =AH8*$B46 -> 159.67088 | AI27: =AI8*$B46 -> 152.84858 | AJ27: =AJ8*$B46 -> 175.23188 | ... AN27: =AN8*$B46 -> 146.97638 | AO27: =SUM(AC27:AN27) -> 1922.8474 | AP27: =AP8*$B46 -> 160.28601 | AQ27: =AQ8*$B46 -> 141.141 | AR27: =AR8*$B46 -> 151.12855 | AS27: =AS8*$B46 -> 150.41192 | AT27: =AT8*$B46 -> 156.311 | AU27: =AU8*$B46 -> 0 | AV27: =AV8*$B46 -> 0 | AW27: =AW8*$B46 -> 0 | ... BA27: =BA8*$B46 -> 0 | BB27: =SUM(AP27:BA27) -> 759.27848
A29: 157001150251 Pennsaid Frt Expense | B29: 7165i | C29: ='Download COV'!D29 -> 192 | D29: ='Download COV'!E29 -> 656 | E29: ='Download COV'!F29 -> 974 | F29: ='Download COV'!G29 -> 685 | G29: =G10*$B48 -> 847.06221 | H29: =H10*$B48 -> 620.58598 | I29: =I10*$B48 -> 984.19172 | J29: =J10*$B48 -> 1285.7657 | K29: =K10*$B48 -> 814.24491 | L29: =L10*$B48 -> 809.88925 | M29: =M10*$B48 -> 826.98889 | N29: =N10*$B48 -> 825.10802 | O29: =SUM(C29:N29) -> 9520.8367 | P29: =P10*$B48 -> 677.90821 | Q29: =Q10*$B48 -> 450.65641 | R29: =R10*$B48 -> 298.69536 | S29: =S10*$B48 -> 193.85211 | T29: =T10*$B48 -> 126.9612 | U29: =U10*$B48 -> 81.019361 | V29: =V10*$B48 -> 81.160167 | W29: =W10*$B48 -> 82.05582 | ... AA29: =AA10*$B48 -> 84.759529 | AB29: =SUM(P29:AA29) -> 2327.971 | AC29: =AC10*$B48 -> 85.361778 | AD29: =AD10*$B48 -> 73.334065 | AE29: =AE10*$B48 -> 46.24955 | AF29: =AF10*$B48 -> 27.717462 | AG29: =AG10*$B48 -> 15.739745 | AH29: =AH10*$B48 -> 7.4977603 | AI29: =AI10*$B48 -> 1.8695936 | AJ29: =AJ10*$B48 -> 0 | ... AN29: =AN10*$B48 -> 0 | AO29: =SUM(AC29:AN29) -> 257.76995 | AP29: =AP10*$B48 -> 0 | AQ29: =AQ10*$B48 -> 0 | AR29: =AR10*$B48 -> 0 | AS29: =AS10*$B48 -> 0 | AT29: =AT10*$B48 -> 0 | AU29: =AU10*$B48 -> 0 | AV29: =AV10*$B48 -> 0 | AW29: =AW10*$B48 -> 0 | ... BA29: =BA10*$B48 -> 0 | BB29: =SUM(AP29:BA29) -> 0
A30: 157001150255 Pennsaid 2% Pump Frt Expense | B30: 7165i | C30: ='Download COV'!D30 -> 0 | D30: ='Download COV'!E30 -> 0 | E30: ='Download COV'!F30 -> 0 | F30: ='Download COV'!G30 -> 0 | G30: =G11*$B49 -> 0 | H30: =H11*$B49 -> 0 | I30: =I11*$B49 -> 0 | J30: =J11*$B49 -> 0 | K30: =K11*$B49 -> 0 | L30: =L11*$B49 -> 0 | M30: =M11*$B49 -> 0 | N30: =N11*$B49 -> 0 | O30: =SUM(C30:N30) -> 0 | P30: =P11*$B49 -> 741.84338 | Q30: =Q11*$B49 -> 512.60622 | R30: =R11*$B49 -> 450.48413 | S30: =S11*$B49 -> 725.66813 | T30: =T11*$B49 -> 824.13511 | U30: =U11*$B49 -> 632.02913 | V30: =V11*$B49 -> 774.501 | W30: =W11*$B49 -> 848.65788 | ... AA30: =AA11*$B49 -> 825.72263 | AB30: =SUM(P30:AA30) -> 8647.5822 | AC30: =AC11*$B49 -> 768.25613 | AD30: =AD11*$B49 -> 776.49488 | AE30: =AE11*$B49 -> 645.13313 | AF30: =AF11*$B49 -> 546.71663 | AG30: =AG11*$B49 -> 487.81615 | AH30: =AH11*$B49 -> 444.99 | AI30: =AI11*$B49 -> 413.35613 | AJ30: =AJ11*$B49 -> 395.24897 | ... AN30: =AN11*$B49 -> 421.1025 | AO30: =SUM(AC30:AN30) -> 6127.0189 | AP30: =AP11*$B49 -> 421.785 | AQ30: =AQ11*$B49 -> 439.87125 | AR30: =AR11*$B49 -> 442.26 | AS30: =AS11*$B49 -> 455.11375 | AT30: =AT11*$B49 -> 465.35125 | AU30: =AU11*$B49 -> 0 | AV30: =AV11*$B49 -> 0 | AW30: =AW11*$B49 -> 0 | ... BA30: =BA11*$B49 -> 0 | BB30: =SUM(AP30:BA30) -> 2224.3813
A31: 157001150256 Diclofenac 2% Pump Frt Exp | B31: 7165i | C31: ='Download COV'!D31 -> 0 | D31: ='Download COV'!E31 -> 0 | E31: ='Download COV'!F31 -> 0 | F31: ='Download COV'!G31 -> 0 | G31: =G12*$B50 -> 0 | H31: =H12*$B50 -> 0 | I31: =I12*$B50 -> 0 | J31: =J12*$B50 -> 0 | K31: =K12*$B50 -> 0 | L31: =L12*$B50 -> 0 | M31: =M12*$B50 -> 0 | N31: =N12*$B50 -> 0 | O31: =SUM(C31:N31) -> 0 | P31: =P12*$B50 -> 0 | Q31: =Q12*$B50 -> 0 | R31: =R12*$B50 -> 0 | S31: =S12*$B50 -> 0 | T31: =T12*$B50 -> 0 | U31: =U12*$B50 -> 0 | V31: =V12*$B50 -> 0 | W31: =W12*$B50 -> 0 | ... AA31: =AA12*$B50 -> 0 | AB31: =SUM(P31:AA31) -> 0 | AC31: =AC12*$B50 -> 0 | AD31: =AD12*$B50 -> 0 | AE31: =AE12*$B50 -> 0 | AF31: =AF12*$B50 -> 0 | AG31: =AG12*$B50 -> 0 | AH31: =AH12*$B50 -> 0 | AI31: =AI12*$B50 -> 0 | AJ31: =AJ12*$B50 -> 0 | ... AN31: =AN12*$B50 -> 0 | AO31: =SUM(AC31:AN31) -> 0 | AP31: =AP12*$B50 -> 0 | AQ31: =AQ12*$B50 -> 0 | AR31: =AR12*$B50 -> 0 | AS31: =AS12*$B50 -> 0 | AT31: =AT12*$B50 -> 0 | AU31: =AU12*$B50 -> 0 | AV31: =AV12*$B50 -> 0 | AW31: =AW12*$B50 -> 0 | ... BA31: =BA12*$B50 -> 0 | BB31: =SUM(AP31:BA31) -> 0
A32: 157001150252 Exalgo Freight Exp | B32: 7165i | C32: ='Download COV'!D32 -> 1308 | D32: ='Download COV'!E32 -> 4747 | E32: ='Download COV'!F32 -> 4195 | F32: ='Download COV'!G32 -> 3533 | G32: =G13*$B51 -> 1318.1037 | H32: =H13*$B51 -> 1009.3281 | I32: =I13*$B51 -> 881.34638 | J32: =J13*$B51 -> 1217.1364 | K32: =K13*$B51 -> 873.36113 | L32: =L13*$B51 -> 909.46899 | M32: =M13*$B51 -> 1454.4814 | N32: =N13*$B51 -> 1163.0128 | O32: =SUM(C32:N32) -> 22609.239 | P32: =P13*$B51 -> 1213.4509 | Q32: =Q13*$B51 -> 1708.2293 | R32: =R13*$B51 -> 404.79075 | S32: =S13*$B51 -> 245.49525 | T32: =T13*$B51 -> 428.43938 | U32: =U13*$B51 -> 270.16762 | V32: =V13*$B51 -> 286.54763 | W32: =W13*$B51 -> 384.41813 | ... AA32: =AA13*$B51 -> 82.411875 | AB32: =SUM(P32:AA32) -> 5812.443 | AC32: =AC13*$B51 -> 76.78125 | AD32: =AD13*$B51 -> 99.610875 | AE32: =AE13*$B51 -> 64.393875 | AF32: =AF13*$B51 -> 63.882 | AG32: =AG13*$B51 -> 102.7845 | AH32: =AH13*$B51 -> 69.2055 | AI32: =AI13*$B51 -> 75.14325 | AJ32: =AJ13*$B51 -> 108.108 | ... AN32: =AN13*$B51 -> 69.41025 | AO32: =SUM(AC32:AN32) -> 996.41588 | AP32: =AP13*$B51 -> 90.70425 | AQ32: =AQ13*$B51 -> 101.76075 | AR32: =AR13*$B51 -> 87.530625 | AS32: =AS13*$B51 -> 97.8705 | AT32: =AT13*$B51 -> 91.830375 | AU32: =AU13*$B51 -> 0 | AV32: =AV13*$B51 -> 0 | AW32: =AW13*$B51 -> 0 | ... BA32: =BA13*$B51 -> 0 | BB32: =SUM(AP32:BA32) -> 469.6965
A34: 157001150258 Hydromorphone ER Frt Exp | B34: 7165i | C34: ='Download COV'!D34 -> 0 | D34: ='Download COV'!E34 -> 0 | E34: ='Download COV'!F34 -> 0 | F34: ='Download COV'!G34 -> 0 | G34: =G15*$B53 -> 0 | H34: =H15*$B53 -> 0 | I34: =I15*$B53 -> 0 | J34: =J15*$B53 -> 0 | K34: =K15*$B53 -> 0 | L34: =L15*$B53 -> 0 | M34: =M15*$B53 -> 0 | N34: =N15*$B53 -> 0 | O34: =SUM(C34:N34) -> 0 | P34: =P15*$B53 -> 0 | Q34: =Q15*$B53 -> 0 | R34: =R15*$B53 -> 0 | S34: =S15*$B53 -> 0 | T34: =T15*$B53 -> 0 | U34: =U15*$B53 -> 0 | V34: =V15*$B53 -> 37.298625 | W34: =W15*$B53 -> 31.565625 | ... AA34: =AA15*$B53 -> 104.59313 | AB34: =SUM(P34:AA34) -> 385.749 | AC34: =AC15*$B53 -> 130.0845 | AD34: =AD15*$B53 -> 123.36188 | AE34: =AE15*$B53 -> 133.87238 | AF34: =AF15*$B53 -> 173.18438 | AG34: =AG15*$B53 -> 149.53575 | AH34: =AH15*$B53 -> 181.51088 | AI34: =AI15*$B53 -> 205.05713 | AJ34: =AJ15*$B53 -> 149.22863 | ... AN34: =AN15*$B53 -> 156.32663 | AO34: =SUM(AC34:AN34) -> 1959.4575 | AP34: =AP15*$B53 -> 156.32663 | AQ34: =AQ15*$B53 -> 176.05832 | AR34: =AR15*$B53 -> 177.18414 | AS34: =AS15*$B53 -> 178.30995 | AT34: =AT15*$B53 -> 188.73871 | AU34: =AU15*$B53 -> 0 | AV34: =AV15*$B53 -> 0 | AW34: =AW15*$B53 -> 0 | ... BA34: =BA15*$B53 -> 0 | BB34: =SUM(AP34:BA34) -> 876.61774
A36: 157001150268 Roxicodone-Freight | B36: 7165i | C36: ='Download COV'!D36 -> 60 | D36: ='Download COV'!E36 -> 129 | E36: ='Download COV'!F36 -> 153 | F36: ='Download COV'!G36 -> 200 | G36: =G17*$B55 -> 146.61423 | H36: =H17*$B55 -> 117.41119 | I36: =I17*$B55 -> 138.20625 | J36: =J17*$B55 -> 126.70613 | K36: =K17*$B55 -> 108.61988 | L36: =L17*$B55 -> 158.49058 | M36: =M17*$B55 -> 129.54779 | N36: =N17*$B55 -> 119.58782 | O36: =SUM(C36:N36) -> 1587.1839 | P36: =P17*$B55 -> 159.46796 | Q36: =Q17*$B55 -> 115.479 | R36: =R17*$B55 -> 111.45225 | S36: =S17*$B55 -> 152.81359 | T36: =T17*$B55 -> 122.91825 | U36: =U17*$B55 -> 117.32175 | V36: =V17*$B55 -> 146.94409 | W36: =W17*$B55 -> 122.91825 | ... AA36: =AA17*$B55 -> 129.06075 | AB36: =SUM(P36:AA36) -> 1565.56 | AC36: =AC17*$B55 -> 129.06259 | AD36: =AD17*$B55 -> 129.06075 | AE36: =AE17*$B55 -> 129.06075 | AF36: =AF17*$B55 -> 129.06259 | AG36: =AG17*$B55 -> 129.06075 | AH36: =AH17*$B55 -> 129.06075 | AI36: =AI17*$B55 -> 129.06259 | AJ36: =AJ17*$B55 -> 129.06075 | ... AN36: =AN17*$B55 -> 129.06075 | AO36: =SUM(AC36:AN36) -> 1548.7364 | AP36: =AP17*$B55 -> 129.06259 | AQ36: =AQ17*$B55 -> 129.06075 | AR36: =AR17*$B55 -> 129.06075 | AS36: =AS17*$B55 -> 130.52813 | AT36: =AT17*$B55 -> 135.14865 | AU36: =AU17*$B55 -> 0 | AV36: =AV17*$B55 -> 0 | AW36: =AW17*$B55 -> 0 | ... BA36: =BA17*$B55 -> 0 | BB36: =SUM(AP36:BA36) -> 652.86086
A37: 157001150269 Intrathecal-Freight | B37: 7165i | C37: ='Download COV'!D37 -> 0 | D37: ='Download COV'!E37 -> 0 | E37: ='Download COV'!F37 -> 0 | F37: ='Download COV'!G37 -> 0 | G37: 0 | H37: 0 | I37: 0 | J37: 0 | K37: 0 | L37: 0 | M37: 0 | N37: 0 | O37: =SUM(C37:N37) -> 0 | P37: 0 | Q37: 0 | R37: 0 | S37: 0 | T37: 0 | U37: 0 | V37: 0 | W37: 0 | X37: 0 | Y37: 0 | Z37: 0 | AA37: 0 | AB37: =SUM(P37:AA37) -> 0 | AC37: 3000 | AD37: =AC37 -> 3000 | AE37: =AD37 -> 3000 | AF37: =AE37 -> 3000 | AG37: =AF37 -> 3000 | AH37: =AG37 -> 3000 | AI37: =AH37 -> 3000 | AJ37: =AI37 -> 3000 | AK37: =AJ37 -> 3000 | ... AN37: =AM37 -> 3000 | AO37: =SUM(AC37:AN37) -> 36000 | AP37: 3500 | AQ37: =AP37 -> 3500 | AR37: =AQ37 -> 3500 | AS37: =AR37 -> 3500 | AT37: =AS37 -> 3500 | AU37: =AT37 -> 3500 | AV37: =AU37 -> 3500 | AW37: =AV37 -> 3500 | AX37: =AW37 -> 3500 | ... BA37: =AZ37 -> 3500 | BB37: =SUM(AP37:BA37) -> 42000
A38: 157210151269 Intrathecal-Freight-General | B38: 7165i | C38: ='Download COV'!D38 -> 0 | D38: ='Download COV'!E38 -> 0 | E38: ='Download COV'!F38 -> 0 | F38: ='Download COV'!G38 -> -8000 | G38: =G19*0.1 -> 330 | H38: =H19*0.1 -> 275 | I38: =I19*0.1 -> 250 | J38: =J19*0.1 -> 250 | K38: =K19*0.1 -> 250 | L38: =L19*0.1 -> 250 | M38: =M19*0.1 -> 250 | N38: =N19*0.1 -> 250 | O38: =SUM(C38:N38) -> -5895 | P38: =P19*0.1 -> 500 | Q38: =Q19*0.1 -> 500 | R38: =R19*0.1 -> 500 | S38: =S19*0.1 -> 500 | T38: =T19*0.1 -> 500 | U38: =U19*0.1 -> 500 | V38: =V19*0.1 -> 500 | W38: =W19*0.1 -> 500 | ... AA38: =AA19*0.1 -> 500 | AB38: =SUM(P38:AA38) -> 6000
A39: 168210151269 Intrathecal-Freight-General | B39: 7165i | C39: ='Download COV'!D39 -> 0 | D39: ='Download COV'!E39 -> 0 | E39: ='Download COV'!F39 -> 21324.15 | F39: ='Download COV'!G39 -> 0 | O39: =SUM(C39:N39) -> 21324.15 | AB39: =SUM(P39:AA39) -> 0 | AO39: =SUM(AC39:AN39) -> 0 | BB39: =SUM(AP39:BA39) -> 0
A40: 168210152000 Intrathecal-2000 mcg/mi | B40: 7165i | C40: ='Download COV'!D40 -> 0 | D40: ='Download COV'!E40 -> 0 | E40: ='Download COV'!F40 -> 0 | F40: ='Download COV'!G40 -> 0 | O40: =SUM(C40:N40) -> 0 | AB40: =SUM(P40:AA40) -> 0 | AO40: =SUM(AC40:AN40) -> 0 | BB40: =SUM(AP40:BA40) -> 0
A41: 157001150249 Hydrocodone/APAP GR | B41: 7165i | C41: ='Download COV'!D41 -> 0 | D41: ='Download COV'!E41 -> 0 | E41: ='Download COV'!F41 -> 0 | F41: ='Download COV'!G41 -> 0 | G41: =G22*$B57 -> 0 | H41: =H22*$B57 -> 0 | I41: =I22*$B57 -> 0 | J41: =J22*$B57 -> 0 | K41: =K22*$B57 -> 0 | L41: =L22*$B57 -> 0 | M41: =M22*$B57 -> 0 | N41: =N22*$B57 -> 0 | O41: =SUM(C41:N41) -> 0 | P41: =P22*$B57 -> 0 | Q41: =Q22*$B57 -> 0 | R41: =R22*$B57 -> 0 | S41: =S22*$B57 -> 0 | T41: =T22*$B57 -> 0 | U41: =U22*$B57 -> 0 | V41: =V22*$B57 -> 0 | W41: =W22*$B57 -> 0 | ... AA41: =AA22*$B57 -> 0 | AB41: =SUM(P41:AA41) -> 0 | AC41: =AC22*$B57 -> 0 | AD41: =AD22*$B57 -> 0 | AE41: =AE22*$B57 -> 0 | AF41: =AF22*$B57 -> 830.63663 | AG41: =AG22*$B57 -> 1661.3074 | AH41: =AH22*$B57 -> 2491.944 | AI41: =AI22*$B57 -> 2927.652 | AJ41: =AJ22*$B57 -> 3363.36 | ... AN41: =AN22*$B57 -> 5760.9143 | AO41: =SUM(AC41:AN41) -> 30394.83 | AP41: =AP22*$B57 -> 6177.171 | AQ41: =AQ22*$B57 -> 6729.7571 | AR41: =AR22*$B57 -> 7282.3433 | AS41: =AS22*$B57 -> 7845.3034 | AT41: =AT22*$B57 -> 8401.3475 | AU41: =AU22*$B57 -> 0 | AV41: =AV22*$B57 -> 0 | AW41: =AW22*$B57 -> 0 | ... BA41: =BA22*$B57 -> 0 | BB41: =SUM(AP41:BA41) -> 36435.922
A42: 157001150250 Oxyocodone/APAP GR | B42: 7165i | C42: ='Download COV'!D42 -> 0 | D42: ='Download COV'!E42 -> 0 | E42: ='Download COV'!F42 -> 0 | F42: ='Download COV'!G42 -> 0 | G42: =G23*$B58 -> 0 | H42: =H23*$B58 -> 0 | I42: =I23*$B58 -> 0 | J42: =J23*$B58 -> 0 | K42: =K23*$B58 -> 0 | L42: =L23*$B58 -> 0 | M42: =M23*$B58 -> 0 | N42: =N23*$B58 -> 0 | O42: =SUM(C42:N42) -> 0 | P42: =P23*$B58 -> 0 | Q42: =Q23*$B58 -> 0 | R42: =R23*$B58 -> 0 | S42: =S23*$B58 -> 0 | T42: =T23*$B58 -> 0 | U42: =U23*$B58 -> 0 | V42: =V23*$B58 -> 448.94464 | W42: =W23*$B58 -> 897.9234 | ... AA42: =AA23*$B58 -> 2056.5715 | AB42: =SUM(P42:AA42) -> 8153.7471 | AC42: =AC23*$B58 -> 2350.5531 | AD42: =AD23*$B58 -> 2696.6375 | AE42: =AE23*$B58 -> 3042.756 | AF42: =AF23*$B58 -> 3343.3687 | AG42: =AG23*$B58 -> 3643.9814 | AH42: =AH23*$B58 -> 3944.6283 | AI42: =AI23*$B58 -> 4280.4608 | AJ42: =AJ23*$B58 -> 4616.3616 | ... AN42: =AN23*$B58 -> 5945.2964 | AO42: =SUM(AC42:AN42) -> 49713.797 | AP42: =AP23*$B58 -> 5834.6463 | AQ42: =AQ23*$B58 -> 5847.9309 | AR42: =AR23*$B58 -> 5863.1607 | AS42: =AS23*$B58 -> 6566.7208 | AT42: =AT23*$B58 -> 6813.9159 | AU42: =AU23*$B58 -> 0 | AV42: =AV23*$B58 -> 0 | AW42: =AW23*$B58 -> 0 | ... BA42: =BA23*$B58 -> 0 | BB42: =SUM(AP42:BA42) -> 30926.375
B44: FY12Act
A45: 157001150245 Tofranil-PM/ImipraPam Frt Exp | B45: 0.25 | G45: =SUM(G7:G44) -> 12937.327 | H45: =SUM(H7:H44) -> 10033.056 | I45: =SUM(I7:I44) -> 11413.219 | J45: =SUM(J7:J44) -> 13706.124 | K45: =SUM(K7:K44) -> 10266.553 | L45: =SUM(L7:L44) -> 10536.743 | M45: =SUM(M7:M44) -> 11817.175 | N45: =SUM(N7:N44) -> 11004.232 | O45: =SUM(O7:O44) -> 169183.62
A46: 157001150225 Frt Exp-CNS Non-Promoted Prod | B46: 0.25
A48: 157001150251 Pennsaid Frt Expense | B48: 0.25
A49: 157001150255 Pennsaid 2% Pump Frt Expense | B49: 0.25
A50: 157001150256 Diclofenac 2% Pump Frt Exp | B50: 0.25
A51: 157001150252 Exalgo Freight Exp | B51: 0.75
A53: 157001150258 Hydromorphone ER Frt Exp | B53: 0.25
A55: 157001150268 Roxicodone-Freight | B55: 0.25
A56: 157001150269 Intrathecal-Freight
A57: 157001150249 Hydrocodone/APAP GR | B57: 0.25
A58: 157001150250 Oxyocodone/APAP GR | B58: 0.25

Sheet Download COV Act
B1: 2011 Actuals | C1: 7171i Out-freight Expense
B2: Oct
A3: 157001150211 Frt Exp-Hydrocodone Products
A4: 157001150210 Frt Exp-Oxycodone Products
A5: 157001150244 Oxycodone APAP-Frt Exp
A6: 157001150222 Frt Exp-ADHD
A7: 157001150227 Oxycodone ER Products Freight
A8: 157001150229 Morphine ER-Frt Exp
A9: 157001150230 Hydromorphone-Frt Exp
A10: 157001150231 Methadone Generics-Frt Exp
A11: 157001150232 APAP Codeine-Frt Exp
A12: 157001150233 APAP Propoxyphene-Frt Exp
A13: 157001150234 Fentanyl Lozenge-Frt Exp
A14: 157001150236 Fentanyl Patch-Frt Exp
... A29: WW Spec Pharma - CYR
B31: =B1 -> 2011 Actuals | C31: 7165i In-freight Expense
B32: Oct
A33: WW Spec Pharma - CYR
B35: =B31 -> 2011 Actuals | C35: Freight Expense
B36: Oct
A37: WW Spec Pharma - CYR
B40: Working Forecast | C40: 7171i Out-freight Expense
B41: Annual
A42: 157001150211 Frt Exp-Hydrocodone Products | B42: 1726234.8
A43: 157001150210 Frt Exp-Oxycodone Products | B43: 663354.39
A44: 157001150244 Oxycodone APAP-Frt Exp | B44: 1015529.3
A45: 157001150222 Frt Exp-ADHD | B45: 170593.3
A46: 157001150229 Morphine ER-Frt Exp | B46: 165338.12
A47: 157001150230 Hydromorphone-Frt Exp | B47: 196057.47
A48: 157001150231 Methadone Generics-Frt Exp | B48: 495762.89
A49: 157001150232 APAP Codeine-Frt Exp | B49: 98905.075
A50: 157001150233 APAP Propoxyphene-Frt Exp | B50: 3437
A51: 157001150234 Fentanyl Lozenge-Frt Exp | B51: 155460.73
A52: 157001150236 Fentanyl Patch-Frt Exp | B52: 73626.694
A53: 157001150253 Temazepam-Frt Exp | B53: 6085.9708
... A64: WW Spec Pharma - CYR | B64: 7828656.2
B66: Working Forecast | C66: 7165i In-freight Expense
B67: Annual
A68: WW Spec Pharma - CYR | B68: 226227.86
B70: Working Forecast | C70: Freight Expense
B71: Annual
A72: WW Spec Pharma - CYR | B72: 8054884.1

Sheet Download COV
C2: Local Cur Total | D2: Local Cur Total
C3: Input | D3: Input
C4: FY 2012 | D4: FY 2013 | E4: FY 2013 | F4: FY 2013 | G4: FY 2013 | H4: FY 2013 | I4: FY 2013 | J4: FY 2013 | K4: FY 2013 | L4: FY 2013 | M4: FY 2013 | N4: FY 2013 | O4: FY 2013 | P4: FY 2013 | Q4: FY 2014 | R4: FY 2014 | S4: FY 2014 | T4: FY 2014 | U4: FY 2014 | V4: FY 2014 | W4: FY 2014 | X4: FY 2014 | Y4: FY 2014 | Z4: FY 2014 | AA4: FY 2014 | AB4: FY 2014 | AC4: FY 2014 | AD4: FY 2015 | AE4: FY 2015 | AF4: FY 2015 | AG4: FY 2015 | AH4: FY 2015 | AI4: FY 2015 | AJ4: FY 2015 | AK4: FY 2015 | AL4: FY 2015 | AM4: FY 2015 | AN4: FY 2015 | AO4: FY 2015 | AP4: FY 2015 | AQ4: FY 2016 | AR4: FY 2016 | AS4: FY 2016 | AT4: FY 2016 | AU4: FY 2016 | AV4: FY 2016 | AW4: FY 2016 | AX4: FY 2016 | AY4: FY 2016 | AZ4: FY 2016 | BA4: FY 2016 | BB4: FY 2016 | BC4: FY 2016
C5: Actuals | D5: Actuals | E5: Actuals | F5: Actuals | G5: Actuals | H5: Working Forecast | I5: Working Forecast | J5: Working Forecast | K5: Working Forecast | L5: Working Forecast | M5: Working Forecast | N5: Working Forecast | O5: Working Forecast | P5: Working Forecast | Q5: Working Forecast | R5: Working Forecast | S5: Working Forecast | T5: Working Forecast | U5: Working Forecast | V5: Working Forecast | W5: Working Forecast | X5: Working Forecast | Y5: Working Forecast | Z5: Working Forecast | AA5: Working Forecast | AB5: Working Forecast | AC5: Working Forecast | AD5: Working Forecast | AE5: Working Forecast | AF5: Working Forecast | AG5: Working Forecast | AH5: Working Forecast | AI5: Working Forecast | AJ5: Working Forecast | AK5: Working Forecast | AL5: Working Forecast | AM5: Working Forecast | AN5: Working Forecast | AO5: Working Forecast | AP5: Working Forecast | AQ5: Working Forecast | AR5: Working Forecast | AS5: Working Forecast | AT5: Working Forecast | AU5: Working Forecast | AV5: Working Forecast | AW5: Working Forecast | AX5: Working Forecast | AY5: Working Forecast | AZ5: Working Forecast | BA5: Working Forecast | BB5: Working Forecast | BC5: Working Forecast
C6: Annual | D6: Oct | E6: Nov | F6: Dec | G6: Jan | H6: Feb | I6: Mar | J6: Apr | K6: May | L6: Jun | M6: Jul | N6: Aug | O6: Sep | P6: Annual | Q6: Oct | R6: Nov | S6: Dec | T6: Jan | U6: Feb | V6: Mar | W6: Apr | X6: May | Y6: Jun | Z6: Jul | AA6: Aug | AB6: Sep | AC6: Annual | AD6: Oct | AE6: Nov | AF6: Dec | AG6: Jan | AH6: Feb | AI6: Mar | AJ6: Apr | AK6: May | AL6: Jun | AM6: Jul | AN6: Aug | AO6: Sep | AP6: Annual | AQ6: Oct | AR6: Nov | AS6: Dec | AT6: Jan | AU6: Feb | AV6: Mar | AW6: Apr | AX6: May | AY6: Jun | AZ6: Jul | BA6: Aug | BB6: Sep | BC6: Annual
A7: 157001150245 Tofranil-PM/ImipraPam Frt Exp | B7: 7171i Out-freight Expense | C7: 780 | D7: 0 | E7: 0 | F7: 42 | G7: 46 | H7: 75.075 | I7: 58.2855 | J7: 62.517 | K7: 70.8435 | L7: 55.692 | M7: 56.9205 | N7: 67.431 | O7: 55.8285 | P7: 590.593 | Q7: 54.1905 | R7: 62.517 | S7: 50.3685 | T7: 49.2765 | U7: 62.1075 | V7: 50.6415 | W7: 49.5495 | X7: 56.784 | Y7: 50.778 | Z7: 44.772 | AA7: 59.1045 | AB7: 46.137 | AC7: 636.2265 | AD7: 46.0005 | AE7: 54.1905 | AF7: 42.9975 | AG7: 41.496 | AH7: 54.6 | AI7: 46.956 | AJ7: 44.772 | AK7: 53.781 | AL7: 46.41 | AM7: 41.769 | AN7: 57.33 | AO7: 41.6325 | AP7: 571.935 | AQ7: 49.959 | AR7: 39.312 | AS7: 45.4545 | AT7: 43.407 | AU7: 43.66635 | AV7: 0 | AW7: 0 | AX7: 0 | AY7: 0 | AZ7: 0 | BA7: 0 | BB7: 0 | BC7: 221.79885
A8: 157001150225 Frt Exp-CNS Non-Promoted Prod | B8: 7171i Out-freight Expense | C8: 10621 | D8: 890 | E8: 1055 | F8: 605 | G8: 751 | H8: 935.62102 | I8: 712.09193 | J8: 733.28621 | K8: 772.1805 | L8: 635.817 | M8: 601.27947 | N8: 645.1302 | O8: 597.8163 | P8: 8934.2226 | Q8: 702.89955 | R8: 716.625 | S8: 612.885 | T8: 666.55904 | U8: 737.919 | V8: 635.1345 | W8: 672.9047 | X8: 702.0195 | Y8: 639.5025 | Z8: 657.58261 | AA8: 730.821 | AB8: 641.9595 | AC8: 8116.8119 | AD8: 612.5818 | AE8: 708.708 | AF8: 599.9175 | AG8: 578.82977 | AH8: 711.711 | AI8: 638.6835 | AJ8: 611.39432 | AK8: 700.9275 | AL8: 629.9475 | AM8: 582.00979 | AN8: 728.7735 | AO8: 587.9055 | AP8: 7691.3897 | AQ8: 641.14405 | AR8: 564.564 | AS8: 604.51418 | AT8: 601.64768 | AU8: 625.24398 | AV8: 0 | AW8: 0 | AX8: 0 | AY8: 0 | AZ8: 0 | BA8: 0 | BB8: 0 | BC8: 3037.1139
A9: 157001150235 Tussicaps-Frt Exp | B9: 7171i Out-freight Expense | C9: 0 | D9: 0 | E9: 0 | F9: 0 | G9: 0 | H9: 0 | I9: 0 | J9: 0 | K9: 0 | L9: 0 | M9: 0 | N9: 0 | O9: 0 | P9: 0 | Q9: 0 | R9: 0 | S9: 0 | T9: 0 | U9: 0 | V9: 0 | W9: 0 | X9: 0 | Y9: 0 | Z9: 0 | AA9: 0 | AB9: 0 | AC9: 0 | AD9: 0 | AE9: 0 | AF9: 0 | AG9: 0 | AH9: 0 | AI9: 0 | AJ9: 0 | AK9: 0 | AL9: 0 | AM9: 0 | AN9: 0 | AO9: 0 | AP9: 0 | AQ9: 0 | AR9: 0 | AS9: 0 | AT9: 0 | AU9: 0 | AV9: 0 | AW9: 0 | AX9: 0 | AY9: 0 | AZ9: 0 | BA9: 0 | BB9: 0 | BC9: 0
A10: 157001150251 Pennsaid Frt Expense | B10: 7171i Out-freight Expense | C10: 47083 | D10: 2075 | E10: 2641 | F10: 1565 | G10: 2371 | H10: 3388.2488 | I10: 2482.3439 | J10: 3936.7669 | K10: 5143.0628 | L10: 3256.9797 | M10: 3239.557 | N10: 3307.9556 | O10: 3300.4321 | P10: 36707.347 | Q10: 2711.6328 | R10: 1802.6256 | S10: 1194.7814 | T10: 775.40845 | U10: 507.84481 | V10: 324.07744 | W10: 324.64067 | X10: 328.22328 | Y10: 332.07724 | Z10: 334.11048 | AA10: 337.42367 | AB10: 339.03812 | AC10: 9311.8841 | AD10: 341.44711 | AE10: 293.33626 | AF10: 184.9982 | AG10: 110.86985 | AH10: 62.958981 | AI10: 29.991041 | AJ10: 7.4783745 | AK10: 0 | AL10: 0 | AM10: 0 | AN10: 0 | AO10: 0 | AP10: 1031.0798 | AQ10: 0 | AR10: 0 | AS10: 0 | AT10: 0 | AU10: 0 | AV10: 0 | AW10: 0 | AX10: 0 | AY10: 0 | AZ10: 0 | BA10: 0 | BB10: 0 | BC10: 0
A11: 157001150255 Pennsaid 2% Pump Frt Expense | B11: 7171i Out-freight Expense | C11: 0 | D11: 0 | E11: 0 | F11: 0 | G11: 0 | H11: 0 | I11: 0 | J11: 0 | K11: 0 | L11: 0 | M11: 0 | N11: 0 | O11: 0 | P11: 0 | Q11: 2967.3735 | R11: 2050.4249 | S11: 1801.9365 | T11: 2902.6725 | U11: 3296.5404 | V11: 2528.1165 | W11: 3098.004 | X11: 3394.6315 | Y11: 2615.067 | Z11: 3056.9175 | AA11: 3575.754 | AB11: 3302.8905 | AC11: 34590.329 | AD11: 3073.0245 | AE11: 3105.9795 | AF11: 2580.5325 | AG11: 2186.8665 | AH11: 1951.2646 | AI11: 1779.96 | AJ11: 1653.4245 | AK11: 1580.9959 | AL11: 1612.611 | AM11: 1634.8605 | AN11: 1664.1461 | AO11: 1684.41 | AP11: 24508.076 | AQ11: 1687.14 | AR11: 1759.485 | AS11: 1769.04 | AT11: 1820.455 | AU11: 1861.405 | AV11: 0 | AW11: 0 | AX11: 0 | AY11: 0 | AZ11: 0 | BA11: 0 | BB11: 0 | BC11: 8897.525
A12: 157001150256 Diclofenac 2% Pump Frt Exp | B12: 7171i Out-freight Expense | C12: 0 | D12: 0 | E12: 0 | F12: 0 | G12: 0 | H12: 0 | I12: 0 | J12: 0 | K12: 0 | L12: 0 | M12: 0 | N12: 0 | O12: 0 | P12: 0 | Q12: 0 | R12: 0 | S12: 0 | T12: 0 | U12: 0 | V12: 0 | W12: 0 | X12: 0 | Y12: 0 | Z12: 0 | AA12: 0 | AB12: 0 | AC12: 0 | AD12: 0 | AE12: 0 | AF12: 0 | AG12: 0 | AH12: 0 | AI12: 0 | AJ12: 0 | AK12: 0 | AL12: 0 | AM12: 0 | AN12: 0 | AO12: 0 | AP12: 0 | AQ12: 0 | AR12: 0 | AS12: 0 | AT12: 0 | AU12: 0 | AV12: 0 | AW12: 0 | AX12: 0 | AY12: 0 | AZ12: 0 | BA12: 0 | BB12: 0 | BC12: 0
A13: 157001150252 Exalgo Freight Exp | B13: 7171i Out-freight Expense | C13: 13007 | D13: 1447 | E13: 1893 | F13: 705 | G13: 1303 | H13: 1757.4715 | I13: 1345.7707 | J13: 1175.1285 | K13: 1622.8485 | L13: 1164.4815 | M13: 1212.6253 | N13: 1939.3085 | O13: 1550.6837 | P13: 17116.318 | Q13: 1617.9345 | R13: 2277.639 | S13: 539.721 | T13: 327.327 | U13: 571.2525 | V13: 360.2235 | W13: 382.0635 | X13: 512.5575 | Y13: 369.096 | Z13: 361.5885 | AA13: 320.6385 | AB13: 109.8825 | AC13: 7749.924 | AD13: 102.375 | AE13: 132.8145 | AF13: 85.8585 | AG13: 85.176 | AH13: 137.046 | AI13: 92.274 | AJ13: 100.191 | AK13: 144.144 | AL13: 92.6835 | AM13: 96.5055 | AN13: 166.9395 | AO13: 92.547 | AP13: 1328.5545 | AQ13: 120.939 | AR13: 135.681 | AS13: 116.7075 | AT13: 130.494 | AU13: 122.4405 | AV13: 0 | AW13: 0 | AX13: 0 | AY13: 0 | AZ13: 0 | BA13: 0 | BB13: 0 | BC13: 626.262
A14: 157001150257 Exalgo 32 Frt Exp | B14: 7171i Out-freight Expense | C14: 0 | D14: 0 | E14: 0 | F14: 0 | G14: 0 | H14: 0 | I14: 0 | J14: 0 | K14: 0 | L14: 0 | M14: 0 | N14: 0 | O14: 0 | P14: 0 | Q14: 0 | R14: 0 | S14: 0 | T14: 0 | U14: 0 | V14: 0 | W14: 0 | X14: 0 | Y14: 0 | Z14: 0 | AA14: 0 | AB14: 0 | AC14: 0 | AD14: 0 | AE14: 0 | AF14: 0 | AG14: 0 | AH14: 0 | AI14: 0 | AJ14: 0 | AK14: 0 | AL14: 0 | AM14: 0 | AN14: 0 | AO14: 0 | AP14: 0 | AQ14: 0 | AR14: 0 | AS14: 0 | AT14: 0 | AU14: 0 | AV14: 0 | AW14: 0 | AX14: 0 | AY14: 0 | AZ14: 0 | BA14: 0 | BB14: 0 | BC14: 0
A15: 157001150258 Hydromorphone ER Frt Exp | B15: 7171i Out-freight Expense | C15: 0 | D15: 0 | E15: 0 | F15: 0 | G15: 0 | H15: 0 | I15: 0 | J15: 0 | K15: 0 | L15: 0 | M15: 0 | N15: 0 | O15: 0 | P15: 0 | Q15: 0 | R15: 0 | S15: 0 | T15: 0 | U15: 0 | V15: 0 | W15: 149.1945 | X15: 126.2625 | Y15: 174.72 | Z15: 352.5795 | AA15: 321.867 | AB15: 418.3725 | AC15: 1542.996 | AD15: 520.338 | AE15: 493.4475 | AF15: 535.4895 | AG15: 692.7375 | AH15: 598.143 | AI15: 726.0435 | AJ15: 820.2285 | AK15: 596.9145 | AL15: 700.9275 | AM15: 902.9475 | AN15: 625.3065 | AO15: 625.3065 | AP15: 7837.83 | AQ15: 625.3065 | AR15: 704.23328 | AS15: 708.73654 | AT15: 713.2398 | AU15: 754.95482 | AV15: 0 | AW15: 0 | AX15: 0 | AY15: 0 | AZ15: 0 | BA15: 0 | BB15: 0 | BC15: 3506.4709
A16: 157001150259 Hydromorphone ER 32 Frt Exp | B16: 7171i Out-freight Expense | C16: 0 | D16: 0 | E16: 0 | F16: 0 | G16: 0 | H16: 0 | I16: 0 | J16: 0 | K16: 0 | L16: 0 | M16: 0 | N16: 0 | O16: 0 | P16: 0 | Q16: 0 | R16: 0 | S16: 0 | T16: 0 | U16: 0 | V16: 0 | W16: 0 | X16: 0 | Y16: 0 | Z16: 0 | AA16: 0 | AB16: 0 | AC16: 0 | AD16: 0 | AE16: 0 | AF16: 0 | AG16: 0 | AH16: 0 | AI16: 0 | AJ16: 0 | AK16: 0 | AL16: 0 | AM16: 0 | AN16: 0 | AO16: 0 | AP16: 0 | AQ16: 0 | AR16: 0 | AS16: 0 | AT16: 0 | AU16: 0 | AV16: 0 | AW16: 0 | AX16: 0 | AY16: 0 | AZ16: 0 | BA16: 0 | BB16: 0 | BC16: 0
A17: 157001150268 Roxicodone-Freight | B17: 7171i Out-freight Expense | C17: 879 | D17: 668 | E17: 561 | F17: 209 | G17: 646 | H17: 586.45692 | I17: 469.64474 | J17: 552.825 | K17: 506.8245 | L17: 434.4795 | M17: 633.96232 | N17: 518.19117 | O17: 478.3513 | P17: 6264.7354 | Q17: 637.87186 | R17: 461.916 | S17: 445.809 | T17: 611.25436 | U17: 491.673 | V17: 469.287 | W17: 587.77636 | X17: 491.673 | Y17: 445.809 | Z17: 635.82436 | AA17: 467.103 | AB17: 516.243 | AC17: 6262.2399 | AD17: 516.25036 | AE17: 516.243 | AF17: 516.243 | AG17: 516.25036 | AH17: 516.243 | AI17: 516.243 | AJ17: 516.25036 | AK17: 516.243 | AL17: 516.243 | AM17: 516.25036 | AN17: 516.243 | AO17: 516.243 | AP17: 6194.9454 | AQ17: 516.25036 | AR17: 516.243 | AS17: 516.243 | AT17: 522.1125 | AU17: 540.5946 | AV17: 0 | AW17: 0 | AX17: 0 | AY17: 0 | AZ17: 0 | BA17: 0 | BB17: 0 | BC17: 2611.4435
A18: 157001150269 Intrathecal-Freight | B18: 7171i Out-freight Expense | C18: 0 | D18: 0 | E18: 0 | F18: 0 | G18: 0 | H18: 0 | I18: 0 | J18: 0 | K18: 0 | L18: 0 | M18: 0 | N18: 0 | O18: 0 | P18: 0 | Q18: 0 | R18: 0 | S18: 0 | T18: 0 | U18: 0 | V18: 0 | W18: 0 | X18: 0 | Y18: 0 | Z18: 0 | AA18: 0 | AB18: 0 | AC18: 0 | AD18: 0 | AE18: 0 | AF18: 0 | AG18: 0 | AH18: 0 | AI18: 0 | AJ18: 0 | AK18: 0 | AL18: 0 | AM18: 0 | AN18: 0 | AO18: 0 | AP18: 0 | AQ18: 0 | AR18: 0 | AS18: 0 | AT18: 0 | AU18: 0 | AV18: 1295.783 | AW18: 1295.783 | AX18: 1619.7287 | AY18: 1295.783 | AZ18: 1295.783 | BA18: 1619.7287 | BB18: 1295.783 | BC18: 9718.3723
... A45: US Branded Pharmaceuticals - CYR | B45: Freight Expense | C45: 91662 | D45: 6837 | E45: 12198 | F45: 30707.15 | G45: 27727.04 | H45: 12937.327 | I45: 10033.056 | J45: 11413.219 | K45: 13706.124 | L45: 10266.553 | M45: 10536.743 | N45: 11817.175 | O45: 11004.232 | P45: 169183.62 | Q45: 17173.846 | R45: 15853.504 | S45: 11576.737 | T45: 12329.286 | U45: 12869.798 | V45: 11139.462 | W45: 14515.921 | X45: 17261.085 | Y45: 18202.7 | Z45: 20402.135 | AA45: 22026.284 | AB45: 22555.953 | AC45: 195906.71 | AD45: 22313.922 | AE45: 24353.639 | AF45: 24934.202 | AG45: 30208.844 | AH45: 35848.57 | AI45: 41056.514 | AJ45: 44871.416 | AK45: 48761.606 | AL45: 52431.163 | AM45: 57632.929 | AN45: 62787.044 | AO45: 67233.426 | AP45: 512433.27 | AQ45: 68170.48 | AR45: 71105.679 | AS45: 73986.743 | AT45: 80414.563 | AU45: 84572.919 | AV45: 4795.783 | AW45: 4795.783 | AX45: 5119.7287 | AY45: 4795.783 | AZ45: 4795.783 | BA45: 5119.7287 | BB45: 4795.783 | BC45: 412468.76
D46: =D24+D43-D45 -> 0 | E46: =E24+E43-E45 -> 0 | F46: =F24+F43-F45 -> 0 | G46: =G24+G43-G45 -> 0 | H46: =H24+H43-H45 -> 0 | I46: =I24+I43-I45 -> 0 | J46: =J24+J43-J45 -> 0 | K46: =K24+K43-K45 -> 0 | ... AP46: =AP24+AP43-AP45 -> 0
