Workbook
Name \0: #REF!
Name \0: #REF!
Name __________ALL2: [3]GERM3435!$A$1:$P$380
Name __________Sum1: '[4]P & L Qtrly Comp Chg 1 vs 2'!$W$8:$W$148
Name __________SUM2: [3]GERM3435!$A$300:$Q$347
Name _________ALL2: [3]GERM3435!$A$1:$P$380
Name _________Sum1: '[4]P & L Qtrly Comp Chg 1 vs 2'!$W$8:$W$148
Name _________SUM2: [3]GERM3435!$A$300:$Q$347
Name ________ALL2: [3]GERM3435!$A$1:$P$380
Name ________Sum1: '[4]P & L Qtrly Comp Chg 1 vs 2'!$W$8:$W$148
Name ________SUM2: [3]GERM3435!$A$300:$Q$347
Name _______ALL2: [3]GERM3435!$A$1:$P$380
Name _______Sum1: '[4]P & L Qtrly Comp Chg 1 vs 2'!$W$8:$W$148
Name _______SUM2: [3]GERM3435!$A$300:$Q$347
Name ______ALL2: [3]GERM3435!$A$1:$P$380
Name ______Sum1: '[4]P & L Qtrly Comp Chg 1 vs 2'!$W$8:$W$148
Name ______SUM2: [3]GERM3435!$A$300:$Q$347
Name _____ALL2: [3]GERM3435!$A$1:$P$380
Name _____Sum1: '[4]P & L Qtrly Comp Chg 1 vs 2'!$W$8:$W$148
Name _____SUM2: [3]GERM3435!$A$300:$Q$347
Name ____ALL2: [3]GERM3435!$A$1:$P$380
Name ____Sum1: '[4]P & L Qtrly Comp Chg 1 vs 2'!$W$8:$W$148
Name ____SUM2: [3]GERM3435!$A$300:$Q$347
Name ___ALL2: [3]GERM3435!$A$1:$P$380
Name ___Sum1: '[4]P & L Qtrly Comp Chg 1 vs 2'!$W$8:$W$148
Name ___SUM2: [3]GERM3435!$A$300:$Q$347
Name __ALL2: [3]GERM3435!$A$1:$P$380
Name __Sum1: '[4]P & L Qtrly Comp Chg 1 vs 2'!$W$8:$W$148
Name __SUM2: [3]GERM3435!$A$300:$Q$347
Name _2006Q4: '[5]2006 Q4 Personnel Summary'!$D$10:$O$1799
Name _2007Q1: '[5]2007 Q1 Personnel Summary'!$C$8:$O$1903
Name _2007Q1BookComp: '[5]Book Option Data'!$C$9:$BA$916
Name _2007Q1BookRSPComp: '[5]Book RSP Data'!$C$10:$AQ$136
Name _2007Q1PersonnelSummary: '[5]2007 Q1 Personnel Summary'!$C$8:$O$1903
Name _ALL2: [3]GERM3435!$A$1:$P$380
Name _EPs2: #REF!
Name _EPs2: #REF!
Name _EPs3: #REF!
Name _EPs3: #REF!
Name _EPs4: #REF!
Name _EPs4: #REF!
Name _EPs5: #REF!
Name _EPs5: #REF!
Name _GrantInformation: #REF!
Name _INT1: #REF!
Name _INT1: #REF!
Name _ISO_Calculaton: #REF!
Name _LTM1: #REF!
Name _LTM1: #REF!
Name _new1: '[6]Plan 00'!#REF!
Name _new1: '[6]Plan 00'!#REF!
Name _old1: #REF!
Name _old1: #REF!
Name _OptionType: '[7]2007Q2 Personnel Summary'!$F$9:$K$1935
Name _PMT1: #REF!
Name _PMT1: #REF!
Name _PriorGrantInformation: #REF!
Name _Sum1: '[4]P & L Qtrly Comp Chg 1 vs 2'!$W$8:$W$148
Name _SUM2: [3]GERM3435!$A$300:$Q$347
Name _tic1: #REF!

Sheet Account Reconciliation Review
B1: Juul Lab
B2: Account Reconciliation
B3: 141110 - Freight In
B4: Date: 12/31/2018
B6: Description of Account being reconciled (To be completed by Preparer) | C6: This account is used to record freight in.
B7: Prepared by / Date: | C7: David Bortz
B8: Reviewed by / Date:
B12: Review Steps (to be completed by Reviewer):
B13: Review Step | D13: Response
B14: Does the beginning balance per the roll-forward tie to the prior period trial balance?
B15: Have all period transactions (i.e.warranty charges) been processed and has the sub-ledger been closed/locked?
B16: Is the current period final GL balance listed and tie to the final trial balance?
B17: Are there adequate descriptions included on the reconciliation to explain supporting items and account balances?
B18: Does the subledger balance agree to the final trial balance?
B19: Are all variances greater than $X,XXX or x% of the account balance properly investigated and explained.
B20: Do the amounts included in the reconciliation tie to supporting documentation?
B21: Are supporting reports/documents (i.e. payment for warranty claims) included in the reconciliation file or clearly referenced to a separate file?
B22: Are there amounts booked to the GL, not included in the supporting documentation (i.e. inventory on-hand, receipts, returns, inventory adjustment support, etc)? If so, have these been adequately explained and supported?
B23: Review mathematical accuracy of reconciliation/supporting documentation.
B24: Do the supporting documents include a report or spreadsheet? (specify which one)
B25: If yes, please indicate how you confirm the accuracy and completeness of the report or spreadsheet?
... B27: Other steps performed (please describe):
A30: # | B30: Review Comment / Action Item | C30: Comment Date | D30: Preparer Response | F30: Response Date | G30: Status
A31: 1
A32: 2
A33: 3
A34: 4
A35: 5

Sheet reconciliation
A2: Subledger Recon: | E2: {a} | G2: {b} | M2: {c}
C3: Period | D3: Classification | E3: Beg. Bal - December | G3: Additions | I3: Release | K3: Reconciling Items | M3: Ending Balance- December
C5: November | D5: Freight In | E5: ='Trial Balance Dec 2018'!D13 -> 0.01 | M5: ='Trial Balance Dec 2018'!D13 -> 0.01
C6: December | D6: Freight In | E6: 0 | G6: =JE_CA!G2 -> 313318.49 | M6: =E6+G6+I6 -> 313318.49
M7: =E7+G7+I7+K7 -> 0
M8: =E8+G8+I8+K8 -> 0
M9: =E9+G9+I9+K9 -> 0
M10: =E10+G10+I10+K10 -> 0
M11: =E11+G11+I11+K11 -> 0
D13: Total | E13: =SUM(E5:E11) -> 0.01 | M13: =SUM(M5:M11) -> 313318.5 | N13: #FQ-141110
D14: Trial Balance | E14: ='Trial Balance Dec 2018'!D13 -> 0.01 | M14: ='Trial Balance Dec 2018'!G13 -> 313318.5
D15: Check | E15: =E14-E13 -> 0 | M15: =M14-M13 -> 0.00179
C17: Refer to NOTES tab for additional information pertaining to balances.

Sheet Note
B1: Notes
A3: {a} | B3: Obtained balance from 'Trial Balance Summary' in Acumatica ERP system.
A5: {b} | B5: Obtained JE and JE support for all entires posted
A7: {c} | B7: Calculated ending balance and agreed to ACM without exception.

Sheet JE_CA
A1: Account | B1: Description | C1: Subaccount | D1: Ref. Number | E1: Quantity | F1: UOM | G1: Debit Amount | H1: Credit Amount | I1: Transaction Description | J1: Reclass. Batch Number
A2: 141110 | B2: Freight In | C2: NACAN-CRP-4600-JUL | G2: =Summary!D36 -> 313318.49 | I2: CA Freight in Accrual_Dec
A3: 515000 | B3: Freight Inbound | C3: NACAN-CRP-4600-JUL | G3: =Summary!D37 -> 119237.84 | I3: CA Freight in expense_Dec
A4: 240102 | B4: I/C Payable - CA | C4: NACAN-CRP-6000-JUL | H4: =Summary!E38 -> 432556.33 | I4: CA Freight in_interco_Dec

Sheet JE_US
A1: Account | B1: Description | C1: Subaccount | D1: Ref. Number | E1: Quantity | F1: UOM | G1: Debit Amount | H1: Credit Amount | I1: Transaction Description | J1: Reclass. Batch Number
A2: 180155 | B2: I/C Receivable - InterCo USD | C2: NACAN-CRP-6000-JUL | G2: 432556.33 | I2: CA Freight in _interco_Dec
A3: 515000 | B3: Freight In COGS | C3: NACAN-CRP-6000-JUL | H3: 432556.33 | I3: CA Freight in _interco_Dec

Sheet Summary
D2: Quantity
B3: Quantities | C3: Units Shipped December 2018 | D3: On-Hand as of 12/31/2018 | E3: TOTAL
B4: BK | C4: =SUMIFS(' Shipments Dec 2018'!M:M,' Shipments Dec 2018'!N:N,Summary!$B4) -> 67290 | D4: =SUMIFS(OnHand_Dec2018!R:R,OnHand_Dec2018!G:G,Summary!$D$2,OnHand_Dec2018!S:S,Summary!B4) -> 140820 | E4: =C4+D4 -> 208110
B5: SK | C5: =SUMIFS(' Shipments Dec 2018'!M:M,' Shipments Dec 2018'!N:N,Summary!$B5) -> 72886 | D5: =SUMIFS(OnHand_Dec2018!R:R,OnHand_Dec2018!G:G,Summary!$D$2,OnHand_Dec2018!S:S,Summary!B5) -> 109500 | E5: =C5+D5 -> 182386 | P5: FPU Analysis Backup
B6: RK | C6: =SUMIFS(' Shipments Dec 2018'!M:M,' Shipments Dec 2018'!N:N,Summary!$B6) -> 831056 | D6: =SUMIFS(OnHand_Dec2018!R:R,OnHand_Dec2018!G:G,Summary!$D$2,OnHand_Dec2018!S:S,Summary!B6) -> 2401400 | E6: =C6+D6 -> 3232456
B7: ACC | C7: =SUMIFS(' Shipments Dec 2018'!M:M,' Shipments Dec 2018'!N:N,Summary!$B7) -> 38966 | D7: =SUMIFS(OnHand_Dec2018!R:R,OnHand_Dec2018!G:G,Summary!$D$2,OnHand_Dec2018!S:S,Summary!B7) -> 176937 | E7: =C7+D7 -> 215903
B9: TOTAL | C9: =SUM(C4:C8) -> 1010198 | D9: =SUM(D4:D8) -> 2828657 | E9: =C9+D9 -> 3838855
B11: Freight Rates (in USD)
B12: BK | C12: 0.925 | D12: 0.925
B13: SK | C13: 0.017 | D13: 0.017
B14: RK | C14: 0.008 | D14: 0.008
B15: ACC | C15: 0.442 | D15: 0.442
B17: (in USD)
B18: BK | C18: =C4*C12 -> 62243.25 | D18: =D4*D12 -> 130258.5 | E18: =SUM(C18:D18) -> 192501.75
B19: SK | C19: =C5*C13 -> 1239.062 | D19: =D5*D13 -> 1861.5 | E19: =SUM(C19:D19) -> 3100.562
B20: RK | C20: =C6*C14 -> 6648.448 | D20: =D6*D14 -> 19211.2 | E20: =SUM(C20:D20) -> 25859.648
B21: ACC | C21: =C7*C15 -> 17222.972 | D21: =D7*D15 -> 78206.154 | E21: =SUM(C21:D21) -> 95429.126
B23: TOTAL | C23: =SUM(C18:C22) -> 87353.732 | D23: =SUM(D18:D22) -> 229537.35 | E23: =C23+D23 -> 316891.09
B26: (in CAD)
B27: BK | C27: =C18*$I$28 -> 84962.036 | D27: =D18*$I$28 -> 177802.85 | E27: =SUM(C27:D27) -> 262764.89
B28: SK | C28: =C19*$I$28 -> 1691.3196 | D28: =D19*$I$28 -> 2540.9475 | E28: =SUM(C28:D28) -> 4232.2671 | H28: FX Rate | I28: 1.365
B29: RK | C29: =C20*$I$28 -> 9075.1315 | D29: =D20*$I$28 -> 26223.288 | E29: =SUM(C29:D29) -> 35298.42
B30: ACC | C30: =C21*$I$28 -> 23509.357 | D30: =D21*$I$28 -> 106751.4 | E30: =SUM(C30:D30) -> 130260.76
B32: TOTAL | C32: =SUM(C27:C31) -> 119237.84 | D32: =SUM(D27:D31) -> 313318.49 | E32: =C32+D32 -> 432556.33
D34: Dr | E34: Cr
A35: CA Entries (in CAD)
A36: 141110 | B36: Freight In | D36: =D32 -> 313318.49
A37: 515000 | B37: Freight Inbound | D37: =C32 -> 119237.84
A38: 240102 | B38: I/C Payable - CA | E38: =D36+D37 -> 432556.33
A41: US Entries (in CAD)
A42: 180155 | B42: I/C Receivable - InterCo USD | D42: =E38 -> 432556.33
A43: 515000 | B43: Freight In COGS | E43: =E38 -> 432556.33

Sheet Shipments
C1: Shipment Details by Inventory Item | H1: Start Date: | I1: 43221 | L1: Page: | M1: 1 of 57
C2: Company: | D2: JUUL CA | H2: End Date: | I2: 43465 | L2: Date: | M2: 43469.774
C3: User: | D3: Karen.Fu
A5: Inventory ID | B5: Item Description | C5: Type | D5: Ref. Nbr. | E5: Operation | F5: Order Status | G5: Order Number | H5: Customer ID | I5: Customer Name | J5: Warehouse | K5: UOM | L5: Order Qty. | M5: Shipped Qty. | O5: INV Type
A6: J1A2399 | B6: JUUL CA USB Charger | C6: BO | D6: SH05-00000076 | E6: Issue | F6: Completed | G6: SO05-00000012 | H6: 05-00000008 | I6: Greenlane | J6: DSLOCATION | K6: EA | L6: 3840 | M6: 3840 | O6: =VLOOKUP(A6,'Item Master'!A:D,4,FALSE) -> Acc
A7: J1A2399 | B7: JUUL CA USB Charger | C7: BO | D7: SH05-00000079 | E7: Issue | F7: Completed | G7: SO05-00000017 | H7: 05-00000004 | I7: Core-Mark International, Inc. | J7: DSLOCATION | K7: EA | L7: 8640 | M7: 8640 | O7: =VLOOKUP(A7,'Item Master'!A:D,4,FALSE) -> Acc
A8: J1A2399 | B8: JUUL CA USB Charger | C8: BO | D8: SH05-00000077 | E8: Issue | F8: Completed | G8: SO05-00000066 | H8: 05-00000009 | I8: Wallace & Carey Inc. | J8: DSLOCATION | K8: EA | L8: 1536 | M8: 1536 | O8: =VLOOKUP(A8,'Item Master'!A:D,4,FALSE) -> Acc
A9: J1A2399 | B9: JUUL CA USB Charger | C9: BO | D9: SH05-00000078 | E9: Issue | F9: Completed | G9: SO05-00000067 | H9: 05-00000004 | I9: Core-Mark International, Inc. | J9: DSLOCATION | K9: EA | L9: 4608 | M9: 4608 | O9: =VLOOKUP(A9,'Item Master'!A:D,4,FALSE) -> Acc
A10: J1A2399 | B10: JUUL CA USB Charger | C10: BO | D10: SH05-00000173 | E10: Issue | F10: Completed | G10: SO05-00000076 | H10: 05-00000004 | I10: Core-Mark International, Inc. | J10: GO DIRECT | K10: EA | L10: 4560 | M10: 4560 | O10: =VLOOKUP(A10,'Item Master'!A:D,4,FALSE) -> Acc
A11: J1A2399 | B11: JUUL CA USB Charger | C11: BO | D11: SH05-00000178 | E11: Issue | F11: Completed | G11: SO05-00000083 | H11: 05-00000008 | I11: Greenlane | J11: GO DIRECT | K11: EA | L11: 1920 | M11: 1920 | O11: =VLOOKUP(A11,'Item Master'!A:D,4,FALSE) -> Acc
A12: J1A2399 | B12: JUUL CA USB Charger | C12: BO | D12: SH05-00000175 | E12: Issue | F12: Completed | G12: SO05-00000086 | H12: 05-00000002 | I12: Pacific Smoke International Inc. | J12: GO DIRECT | K12: EA | L12: 2400 | M12: 2400 | O12: =VLOOKUP(A12,'Item Master'!A:D,4,FALSE) -> Acc
A13: J1A2399 | B13: JUUL CA USB Charger | C13: BO | D13: SH05-00000180 | E13: Issue | F13: Completed | G13: SO05-00000164 | H13: 05-00000004 | I13: Core-Mark International, Inc. | J13: GO DIRECT | K13: EA | L13: 2112 | M13: 2112 | O13: =VLOOKUP(A13,'Item Master'!A:D,4,FALSE) -> Acc
A14: J1A2399 | B14: JUUL CA USB Charger | C14: BO | D14: SH05-00000176 | E14: Issue | F14: Completed | G14: SO05-00000168 | H14: 05-00000009 | I14: Wallace & Carey Inc. | J14: GO DIRECT | K14: EA | L14: 1200 | M14: 1200 | O14: =VLOOKUP(A14,'Item Master'!A:D,4,FALSE) -> Acc
A15: J1A2399 | B15: JUUL CA USB Charger | C15: BO | D15: SH05-00000177 | E15: Issue | F15: Completed | G15: SO05-00000170 | H15: 05-00000009 | I15: Wallace & Carey Inc. | J15: GO DIRECT | K15: EA | L15: 48 | M15: 48 | O15: =VLOOKUP(A15,'Item Master'!A:D,4,FALSE) -> Acc
A16: J1A2399 | B16: JUUL CA USB Charger | C16: BO | D16: SH05-00000222 | E16: Issue | F16: Completed | G16: SO05-00000171 | H16: 05-00000012 | I16: Sobeys Capital Inc. | J16: GO DIRECT | K16: EA | L16: 96 | M16: 96 | O16: =VLOOKUP(A16,'Item Master'!A:D,4,FALSE) -> Acc
A17: J1A2399 | B17: JUUL CA USB Charger | C17: BO | D17: SH05-00000221 | E17: Issue | F17: Completed | G17: SO05-00000172 | H17: 05-00000012 | I17: Sobeys Capital Inc. | J17: GO DIRECT | K17: EA | L17: 48 | M17: 48 | O17: =VLOOKUP(A17,'Item Master'!A:D,4,FALSE) -> Acc
... A2436: J1T2578 | B2436: JUULpods CA Cucumber Refill Kit, 3%, 4 pods | C2436: BO | D2436: SH05-00000479 | E2436: Issue | F2436: Completed | G2436: SO05-00000371 | H2436: 05-00000021 | I2436: Beaudry & Cadrin | J2436: GO DIRECT | K2436: EA | L2436: 48 | M2436: 48 | O2436: =VLOOKUP(A2436,'Item Master'!A:D,4,FALSE) -> RK

Sheet OnHand_Dec2018
A1: Historical Inventory Valuation | K1: Page: | L1: 1 of 3
A2: Company: | B2: Juul Labs Canada, Ltd. | F2: Start Period: | G2: 12-2018 | K2: Date: | L2: 43469
A3: User: | B3: Karen.Fu | F3: End Period: | G3: 12-2018
S4: =SUBTOTAL(9,R:R) -> 14889398
A5: Period | B5: Inventory ID | C5: Description | D5: Warehouse | E5: Account | F5: Subaccount | G5: Type | H5: Beg. Cost/Qty. | I5: Receipt | J5: Transfer In | K5: Assembly In | L5: Credit Memo | M5: Adjustment | N5: Transfer Out | O5: Assembly Out | P5: Sale | Q5: Issue | R5: End Cost/Qty. | S5: Inv Type
A7: 12-2018 | B7: J1A2399 | C7: JUUL CA USB Charger | D7: DSLOCATION | E7: 141000 | F7: NACAN-CRP-6000-JAC | G7: Cost | H7: 51593.99 | I7: 0 | J7: 0 | K7: 0 | L7: 0 | M7: 0 | N7: 51591.89 | O7: 51591.89 | P7: 0 | Q7: 0 | R7: 2.1 | S7: =VLOOKUP(B7,'Item Master'!A:D,4,FALSE) -> Acc
A8: 12-2018 | B8: J1A2399 | C8: JUUL CA USB Charger | D8: DSLOCATION | E8: 141000 | F8: NACAN-CRP-6000-JAC | G8: Quantity | H8: 24577 | I8: 0 | J8: 0 | K8: 0 | L8: 0 | M8: 0 | N8: 24576 | O8: 24576 | P8: 0 | Q8: 0 | R8: 1 | S8: =VLOOKUP(B8,'Item Master'!A:D,4,FALSE) -> Acc
A9: 12-2018 | B9: J1A2399 | C9: JUUL CA USB Charger | D9: GO DIRECT | E9: 141000 | F9: NACAN-CRP-6000-JAC | G9: Cost | H9: 245787.5 | I9: 162373.1 | J9: 51591.89 | K9: 0 | L9: 0 | M9: 0 | N9: 0 | O9: 0 | P9: 82194.97 | Q9: 0 | R9: 377557.52 | S9: =VLOOKUP(B9,'Item Master'!A:D,4,FALSE) -> Acc
A10: 12-2018 | B10: J1A2399 | C10: JUUL CA USB Charger | D10: GO DIRECT | E10: 141000 | F10: NACAN-CRP-6000-JAC | G10: Quantity | H10: 116062 | I10: 75264 | J10: 24576 | K10: 0 | L10: 0 | M10: 0 | N10: 0 | O10: 0 | P10: 38966 | Q10: 0 | R10: 176936 | S10: =VLOOKUP(B10,'Item Master'!A:D,4,FALSE) -> Acc
A11: 12-2018 | B11: J1D2392 | C11: JUUL CA Starter Kit, 5% | D11: DSLOCATION | E11: 141000 | F11: NACAN-CRP-6000-JSK | G11: Cost | H11: 0 | I11: 0 | J11: 0 | K11: 0 | L11: 0 | M11: 0 | N11: 0 | O11: 0 | P11: 0 | Q11: 0 | R11: 0 | S11: =VLOOKUP(B11,'Item Master'!A:D,4,FALSE) -> SK
A12: 12-2018 | B12: J1D2392 | C12: JUUL CA Starter Kit, 5% | D12: DSLOCATION | E12: 141000 | F12: NACAN-CRP-6000-JSK | G12: Quantity | H12: 0 | I12: 0 | J12: 0 | K12: 0 | L12: 0 | M12: 0 | N12: 0 | O12: 0 | P12: 0 | Q12: 0 | R12: 0 | S12: =VLOOKUP(B12,'Item Master'!A:D,4,FALSE) -> SK
A13: 12-2018 | B13: J1D2392 | C13: JUUL CA Starter Kit, 5% | D13: GO DIRECT | E13: 141000 | F13: NACAN-CRP-6000-JSK | G13: Cost | H13: 3107129 | I13: 598678.15 | J13: 17756.76 | K13: 0 | L13: 0 | M13: 0 | N13: 0 | O13: 0 | P13: 1474625.4 | Q13: 0 | R13: 2248938.5 | S13: =VLOOKUP(B13,'Item Master'!A:D,4,FALSE) -> SK
A14: 12-2018 | B14: J1D2392 | C14: JUUL CA Starter Kit, 5% | D14: GO DIRECT | E14: 141000 | F14: NACAN-CRP-6000-JSK | G14: Quantity | H14: 152725 | I14: 28785 | J14: 876 | K14: 0 | L14: 0 | M14: 0 | N14: 0 | O14: 0 | P14: 72886 | Q14: 0 | R14: 109500 | S14: =VLOOKUP(B14,'Item Master'!A:D,4,FALSE) -> SK
A15: 12-2018 | B15: J1D2393 | C15: JUUL CA Device Kit | D15: DSLOCATION | E15: 141000 | F15: NACAN-CRP-6000-JUL | G15: Cost | H15: 0 | I15: 0 | J15: 0 | K15: 0 | L15: 0 | M15: 0 | N15: 0 | O15: 0 | P15: 0 | Q15: 0 | R15: 0 | S15: =VLOOKUP(B15,'Item Master'!A:D,4,FALSE) -> BK
A16: 12-2018 | B16: J1D2393 | C16: JUUL CA Device Kit | D16: DSLOCATION | E16: 141000 | F16: NACAN-CRP-6000-JUL | G16: Quantity | H16: 0 | I16: 0 | J16: 0 | K16: 0 | L16: 0 | M16: 0 | N16: 0 | O16: 0 | P16: 0 | Q16: 0 | R16: 0 | S16: =VLOOKUP(B16,'Item Master'!A:D,4,FALSE) -> BK
A17: 12-2018 | B17: J1D2393 | C17: JUUL CA Device Kit | D17: DSLOCATION | E17: 141000 | F17: NACAN-CRP-6000-JBK | G17: Cost | H17: 6042.98 | I17: 0 | J17: 0 | K17: 0 | L17: 0 | M17: 0 | N17: 0 | O17: 0 | P17: 0 | Q17: 0 | R17: 6042.98 | S17: =VLOOKUP(B17,'Item Master'!A:D,4,FALSE) -> BK
A18: 12-2018 | B18: J1D2393 | C18: JUUL CA Device Kit | D18: DSLOCATION | E18: 141000 | F18: NACAN-CRP-6000-JBK | G18: Quantity | H18: 373 | I18: 0 | J18: 0 | K18: 0 | L18: 0 | M18: 0 | N18: 0 | O18: 0 | P18: 0 | Q18: 0 | R18: 373 | S18: =VLOOKUP(B18,'Item Master'!A:D,4,FALSE) -> BK
... A66: 12-2018 | B66: J1T2578 | C66: JUULpods CA Cucumber Refill Kit, 3%, 4 pods | D66: GO DIRECT | E66: 141000 | F66: NACAN-CRP-6000-JRK | G66: Quantity | H66: 0 | I66: 90576 | J66: 0 | K66: 0 | L66: 0 | M66: 0 | N66: 0 | O66: 0 | P66: 432 | Q66: 0 | R66: 90144 | S66: =VLOOKUP(B66,'Item Master'!A:D,4,FALSE) -> RK

Sheet  Shipments Dec 2018
C1: Shipment Details by Inventory Item | H1: Start Date: | I1: 43435 | L1: Page: | M1: 1 of 23
C2: Company: | D2: JUUL CA | H2: End Date: | I2: 43465 | L2: Date: | M2: 43469.913
C3: User: | D3: Karen.Fu
A5: Inventory ID | B5: Item Description | C5: Type | D5: Ref. Nbr. | E5: Operation | F5: Order Status | G5: Order Number | H5: Customer ID | I5: Customer Name | J5: Warehouse | K5: UOM | L5: Order Qty. | M5: Shipped Qty.
A6: J1A2399 | B6: JUUL CA USB Charger | C6: BO | D6: SH05-00000375 | E6: Issue | F6: Completed | G6: SO05-00000311 | H6: 05-00000019 | I6: Karic Sales Limited | J6: GO DIRECT | K6: EA | L6: 576 | M6: 576 | N6: =VLOOKUP(A6,'Item Master'!A:D,4,FALSE) -> Acc
A7: J1A2399 | B7: JUUL CA USB Charger | C7: BO | D7: SH05-00000374 | E7: Issue | F7: Completed | G7: SO05-00000312 | H7: 05-00000019 | I7: Karic Sales Limited | J7: GO DIRECT | K7: EA | L7: 192 | M7: 192 | N7: =VLOOKUP(A7,'Item Master'!A:D,4,FALSE) -> Acc
A8: J1A2399 | B8: JUUL CA USB Charger | C8: BO | D8: SH05-00000380 | E8: Issue | F8: Completed | G8: SO05-00000335 | H8: 05-00000009 | I8: Wallace & Carey Inc. | J8: GO DIRECT | K8: EA | L8: 960 | M8: 960 | N8: =VLOOKUP(A8,'Item Master'!A:D,4,FALSE) -> Acc
A9: J1A2399 | B9: JUUL CA USB Charger | C9: BO | D9: SH05-00000381 | E9: Issue | F9: Completed | G9: SO05-00000336 | H9: 05-00000009 | I9: Wallace & Carey Inc. | J9: GO DIRECT | K9: EA | L9: 240 | M9: 240 | N9: =VLOOKUP(A9,'Item Master'!A:D,4,FALSE) -> Acc
A10: J1A2399 | B10: JUUL CA USB Charger | C10: BO | D10: SH05-00000383 | E10: Issue | F10: Completed | G10: SO05-00000339 | H10: 05-00000012 | I10: Sobeys Capital Inc. | J10: GO DIRECT | K10: EA | L10: 9792 | M10: 9792 | N10: =VLOOKUP(A10,'Item Master'!A:D,4,FALSE) -> Acc
A11: J1A2399 | B11: JUUL CA USB Charger | C11: BO | D11: SH05-00000387 | E11: Issue | F11: Completed | G11: SO05-00000340 | H11: 05-00000004 | I11: Core-Mark International, Inc. | J11: GO DIRECT | K11: EA | L11: 768 | M11: 768 | N11: =VLOOKUP(A11,'Item Master'!A:D,4,FALSE) -> Acc
A12: J1A2399 | B12: JUUL CA USB Charger | C12: BO | D12: SH05-00000389 | E12: Issue | F12: Completed | G12: SO05-00000342 | H12: 05-00000014 | I12: Pratts Wholesale | J12: GO DIRECT | K12: EA | L12: 48 | M12: 48 | N12: =VLOOKUP(A12,'Item Master'!A:D,4,FALSE) -> Acc
A13: J1A2399 | B13: JUUL CA USB Charger | C13: BO | D13: SH05-00000390 | E13: Issue | F13: Completed | G13: SO05-00000343 | H13: 05-00000014 | I13: Pratts Wholesale | J13: GO DIRECT | K13: EA | L13: 48 | M13: 48 | N13: =VLOOKUP(A13,'Item Master'!A:D,4,FALSE) -> Acc
A14: J1A2399 | B14: JUUL CA USB Charger | C14: BO | D14: SH05-00000396 | E14: Issue | F14: Completed | G14: SO05-00000345 | H14: 05-00000008 | I14: Greenlane | J14: GO DIRECT | K14: EA | L14: 384 | M14: 384 | N14: =VLOOKUP(A14,'Item Master'!A:D,4,FALSE) -> Acc
A15: J1A2399 | B15: JUUL CA USB Charger | C15: BO | D15: SH05-00000394 | E15: Issue | F15: Completed | G15: SO05-00000350 | H15: 05-00000002 | I15: Pacific Smoke International Inc. | J15: GO DIRECT | K15: EA | L15: 480 | M15: 480 | N15: =VLOOKUP(A15,'Item Master'!A:D,4,FALSE) -> Acc
A16: J1A2399 | B16: JUUL CA USB Charger | C16: BO | D16: SH05-00000400 | E16: Issue | F16: Completed | G16: SO05-00000351 | H16: 05-00000009 | I16: Wallace & Carey Inc. | J16: GO DIRECT | K16: EA | L16: 9552 | M16: 9552 | N16: =VLOOKUP(A16,'Item Master'!A:D,4,FALSE) -> Acc
A17: J1A2399 | B17: JUUL CA USB Charger | C17: BO | D17: SH05-00000399 | E17: Issue | F17: Completed | G17: SO05-00000352 | H17: 05-00000009 | I17: Wallace & Carey Inc. | J17: GO DIRECT | K17: EA | L17: 3408 | M17: 3408 | N17: =VLOOKUP(A17,'Item Master'!A:D,4,FALSE) -> Acc
... A939: J1T2578 | B939: JUULpods CA Cucumber Refill Kit, 3%, 4 pods | C939: BO | D939: SH05-00000479 | E939: Issue | F939: Completed | G939: SO05-00000371 | H939: 05-00000021 | I939: Beaudry & Cadrin | J939: GO DIRECT | K939: EA | L939: 48 | M939: 48 | N939: =VLOOKUP(A939,'Item Master'!A:D,4,FALSE) -> RK

Sheet Trial Balance Dec 2018
A1: Trial Balance Summary | D1: Ledger: | E1: ACTUAL | F1: Page: | G1: 1 of 3
A2: Company: | B2: JUUL CA | F2: Date: | G2: 43475.752
A3: User: | B3: jayden.xu | D3: Fin. Period: | E3: 12-2018
A5: Account | B5: Type | C5: Description | D5: Beginning Balance | E5: Debit | F5: Credit | G5: Ending Balance
A6: 112000 | B6: A | C6: CITIBANK - CAD | D6: 5899650.2 | E6: 5183323.2 | F6: 1824279.3 | G6: 9258694.2
A7: 119000 | B7: A | C7: Undeposited/Cash in Transit | D7: 0 | E7: 745780.15 | F7: 511970.6 | G7: 233809.55
A8: 119500 | B8: A | C8: Clearing Account | D8: 0 | E8: 638374.5 | F8: 638374.5 | G8: 0
A9: 121100 | B9: A | C9: Trade Accounts Receivable | D9: 13413374 | E9: 19449353 | F9: 6409053.4 | G9: 26453673
A10: 130200 | B10: A | C10: Prepaid Health Insurance | D10: 0 | E10: 23783.47 | F10: 23783.47 | G10: 0
A11: 130550 | B11: A | C11: Prepaid Legal | D11: 0 | E11: 34107.02 | F11: 5684.55 | G11: 28422.47
A12: 141000 | B12: A | C12: Inventory - Finished Products | D12: 9909726.5 | E12: 7558998.6 | F12: 5407497.6 | G12: 12061228
A13: 141110 | B13: A | C13: Freight In | D13: 0.01 | E13: 313318.49 | F13: 0 | G13: 313318.5
A14: 143100 | B14: A | C14: Deferred COGS | D14: 182406.35 | E14: 0 | F14: 0 | G14: 182406.35
A15: 180152 | B15: A | C15: I/C Receivable - US | D15: 3311858.2 | E15: 0 | F15: 0 | G15: 3311858.2
A16: 191000 | B16: A | C16: Deposits - Long Term | D16: 15928 | E16: 0 | F16: 0 | G16: 15928
A17: 200100 | B17: L | C17: Purchase Order Received (unbilled) | D17: 0 | E17: 7225325.9 | F17: 7225325.9 | G17: 0
... A90: 821200 | B90: E | C90: Unrealized (gain) loss - currency conversion | D90: 253407.1 | E90: 297589.89 | F90: 253856.37 | G90: 297140.62
C91: Total: | D91: -3.3178367e-09 | E91: 53242978 | F91: 53242978 | G91: -2.4097972e-08

Sheet Item Master
A1: Title: | B1: Katie - Item Record
A2: Company: | B2: Juul
A3: Date: | B3: 02 Jan 2019 14:08 PM GMT-08:00
C4: Manual Imput
A5: Item Code | B5: Status | C5: Clasification | D5: Inv Type | E5: 11.26 | F5: Description | G5: Item Class | H5: Item Type | I5: Kit? | J5: Valuation Method | K5: Tax Category | L5: Post Class ID | M5: Lot / Serial Class | N5: Inventory Account | O5: Inventory Sub | P5: Expense Account | Q5: Expense Sub | R5: Sales Account | S5: Sales Sub ID | T5: PO Accrual Account | U5: PO Accrual Sub | V5: PPV Account | W5: PPV Sub ID | X5: Landed Cost V Account | Y5: Landed Cost V Sub
A6: C1-BLK | B6: Inactive | C6: =VLOOKUP(A6,[1]Items!$A:$D,3,0) -> Inactive | D6: =VLOOKUP(A6,[1]Items!$A:$D,4,0) -> Inactive | E6: Inactive | F6: Pax - Black | G6: P1D | H6: Finished Good | I6: False | J6: FIFO | K6: TAXABLE | L6: PAX | M6: NOTTRACKED | N6: 141000 | O6: HCORP-CRP-4100-PAX | P6: 511000 | Q6: HCORP-CRP-4100-PAX | R6: 410000 | S6: HCORP-CRP-4100-PAX | T6: 200100 | U6: HCORP-CRP-4100-PAX | V6: 514000
A7: C1-POS-BRCH | B7: Active | C7: =VLOOKUP(A7,[1]Items!$A:$D,3,0) -> Inactive | D7: =VLOOKUP(A7,[1]Items!$A:$D,4,0) -> Inactive | E7: Inactive | F7: Pax Brochure | G7: NSK ITEMS | H7: Finished Good | I7: False | J7: FIFO | K7: TAXABLE | L7: PAX | M7: NOTTRACKED | N7: 141000 | O7: HCORP-CRP-4100-PAX | P7: 511000 | Q7: HCORP-CRP-4100-CRP | R7: 410000 | S7: HCORP-CRP-4100-CRP | T7: 200100 | U7: HCORP-CRP-4100-CRP | X7: 513000 | Y7: HCORP-CRP-4600-CRP
A8: PLOOM STICKER | B8: Active | C8: =VLOOKUP(A8,[1]Items!$A:$D,3,0) -> Inactive | D8: =VLOOKUP(A8,[1]Items!$A:$D,4,0) -> Inactive | E8: Inactive | F8: Ploom sticker | G8: NSK ITEMS | H8: Finished Good | I8: False | J8: FIFO | K8: TAXABLE | L8: CORP | M8: NOTTRACKED | N8: 730600 | O8: HCORP-CRP-5100-CRP | P8: 511000 | Q8: HCORP-CRP-4100-CRP | R8: 410000 | S8: HCORP-CRP-4100-CRP | T8: 200100 | U8: HCORP-CRP-5100-CRP | X8: 513000 | Y8: HCORP-CRP-4600-CRP
A9: MAGNET | B9: Active | C9: =VLOOKUP(A9,[1]Items!$A:$D,3,0) -> Inactive | D9: =VLOOKUP(A9,[1]Items!$A:$D,4,0) -> Inactive | E9: Inactive | F9: Pax - Magnet | G9: NSK ITEMS | H9: Finished Good | I9: False | J9: FIFO | K9: TAXABLE | L9: CORP | M9: NOTTRACKED | N9: 141000 | O9: HCORP-CRP-6000-CRP | P9: 511000 | Q9: HCORP-CRP-4100-CRP | R9: 410000 | S9: HCORP-CRP-4100-CRP | T9: 200100 | U9: HCORP-CRP-4100-CRP | X9: 513000 | Y9: HCORP-CRP-4600-CRP
A10: TSHIRT M L | B10: Active | C10: =VLOOKUP(A10,[1]Items!$A:$D,3,0) -> Inactive | D10: =VLOOKUP(A10,[1]Items!$A:$D,4,0) -> Inactive | E10: Inactive | F10: Mens Large Ploom T-shirt | G10: NSK ITEMS | H10: Finished Good | I10: False | J10: FIFO | K10: TAXABLE | L10: CORP | M10: NOTTRACKED | N10: 730600 | O10: HCORP-CRP-5100-CRP | P10: 511000 | Q10: HCORP-CRP-4100-CRP | R10: 410000 | S10: HCORP-CRP-4100-CRP | T10: 200100 | U10: HCORP-CRP-5100-CRP | X10: 513000 | Y10: HCORP-CRP-4600-CRP
A11: TSHIRT M M | B11: Active | C11: =VLOOKUP(A11,[1]Items!$A:$D,3,0) -> Inactive | D11: =VLOOKUP(A11,[1]Items!$A:$D,4,0) -> Inactive | E11: Inactive | F11: Mens M Ploom T-shirt | G11: NSK ITEMS | H11: Finished Good | I11: False | J11: FIFO | K11: TAXABLE | L11: CORP | M11: NOTTRACKED | N11: 730600 | O11: HCORP-CRP-5100-CRP | P11: 511000 | Q11: HCORP-CRP-4100-CRP | R11: 410000 | S11: HCORP-CRP-4100-CRP | T11: 200100 | U11: HCORP-CRP-5100-CRP | X11: 513000 | Y11: HCORP-CRP-4600-CRP
A12: TSHIRT M XL | B12: Active | C12: =VLOOKUP(A12,[1]Items!$A:$D,3,0) -> Inactive | D12: =VLOOKUP(A12,[1]Items!$A:$D,4,0) -> Inactive | E12: Inactive | F12: Mens XL Ploom T-shirt | G12: NSK ITEMS | H12: Finished Good | I12: False | J12: FIFO | K12: TAXABLE | L12: CORP | M12: NOTTRACKED | N12: 730600 | O12: HCORP-CRP-5100-CRP | P12: 511000 | Q12: HCORP-CRP-4100-CRP | R12: 410000 | S12: HCORP-CRP-4100-CRP | T12: 200100 | U12: HCORP-CRP-5100-CRP | X12: 513000 | Y12: HCORP-CRP-4600-CRP
A13: CARD DISPENSER | B13: Inactive | C13: =VLOOKUP(A13,[1]Items!$A:$D,3,0) -> Inactive | D13: =VLOOKUP(A13,[1]Items!$A:$D,4,0) -> Inactive | E13: Inactive | F13: Take Away Card Dispenser | G13: NSK ITEMS | H13: Finished Good | I13: False | J13: FIFO | K13: TAXABLE | L13: CORP | M13: NOTTRACKED | N13: 141000 | O13: HCORP-CRP-6000-CRP | P13: 511000 | Q13: HCORP-CRP-4100-CRP | R13: 410000 | S13: HCORP-CRP-4100-CRP | T13: 200100 | U13: HCORP-CRP-4100-CRP | X13: 513000 | Y13: HCORP-CRP-4600-CRP
A14: PRO-TIPS-CARD | B14: Active | C14: =VLOOKUP(A14,[1]Items!$A:$D,3,0) -> Inactive | D14: =VLOOKUP(A14,[1]Items!$A:$D,4,0) -> Inactive | E14: Inactive | F14: Pax Pro Tips Card | G14: NSK ITEMS | H14: Finished Good | I14: False | J14: FIFO | K14: TAXABLE | L14: CORP | M14: NOTTRACKED | N14: 730600 | O14: HCORP-CRP-5100-CRP | P14: 511000 | Q14: HCORP-CRP-4100-CRP | R14: 410000 | S14: HCORP-CRP-4100-CRP | T14: 200100 | U14: HCORP-CRP-5100-CRP | X14: 513000 | Y14: HCORP-CRP-4600-CRP
A15: C1-J02 | B15: Active | C15: =VLOOKUP(A15,[1]Items!$A:$D,3,0) -> Inactive | D15: =VLOOKUP(A15,[1]Items!$A:$D,4,0) -> Inactive | E15: Inactive | F15: Pax - Packaged Cleaning Kit - Not in Use | G15: P1A | H15: Finished Good | I15: False | J15: FIFO | K15: TAXABLE | L15: PAX | M15: NOTTRACKED | N15: 141000 | O15: HCORP-CRP-4100-PAX | P15: 511000 | Q15: HCORP-CRP-4100-PAX | R15: 410000 | S15: HCORP-CRP-4100-PAX | T15: 200100 | U15: HCORP-CRP-4100-PAX | X15: 513000 | Y15: HCORP-CRP-4600-CRP
A16: C1-J04 | B16: Active | C16: =VLOOKUP(A16,[1]Items!$A:$D,3,0) -> Inactive | D16: =VLOOKUP(A16,[1]Items!$A:$D,4,0) -> Inactive | E16: Inactive | F16: Pax - 3 Screens | G16: P1A | H16: Finished Good | I16: False | J16: FIFO | K16: TAXABLE | L16: PAX | M16: NOTTRACKED | N16: 141000 | O16: HCORP-CRP-4100-PAX | P16: 511000 | Q16: HCORP-CRP-4100-PAX | R16: 410000 | S16: HCORP-CRP-4100-PAX | T16: 200100 | U16: HCORP-CRP-4100-PAX | X16: 513000 | Y16: HCORP-CRP-4600-CRP
A17: C1-J05 | B17: Active | C17: =VLOOKUP(A17,[1]Items!$A:$D,3,0) -> Inactive | D17: =VLOOKUP(A17,[1]Items!$A:$D,4,0) -> Inactive | E17: Inactive | F17: Pax - Mouthpiece | G17: P1A | H17: Finished Good | I17: False | J17: FIFO | K17: TAXABLE | L17: PAX | M17: NOTTRACKED | N17: 141000 | O17: HCORP-CRP-4100-PAX | P17: 511000 | Q17: HCORP-CRP-4100-PAX | R17: 410000 | S17: HCORP-CRP-4100-PAX | T17: 200100 | U17: HCORP-CRP-4100-PAX | X17: 513000 | Y17: HCORP-CRP-4600-CRP
A18: C1-J07 | B18: Active | C18: =VLOOKUP(A18,[1]Items!$A:$D,3,0) -> Inactive | D18: =VLOOKUP(A18,[1]Items!$A:$D,4,0) -> Inactive | E18: Inactive | F18: Pax - Charging Dock | G18: P1A | H18: Finished Good | I18: False | J18: FIFO | K18: TAXABLE | L18: PAX | M18: NOTTRACKED | N18: 141000 | O18: HCORP-CRP-4100-PAX | P18: 511000 | Q18: HCORP-CRP-4100-PAX | R18: 410000 | S18: HCORP-CRP-4100-PAX | T18: 200100 | U18: HCORP-CRP-4100-PAX | X18: 513000 | Y18: HCORP-CRP-4600-CRP
... A29: C1-SLV | B29: Active | C29: =VLOOKUP(A29,[1]Items!$A:$D,3,0) -> Inactive | D29: =VLOOKUP(A29,[1]Items!$A:$D,4,0) -> Inactive | E29: Inactive | F29: Pax - Silver | G29: P1D | H29: Finished Good | I29: False | J29: FIFO | K29: TAXABLE | L29: PAX | M29: NOTTRACKED | N29: 141000 | O29: HCORP-CRP-4100-PAX | P29: 511000 | Q29: HCORP-CRP-4100-PAX | R29: 410000 | S29: HCORP-CRP-4100-PAX | T29: 200100 | U29: HCORP-CRP-4100-PAX | X29: 513000 | Y29: HCORP-CRP-4600-CRP
A30: P2D1013 | B30: Active | C30: =VLOOKUP(A30,[1]Items!$A:$D,3,0) -> Inactive | D30: =VLOOKUP(A30,[1]Items!$A:$D,4,0) -> Inactive | E30: Inactive | F30: PAX2 Device Platinum | G30: P2D | H30: Finished Good | I30: False | J30: FIFO | K30: TAXABLE | L30: PAX | M30: NOTTRACKED | N30: 141000 | O30: HCORP-CRP-4100-PAX | P30: 511000 | Q30: HCORP-CRP-4100-PAX | R30: 410000 | S30: HCORP-CRP-4100-PAX | T30: 200100 | U30: HCORP-CRP-4100-PAX | V30: 514000 | W30: HCORP-CRP-4100-PAX | X30: 513000 | Y30: HCORP-CRP-4600-CRP
A31: KIT1020 | B31: Active | C31: WIP | D31: Other | E31: WIP | F31: Portfolio shipper, singles | G31: NSK KITS | H31: Finished Good | I31: True | J31: FIFO | K31: TAXABLE | L31: CORP | M31: NOTTRACKED | N31: 140200 | O31: HCORP-CRP-6000-CRP | P31: 511000 | Q31: HCORP-CRP-4100-CRP | R31: 410000 | S31: HCORP-CRP-4100-CRP | T31: 200100 | U31: HCORP-CRP-4100-CRP | X31: 513000 | Y31: HCORP-CRP-4600-CRP
A32: S-9849 | B32: Active | C32: =VLOOKUP(A32,[1]Items!$A:$D,3,0) -> RM | D32: =VLOOKUP(A32,[1]Items!$A:$D,4,0) -> Pkg | E32: RM | F32: Indestructo Boxes | G32: PACKAGING | H32: Non-Stock Item | I32: False | J32: Standard | K32: TAXABLE | L32: CORP | P32: 511000 | Q32: HCORP-CRP-4100-JUL | T32: 200100 | U32: HCORP-CRP-6000-JUL | X32: 513000
A33: GIFT CARD | B33: Active | C33: =VLOOKUP(A33,[1]Items!$A:$D,3,0) -> GFC | D33: =VLOOKUP(A33,[1]Items!$A:$D,4,0) -> GFC | E33: GFC | F33: Gift Card | G33: GFC | H33: Non-Stock Item | I33: False | J33: Standard | K33: TAXABLE | L33: CORP | N33: 220100 | O33: HCORP-CRP-6000-JUL | P33: 511000 | Q33: HCORP-CRP-4100-JUL | T33: 200100 | U33: HCORP-CRP-6000-JUL | X33: 513000
A34: J1D1030 | B34: Active | C34: =VLOOKUP(A34,[1]Items!$A:$D,3,0) -> FG | D34: =VLOOKUP(A34,[1]Items!$A:$D,4,0) -> SK | E34: FG | F34: JUUL Starter Kit MT | G34: J1D | H34: Finished Good | I34: False | J34: FIFO | K34: TAXABLE | L34: JUL | M34: NOTTRACKED | N34: 141000 | O34: HCORP-CRP-6000-JUL | P34: 511000 | Q34: HCORP-CRP-4100-JUL | R34: 410000 | S34: HCORP-CRP-4100-JUL | T34: 200100 | U34: HCORP-CRP-4100-JUL | X34: 513000 | Y34: HCORP-CRP-4600-CRP
A35: P2D1010 | B35: Active | C35: =VLOOKUP(A35,[1]Items!$A:$D,3,0) -> Inactive | D35: =VLOOKUP(A35,[1]Items!$A:$D,4,0) -> Inactive | E35: Inactive | F35: PAX2 Device Charcoal | G35: P2D | H35: Finished Good | I35: False | J35: FIFO | K35: TAXABLE | L35: PAX | M35: NOTTRACKED | N35: 141000 | O35: HCORP-CRP-4100-PAX | P35: 511000 | Q35: HCORP-CRP-4100-PAX | R35: 410000 | S35: HCORP-CRP-4100-PAX | T35: 200100 | U35: HCORP-CRP-4100-PAX | V35: 514000 | W35: HCORP-CRP-4100-PAX | X35: 513000 | Y35: HCORP-CRP-4600-CRP
A36: P2D1011 | B36: Active | C36: =VLOOKUP(A36,[1]Items!$A:$D,3,0) -> Inactive | D36: =VLOOKUP(A36,[1]Items!$A:$D,4,0) -> Inactive | E36: Inactive | F36: PAX2 Device Topaz | G36: P2D | H36: Finished Good | I36: False | J36: FIFO | K36: TAXABLE | L36: PAX | M36: NOTTRACKED | N36: 141000 | O36: HCORP-CRP-4100-PAX | P36: 511000 | Q36: HCORP-CRP-4100-PAX | R36: 410000 | S36: HCORP-CRP-4100-PAX | T36: 200100 | U36: HCORP-CRP-4100-PAX | X36: 513000 | Y36: HCORP-CRP-4600-CRP
A37: P2D1012 | B37: Active | C37: =VLOOKUP(A37,[1]Items!$A:$D,3,0) -> Inactive | D37: =VLOOKUP(A37,[1]Items!$A:$D,4,0) -> Inactive | E37: Inactive | F37: PAX2 Device Flare | G37: P2D | H37: Finished Good | I37: False | J37: FIFO | K37: TAXABLE | L37: PAX | M37: NOTTRACKED | N37: 141000 | O37: HCORP-CRP-4100-PAX | P37: 511000 | Q37: HCORP-CRP-4100-PAX | R37: 410000 | S37: HCORP-CRP-4100-PAX | T37: 200100 | U37: HCORP-CRP-4100-PAX | X37: 513000 | Y37: HCORP-CRP-4600-CRP
A38: J1D1023 | B38: Active | C38: =VLOOKUP(A38,[1]Items!$A:$D,3,0) -> FG | D38: =VLOOKUP(A38,[1]Items!$A:$D,4,0) -> SK | E38: FG | F38: JUUL Starter Kit Slate 5.0% 2.8ml 4-Pack | G38: J1D | H38: Finished Good | I38: True | J38: FIFO | K38: TAXABLE | L38: JUL | M38: LOTCONTROL | N38: 141000 | O38: HCORP-CRP-6000-JUL | P38: 511000 | Q38: HCORP-CRP-4100-JUL | R38: 410000 | S38: HCORP-CRP-4100-JUL | T38: 200100 | U38: HCORP-CRP-4100-JUL | V38: 514000 | W38: HCORP-CRP-4600-JUL
A39: KIT1059 | B39: Active | C39: WIP | D39: Other | E39: WIP | F39: JUUL Component Device, Charger, Packaging | G39: COMPONENTS | H39: Component Part | I39: True | J39: FIFO | K39: TAXABLE | L39: JUL | M39: NOTTRACKED | N39: 140200 | O39: HCORP-CRP-6000-JUL | P39: 511000 | Q39: HCORP-CRP-4100-CRP | R39: 410000 | S39: HCORP-CRP-4100-CRP | T39: 200100 | U39: HCORP-CRP-4100-CRP | X39: 513000 | Y39: HCORP-CRP-4600-CRP
A40: KIT1061 | B40: Inactive | C40: WIP | D40: Other | E40: Inactive | F40: JUUL Starter Kit MT Labor, Packaging | G40: LABORCOGS | H40: Labor | I40: False | J40: Standard | K40: EXEMPT | L40: CORP | P40: 511000 | Q40: HCORP-CRP-4100-JUL | X40: 513000
A41: PAXSTICKER | B41: Active | C41: =VLOOKUP(A41,[1]Items!$A:$D,3,0) -> Inactive | D41: =VLOOKUP(A41,[1]Items!$A:$D,4,0) -> Inactive | E41: Inactive | F41: Pax sticker | G41: NSK ITEMS | H41: Finished Good | I41: False | J41: FIFO | K41: TAXABLE | L41: CORP | M41: NOTTRACKED | N41: 730600 | O41: HCORP-CRP-5100-PAX | P41: 511000 | Q41: HCORP-CRP-4100-CRP | R41: 410000 | S41: HCORP-CRP-4100-CRP | T41: 200100 | U41: HCORP-CRP-5100-PAX | X41: 513000
A42: PAXIITEST | B42: Inactive | C42: =VLOOKUP(A42,[1]Items!$A:$D,3,0) -> Inactive | D42: =VLOOKUP(A42,[1]Items!$A:$D,4,0) -> Inactive | E42: Inactive | F42: Pax 2 PN for testing | G42: P2D | H42: Finished Good | I42: False | J42: FIFO | K42: TAXABLE | L42: PAX | M42: NOTTRACKED | N42: 141000 | O42: HCORP-CRP-4100-PAX | P42: 511000 | Q42: HCORP-CRP-4100-PAX | R42: 410000 | S42: HCORP-CRP-4100-PAX | T42: 200100 | U42: HCORP-CRP-4100-PAX | X42: 513000 | Y42: HCORP-CRP-4600-CRP
A43: J1T1026 | B43: Active | C43: =VLOOKUP(A43,[1]Items!$A:$D,3,0) -> FG | D43: =VLOOKUP(A43,[1]Items!$A:$D,4,0) -> RK | E43: FG | F43: JUUL Pods, Mint, 5%, 4-Pack | G43: J1C | H43: Finished Good | I43: True | J43: FIFO | K43: TAXABLE | L43: JUL | M43: LOTCONTROL | N43: 141000 | O43: HCORP-CRP-6000-JUL | P43: 511000 | Q43: HCORP-CRP-4100-JUL | R43: 410000 | S43: HCORP-CRP-4100-JUL | T43: 200100 | U43: HCORP-CRP-4100-JUL | V43: 514000 | W43: HCORP-CRP-4100-JUL | X43: 513000 | Y43: HCORP-CRP-4600-JUL
A44: J1T1028 | B44: Active | C44: =VLOOKUP(A44,[1]Items!$A:$D,3,0) -> FG | D44: =VLOOKUP(A44,[1]Items!$A:$D,4,0) -> RK | E44: FG | F44: JUUL pods Virginia Tobacco 5% 2.8ml 4-Pack | G44: J1C | H44: Finished Good | I44: True | J44: FIFO | K44: TAXABLE | L44: JUL | M44: LOTCONTROL | N44: 141000 | O44: HCORP-CRP-6000-JUL | P44: 511000 | Q44: HCORP-CRP-4100-JUL | R44: 410000 | S44: HCORP-CRP-4100-JUL | T44: 200100 | U44: HCORP-CRP-4100-JUL | V44: 514000 | W44: HCORP-CRP-4100-JUL | X44: 513000 | Y44: HCORP-CRP-4600-CRP
A45: J1T1024 | B45: Active | C45: =VLOOKUP(A45,[1]Items!$A:$D,3,0) -> FG | D45: =VLOOKUP(A45,[1]Items!$A:$D,4,0) -> RK | E45: FG | F45: JUUL Pods, Creme, 5%, 4-Pack | G45: J1C | H45: Finished Good | I45: True | J45: FIFO | K45: TAXABLE | L45: JUL | M45: LOTCONTROL | N45: 141000 | O45: HCORP-CRP-6000-JUL | P45: 511000 | Q45: HCORP-CRP-4100-JUL | R45: 410000 | S45: HCORP-CRP-4100-JUL | T45: 200100 | U45: HCORP-CRP-4100-JUL | V45: 514000 | W45: HCORP-CRP-4100-JUL | X45: 513000 | Y45: HCORP-CRP-4600-CRP
A46: J1T1025 | B46: Active | C46: =VLOOKUP(A46,[1]Items!$A:$D,3,0) -> FG | D46: =VLOOKUP(A46,[1]Items!$A:$D,4,0) -> RK | E46: FG | F46: JUUL Pods, Fruit, 5%, 4-Pack | G46: J1C | H46: Finished Good | I46: True | J46: FIFO | K46: TAXABLE | L46: JUL | M46: LOTCONTROL | N46: 141000 | O46: HCORP-CRP-6000-JUL | P46: 511000 | Q46: HCORP-CRP-4100-JUL | R46: 410000 | S46: HCORP-CRP-4100-JUL | T46: 200100 | U46: HCORP-CRP-4100-JUL | V46: 514000 | W46: HCORP-CRP-4100-JUL
A47: J1T1027 | B47: Active | C47: =VLOOKUP(A47,[1]Items!$A:$D,3,0) -> FG | D47: =VLOOKUP(A47,[1]Items!$A:$D,4,0) -> RK | E47: FG | F47: JUUL pods Multipack | G47: J1C | H47: Finished Good | I47: True | J47: FIFO | K47: TAXABLE | L47: JUL | M47: LOTCONTROL | N47: 141000 | O47: HCORP-CRP-6000-JUL | P47: 511000 | Q47: HCORP-CRP-4100-JUL | R47: 410000 | S47: HCORP-CRP-4100-JUL | T47: 200100 | U47: HCORP-CRP-4100-JUL | V47: 514000 | W47: HCORP-CRP-4100-JUL | X47: 513000 | Y47: HCORP-CRP-4600-CRP
A48: J1T1031 | B48: Active | C48: =VLOOKUP(A48,[1]Items!$A:$D,3,0) -> FG | D48: =VLOOKUP(A48,[1]Items!$A:$D,4,0) -> RK | E48: FG | F48: JUUL pods Multipack MT | G48: J1C | H48: Finished Good | I48: False | J48: FIFO | K48: TAXABLE | L48: JUL | M48: NOTTRACKED | N48: 141000 | O48: HCORP-CRP-6000-JUL | P48: 511000 | Q48: HCORP-CRP-4100-JUL | R48: 410000 | S48: HCORP-CRP-4100-JUL | T48: 200100 | U48: HCORP-CRP-4100-JUL | X48: 513000 | Y48: HCORP-CRP-4600-CRP
A49: P2A1018 | B49: Active | C49: =VLOOKUP(A49,[1]Items!$A:$D,3,0) -> Inactive | D49: =VLOOKUP(A49,[1]Items!$A:$D,4,0) -> Inactive | E49: Inactive | F49: PAX2 Screens 3pk | G49: P2A | H49: Finished Good | I49: False | J49: FIFO | K49: TAXABLE | L49: PAX | M49: NOTTRACKED | N49: 141000 | O49: HCORP-CRP-4100-PAX | P49: 511000 | Q49: HCORP-CRP-4100-PAX | R49: 410000 | S49: HCORP-CRP-4100-PAX | T49: 200100 | U49: HCORP-CRP-4100-PAX | X49: 513000 | Y49: HCORP-CRP-4600-CRP
A50: P2A1016 | B50: Active | C50: =VLOOKUP(A50,[1]Items!$A:$D,3,0) -> Inactive | D50: =VLOOKUP(A50,[1]Items!$A:$D,4,0) -> Inactive | E50: Inactive | F50: PAX2 Mouthpiece 2pk flat | G50: P2A | H50: Finished Good | I50: False | J50: FIFO | K50: TAXABLE | L50: PAX | M50: NOTTRACKED | N50: 141000 | O50: HCORP-CRP-4100-PAX | P50: 511000 | Q50: HCORP-CRP-4100-PAX | R50: 410000 | S50: HCORP-CRP-4100-PAX | T50: 200100 | U50: HCORP-CRP-4100-PAX | X50: 513000 | Y50: HCORP-CRP-4600-CRP
A51: P2A1017 | B51: Active | C51: =VLOOKUP(A51,[1]Items!$A:$D,3,0) -> Inactive | D51: =VLOOKUP(A51,[1]Items!$A:$D,4,0) -> Inactive | E51: Inactive | F51: PAX2 Mouthpiece 2pk raised | G51: P2A | H51: Finished Good | I51: False | J51: FIFO | K51: TAXABLE | L51: PAX | M51: NOTTRACKED | N51: 141000 | O51: HCORP-CRP-4100-PAX | P51: 511000 | Q51: HCORP-CRP-4100-PAX | R51: 410000 | S51: HCORP-CRP-4100-PAX | T51: 200100 | U51: HCORP-CRP-4100-PAX | X51: 513000 | Y51: HCORP-CRP-4600-CRP
A52: P2A1021 | B52: Active | C52: =VLOOKUP(A52,[1]Items!$A:$D,3,0) -> Inactive | D52: =VLOOKUP(A52,[1]Items!$A:$D,4,0) -> Inactive | E52: Inactive | F52: PAX2 Cleaning kit | G52: P2A | H52: Finished Good | I52: False | J52: FIFO | K52: TAXABLE | L52: PAX | M52: NOTTRACKED | N52: 141000 | O52: HCORP-CRP-4100-PAX | P52: 511000 | Q52: HCORP-CRP-4100-PAX | R52: 410000 | S52: HCORP-CRP-4100-PAX | T52: 200100 | U52: HCORP-CRP-4100-PAX | X52: 513000 | Y52: HCORP-CRP-4600-CRP
A53: P2A1022 | B53: Active | C53: =VLOOKUP(A53,[1]Items!$A:$D,3,0) -> Inactive | D53: =VLOOKUP(A53,[1]Items!$A:$D,4,0) -> Inactive | E53: Inactive | F53: PAX2 Oven Lid | G53: P2A | H53: Finished Good | I53: False | J53: FIFO | K53: TAXABLE | L53: PAX | M53: NOTTRACKED | N53: 141000 | O53: HCORP-CRP-4100-PAX | P53: 511000 | Q53: HCORP-CRP-4100-PAX | R53: 410000 | S53: HCORP-CRP-4100-PAX | T53: 200100 | U53: HCORP-CRP-4100-PAX | X53: 513000 | Y53: HCORP-CRP-4600-CRP
A54: P2A1020 | B54: Active | C54: =VLOOKUP(A54,[1]Items!$A:$D,3,0) -> Inactive | D54: =VLOOKUP(A54,[1]Items!$A:$D,4,0) -> Inactive | E54: Inactive | F54: PAX2 Charging Dock | G54: P2A | H54: Finished Good | I54: False | J54: FIFO | K54: TAXABLE | L54: PAX | M54: NOTTRACKED | N54: 141000 | O54: HCORP-CRP-4100-PAX | P54: 511000 | Q54: HCORP-CRP-4100-PAX | R54: 410000 | S54: HCORP-CRP-4100-PAX | T54: 200100 | U54: HCORP-CRP-4100-PAX | X54: 513000 | Y54: HCORP-CRP-4600-CRP
A55: J1K1052 | B55: Active | C55: =VLOOKUP(A55,[1]Items!$A:$D,3,0) -> FG | D55: =VLOOKUP(A55,[1]Items!$A:$D,4,0) -> Acc | E55: FG | F55: JUUL Shipper with lock | G55: J1D | H55: Finished Good | I55: True | J55: FIFO | K55: TAXABLE | L55: JUL | M55: NOTTRACKED | N55: 141000 | O55: HCORP-CRP-6000-JUL | P55: 511000 | Q55: HCORP-B2B-4100-JUL | R55: 410000 | S55: HCORP-B2B-4100-JUL | T55: 200100 | U55: HCORP-B2B-4100-JUL | X55: 513000 | Y55: HCORP-CRP-4600-CRP
A56: MKT1093 | B56: Active | C56: =VLOOKUP(A56,[1]Items!$A:$D,3,0) -> Expense | D56: =VLOOKUP(A56,[1]Items!$A:$D,4,0) -> Expense | E56: Expense | F56: Shipping Box | G56: PACKAGING | H56: Non-Stock Item | I56: False | J56: Standard | K56: TAXABLE | L56: CORP | P56: 511000 | Q56: HCORP-CRP-4100-JUL | T56: 200100 | U56: HCORP-CRP-6000-JUL | X56: 513000
A57: MKT1095 | B57: Active | C57: =VLOOKUP(A57,[1]Items!$A:$D,3,0) -> Expense | D57: =VLOOKUP(A57,[1]Items!$A:$D,4,0) -> Expense | E57: Expense | F57: Exterior RETAILER ACTIVATION KIT Sticker | G57: PACKAGING | H57: Non-Stock Item | I57: False | J57: Standard | K57: TAXABLE | L57: CORP | P57: 511000 | Q57: HCORP-CRP-4100-JUL | T57: 200100 | U57: HCORP-CRP-6000-JUL | X57: 513000
A58: NSK1140 | B58: Active | C58: =VLOOKUP(A58,[1]Items!$A:$D,3,0) -> RM | D58: =VLOOKUP(A58,[1]Items!$A:$D,4,0) -> Pkg | E58: RM | F58: Easy Peel White round label | G58: PACKAGING | H58: Non-Stock Item | I58: False | J58: Standard | K58: TAXABLE | L58: CORP | P58: 511000 | Q58: HCORP-CRP-4100-JUL | T58: 200100 | U58: HCORP-CRP-6000-JUL | X58: 513000
A59: NSK1141 | B59: Inactive | C59: =VLOOKUP(A59,[1]Items!$A:$D,3,0) -> Inactive | D59: =VLOOKUP(A59,[1]Items!$A:$D,4,0) -> Inactive | E59: Inactive | F59: S-3385 PAX Generic Medium Shippers | G59: PACKAGING | H59: Non-Stock Item | I59: False | J59: Standard | K59: TAXABLE | L59: CORP | P59: 511000 | Q59: HCORP-CRP-4100-CRP | X59: 513000
A60: DISCOUNT | B60: Active | C60: =VLOOKUP(A60,[1]Items!$A:$D,3,0) -> GFC | D60: =VLOOKUP(A60,[1]Items!$A:$D,4,0) -> GFC | E60: GFC | F60: Discounts B2C | G60: GFC | H60: Non-Stock Item | I60: False | J60: Standard | K60: TAXABLE | L60: CORP | P60: 492000 | Q60: HCORP-B2C-4100-JUL | R60: 492000 | S60: HCORP-CRP-4100-JUL | X60: 513000
A61: FREIGHT | B61: Active | C61: =VLOOKUP(A61,[1]Items!$A:$D,3,0) -> Expense | D61: =VLOOKUP(A61,[1]Items!$A:$D,4,0) -> Expense | E61: Expense | F61: Freight B2C outbound | H61: Service | I61: False | J61: Standard | K61: EXEMPT | L61: CORP | N61: 220950 | O61: HCORP-CRP-6000-JUL | P61: 511000 | Q61: HCORP-B2C-6000-JUL | T61: 200100 | U61: HCORP-CRP-6000-JUL | X61: 513000
A62: P2A1055 | B62: Active | C62: =VLOOKUP(A62,[1]Items!$A:$D,3,0) -> Inactive | D62: =VLOOKUP(A62,[1]Items!$A:$D,4,0) -> Inactive | E62: Inactive | F62: PAX2 AC Adaptor | G62: P2A | H62: Finished Good | I62: False | J62: FIFO | K62: TAXABLE | L62: PAX | M62: NOTTRACKED | N62: 141000 | O62: HCORP-CRP-4100-PAX | P62: 511000 | Q62: HCORP-CRP-4100-PAX | R62: 410000 | S62: HCORP-CRP-4100-PAX | T62: 200100 | U62: HCORP-CRP-4100-PAX | X62: 513000 | Y62: HCORP-CRP-4600-CRP
A63: MKT1092 | B63: Inactive | C63: =VLOOKUP(A63,[1]Items!$A:$D,3,0) -> Inactive | D63: =VLOOKUP(A63,[1]Items!$A:$D,4,0) -> Inactive | E63: Inactive | F63: PAX2 Pack of Takeaway Cards | G63: EXPENSE | H63: Finished Good | I63: False | J63: FIFO | K63: TAXABLE | L63: MKT PAX | M63: NOTTRACKED | N63: 730600 | O63: HCORP-CRP-5100-PAX | P63: 730600 | Q63: HCORP-CRP-5100-PAX | R63: 410000 | S63: HCORP-CRP-5100-PAX | T63: 200100 | U63: HCORP-CRP-5100-PAX | V63: 514000 | W63: HCORP-CRP-5100-PAX | X63: 513000 | Y63: HCORP-CRP-5100-PAX
A64: KIT1083 | B64: Inactive | C64: WIP | D64: Other | E64: Inactive | F64: Launch retailer Activation Kit A | G64: NSK KITS | H64: Finished Good | I64: True | J64: FIFO | K64: TAXABLE | L64: CORP | M64: NOTTRACKED | N64: 141000 | O64: HCORP-CRP-6000-CRP | P64: 511000 | Q64: HCORP-CRP-4100-CRP | R64: 410000 | S64: HCORP-CRP-4100-CRP | T64: 200100 | U64: HCORP-CRP-4100-CRP | X64: 513000 | Y64: HCORP-CRP-4600-CRP
A65: MKT1146 | B65: Inactive | C65: =VLOOKUP(A65,[1]Items!$A:$D,3,0) -> Inactive | D65: =VLOOKUP(A65,[1]Items!$A:$D,4,0) -> Inactive | E65: Inactive | F65: PAX 2 Available Now Poster | G65: EXPENSE | H65: Finished Good | I65: False | J65: FIFO | K65: TAXABLE | L65: MKT PAX | M65: NOTTRACKED | N65: 730600 | O65: HCORP-CRP-5100-PAX | P65: 730600 | Q65: HCORP-CRP-5100-PAX | R65: 410000 | S65: HCORP-CRP-5100-PAX | T65: 200100 | U65: HCORP-CRP-5100-PAX | V65: 514000 | W65: HCORP-CRP-5100-PAX | X65: 513000 | Y65: HCORP-CRP-5100-PAX
A66: MKT1085 | B66: Inactive | C66: =VLOOKUP(A66,[1]Items!$A:$D,3,0) -> Inactive | D66: =VLOOKUP(A66,[1]Items!$A:$D,4,0) -> Inactive | E66: Inactive | F66: PAX2 Product Sell Sheet | G66: EXPENSE | H66: Finished Good | I66: False | J66: FIFO | K66: TAXABLE | L66: MKT PAX | M66: NOTTRACKED | N66: 730600 | O66: HCORP-CRP-5100-PAX | P66: 730600 | Q66: HCORP-CRP-5100-PAX | R66: 410000 | S66: HCORP-CRP-5100-PAX | T66: 200100 | U66: HCORP-CRP-5100-PAX | V66: 514000 | W66: HCORP-CRP-5100-PAX | X66: 513000 | Y66: HCORP-CRP-5100-PAX
A67: MKT1086 | B67: Active | C67: =VLOOKUP(A67,[1]Items!$A:$D,3,0) -> Inactive | D67: =VLOOKUP(A67,[1]Items!$A:$D,4,0) -> Inactive | E67: Inactive | F67: PAX2 Accessory Sell Sheet | G67: EXPENSE | H67: Finished Good | I67: False | J67: FIFO | K67: TAXABLE | L67: MKT PAX | M67: NOTTRACKED | N67: 730600 | O67: HCORP-CRP-5100-PAX | P67: 730600 | Q67: HCORP-CRP-5100-PAX | R67: 410000 | S67: HCORP-CRP-5100-PAX | T67: 200100 | U67: HCORP-CRP-5100-PAX | V67: 514000 | W67: HCORP-CRP-5100-PAX | X67: 513000 | Y67: HCORP-CRP-5100-PAX
A68: MKT1087 | B68: Active | C68: =VLOOKUP(A68,[1]Items!$A:$D,3,0) -> Inactive | D68: =VLOOKUP(A68,[1]Items!$A:$D,4,0) -> Inactive | E68: Inactive | F68: PAX Comparison Chart | G68: EXPENSE | H68: Finished Good | I68: False | J68: FIFO | K68: TAXABLE | L68: MKT PAX | M68: NOTTRACKED | N68: 730600 | O68: HCORP-CRP-5100-PAX | P68: 730600 | Q68: HCORP-CRP-5100-PAX | R68: 410000 | S68: HCORP-CRP-5100-PAX | T68: 200100 | U68: HCORP-CRP-5100-PAX | V68: 514000 | W68: HCORP-CRP-5100-PAX | X68: 513000 | Y68: HCORP-CRP-5100-PAX
A69: MKT1088 | B69: Active | C69: =VLOOKUP(A69,[1]Items!$A:$D,3,0) -> Inactive | D69: =VLOOKUP(A69,[1]Items!$A:$D,4,0) -> Inactive | E69: Inactive | F69: PAX2 Thank You Card | G69: EXPENSE | H69: Finished Good | I69: False | J69: FIFO | K69: TAXABLE | L69: MKT PAX | M69: NOTTRACKED | N69: 730600 | O69: HCORP-CRP-5100-PAX | P69: 730600 | Q69: HCORP-CRP-5100-PAX | R69: 410000 | S69: HCORP-CRP-5100-PAX | T69: 200100 | U69: HCORP-CRP-5100-PAX | V69: 514000 | W69: HCORP-CRP-5100-PAX | X69: 513000 | Y69: HCORP-CRP-5100-PAX
A70: MKT1089 | B70: Inactive | C70: =VLOOKUP(A70,[1]Items!$A:$D,3,0) -> Inactive | D70: =VLOOKUP(A70,[1]Items!$A:$D,4,0) -> Inactive | E70: Inactive | F70: PAX2 Authorized Retailer Poster | G70: EXPENSE | H70: Finished Good | I70: False | J70: FIFO | K70: TAXABLE | L70: MKT PAX | M70: NOTTRACKED | N70: 730600 | O70: HCORP-CRP-5100-PAX | P70: 730600 | Q70: HCORP-CRP-5100-PAX | R70: 410000 | S70: HCORP-CRP-5100-PAX | T70: 200100 | U70: HCORP-CRP-5100-PAX | V70: 514000 | W70: HCORP-CRP-5100-PAX | X70: 513000 | Y70: HCORP-CRP-5100-PAX
A71: MKT1090 | B71: Inactive | C71: =VLOOKUP(A71,[1]Items!$A:$D,3,0) -> Inactive | D71: =VLOOKUP(A71,[1]Items!$A:$D,4,0) -> Inactive | E71: Inactive | F71: PAX2 Authorized Retailer Cling | G71: EXPENSE | H71: Finished Good | I71: False | J71: FIFO | K71: TAXABLE | L71: MKT PAX | M71: NOTTRACKED | N71: 730600 | O71: HCORP-CRP-5100-PAX | P71: 730600 | Q71: HCORP-CRP-5100-PAX | R71: 410000 | S71: HCORP-CRP-5100-PAX | T71: 200100 | U71: HCORP-CRP-5100-PAX | V71: 514000 | W71: HCORP-CRP-5100-PAX | X71: 513000 | Y71: HCORP-CRP-5100-PAX
A72: MKT1091 | B72: Inactive | C72: =VLOOKUP(A72,[1]Items!$A:$D,3,0) -> Inactive | D72: =VLOOKUP(A72,[1]Items!$A:$D,4,0) -> Inactive | E72: Inactive | F72: PAX2 Pro Tips Card | G72: EXPENSE | H72: Finished Good | I72: False | J72: FIFO | K72: TAXABLE | L72: MKT PAX | M72: NOTTRACKED | N72: 730600 | O72: HCORP-CRP-5100-PAX | P72: 730600 | Q72: HCORP-CRP-5100-PAX | R72: 410000 | S72: HCORP-CRP-5100-PAX | T72: 200100 | U72: HCORP-CRP-5100-PAX | V72: 514000 | W72: HCORP-CRP-5100-PAX | X72: 513000 | Y72: HCORP-CRP-5100-PAX
A73: MKT1096 | B73: Active | C73: =VLOOKUP(A73,[1]Items!$A:$D,3,0) -> Inactive | D73: =VLOOKUP(A73,[1]Items!$A:$D,4,0) -> Inactive | E73: Inactive | F73: PAX2 Pro Tips Card Holder | G73: EXPENSE | H73: Finished Good | I73: False | J73: FIFO | K73: TAXABLE | L73: MKT PAX | M73: NOTTRACKED | N73: 730600 | O73: HCORP-CRP-5100-PAX | P73: 730600 | Q73: HCORP-CRP-5100-PAX | R73: 410000 | S73: HCORP-CRP-5100-PAX | T73: 200100 | U73: HCORP-CRP-5100-PAX | V73: 514000 | W73: HCORP-CRP-5100-PAX | X73: 513000 | Y73: HCORP-CRP-5100-PAX
A74: MKT1097 | B74: Active | C74: =VLOOKUP(A74,[1]Items!$A:$D,3,0) -> Inactive | D74: =VLOOKUP(A74,[1]Items!$A:$D,4,0) -> Inactive | E74: Inactive | F74: PAX2 Takeaway Card Holder | G74: EXPENSE | H74: Finished Good | I74: False | J74: FIFO | K74: TAXABLE | L74: MKT PAX | M74: NOTTRACKED | N74: 730600 | O74: HCORP-CRP-5100-PAX | P74: 730600 | Q74: HCORP-CRP-5100-PAX | R74: 410000 | S74: HCORP-CRP-5100-PAX | T74: 200100 | U74: HCORP-CRP-5100-PAX | V74: 514000 | W74: HCORP-CRP-5100-PAX | X74: 513000 | Y74: HCORP-CRP-5100-PAX
A75: J1A1063 | B75: Active | C75: =VLOOKUP(A75,[1]Items!$A:$D,3,0) -> FG | D75: =VLOOKUP(A75,[1]Items!$A:$D,4,0) -> Acc | E75: FG | F75: JUUL USB Charging Dock | G75: J1A | H75: Finished Good | I75: False | J75: FIFO | K75: TAXABLE | L75: JUL | M75: NOTTRACKED | N75: 141000 | O75: HCORP-CRP-6000-JUL | P75: 511000 | Q75: HCORP-CRP-4100-JUL | R75: 410000 | S75: HCORP-CRP-4100-JUL | T75: 200100 | U75: HCORP-CRP-4100-JUL | V75: 514000 | W75: HCORP-CRP-4600-JUL | X75: 513000 | Y75: HCORP-CRP-4600-JUL
A76: J1D1064 | B76: Active | C76: =VLOOKUP(A76,[1]Items!$A:$D,3,0) -> FG | D76: =VLOOKUP(A76,[1]Items!$A:$D,4,0) -> BK | E76: FG | F76: JUUL Device RMA | G76: J1D | H76: Finished Good | I76: False | J76: FIFO | K76: TAXABLE | L76: JUL | M76: NOTTRACKED | N76: 141000 | O76: HCORP-CRP-6000-JUL | P76: 511000 | Q76: HCORP-CRP-4100-JUL | R76: 410000 | S76: HCORP-CRP-4100-JUL | T76: 200100 | U76: HCORP-CRP-4100-JUL | X76: 513000 | Y76: HCORP-CRP-4600-CRP
A77: J1D1147 | B77: Active | C77: =VLOOKUP(A77,[1]Items!$A:$D,3,0) -> FG | D77: =VLOOKUP(A77,[1]Items!$A:$D,4,0) -> BK | E77: FG | F77: JUUL Basic Kit Slate | G77: J1D | H77: Finished Good | I77: True | J77: FIFO | K77: TAXABLE | L77: JUL | M77: NOTTRACKED | N77: 141000 | O77: HCORP-CRP-4100-JUL | P77: 511000 | Q77: HCORP-CRP-4100-JUL | R77: 410000 | S77: HCORP-CRP-4100-JUL | T77: 200100 | U77: HCORP-CRP-4600-JUL | V77: 514000 | W77: HCORP-CRP-4600-JUL | X77: 513000 | Y77: HCORP-CRP-4600-JUL
A78: J1A1168 | B78: Active | C78: =VLOOKUP(A78,[1]Items!$A:$D,3,0) -> FG | D78: =VLOOKUP(A78,[1]Items!$A:$D,4,0) -> Acc | E78: FG | F78: JUUL Charging Case | G78: J1A | H78: Finished Good | I78: False | J78: FIFO | K78: TAXABLE | L78: JUL | M78: NOTTRACKED | N78: 141000 | O78: HCORP-CRP-6000-JUL | P78: 511000 | Q78: HCORP-CRP-4100-JUL | R78: 410000 | S78: HCORP-CRP-4100-JUL | T78: 200100 | U78: HCORP-CRP-4100-JUL | X78: 513000 | Y78: HCORP-CRP-4600-CRP
A79: P2A1014 | B79: Active | C79: =VLOOKUP(A79,[1]Items!$A:$D,3,0) -> Inactive | D79: =VLOOKUP(A79,[1]Items!$A:$D,4,0) -> Inactive | E79: Inactive | F79: PAX2 Mouthpiece 2pk flat green | G79: P2A | H79: Finished Good | I79: False | J79: FIFO | K79: TAXABLE | L79: PAX | M79: NOTTRACKED | N79: 141000 | O79: HCORP-CRP-4100-PAX | P79: 511000 | Q79: HCORP-CRP-4100-PAX | R79: 410000 | S79: HCORP-CRP-4100-PAX | T79: 200100 | U79: HCORP-CRP-4100-PAX | X79: 513000 | Y79: HCORP-CRP-4600-CRP
A80: P2A1015 | B80: Active | C80: =VLOOKUP(A80,[1]Items!$A:$D,3,0) -> Inactive | D80: =VLOOKUP(A80,[1]Items!$A:$D,4,0) -> Inactive | E80: Inactive | F80: PAX2 Mouthpiece 2pk flat blue1 | G80: P2A | H80: Finished Good | I80: False | J80: FIFO | K80: TAXABLE | L80: PAX | M80: NOTTRACKED | N80: 141000 | O80: HCORP-CRP-4100-PAX | P80: 511000 | Q80: HCORP-CRP-4100-PAX | R80: 410000 | S80: HCORP-CRP-4100-PAX | T80: 200100 | U80: HCORP-CRP-4100-PAX | X80: 513000 | Y80: HCORP-CRP-4600-CRP
A81: P2A1169 | B81: Active | C81: =VLOOKUP(A81,[1]Items!$A:$D,3,0) -> Inactive | D81: =VLOOKUP(A81,[1]Items!$A:$D,4,0) -> Inactive | E81: Inactive | F81: PAX2 Mouthpiece 2pk flat pink | G81: P2A | H81: Finished Good | I81: False | J81: FIFO | K81: TAXABLE | L81: PAX | M81: NOTTRACKED | N81: 141000 | O81: HCORP-CRP-4100-PAX | P81: 511000 | Q81: HCORP-CRP-4100-PAX | R81: 410000 | S81: HCORP-CRP-4100-PAX | T81: 200100 | U81: HCORP-CRP-4100-PAX | X81: 513000 | Y81: HCORP-CRP-4600-CRP
A82: P2A1170 | B82: Inactive | C82: =VLOOKUP(A82,[1]Items!$A:$D,3,0) -> Inactive | D82: =VLOOKUP(A82,[1]Items!$A:$D,4,0) -> Inactive | E82: Inactive | F82: PAX2 Mouthpiece 2pk flat yellow1 | G82: P2A | H82: Finished Good | I82: False | J82: FIFO | K82: TAXABLE | L82: PAX | M82: NOTTRACKED | N82: 141000 | O82: HCORP-CRP-4100-PAX | P82: 511000 | Q82: HCORP-CRP-4100-PAX | R82: 410000 | S82: HCORP-CRP-4100-PAX | T82: 200100 | U82: HCORP-CRP-4100-PAX | X82: 513000 | Y82: HCORP-CRP-4600-CRP
A83: P2A1171 | B83: Active | C83: =VLOOKUP(A83,[1]Items!$A:$D,3,0) -> Inactive | D83: =VLOOKUP(A83,[1]Items!$A:$D,4,0) -> Inactive | E83: Inactive | F83: PAX2 Mouthpiece 3pk flat multicolor | G83: P2A | H83: Finished Good | I83: False | J83: FIFO | K83: TAXABLE | L83: PAX | M83: NOTTRACKED | N83: 141000 | O83: HCORP-CRP-4100-PAX | P83: 511000 | Q83: HCORP-CRP-4100-PAX | R83: 410000 | S83: HCORP-CRP-4100-PAX | T83: 200100 | U83: HCORP-CRP-4100-PAX | X83: 513000 | Y83: HCORP-CRP-4600-CRP
A84: NSK1072 | B84: Active | C84: =VLOOKUP(A84,[1]Items!$A:$D,3,0) -> RM | D84: =VLOOKUP(A84,[1]Items!$A:$D,4,0) -> Pkg | E84: RM | F84: JUUL Small Box | G84: PACKAGING | H84: Non-Stock Item | I84: False | J84: Standard | K84: TAXABLE | L84: CORP | P84: 511000 | Q84: HCORP-CRP-4100-JUL | T84: 200100 | U84: HCORP-CRP-6000-JUL | X84: 513000
A85: NSK1073 | B85: Active | C85: =VLOOKUP(A85,[1]Items!$A:$D,3,0) -> RM | D85: =VLOOKUP(A85,[1]Items!$A:$D,4,0) -> Pkg | E85: RM | F85: JUUL medium box | G85: PACKAGING | H85: Non-Stock Item | I85: False | J85: Standard | K85: TAXABLE | L85: CORP | P85: 511000 | Q85: HCORP-CRP-4100-JUL | T85: 200100 | U85: HCORP-CRP-6000-JUL | X85: 513000
A86: NSK1074 | B86: Inactive | C86: =VLOOKUP(A86,[1]Items!$A:$D,3,0) -> Inactive | D86: =VLOOKUP(A86,[1]Items!$A:$D,4,0) -> Inactive | E86: Inactive | F86: PAX 2 small box | G86: PACKAGING | H86: Non-Stock Item | I86: False | J86: Standard | K86: TAXABLE | L86: CORP | P86: 511000 | Q86: HCORP-CRP-4100-CRP | X86: 513000
A87: NSK1075 | B87: Inactive | C87: =VLOOKUP(A87,[1]Items!$A:$D,3,0) -> Inactive | D87: =VLOOKUP(A87,[1]Items!$A:$D,4,0) -> Inactive | E87: Inactive | F87: PAX 2 medium box | G87: PACKAGING | H87: Non-Stock Item | I87: False | J87: Standard | K87: TAXABLE | L87: CORP | P87: 511000 | Q87: HCORP-CRP-4100-CRP | X87: 513000
A88: NSK1076 | B88: Active | C88: =VLOOKUP(A88,[1]Items!$A:$D,3,0) -> RM | D88: =VLOOKUP(A88,[1]Items!$A:$D,4,0) -> Pkg | E88: RM | F88: Large box unbranded | G88: PACKAGING | H88: Non-Stock Item | I88: False | J88: Standard | K88: TAXABLE | L88: CORP | P88: 511000 | Q88: HCORP-CRP-4100-JUL | T88: 200100 | U88: HCORP-CRP-6000-JUL | X88: 513000
A89: NSK1077 | B89: Active | C89: =VLOOKUP(A89,[1]Items!$A:$D,3,0) -> RM | D89: =VLOOKUP(A89,[1]Items!$A:$D,4,0) -> Pkg | E89: RM | F89: Black tissue paper | G89: PACKAGING | H89: Non-Stock Item | I89: False | J89: Standard | K89: TAXABLE | L89: CORP | P89: 511000 | Q89: HCORP-CRP-4100-JUL | T89: 200100 | U89: HCORP-CRP-6000-JUL | X89: 513000
A90: NSK1189 | B90: Active | C90: =VLOOKUP(A90,[1]Items!$A:$D,3,0) -> RM | D90: =VLOOKUP(A90,[1]Items!$A:$D,4,0) -> Pkg | E90: RM | F90: JUUL Exterior Counter Unit Sticker | G90: PACKAGING | H90: Non-Stock Item | I90: False | J90: Standard | K90: TAXABLE | L90: CORP | P90: 511000 | Q90: HCORP-CRP-4100-JUL | T90: 200100 | U90: HCORP-CRP-6000-JUL | X90: 513000
A91: NSK1191 | B91: Active | C91: =VLOOKUP(A91,[1]Items!$A:$D,3,0) -> RM | D91: =VLOOKUP(A91,[1]Items!$A:$D,4,0) -> Pkg | E91: RM | F91: Gorilla glue dots | G91: PACKAGING | H91: Non-Stock Item | I91: False | J91: Standard | K91: TAXABLE | L91: CORP | P91: 511000 | Q91: HCORP-CRP-4100-JUL | T91: 200100 | U91: HCORP-CRP-6000-JUL | X91: 513000
A92: KIT1062 | B92: Inactive | C92: WIP | D92: Other | E92: Inactive | F92: JUUL Component Device MT, Charger, Packaging | G92: COMPONENTS | H92: Component Part | I92: True | J92: FIFO | K92: TAXABLE | L92: JUL | M92: NOTTRACKED | N92: 141000 | O92: HCORP-CRP-6000-JUL | P92: 511000 | Q92: HCORP-CRP-4100-CRP | R92: 410000 | S92: HCORP-CRP-4100-CRP | T92: 200100 | U92: HCORP-CRP-4100-CRP | X92: 513000 | Y92: HCORP-CRP-4600-CRP
A93: KIT1084 | B93: Inactive | C93: WIP | D93: Other | E93: Inactive | F93: PAX Retailer Activation Kit | G93: NSK KITS | H93: Finished Good | I93: True | J93: FIFO | K93: TAXABLE | L93: CORP | M93: NOTTRACKED | N93: 141000 | O93: HCORP-CRP-6000-CRP | P93: 511000 | Q93: HCORP-CRP-4100-CRP | R93: 410000 | S93: HCORP-CRP-4100-CRP | T93: 200100 | U93: HCORP-CRP-4100-CRP | X93: 513000 | Y93: HCORP-CRP-4600-CRP
A94: MKT1154 | B94: Active | C94: =VLOOKUP(A94,[1]Items!$A:$D,3,0) -> Expense | D94: =VLOOKUP(A94,[1]Items!$A:$D,4,0) -> Expense | E94: Expense | F94: JUUL Acrylic Counter Unit with Lock | G94: EXPENSE | H94: Finished Good | I94: False | J94: FIFO | K94: TAXABLE | L94: MKT jul | M94: NOTTRACKED | N94: 730600 | O94: HCORP-CRP-5100-JUL | P94: 730600 | Q94: HCORP-CRP-5100-JUL | R94: 410000 | S94: HCORP-CRP-5100-JUL | T94: 200100 | U94: HCORP-CRP-5100-JUL | V94: 514000 | W94: HCORP-CRP-5100-JUL | X94: 514000 | Y94: HCORP-CRP-5100-JUL
A95: MKT1162 | B95: Inactive | C95: =VLOOKUP(A95,[1]Items!$A:$D,3,0) -> Inactive | D95: =VLOOKUP(A95,[1]Items!$A:$D,4,0) -> Inactive | E95: Inactive | F95: JUUL Counter Unit Planogram w/cling | G95: EXPENSE | H95: Finished Good | I95: False | J95: FIFO | K95: TAXABLE | L95: MKT JUL | M95: NOTTRACKED | N95: 730600 | O95: HCORP-CRP-5100-JUL | P95: 730600 | Q95: HCORP-CRP-5100-JUL | R95: 410000 | S95: HCORP-CRP-5100-JUL | T95: 200100 | U95: HCORP-CRP-5100-JUL | V95: 514000 | W95: HCORP-CRP-5100-JUL | X95: 514000 | Y95: HCORP-CRP-5100-JUL
A96: MKT1151 | B96: Active | C96: =VLOOKUP(A96,[1]Items!$A:$D,3,0) -> Expense | D96: =VLOOKUP(A96,[1]Items!$A:$D,4,0) -> Expense | E96: Expense | F96: JUUL Counter Unit Checklist | G96: EXPENSE | H96: Finished Good | I96: False | J96: FIFO | K96: TAXABLE | L96: MKT JUL | M96: NOTTRACKED | N96: 730600 | O96: HCORP-CRP-5100-JUL | P96: 730600 | Q96: HCORP-CRP-5100-JUL | R96: 410000 | S96: HCORP-CRP-5100-JUL | T96: 200100 | U96: HCORP-CRP-5100-JUL | V96: 514000 | W96: HCORP-CRP-5100-JUL | X96: 514000 | Y96: HCORP-CRP-5100-JUL
A97: NSK1187 | B97: Active | C97: =VLOOKUP(A97,[1]Items!$A:$D,3,0) -> RM | D97: =VLOOKUP(A97,[1]Items!$A:$D,4,0) -> Pkg | E97: RM | F97: JUUL Counter Unit Shelf Liner | G97: PACKAGING | H97: Non-Stock Item | I97: False | J97: Standard | K97: TAXABLE | L97: CORP | P97: 511000 | Q97: HCORP-CRP-4100-JUL | T97: 200100 | U97: HCORP-CRP-6000-JUL | X97: 513000
A98: MKT1155 | B98: Active | C98: =VLOOKUP(A98,[1]Items!$A:$D,3,0) -> Expense | D98: =VLOOKUP(A98,[1]Items!$A:$D,4,0) -> Expense | E98: Expense | F98: JUUL Acrylic Counter Unit without Lock | G98: EXPENSE | H98: Finished Good | I98: False | J98: FIFO | K98: TAXABLE | L98: MKT JUL | M98: NOTTRACKED | N98: 730600 | O98: HCORP-CRP-5100-JUL | P98: 730600 | Q98: HCORP-CRP-5100-JUL | R98: 410000 | S98: HCORP-CRP-5100-JUL | T98: 200100 | U98: HCORP-CRP-5100-JUL | V98: 514000 | W98: HCORP-CRP-5100-JUL | X98: 514000 | Y98: HCORP-CRP-5100-JUL
A99: NSK1081 | B99: Active | C99: =VLOOKUP(A99,[1]Items!$A:$D,3,0) -> RM | D99: =VLOOKUP(A99,[1]Items!$A:$D,4,0) -> Pkg | E99: RM | F99: JUUL POS display box | G99: PACKAGING | H99: Non-Stock Item | I99: False | J99: Standard | K99: TAXABLE | L99: CORP | P99: 511000 | Q99: HCORP-CRP-4100-JUL | T99: 200100 | U99: HCORP-CRP-6000-JUL | X99: 513000
A100: KIT1194 | B100: Active | C100: WIP | D100: Other | E100: WIP | F100: JUUL NY launch retailer activation kit | G100: NSK KITS | H100: Finished Good | I100: True | J100: FIFO | K100: TAXABLE | L100: CORP | M100: NOTTRACKED | N100: 140200 | O100: HCORP-CRP-6000-CRP | P100: 511000 | Q100: HCORP-CRP-4100-CRP | R100: 410000 | S100: HCORP-CRP-4100-CRP | T100: 200100 | U100: HCORP-CRP-4100-CRP | X100: 513000 | Y100: HCORP-CRP-4600-CRP
A101: MKT1160 | B101: Active | C101: =VLOOKUP(A101,[1]Items!$A:$D,3,0) -> Expense | D101: =VLOOKUP(A101,[1]Items!$A:$D,4,0) -> Expense | E101: Expense | F101: JUUL Takeaway cards 50/pk | G101: EXPENSE | H101: Finished Good | I101: False | J101: FIFO | K101: TAXABLE | L101: MKT JUL | M101: NOTTRACKED | N101: 730600 | O101: HCORP-CRP-5100-JUL | P101: 730600 | Q101: HCORP-CRP-5100-JUL | R101: 410000 | S101: HCORP-CRP-5100-JUL | T101: 200100 | U101: HCORP-CRP-5100-JUL | V101: 514000 | W101: HCORP-CRP-5100-JUL | X101: 514000 | Y101: HCORP-CRP-5100-JUL
A102: MKT1161 | B102: Active | C102: =VLOOKUP(A102,[1]Items!$A:$D,3,0) -> Expense | D102: =VLOOKUP(A102,[1]Items!$A:$D,4,0) -> Expense | E102: Expense | F102: takeway card holders | G102: EXPENSE | H102: Finished Good | I102: False | J102: FIFO | K102: TAXABLE | L102: MKT CRP | M102: NOTTRACKED | N102: 730600 | O102: HCORP-CRP-5100-CRP | P102: 730600 | Q102: HCORP-CRP-5100-CRP | R102: 410000 | S102: HCORP-CRP-5100-CRP | T102: 200100 | U102: HCORP-CRP-5100-CRP | V102: 514000 | W102: HCORP-CRP-5100-CRP | X102: 513000 | Y102: HCORP-CRP-5100-CRP
A103: MKT1179 | B103: Active | C103: =VLOOKUP(A103,[1]Items!$A:$D,3,0) -> Expense | D103: =VLOOKUP(A103,[1]Items!$A:$D,4,0) -> Expense | E103: Expense | F103: JUUL IRC change mat | G103: EXPENSE | H103: Finished Good | I103: False | J103: FIFO | K103: TAXABLE | L103: MKT JUL | M103: NOTTRACKED | N103: 730600 | O103: HCORP-CRP-5100-JUL | P103: 730600 | Q103: HCORP-CRP-5100-JUL | R103: 410000 | S103: HCORP-CRP-5100-JUL | T103: 200100 | U103: HCORP-CRP-5100-JUL | V103: 514000 | W103: HCORP-CRP-5100-JUL | X103: 514000 | Y103: HCORP-CRP-5100-JUL
A104: MKT1180 | B104: Active | C104: =VLOOKUP(A104,[1]Items!$A:$D,3,0) -> Expense | D104: =VLOOKUP(A104,[1]Items!$A:$D,4,0) -> Expense | E104: Expense | F104: JUUL IRC poster | G104: EXPENSE | H104: Finished Good | I104: False | J104: FIFO | K104: TAXABLE | L104: MKT JUL | M104: NOTTRACKED | N104: 730600 | O104: HCORP-CRP-5100-JUL | P104: 730600 | Q104: HCORP-CRP-5100-JUL | R104: 410000 | S104: HCORP-CRP-5100-JUL | T104: 200100 | U104: HCORP-CRP-5100-JUL | V104: 514000 | W104: HCORP-CRP-5100-JUL | X104: 514000 | Y104: HCORP-CRP-5100-JUL
A105: MKT1163 | B105: Inactive | C105: =VLOOKUP(A105,[1]Items!$A:$D,3,0) -> Inactive | D105: =VLOOKUP(A105,[1]Items!$A:$D,4,0) -> Inactive | E105: Inactive | F105: JUUL in-rack planogram | G105: EXPENSE | H105: Finished Good | I105: False | J105: FIFO | K105: TAXABLE | L105: MKT JUL | M105: NOTTRACKED | N105: 730600 | O105: HCORP-CRP-5100-JUL | P105: 730600 | Q105: HCORP-CRP-5100-JUL | R105: 410000 | S105: HCORP-CRP-5100-JUL | T105: 200100 | U105: HCORP-CRP-5100-JUL | V105: 514000 | W105: HCORP-CRP-5100-JUL | X105: 514000 | Y105: HCORP-CRP-5100-JUL
A106: MKT1195 | B106: Active | C106: =VLOOKUP(A106,[1]Items!$A:$D,3,0) -> Expense | D106: =VLOOKUP(A106,[1]Items!$A:$D,4,0) -> Expense | E106: Expense | F106: JUUL IRC Coupon Save $15 | G106: EXPENSE | H106: Finished Good | I106: False | J106: FIFO | K106: TAXABLE | L106: MKT JUL | M106: NOTTRACKED | N106: 730600 | O106: HCORP-CRP-5100-JUL | P106: 730600 | Q106: HCORP-CRP-5100-JUL | R106: 410000 | S106: HCORP-CRP-5100-JUL | T106: 200100 | U106: HCORP-CRP-5100-JUL | V106: 514000 | W106: HCORP-CRP-5100-JUL | X106: 514000 | Y106: HCORP-CRP-5100-JUL
A107: MKT1201 | B107: Inactive | C107: =VLOOKUP(A107,[1]Items!$A:$D,3,0) -> Inactive | D107: =VLOOKUP(A107,[1]Items!$A:$D,4,0) -> Inactive | E107: Inactive | F107: JUUL Launch IRC Easel | G107: EXPENSE | H107: Finished Good | I107: False | J107: FIFO | K107: TAXABLE | L107: MKT JUL | M107: NOTTRACKED | N107: 730600 | O107: HCORP-CRP-5100-JUL | P107: 730600 | Q107: HCORP-CRP-5100-JUL | R107: 410000 | S107: HCORP-CRP-5100-JUL | T107: 200100 | U107: HCORP-CRP-5100-JUL | V107: 514000 | W107: HCORP-CRP-5100-JUL | X107: 514000 | Y107: HCORP-CRP-5100-JUL
A108: KIT1200 | B108: Active | C108: WIP | D108: Other | E108: WIP | F108: JUUL Exxon mobil activation 1 PBD SE | G108: NSK KITS | H108: Finished Good | I108: True | J108: FIFO | K108: TAXABLE | L108: CORP | M108: NOTTRACKED | N108: 140200 | O108: HCORP-CRP-6000-CRP | P108: 511000 | Q108: HCORP-CRP-4100-CRP | R108: 410000 | S108: HCORP-CRP-4100-CRP | T108: 200100 | U108: HCORP-CRP-4100-CRP | X108: 513000 | Y108: HCORP-CRP-4600-CRP
A109: MKT1158 | B109: Active | C109: =VLOOKUP(A109,[1]Items!$A:$D,3,0) -> Expense | D109: =VLOOKUP(A109,[1]Items!$A:$D,4,0) -> Expense | E109: Expense | F109: JUUL sell sheet | G109: EXPENSE | H109: Finished Good | I109: False | J109: FIFO | K109: TAXABLE | L109: MKT JUL | M109: NOTTRACKED | N109: 730600 | O109: HCORP-CRP-5100-JUL | P109: 730600 | Q109: HCORP-CRP-5100-JUL | R109: 410000 | S109: HCORP-CRP-5100-JUL | T109: 200100 | U109: HCORP-CRP-5100-JUL | V109: 514000 | W109: HCORP-CRP-5100-JUL | X109: 514000 | Y109: HCORP-CRP-5100-JUL
A110: MKT1159 | B110: Inactive | C110: =VLOOKUP(A110,[1]Items!$A:$D,3,0) -> Inactive | D110: =VLOOKUP(A110,[1]Items!$A:$D,4,0) -> Inactive | E110: Inactive | F110: JUUL counter unit half sheet | G110: EXPENSE | H110: Finished Good | I110: False | J110: FIFO | K110: TAXABLE | L110: MKT JUL | M110: NOTTRACKED | N110: 730600 | O110: HCORP-CRP-5100-JUL | P110: 730600 | Q110: HCORP-CRP-5100-JUL | R110: 410000 | S110: HCORP-CRP-5100-JUL | T110: 200100 | U110: HCORP-CRP-5100-JUL | V110: 514000 | W110: HCORP-CRP-5100-JUL | X110: 514000 | Y110: HCORP-CRP-5100-JUL
...

Sheet Sheet1
D1: Shipment Details by Inventory Item | I1: Start Date: | J1: 43221 | M1: Page: | N1: 1 of 57
D2: Company: | E2: JUUL CA | I2: End Date: | J2: 43465 | M2: Date: | N2: 43469.774
D3: User: | E3: Karen.Fu
D5: Inventory ID | F5: Item Description | J5: Subitem
D6: J1A2399 | F6: JUUL CA USB Charger
A7: Inventory ID | C7: Item Description | D7: Type | E7: Ref. Nbr. | F7: Operation | G7: Order Status | H7: Order Number | I7: Customer ID | J7: Customer Name | K7: Warehouse | L7: UOM | M7: Order Qty. | N7: Shipped Qty.
A8: J1A2399 | C8: JUUL CA USB Charger | D8: BO | E8: SH05-00000076 | F8: Issue | G8: Completed | H8: SO05-00000012 | I8: 05-00000008 | J8: Greenlane | K8: DSLOCATION | L8: EA | M8: 3840 | N8: 3840
A9: J1A2399 | C9: JUUL CA USB Charger | D9: BO | E9: SH05-00000079 | F9: Issue | G9: Completed | H9: SO05-00000017 | I9: 05-00000004 | J9: Core-Mark International, Inc. | K9: DSLOCATION | L9: EA | M9: 8640 | N9: 8640
A10: J1A2399 | C10: JUUL CA USB Charger | D10: BO | E10: SH05-00000077 | F10: Issue | G10: Completed | H10: SO05-00000066 | I10: 05-00000009 | J10: Wallace & Carey Inc. | K10: DSLOCATION | L10: EA | M10: 1536 | N10: 1536
A11: J1A2399 | C11: JUUL CA USB Charger | D11: BO | E11: SH05-00000078 | F11: Issue | G11: Completed | H11: SO05-00000067 | I11: 05-00000004 | J11: Core-Mark International, Inc. | K11: DSLOCATION | L11: EA | M11: 4608 | N11: 4608
A12: J1A2399 | C12: JUUL CA USB Charger | D12: BO | E12: SH05-00000173 | F12: Issue | G12: Completed | H12: SO05-00000076 | I12: 05-00000004 | J12: Core-Mark International, Inc. | K12: GO DIRECT | L12: EA | M12: 4560 | N12: 4560
A13: J1A2399 | C13: JUUL CA USB Charger | D13: BO | E13: SH05-00000178 | F13: Issue | G13: Completed | H13: SO05-00000083 | I13: 05-00000008 | J13: Greenlane | K13: GO DIRECT | L13: EA | M13: 1920 | N13: 1920
A14: J1A2399 | C14: JUUL CA USB Charger | D14: BO | E14: SH05-00000175 | F14: Issue | G14: Completed | H14: SO05-00000086 | I14: 05-00000002 | J14: Pacific Smoke International Inc. | K14: GO DIRECT | L14: EA | M14: 2400 | N14: 2400
A15: J1A2399 | C15: JUUL CA USB Charger | D15: BO | E15: SH05-00000180 | F15: Issue | G15: Completed | H15: SO05-00000164 | I15: 05-00000004 | J15: Core-Mark International, Inc. | K15: GO DIRECT | L15: EA | M15: 2112 | N15: 2112
A16: J1A2399 | C16: JUUL CA USB Charger | D16: BO | E16: SH05-00000176 | F16: Issue | G16: Completed | H16: SO05-00000168 | I16: 05-00000009 | J16: Wallace & Carey Inc. | K16: GO DIRECT | L16: EA | M16: 1200 | N16: 1200
A17: J1A2399 | C17: JUUL CA USB Charger | D17: BO | E17: SH05-00000177 | F17: Issue | G17: Completed | H17: SO05-00000170 | I17: 05-00000009 | J17: Wallace & Carey Inc. | K17: GO DIRECT | L17: EA | M17: 48 | N17: 48
A18: J1A2399 | C18: JUUL CA USB Charger | D18: BO | E18: SH05-00000222 | F18: Issue | G18: Completed | H18: SO05-00000171 | I18: 05-00000012 | J18: Sobeys Capital Inc. | K18: GO DIRECT | L18: EA | M18: 96 | N18: 96
A19: J1A2399 | C19: JUUL CA USB Charger | D19: BO | E19: SH05-00000221 | F19: Issue | G19: Completed | H19: SO05-00000172 | I19: 05-00000012 | J19: Sobeys Capital Inc. | K19: GO DIRECT | L19: EA | M19: 48 | N19: 48
... A80: J1A2399 | C80: JUUL CA USB Charger | D80: SO | E80: SH05-00000498 | F80: Issue | G80: Completed | H80: SO05-00000434 | I80: 05-00000011 | J80: JUUL B2C - Batch | K80: GO DIRECT | L80: EA | M80: 118 | N80: 118
L81: Total: | M81: 87687 | N81: 87687
D83: J1D2392 | F83: JUUL CA Starter Kit, 5%
D84: Type | E84: Ref. Nbr. | F84: Operation | G84: Order Status | H84: Order Number | I84: Customer ID | J84: Customer Name | K84: Warehouse | L84: UOM | M84: Order Qty. | N84: Shipped Qty.
A85: J1D2392 | C85: JUUL CA Starter Kit, 5% | D85: BO | E85: SH05-00000001 | F85: Issue | G85: Completed | H85: SO05-00000001 | I85: 05-00000002 | J85: Pacific Smoke International Inc. | K85: DSLOCATION | L85: EA | M85: 7200 | N85: 7200
A86: J1D2392 | C86: JUUL CA Starter Kit, 5% | D86: BO | E86: SH05-00000003 | F86: Issue | G86: Completed | H86: SO05-00000002 | I86: 05-00000002 | J86: Pacific Smoke International Inc. | K86: DSLOCATION | L86: EA | M86: 3600 | N86: 3600
A87: J1D2392 | C87: JUUL CA Starter Kit, 5% | D87: BO | E87: SH05-00000010 | F87: Issue | G87: Completed | H87: SO05-00000004 | I87: 05-00000004 | J87: Core-Mark International, Inc. | K87: DSLOCATION | L87: EA | M87: 2376 | N87: 2376
A88: J1D2392 | C88: JUUL CA Starter Kit, 5% | D88: BO | E88: SH05-00000011 | F88: Issue | G88: Completed | H88: SO05-00000005 | I88: 05-00000004 | J88: Core-Mark International, Inc. | K88: DSLOCATION | L88: EA | M88: 4968 | N88: 4968
A89: J1D2392 | C89: JUUL CA Starter Kit, 5% | D89: BO | E89: SH05-00000012 | F89: Issue | G89: Completed | H89: SO05-00000006 | I89: 05-00000004 | J89: Core-Mark International, Inc. | K89: DSLOCATION | L89: EA | M89: 1176 | N89: 1176
A90: J1D2392 | C90: JUUL CA Starter Kit, 5% | D90: BO | E90: SH05-00000013 | F90: Issue | G90: Completed | H90: SO05-00000007 | I90: 05-00000004 | J90: Core-Mark International, Inc. | K90: DSLOCATION | L90: EA | M90: 3216 | N90: 3216
A91: J1D2392 | C91: JUUL CA Starter Kit, 5% | D91: BO | E91: SH05-00000014 | F91: Issue | G91: Completed | H91: SO05-00000008 | I91: 05-00000004 | J91: Core-Mark International, Inc. | K91: DSLOCATION | L91: EA | M91: 1296 | N91: 1296
A92: J1D2392 | C92: JUUL CA Starter Kit, 5% | D92: BO | E92: SH05-00000015 | F92: Issue | G92: Completed | H92: SO05-00000009 | I92: 05-00000008 | J92: Greenlane | K92: DSLOCATION | L92: EA | M92: 4992 | N92: 4992
A93: J1D2392 | C93: JUUL CA Starter Kit, 5% | D93: BO | E93: SH05-00000018 | F93: Issue | G93: Completed | H93: SO05-00000010 | I93: 05-00000002 | J93: Pacific Smoke International Inc. | K93: DSLOCATION | L93: EA | M93: 7920 | N93: 7920
A94: J1D2392 | C94: JUUL CA Starter Kit, 5% | D94: BO | E94: SH05-00000017 | F94: Issue | G94: Completed | H94: SO05-00000011 | I94: 05-00000009 | J94: Wallace & Carey Inc. | K94: DSLOCATION | L94: EA | M94: 768 | N94: 768
A95: J1D2392 | C95: JUUL CA Starter Kit, 5% | D95: BO | E95: SH05-00000020 | F95: Issue | G95: Completed | H95: SO05-00000013 | I95: 05-00000004 | J95: Core-Mark International, Inc. | K95: DSLOCATION | L95: EA | M95: 48 | N95: 48
A96: J1D2392 | C96: JUUL CA Starter Kit, 5% | D96: BO | E96: SH05-00000023 | F96: Issue | G96: Completed | H96: SO05-00000015 | I96: 05-00000004 | J96: Core-Mark International, Inc. | K96: DSLOCATION | L96: EA | M96: 864 | N96: 864
... A334: J1D2392 | C334: JUUL CA Starter Kit, 5% | D334: SO | E334: SH05-00000498 | F334: Issue | G334: Completed | H334: SO05-00000434 | I334: 05-00000011 | J334: JUUL B2C - Batch | K334: GO DIRECT | L334: EA | M334: 3 | N334: 3
L335: Total: | M335: 183910 | N335: 183910
D337: J1D2393 | F337: JUUL CA Device Kit
D338: Type | E338: Ref. Nbr. | F338: Operation | G338: Order Status | H338: Order Number | I338: Customer ID | J338: Customer Name | K338: Warehouse | L338: UOM | M338: Order Qty. | N338: Shipped Qty.
A339: J1D2393 | C339: JUUL CA Device Kit | D339: BO | E339: SH05-00000001 | F339: Issue | G339: Completed | H339: SO05-00000001 | I339: 05-00000002 | J339: Pacific Smoke International Inc. | K339: DSLOCATION | L339: EA | M339: 2880 | N339: 2880
A340: J1D2393 | C340: JUUL CA Device Kit | D340: BO | E340: SH05-00000010 | F340: Issue | G340: Completed | H340: SO05-00000004 | I340: 05-00000004 | J340: Core-Mark International, Inc. | K340: DSLOCATION | L340: EA | M340: 5376 | N340: 5376
A341: J1D2393 | C341: JUUL CA Device Kit | D341: BO | E341: SH05-00000011 | F341: Issue | G341: Completed | H341: SO05-00000005 | I341: 05-00000004 | J341: Core-Mark International, Inc. | K341: DSLOCATION | L341: EA | M341: 14352 | N341: 14352
A342: J1D2393 | C342: JUUL CA Device Kit | D342: BO | E342: SH05-00000012 | F342: Issue | G342: Completed | H342: SO05-00000006 | I342: 05-00000004 | J342: Core-Mark International, Inc. | K342: DSLOCATION | L342: EA | M342: 3552 | N342: 3552
A343: J1D2393 | C343: JUUL CA Device Kit | D343: BO | E343: SH05-00000013 | F343: Issue | G343: Completed | H343: SO05-00000007 | I343: 05-00000004 | J343: Core-Mark International, Inc. | K343: DSLOCATION | L343: EA | M343: 1200 | N343: 1200
A344: J1D2393 | C344: JUUL CA Device Kit | D344: BO | E344: SH05-00000014 | F344: Issue | G344: Completed | H344: SO05-00000008 | I344: 05-00000004 | J344: Core-Mark International, Inc. | K344: DSLOCATION | L344: EA | M344: 3216 | N344: 1760
A345: J1D2393 | C345: JUUL CA Device Kit | D345: BO | E345: SH05-00000017 | F345: Issue | G345: Completed | H345: SO05-00000011 | I345: 05-00000009 | J345: Wallace & Carey Inc. | K345: DSLOCATION | L345: EA | M345: 1536 | N345: 1536
A346: J1D2393 | C346: JUUL CA Device Kit | D346: BO | E346: SH05-00000021 | F346: Issue | G346: Completed | H346: SO05-00000012 | I346: 05-00000008 | J346: Greenlane | K346: DSLOCATION | L346: EA | M346: 9984 | N346: 9984
A347: J1D2393 | C347: JUUL CA Device Kit | D347: BO | E347: SH05-00000020 | F347: Issue | G347: Completed | H347: SO05-00000013 | I347: 05-00000004 | J347: Core-Mark International, Inc. | K347: DSLOCATION | L347: EA | M347: 144 | N347: 144
A348: J1D2393 | C348: JUUL CA Device Kit | D348: BO | E348: SH05-00000022 | F348: Issue | G348: Completed | H348: SO05-00000014 | I348: 05-00000002 | J348: Pacific Smoke International Inc. | K348: DSLOCATION | L348: EA | M348: 8160 | N348: 8160
A349: J1D2393 | C349: JUUL CA Device Kit | D349: BO | E349: SH05-00000023 | F349: Issue | G349: Completed | H349: SO05-00000015 | I349: 05-00000004 | J349: Core-Mark International, Inc. | K349: DSLOCATION | L349: EA | M349: 1728 | N349: 1728
A350: J1D2393 | C350: JUUL CA Device Kit | D350: BO | E350: SH05-00000025 | F350: Issue | G350: Completed | H350: SO05-00000016 | I350: 05-00000004 | J350: Core-Mark International, Inc. | K350: DSLOCATION | L350: EA | M350: 1440 | N350: 1440
... A520: J1D2393 | C520: JUUL CA Device Kit | D520: SO | E520: SH05-00000498 | F520: Issue | G520: Completed | H520: SO05-00000434 | I520: 05-00000011 | J520: JUUL B2C - Batch | K520: GO DIRECT | L520: EA | M520: 802 | N520: 802
L521: Total: | M521: 182496 | N521: 181040
D523: J1T2394 | F523: JUUL CA Virginia Tobacco Refill Kit, 5%, 4 pods
D524: Type | E524: Ref. Nbr. | F524: Operation | G524: Order Status | H524: Order Number | I524: Customer ID | J524: Customer Name | K524: Warehouse | L524: UOM | M524: Order Qty. | N524: Shipped Qty.
A525: J1T2394 | C525: JUUL CA Virginia Tobacco Refill Kit, 5%, 4 pods | D525: BO | E525: SH05-00000001 | F525: Issue | G525: Completed | H525: SO05-00000001 | I525: 05-00000002 | J525: Pacific Smoke International Inc. | K525: DSLOCATION | L525: EA | M525: 4800 | N525: 4800
A526: J1T2394 | C526: JUUL CA Virginia Tobacco Refill Kit, 5%, 4 pods | D526: BO | E526: SH05-00000010 | F526: Issue | G526: Completed | H526: SO05-00000004 | I526: 05-00000004 | J526: Core-Mark International, Inc. | K526: DSLOCATION | L526: EA | M526: 4608 | N526: 4608
A527: J1T2394 | C527: JUUL CA Virginia Tobacco Refill Kit, 5%, 4 pods | D527: BO | E527: SH05-00000011 | F527: Issue | G527: Completed | H527: SO05-00000005 | I527: 05-00000004 | J527: Core-Mark International, Inc. | K527: DSLOCATION | L527: EA | M527: 10608 | N527: 10608
A528: J1T2394 | C528: JUUL CA Virginia Tobacco Refill Kit, 5%, 4 pods | D528: BO | E528: SH05-00000012 | F528: Issue | G528: Completed | H528: SO05-00000006 | I528: 05-00000004 | J528: Core-Mark International, Inc. | K528: DSLOCATION | L528: EA | M528: 2736 | N528: 2736
A529: J1T2394 | C529: JUUL CA Virginia Tobacco Refill Kit, 5%, 4 pods | D529: BO | E529: SH05-00000013 | F529: Issue | G529: Completed | H529: SO05-00000007 | I529: 05-00000004 | J529: Core-Mark International, Inc. | K529: DSLOCATION | L529: EA | M529: 1200 | N529: 1200
A530: J1T2394 | C530: JUUL CA Virginia Tobacco Refill Kit, 5%, 4 pods | D530: BO | E530: SH05-00000014 | F530: Issue | G530: Completed | H530: SO05-00000008 | I530: 05-00000004 | J530: Core-Mark International, Inc. | K530: DSLOCATION | L530: EA | M530: 2208 | N530: 2208
A531: J1T2394 | C531: JUUL CA Virginia Tobacco Refill Kit, 5%, 4 pods | D531: BO | E531: SH05-00000015 | F531: Issue | G531: Completed | H531: SO05-00000009 | I531: 05-00000008 | J531: Greenlane | K531: DSLOCATION | L531: EA | M531: 9984 | N531: 9984
A532: J1T2394 | C532: JUUL CA Virginia Tobacco Refill Kit, 5%, 4 pods | D532: BO | E532: SH05-00000018 | F532: Issue | G532: Completed | H532: SO05-00000010 | I532: 05-00000002 | J532: Pacific Smoke International Inc. | K532: DSLOCATION | L532: EA | M532: 4560 | N532: 4560
A533: J1T2394 | C533: JUUL CA Virginia Tobacco Refill Kit, 5%, 4 pods | D533: BO | E533: SH05-00000017 | F533: Issue | G533: Completed | H533: SO05-00000011 | I533: 05-00000009 | J533: Wallace & Carey Inc. | K533: DSLOCATION | L533: EA | M533: 1536 | N533: 1536
A534: J1T2394 | C534: JUUL CA Virginia Tobacco Refill Kit, 5%, 4 pods | D534: BO | E534: SH05-00000020 | F534: Issue | G534: Completed | H534: SO05-00000013 | I534: 05-00000004 | J534: Core-Mark International, Inc. | K534: DSLOCATION | L534: EA | M534: 96 | N534: 96
A535: J1T2394 | C535: JUUL CA Virginia Tobacco Refill Kit, 5%, 4 pods | D535: BO | E535: SH05-00000023 | F535: Issue | G535: Completed | H535: SO05-00000015 | I535: 05-00000004 | J535: Core-Mark International, Inc. | K535: DSLOCATION | L535: EA | M535: 864 | N535: 864
A536: J1T2394 | C536: JUUL CA Virginia Tobacco Refill Kit, 5%, 4 pods | D536: BO | E536: SH05-00000025 | F536: Issue | G536: Completed | H536: SO05-00000016 | I536: 05-00000004 | J536: Core-Mark International, Inc. | K536: DSLOCATION | L536: EA | M536: 720 | N536: 720
... A759: J1T2394 | C759: JUUL CA Virginia Tobacco Refill Kit, 5%, 4 pods | D759: SO | E759: SH05-00000498 | F759: Issue | G759: Completed | H759: SO05-00000434 | I759: 05-00000011 | J759: JUUL B2C - Batch | K759: GO DIRECT | L759: EA | M759: 890 | N759: 890
L760: Total: | M760: 209902 | N760: 209887
D762: J1T2395 | F762: JUUL CA Cool Mint Refill Kit, 5%, 4 pods
D763: Type | E763: Ref. Nbr. | F763: Operation | G763: Order Status | H763: Order Number | I763: Customer ID | J763: Customer Name | K763: Warehouse | L763: UOM | M763: Order Qty. | N763: Shipped Qty.
A764: J1T2395 | C764: JUUL CA Cool Mint Refill Kit, 5%, 4 pods | D764: BO | E764: SH05-00000001 | F764: Issue | G764: Completed | H764: SO05-00000001 | I764: 05-00000002 | J764: Pacific Smoke International Inc. | K764: DSLOCATION | L764: EA | M764: 9600 | N764: 9600
A765: v | C765: JUUL CA Cool Mint Refill Kit, 5%, 4 pods | D765: BO | E765: SH05-00000010 | F765: Issue | G765: Completed | H765: SO05-00000004 | I765: 05-00000004 | J765: Core-Mark International, Inc. | K765: DSLOCATION | L765: EA | M765: 4608 | N765: 4608
A766: J1T2395 | C766: JUUL CA Cool Mint Refill Kit, 5%, 4 pods | D766: BO | E766: SH05-00000011 | F766: Issue | G766: Completed | H766: SO05-00000005 | I766: 05-00000004 | J766: Core-Mark International, Inc. | K766: DSLOCATION | L766: EA | M766: 11904 | N766: 11904
A767: J1T2395 | C767: JUUL CA Cool Mint Refill Kit, 5%, 4 pods | D767: BO | E767: SH05-00000012 | F767: Issue | G767: Completed | H767: SO05-00000006 | I767: 05-00000004 | J767: Core-Mark International, Inc. | K767: DSLOCATION | L767: EA | M767: 2976 | N767: 2976
A768: J1T2395 | C768: JUUL CA Cool Mint Refill Kit, 5%, 4 pods | D768: BO | E768: SH05-00000013 | F768: Issue | G768: Completed | H768: SO05-00000007 | I768: 05-00000004 | J768: Core-Mark International, Inc. | K768: DSLOCATION | L768: EA | M768: 1200 | N768: 1200
A769: J1T2395 | C769: JUUL CA Cool Mint Refill Kit, 5%, 4 pods | D769: BO | E769: SH05-00000014 | F769: Issue | G769: Completed | H769: SO05-00000008 | I769: 05-00000004 | J769: Core-Mark International, Inc. | K769: DSLOCATION | L769: EA | M769: 2592 | N769: 2592
A770: J1T2395 | C770: JUUL CA Cool Mint Refill Kit, 5%, 4 pods | D770: BO | E770: SH05-00000015 | F770: Issue | G770: Completed | H770: SO05-00000009 | I770: 05-00000008 | J770: Greenlane | K770: DSLOCATION | L770: EA | M770: 25728 | N770: 25728
A771: J1T2395 | C771: JUUL CA Cool Mint Refill Kit, 5%, 4 pods | D771: BO | E771: SH05-00000018 | F771: Issue | G771: Completed | H771: SO05-00000010 | I771: 05-00000002 | J771: Pacific Smoke International Inc. | K771: DSLOCATION | L771: EA | M771: 3360 | N771: 3360
A772: J1T2395 | C772: JUUL CA Cool Mint Refill Kit, 5%, 4 pods | D772: BO | E772: SH05-00000017 | F772: Issue | G772: Completed | H772: SO05-00000011 | I772: 05-00000009 | J772: Wallace & Carey Inc. | K772: DSLOCATION | L772: EA | M772: 1536 | N772: 1536
A773: J1T2395 | C773: JUUL CA Cool Mint Refill Kit, 5%, 4 pods | D773: BO | E773: SH05-00000020 | F773: Issue | G773: Completed | H773: SO05-00000013 | I773: 05-00000004 | J773: Core-Mark International, Inc. | K773: DSLOCATION | L773: EA | M773: 96 | N773: 96
A774: J1T2395 | C774: JUUL CA Cool Mint Refill Kit, 5%, 4 pods | D774: BO | E774: SH05-00000023 | F774: Issue | G774: Completed | H774: SO05-00000015 | I774: 05-00000004 | J774: Core-Mark International, Inc. | K774: DSLOCATION | L774: EA | M774: 1728 | N774: 1728
A775: J1T2395 | C775: JUUL CA Cool Mint Refill Kit, 5%, 4 pods | D775: BO | E775: SH05-00000025 | F775: Issue | G775: Completed | H775: SO05-00000016 | I775: 05-00000004 | J775: Core-Mark International, Inc. | K775: DSLOCATION | L775: EA | M775: 768 | N775: 768
... A1010: J1T2395 | C1010: JUUL CA Cool Mint Refill Kit, 5%, 4 pods | D1010: SO | E1010: SH05-00000498 | F1010: Issue | G1010: Completed | H1010: SO05-00000434 | I1010: 05-00000011 | J1010: JUUL B2C - Batch | K1010: GO DIRECT | L1010: EA | M1010: 870 | N1010: 870
L1011: Total: | M1011: 366184 | N1011: 366184
D1013: J1T2396 | F1013: JUUL CA Mango Refill Kit, 5%, 4 pods
D1014: Type | E1014: Ref. Nbr. | F1014: Operation | G1014: Order Status | H1014: Order Number | I1014: Customer ID | J1014: Customer Name | K1014: Warehouse | L1014: UOM | M1014: Order Qty. | N1014: Shipped Qty.
A1015: J1T2396 | C1015: JUUL CA Mango Refill Kit, 5%, 4 pods | D1015: BO | E1015: SH05-00000001 | F1015: Issue | G1015: Completed | H1015: SO05-00000001 | I1015: 05-00000002 | J1015: Pacific Smoke International Inc. | K1015: DSLOCATION | L1015: EA | M1015: 9600 | N1015: 9600
A1016: J1T2396 | C1016: JUUL CA Mango Refill Kit, 5%, 4 pods | D1016: BO | E1016: SH05-00000010 | F1016: Issue | G1016: Completed | H1016: SO05-00000004 | I1016: 05-00000004 | J1016: Core-Mark International, Inc. | K1016: DSLOCATION | L1016: EA | M1016: 4608 | N1016: 4608
A1017: J1T2396 | C1017: JUUL CA Mango Refill Kit, 5%, 4 pods | D1017: BO | E1017: SH05-00000011 | F1017: Issue | G1017: Completed | H1017: SO05-00000005 | I1017: 05-00000004 | J1017: Core-Mark International, Inc. | K1017: DSLOCATION | L1017: EA | M1017: 10464 | N1017: 10464
A1018: J1T2396 | C1018: JUUL CA Mango Refill Kit, 5%, 4 pods | D1018: BO | E1018: SH05-00000012 | F1018: Issue | G1018: Completed | H1018: SO05-00000006 | I1018: 05-00000004 | J1018: Core-Mark International, Inc. | K1018: DSLOCATION | L1018: EA | M1018: 2496 | N1018: 2496
A1019: J1T2396 | C1019: JUUL CA Mango Refill Kit, 5%, 4 pods | D1019: BO | E1019: SH05-00000013 | F1019: Issue | G1019: Completed | H1019: SO05-00000007 | I1019: 05-00000004 | J1019: Core-Mark International, Inc. | K1019: DSLOCATION | L1019: EA | M1019: 1200 | N1019: 1200
A1020: J1T2396 | C1020: JUUL CA Mango Refill Kit, 5%, 4 pods | D1020: BO | E1020: SH05-00000014 | F1020: Issue | G1020: Completed | H1020: SO05-00000008 | I1020: 05-00000004 | J1020: Core-Mark International, Inc. | K1020: DSLOCATION | L1020: EA | M1020: 2592 | N1020: 2592
A1021: J1T2396 | C1021: JUUL CA Mango Refill Kit, 5%, 4 pods | D1021: BO | E1021: SH05-00000015 | F1021: Issue | G1021: Completed | H1021: SO05-00000009 | I1021: 05-00000008 | J1021: Greenlane | K1021: DSLOCATION | L1021: EA | M1021: 25728 | N1021: 25728
A1022: J1T2396 | C1022: JUUL CA Mango Refill Kit, 5%, 4 pods | D1022: BO | E1022: SH05-00000018 | F1022: Issue | G1022: Completed | H1022: SO05-00000010 | I1022: 05-00000002 | J1022: Pacific Smoke International Inc. | K1022: DSLOCATION | L1022: EA | M1022: 4320 | N1022: 4320
A1023: J1T2396 | C1023: JUUL CA Mango Refill Kit, 5%, 4 pods | D1023: BO | E1023: SH05-00000017 | F1023: Issue | G1023: Completed | H1023: SO05-00000011 | I1023: 05-00000009 | J1023: Wallace & Carey Inc. | K1023: DSLOCATION | L1023: EA | M1023: 1536 | N1023: 1536
A1024: J1T2396 | C1024: JUUL CA Mango Refill Kit, 5%, 4 pods | D1024: BO | E1024: SH05-00000020 | F1024: Issue | G1024: Completed | H1024: SO05-00000013 | I1024: 05-00000004 | J1024: Core-Mark International, Inc. | K1024: DSLOCATION | L1024: EA | M1024: 96 | N1024: 96
A1025: J1T2396 | C1025: JUUL CA Mango Refill Kit, 5%, 4 pods | D1025: BO | E1025: SH05-00000023 | F1025: Issue | G1025: Completed | H1025: SO05-00000015 | I1025: 05-00000004 | J1025: Core-Mark International, Inc. | K1025: DSLOCATION | L1025: EA | M1025: 1728 | N1025: 1728
A1026: J1T2396 | C1026: JUUL CA Mango Refill Kit, 5%, 4 pods | D1026: BO | E1026: SH05-00000025 | F1026: Issue | G1026: Completed | H1026: SO05-00000016 | I1026: 05-00000004 | J1026: Core-Mark International, Inc. | K1026: DSLOCATION | L1026: EA | M1026: 768 | N1026: 768
... A1261: J1T2396 | C1261: JUUL CA Mango Refill Kit, 5%, 4 pods | D1261: SO | E1261: SH05-00000498 | F1261: Issue | G1261: Completed | H1261: SO05-00000434 | I1261: 05-00000011 | J1261: JUUL B2C - Batch | K1261: GO DIRECT | L1261: EA | M1261: 1187 | N1261: 1187
L1262: Total: | M1262: 426233 | N1262: 426233
...
