Workbook
Name \0: #REF!
Name __________ALL2: [1]GERM3435!$A$1:$P$380
Name __________Sum1: '[2]P & L Qtrly Comp Chg 1 vs 2'!$W$8:$W$148
Name __________SUM2: [1]GERM3435!$A$300:$Q$347
Name _________ALL2: [1]GERM3435!$A$1:$P$380
Name _________Sum1: '[2]P & L Qtrly Comp Chg 1 vs 2'!$W$8:$W$148
Name _________SUM2: [1]GERM3435!$A$300:$Q$347
Name ________ALL2: [1]GERM3435!$A$1:$P$380
Name ________Sum1: '[2]P & L Qtrly Comp Chg 1 vs 2'!$W$8:$W$148
Name ________SUM2: [1]GERM3435!$A$300:$Q$347
Name _______ALL2: [1]GERM3435!$A$1:$P$380
Name _______Sum1: '[2]P & L Qtrly Comp Chg 1 vs 2'!$W$8:$W$148
Name _______SUM2: [1]GERM3435!$A$300:$Q$347
Name ______ALL2: [1]GERM3435!$A$1:$P$380
Name ______Sum1: '[2]P & L Qtrly Comp Chg 1 vs 2'!$W$8:$W$148
Name ______SUM2: [1]GERM3435!$A$300:$Q$347
Name _____ALL2: [1]GERM3435!$A$1:$P$380
Name _____Sum1: '[2]P & L Qtrly Comp Chg 1 vs 2'!$W$8:$W$148
Name _____SUM2: [1]GERM3435!$A$300:$Q$347
Name ____ALL2: [1]GERM3435!$A$1:$P$380
Name ____Sum1: '[2]P & L Qtrly Comp Chg 1 vs 2'!$W$8:$W$148
Name ____SUM2: [1]GERM3435!$A$300:$Q$347
Name ___ALL2: [1]GERM3435!$A$1:$P$380
Name ___Sum1: '[2]P & L Qtrly Comp Chg 1 vs 2'!$W$8:$W$148
Name ___SUM2: [1]GERM3435!$A$300:$Q$347
Name __ALL2: [1]GERM3435!$A$1:$P$380
Name __Sum1: '[2]P & L Qtrly Comp Chg 1 vs 2'!$W$8:$W$148
Name __SUM2: [1]GERM3435!$A$300:$Q$347
Name _2006Q4: '[3]2006 Q4 Personnel Summary'!$D$10:$O$1799
Name _2007Q1: '[3]2007 Q1 Personnel Summary'!$C$8:$O$1903
Name _2007Q1BookComp: '[3]Book Option Data'!$C$9:$BA$916
Name _2007Q1BookRSPComp: '[3]Book RSP Data'!$C$10:$AQ$136
Name _2007Q1PersonnelSummary: '[3]2007 Q1 Personnel Summary'!$C$8:$O$1903
Name _ALL2: [1]GERM3435!$A$1:$P$380
Name _EPs2: #REF!
Name _EPs3: #REF!
Name _EPs4: #REF!
Name _EPs5: #REF!
Name _GrantInformation: #REF!
Name _INT1: #REF!
Name _ISO_Calculaton: #REF!
Name _LTM1: #REF!
Name _new1: '[4]Plan 00'!#REF!
Name _old1: #REF!
Name _OptionType: '[5]2007Q2 Personnel Summary'!$F$9:$K$1935
Name _PMT1: #REF!
Name _PriorGrantInformation: #REF!
Name _Sum1: '[2]P & L Qtrly Comp Chg 1 vs 2'!$W$8:$W$148
Name _SUM2: [1]GERM3435!$A$300:$Q$347
Name _tic1: #REF!
Name _tic2: #REF!
Name aassdd: [0]!aassdd
Name Abschreibungen_April: [6]Abschreibungen!$O$173
Name Abschreibungen_August: [6]Abschreibungen!$S$173
Name Abschreibungen_Dezember: [6]Abschreibungen!$W$173
Name Abschreibungen_Februar: [6]Abschreibungen!$M$173
Name Abschreibungen_Januar: [6]Abschreibungen!$L$173
Name Abschreibungen_Juli: [6]Abschreibungen!$R$173
Name Abschreibungen_Juni: [6]Abschreibungen!$Q$173
Name Abschreibungen_Mai: [6]Abschreibungen!$P$173

Sheet 220950 Accrued Freight & Fulfil
C2: Type of Spreadsheet or Key Report: | D2: Reconcilliation
C3: Spreadsheet or Key Report Name: | D3: 220950 Accrued Freight & Fulfillment Reconcilliation
D4: Reconcilliation for Freight out accrued and fulfillment account with all ending and beginning balances.
C5: File Path: | D5: https://juul.box.com/s/480d6xcpgpn1qw168mo8rhvqy51a8v2f
C6: Version: | D6: 1
C7: GL Account(s) affected: | D7: 220950
C8: Reporting Currency | D8: SGD
C9: Amount per Subledger/Detailed Recon/Calculation | D9: ='Reconciliation Sheet'!M19 -> -1192948.8
C10: GL Balance: Current Period | D10: ='Reconciliation Sheet'!M20 -> -1192948.8
C11: Difference | D11: =D9-D10 -> 0
C12: Difference explained - Please add explanation herein e.g. "Below de minimis" or reference where reconciliation has been done | D12: N/A
C14: Balance Change Month over Month: | D14: ='Trial Balance 9.10.19'!D39-'Trial Balance 9.10.19'!G39 -> -279019.83
C15: Percentage Balance Change Month over Month: | D15: ='Trial Balance 9.10.19'!D39/'Trial Balance 9.10.19'!G39 -> #DIV/0!
C16: Period on Period Change Threshold | D16: 0
C17: Flux/Trending Analysis if period on Period change is greater than Threshold | D17: 0
C18: Key or Non-Key Account: | D18: 0
C19: Risk Level (High, Medium, Low): | D19: LOW
C20: Data source(s): | D20: Freight rates & Accumatica Journal Entries
C21: Source system: | D21: Accumatica
C22: Source Report Name: | D22: Account Details & Trial Balance Summary
C23: Control Number (if applicable):
C24: Frequency: | D24: Monthly
C25: Month / Period: | D25: 43678
C27: Preparer: | D27: Gilberto M. Guajardo
C28: 1st Reviewer: | D28: Seyong Lee
C29: 2nd Reviewer:
C31: PREPARER PROCEDURES
C32: Procedures performed to prepare the spreadsheet:
C33: Download acccount details and trial balance and use DCL Invoices to calculate correct freight out expenses for adjustments.
C35: Name of Excel Tab: | D35: Description / Purpose of Tab:
C36: Reconciiliation Sheet | D36: Reconilliation of invoices, additions and adjustments for Account 220950. Including outstanding balances aswell
C37: TB 9.10.19 | D37: Trial Balance for Account 220950 for Month of Aug 2019
C38: 220950 Account Details June | D38: Transactions for Account 220950 for Month
H44: Sign-off | I44: Date
C45: I have independently calculated the balance and included all relevant support to validate the balance. | H45: GG | I45: 43719
C46: I have ensured the mathematical accuracy of this reconciliation. | H46: GG | I46: 43719
C47: I have ensured there are no hard coded numbers or all hard coded numbers are properly supported. | H47: GG | I47: 43719
C48: I have investigated unusual items, if any, and have posted adjustments if necessary. | H48: GG | I48: 43719
C49: I have appropriately addressed review comments provided by the reviewer. | H49: GG | I49: 43719
C50: All reconciling items/variances over $450,000 or 10% have been verified as valid and properly explained in the documentation. | H50: GG | I50: 43719
C51: I have reviewed reconciling items (as applicable) carried over from prior months and documented reason to maintain or write off item. | H51: GG | I51: 43719
C54: REVIEWER PROCEDURES
C55: Criteria for Investigation (both qualitative and quantitative factors):
C58: Predictability of Expectations:
C61: Procedures performed by reviewer, including samples sub-selected and items requiring further explanation:
C64: For all spreadsheets: | H64: Sign-off | I64: Date
C65: Change/Version Review
C66: Calculations/Formulas
C67: Correct Data Source
C68: Correct Logic
C69: Saved on Shared Drive (automatically backed up)
C71: If the spreadsheet is a reconciliation: | H71: Sign-off | I71: Date
C72: I have agreed the balance per the reconciliation to the general ledger and ensured that the reconciliation is not reconciling the GL to the GL.
C73: I have ensured there are no hard coded numbers or all hard coded numbers are properly supported.
C74: I have validated that the independently calculated balance is sufficiently supported by appropriate documentation.
C75: I have ensured that supporting documentation is adequate and agrees to the reconciliation.
C76: I have received sufficient responses to any queries I may have had.
C77: I have ensured that the reconciliation and underlying details were prepared in accordance with the Company's accounting policies.
C79: SPREADSHEET CHANGE CONTROL
C80: Spreadsheet Change Control
C81: Date of Change:
C82: Purpose of Change:
C83: Version:
C84: Description of Change(s):
C86: Change Control Checklist | F86: Yes / No | G86: Sign-off | H86: Date
C87: Were new GL accounts being affected by this spreadsheet change? If Yes, were these tested to ensure completeness/accuracy?
C88: Was there a change in calculation methodology? If Yes, was a technical memo prepared?
C89: Were sources (reports, systems) of the spreadsheet changed? If Yes, were these tested to ensure completeness/accuracy?
C90: Were input totals re-checked from the source document?
C91: Were all formulas and cell links verified?
C92: Were totals recomputed for accuracy and completeness?
C93: Are check totals built into spreadsheet to ensure accuracy?
C95: REPORTS
C96: Description of key reports used in creating the spreadsheet:
C97: Trial Balance | Account Details 220950 | DCL Invoices
C99: Steps taken to validate completeness and accuracy of source data:
C100: Provided reconcilliation table to verify that there is no variance between trasactions and current month ending balance.
C102: Assertions relating to classes of transactions
C103: Assertions | D103: Explanation | E103: Procedures | F103: Assertion Mapping - document Reference
C104: Occurrence | D104: Transactions recognized in the financial statements have occurred and relate to the entity.
C105: Completeness | D105: All transactions that were supposed to be recorded have been recognized in the financial statements. | E105: When pulling account detail data only posted entries appear in our transaction details.
C106: Accuracy | D106: Transactions have been recorded accurately at their appropriate amounts. | E106: Transactions based on JE Calculations based on current month Freight rates and shipment Volumes
C107: Cut-off | D107: Transactions have been recognized in the correct accounting periods. | E107: All Journal entries and account detials have been retrieved for the correct month of analysis.
C108: Classification | D108: Transactions have been classified and presented fairly in the financial statements. | E108: All data in reconciliation has sources and formulas to explain are final calculation and classifications.
C110: Assertions relating to assets, liabilities and equity balances at the period end
C111: Assertions | D111: Explanation | E111: Procedures
C112: Existence | D112: Assets, liabilities and equity balances exist at the period end. | E112: Freight out and warehousing balances for current month have been reconcilled between account 220950 beginning balances and ending balances.
C113: Completeness | D113: All assets, liabilities and equity balances that were supposed to be recorded have been recognized in the financial statements. | E113: Total transactions (Warehouses, Freight out, Warranty) are tied out to 220950 ending balance
C114: Rights & Obligations | D114: Entity has the right to ownership or use of the recognized assets, and the liabilities recognized in the financial statements represent the obligations of the entity. | E114: Freight out rates and cost have been communicated to supervisor and other management for leadership reporting.
C115: Valuation | D115: Assets, liabilities and equity balances have been valued appropriately. | E115: Transactions between beginning balance and ending balance have all tied out to current Trial Balance Data.
C117: Assertions relating to presentation and disclosures
C118: Assertions | D118: Explanation | E118: Examples: Related Party Disclosures
C119: Occurrence | D119: Transactions and events disclosed in the financial statements have occurred and relate to the entity. | E119: All Additions, invoices and adjustment are reflected by the 220950 Account details tab. This show all of the transactions that ocurred to the account for the current month of analysis.
C120: Completeness | D120: All transactions, balances, events and other matters that should have been disclosed have been disclosed in the financial statements. | E120: A) Trial balance and Account details must match in ending balance. If they do then all transactions for current account have been disclosed and are available for review.
C121: Classification & Understandability | D121: Disclosed events, transactions, balances and other financial matters have been classified appropriately and presented clearly in a manner that promotes the understandability of information contained in the financial statements. | E121: Mapping is done by GL team in consulation with Logistics team including new accounts
C122: Accuracy & Valuation | D122: Transactions, events, balances and other financial matters have been disclosed accurately at their appropriate amounts. | E122: a) JE Input is compared to uploaded JE in ACM b) Accrued rebates have matched payments to customers or shortpayments by customers

Sheet Reconciliation Sheet
A1: SGHoldco ACCRUED FREIGHT RECONCILIATION
A2: 43678
A3: Subledger Recon:
C4: Period | D4: Classification | E4: Beginning Balance - July 2019 | G4: Additions | I4: Invoiced | K4: Reconciling Items | M4: Ending Balance - July 2019 | N4: Pending Invoice Balance
C6: MAY | D6: Freight Out Capitalization | E6: -379311.11 | M6: =(G6+E6+I6+K6) -> -379311.11
C7: MAY | D7: Fulfillment | E7: -67167.06 | M7: =(G7+E7+I7+K7) -> -67167.06
C8: MAY | D8: Freight Out Expense | E8: -1449.37 | M8: =(G8+E8+I8+K8) -> -1449.37
C9: JUNE | D9: Fulfillment | E9: -33046.43 | M9: =(G9+E9+I9+K9) -> -33046.43
C10: JUNE | D10: Freight Out Expense | E10: -713.09 | M10: =(G10+E10+I10+K10) -> -713.09
C11: JULY | D11: Fulfillment | E11: -96222.91 | M11: =(G11+E11+I11+K11) -> -96222.91
C12: JULY | D12: Freight Out Expense | E12: -208267.25 | M12: =(G12+E12+I12+K12) -> -208267.25
C13: JULY | D13: Freight Out Capitalization | G13: =-SUM('220950 Account Details'!L27:L35) -> -115343.72 | M13: =(G13+E13+I13+K13) -> -115343.72
C14: August | D14: Fulfillment | G14: =(SUM('220950 Account Details'!K44:K51)-SUM('220950 Account Details'!L44:L51)) -> -85639.74 | M14: =(G14+E14+I14+K14) -> -85639.74
C15: August | D15: Freight Out Expense | E15: 0 | G15: =(SUM('220950 Account Details'!K52:K59)-SUM('220950 Account Details'!L52:L59)) -> -14849.06 | M15: =(G15+E15+I15+K15) -> -14849.06
C16: August | D16: Freight Out Capitalization | E16: 0 | G16: =(SUM('220950 Account Details'!K36:K43)+SUM('220950 Account Details'!L36:L43)) -> -190939.02 | M16: =(G16+E16+I16+K16) -> -190939.02
E17: 0 | M17: =(G17+E17+I17+K17) -> 0
E18: 0 | M18: =(E18+G18+I18+K18) -> 0
D19: Total | E19: =SUM(E5:E17) -> -786177.22 | F19: {b} | M19: =SUM(M5:M18) -> -1192948.8 | N19: #FQ-220950 | O19: {c}
D20: Trial Balance | E20: ='Trial Balance 9.10.19'!D44 -> -786177.22 | M20: ='Trial Balance 9.10.19'!G44 -> -1192948.8
D21: Check | E21: =E20-E19 -> 0 | F21: Rx | M21: =M20-M19 -> 0 | N21: Rx
C23: Refer to NOTES tab for additional information pertaining to balances.

Sheet Trial Balance 9.10.19
A1: Trial Balance Summary | D1: Ledger: | E1: ACTUAL | F1: Page: | G1: 1 of 4
A2: Company: | B2: SGHoldCo | F2: Date: | G2: 43718.974
A3: User: | B3: Guajardo, Gilberto | D3: Fin. Period: | E3: 08-2019
A5: Account | B5: Type | C5: Description | D5: Beginning Balance | E5: Debit | F5: Credit | G5: Ending Balance
A6: 112000 | B6: A | C6: Citi Oper Acct - 4003 | D6: 707190.83 | E6: 5453650 | F6: 4687829.6 | G6: 1473011.2
A7: 112001 | B7: A | C7: Citi Oper Acct - 4011 | D7: 5878145.9 | E7: 31973428 | F7: 32109816 | G7: 5741757.1
A8: 119100 | B8: A | C8: System Cash Clearing Account | D8: 0 | E8: 5539449.4 | F8: 5539449.4 | G8: 0
A9: 121100 | B9: A | C9: Trade Accounts Receivable | D9: 3791391.2 | E9: 4574304.2 | F9: 6638578.3 | G9: 1727117.1
A10: 121130 | B10: A | C10: Trade AR Adjustments | D10: 46423.45 | E10: 5832.69 | F10: 46423.45 | G10: 5832.69
A11: 123100 | B11: A | C11: EE Advances & Other Receivables | D11: 32817 | E11: 0 | F11: 32817 | G11: 0
A12: 123220 | B12: A | C12: VAT Input | D12: 242201.97 | E12: 25534.52 | F12: 0 | G12: 267736.49
A13: 130620 | B13: A | C13: Prepaid Rent | D13: 0 | E13: 5674.8 | F13: 0 | G13: 5674.8
A14: 131000 | B14: A | C14: Deposits - Short Term | D14: 138934.25 | E14: 1800 | F14: 0 | G14: 140734.25
A15: 141000 | B15: A | C15: Inventory - Finished Products | D15: 9682277.7 | E15: 16835584 | F15: 10881610 | G15: 15636251
A16: 141110 | B16: A | C16: Freight In | D16: 23584.42 | E16: 349030.22 | F16: 47893.39 | G16: 324721.25
A17: 148100 | B17: A | C17: I/C PII Adjustment | D17: -2281514.3 | E17: 0 | F17: 31921.91 | G17: -2313436.2
... A119: 821200 | B119: E | C119: Unrealized (gain) loss - currency conversion | D119: -243369.32 | E119: 1684333.5 | F119: 2421656.3 | G119: -980692.13
C120: Total: | D120: 4.429603e-08 | E120: 2.0766069e+08 | F120: 2.0766069e+08 | G120: -1.1641532e-08

Sheet 220950 Account Details
A1: Title: | B1: Account Details
A2: Company: | B2: SGHoldCo
A3: Date: | B3: 10 Sep 2019 23:23 PM GMT+00:00
A5: Parameters
A6: Company (Dynamic): | B6: JUULSG
A7: Branch (Dynamic): | B7: JUULSG
A8: Ledger (Dynamic): | B8: ACTUAL
A9: From Period: | B9: 082019
A10: To Period: | B10: 082019
A11: Account: | B11: 220950
A12: Subaccount (Dynamic): | B12: <Empty>
A13: From Date (Dynamic): | B13: <Empty>
A14: Period Start Date: | B14: 01/08/2019 00:00:00
A15: To Date (Dynamic): | B15: <Empty>
A16: Period End Date: | B16: 31/08/2019 00:00:00
A17: Show Summary (Dynamic): | B17: FALSE
... A24: Ending Balance: | B24: -1192948.76
A26: Selected | B26: Module | C26: Batch Number | D26: Tran. Date | E26: Period | F26: Description | G26: Ref. Number | H26: Account | I26: Subaccount | J26: Beg. Balance | K26: Debit Amount | L26: Credit Amount | M26: Ending Balance | N26: Reclass. Batch Number
B27: GL | C27: GL08-00002245 | D27: 43685 | E27: 08-2019 | F27: Freight in Capitalizatio | July 2019 | H27: 220950 | I27: GU001-DUT-4140-JRK | J27: -786177.22 | K27: 0 | L27: 1238.68 | M27: -787415.9
B28: GL | C28: GL08-00002245 | D28: 43685 | E28: 08-2019 | F28: Freight in Capitalizatio | July 2019 | H28: 220950 | I28: KR001-DUT-4140-JRK | J28: -787415.9 | K28: 0 | L28: 48150.91 | M28: -835566.81
B29: GL | C29: GL08-00002245 | D29: 43685 | E29: 08-2019 | F29: Freight in Capitalizatio | July 2019 | H29: 220950 | I29: PH001-STR-4100-JRK | J29: -835566.81 | K29: 0 | L29: 39232.4 | M29: -874799.21
B30: GL | C30: GL08-00002245 | D30: 43685 | E30: 08-2019 | F30: Freight in Capitalizatio | July 2019 | H30: 220950 | I30: SG001-DUT-4140-JRK | J30: -874799.21 | K30: 0 | L30: 3603.44 | M30: -878402.65
B31: GL | C31: GL08-00002245 | D31: 43685 | E31: 08-2019 | F31: Freight in Capitalizatio | July 2019 | H31: 220950 | I31: SG001-DUT-4140-JUL | J31: -878402.65 | K31: 0 | L31: 1081.03 | M31: -879483.68
B32: GL | C32: GL08-00002245 | D32: 43685 | E32: 08-2019 | F32: Freight in Capitalizatio | July 2019 | H32: 220950 | I32: PH001-STR-4100-JUL | J32: -879483.68 | K32: 0 | L32: 14391.22 | M32: -893874.9
B33: GL | C33: GL08-00002245 | D33: 43685 | E33: 08-2019 | F33: Freight in Capitalizatio | July 2019 | H33: 220950 | I33: GU001-DUT-4140-JSK | J33: -893874.9 | K33: 0 | L33: 326.56 | M33: -894201.46
B34: GL | C34: GL08-00002245 | D34: 43685 | E34: 08-2019 | F34: Freight in Capitalizatio | July 2019 | H34: 220950 | I34: PH001-STR-4100-JAC | J34: -894201.46 | K34: 0 | L34: 472.95 | M34: -894674.41
B35: GL | C35: GL08-00002245 | D35: 43685 | E35: 08-2019 | F35: Freight in Capitalizatio | July 2019 | H35: 220950 | I35: KR001-DUT-4140-JUL | J35: -894674.41 | K35: 0 | L35: 6846.53 | M35: -901520.94
B36: GL | C36: GL08-00002742 | D36: 43708 | E36: 08-2019 | F36: Freight in Capitalization | August 2019 | H36: 220950 | I36: PH001-STR-4100-JRK | J36: -901520.94 | K36: 0 | L36: -31776.71 | M36: -933297.65
B37: GL | C37: GL08-00002742 | D37: 43708 | E37: 08-2019 | F37: Freight in Capitalization | August 2019 | H37: 220950 | I37: PH001-STR-4100-JAC | J37: -933297.65 | K37: 0 | L37: -557.49 | M37: -933855.14
B38: GL | C38: GL08-00002742 | D38: 43708 | E38: 08-2019 | F38: Freight in Capitalization | August 2019 | H38: 220950 | I38: KR001-CRP-6000-JAC | J38: -933855.14 | K38: 23786.08 | L38: 0 | M38: -910069.06
... B59: GL | C59: GL08-00002743 | D59: 43708 | E59: 08-2019 | F59: Freight Out Expense | August 2019 | H59: 220950 | I59: KR001-CRP-6000-JBK | J59: -1194336.1 | K59: 1387.36 | L59: 0 | M59: -1192948.8
