Workbook

Sheet Summary
L1: Invoiced | M1: Freight Coding | N1: February | O1: March | P1: April | Q1: May | R1: June | S1: July | T1: August | U1: September | V1: October | W1: November | X1: December | Y1: Total Expense May to Jul 2018 | AB1: Trial Balance Summary | AE1: Ledger: | AF1: ACTUAL | AG1: Page: | AH1: 1 of 1
M2: Total by Month | N2: =SUM(N3:N250) -> 72 | O2: =SUM(O3:O250) -> 181575.68 | P2: =SUM(P3:P250) -> 1309884.9 | Q2: =SUM(Q3:Q250) -> 1023340 | R2: =SUM(R3:R250) -> 1038270 | S2: =SUM(S3:S250) -> 920939.59 | T2: =SUM(T3:T250) -> 110601.42 | U2: =SUM(U3:U250) -> 0 | ... X2: =SUM(X3:X250) -> 0 | Y2: =SUM(N2:X2) -> 4584683.5 | AB2: Company: | AC2: Juul | AE2: Branch: | AF2: PLOOM | AG2: Date: | AH2: 43322.44
A3: =$L3&N$1&$M3 -> MarchFebruaryAFG NC - DCL KY | B3: =$L3&O$1&$M3 -> MarchMarchAFG NC - DCL KY | C3: =$L3&P$1&$M3 -> MarchAprilAFG NC - DCL KY | D3: =$L3&Q$1&$M3 -> MarchMayAFG NC - DCL KY | E3: =$L3&R$1&$M3 -> MarchJuneAFG NC - DCL KY | F3: =$L3&S$1&$M3 -> MarchJulyAFG NC - DCL KY | G3: =$L3&T$1&$M3 -> MarchAugustAFG NC - DCL KY | H3: =$L3&U$1&$M3 -> MarchSeptemberAFG NC - DCL KY | ... K3: =$L3&X$1&$M3 -> MarchDecemberAFG NC - DCL KY | L3: March | M3: AFG NC - DCL KY | N3: =SUMIF(Data!$A:$A,Summary!A3,Data!$M:$M) -> 0 | O3: =SUMIF(Data!$A:$A,Summary!B3,Data!$M:$M) -> 1725 | P3: =SUMIF(Data!$A:$A,Summary!C3,Data!$M:$M) -> 0 | Q3: =SUMIF(Data!$A:$A,Summary!D3,Data!$M:$M) -> 0 | R3: =SUMIF(Data!$A:$A,Summary!E3,Data!$M:$M) -> 0 | S3: =SUMIF(Data!$A:$A,Summary!F3,Data!$M:$M) -> 0 | T3: =SUMIF(Data!$A:$A,Summary!G3,Data!$M:$M) -> 0 | U3: =SUMIF(Data!$A:$A,Summary!H3,Data!$M:$M) -> 0 | ... X3: =SUMIF(Data!$A:$A,Summary!K3,Data!$M:$M) -> 0 | AB3: User: | AC3: alejandro | AE3: Fin. Period: | AF3: 05-2018
A4: =$L4&N$1&$M4 -> MarchFebruaryAFG NC - Canada | B4: =$L4&O$1&$M4 -> MarchMarchAFG NC - Canada | C4: =$L4&P$1&$M4 -> MarchAprilAFG NC - Canada | D4: =$L4&Q$1&$M4 -> MarchMayAFG NC - Canada | E4: =$L4&R$1&$M4 -> MarchJuneAFG NC - Canada | F4: =$L4&S$1&$M4 -> MarchJulyAFG NC - Canada | G4: =$L4&T$1&$M4 -> MarchAugustAFG NC - Canada | H4: =$L4&U$1&$M4 -> MarchSeptemberAFG NC - Canada | ... K4: =$L4&X$1&$M4 -> MarchDecemberAFG NC - Canada | L4: March | M4: AFG NC - Canada | N4: =SUMIF(Data!$A:$A,Summary!A4,Data!$M:$M) -> 0 | O4: =SUMIF(Data!$A:$A,Summary!B4,Data!$M:$M) -> 0 | P4: =SUMIF(Data!$A:$A,Summary!C4,Data!$M:$M) -> 0 | Q4: =SUMIF(Data!$A:$A,Summary!D4,Data!$M:$M) -> 0 | R4: =SUMIF(Data!$A:$A,Summary!E4,Data!$M:$M) -> 0 | S4: =SUMIF(Data!$A:$A,Summary!F4,Data!$M:$M) -> 0 | T4: =SUMIF(Data!$A:$A,Summary!G4,Data!$M:$M) -> 0 | U4: =SUMIF(Data!$A:$A,Summary!H4,Data!$M:$M) -> 0 | ... X4: =SUMIF(Data!$A:$A,Summary!K4,Data!$M:$M) -> 0 | AB4: Account | AC4: Type | AD4: Description | AE4: Beginning Balance | AF4: Debit | AG4: Credit | AH4: Ending Balance
A5: =$L5&N$1&$M5 -> MarchFebruaryAFG NC - Phillips WI | B5: =$L5&O$1&$M5 -> MarchMarchAFG NC - Phillips WI | C5: =$L5&P$1&$M5 -> MarchAprilAFG NC - Phillips WI | D5: =$L5&Q$1&$M5 -> MarchMayAFG NC - Phillips WI | E5: =$L5&R$1&$M5 -> MarchJuneAFG NC - Phillips WI | F5: =$L5&S$1&$M5 -> MarchJulyAFG NC - Phillips WI | G5: =$L5&T$1&$M5 -> MarchAugustAFG NC - Phillips WI | H5: =$L5&U$1&$M5 -> MarchSeptemberAFG NC - Phillips WI | ... K5: =$L5&X$1&$M5 -> MarchDecemberAFG NC - Phillips WI | L5: March | M5: AFG NC - Phillips WI | N5: =SUMIF(Data!$A:$A,Summary!A5,Data!$M:$M) -> 0 | O5: =SUMIF(Data!$A:$A,Summary!B5,Data!$M:$M) -> 0 | P5: =SUMIF(Data!$A:$A,Summary!C5,Data!$M:$M) -> 0 | Q5: =SUMIF(Data!$A:$A,Summary!D5,Data!$M:$M) -> 0 | R5: =SUMIF(Data!$A:$A,Summary!E5,Data!$M:$M) -> 0 | S5: =SUMIF(Data!$A:$A,Summary!F5,Data!$M:$M) -> 0 | T5: =SUMIF(Data!$A:$A,Summary!G5,Data!$M:$M) -> 0 | U5: =SUMIF(Data!$A:$A,Summary!H5,Data!$M:$M) -> 0 | ... X5: =SUMIF(Data!$A:$A,Summary!K5,Data!$M:$M) -> 0 | AB5: 513000 | AC5: E | AD5: Cost of Goods - Landed Cost Variance | AE5: 2421092.3 | AF5: 749631.24 | AG5: 0 | AH5: 3170723.5
A6: =$L6&N$1&$M6 -> MarchFebruaryAFG Suzho - DCL KY | B6: =$L6&O$1&$M6 -> MarchMarchAFG Suzho - DCL KY | C6: =$L6&P$1&$M6 -> MarchAprilAFG Suzho - DCL KY | D6: =$L6&Q$1&$M6 -> MarchMayAFG Suzho - DCL KY | E6: =$L6&R$1&$M6 -> MarchJuneAFG Suzho - DCL KY | F6: =$L6&S$1&$M6 -> MarchJulyAFG Suzho - DCL KY | G6: =$L6&T$1&$M6 -> MarchAugustAFG Suzho - DCL KY | H6: =$L6&U$1&$M6 -> MarchSeptemberAFG Suzho - DCL KY | ... K6: =$L6&X$1&$M6 -> MarchDecemberAFG Suzho - DCL KY | L6: March | M6: AFG Suzho - DCL KY | N6: =SUMIF(Data!$A:$A,Summary!A6,Data!$M:$M) -> 0 | O6: =SUMIF(Data!$A:$A,Summary!B6,Data!$M:$M) -> 0 | P6: =SUMIF(Data!$A:$A,Summary!C6,Data!$M:$M) -> 0 | Q6: =SUMIF(Data!$A:$A,Summary!D6,Data!$M:$M) -> 0 | R6: =SUMIF(Data!$A:$A,Summary!E6,Data!$M:$M) -> 0 | S6: =SUMIF(Data!$A:$A,Summary!F6,Data!$M:$M) -> 0 | T6: =SUMIF(Data!$A:$A,Summary!G6,Data!$M:$M) -> 0 | U6: =SUMIF(Data!$A:$A,Summary!H6,Data!$M:$M) -> 0 | ... X6: =SUMIF(Data!$A:$A,Summary!K6,Data!$M:$M) -> 0 | AB6: 515000 | AC6: E | AD6: Freight Inbound | AE6: 403113.61 | AF6: 986440.3 | AG6: 534470.8 | AH6: 855083.11
A7: =$L7&N$1&$M7 -> MarchFebruaryAFG Suzho - DECI NC | B7: =$L7&O$1&$M7 -> MarchMarchAFG Suzho - DECI NC | C7: =$L7&P$1&$M7 -> MarchAprilAFG Suzho - DECI NC | D7: =$L7&Q$1&$M7 -> MarchMayAFG Suzho - DECI NC | E7: =$L7&R$1&$M7 -> MarchJuneAFG Suzho - DECI NC | F7: =$L7&S$1&$M7 -> MarchJulyAFG Suzho - DECI NC | G7: =$L7&T$1&$M7 -> MarchAugustAFG Suzho - DECI NC | H7: =$L7&U$1&$M7 -> MarchSeptemberAFG Suzho - DECI NC | ... K7: =$L7&X$1&$M7 -> MarchDecemberAFG Suzho - DECI NC | L7: March | M7: AFG Suzho - DECI NC | N7: =SUMIF(Data!$A:$A,Summary!A7,Data!$M:$M) -> 0 | O7: =SUMIF(Data!$A:$A,Summary!B7,Data!$M:$M) -> 0 | P7: =SUMIF(Data!$A:$A,Summary!C7,Data!$M:$M) -> 0 | Q7: =SUMIF(Data!$A:$A,Summary!D7,Data!$M:$M) -> 0 | R7: =SUMIF(Data!$A:$A,Summary!E7,Data!$M:$M) -> 0 | S7: =SUMIF(Data!$A:$A,Summary!F7,Data!$M:$M) -> 0 | T7: =SUMIF(Data!$A:$A,Summary!G7,Data!$M:$M) -> 0 | U7: =SUMIF(Data!$A:$A,Summary!H7,Data!$M:$M) -> 0 | ... X7: =SUMIF(Data!$A:$A,Summary!K7,Data!$M:$M) -> 0 | AD7: Total: | AE7: =SUM(AE5:AE6) -> 2824205.9 | AF7: =SUM(AF5:AF6) -> 1736071.5 | AG7: =SUM(AG5:AG6) -> 534470.8 | AH7: =SUM(AH5:AH6) -> 4025806.7
A8: =$L8&N$1&$M8 -> MarchFebruaryAFG Suzho - Flex IL | B8: =$L8&O$1&$M8 -> MarchMarchAFG Suzho - Flex IL | C8: =$L8&P$1&$M8 -> MarchAprilAFG Suzho - Flex IL | D8: =$L8&Q$1&$M8 -> MarchMayAFG Suzho - Flex IL | E8: =$L8&R$1&$M8 -> MarchJuneAFG Suzho - Flex IL | F8: =$L8&S$1&$M8 -> MarchJulyAFG Suzho - Flex IL | G8: =$L8&T$1&$M8 -> MarchAugustAFG Suzho - Flex IL | H8: =$L8&U$1&$M8 -> MarchSeptemberAFG Suzho - Flex IL | ... K8: =$L8&X$1&$M8 -> MarchDecemberAFG Suzho - Flex IL | L8: March | M8: AFG Suzho - Flex IL | N8: =SUMIF(Data!$A:$A,Summary!A8,Data!$M:$M) -> 0 | O8: =SUMIF(Data!$A:$A,Summary!B8,Data!$M:$M) -> 0 | P8: =SUMIF(Data!$A:$A,Summary!C8,Data!$M:$M) -> 0 | Q8: =SUMIF(Data!$A:$A,Summary!D8,Data!$M:$M) -> 0 | R8: =SUMIF(Data!$A:$A,Summary!E8,Data!$M:$M) -> 0 | S8: =SUMIF(Data!$A:$A,Summary!F8,Data!$M:$M) -> 0 | T8: =SUMIF(Data!$A:$A,Summary!G8,Data!$M:$M) -> 0 | U8: =SUMIF(Data!$A:$A,Summary!H8,Data!$M:$M) -> 0 | ... X8: =SUMIF(Data!$A:$A,Summary!K8,Data!$M:$M) -> 0 | AF8: =AF7-AG7 -> 1201600.7
A9: =$L9&N$1&$M9 -> MarchFebruaryChicago IL - Phillips WI | B9: =$L9&O$1&$M9 -> MarchMarchChicago IL - Phillips WI | C9: =$L9&P$1&$M9 -> MarchAprilChicago IL - Phillips WI | D9: =$L9&Q$1&$M9 -> MarchMayChicago IL - Phillips WI | E9: =$L9&R$1&$M9 -> MarchJuneChicago IL - Phillips WI | F9: =$L9&S$1&$M9 -> MarchJulyChicago IL - Phillips WI | G9: =$L9&T$1&$M9 -> MarchAugustChicago IL - Phillips WI | H9: =$L9&U$1&$M9 -> MarchSeptemberChicago IL - Phillips WI | ... K9: =$L9&X$1&$M9 -> MarchDecemberChicago IL - Phillips WI | L9: March | M9: Chicago IL - Phillips WI | N9: =SUMIF(Data!$A:$A,Summary!A9,Data!$M:$M) -> 0 | O9: =SUMIF(Data!$A:$A,Summary!B9,Data!$M:$M) -> 0 | P9: =SUMIF(Data!$A:$A,Summary!C9,Data!$M:$M) -> 0 | Q9: =SUMIF(Data!$A:$A,Summary!D9,Data!$M:$M) -> 0 | R9: =SUMIF(Data!$A:$A,Summary!E9,Data!$M:$M) -> 0 | S9: =SUMIF(Data!$A:$A,Summary!F9,Data!$M:$M) -> 0 | T9: =SUMIF(Data!$A:$A,Summary!G9,Data!$M:$M) -> 0 | U9: =SUMIF(Data!$A:$A,Summary!H9,Data!$M:$M) -> 0 | ... X9: =SUMIF(Data!$A:$A,Summary!K9,Data!$M:$M) -> 0 | AB9: Trial Balance Summary | AE9: Ledger: | AF9: ACTUAL | AG9: Page: | AH9: 1 of 1
A10: =$L10&N$1&$M10 -> MarchFebruaryChina - DCL KY | B10: =$L10&O$1&$M10 -> MarchMarchChina - DCL KY | C10: =$L10&P$1&$M10 -> MarchAprilChina - DCL KY | D10: =$L10&Q$1&$M10 -> MarchMayChina - DCL KY | E10: =$L10&R$1&$M10 -> MarchJuneChina - DCL KY | F10: =$L10&S$1&$M10 -> MarchJulyChina - DCL KY | G10: =$L10&T$1&$M10 -> MarchAugustChina - DCL KY | H10: =$L10&U$1&$M10 -> MarchSeptemberChina - DCL KY | ... K10: =$L10&X$1&$M10 -> MarchDecemberChina - DCL KY | L10: March | M10: China - DCL KY | N10: =SUMIF(Data!$A:$A,Summary!A10,Data!$M:$M) -> 0 | O10: =SUMIF(Data!$A:$A,Summary!B10,Data!$M:$M) -> 62064.18 | P10: =SUMIF(Data!$A:$A,Summary!C10,Data!$M:$M) -> 0 | Q10: =SUMIF(Data!$A:$A,Summary!D10,Data!$M:$M) -> 0 | R10: =SUMIF(Data!$A:$A,Summary!E10,Data!$M:$M) -> 0 | S10: =SUMIF(Data!$A:$A,Summary!F10,Data!$M:$M) -> 0 | T10: =SUMIF(Data!$A:$A,Summary!G10,Data!$M:$M) -> 0 | U10: =SUMIF(Data!$A:$A,Summary!H10,Data!$M:$M) -> 0 | ... X10: =SUMIF(Data!$A:$A,Summary!K10,Data!$M:$M) -> 0 | AB10: Company: | AC10: Juul | AE10: Branch: | AF10: PLOOM | AG10: Date: | AH10: 43322.501
A11: =$L11&N$1&$M11 -> MarchFebruaryChina - DECI NC | B11: =$L11&O$1&$M11 -> MarchMarchChina - DECI NC | C11: =$L11&P$1&$M11 -> MarchAprilChina - DECI NC | D11: =$L11&Q$1&$M11 -> MarchMayChina - DECI NC | E11: =$L11&R$1&$M11 -> MarchJuneChina - DECI NC | F11: =$L11&S$1&$M11 -> MarchJulyChina - DECI NC | G11: =$L11&T$1&$M11 -> MarchAugustChina - DECI NC | H11: =$L11&U$1&$M11 -> MarchSeptemberChina - DECI NC | ... K11: =$L11&X$1&$M11 -> MarchDecemberChina - DECI NC | L11: March | M11: China - DECI NC | N11: =SUMIF(Data!$A:$A,Summary!A11,Data!$M:$M) -> 0 | O11: =SUMIF(Data!$A:$A,Summary!B11,Data!$M:$M) -> 0 | P11: =SUMIF(Data!$A:$A,Summary!C11,Data!$M:$M) -> 0 | Q11: =SUMIF(Data!$A:$A,Summary!D11,Data!$M:$M) -> 0 | R11: =SUMIF(Data!$A:$A,Summary!E11,Data!$M:$M) -> 0 | S11: =SUMIF(Data!$A:$A,Summary!F11,Data!$M:$M) -> 0 | T11: =SUMIF(Data!$A:$A,Summary!G11,Data!$M:$M) -> 0 | U11: =SUMIF(Data!$A:$A,Summary!H11,Data!$M:$M) -> 0 | ... X11: =SUMIF(Data!$A:$A,Summary!K11,Data!$M:$M) -> 0 | AB11: User: | AC11: alejandro | AE11: Fin. Period: | AF11: 06-2018
A12: =$L12&N$1&$M12 -> MarchFebruaryChina - Flex IL | B12: =$L12&O$1&$M12 -> MarchMarchChina - Flex IL | C12: =$L12&P$1&$M12 -> MarchAprilChina - Flex IL | D12: =$L12&Q$1&$M12 -> MarchMayChina - Flex IL | E12: =$L12&R$1&$M12 -> MarchJuneChina - Flex IL | F12: =$L12&S$1&$M12 -> MarchJulyChina - Flex IL | G12: =$L12&T$1&$M12 -> MarchAugustChina - Flex IL | H12: =$L12&U$1&$M12 -> MarchSeptemberChina - Flex IL | ... K12: =$L12&X$1&$M12 -> MarchDecemberChina - Flex IL | L12: March | M12: China - Flex IL | N12: =SUMIF(Data!$A:$A,Summary!A12,Data!$M:$M) -> 0 | O12: =SUMIF(Data!$A:$A,Summary!B12,Data!$M:$M) -> 0 | P12: =SUMIF(Data!$A:$A,Summary!C12,Data!$M:$M) -> 0 | Q12: =SUMIF(Data!$A:$A,Summary!D12,Data!$M:$M) -> 0 | R12: =SUMIF(Data!$A:$A,Summary!E12,Data!$M:$M) -> 0 | S12: =SUMIF(Data!$A:$A,Summary!F12,Data!$M:$M) -> 0 | T12: =SUMIF(Data!$A:$A,Summary!G12,Data!$M:$M) -> 0 | U12: =SUMIF(Data!$A:$A,Summary!H12,Data!$M:$M) -> 0 | ... X12: =SUMIF(Data!$A:$A,Summary!K12,Data!$M:$M) -> 0 | AB12: Account | AC12: Type | AD12: Description | AE12: Beginning Balance | AF12: Debit | AG12: Credit | AH12: Ending Balance
A13: =$L13&N$1&$M13 -> MarchFebruaryChina - Phillips WI | B13: =$L13&O$1&$M13 -> MarchMarchChina - Phillips WI | C13: =$L13&P$1&$M13 -> MarchAprilChina - Phillips WI | D13: =$L13&Q$1&$M13 -> MarchMayChina - Phillips WI | E13: =$L13&R$1&$M13 -> MarchJuneChina - Phillips WI | F13: =$L13&S$1&$M13 -> MarchJulyChina - Phillips WI | G13: =$L13&T$1&$M13 -> MarchAugustChina - Phillips WI | H13: =$L13&U$1&$M13 -> MarchSeptemberChina - Phillips WI | ... K13: =$L13&X$1&$M13 -> MarchDecemberChina - Phillips WI | L13: March | M13: China - Phillips WI | N13: =SUMIF(Data!$A:$A,Summary!A13,Data!$M:$M) -> 0 | O13: =SUMIF(Data!$A:$A,Summary!B13,Data!$M:$M) -> 0 | P13: =SUMIF(Data!$A:$A,Summary!C13,Data!$M:$M) -> 0 | Q13: =SUMIF(Data!$A:$A,Summary!D13,Data!$M:$M) -> 0 | R13: =SUMIF(Data!$A:$A,Summary!E13,Data!$M:$M) -> 0 | S13: =SUMIF(Data!$A:$A,Summary!F13,Data!$M:$M) -> 0 | T13: =SUMIF(Data!$A:$A,Summary!G13,Data!$M:$M) -> 0 | U13: =SUMIF(Data!$A:$A,Summary!H13,Data!$M:$M) -> 0 | ... X13: =SUMIF(Data!$A:$A,Summary!K13,Data!$M:$M) -> 0 | AB13: 513000 | AC13: E | AD13: Cost of Goods - Landed Cost Variance | AE13: 3170723.5 | AF13: 491441.76 | AG13: 0 | AH13: 3662165.3
A14: =$L14&N$1&$M14 -> MarchFebruaryChina - San Francisco | B14: =$L14&O$1&$M14 -> MarchMarchChina - San Francisco | C14: =$L14&P$1&$M14 -> MarchAprilChina - San Francisco | D14: =$L14&Q$1&$M14 -> MarchMayChina - San Francisco | E14: =$L14&R$1&$M14 -> MarchJuneChina - San Francisco | F14: =$L14&S$1&$M14 -> MarchJulyChina - San Francisco | G14: =$L14&T$1&$M14 -> MarchAugustChina - San Francisco | H14: =$L14&U$1&$M14 -> MarchSeptemberChina - San Francisco | ... K14: =$L14&X$1&$M14 -> MarchDecemberChina - San Francisco | L14: March | M14: China - San Francisco | N14: =SUMIF(Data!$A:$A,Summary!A14,Data!$M:$M) -> 0 | O14: =SUMIF(Data!$A:$A,Summary!B14,Data!$M:$M) -> 0 | P14: =SUMIF(Data!$A:$A,Summary!C14,Data!$M:$M) -> 0 | Q14: =SUMIF(Data!$A:$A,Summary!D14,Data!$M:$M) -> 0 | R14: =SUMIF(Data!$A:$A,Summary!E14,Data!$M:$M) -> 0 | S14: =SUMIF(Data!$A:$A,Summary!F14,Data!$M:$M) -> 0 | T14: =SUMIF(Data!$A:$A,Summary!G14,Data!$M:$M) -> 0 | U14: =SUMIF(Data!$A:$A,Summary!H14,Data!$M:$M) -> 0 | ... X14: =SUMIF(Data!$A:$A,Summary!K14,Data!$M:$M) -> 0 | AB14: 515000 | AC14: E | AD14: Freight Inbound | AE14: 855083.11 | AF14: 730453.14 | AG14: 87693.64 | AH14: 1497842.6
A15: =$L15&N$1&$M15 -> MarchFebruaryDCL KY - Canada | B15: =$L15&O$1&$M15 -> MarchMarchDCL KY - Canada | C15: =$L15&P$1&$M15 -> MarchAprilDCL KY - Canada | D15: =$L15&Q$1&$M15 -> MarchMayDCL KY - Canada | E15: =$L15&R$1&$M15 -> MarchJuneDCL KY - Canada | F15: =$L15&S$1&$M15 -> MarchJulyDCL KY - Canada | G15: =$L15&T$1&$M15 -> MarchAugustDCL KY - Canada | H15: =$L15&U$1&$M15 -> MarchSeptemberDCL KY - Canada | ... K15: =$L15&X$1&$M15 -> MarchDecemberDCL KY - Canada | L15: March | M15: DCL KY - Canada | N15: =SUMIF(Data!$A:$A,Summary!A15,Data!$M:$M) -> 0 | O15: =SUMIF(Data!$A:$A,Summary!B15,Data!$M:$M) -> 0 | P15: =SUMIF(Data!$A:$A,Summary!C15,Data!$M:$M) -> 0 | Q15: =SUMIF(Data!$A:$A,Summary!D15,Data!$M:$M) -> 0 | R15: =SUMIF(Data!$A:$A,Summary!E15,Data!$M:$M) -> 0 | S15: =SUMIF(Data!$A:$A,Summary!F15,Data!$M:$M) -> 0 | T15: =SUMIF(Data!$A:$A,Summary!G15,Data!$M:$M) -> 0 | U15: =SUMIF(Data!$A:$A,Summary!H15,Data!$M:$M) -> 0 | ... X15: =SUMIF(Data!$A:$A,Summary!K15,Data!$M:$M) -> 0 | AD15: Total: | AE15: =SUM(AE13:AE14) -> 4025806.7 | AF15: =SUM(AF13:AF14) -> 1221894.9 | AG15: =SUM(AG13:AG14) -> 87693.64 | AH15: =SUM(AH13:AH14) -> 5160007.9
A16: =$L16&N$1&$M16 -> MarchFebruaryDECI NC - DCL KY | B16: =$L16&O$1&$M16 -> MarchMarchDECI NC - DCL KY | C16: =$L16&P$1&$M16 -> MarchAprilDECI NC - DCL KY | D16: =$L16&Q$1&$M16 -> MarchMayDECI NC - DCL KY | E16: =$L16&R$1&$M16 -> MarchJuneDECI NC - DCL KY | F16: =$L16&S$1&$M16 -> MarchJulyDECI NC - DCL KY | G16: =$L16&T$1&$M16 -> MarchAugustDECI NC - DCL KY | H16: =$L16&U$1&$M16 -> MarchSeptemberDECI NC - DCL KY | ... K16: =$L16&X$1&$M16 -> MarchDecemberDECI NC - DCL KY | L16: March | M16: DECI NC - DCL KY | N16: =SUMIF(Data!$A:$A,Summary!A16,Data!$M:$M) -> 0 | O16: =SUMIF(Data!$A:$A,Summary!B16,Data!$M:$M) -> 0 | P16: =SUMIF(Data!$A:$A,Summary!C16,Data!$M:$M) -> 0 | Q16: =SUMIF(Data!$A:$A,Summary!D16,Data!$M:$M) -> 0 | R16: =SUMIF(Data!$A:$A,Summary!E16,Data!$M:$M) -> 0 | S16: =SUMIF(Data!$A:$A,Summary!F16,Data!$M:$M) -> 0 | T16: =SUMIF(Data!$A:$A,Summary!G16,Data!$M:$M) -> 0 | U16: =SUMIF(Data!$A:$A,Summary!H16,Data!$M:$M) -> 0 | ... X16: =SUMIF(Data!$A:$A,Summary!K16,Data!$M:$M) -> 0 | AF16: =AF15-AG15 -> 1134201.3
A17: =$L17&N$1&$M17 -> MarchFebruaryGreensboro NC - Phillips WI | B17: =$L17&O$1&$M17 -> MarchMarchGreensboro NC - Phillips WI | C17: =$L17&P$1&$M17 -> MarchAprilGreensboro NC - Phillips WI | D17: =$L17&Q$1&$M17 -> MarchMayGreensboro NC - Phillips WI | E17: =$L17&R$1&$M17 -> MarchJuneGreensboro NC - Phillips WI | F17: =$L17&S$1&$M17 -> MarchJulyGreensboro NC - Phillips WI | G17: =$L17&T$1&$M17 -> MarchAugustGreensboro NC - Phillips WI | H17: =$L17&U$1&$M17 -> MarchSeptemberGreensboro NC - Phillips WI | ... K17: =$L17&X$1&$M17 -> MarchDecemberGreensboro NC - Phillips WI | L17: March | M17: Greensboro NC - Phillips WI | N17: =SUMIF(Data!$A:$A,Summary!A17,Data!$M:$M) -> 0 | O17: =SUMIF(Data!$A:$A,Summary!B17,Data!$M:$M) -> 3122.8 | P17: =SUMIF(Data!$A:$A,Summary!C17,Data!$M:$M) -> 0 | Q17: =SUMIF(Data!$A:$A,Summary!D17,Data!$M:$M) -> 0 | R17: =SUMIF(Data!$A:$A,Summary!E17,Data!$M:$M) -> 0 | S17: =SUMIF(Data!$A:$A,Summary!F17,Data!$M:$M) -> 0 | T17: =SUMIF(Data!$A:$A,Summary!G17,Data!$M:$M) -> 0 | U17: =SUMIF(Data!$A:$A,Summary!H17,Data!$M:$M) -> 0 | ... X17: =SUMIF(Data!$A:$A,Summary!K17,Data!$M:$M) -> 0 | AB17: Trial Balance Summary | AE17: Ledger: | AF17: ACTUAL | AG17: Page: | AH17: 1 of 1
A18: =$L18&N$1&$M18 -> MarchFebruaryFlex IL - UK | B18: =$L18&O$1&$M18 -> MarchMarchFlex IL - UK | C18: =$L18&P$1&$M18 -> MarchAprilFlex IL - UK | D18: =$L18&Q$1&$M18 -> MarchMayFlex IL - UK | E18: =$L18&R$1&$M18 -> MarchJuneFlex IL - UK | F18: =$L18&S$1&$M18 -> MarchJulyFlex IL - UK | G18: =$L18&T$1&$M18 -> MarchAugustFlex IL - UK | H18: =$L18&U$1&$M18 -> MarchSeptemberFlex IL - UK | ... K18: =$L18&X$1&$M18 -> MarchDecemberFlex IL - UK | L18: March | M18: Flex IL - UK | N18: =SUMIF(Data!$A:$A,Summary!A18,Data!$M:$M) -> 0 | O18: =SUMIF(Data!$A:$A,Summary!B18,Data!$M:$M) -> 0 | P18: =SUMIF(Data!$A:$A,Summary!C18,Data!$M:$M) -> 0 | Q18: =SUMIF(Data!$A:$A,Summary!D18,Data!$M:$M) -> 0 | R18: =SUMIF(Data!$A:$A,Summary!E18,Data!$M:$M) -> 0 | S18: =SUMIF(Data!$A:$A,Summary!F18,Data!$M:$M) -> 0 | T18: =SUMIF(Data!$A:$A,Summary!G18,Data!$M:$M) -> 0 | U18: =SUMIF(Data!$A:$A,Summary!H18,Data!$M:$M) -> 0 | ... X18: =SUMIF(Data!$A:$A,Summary!K18,Data!$M:$M) -> 0 | AB18: Company: | AC18: Juul | AE18: Branch: | AF18: PLOOM | AG18: Date: | AH18: 43322.44
A19: =$L19&N$1&$M19 -> MarchFebruaryFlorida - Phillips WI | B19: =$L19&O$1&$M19 -> MarchMarchFlorida - Phillips WI | C19: =$L19&P$1&$M19 -> MarchAprilFlorida - Phillips WI | D19: =$L19&Q$1&$M19 -> MarchMayFlorida - Phillips WI | E19: =$L19&R$1&$M19 -> MarchJuneFlorida - Phillips WI | F19: =$L19&S$1&$M19 -> MarchJulyFlorida - Phillips WI | G19: =$L19&T$1&$M19 -> MarchAugustFlorida - Phillips WI | H19: =$L19&U$1&$M19 -> MarchSeptemberFlorida - Phillips WI | ... K19: =$L19&X$1&$M19 -> MarchDecemberFlorida - Phillips WI | L19: March | M19: Florida - Phillips WI | N19: =SUMIF(Data!$A:$A,Summary!A19,Data!$M:$M) -> 0 | O19: =SUMIF(Data!$A:$A,Summary!B19,Data!$M:$M) -> 0 | P19: =SUMIF(Data!$A:$A,Summary!C19,Data!$M:$M) -> 0 | Q19: =SUMIF(Data!$A:$A,Summary!D19,Data!$M:$M) -> 0 | R19: =SUMIF(Data!$A:$A,Summary!E19,Data!$M:$M) -> 0 | S19: =SUMIF(Data!$A:$A,Summary!F19,Data!$M:$M) -> 0 | T19: =SUMIF(Data!$A:$A,Summary!G19,Data!$M:$M) -> 0 | U19: =SUMIF(Data!$A:$A,Summary!H19,Data!$M:$M) -> 0 | ... X19: =SUMIF(Data!$A:$A,Summary!K19,Data!$M:$M) -> 0 | AB19: User: | AC19: alejandro | AE19: Fin. Period: | AF19: 07-2018
A20: =$L20&N$1&$M20 -> MarchFebruaryHong Kong - AFG NC | B20: =$L20&O$1&$M20 -> MarchMarchHong Kong - AFG NC | C20: =$L20&P$1&$M20 -> MarchAprilHong Kong - AFG NC | D20: =$L20&Q$1&$M20 -> MarchMayHong Kong - AFG NC | E20: =$L20&R$1&$M20 -> MarchJuneHong Kong - AFG NC | F20: =$L20&S$1&$M20 -> MarchJulyHong Kong - AFG NC | G20: =$L20&T$1&$M20 -> MarchAugustHong Kong - AFG NC | H20: =$L20&U$1&$M20 -> MarchSeptemberHong Kong - AFG NC | ... K20: =$L20&X$1&$M20 -> MarchDecemberHong Kong - AFG NC | L20: March | M20: Hong Kong - AFG NC | N20: =SUMIF(Data!$A:$A,Summary!A20,Data!$M:$M) -> 72 | O20: =SUMIF(Data!$A:$A,Summary!B20,Data!$M:$M) -> 0 | P20: =SUMIF(Data!$A:$A,Summary!C20,Data!$M:$M) -> 4398.85 | Q20: =SUMIF(Data!$A:$A,Summary!D20,Data!$M:$M) -> 0 | R20: =SUMIF(Data!$A:$A,Summary!E20,Data!$M:$M) -> 0 | S20: =SUMIF(Data!$A:$A,Summary!F20,Data!$M:$M) -> 0 | T20: =SUMIF(Data!$A:$A,Summary!G20,Data!$M:$M) -> 0 | U20: =SUMIF(Data!$A:$A,Summary!H20,Data!$M:$M) -> 0 | ... X20: =SUMIF(Data!$A:$A,Summary!K20,Data!$M:$M) -> 0 | AB20: Account | AC20: Type | AD20: Description | AE20: Beginning Balance | AF20: Debit | AG20: Credit | AH20: Ending Balance
A21: =$L21&N$1&$M21 -> MarchFebruaryHong Kong - DCL KY | B21: =$L21&O$1&$M21 -> MarchMarchHong Kong - DCL KY | C21: =$L21&P$1&$M21 -> MarchAprilHong Kong - DCL KY | D21: =$L21&Q$1&$M21 -> MarchMayHong Kong - DCL KY | E21: =$L21&R$1&$M21 -> MarchJuneHong Kong - DCL KY | F21: =$L21&S$1&$M21 -> MarchJulyHong Kong - DCL KY | G21: =$L21&T$1&$M21 -> MarchAugustHong Kong - DCL KY | H21: =$L21&U$1&$M21 -> MarchSeptemberHong Kong - DCL KY | ... K21: =$L21&X$1&$M21 -> MarchDecemberHong Kong - DCL KY | L21: March | M21: Hong Kong - DCL KY | N21: =SUMIF(Data!$A:$A,Summary!A21,Data!$M:$M) -> 0 | O21: =SUMIF(Data!$A:$A,Summary!B21,Data!$M:$M) -> 55750.41 | P21: =SUMIF(Data!$A:$A,Summary!C21,Data!$M:$M) -> 0 | Q21: =SUMIF(Data!$A:$A,Summary!D21,Data!$M:$M) -> 0 | R21: =SUMIF(Data!$A:$A,Summary!E21,Data!$M:$M) -> 0 | S21: =SUMIF(Data!$A:$A,Summary!F21,Data!$M:$M) -> 0 | T21: =SUMIF(Data!$A:$A,Summary!G21,Data!$M:$M) -> 0 | U21: =SUMIF(Data!$A:$A,Summary!H21,Data!$M:$M) -> 0 | ... X21: =SUMIF(Data!$A:$A,Summary!K21,Data!$M:$M) -> 0 | AB21: 513000 | AC21: E | AD21: Cost of Goods - Landed Cost Variance | AE21: 3662165.3 | AF21: 100021.68 | AG21: 100021.68 | AH21: 3662165.3
A22: =$L22&N$1&$M22 -> MarchFebruaryHong Kong - DECI NC | B22: =$L22&O$1&$M22 -> MarchMarchHong Kong - DECI NC | C22: =$L22&P$1&$M22 -> MarchAprilHong Kong - DECI NC | D22: =$L22&Q$1&$M22 -> MarchMayHong Kong - DECI NC | E22: =$L22&R$1&$M22 -> MarchJuneHong Kong - DECI NC | F22: =$L22&S$1&$M22 -> MarchJulyHong Kong - DECI NC | G22: =$L22&T$1&$M22 -> MarchAugustHong Kong - DECI NC | H22: =$L22&U$1&$M22 -> MarchSeptemberHong Kong - DECI NC | ... K22: =$L22&X$1&$M22 -> MarchDecemberHong Kong - DECI NC | L22: March | M22: Hong Kong - DECI NC | N22: =SUMIF(Data!$A:$A,Summary!A22,Data!$M:$M) -> 0 | O22: =SUMIF(Data!$A:$A,Summary!B22,Data!$M:$M) -> 58913.29 | P22: =SUMIF(Data!$A:$A,Summary!C22,Data!$M:$M) -> 0 | Q22: =SUMIF(Data!$A:$A,Summary!D22,Data!$M:$M) -> 0 | R22: =SUMIF(Data!$A:$A,Summary!E22,Data!$M:$M) -> 0 | S22: =SUMIF(Data!$A:$A,Summary!F22,Data!$M:$M) -> 0 | T22: =SUMIF(Data!$A:$A,Summary!G22,Data!$M:$M) -> 0 | U22: =SUMIF(Data!$A:$A,Summary!H22,Data!$M:$M) -> 0 | ... X22: =SUMIF(Data!$A:$A,Summary!K22,Data!$M:$M) -> 0 | AB22: 515000 | AC22: E | AD22: Freight Inbound | AE22: 1497842.6 | AF22: 1388272.6 | AG22: 197141.27 | AH22: 2688974
A23: =$L23&N$1&$M23 -> MarchFebruaryHong Kong - Flex IL | B23: =$L23&O$1&$M23 -> MarchMarchHong Kong - Flex IL | C23: =$L23&P$1&$M23 -> MarchAprilHong Kong - Flex IL | D23: =$L23&Q$1&$M23 -> MarchMayHong Kong - Flex IL | E23: =$L23&R$1&$M23 -> MarchJuneHong Kong - Flex IL | F23: =$L23&S$1&$M23 -> MarchJulyHong Kong - Flex IL | G23: =$L23&T$1&$M23 -> MarchAugustHong Kong - Flex IL | H23: =$L23&U$1&$M23 -> MarchSeptemberHong Kong - Flex IL | ... K23: =$L23&X$1&$M23 -> MarchDecemberHong Kong - Flex IL | L23: March | M23: Hong Kong - Flex IL | N23: =SUMIF(Data!$A:$A,Summary!A23,Data!$M:$M) -> 0 | O23: =SUMIF(Data!$A:$A,Summary!B23,Data!$M:$M) -> 0 | P23: =SUMIF(Data!$A:$A,Summary!C23,Data!$M:$M) -> 0 | Q23: =SUMIF(Data!$A:$A,Summary!D23,Data!$M:$M) -> 0 | R23: =SUMIF(Data!$A:$A,Summary!E23,Data!$M:$M) -> 0 | S23: =SUMIF(Data!$A:$A,Summary!F23,Data!$M:$M) -> 0 | T23: =SUMIF(Data!$A:$A,Summary!G23,Data!$M:$M) -> 0 | U23: =SUMIF(Data!$A:$A,Summary!H23,Data!$M:$M) -> 0 | ... X23: =SUMIF(Data!$A:$A,Summary!K23,Data!$M:$M) -> 0 | AD23: Total: | AE23: =SUM(AE21:AE22) -> 5160007.9 | AF23: =SUM(AF21:AF22) -> 1488294.3 | AG23: =SUM(AG21:AG22) -> 297162.95 | AH23: =SUM(AH21:AH22) -> 6351139.3
A24: =$L24&N$1&$M24 -> MarchFebruaryHong Kong - Phillips WI | B24: =$L24&O$1&$M24 -> MarchMarchHong Kong - Phillips WI | C24: =$L24&P$1&$M24 -> MarchAprilHong Kong - Phillips WI | D24: =$L24&Q$1&$M24 -> MarchMayHong Kong - Phillips WI | E24: =$L24&R$1&$M24 -> MarchJuneHong Kong - Phillips WI | F24: =$L24&S$1&$M24 -> MarchJulyHong Kong - Phillips WI | G24: =$L24&T$1&$M24 -> MarchAugustHong Kong - Phillips WI | H24: =$L24&U$1&$M24 -> MarchSeptemberHong Kong - Phillips WI | ... K24: =$L24&X$1&$M24 -> MarchDecemberHong Kong - Phillips WI | L24: March | M24: Hong Kong - Phillips WI | N24: =SUMIF(Data!$A:$A,Summary!A24,Data!$M:$M) -> 0 | O24: =SUMIF(Data!$A:$A,Summary!B24,Data!$M:$M) -> 0 | P24: =SUMIF(Data!$A:$A,Summary!C24,Data!$M:$M) -> 0 | Q24: =SUMIF(Data!$A:$A,Summary!D24,Data!$M:$M) -> 0 | R24: =SUMIF(Data!$A:$A,Summary!E24,Data!$M:$M) -> 0 | S24: =SUMIF(Data!$A:$A,Summary!F24,Data!$M:$M) -> 0 | T24: =SUMIF(Data!$A:$A,Summary!G24,Data!$M:$M) -> 0 | U24: =SUMIF(Data!$A:$A,Summary!H24,Data!$M:$M) -> 0 | ... X24: =SUMIF(Data!$A:$A,Summary!K24,Data!$M:$M) -> 0 | AF24: =AF23-AG23 -> 1191131.4
A25: =$L25&N$1&$M25 -> MarchFebruaryPhillips WI - DCL KY | B25: =$L25&O$1&$M25 -> MarchMarchPhillips WI - DCL KY | C25: =$L25&P$1&$M25 -> MarchAprilPhillips WI - DCL KY | D25: =$L25&Q$1&$M25 -> MarchMayPhillips WI - DCL KY | E25: =$L25&R$1&$M25 -> MarchJunePhillips WI - DCL KY | F25: =$L25&S$1&$M25 -> MarchJulyPhillips WI - DCL KY | G25: =$L25&T$1&$M25 -> MarchAugustPhillips WI - DCL KY | H25: =$L25&U$1&$M25 -> MarchSeptemberPhillips WI - DCL KY | ... K25: =$L25&X$1&$M25 -> MarchDecemberPhillips WI - DCL KY | L25: March | M25: Phillips WI - DCL KY | N25: =SUMIF(Data!$A:$A,Summary!A25,Data!$M:$M) -> 0 | O25: =SUMIF(Data!$A:$A,Summary!B25,Data!$M:$M) -> 0 | P25: =SUMIF(Data!$A:$A,Summary!C25,Data!$M:$M) -> 0 | Q25: =SUMIF(Data!$A:$A,Summary!D25,Data!$M:$M) -> 0 | R25: =SUMIF(Data!$A:$A,Summary!E25,Data!$M:$M) -> 0 | S25: =SUMIF(Data!$A:$A,Summary!F25,Data!$M:$M) -> 0 | T25: =SUMIF(Data!$A:$A,Summary!G25,Data!$M:$M) -> 0 | U25: =SUMIF(Data!$A:$A,Summary!H25,Data!$M:$M) -> 0 | ... X25: =SUMIF(Data!$A:$A,Summary!K25,Data!$M:$M) -> 0 | AB25: Trial Balance Summary | AE25: Ledger: | AF25: ACTUAL | AG25: Page: | AH25: 1 of 1
A26: =$L26&N$1&$M26 -> MarchFebruarySan Francisco - Canada | B26: =$L26&O$1&$M26 -> MarchMarchSan Francisco - Canada | C26: =$L26&P$1&$M26 -> MarchAprilSan Francisco - Canada | D26: =$L26&Q$1&$M26 -> MarchMaySan Francisco - Canada | E26: =$L26&R$1&$M26 -> MarchJuneSan Francisco - Canada | F26: =$L26&S$1&$M26 -> MarchJulySan Francisco - Canada | G26: =$L26&T$1&$M26 -> MarchAugustSan Francisco - Canada | H26: =$L26&U$1&$M26 -> MarchSeptemberSan Francisco - Canada | ... K26: =$L26&X$1&$M26 -> MarchDecemberSan Francisco - Canada | L26: March | M26: San Francisco - Canada | N26: =SUMIF(Data!$A:$A,Summary!A26,Data!$M:$M) -> 0 | O26: =SUMIF(Data!$A:$A,Summary!B26,Data!$M:$M) -> 0 | P26: =SUMIF(Data!$A:$A,Summary!C26,Data!$M:$M) -> 0 | Q26: =SUMIF(Data!$A:$A,Summary!D26,Data!$M:$M) -> 0 | R26: =SUMIF(Data!$A:$A,Summary!E26,Data!$M:$M) -> 0 | S26: =SUMIF(Data!$A:$A,Summary!F26,Data!$M:$M) -> 0 | T26: =SUMIF(Data!$A:$A,Summary!G26,Data!$M:$M) -> 0 | U26: =SUMIF(Data!$A:$A,Summary!H26,Data!$M:$M) -> 0 | ... X26: =SUMIF(Data!$A:$A,Summary!K26,Data!$M:$M) -> 0 | AB26: Company: | AC26: Juul | AE26: Branch: | AF26: PLOOM | AG26: Date: | AH26: 43367.421
A27: =$L27&N$1&$M27 -> MarchFebruaryShanghai - DCL KY | B27: =$L27&O$1&$M27 -> MarchMarchShanghai - DCL KY | C27: =$L27&P$1&$M27 -> MarchAprilShanghai - DCL KY | D27: =$L27&Q$1&$M27 -> MarchMayShanghai - DCL KY | E27: =$L27&R$1&$M27 -> MarchJuneShanghai - DCL KY | F27: =$L27&S$1&$M27 -> MarchJulyShanghai - DCL KY | G27: =$L27&T$1&$M27 -> MarchAugustShanghai - DCL KY | H27: =$L27&U$1&$M27 -> MarchSeptemberShanghai - DCL KY | ... K27: =$L27&X$1&$M27 -> MarchDecemberShanghai - DCL KY | L27: March | M27: Shanghai - DCL KY | N27: =SUMIF(Data!$A:$A,Summary!A27,Data!$M:$M) -> 0 | O27: =SUMIF(Data!$A:$A,Summary!B27,Data!$M:$M) -> 0 | P27: =SUMIF(Data!$A:$A,Summary!C27,Data!$M:$M) -> 0 | Q27: =SUMIF(Data!$A:$A,Summary!D27,Data!$M:$M) -> 0 | R27: =SUMIF(Data!$A:$A,Summary!E27,Data!$M:$M) -> 0 | S27: =SUMIF(Data!$A:$A,Summary!F27,Data!$M:$M) -> 0 | T27: =SUMIF(Data!$A:$A,Summary!G27,Data!$M:$M) -> 0 | U27: =SUMIF(Data!$A:$A,Summary!H27,Data!$M:$M) -> 0 | ... X27: =SUMIF(Data!$A:$A,Summary!K27,Data!$M:$M) -> 0 | AB27: User: | AC27: Barajas, Alejandro | AE27: Fin. Period: | AF27: 08-2018
A28: =$L28&N$1&$M28 -> MarchFebruaryShanghai - DECI NC | B28: =$L28&O$1&$M28 -> MarchMarchShanghai - DECI NC | C28: =$L28&P$1&$M28 -> MarchAprilShanghai - DECI NC | D28: =$L28&Q$1&$M28 -> MarchMayShanghai - DECI NC | E28: =$L28&R$1&$M28 -> MarchJuneShanghai - DECI NC | F28: =$L28&S$1&$M28 -> MarchJulyShanghai - DECI NC | G28: =$L28&T$1&$M28 -> MarchAugustShanghai - DECI NC | H28: =$L28&U$1&$M28 -> MarchSeptemberShanghai - DECI NC | ... K28: =$L28&X$1&$M28 -> MarchDecemberShanghai - DECI NC | L28: March | M28: Shanghai - DECI NC | N28: =SUMIF(Data!$A:$A,Summary!A28,Data!$M:$M) -> 0 | O28: =SUMIF(Data!$A:$A,Summary!B28,Data!$M:$M) -> 0 | P28: =SUMIF(Data!$A:$A,Summary!C28,Data!$M:$M) -> 0 | Q28: =SUMIF(Data!$A:$A,Summary!D28,Data!$M:$M) -> 0 | R28: =SUMIF(Data!$A:$A,Summary!E28,Data!$M:$M) -> 0 | S28: =SUMIF(Data!$A:$A,Summary!F28,Data!$M:$M) -> 0 | T28: =SUMIF(Data!$A:$A,Summary!G28,Data!$M:$M) -> 0 | U28: =SUMIF(Data!$A:$A,Summary!H28,Data!$M:$M) -> 0 | ... X28: =SUMIF(Data!$A:$A,Summary!K28,Data!$M:$M) -> 0
A29: =$L29&N$1&$M29 -> MarchFebruaryTaiwan - DCL KY | B29: =$L29&O$1&$M29 -> MarchMarchTaiwan - DCL KY | C29: =$L29&P$1&$M29 -> MarchAprilTaiwan - DCL KY | D29: =$L29&Q$1&$M29 -> MarchMayTaiwan - DCL KY | E29: =$L29&R$1&$M29 -> MarchJuneTaiwan - DCL KY | F29: =$L29&S$1&$M29 -> MarchJulyTaiwan - DCL KY | G29: =$L29&T$1&$M29 -> MarchAugustTaiwan - DCL KY | H29: =$L29&U$1&$M29 -> MarchSeptemberTaiwan - DCL KY | ... K29: =$L29&X$1&$M29 -> MarchDecemberTaiwan - DCL KY | L29: March | M29: Taiwan - DCL KY | N29: =SUMIF(Data!$A:$A,Summary!A29,Data!$M:$M) -> 0 | O29: =SUMIF(Data!$A:$A,Summary!B29,Data!$M:$M) -> 0 | P29: =SUMIF(Data!$A:$A,Summary!C29,Data!$M:$M) -> 0 | Q29: =SUMIF(Data!$A:$A,Summary!D29,Data!$M:$M) -> 0 | R29: =SUMIF(Data!$A:$A,Summary!E29,Data!$M:$M) -> 0 | S29: =SUMIF(Data!$A:$A,Summary!F29,Data!$M:$M) -> 0 | T29: =SUMIF(Data!$A:$A,Summary!G29,Data!$M:$M) -> 0 | U29: =SUMIF(Data!$A:$A,Summary!H29,Data!$M:$M) -> 0 | ... X29: =SUMIF(Data!$A:$A,Summary!K29,Data!$M:$M) -> 0 | AB29: Account | AC29: Type | AD29: Description | AE29: Beginning Balance | AF29: Debit | AG29: Credit | AH29: Ending Balance
A30: =$L30&N$1&$M30 -> AprilFebruaryAFG NC - DCL KY | B30: =$L30&O$1&$M30 -> AprilMarchAFG NC - DCL KY | C30: =$L30&P$1&$M30 -> AprilAprilAFG NC - DCL KY | D30: =$L30&Q$1&$M30 -> AprilMayAFG NC - DCL KY | E30: =$L30&R$1&$M30 -> AprilJuneAFG NC - DCL KY | F30: =$L30&S$1&$M30 -> AprilJulyAFG NC - DCL KY | G30: =$L30&T$1&$M30 -> AprilAugustAFG NC - DCL KY | H30: =$L30&U$1&$M30 -> AprilSeptemberAFG NC - DCL KY | ... K30: =$L30&X$1&$M30 -> AprilDecemberAFG NC - DCL KY | L30: April | M30: AFG NC - DCL KY | N30: =SUMIF(Data!$A:$A,Summary!A30,Data!$M:$M) -> 0 | O30: =SUMIF(Data!$A:$A,Summary!B30,Data!$M:$M) -> 0 | P30: =SUMIF(Data!$A:$A,Summary!C30,Data!$M:$M) -> 33300 | Q30: =SUMIF(Data!$A:$A,Summary!D30,Data!$M:$M) -> 0 | R30: =SUMIF(Data!$A:$A,Summary!E30,Data!$M:$M) -> 0 | S30: =SUMIF(Data!$A:$A,Summary!F30,Data!$M:$M) -> 0 | T30: =SUMIF(Data!$A:$A,Summary!G30,Data!$M:$M) -> 0 | U30: =SUMIF(Data!$A:$A,Summary!H30,Data!$M:$M) -> 0 | ... X30: =SUMIF(Data!$A:$A,Summary!K30,Data!$M:$M) -> 0 | AB30: 513000 | AC30: E | AD30: Cost of Goods - Landed Cost Variance | AE30: 3662165.3 | AF30: 0 | AG30: 0 | AH30: 3662165.3
A31: =$L31&N$1&$M31 -> AprilFebruaryAFG NC - Canada | B31: =$L31&O$1&$M31 -> AprilMarchAFG NC - Canada | C31: =$L31&P$1&$M31 -> AprilAprilAFG NC - Canada | D31: =$L31&Q$1&$M31 -> AprilMayAFG NC - Canada | E31: =$L31&R$1&$M31 -> AprilJuneAFG NC - Canada | F31: =$L31&S$1&$M31 -> AprilJulyAFG NC - Canada | G31: =$L31&T$1&$M31 -> AprilAugustAFG NC - Canada | H31: =$L31&U$1&$M31 -> AprilSeptemberAFG NC - Canada | ... K31: =$L31&X$1&$M31 -> AprilDecemberAFG NC - Canada | L31: April | M31: AFG NC - Canada | N31: =SUMIF(Data!$A:$A,Summary!A31,Data!$M:$M) -> 0 | O31: =SUMIF(Data!$A:$A,Summary!B31,Data!$M:$M) -> 0 | P31: =SUMIF(Data!$A:$A,Summary!C31,Data!$M:$M) -> 0 | Q31: =SUMIF(Data!$A:$A,Summary!D31,Data!$M:$M) -> 0 | R31: =SUMIF(Data!$A:$A,Summary!E31,Data!$M:$M) -> 0 | S31: =SUMIF(Data!$A:$A,Summary!F31,Data!$M:$M) -> 0 | T31: =SUMIF(Data!$A:$A,Summary!G31,Data!$M:$M) -> 0 | U31: =SUMIF(Data!$A:$A,Summary!H31,Data!$M:$M) -> 0 | ... X31: =SUMIF(Data!$A:$A,Summary!K31,Data!$M:$M) -> 0 | AB31: 515000 | AC31: E | AD31: Freight Inbound | AE31: 2688974 | AF31: 1105646 | AG31: 0 | AH31: 3794620
A32: =$L32&N$1&$M32 -> AprilFebruaryAFG NC - Phillips WI | B32: =$L32&O$1&$M32 -> AprilMarchAFG NC - Phillips WI | C32: =$L32&P$1&$M32 -> AprilAprilAFG NC - Phillips WI | D32: =$L32&Q$1&$M32 -> AprilMayAFG NC - Phillips WI | E32: =$L32&R$1&$M32 -> AprilJuneAFG NC - Phillips WI | F32: =$L32&S$1&$M32 -> AprilJulyAFG NC - Phillips WI | G32: =$L32&T$1&$M32 -> AprilAugustAFG NC - Phillips WI | H32: =$L32&U$1&$M32 -> AprilSeptemberAFG NC - Phillips WI | ... K32: =$L32&X$1&$M32 -> AprilDecemberAFG NC - Phillips WI | L32: April | M32: AFG NC - Phillips WI | N32: =SUMIF(Data!$A:$A,Summary!A32,Data!$M:$M) -> 0 | O32: =SUMIF(Data!$A:$A,Summary!B32,Data!$M:$M) -> 0 | P32: =SUMIF(Data!$A:$A,Summary!C32,Data!$M:$M) -> 0 | Q32: =SUMIF(Data!$A:$A,Summary!D32,Data!$M:$M) -> 0 | R32: =SUMIF(Data!$A:$A,Summary!E32,Data!$M:$M) -> 0 | S32: =SUMIF(Data!$A:$A,Summary!F32,Data!$M:$M) -> 0 | T32: =SUMIF(Data!$A:$A,Summary!G32,Data!$M:$M) -> 0 | U32: =SUMIF(Data!$A:$A,Summary!H32,Data!$M:$M) -> 0 | ... X32: =SUMIF(Data!$A:$A,Summary!K32,Data!$M:$M) -> 0 | AD32: Total: | AE32: =SUM(AE30:AE31) -> 6351139.3 | AF32: =SUM(AF30:AF31) -> 1105646 | AG32: =SUM(AG30:AG31) -> 0 | AH32: =SUM(AH30:AH31) -> 7456785.3
A33: =$L33&N$1&$M33 -> AprilFebruaryAFG Suzho - DCL KY | B33: =$L33&O$1&$M33 -> AprilMarchAFG Suzho - DCL KY | C33: =$L33&P$1&$M33 -> AprilAprilAFG Suzho - DCL KY | D33: =$L33&Q$1&$M33 -> AprilMayAFG Suzho - DCL KY | E33: =$L33&R$1&$M33 -> AprilJuneAFG Suzho - DCL KY | F33: =$L33&S$1&$M33 -> AprilJulyAFG Suzho - DCL KY | G33: =$L33&T$1&$M33 -> AprilAugustAFG Suzho - DCL KY | H33: =$L33&U$1&$M33 -> AprilSeptemberAFG Suzho - DCL KY | ... K33: =$L33&X$1&$M33 -> AprilDecemberAFG Suzho - DCL KY | L33: April | M33: AFG Suzho - DCL KY | N33: =SUMIF(Data!$A:$A,Summary!A33,Data!$M:$M) -> 0 | O33: =SUMIF(Data!$A:$A,Summary!B33,Data!$M:$M) -> 0 | P33: =SUMIF(Data!$A:$A,Summary!C33,Data!$M:$M) -> 0 | Q33: =SUMIF(Data!$A:$A,Summary!D33,Data!$M:$M) -> 0 | R33: =SUMIF(Data!$A:$A,Summary!E33,Data!$M:$M) -> 0 | S33: =SUMIF(Data!$A:$A,Summary!F33,Data!$M:$M) -> 0 | T33: =SUMIF(Data!$A:$A,Summary!G33,Data!$M:$M) -> 0 | U33: =SUMIF(Data!$A:$A,Summary!H33,Data!$M:$M) -> 0 | ... X33: =SUMIF(Data!$A:$A,Summary!K33,Data!$M:$M) -> 0 | AF33: =AF32-AG32 -> 1105646
A34: =$L34&N$1&$M34 -> AprilFebruaryAFG Suzho - DECI NC | B34: =$L34&O$1&$M34 -> AprilMarchAFG Suzho - DECI NC | C34: =$L34&P$1&$M34 -> AprilAprilAFG Suzho - DECI NC | D34: =$L34&Q$1&$M34 -> AprilMayAFG Suzho - DECI NC | E34: =$L34&R$1&$M34 -> AprilJuneAFG Suzho - DECI NC | F34: =$L34&S$1&$M34 -> AprilJulyAFG Suzho - DECI NC | G34: =$L34&T$1&$M34 -> AprilAugustAFG Suzho - DECI NC | H34: =$L34&U$1&$M34 -> AprilSeptemberAFG Suzho - DECI NC | ... K34: =$L34&X$1&$M34 -> AprilDecemberAFG Suzho - DECI NC | L34: April | M34: AFG Suzho - DECI NC | N34: =SUMIF(Data!$A:$A,Summary!A34,Data!$M:$M) -> 0 | O34: =SUMIF(Data!$A:$A,Summary!B34,Data!$M:$M) -> 0 | P34: =SUMIF(Data!$A:$A,Summary!C34,Data!$M:$M) -> 0 | Q34: =SUMIF(Data!$A:$A,Summary!D34,Data!$M:$M) -> 0 | R34: =SUMIF(Data!$A:$A,Summary!E34,Data!$M:$M) -> 0 | S34: =SUMIF(Data!$A:$A,Summary!F34,Data!$M:$M) -> 0 | T34: =SUMIF(Data!$A:$A,Summary!G34,Data!$M:$M) -> 0 | U34: =SUMIF(Data!$A:$A,Summary!H34,Data!$M:$M) -> 0 | ... X34: =SUMIF(Data!$A:$A,Summary!K34,Data!$M:$M) -> 0 | AE34: Total May to Aug | AF34: =SUM(AF24,AF16,AF8,AF33) -> 4632579.4
A35: =$L35&N$1&$M35 -> AprilFebruaryAFG Suzho - Flex IL | B35: =$L35&O$1&$M35 -> AprilMarchAFG Suzho - Flex IL | C35: =$L35&P$1&$M35 -> AprilAprilAFG Suzho - Flex IL | D35: =$L35&Q$1&$M35 -> AprilMayAFG Suzho - Flex IL | E35: =$L35&R$1&$M35 -> AprilJuneAFG Suzho - Flex IL | F35: =$L35&S$1&$M35 -> AprilJulyAFG Suzho - Flex IL | G35: =$L35&T$1&$M35 -> AprilAugustAFG Suzho - Flex IL | H35: =$L35&U$1&$M35 -> AprilSeptemberAFG Suzho - Flex IL | ... K35: =$L35&X$1&$M35 -> AprilDecemberAFG Suzho - Flex IL | L35: April | M35: AFG Suzho - Flex IL | N35: =SUMIF(Data!$A:$A,Summary!A35,Data!$M:$M) -> 0 | O35: =SUMIF(Data!$A:$A,Summary!B35,Data!$M:$M) -> 0 | P35: =SUMIF(Data!$A:$A,Summary!C35,Data!$M:$M) -> 0 | Q35: =SUMIF(Data!$A:$A,Summary!D35,Data!$M:$M) -> 0 | R35: =SUMIF(Data!$A:$A,Summary!E35,Data!$M:$M) -> 0 | S35: =SUMIF(Data!$A:$A,Summary!F35,Data!$M:$M) -> 0 | T35: =SUMIF(Data!$A:$A,Summary!G35,Data!$M:$M) -> 0 | U35: =SUMIF(Data!$A:$A,Summary!H35,Data!$M:$M) -> 0 | ... X35: =SUMIF(Data!$A:$A,Summary!K35,Data!$M:$M) -> 0
A36: =$L36&N$1&$M36 -> AprilFebruaryChicago IL - Phillips WI | B36: =$L36&O$1&$M36 -> AprilMarchChicago IL - Phillips WI | C36: =$L36&P$1&$M36 -> AprilAprilChicago IL - Phillips WI | D36: =$L36&Q$1&$M36 -> AprilMayChicago IL - Phillips WI | E36: =$L36&R$1&$M36 -> AprilJuneChicago IL - Phillips WI | F36: =$L36&S$1&$M36 -> AprilJulyChicago IL - Phillips WI | G36: =$L36&T$1&$M36 -> AprilAugustChicago IL - Phillips WI | H36: =$L36&U$1&$M36 -> AprilSeptemberChicago IL - Phillips WI | ... K36: =$L36&X$1&$M36 -> AprilDecemberChicago IL - Phillips WI | L36: April | M36: Chicago IL - Phillips WI | N36: =SUMIF(Data!$A:$A,Summary!A36,Data!$M:$M) -> 0 | O36: =SUMIF(Data!$A:$A,Summary!B36,Data!$M:$M) -> 0 | P36: =SUMIF(Data!$A:$A,Summary!C36,Data!$M:$M) -> 0 | Q36: =SUMIF(Data!$A:$A,Summary!D36,Data!$M:$M) -> 0 | R36: =SUMIF(Data!$A:$A,Summary!E36,Data!$M:$M) -> 0 | S36: =SUMIF(Data!$A:$A,Summary!F36,Data!$M:$M) -> 0 | T36: =SUMIF(Data!$A:$A,Summary!G36,Data!$M:$M) -> 0 | U36: =SUMIF(Data!$A:$A,Summary!H36,Data!$M:$M) -> 0 | ... X36: =SUMIF(Data!$A:$A,Summary!K36,Data!$M:$M) -> 0
A37: =$L37&N$1&$M37 -> AprilFebruaryChina - DCL KY | B37: =$L37&O$1&$M37 -> AprilMarchChina - DCL KY | C37: =$L37&P$1&$M37 -> AprilAprilChina - DCL KY | D37: =$L37&Q$1&$M37 -> AprilMayChina - DCL KY | E37: =$L37&R$1&$M37 -> AprilJuneChina - DCL KY | F37: =$L37&S$1&$M37 -> AprilJulyChina - DCL KY | G37: =$L37&T$1&$M37 -> AprilAugustChina - DCL KY | H37: =$L37&U$1&$M37 -> AprilSeptemberChina - DCL KY | ... K37: =$L37&X$1&$M37 -> AprilDecemberChina - DCL KY | L37: April | M37: China - DCL KY | N37: =SUMIF(Data!$A:$A,Summary!A37,Data!$M:$M) -> 0 | O37: =SUMIF(Data!$A:$A,Summary!B37,Data!$M:$M) -> 0 | P37: =SUMIF(Data!$A:$A,Summary!C37,Data!$M:$M) -> 215526.2 | Q37: =SUMIF(Data!$A:$A,Summary!D37,Data!$M:$M) -> 0 | R37: =SUMIF(Data!$A:$A,Summary!E37,Data!$M:$M) -> 0 | S37: =SUMIF(Data!$A:$A,Summary!F37,Data!$M:$M) -> 0 | T37: =SUMIF(Data!$A:$A,Summary!G37,Data!$M:$M) -> 0 | U37: =SUMIF(Data!$A:$A,Summary!H37,Data!$M:$M) -> 0 | ... X37: =SUMIF(Data!$A:$A,Summary!K37,Data!$M:$M) -> 0
A38: =$L38&N$1&$M38 -> AprilFebruaryChina - DECI NC | B38: =$L38&O$1&$M38 -> AprilMarchChina - DECI NC | C38: =$L38&P$1&$M38 -> AprilAprilChina - DECI NC | D38: =$L38&Q$1&$M38 -> AprilMayChina - DECI NC | E38: =$L38&R$1&$M38 -> AprilJuneChina - DECI NC | F38: =$L38&S$1&$M38 -> AprilJulyChina - DECI NC | G38: =$L38&T$1&$M38 -> AprilAugustChina - DECI NC | H38: =$L38&U$1&$M38 -> AprilSeptemberChina - DECI NC | ... K38: =$L38&X$1&$M38 -> AprilDecemberChina - DECI NC | L38: April | M38: China - DECI NC | N38: =SUMIF(Data!$A:$A,Summary!A38,Data!$M:$M) -> 0 | O38: =SUMIF(Data!$A:$A,Summary!B38,Data!$M:$M) -> 0 | P38: =SUMIF(Data!$A:$A,Summary!C38,Data!$M:$M) -> 301176.02 | Q38: =SUMIF(Data!$A:$A,Summary!D38,Data!$M:$M) -> 0 | R38: =SUMIF(Data!$A:$A,Summary!E38,Data!$M:$M) -> 0 | S38: =SUMIF(Data!$A:$A,Summary!F38,Data!$M:$M) -> 0 | T38: =SUMIF(Data!$A:$A,Summary!G38,Data!$M:$M) -> 0 | U38: =SUMIF(Data!$A:$A,Summary!H38,Data!$M:$M) -> 0 | ... X38: =SUMIF(Data!$A:$A,Summary!K38,Data!$M:$M) -> 0
A39: =$L39&N$1&$M39 -> AprilFebruaryChina - Flex IL | B39: =$L39&O$1&$M39 -> AprilMarchChina - Flex IL | C39: =$L39&P$1&$M39 -> AprilAprilChina - Flex IL | D39: =$L39&Q$1&$M39 -> AprilMayChina - Flex IL | E39: =$L39&R$1&$M39 -> AprilJuneChina - Flex IL | F39: =$L39&S$1&$M39 -> AprilJulyChina - Flex IL | G39: =$L39&T$1&$M39 -> AprilAugustChina - Flex IL | H39: =$L39&U$1&$M39 -> AprilSeptemberChina - Flex IL | ... K39: =$L39&X$1&$M39 -> AprilDecemberChina - Flex IL | L39: April | M39: China - Flex IL | N39: =SUMIF(Data!$A:$A,Summary!A39,Data!$M:$M) -> 0 | O39: =SUMIF(Data!$A:$A,Summary!B39,Data!$M:$M) -> 0 | P39: =SUMIF(Data!$A:$A,Summary!C39,Data!$M:$M) -> 0 | Q39: =SUMIF(Data!$A:$A,Summary!D39,Data!$M:$M) -> 0 | R39: =SUMIF(Data!$A:$A,Summary!E39,Data!$M:$M) -> 0 | S39: =SUMIF(Data!$A:$A,Summary!F39,Data!$M:$M) -> 0 | T39: =SUMIF(Data!$A:$A,Summary!G39,Data!$M:$M) -> 0 | U39: =SUMIF(Data!$A:$A,Summary!H39,Data!$M:$M) -> 0 | ... X39: =SUMIF(Data!$A:$A,Summary!K39,Data!$M:$M) -> 0
A40: =$L40&N$1&$M40 -> AprilFebruaryChina - Phillips WI | B40: =$L40&O$1&$M40 -> AprilMarchChina - Phillips WI | C40: =$L40&P$1&$M40 -> AprilAprilChina - Phillips WI | D40: =$L40&Q$1&$M40 -> AprilMayChina - Phillips WI | E40: =$L40&R$1&$M40 -> AprilJuneChina - Phillips WI | F40: =$L40&S$1&$M40 -> AprilJulyChina - Phillips WI | G40: =$L40&T$1&$M40 -> AprilAugustChina - Phillips WI | H40: =$L40&U$1&$M40 -> AprilSeptemberChina - Phillips WI | ... K40: =$L40&X$1&$M40 -> AprilDecemberChina - Phillips WI | L40: April | M40: China - Phillips WI | N40: =SUMIF(Data!$A:$A,Summary!A40,Data!$M:$M) -> 0 | O40: =SUMIF(Data!$A:$A,Summary!B40,Data!$M:$M) -> 0 | P40: =SUMIF(Data!$A:$A,Summary!C40,Data!$M:$M) -> 0 | Q40: =SUMIF(Data!$A:$A,Summary!D40,Data!$M:$M) -> 0 | R40: =SUMIF(Data!$A:$A,Summary!E40,Data!$M:$M) -> 0 | S40: =SUMIF(Data!$A:$A,Summary!F40,Data!$M:$M) -> 0 | T40: =SUMIF(Data!$A:$A,Summary!G40,Data!$M:$M) -> 0 | U40: =SUMIF(Data!$A:$A,Summary!H40,Data!$M:$M) -> 0 | ... X40: =SUMIF(Data!$A:$A,Summary!K40,Data!$M:$M) -> 0
A41: =$L41&N$1&$M41 -> AprilFebruaryChina - San Francisco | B41: =$L41&O$1&$M41 -> AprilMarchChina - San Francisco | C41: =$L41&P$1&$M41 -> AprilAprilChina - San Francisco | D41: =$L41&Q$1&$M41 -> AprilMayChina - San Francisco | E41: =$L41&R$1&$M41 -> AprilJuneChina - San Francisco | F41: =$L41&S$1&$M41 -> AprilJulyChina - San Francisco | G41: =$L41&T$1&$M41 -> AprilAugustChina - San Francisco | H41: =$L41&U$1&$M41 -> AprilSeptemberChina - San Francisco | ... K41: =$L41&X$1&$M41 -> AprilDecemberChina - San Francisco | L41: April | M41: China - San Francisco | N41: =SUMIF(Data!$A:$A,Summary!A41,Data!$M:$M) -> 0 | O41: =SUMIF(Data!$A:$A,Summary!B41,Data!$M:$M) -> 0 | P41: =SUMIF(Data!$A:$A,Summary!C41,Data!$M:$M) -> 3532.92 | Q41: =SUMIF(Data!$A:$A,Summary!D41,Data!$M:$M) -> 0 | R41: =SUMIF(Data!$A:$A,Summary!E41,Data!$M:$M) -> 0 | S41: =SUMIF(Data!$A:$A,Summary!F41,Data!$M:$M) -> 0 | T41: =SUMIF(Data!$A:$A,Summary!G41,Data!$M:$M) -> 0 | U41: =SUMIF(Data!$A:$A,Summary!H41,Data!$M:$M) -> 0 | ... X41: =SUMIF(Data!$A:$A,Summary!K41,Data!$M:$M) -> 0
A42: =$L42&N$1&$M42 -> AprilFebruaryDCL KY - Canada | B42: =$L42&O$1&$M42 -> AprilMarchDCL KY - Canada | C42: =$L42&P$1&$M42 -> AprilAprilDCL KY - Canada | D42: =$L42&Q$1&$M42 -> AprilMayDCL KY - Canada | E42: =$L42&R$1&$M42 -> AprilJuneDCL KY - Canada | F42: =$L42&S$1&$M42 -> AprilJulyDCL KY - Canada | G42: =$L42&T$1&$M42 -> AprilAugustDCL KY - Canada | H42: =$L42&U$1&$M42 -> AprilSeptemberDCL KY - Canada | ... K42: =$L42&X$1&$M42 -> AprilDecemberDCL KY - Canada | L42: April | M42: DCL KY - Canada | N42: =SUMIF(Data!$A:$A,Summary!A42,Data!$M:$M) -> 0 | O42: =SUMIF(Data!$A:$A,Summary!B42,Data!$M:$M) -> 0 | P42: =SUMIF(Data!$A:$A,Summary!C42,Data!$M:$M) -> 0 | Q42: =SUMIF(Data!$A:$A,Summary!D42,Data!$M:$M) -> 0 | R42: =SUMIF(Data!$A:$A,Summary!E42,Data!$M:$M) -> 0 | S42: =SUMIF(Data!$A:$A,Summary!F42,Data!$M:$M) -> 0 | T42: =SUMIF(Data!$A:$A,Summary!G42,Data!$M:$M) -> 0 | U42: =SUMIF(Data!$A:$A,Summary!H42,Data!$M:$M) -> 0 | ... X42: =SUMIF(Data!$A:$A,Summary!K42,Data!$M:$M) -> 0
A43: =$L43&N$1&$M43 -> AprilFebruaryDECI NC - DCL KY | B43: =$L43&O$1&$M43 -> AprilMarchDECI NC - DCL KY | C43: =$L43&P$1&$M43 -> AprilAprilDECI NC - DCL KY | D43: =$L43&Q$1&$M43 -> AprilMayDECI NC - DCL KY | E43: =$L43&R$1&$M43 -> AprilJuneDECI NC - DCL KY | F43: =$L43&S$1&$M43 -> AprilJulyDECI NC - DCL KY | G43: =$L43&T$1&$M43 -> AprilAugustDECI NC - DCL KY | H43: =$L43&U$1&$M43 -> AprilSeptemberDECI NC - DCL KY | ... K43: =$L43&X$1&$M43 -> AprilDecemberDECI NC - DCL KY | L43: April | M43: DECI NC - DCL KY | N43: =SUMIF(Data!$A:$A,Summary!A43,Data!$M:$M) -> 0 | O43: =SUMIF(Data!$A:$A,Summary!B43,Data!$M:$M) -> 0 | P43: =SUMIF(Data!$A:$A,Summary!C43,Data!$M:$M) -> 1450 | Q43: =SUMIF(Data!$A:$A,Summary!D43,Data!$M:$M) -> 0 | R43: =SUMIF(Data!$A:$A,Summary!E43,Data!$M:$M) -> 0 | S43: =SUMIF(Data!$A:$A,Summary!F43,Data!$M:$M) -> 0 | T43: =SUMIF(Data!$A:$A,Summary!G43,Data!$M:$M) -> 0 | U43: =SUMIF(Data!$A:$A,Summary!H43,Data!$M:$M) -> 0 | ... X43: =SUMIF(Data!$A:$A,Summary!K43,Data!$M:$M) -> 0
A44: =$L44&N$1&$M44 -> AprilFebruaryGreensboro NC - Phillips WI | B44: =$L44&O$1&$M44 -> AprilMarchGreensboro NC - Phillips WI | C44: =$L44&P$1&$M44 -> AprilAprilGreensboro NC - Phillips WI | D44: =$L44&Q$1&$M44 -> AprilMayGreensboro NC - Phillips WI | E44: =$L44&R$1&$M44 -> AprilJuneGreensboro NC - Phillips WI | F44: =$L44&S$1&$M44 -> AprilJulyGreensboro NC - Phillips WI | G44: =$L44&T$1&$M44 -> AprilAugustGreensboro NC - Phillips WI | H44: =$L44&U$1&$M44 -> AprilSeptemberGreensboro NC - Phillips WI | ... K44: =$L44&X$1&$M44 -> AprilDecemberGreensboro NC - Phillips WI | L44: April | M44: Greensboro NC - Phillips WI | N44: =SUMIF(Data!$A:$A,Summary!A44,Data!$M:$M) -> 0 | O44: =SUMIF(Data!$A:$A,Summary!B44,Data!$M:$M) -> 0 | P44: =SUMIF(Data!$A:$A,Summary!C44,Data!$M:$M) -> 0 | Q44: =SUMIF(Data!$A:$A,Summary!D44,Data!$M:$M) -> 0 | R44: =SUMIF(Data!$A:$A,Summary!E44,Data!$M:$M) -> 0 | S44: =SUMIF(Data!$A:$A,Summary!F44,Data!$M:$M) -> 0 | T44: =SUMIF(Data!$A:$A,Summary!G44,Data!$M:$M) -> 0 | U44: =SUMIF(Data!$A:$A,Summary!H44,Data!$M:$M) -> 0 | ... X44: =SUMIF(Data!$A:$A,Summary!K44,Data!$M:$M) -> 0
A45: =$L45&N$1&$M45 -> AprilFebruaryFlex IL - UK | B45: =$L45&O$1&$M45 -> AprilMarchFlex IL - UK | C45: =$L45&P$1&$M45 -> AprilAprilFlex IL - UK | D45: =$L45&Q$1&$M45 -> AprilMayFlex IL - UK | E45: =$L45&R$1&$M45 -> AprilJuneFlex IL - UK | F45: =$L45&S$1&$M45 -> AprilJulyFlex IL - UK | G45: =$L45&T$1&$M45 -> AprilAugustFlex IL - UK | H45: =$L45&U$1&$M45 -> AprilSeptemberFlex IL - UK | ... K45: =$L45&X$1&$M45 -> AprilDecemberFlex IL - UK | L45: April | M45: Flex IL - UK | N45: =SUMIF(Data!$A:$A,Summary!A45,Data!$M:$M) -> 0 | O45: =SUMIF(Data!$A:$A,Summary!B45,Data!$M:$M) -> 0 | P45: =SUMIF(Data!$A:$A,Summary!C45,Data!$M:$M) -> 0 | Q45: =SUMIF(Data!$A:$A,Summary!D45,Data!$M:$M) -> 0 | R45: =SUMIF(Data!$A:$A,Summary!E45,Data!$M:$M) -> 0 | S45: =SUMIF(Data!$A:$A,Summary!F45,Data!$M:$M) -> 0 | T45: =SUMIF(Data!$A:$A,Summary!G45,Data!$M:$M) -> 0 | U45: =SUMIF(Data!$A:$A,Summary!H45,Data!$M:$M) -> 0 | ... X45: =SUMIF(Data!$A:$A,Summary!K45,Data!$M:$M) -> 0
A46: =$L46&N$1&$M46 -> AprilFebruaryFlorida - Phillips WI | B46: =$L46&O$1&$M46 -> AprilMarchFlorida - Phillips WI | C46: =$L46&P$1&$M46 -> AprilAprilFlorida - Phillips WI | D46: =$L46&Q$1&$M46 -> AprilMayFlorida - Phillips WI | E46: =$L46&R$1&$M46 -> AprilJuneFlorida - Phillips WI | F46: =$L46&S$1&$M46 -> AprilJulyFlorida - Phillips WI | G46: =$L46&T$1&$M46 -> AprilAugustFlorida - Phillips WI | H46: =$L46&U$1&$M46 -> AprilSeptemberFlorida - Phillips WI | ... K46: =$L46&X$1&$M46 -> AprilDecemberFlorida - Phillips WI | L46: April | M46: Florida - Phillips WI | N46: =SUMIF(Data!$A:$A,Summary!A46,Data!$M:$M) -> 0 | O46: =SUMIF(Data!$A:$A,Summary!B46,Data!$M:$M) -> 0 | P46: =SUMIF(Data!$A:$A,Summary!C46,Data!$M:$M) -> 0 | Q46: =SUMIF(Data!$A:$A,Summary!D46,Data!$M:$M) -> 0 | R46: =SUMIF(Data!$A:$A,Summary!E46,Data!$M:$M) -> 0 | S46: =SUMIF(Data!$A:$A,Summary!F46,Data!$M:$M) -> 0 | T46: =SUMIF(Data!$A:$A,Summary!G46,Data!$M:$M) -> 0 | U46: =SUMIF(Data!$A:$A,Summary!H46,Data!$M:$M) -> 0 | ... X46: =SUMIF(Data!$A:$A,Summary!K46,Data!$M:$M) -> 0
... A164: =$L164&N$1&$M164 -> AugustFebruaryTaiwan - DCL KY | B164: =$L164&O$1&$M164 -> AugustMarchTaiwan - DCL KY | C164: =$L164&P$1&$M164 -> AugustAprilTaiwan - DCL KY | D164: =$L164&Q$1&$M164 -> AugustMayTaiwan - DCL KY | E164: =$L164&R$1&$M164 -> AugustJuneTaiwan - DCL KY | F164: =$L164&S$1&$M164 -> AugustJulyTaiwan - DCL KY | G164: =$L164&T$1&$M164 -> AugustAugustTaiwan - DCL KY | H164: =$L164&U$1&$M164 -> AugustSeptemberTaiwan - DCL KY | ... K164: =$L164&X$1&$M164 -> AugustDecemberTaiwan - DCL KY | L164: August | M164: Taiwan - DCL KY | N164: =SUMIF(Data!$A:$A,Summary!A164,Data!$M:$M) -> 0 | O164: =SUMIF(Data!$A:$A,Summary!B164,Data!$M:$M) -> 0 | P164: =SUMIF(Data!$A:$A,Summary!C164,Data!$M:$M) -> 0 | Q164: =SUMIF(Data!$A:$A,Summary!D164,Data!$M:$M) -> 0 | R164: =SUMIF(Data!$A:$A,Summary!E164,Data!$M:$M) -> 0 | S164: =SUMIF(Data!$A:$A,Summary!F164,Data!$M:$M) -> 0 | T164: =SUMIF(Data!$A:$A,Summary!G164,Data!$M:$M) -> 0 | U164: =SUMIF(Data!$A:$A,Summary!H164,Data!$M:$M) -> 0 | ... X164: =SUMIF(Data!$A:$A,Summary!K164,Data!$M:$M) -> 0

Sheet Data
A1: Code | B1: Type | C1: Module | D1: Batch Number | E1: Tran. Date | F1: Period | G1: Description | H1: Ref. Number | I1: Account | J1: Subaccount | K1: Debit Amount | L1: Credit Amount | M1: Net Activity | N1: Reclass. Batch | O1: Freight Full Comments | P1: Freight Code | Q1: Invoice | R1: Ship Month | S1: Rec Month | T1: Invoiced | U1: Month
A2: =U2&W2&P2 -> MarchMarchGreensboro NC - Phillips WI | B2: Freight Inbound | C2: AP | D2: 3395916 | E2: 43164 | F2: 06-2018 | G2: Shipping and Handling | H2: 1011158 | I2: 515000 | J2: HCORP-CRP-4600-JUL | K2: 1700 | L2: 0 | M2: 1700 | O2: Shipping and Handling | P2: Greensboro NC - Phillips WI | Q2: 0001445 | R2: 43160 | S2: 43160 | T2: 3 | U2: =IF(T2=6,"June",IF(T2=5,"May",IF(T2=4,"April",IF(T2=3,"March",0)))) -> March | V2: =MONTH(S2) -> 3 | W2: =IF(V2=6,"June",IF(V2=5,"May",IF(V2=4,"April",IF(V2=3,"March",IF(V2=7,"July",IF(V2=2,"February",0)))))) -> March
A3: =U3&W3&P3 -> MarchMarchGreensboro NC - Phillips WI | B3: Freight Inbound | C3: AP | D3: 3386028 | E3: 43186 | F3: 06-2018 | G3: Freight Charges | H3: 1010838 | I3: 515000 | J3: HCORP-CRP-4600-JUL | K3: 1422.8 | L3: 0 | M3: 1422.8 | O3: Shipping and Handling | P3: Greensboro NC - Phillips WI | Q3: 0001512 | R3: 43160 | S3: 43160 | T3: 3 | U3: =IF(T3=6,"June",IF(T3=5,"May",IF(T3=4,"April",IF(T3=3,"March",0)))) -> March | V3: =MONTH(S3) -> 3 | W3: =IF(V3=6,"June",IF(V3=5,"May",IF(V3=4,"April",IF(V3=3,"March",IF(V3=7,"July",IF(V3=2,"February",0)))))) -> March
A4: =U4&W4&P4 -> MarchFebruaryHong Kong - AFG NC | B4: Freight Inbound | C4: AP | D4: 3353216 | E4: 43160 | F4: 05-2018 | G4: Freight Inbound | H4: 1006462 | I4: 515000 | J4: HCORP-CRP-4600-JUL | K4: 72 | L4: 0 | M4: 72 | O4: Freight Inbound | P4: Hong Kong - AFG NC | Q4: W2B18DN0100 | R4: 43132 | S4: 43132 | T4: 3 | U4: =IF(T4=6,"June",IF(T4=5,"May",IF(T4=4,"April",IF(T4=3,"March",0)))) -> March | V4: =MONTH(S4) -> 2 | W4: =IF(V4=6,"June",IF(V4=5,"May",IF(V4=4,"April",IF(V4=3,"March",IF(V4=7,"July",IF(V4=2,"February",0)))))) -> February
A5: =U5&W5&P5 -> MarchMarchHong Kong - DCL KY | B5: Freight Inbound | C5: AP | D5: 3346582 | E5: 43161 | F5: 05-2018 | G5: Pallet Charges | H5: 1009610 | I5: 515000 | J5: HCORP-CRP-4600-JUL | K5: 48 | L5: 0 | M5: 48 | O5: Pallet Charges | P5: Hong Kong - DCL KY | Q5: W2C18DN0019 | R5: 43160 | S5: 43160 | T5: 3 | U5: =IF(T5=6,"June",IF(T5=5,"May",IF(T5=4,"April",IF(T5=3,"March",0)))) -> March | V5: =MONTH(S5) -> 3 | W5: =IF(V5=6,"June",IF(V5=5,"May",IF(V5=4,"April",IF(V5=3,"March",IF(V5=7,"July",IF(V5=2,"February",0)))))) -> March
A6: =U6&W6&P6 -> MarchMarchHong Kong - DCL KY | B6: Freight Inbound | C6: AP | D6: 3342417 | E6: 43168 | F6: 05-2018 | G6: Freight Charge | H6: 1009360 | I6: 515000 | J6: HCORP-CRP-4600-JUL | K6: 741.66 | L6: 0 | M6: 741.66 | O6: Freight Charge | P6: Hong Kong - DCL KY | R6: 43160 | S6: 43160 | T6: 3 | U6: =IF(T6=6,"June",IF(T6=5,"May",IF(T6=4,"April",IF(T6=3,"March",0)))) -> March | V6: =MONTH(S6) -> 3 | W6: =IF(V6=6,"June",IF(V6=5,"May",IF(V6=4,"April",IF(V6=3,"March",IF(V6=7,"July",IF(V6=2,"February",0)))))) -> March
A7: =U7&W7&P7 -> MarchMarchHong Kong - DCL KY | B7: Freight Inbound | C7: AP | D7: 3346584 | E7: 43168 | F7: 05-2018 | G7: Pallet Charges | H7: 1009614 | I7: 515000 | J7: HCORP-CRP-4600-JUL | K7: 24 | L7: 0 | M7: 24 | O7: Pallet Charges | P7: Hong Kong - DCL KY | R7: 43160 | S7: 43160 | T7: 3 | U7: =IF(T7=6,"June",IF(T7=5,"May",IF(T7=4,"April",IF(T7=3,"March",0)))) -> March | V7: =MONTH(S7) -> 3 | W7: =IF(V7=6,"June",IF(V7=5,"May",IF(V7=4,"April",IF(V7=3,"March",IF(V7=7,"July",IF(V7=2,"February",0)))))) -> March
A8: =U8&W8&P8 -> MarchMarchAFG NC - DCL KY | B8: Freight Inbound | C8: AP | D8: 3346472 | E8: 43185 | F8: 05-2018 | G8: Freight Inbound-Rec 03/21/18 Morrisville,NC to Louisville,KY | H8: 1009618 | I8: 515000 | J8: NAUSA-CRP-4600-JUL | K8: 1725 | L8: 0 | M8: 1725 | O8: Freight Inbound-Rec 03/21/18 Morrisville,NC to Louisville,KY | P8: AFG NC - DCL KY | R8: 43160 | S8: 43160 | T8: 3 | U8: =IF(T8=6,"June",IF(T8=5,"May",IF(T8=4,"April",IF(T8=3,"March",0)))) -> March | V8: =MONTH(S8) -> 3 | W8: =IF(V8=6,"June",IF(V8=5,"May",IF(V8=4,"April",IF(V8=3,"March",IF(V8=7,"July",IF(V8=2,"February",0)))))) -> March
A9: =U9&W9&P9 -> MarchMarchHong Kong - DECI NC | B9: Freight Inbound | C9: GL | D9: 3274637 | E9: 43189 | F9: 05-2018 | G9: Freight Inbound Delivered 03/29/18 Hong Kong - Durham, NC | H9: 1007676 | I9: 223100 | J9: HCORP-CRP-4600-JUL | K9: 11426.21 | L9: 0 | M9: 11426.21 | O9: Freight Inbound Delivered 03/29/18 Hong Kong - Durham, NC | P9: Hong Kong - DECI NC | Q9: FLEX-232032-1 | R9: 43160 | S9: 43160 | T9: 3 | U9: =IF(T9=6,"June",IF(T9=5,"May",IF(T9=4,"April",IF(T9=3,"March",0)))) -> March | V9: =MONTH(S9) -> 3 | W9: =IF(V9=6,"June",IF(V9=5,"May",IF(V9=4,"April",IF(V9=3,"March",IF(V9=7,"July",IF(V9=2,"February",0)))))) -> March
A10: =U10&W10&P10 -> MarchMarchHong Kong - DECI NC | B10: Freight Inbound | C10: GL | D10: 3274639 | E10: 43189 | F10: 05-2018 | G10: Freight Inbound Delivered 03/29/18 Hong Kong - Durham, NC | H10: 1007677 | I10: 223100 | J10: HCORP-CRP-4600-JUL | K10: 13267.81 | L10: 0 | M10: 13267.81 | O10: Freight Inbound Delivered 03/29/18 Hong Kong - Durham, NC | P10: Hong Kong - DECI NC | R10: 43160 | S10: 43160 | T10: 3 | U10: =IF(T10=6,"June",IF(T10=5,"May",IF(T10=4,"April",IF(T10=3,"March",0)))) -> March | V10: =MONTH(S10) -> 3 | W10: =IF(V10=6,"June",IF(V10=5,"May",IF(V10=4,"April",IF(V10=3,"March",IF(V10=7,"July",IF(V10=2,"February",0)))))) -> March
A11: =U11&W11&P11 -> MarchMarchHong Kong - DECI NC | B11: Freight Inbound | C11: GL | D11: 3274641 | E11: 43189 | F11: 05-2018 | G11: Freight Inbound Delivered 03/30/18 Hong Kong - Durham, NC | H11: 1007678 | I11: 223100 | J11: HCORP-CRP-4600-JUL | K11: 8290.41 | L11: 0 | M11: 8290.41 | O11: Freight Inbound Delivered 03/30/18 Hong Kong - Durham, NC | P11: Hong Kong - DECI NC | R11: 43160 | S11: 43160 | T11: 3 | U11: =IF(T11=6,"June",IF(T11=5,"May",IF(T11=4,"April",IF(T11=3,"March",0)))) -> March | V11: =MONTH(S11) -> 3 | W11: =IF(V11=6,"June",IF(V11=5,"May",IF(V11=4,"April",IF(V11=3,"March",IF(V11=7,"July",IF(V11=2,"February",0)))))) -> March
A12: =U12&W12&P12 -> MarchMarchChina - DCL KY | B12: Freight Inbound | C12: GL | D12: 3274643 | E12: 43189 | F12: 05-2018 | G12: Freight Inbound Delivered 03/28/18 China-Louisville,KY | H12: 1007679 | I12: 223100 | J12: HCORP-CRP-4600-JUL | K12: 30091.58 | L12: 0 | M12: 30091.58 | O12: Freight Inbound Delivered 03/28/18 China-Louisville,KY | P12: China - DCL KY | R12: 43160 | S12: 43160 | T12: 3 | U12: =IF(T12=6,"June",IF(T12=5,"May",IF(T12=4,"April",IF(T12=3,"March",0)))) -> March | V12: =MONTH(S12) -> 3 | W12: =IF(V12=6,"June",IF(V12=5,"May",IF(V12=4,"April",IF(V12=3,"March",IF(V12=7,"July",IF(V12=2,"February",0)))))) -> March
A13: =U13&W13&P13 -> MarchMarchHong Kong - DECI NC | B13: Freight Inbound | C13: GL | D13: 3274645 | E13: 43189 | F13: 05-2018 | G13: Freight Inbound Delivered 03/29/18 Hong Kong - Durham, NC | H13: 1007681 | I13: 223100 | J13: HCORP-CRP-4600-JUL | K13: 9881.8 | L13: 0 | M13: 9881.8 | O13: Freight Inbound Delivered 03/29/18 Hong Kong - Durham, NC | P13: Hong Kong - DECI NC | R13: 43160 | S13: 43160 | T13: 3 | U13: =IF(T13=6,"June",IF(T13=5,"May",IF(T13=4,"April",IF(T13=3,"March",0)))) -> March | V13: =MONTH(S13) -> 3 | W13: =IF(V13=6,"June",IF(V13=5,"May",IF(V13=4,"April",IF(V13=3,"March",IF(V13=7,"July",IF(V13=2,"February",0)))))) -> March
A14: =U14&W14&P14 -> MarchMarchHong Kong - DCL KY | B14: Freight Inbound | C14: GL | D14: 3274662 | E14: 43189 | F14: 05-2018 | G14: Freight Inbound Delivered 03/28/18 Hong Kong-Louisville,KY | H14: 1007695 | I14: 223100 | J14: HCORP-CRP-4600-JUL | K14: 12626.39 | L14: 0 | M14: 12626.39 | O14: Freight Inbound Delivered 03/28/18 Hong Kong-Louisville,KY | P14: Hong Kong - DCL KY | R14: 43160 | S14: 43160 | T14: 3 | U14: =IF(T14=6,"June",IF(T14=5,"May",IF(T14=4,"April",IF(T14=3,"March",0)))) -> March | V14: =MONTH(S14) -> 3 | W14: =IF(V14=6,"June",IF(V14=5,"May",IF(V14=4,"April",IF(V14=3,"March",IF(V14=7,"July",IF(V14=2,"February",0)))))) -> March
A15: =U15&W15&P15 -> MarchMarchHong Kong - DCL KY | B15: Freight Inbound | C15: GL | D15: 3274664 | E15: 43189 | F15: 05-2018 | G15: Freight Inbound Delivered 03/26/18 Hong Kong-Louisville,KY | H15: 1007697 | I15: 223100 | J15: HCORP-CRP-4600-JUL | K15: 20178.6 | L15: 0 | M15: 20178.6 | O15: Freight Inbound Delivered 03/26/18 Hong Kong-Louisville,KY | P15: Hong Kong - DCL KY | R15: 43160 | S15: 43160 | T15: 3 | U15: =IF(T15=6,"June",IF(T15=5,"May",IF(T15=4,"April",IF(T15=3,"March",0)))) -> March | V15: =MONTH(S15) -> 3 | W15: =IF(V15=6,"June",IF(V15=5,"May",IF(V15=4,"April",IF(V15=3,"March",IF(V15=7,"July",IF(V15=2,"February",0)))))) -> March
A16: =U16&W16&P16 -> MarchMarchChina - DCL KY | B16: Freight Inbound | C16: GL | D16: 3274666 | E16: 43189 | F16: 05-2018 | G16: Freight Inbound Delivered 03/26/18 China-Louisville,KY | H16: 1007698 | I16: 223100 | J16: HCORP-CRP-4600-JUL | K16: 566.25 | L16: 0 | M16: 566.25 | O16: Freight Inbound Delivered 03/26/18 China-Louisville,KY | P16: China - DCL KY | R16: 43160 | S16: 43160 | T16: 3 | U16: =IF(T16=6,"June",IF(T16=5,"May",IF(T16=4,"April",IF(T16=3,"March",0)))) -> March | V16: =MONTH(S16) -> 3 | W16: =IF(V16=6,"June",IF(V16=5,"May",IF(V16=4,"April",IF(V16=3,"March",IF(V16=7,"July",IF(V16=2,"February",0)))))) -> March
A17: =U17&W17&P17 -> MarchMarchHong Kong - DCL KY | B17: Freight Inbound | C17: GL | D17: 3274668 | E17: 43189 | F17: 05-2018 | G17: Freight Inbound Delivered 03/28/18 Hong Kong-Louisville,KY | H17: 1007699 | I17: 223100 | J17: HCORP-CRP-4600-JUL | K17: 22131.76 | L17: 0 | M17: 22131.76 | O17: Freight Inbound Delivered 03/28/18 Hong Kong-Louisville,KY | P17: Hong Kong - DCL KY | R17: 43160 | S17: 43160 | T17: 3 | U17: =IF(T17=6,"June",IF(T17=5,"May",IF(T17=4,"April",IF(T17=3,"March",0)))) -> March | V17: =MONTH(S17) -> 3 | W17: =IF(V17=6,"June",IF(V17=5,"May",IF(V17=4,"April",IF(V17=3,"March",IF(V17=7,"July",IF(V17=2,"February",0)))))) -> March
A18: =U18&W18&P18 -> MarchMarchChina - DCL KY | B18: Freight Inbound | C18: GL | D18: 3274670 | E18: 43189 | F18: 05-2018 | G18: Freight Inbound Delivered 03/26/18 China-Louisville,KY | H18: 1007700 | I18: 223100 | J18: HCORP-CRP-4600-JUL | K18: 29986.6 | L18: 0 | M18: 29986.6 | O18: Freight Inbound Delivered 03/26/18 China-Louisville,KY | P18: China - DCL KY | R18: 43160 | S18: 43160 | T18: 3 | U18: =IF(T18=6,"June",IF(T18=5,"May",IF(T18=4,"April",IF(T18=3,"March",0)))) -> March | V18: =MONTH(S18) -> 3 | W18: =IF(V18=6,"June",IF(V18=5,"May",IF(V18=4,"April",IF(V18=3,"March",IF(V18=7,"July",IF(V18=2,"February",0)))))) -> March
A19: =U19&W19&P19 -> MarchMarchChina - DCL KY | B19: Freight Inbound | C19: GL | D19: 3274672 | E19: 43189 | F19: 05-2018 | G19: Freight Inbound Delivered 03/28/18 China-Louisville,KY | H19: 1007701 | I19: 223100 | J19: HCORP-CRP-4600-JUL | K19: 570.3 | L19: 0 | M19: 570.3 | O19: Freight Inbound Delivered 03/28/18 China-Louisville,KY | P19: China - DCL KY | R19: 43160 | S19: 43160 | T19: 3 | U19: =IF(T19=6,"June",IF(T19=5,"May",IF(T19=4,"April",IF(T19=3,"March",0)))) -> March | V19: =MONTH(S19) -> 3 | W19: =IF(V19=6,"June",IF(V19=5,"May",IF(V19=4,"April",IF(V19=3,"March",IF(V19=7,"July",IF(V19=2,"February",0)))))) -> March
A20: =U20&W20&P20 -> MarchMarchHong Kong - DECI NC | B20: Freight Inbound | C20: GL | D20: 3274678 | E20: 43189 | F20: 05-2018 | G20: Freight Inbound Delivered 03/26/18 Hong Kong - Durham, NC | H20: 1007705 | I20: 223100 | J20: HCORP-CRP-4600-JUL | K20: 5275.15 | L20: 0 | M20: 5275.15 | O20: Freight Inbound Delivered 03/26/18 Hong Kong - Durham, NC | P20: Hong Kong - DECI NC | R20: 43160 | S20: 43160 | T20: 3 | U20: =IF(T20=6,"June",IF(T20=5,"May",IF(T20=4,"April",IF(T20=3,"March",0)))) -> March | V20: =MONTH(S20) -> 3 | W20: =IF(V20=6,"June",IF(V20=5,"May",IF(V20=4,"April",IF(V20=3,"March",IF(V20=7,"July",IF(V20=2,"February",0)))))) -> March
A21: =U21&W21&P21 -> MarchMarchHong Kong - DECI NC | B21: Freight Inbound | C21: GL | D21: 3274681 | E21: 43189 | F21: 05-2018 | G21: Freight Inbound Delivered 03/30/18 Hong Kong - Durham, NC | H21: 1007710 | I21: 223100 | J21: HCORP-CRP-4600-JUL | K21: 10771.91 | L21: 0 | M21: 10771.91 | O21: Freight Inbound Delivered 03/30/18 Hong Kong - Durham, NC | P21: Hong Kong - DECI NC | R21: 43160 | S21: 43160 | T21: 3 | U21: =IF(T21=6,"June",IF(T21=5,"May",IF(T21=4,"April",IF(T21=3,"March",0)))) -> March | V21: =MONTH(S21) -> 3 | W21: =IF(V21=6,"June",IF(V21=5,"May",IF(V21=4,"April",IF(V21=3,"March",IF(V21=7,"July",IF(V21=2,"February",0)))))) -> March
A22: =U22&W22&P22 -> MarchMarchChina - DCL KY | B22: Freight Inbound | C22: GL | D22: 3274683 | E22: 43189 | F22: 05-2018 | G22: Freight Inbound Delivered 03/23/18 China-Louisville,KY | H22: 1007711 | I22: 223100 | J22: HCORP-CRP-4600-JUL | K22: 849.45 | L22: 0 | M22: 849.45 | O22: Freight Inbound Delivered 03/23/18 China-Louisville,KY | P22: China - DCL KY | R22: 43160 | S22: 43160 | T22: 3 | U22: =IF(T22=6,"June",IF(T22=5,"May",IF(T22=4,"April",IF(T22=3,"March",0)))) -> March | V22: =MONTH(S22) -> 3 | W22: =IF(V22=6,"June",IF(V22=5,"May",IF(V22=4,"April",IF(V22=3,"March",IF(V22=7,"July",IF(V22=2,"February",0)))))) -> March
A23: =U23&W23&P23 -> AprilAprilHong Kong - DECI NC | B23: Freight Inbound | C23: AP | D23: 3368458 | E23: 43194 | F23: 06-2018 | G23: Pallet Charges | H23: 1010008 | I23: 515000 | J23: HCORP-CRP-4600-JUL | K23: 30 | L23: 0 | M23: 30 | O23: Pallet Charges | P23: Hong Kong - DECI NC | Q23: W2D18DN0011 | R23: 43191 | S23: 43191 | T23: 4 | U23: =IF(T23=6,"June",IF(T23=5,"May",IF(T23=4,"April",IF(T23=3,"March",0)))) -> April | V23: =MONTH(S23) -> 4 | W23: =IF(V23=6,"June",IF(V23=5,"May",IF(V23=4,"April",IF(V23=3,"March",IF(V23=7,"July",IF(V23=2,"February",0)))))) -> April
A24: =U24&W24&P24 -> AprilAprilHong Kong - DCL KY | B24: Freight Inbound | C24: AP | D24: 3358408 | E24: 43196 | F24: 06-2018 | G24: Freight Inbound | H24: 1010011 | I24: 515000 | J24: HCORP-CRP-4600-JUL | K24: 132 | L24: 0 | M24: 132 | O24: Pallet Charges | P24: Hong Kong - DCL KY | Q24: W2D18DN0022 | R24: 43191 | S24: 43191 | T24: 4 | U24: =IF(T24=6,"June",IF(T24=5,"May",IF(T24=4,"April",IF(T24=3,"March",0)))) -> April | V24: =MONTH(S24) -> 4 | W24: =IF(V24=6,"June",IF(V24=5,"May",IF(V24=4,"April",IF(V24=3,"March",IF(V24=7,"July",IF(V24=2,"February",0)))))) -> April
A25: =U25&W25&P25 -> AprilAprilHong Kong - DCL KY | B25: Freight Inbound | C25: AP | D25: 3372874 | E25: 43196 | F25: 06-2018 | G25: Pallet Charges | H25: 1010305 | I25: 515000 | J25: HCORP-CRP-4600-JUL | K25: 48 | L25: 0 | M25: 48 | O25: Pallet Charges | P25: Hong Kong - DCL KY | Q25: A2D18DN0004 | R25: 43191 | S25: 43191 | T25: 4 | U25: =IF(T25=6,"June",IF(T25=5,"May",IF(T25=4,"April",IF(T25=3,"March",0)))) -> April | V25: =MONTH(S25) -> 4 | W25: =IF(V25=6,"June",IF(V25=5,"May",IF(V25=4,"April",IF(V25=3,"March",IF(V25=7,"July",IF(V25=2,"February",0)))))) -> April
A26: =U26&W26&P26 -> AprilAprilAFG NC - DCL KY | B26: Freight Inbound | C26: AP | D26: 3371286 | E26: 43199 | F26: 06-2018 | G26: Freight Inbound-Rec 04/06/18 Morrisville,NC to Louisville,KY | H26: 1008448 | I26: 515000 | J26: NAUSA-CRP-4600-JUL | K26: 1675 | L26: 0 | M26: 1675 | O26: Freight Inbound-Rec 04/06/18 Morrisville,NC to Louisville,KY | P26: AFG NC - DCL KY | Q26: S01178205 | R26: 43191 | S26: 43191 | T26: 4 | U26: =IF(T26=6,"June",IF(T26=5,"May",IF(T26=4,"April",IF(T26=3,"March",0)))) -> April | V26: =MONTH(S26) -> 4 | W26: =IF(V26=6,"June",IF(V26=5,"May",IF(V26=4,"April",IF(V26=3,"March",IF(V26=7,"July",IF(V26=2,"February",0)))))) -> April
A27: =U27&W27&P27 -> AprilAprilDECI NC - DCL KY | B27: Freight Inbound | C27: AP | D27: 3386039 | E27: 43202 | F27: 06-2018 | G27: Freight Inbound - Rec 04/19/18 Durham, NC to Louisville, KY | H27: 1010612 | I27: 515000 | J27: NAUSA-CRP-4600-JUL | K27: 1450 | L27: 0 | M27: 1450 | O27: Freight Inbound - Rec 04/19/18 Durham, NC to Louisville, KY | P27: DECI NC - DCL KY | Q27: S01181251 | R27: 43191 | S27: 43191 | T27: 4 | U27: =IF(T27=6,"June",IF(T27=5,"May",IF(T27=4,"April",IF(T27=3,"March",0)))) -> April | V27: =MONTH(S27) -> 4 | W27: =IF(V27=6,"June",IF(V27=5,"May",IF(V27=4,"April",IF(V27=3,"March",IF(V27=7,"July",IF(V27=2,"February",0)))))) -> April
A28: =U28&W28&P28 -> AprilAprilHong Kong - DECI NC | B28: Freight Inbound | C28: AP | D28: 3368437 | E28: 43204 | F28: 06-2018 | G28: Pallet Charges | H28: 1010274 | I28: 515000 | J28: HCORP-CRP-4600-JUL | K28: 45 | L28: 0 | M28: 45 | O28: Pallet Charges | P28: Hong Kong - DECI NC | Q28: W2D18DN0037 | R28: 43191 | S28: 43191 | T28: 4 | U28: =IF(T28=6,"June",IF(T28=5,"May",IF(T28=4,"April",IF(T28=3,"March",0)))) -> April | V28: =MONTH(S28) -> 4 | W28: =IF(V28=6,"June",IF(V28=5,"May",IF(V28=4,"April",IF(V28=3,"March",IF(V28=7,"July",IF(V28=2,"February",0)))))) -> April
A29: =U29&W29&P29 -> AprilAprilAFG NC - DCL KY | B29: Freight Inbound | C29: AP | D29: 3346451 | E29: 43214 | F29: 05-2018 | G29: Freight Inbound ETA 04/24/18 ASTEELFLASH NC to Louisville KY | H29: 1009535 | I29: 515000 | J29: NAUSA-CRP-4600-JUL | K29: 3100 | L29: 0 | M29: 3100 | O29: Freight Inbound ETA 04/24/18 ASTEELFLASH NC to Louisville KY | P29: AFG NC - DCL KY | R29: 43191 | S29: 43191 | T29: 4 | U29: =IF(T29=6,"June",IF(T29=5,"May",IF(T29=4,"April",IF(T29=3,"March",0)))) -> April | V29: =MONTH(S29) -> 4 | W29: =IF(V29=6,"June",IF(V29=5,"May",IF(V29=4,"April",IF(V29=3,"March",IF(V29=7,"July",IF(V29=2,"February",0)))))) -> April
A30: =U30&W30&P30 -> AprilAprilAFG NC - DCL KY | B30: Freight Inbound | C30: AP | D30: 3346442 | E30: 43216 | F30: 05-2018 | G30: Freight Inbound ETA 04/26/18 ASTEELFLASH NC to Louisville KY | H30: 1009484 | I30: 515000 | J30: NAUSA-CRP-4600-JUL | K30: 4650 | L30: 0 | M30: 4650 | O30: Freight Inbound ETA 04/26/18 ASTEELFLASH NC to Louisville KY | P30: AFG NC - DCL KY | R30: 43191 | S30: 43191 | T30: 4 | U30: =IF(T30=6,"June",IF(T30=5,"May",IF(T30=4,"April",IF(T30=3,"March",0)))) -> April | V30: =MONTH(S30) -> 4 | W30: =IF(V30=6,"June",IF(V30=5,"May",IF(V30=4,"April",IF(V30=3,"March",IF(V30=7,"July",IF(V30=2,"February",0)))))) -> April
A31: =U31&W31&P31 -> AprilAprilAFG NC - DCL KY | B31: Freight Inbound | C31: AP | D31: 3346446 | E31: 43216 | F31: 05-2018 | G31: Freight Inbound ETA 04/26/18 ASTEELFLASH NC to Louisville KY | H31: 1009526 | I31: 515000 | J31: NAUSA-CRP-4600-JUL | K31: 4650 | L31: 0 | M31: 4650 | O31: Freight Inbound ETA 04/26/18 ASTEELFLASH NC to Louisville KY | P31: AFG NC - DCL KY | R31: 43191 | S31: 43191 | T31: 4 | U31: =IF(T31=6,"June",IF(T31=5,"May",IF(T31=4,"April",IF(T31=3,"March",0)))) -> April | V31: =MONTH(S31) -> 4 | W31: =IF(V31=6,"June",IF(V31=5,"May",IF(V31=4,"April",IF(V31=3,"March",IF(V31=7,"July",IF(V31=2,"February",0)))))) -> April
A32: =U32&W32&P32 -> AprilAprilAFG NC - DCL KY | B32: Freight Inbound | C32: AP | D32: 3346471 | E32: 43216 | F32: 05-2018 | G32: Freight Inbound-Rec 04/19/18 Morrisville,NC to Louisville,KY | H32: 1009616 | I32: 515000 | J32: NAUSA-CRP-4600-JUL | K32: 1675 | L32: 0 | M32: 1675 | O32: Freight Inbound-Rec 04/19/18 Morrisville,NC to Louisville,KY | P32: AFG NC - DCL KY | R32: 43191 | S32: 43191 | T32: 4 | U32: =IF(T32=6,"June",IF(T32=5,"May",IF(T32=4,"April",IF(T32=3,"March",0)))) -> April | V32: =MONTH(S32) -> 4 | W32: =IF(V32=6,"June",IF(V32=5,"May",IF(V32=4,"April",IF(V32=3,"March",IF(V32=7,"July",IF(V32=2,"February",0)))))) -> April
A33: =U33&W33&P33 -> AprilAprilAFG NC - DCL KY | B33: Freight Inbound | C33: AP | D33: 3346467 | E33: 43217 | F33: 05-2018 | G33: Freight Inbound-Rec 04/24/18 Morrisville,NC to Louisville,KY | H33: 1009605 | I33: 515000 | J33: NAUSA-CRP-4600-JUL | K33: 1675 | L33: 0 | M33: 1675 | O33: Freight Inbound-Rec 04/24/18 Morrisville,NC to Louisville,KY | P33: AFG NC - DCL KY | R33: 43191 | S33: 43191 | T33: 4 | U33: =IF(T33=6,"June",IF(T33=5,"May",IF(T33=4,"April",IF(T33=3,"March",0)))) -> April | V33: =MONTH(S33) -> 4 | W33: =IF(V33=6,"June",IF(V33=5,"May",IF(V33=4,"April",IF(V33=3,"March",IF(V33=7,"July",IF(V33=2,"February",0)))))) -> April
A34: =U34&W34&P34 -> AprilAprilAFG NC - DCL KY | B34: Freight Inbound | C34: AP | D34: 3346468 | E34: 43217 | F34: 05-2018 | G34: Freight Inbound-Rec 04/22/18 Morrisville,NC to Louisville,KY | H34: 1009606 | I34: 515000 | J34: NAUSA-CRP-4600-JUL | K34: 1675 | L34: 0 | M34: 1675 | O34: Freight Inbound-Rec 04/22/18 Morrisville,NC to Louisville,KY | P34: AFG NC - DCL KY | R34: 43191 | S34: 43191 | T34: 4 | U34: =IF(T34=6,"June",IF(T34=5,"May",IF(T34=4,"April",IF(T34=3,"March",0)))) -> April | V34: =MONTH(S34) -> 4 | W34: =IF(V34=6,"June",IF(V34=5,"May",IF(V34=4,"April",IF(V34=3,"March",IF(V34=7,"July",IF(V34=2,"February",0)))))) -> April
A35: =U35&W35&P35 -> AprilAprilAFG NC - DCL KY | B35: Freight Inbound | C35: AP | D35: 3346469 | E35: 43217 | F35: 05-2018 | G35: Freight Inbound-Rec 04/21/18 Morrisville,NC to Louisville,KY | H35: 1009609 | I35: 515000 | J35: NAUSA-CRP-4600-JUL | K35: 1675 | L35: 0 | M35: 1675 | O35: Freight Inbound-Rec 04/21/18 Morrisville,NC to Louisville,KY | P35: AFG NC - DCL KY | R35: 43191 | S35: 43191 | T35: 4 | U35: =IF(T35=6,"June",IF(T35=5,"May",IF(T35=4,"April",IF(T35=3,"March",0)))) -> April | V35: =MONTH(S35) -> 4 | W35: =IF(V35=6,"June",IF(V35=5,"May",IF(V35=4,"April",IF(V35=3,"March",IF(V35=7,"July",IF(V35=2,"February",0)))))) -> April
A36: =U36&W36&P36 -> AprilAprilAFG NC - DCL KY | B36: Freight Inbound | C36: AP | D36: 3346470 | E36: 43217 | F36: 05-2018 | G36: Freight Inbound-Rec 04/17/18 Morrisville,NC to Louisville,KY | H36: 1009611 | I36: 515000 | J36: NAUSA-CRP-4600-JUL | K36: 1675 | L36: 0 | M36: 1675 | O36: Freight Inbound-Rec 04/17/18 Morrisville,NC to Louisville,KY | P36: AFG NC - DCL KY | R36: 43191 | S36: 43191 | T36: 4 | U36: =IF(T36=6,"June",IF(T36=5,"May",IF(T36=4,"April",IF(T36=3,"March",0)))) -> April | V36: =MONTH(S36) -> 4 | W36: =IF(V36=6,"June",IF(V36=5,"May",IF(V36=4,"April",IF(V36=3,"March",IF(V36=7,"July",IF(V36=2,"February",0)))))) -> April
A37: =U37&W37&P37 -> AprilAprilAFG NC - DCL KY | B37: Freight Inbound | C37: AP | D37: 3346438 | E37: 43220 | F37: 05-2018 | G37: Freight Inbound ETA 04/29/18 ASTEELFLASH NC to Louisville KY | H37: 1009477 | I37: 515000 | J37: NAUSA-CRP-4600-JUL | K37: 3100 | L37: 0 | M37: 3100 | O37: Freight Inbound ETA 04/29/18 ASTEELFLASH NC to Louisville KY | P37: AFG NC - DCL KY | R37: 43191 | S37: 43191 | T37: 4 | U37: =IF(T37=6,"June",IF(T37=5,"May",IF(T37=4,"April",IF(T37=3,"March",0)))) -> April | V37: =MONTH(S37) -> 4 | W37: =IF(V37=6,"June",IF(V37=5,"May",IF(V37=4,"April",IF(V37=3,"March",IF(V37=7,"July",IF(V37=2,"February",0)))))) -> April
A38: =U38&W38&P38 -> AprilAprilAFG NC - DCL KY | B38: Freight Inbound | C38: AP | D38: 3346441 | E38: 43220 | F38: 05-2018 | G38: Freight Inbound ETA 05/02/18 ASTEELFLASH NC to Louisville KY | H38: 1009482 | I38: 515000 | J38: NAUSA-CRP-4600-JUL | K38: 3100 | L38: 0 | M38: 3100 | O38: Freight Inbound ETA 05/02/18 ASTEELFLASH NC to Louisville KY | P38: AFG NC - DCL KY | R38: 43191 | S38: 43191 | T38: 4 | U38: =IF(T38=6,"June",IF(T38=5,"May",IF(T38=4,"April",IF(T38=3,"March",0)))) -> April | V38: =MONTH(S38) -> 4 | W38: =IF(V38=6,"June",IF(V38=5,"May",IF(V38=4,"April",IF(V38=3,"March",IF(V38=7,"July",IF(V38=2,"February",0)))))) -> April
A39: =U39&W39&P39 -> AprilAprilAFG NC - DCL KY | B39: Freight Inbound | C39: AP | D39: 3346450 | E39: 43220 | F39: 05-2018 | G39: Freight Inbound ETA 04/27/18 ASTEELFLASH NC to Louisville KY | H39: 1009534 | I39: 515000 | J39: NAUSA-CRP-4600-JUL | K39: 4650 | L39: 0 | M39: 4650 | O39: Freight Inbound ETA 04/27/18 ASTEELFLASH NC to Louisville KY | P39: AFG NC - DCL KY | R39: 43191 | S39: 43191 | T39: 4 | U39: =IF(T39=6,"June",IF(T39=5,"May",IF(T39=4,"April",IF(T39=3,"March",0)))) -> April | V39: =MONTH(S39) -> 4 | W39: =IF(V39=6,"June",IF(V39=5,"May",IF(V39=4,"April",IF(V39=3,"March",IF(V39=7,"July",IF(V39=2,"February",0)))))) -> April
A40: =U40&W40&P40 -> AprilAprilHong Kong - DCL KY | B40: Freight Inbound | C40: GL | D40: 3312771 | E40: 43195 | F40: 05-2018 | G40: Freight Inbound Delivered 04/03/18 Hong Kong-Louisville,KY | H40: 1008558 | I40: 223100 | J40: HCORP-CRP-4600-JUL | K40: 22773.46 | L40: 0 | M40: 22773.46 | O40: Freight Inbound Delivered 04/03/18 Hong Kong-Louisville,KY | P40: Hong Kong - DCL KY | R40: 43191 | S40: 43191 | T40: 4 | U40: =IF(T40=6,"June",IF(T40=5,"May",IF(T40=4,"April",IF(T40=3,"March",0)))) -> April | V40: =MONTH(S40) -> 4 | W40: =IF(V40=6,"June",IF(V40=5,"May",IF(V40=4,"April",IF(V40=3,"March",IF(V40=7,"July",IF(V40=2,"February",0)))))) -> April
... A82: =U82&W82&P82 -> AprilAprilChina - DECI NC | B82: Freight Inbound | C82: GL | D82: 3346397 | E82: 43217 | F82: 05-2018 | G82: Freight inbound Delivered 04/23/18 China - Durham, NC | H82: 1009527 | I82: 223100 | J82: HCORP-CRP-4600-JUL | K82: 17882.41 | L82: 0 | M82: 17882.41 | O82: Freight inbound Delivered 04/23/18 China - Durham, NC | P82: China - DECI NC | R82: 43191 | S82: 43191 | T82: 4 | U82: =IF(T82=6,"June",IF(T82=5,"May",IF(T82=4,"April",IF(T82=3,"March",0)))) -> April | V82: =MONTH(S82) -> 4 | W82: =IF(V82=6,"June",IF(V82=5,"May",IF(V82=4,"April",IF(V82=3,"March",IF(V82=7,"July",IF(V82=2,"February",0)))))) -> April
A83: =U83&W83&P83 -> AprilAprilChina - DECI NC | B83: Freight Inbound | C83: AP | D83: 3346357 | E83: 43217 | F83: 07-2018 | G83: Freight inbound Delivered 04/23/18 China - Durham, NC | H83: 1009479 | I83: 223100 | J83: HCORP-CRP-4600-JUL | K83: 15458.87 | L83: 0 | M83: 15458.87 | O83: Freight inbound Delivered 04/23/18 China - Durham, NC | P83: China - DECI NC | S83: 43191 | T83: 4 | U83: =IF(T83=6,"June",IF(T83=5,"May",IF(T83=4,"April",IF(T83=3,"March",IF(T83=7,"July",0))))) -> April | V83: =MONTH(S83) -> 4 | W83: =IF(V83=6,"June",IF(V83=5,"May",IF(V83=4,"April",IF(V83=3,"March",IF(V83=7,"July",IF(V83=2,"February",0)))))) -> April
A84: =U84&W84&P84 -> AprilAprilChina - DECI NC | B84: Freight Inbound | C84: AP | D84: 3346397 | E84: 43217 | F84: 07-2018 | G84: Freight inbound Delivered 04/23/18 China - Durham, NC | H84: 1009527 | I84: 223100 | J84: HCORP-CRP-4600-JUL | K84: 17882.41 | L84: 0 | M84: 17882.41 | O84: Freight inbound Delivered 04/23/18 China - Durham, NC | P84: China - DECI NC | S84: 43191 | T84: 4 | U84: =IF(T84=6,"June",IF(T84=5,"May",IF(T84=4,"April",IF(T84=3,"March",IF(T84=7,"July",0))))) -> April | V84: =MONTH(S84) -> 4 | W84: =IF(V84=6,"June",IF(V84=5,"May",IF(V84=4,"April",IF(V84=3,"March",IF(V84=7,"July",IF(V84=2,"February",0)))))) -> April
A85: =U85&W85&P85 -> AprilAprilHong Kong - DECI NC | B85: Freight Inbound | C85: AP | D85: 3346304 | E85: 43216 | F85: 07-2018 | G85: Freight Inbound Delivered 04/18/18 Hong Kong - Durham, NC | H85: 1009346 | I85: 223100 | J85: HCORP-CRP-4600-JUL | K85: 12609.53 | L85: 0 | M85: 12609.53 | O85: Freight Inbound Delivered 04/18/18 Hong Kong - Durham, NC | P85: Hong Kong - DECI NC | S85: 43191 | T85: 4 | U85: =IF(T85=6,"June",IF(T85=5,"May",IF(T85=4,"April",IF(T85=3,"March",IF(T85=7,"July",0))))) -> April | V85: =MONTH(S85) -> 4 | W85: =IF(V85=6,"June",IF(V85=5,"May",IF(V85=4,"April",IF(V85=3,"March",IF(V85=7,"July",IF(V85=2,"February",0)))))) -> April
A86: =U86&W86&P86 -> AprilAprilChina - San Francisco | B86: Freight Inbound | C86: AP | D86: 3346306 | E86: 43216 | F86: 07-2018 | G86: Freight Inbound Delivered 04/18/18 China - San Francisco, CA | H86: 1009349 | I86: 223100 | J86: HCORP-CRP-4600-JUL | K86: 1766.46 | L86: 0 | M86: 1766.46 | O86: Freight Inbound Delivered 04/18/18 China - San Francisco, CA | P86: China - San Francisco | S86: 43191 | T86: 4 | U86: =IF(T86=6,"June",IF(T86=5,"May",IF(T86=4,"April",IF(T86=3,"March",IF(T86=7,"July",0))))) -> April | V86: =MONTH(S86) -> 4 | W86: =IF(V86=6,"June",IF(V86=5,"May",IF(V86=4,"April",IF(V86=3,"March",IF(V86=7,"July",IF(V86=2,"February",0)))))) -> April
A87: =U87&W87&P87 -> AprilAprilChina - DCL KY | B87: Freight Inbound | C87: AP | D87: 3346332 | E87: 43216 | F87: 07-2018 | G87: Freight inbound Delivered 04/23/18 China - Louisville, KY | H87: 1009404 | I87: 223100 | J87: HCORP-CRP-4600-JUL | K87: 40485.04 | L87: 0 | M87: 40485.04 | O87: Freight inbound Delivered 04/23/18 China - Louisville, KY | P87: China - DCL KY | S87: 43191 | T87: 4 | U87: =IF(T87=6,"June",IF(T87=5,"May",IF(T87=4,"April",IF(T87=3,"March",IF(T87=7,"July",0))))) -> April | V87: =MONTH(S87) -> 4 | W87: =IF(V87=6,"June",IF(V87=5,"May",IF(V87=4,"April",IF(V87=3,"March",IF(V87=7,"July",IF(V87=2,"February",0)))))) -> April
A88: =U88&W88&P88 -> AprilAprilChina - DECI NC | B88: Freight Inbound | C88: AP | D88: 3346382 | E88: 43216 | F88: 07-2018 | G88: Freight inbound Delivered 04/23/18 China - Durham, NC | H88: 1009510 | I88: 223100 | J88: HCORP-CRP-4600-JUL | K88: 21807.88 | L88: 0 | M88: 21807.88 | O88: Freight inbound Delivered 04/23/18 China - Durham, NC | P88: China - DECI NC | S88: 43191 | T88: 4 | U88: =IF(T88=6,"June",IF(T88=5,"May",IF(T88=4,"April",IF(T88=3,"March",IF(T88=7,"July",0))))) -> April | V88: =MONTH(S88) -> 4 | W88: =IF(V88=6,"June",IF(V88=5,"May",IF(V88=4,"April",IF(V88=3,"March",IF(V88=7,"July",IF(V88=2,"February",0)))))) -> April
A89: =U89&W89&P89 -> AprilAprilHong Kong - DCL KY | B89: Freight Inbound | C89: AP | D89: 3346303 | E89: 43214 | F89: 07-2018 | G89: Freight Inbound Delivered 04/19/18 Hong Kong-Louisville, KY | H89: 1009345 | I89: 223100 | J89: HCORP-CRP-4600-JUL | K89: 15403.66 | L89: 0 | M89: 15403.66 | O89: Freight Inbound Delivered 04/19/18 Hong Kong-Louisville, KY | P89: Hong Kong - DCL KY | S89: 43191 | T89: 4 | U89: =IF(T89=6,"June",IF(T89=5,"May",IF(T89=4,"April",IF(T89=3,"March",IF(T89=7,"July",0))))) -> April | V89: =MONTH(S89) -> 4 | W89: =IF(V89=6,"June",IF(V89=5,"May",IF(V89=4,"April",IF(V89=3,"March",IF(V89=7,"July",IF(V89=2,"February",0)))))) -> April
A90: =U90&W90&P90 -> AprilAprilChina - DCL KY | B90: Freight Inbound | C90: AP | D90: 3346331 | E90: 43214 | F90: 07-2018 | G90: Freight inbound Delivered 04/19/18 China - Louisville, KY | H90: 1009392 | I90: 223100 | J90: HCORP-CRP-4600-JUL | K90: 18761.95 | L90: 0 | M90: 18761.95 | O90: Freight inbound Delivered 04/19/18 China - Louisville, KY | P90: China - DCL KY | S90: 43191 | T90: 4 | U90: =IF(T90=6,"June",IF(T90=5,"May",IF(T90=4,"April",IF(T90=3,"March",IF(T90=7,"July",0))))) -> April | V90: =MONTH(S90) -> 4 | W90: =IF(V90=6,"June",IF(V90=5,"May",IF(V90=4,"April",IF(V90=3,"March",IF(V90=7,"July",IF(V90=2,"February",0)))))) -> April
A91: =U91&W91&P91 -> AprilAprilHong Kong - DCL KY | B91: Freight Inbound | C91: AP | D91: 3372875 | E91: 43200 | F91: 07-2018 | G91: Freight Inbound Delivered 04/05/18 Hong Kong-Louisville,KY | H91: 1008536 | I91: 223100 | J91: HCORP-CRP-4600-JUL | K91: 5217.04 | L91: 0 | M91: 5217.04 | O91: Freight Inbound Delivered 04/05/18 Hong Kong-Louisville,KY | P91: Hong Kong - DCL KY | S91: 43191 | T91: 4 | U91: =IF(T91=6,"June",IF(T91=5,"May",IF(T91=4,"April",IF(T91=3,"March",IF(T91=7,"July",0))))) -> April | V91: =MONTH(S91) -> 4 | W91: =IF(V91=6,"June",IF(V91=5,"May",IF(V91=4,"April",IF(V91=3,"March",IF(V91=7,"July",IF(V91=2,"February",0)))))) -> April
A92: =U92&W92&P92 -> AprilAprilChina - DECI NC | B92: Freight Inbound | C92: AP | D92: 3346305 | E92: 43195 | F92: 07-2018 | G92: Freight Inbound Delivered 04/03/18 China - Durham, NC | H92: 1009348 | I92: 223100 | J92: HCORP-CRP-4600-JUL | K92: 21747.58 | L92: 0 | M92: 21747.58 | O92: Freight Inbound Delivered 04/03/18 China - Durham, NC | P92: China - DECI NC | S92: 43191 | T92: 4 | U92: =IF(T92=6,"June",IF(T92=5,"May",IF(T92=4,"April",IF(T92=3,"March",IF(T92=7,"July",0))))) -> April | V92: =MONTH(S92) -> 4 | W92: =IF(V92=6,"June",IF(V92=5,"May",IF(V92=4,"April",IF(V92=3,"March",IF(V92=7,"July",IF(V92=2,"February",0)))))) -> April
A93: =U93&W93&P93 -> MayMayChicago IL - Phillips WI | B93: Freight Inbound | C93: AP | D93: 3364813 | E93: 43224 | F93: 06-2018 | G93: Bemis Lot Freight Charges | H93: 1010152 | I93: 515000 | J93: HCORP-CRP-4600-JUL | K93: 378.67 | L93: 0 | M93: 378.67 | O93: Freight Charge | P93: Chicago IL - Phillips WI | Q93: 90924544 | R93: 43221 | S93: 43221 | T93: 5 | U93: =IF(T93=6,"June",IF(T93=5,"May",IF(T93=4,"April",IF(T93=3,"March",0)))) -> May | V93: =MONTH(S93) -> 5 | W93: =IF(V93=6,"June",IF(V93=5,"May",IF(V93=4,"April",IF(V93=3,"March",IF(V93=7,"July",IF(V93=2,"February",0)))))) -> May
A94: =U94&W94&P94 -> MayMayHong Kong - DCL KY | B94: Freight Inbound | C94: AP | D94: 3368293 | E94: 43225 | F94: 06-2018 | G94: Pallet Charges | H94: 1010270 | I94: 515000 | J94: HCORP-CRP-4600-JUL | K94: 48 | L94: 0 | M94: 48 | O94: Pallet Charges | P94: Hong Kong - DCL KY | Q94: W2E18DN0014 | R94: 43221 | S94: 43221 | T94: 5 | U94: =IF(T94=6,"June",IF(T94=5,"May",IF(T94=4,"April",IF(T94=3,"March",0)))) -> May | V94: =MONTH(S94) -> 5 | W94: =IF(V94=6,"June",IF(V94=5,"May",IF(V94=4,"April",IF(V94=3,"March",IF(V94=7,"July",IF(V94=2,"February",0)))))) -> May
A95: =U95&W95&P95 -> MayMayHong Kong - Phillips WI | B95: Freight Inbound | C95: AP | D95: 3368372 | E95: 43225 | F95: 06-2018 | G95: Pallet Charges | H95: 1010272 | I95: 515000 | J95: HCORP-CRP-4600-JUL | K95: 72 | L95: 0 | M95: 72 | O95: Pallet Charges | P95: Hong Kong - Phillips WI | Q95: W2E18DN0015 | R95: 43221 | S95: 43221 | T95: 5 | U95: =IF(T95=6,"June",IF(T95=5,"May",IF(T95=4,"April",IF(T95=3,"March",0)))) -> May | V95: =MONTH(S95) -> 5 | W95: =IF(V95=6,"June",IF(V95=5,"May",IF(V95=4,"April",IF(V95=3,"March",IF(V95=7,"July",IF(V95=2,"February",0)))))) -> May
A96: =U96&W96&P96 -> MayMayHong Kong - DECI NC | B96: Freight Inbound | C96: AP | D96: 3400379 | E96: 43231 | F96: 06-2018 | G96: Pallets SD 5/13/18 | H96: 1011288 | I96: 515000 | J96: HCORP-CRP-6000-JUL | K96: 48 | L96: 0 | M96: 48 | O96: Pallet Charges | P96: Hong Kong - DECI NC | Q96: W2EI8DN0028 | R96: 43221 | S96: 43221 | T96: 5 | U96: =IF(T96=6,"June",IF(T96=5,"May",IF(T96=4,"April",IF(T96=3,"March",0)))) -> May | V96: =MONTH(S96) -> 5 | W96: =IF(V96=6,"June",IF(V96=5,"May",IF(V96=4,"April",IF(V96=3,"March",IF(V96=7,"July",IF(V96=2,"February",0)))))) -> May
A97: =U97&W97&P97 -> MayMayHong Kong - DCL KY | B97: Freight Inbound | C97: AP | D97: 3368424 | E97: 43235 | F97: 06-2018 | G97: Pallet Charges | H97: 1010266 | I97: 515000 | J97: HCORP-CRP-4600-JUL | K97: 96 | L97: 0 | M97: 96 | O97: Pallet Charges | P97: Hong Kong - DCL KY | Q97: W2E18DN0029 | R97: 43221 | S97: 43221 | T97: 5 | U97: =IF(T97=6,"June",IF(T97=5,"May",IF(T97=4,"April",IF(T97=3,"March",0)))) -> May | V97: =MONTH(S97) -> 5 | W97: =IF(V97=6,"June",IF(V97=5,"May",IF(V97=4,"April",IF(V97=3,"March",IF(V97=7,"July",IF(V97=2,"February",0)))))) -> May
A98: =U98&W98&P98 -> MayMayHong Kong - DCL KY | B98: Freight Inbound | C98: AP | D98: 3368666 | E98: 43245 | F98: 06-2018 | G98: Pallet Charges | H98: 1010022 | I98: 515000 | J98: HCORP-CRP-4600-JUL | K98: 60 | L98: 0 | M98: 60 | O98: Pallet Charges | P98: Hong Kong - DCL KY | Q98: A2E18DN0048 | R98: 43221 | S98: 43221 | T98: 5 | U98: =IF(T98=6,"June",IF(T98=5,"May",IF(T98=4,"April",IF(T98=3,"March",0)))) -> May | V98: =MONTH(S98) -> 5 | W98: =IF(V98=6,"June",IF(V98=5,"May",IF(V98=4,"April",IF(V98=3,"March",IF(V98=7,"July",IF(V98=2,"February",0)))))) -> May
A99: =U99&W99&P99 -> MayMayHong Kong - Phillips WI | B99: Freight Inbound | C99: AP | D99: 3368667 | E99: 43245 | F99: 06-2018 | G99: Pallet Charges | H99: 1010025 | I99: 515000 | J99: HCORP-CRP-4600-JUL | K99: 36 | L99: 0 | M99: 36 | O99: Pallet Charges | P99: Hong Kong - Phillips WI | Q99: W2E18DN0049 | R99: 43221 | S99: 43221 | T99: 5 | U99: =IF(T99=6,"June",IF(T99=5,"May",IF(T99=4,"April",IF(T99=3,"March",0)))) -> May | V99: =MONTH(S99) -> 5 | W99: =IF(V99=6,"June",IF(V99=5,"May",IF(V99=4,"April",IF(V99=3,"March",IF(V99=7,"July",IF(V99=2,"February",0)))))) -> May
A100: =U100&W100&P100 -> MayMayHong Kong - DCL KY | B100: Freight Inbound | C100: AP | D100: 3368668 | E100: 43245 | F100: 06-2018 | G100: Pallet Charges | H100: 1010034 | I100: 515000 | J100: HCORP-CRP-4600-JUL | K100: 72 | L100: 0 | M100: 72 | O100: Pallet Charges | P100: Hong Kong - DCL KY | Q100: W2E18DN0048 | R100: 43221 | S100: 43221 | T100: 5 | U100: =IF(T100=6,"June",IF(T100=5,"May",IF(T100=4,"April",IF(T100=3,"March",0)))) -> May | V100: =MONTH(S100) -> 5 | W100: =IF(V100=6,"June",IF(V100=5,"May",IF(V100=4,"April",IF(V100=3,"March",IF(V100=7,"July",IF(V100=2,"February",0)))))) -> May
A101: =U101&W101&P101 -> MayMayHong Kong - Phillips WI | B101: Freight Inbound | C101: AP | D101: 3368672 | E101: 43245 | F101: 06-2018 | G101: Pallet Charges | H101: 1010279 | I101: 515000 | J101: HCORP-CRP-4600-JUL | K101: 36 | L101: 0 | M101: 36 | O101: Pallet Charges | P101: Hong Kong - Phillips WI | Q101: W2E18DN0047 | R101: 43221 | S101: 43221 | T101: 5 | U101: =IF(T101=6,"June",IF(T101=5,"May",IF(T101=4,"April",IF(T101=3,"March",0)))) -> May | V101: =MONTH(S101) -> 5 | W101: =IF(V101=6,"June",IF(V101=5,"May",IF(V101=4,"April",IF(V101=3,"March",IF(V101=7,"July",IF(V101=2,"February",0)))))) -> May
A102: =U102&W102&P102 -> MayMayAFG Suzho - DECI NC | B102: Freight Inbound | C102: GL | D102: 3381526 | E102: 43230 | F102: 06-2018 | G102: May 2018 Freight and Fulfillment Accrual Adjustment | H102: FLEXPORT | I102: 515000 | J102: HCORP-CRP-4600-JUL | K102: 6065.83 | L102: 0 | M102: 6065.83 | P102: AFG Suzho - DECI NC | Q102: FLEX-260024-2 | R102: 43191 | S102: 43221 | T102: 5 | U102: =IF(T102=6,"June",IF(T102=5,"May",IF(T102=4,"April",IF(T102=3,"March",0)))) -> May | V102: =MONTH(S102) -> 5 | W102: =IF(V102=6,"June",IF(V102=5,"May",IF(V102=4,"April",IF(V102=3,"March",IF(V102=7,"July",IF(V102=2,"February",0)))))) -> May
A103: =U103&W103&P103 -> MayMayAFG Suzho - DCL KY | B103: Freight Inbound | C103: GL | D103: 3381526 | E103: 43239 | F103: 06-2018 | G103: May 2018 Freight and Fulfillment Accrual Adjustment | H103: FLEXPORT | I103: 515000 | J103: HCORP-CRP-4600-JUL | K103: 73190.63 | L103: 0 | M103: 73190.63 | P103: AFG Suzho - DCL KY | Q103: FLEX-269916-1 | R103: 43221 | S103: 43221 | T103: 5 | U103: =IF(T103=6,"June",IF(T103=5,"May",IF(T103=4,"April",IF(T103=3,"March",0)))) -> May | V103: =MONTH(S103) -> 5 | W103: =IF(V103=6,"June",IF(V103=5,"May",IF(V103=4,"April",IF(V103=3,"March",IF(V103=7,"July",IF(V103=2,"February",0)))))) -> May
A104: =U104&W104&P104 -> MayMayAFG Suzho - DCL KY | B104: Freight Inbound | C104: GL | D104: 3381526 | E104: 43246 | F104: 06-2018 | G104: May 2018 Freight and Fulfillment Accrual Adjustment | H104: FLEXPORT | I104: 515000 | J104: HCORP-CRP-4600-JUL | K104: 9984.53 | L104: 0 | M104: 9984.53 | P104: AFG Suzho - DCL KY | Q104: FLEX-269924-1 | R104: 43221 | S104: 43221 | T104: 5 | U104: =IF(T104=6,"June",IF(T104=5,"May",IF(T104=4,"April",IF(T104=3,"March",0)))) -> May | V104: =MONTH(S104) -> 5 | W104: =IF(V104=6,"June",IF(V104=5,"May",IF(V104=4,"April",IF(V104=3,"March",IF(V104=7,"July",IF(V104=2,"February",0)))))) -> May
A105: =U105&W105&P105 -> MayMayHong Kong - DECI NC | B105: Freight Inbound | C105: GL | D105: 3381526 | E105: 43246 | F105: 06-2018 | G105: May 2018 Freight and Fulfillment Accrual Adjustment | H105: FLEXPORT | I105: 515000 | J105: HCORP-CRP-4600-JUL | K105: 7102.8 | L105: 0 | M105: 7102.8 | P105: Hong Kong - DECI NC | Q105: FLEX-275538-1 | R105: 43221 | S105: 43221 | T105: 5 | U105: =IF(T105=6,"June",IF(T105=5,"May",IF(T105=4,"April",IF(T105=3,"March",0)))) -> May | V105: =MONTH(S105) -> 5 | W105: =IF(V105=6,"June",IF(V105=5,"May",IF(V105=4,"April",IF(V105=3,"March",IF(V105=7,"July",IF(V105=2,"February",0)))))) -> May
A106: =U106&W106&P106 -> MayMayAFG Suzho - DECI NC | B106: Freight Inbound | C106: GL | D106: 3381526 | E106: 43246 | F106: 06-2018 | G106: May 2018 Freight and Fulfillment Accrual Adjustment | H106: FLEXPORT | I106: 515000 | J106: HCORP-CRP-4600-JUL | K106: 57591.86 | L106: 0 | M106: 57591.86 | P106: AFG Suzho - DECI NC | Q106: FLEX-276804-1 | R106: 43221 | S106: 43221 | T106: 5 | U106: =IF(T106=6,"June",IF(T106=5,"May",IF(T106=4,"April",IF(T106=3,"March",0)))) -> May | V106: =MONTH(S106) -> 5 | W106: =IF(V106=6,"June",IF(V106=5,"May",IF(V106=4,"April",IF(V106=3,"March",IF(V106=7,"July",IF(V106=2,"February",0)))))) -> May
A107: =U107&W107&P107 -> MayMayAFG Suzho - DCL KY | B107: Freight Inbound | C107: GL | D107: 3381526 | E107: 43246 | F107: 06-2018 | G107: May 2018 Freight and Fulfillment Accrual Adjustment | H107: FLEXPORT | I107: 515000 | J107: HCORP-CRP-4600-JUL | K107: 18009.23 | L107: 0 | M107: 18009.23 | P107: AFG Suzho - DCL KY | Q107: FLEX-276807-1 | R107: 43221 | S107: 43221 | T107: 5 | U107: =IF(T107=6,"June",IF(T107=5,"May",IF(T107=4,"April",IF(T107=3,"March",0)))) -> May | V107: =MONTH(S107) -> 5 | W107: =IF(V107=6,"June",IF(V107=5,"May",IF(V107=4,"April",IF(V107=3,"March",IF(V107=7,"July",IF(V107=2,"February",0)))))) -> May
A108: =U108&W108&P108 -> MayMayAFG Suzho - DECI NC | B108: Freight Inbound | C108: GL | D108: 3381526 | E108: 43246 | F108: 06-2018 | G108: May 2018 Freight and Fulfillment Accrual Adjustment | H108: FLEXPORT | I108: 515000 | J108: HCORP-CRP-4600-JUL | K108: 49366.27 | L108: 0 | M108: 49366.27 | P108: AFG Suzho - DECI NC | Q108: FLEX-276812-1 | R108: 43221 | S108: 43221 | T108: 5 | U108: =IF(T108=6,"June",IF(T108=5,"May",IF(T108=4,"April",IF(T108=3,"March",0)))) -> May | V108: =MONTH(S108) -> 5 | W108: =IF(V108=6,"June",IF(V108=5,"May",IF(V108=4,"April",IF(V108=3,"March",IF(V108=7,"July",IF(V108=2,"February",0)))))) -> May
A109: =U109&W109&P109 -> MayMayDCL KY - Canada | B109: Freight Inbound | C109: GL | D109: 3381526 | E109: 43246 | F109: 06-2018 | G109: May 2018 Freight and Fulfillment Accrual Adjustment | H109: FLEXPORT | I109: 515000 | J109: HCORP-CRP-4600-JUL | K109: 3781.09 | L109: 0 | M109: 3781.09 | P109: DCL KY - Canada | Q109: FLEX-281123-1 | R109: 43221 | S109: 43221 | T109: 5 | U109: =IF(T109=6,"June",IF(T109=5,"May",IF(T109=4,"April",IF(T109=3,"March",0)))) -> May | V109: =MONTH(S109) -> 5 | W109: =IF(V109=6,"June",IF(V109=5,"May",IF(V109=4,"April",IF(V109=3,"March",IF(V109=7,"July",IF(V109=2,"February",0)))))) -> May
A110: =U110&W110&P110 -> MayMayHong Kong - Phillips WI | B110: Freight Inbound | C110: GL | D110: 3381526 | E110: 43246 | F110: 06-2018 | G110: May 2018 Freight and Fulfillment Accrual Adjustment | H110: FLEXPORT | I110: 515000 | J110: HCORP-CRP-4600-JUL | K110: 16928.59 | L110: 0 | M110: 16928.59 | P110: Hong Kong - Phillips WI | Q110: FLEX-282790-1 | R110: 43221 | S110: 43221 | T110: 5 | U110: =IF(T110=6,"June",IF(T110=5,"May",IF(T110=4,"April",IF(T110=3,"March",0)))) -> May | V110: =MONTH(S110) -> 5 | W110: =IF(V110=6,"June",IF(V110=5,"May",IF(V110=4,"April",IF(V110=3,"March",IF(V110=7,"July",IF(V110=2,"February",0)))))) -> May
A111: =U111&W111&P111 -> MayMayHong Kong - Phillips WI | B111: Freight Inbound | C111: GL | D111: 3381526 | E111: 43246 | F111: 06-2018 | G111: May 2018 Freight and Fulfillment Accrual Adjustment | H111: FLEXPORT | I111: 515000 | J111: HCORP-CRP-4600-JUL | K111: 9461.81 | L111: 0 | M111: 9461.81 | P111: Hong Kong - Phillips WI | Q111: FLEX-282827-1 | R111: 43221 | S111: 43221 | T111: 5 | U111: =IF(T111=6,"June",IF(T111=5,"May",IF(T111=4,"April",IF(T111=3,"March",0)))) -> May | V111: =MONTH(S111) -> 5 | W111: =IF(V111=6,"June",IF(V111=5,"May",IF(V111=4,"April",IF(V111=3,"March",IF(V111=7,"July",IF(V111=2,"February",0)))))) -> May
A112: =U112&W112&P112 -> MayMayHong Kong - DCL KY | B112: Freight Inbound | C112: GL | D112: 3381526 | E112: 43246 | F112: 06-2018 | G112: May 2018 Freight and Fulfillment Accrual Adjustment | H112: FLEXPORT | I112: 515000 | J112: HCORP-CRP-4600-JUL | K112: 1522.23 | L112: 0 | M112: 1522.23 | P112: Hong Kong - DCL KY | Q112: FLEX-283010-1 | R112: 43221 | S112: 43221 | T112: 5 | U112: =IF(T112=6,"June",IF(T112=5,"May",IF(T112=4,"April",IF(T112=3,"March",0)))) -> May | V112: =MONTH(S112) -> 5 | W112: =IF(V112=6,"June",IF(V112=5,"May",IF(V112=4,"April",IF(V112=3,"March",IF(V112=7,"July",IF(V112=2,"February",0)))))) -> May
A113: =U113&W113&P113 -> MayMayAFG Suzho - Flex IL | B113: Freight Inbound | C113: GL | D113: 3381526 | E113: 43246 | F113: 06-2018 | G113: May 2018 Freight and Fulfillment Accrual Adjustment | H113: FLEXPORT | I113: 515000 | J113: HCORP-CRP-4600-JUL | K113: 5079.68 | L113: 0 | M113: 5079.68 | P113: AFG Suzho - Flex IL | Q113: FLEX-286414-1 | R113: 43221 | S113: 43221 | T113: 5 | U113: =IF(T113=6,"June",IF(T113=5,"May",IF(T113=4,"April",IF(T113=3,"March",0)))) -> May | V113: =MONTH(S113) -> 5 | W113: =IF(V113=6,"June",IF(V113=5,"May",IF(V113=4,"April",IF(V113=3,"March",IF(V113=7,"July",IF(V113=2,"February",0)))))) -> May
... A118: =U118&W118&P118 -> MayMayPhillips WI - DCL KY | B118: Freight Inbound | C118: GL | D118: 3410206 | E118: 43244 | F118: 06-2018 | G118: June 2018 Freight and Fulfillment Accrual | H118: K+N | I118: 515000 | J118: NAUSA-CRP-4600-JUL | K118: -5825 | L118: 0 | M118: -5825 | P118: Phillips WI - DCL KY | Q118: LAXFO18050287 | R118: 43221 | S118: 43221 | T118: 5 | U118: =IF(T118=6,"June",IF(T118=5,"May",IF(T118=4,"April",IF(T118=3,"March",0)))) -> May | V118: =MONTH(S118) -> 5 | W118: =IF(V118=6,"June",IF(V118=5,"May",IF(V118=4,"April",IF(V118=3,"March",IF(V118=7,"July",IF(V118=2,"February",0)))))) -> May
A119: =U119&W119&P119 -> MayMayHong Kong - DECI NC | B119: Freight Inbound | C119: AP | D119: 3336225 | E119: 43223 | F119: 05-2018 | G119: Pallet Charges | H119: 1009123 | I119: 515000 | J119: HCORP-CRP-4600-JUL | K119: 60 | L119: 0 | M119: 60 | O119: Pallet Charges | P119: Hong Kong - DECI NC | Q119: W2E18DN0008 | R119: 43221 | S119: 43221 | T119: 5 | U119: =IF(T119=6,"June",IF(T119=5,"May",IF(T119=4,"April",IF(T119=3,"March",0)))) -> May | V119: =MONTH(S119) -> 5 | W119: =IF(V119=6,"June",IF(V119=5,"May",IF(V119=4,"April",IF(V119=3,"March",IF(V119=7,"July",IF(V119=2,"February",0)))))) -> May
A120: =U120&W120&P120 -> MayMayChina - Flex IL | B120: Freight Inbound | C120: AP | D120: 3346449 | E120: 43223 | F120: 05-2018 | G120: Freight Inbound ETA 05/02/18 Chippewa/Flex Buffalo Grove, IL | H120: 1009533 | I120: 515000 | J120: NAUSA-CRP-4600-JUL | K120: 1250 | L120: 0 | M120: 1250 | O120: Freight Inbound ETA 05/02/18 Chippewa/Flex Buffalo Grove, IL | P120: China - Flex IL | R120: 43221 | S120: 43221 | T120: 5 | U120: =IF(T120=6,"June",IF(T120=5,"May",IF(T120=4,"April",IF(T120=3,"March",0)))) -> May | V120: =MONTH(S120) -> 5 | W120: =IF(V120=6,"June",IF(V120=5,"May",IF(V120=4,"April",IF(V120=3,"March",IF(V120=7,"July",IF(V120=2,"February",0)))))) -> May
A121: =U121&W121&P121 -> MayMayHong Kong - AFG NC | B121: Freight Inbound | C121: AP | D121: 3336158 | E121: 43231 | F121: 05-2018 | G121: Pallet Charges | H121: 1009213 | I121: 515000 | J121: HCORP-CRP-4600-JUL | K121: 48 | L121: 0 | M121: 48 | O121: Pallet Charges | P121: Hong Kong - AFG NC | R121: 43221 | S121: 43221 | T121: 5 | U121: =IF(T121=6,"June",IF(T121=5,"May",IF(T121=4,"April",IF(T121=3,"March",0)))) -> May | V121: =MONTH(S121) -> 5 | W121: =IF(V121=6,"June",IF(V121=5,"May",IF(V121=4,"April",IF(V121=3,"March",IF(V121=7,"July",IF(V121=2,"February",0)))))) -> May
A122: =U122&W122&P122 -> MayMayHong Kong - AFG NC | B122: Freight Inbound | C122: AP | D122: 3353218 | E122: 43231 | F122: 05-2018 | G122: Pallet Charges | H122: 1009784 | I122: 515000 | J122: HCORP-CRP-4600-JUL | K122: 60 | L122: 0 | M122: 60 | O122: Pallet Charges | P122: Hong Kong - AFG NC | R122: 43221 | S122: 43221 | T122: 5 | U122: =IF(T122=6,"June",IF(T122=5,"May",IF(T122=4,"April",IF(T122=3,"March",0)))) -> May | V122: =MONTH(S122) -> 5 | W122: =IF(V122=6,"June",IF(V122=5,"May",IF(V122=4,"April",IF(V122=3,"March",IF(V122=7,"July",IF(V122=2,"February",0)))))) -> May
A123: =U123&W123&P123 -> MayMayHong Kong - AFG NC | B123: Freight Inbound | C123: AP | D123: 3355368 | E123: 43231 | F123: 05-2018 | G123: Pallet Charges | H123: 1009814 | I123: 515000 | J123: HCORP-CRP-4600-JUL | K123: 60 | L123: 0 | M123: 60 | O123: Pallet Charges | P123: Hong Kong - AFG NC | R123: 43221 | S123: 43221 | T123: 5 | U123: =IF(T123=6,"June",IF(T123=5,"May",IF(T123=4,"April",IF(T123=3,"March",0)))) -> May | V123: =MONTH(S123) -> 5 | W123: =IF(V123=6,"June",IF(V123=5,"May",IF(V123=4,"April",IF(V123=3,"March",IF(V123=7,"July",IF(V123=2,"February",0)))))) -> May
A124: =U124&W124&P124 -> MayMayDECI NC - DCL KY | B124: Freight Inbound | C124: AP | D124: 3346435 | E124: 43234 | F124: 05-2018 | G124: Freight Inbound ETA 05/09/18 DECI NC to Louisville KY | H124: 1009463 | I124: 515000 | J124: NAUSA-CRP-4600-JUL | K124: 1725 | L124: 0 | M124: 1725 | O124: Freight Inbound ETA 05/09/18 DECI NC to Louisville KY | P124: DECI NC - DCL KY | R124: 43221 | S124: 43221 | T124: 5 | U124: =IF(T124=6,"June",IF(T124=5,"May",IF(T124=4,"April",IF(T124=3,"March",0)))) -> May | V124: =MONTH(S124) -> 5 | W124: =IF(V124=6,"June",IF(V124=5,"May",IF(V124=4,"April",IF(V124=3,"March",IF(V124=7,"July",IF(V124=2,"February",0)))))) -> May
A125: =U125&W125&P125 -> MayMayAFG NC - DCL KY | B125: Freight Inbound | C125: AP | D125: 3346436 | E125: 43234 | F125: 05-2018 | G125: Freight Inbound ETA 05/03/18 ASTEELFLASH NC to Louisville KY | H125: 1009469 | I125: 515000 | J125: NAUSA-CRP-4600-JUL | K125: 4650 | L125: 0 | M125: 4650 | O125: Freight Inbound ETA 05/03/18 ASTEELFLASH NC to Louisville KY | P125: AFG NC - DCL KY | R125: 43221 | S125: 43221 | T125: 5 | U125: =IF(T125=6,"June",IF(T125=5,"May",IF(T125=4,"April",IF(T125=3,"March",0)))) -> May | V125: =MONTH(S125) -> 5 | W125: =IF(V125=6,"June",IF(V125=5,"May",IF(V125=4,"April",IF(V125=3,"March",IF(V125=7,"July",IF(V125=2,"February",0)))))) -> May
A126: =U126&W126&P126 -> MayMayAFG NC - DCL KY | B126: Freight Inbound | C126: AP | D126: 3346437 | E126: 43234 | F126: 05-2018 | G126: Freight Inbound ETA 05/06/18 ASTEELFLASH NC to Louisville KY | H126: 1009471 | I126: 515000 | J126: NAUSA-CRP-4600-JUL | K126: 1550 | L126: 0 | M126: 1550 | O126: Freight Inbound ETA 05/06/18 ASTEELFLASH NC to Louisville KY | P126: AFG NC - DCL KY | R126: 43221 | S126: 43221 | T126: 5 | U126: =IF(T126=6,"June",IF(T126=5,"May",IF(T126=4,"April",IF(T126=3,"March",0)))) -> May | V126: =MONTH(S126) -> 5 | W126: =IF(V126=6,"June",IF(V126=5,"May",IF(V126=4,"April",IF(V126=3,"March",IF(V126=7,"July",IF(V126=2,"February",0)))))) -> May
A127: =U127&W127&P127 -> MayMayAFG NC - DCL KY | B127: Freight Inbound | C127: AP | D127: 3346439 | E127: 43234 | F127: 05-2018 | G127: Freight Inbound ETA 05/04/18 ASTEELFLASH NC to Louisville KY | H127: 1009478 | I127: 515000 | J127: NAUSA-CRP-4600-JUL | K127: 3100 | L127: 0 | M127: 3100 | O127: Freight Inbound ETA 05/04/18 ASTEELFLASH NC to Louisville KY | P127: AFG NC - DCL KY | R127: 43221 | S127: 43221 | T127: 5 | U127: =IF(T127=6,"June",IF(T127=5,"May",IF(T127=4,"April",IF(T127=3,"March",0)))) -> May | V127: =MONTH(S127) -> 5 | W127: =IF(V127=6,"June",IF(V127=5,"May",IF(V127=4,"April",IF(V127=3,"March",IF(V127=7,"July",IF(V127=2,"February",0)))))) -> May
A128: =U128&W128&P128 -> MayMayAFG NC - DCL KY | B128: Freight Inbound | C128: AP | D128: 3346440 | E128: 43234 | F128: 05-2018 | G128: Freight Inbound ETA 05/08/18 ASTEELFLASH NC to Louisville KY | H128: 1009480 | I128: 515000 | J128: NAUSA-CRP-4600-JUL | K128: 3100 | L128: 0 | M128: 3100 | O128: Freight Inbound ETA 05/08/18 ASTEELFLASH NC to Louisville KY | P128: AFG NC - DCL KY | R128: 43221 | S128: 43221 | T128: 5 | U128: =IF(T128=6,"June",IF(T128=5,"May",IF(T128=4,"April",IF(T128=3,"March",0)))) -> May | V128: =MONTH(S128) -> 5 | W128: =IF(V128=6,"June",IF(V128=5,"May",IF(V128=4,"April",IF(V128=3,"March",IF(V128=7,"July",IF(V128=2,"February",0)))))) -> May
A129: =U129&W129&P129 -> MayMayAFG NC - DCL KY | B129: Freight Inbound | C129: AP | D129: 3346443 | E129: 43234 | F129: 05-2018 | G129: Freight Inbound ETA 05/01/18 ASTEELFLASH NC to Louisville KY | H129: 1009485 | I129: 515000 | J129: NAUSA-CRP-4600-JUL | K129: 3100 | L129: 0 | M129: 3100 | O129: Freight Inbound ETA 05/01/18 ASTEELFLASH NC to Louisville KY | P129: AFG NC - DCL KY | R129: 43221 | S129: 43221 | T129: 5 | U129: =IF(T129=6,"June",IF(T129=5,"May",IF(T129=4,"April",IF(T129=3,"March",0)))) -> May | V129: =MONTH(S129) -> 5 | W129: =IF(V129=6,"June",IF(V129=5,"May",IF(V129=4,"April",IF(V129=3,"March",IF(V129=7,"July",IF(V129=2,"February",0)))))) -> May
A130: =U130&W130&P130 -> MayMayAFG NC - DCL KY | B130: Freight Inbound | C130: AP | D130: 3346444 | E130: 43234 | F130: 05-2018 | G130: Freight Inbound ETA 05/05/18 ASTEELFLASH NC to Louisville KY | H130: 1009520 | I130: 515000 | J130: NAUSA-CRP-4600-JUL | K130: 3100 | L130: 0 | M130: 3100 | O130: Freight Inbound ETA 05/05/18 ASTEELFLASH NC to Louisville KY | P130: AFG NC - DCL KY | R130: 43221 | S130: 43221 | T130: 5 | U130: =IF(T130=6,"June",IF(T130=5,"May",IF(T130=4,"April",IF(T130=3,"March",0)))) -> May | V130: =MONTH(S130) -> 5 | W130: =IF(V130=6,"June",IF(V130=5,"May",IF(V130=4,"April",IF(V130=3,"March",IF(V130=7,"July",IF(V130=2,"February",0)))))) -> May
A131: =U131&W131&P131 -> MayMayAFG NC - DCL KY | B131: Freight Inbound | C131: AP | D131: 3346445 | E131: 43234 | F131: 05-2018 | G131: Freight Inbound ETA 05/14/18 ASTEELFLASH NC to Louisville KY | H131: 1009524 | I131: 515000 | J131: NAUSA-CRP-4600-JUL | K131: 4650 | L131: 0 | M131: 4650 | O131: Freight Inbound ETA 05/14/18 ASTEELFLASH NC to Louisville KY | P131: AFG NC - DCL KY | R131: 43221 | S131: 43221 | T131: 5 | U131: =IF(T131=6,"June",IF(T131=5,"May",IF(T131=4,"April",IF(T131=3,"March",0)))) -> May | V131: =MONTH(S131) -> 5 | W131: =IF(V131=6,"June",IF(V131=5,"May",IF(V131=4,"April",IF(V131=3,"March",IF(V131=7,"July",IF(V131=2,"February",0)))))) -> May
... A143: =U143&W143&P143 -> MayMayHong Kong - AFG NC | B143: Freight Inbound | C143: AP | D143: 3346586 | E143: 43238 | F143: 05-2018 | G143: Pallet Charges | H143: 1009619 | I143: 515000 | J143: HCORP-CRP-4600-JUL | K143: 96 | L143: 0 | M143: 96 | O143: Pallet Charges | P143: Hong Kong - AFG NC | R143: 43221 | S143: 43221 | T143: 5 | U143: =IF(T143=6,"June",IF(T143=5,"May",IF(T143=4,"April",IF(T143=3,"March",0)))) -> May | V143: =MONTH(S143) -> 5 | W143: =IF(V143=6,"June",IF(V143=5,"May",IF(V143=4,"April",IF(V143=3,"March",IF(V143=7,"July",IF(V143=2,"February",0)))))) -> May
A144: =U144&W144&P144 -> MayAprilHong Kong - DECI NC | B144: Freight Inbound | C144: IN | D144: 3346308 | E144: 43222 | F144: 05-2018 | G144: JUUL Basic Kit for Starter Kit | H144: 000495 | I144: 513000 | J144: HCORP-CRP-4600-JUL | K144: 791.13 | L144: 0 | M144: 791.13 | N144: 3346307 | O144: Freight inbound Delivered 04/25/18 Hong Kong - Durham, NC | P144: Hong Kong - DECI NC | Q144: FLEX-254492-1 | R144: 43191 | S144: 43191 | T144: 5 | U144: =IF(T144=6,"June",IF(T144=5,"May",IF(T144=4,"April",IF(T144=3,"March",0)))) -> May | V144: =MONTH(S144) -> 4 | W144: =IF(V144=6,"June",IF(V144=5,"May",IF(V144=4,"April",IF(V144=3,"March",IF(V144=7,"July",IF(V144=2,"February",0)))))) -> April
A145: =U145&W145&P145 -> MayAprilHong Kong - DECI NC | B145: Freight Inbound | C145: IN | D145: 3346308 | E145: 43222 | F145: 05-2018 | G145: JUUL Basic Kit for Starter Kit | H145: 000495 | I145: 513000 | J145: HCORP-CRP-4600-JUL | K145: 9945.58 | L145: 0 | M145: 9945.58 | N145: 3346307 | O145: Freight inbound Delivered 04/25/18 Hong Kong - Durham, NC | P145: Hong Kong - DECI NC | Q145: FLEX-254492-1 | R145: 43191 | S145: 43191 | T145: 5 | U145: =IF(T145=6,"June",IF(T145=5,"May",IF(T145=4,"April",IF(T145=3,"March",0)))) -> May | V145: =MONTH(S145) -> 4 | W145: =IF(V145=6,"June",IF(V145=5,"May",IF(V145=4,"April",IF(V145=3,"March",IF(V145=7,"July",IF(V145=2,"February",0)))))) -> April
A146: =U146&W146&P146 -> MayAprilHong Kong - DECI NC | B146: Freight Inbound | C146: IN | D146: 3346308 | E146: 43222 | F146: 05-2018 | G146: JUUL Basic Kit for Starter Kit | H146: 000495 | I146: 513000 | J146: HCORP-CRP-4600-JUL | K146: 59.33 | L146: 0 | M146: 59.33 | N146: 3346307 | O146: Freight inbound Delivered 04/25/18 Hong Kong - Durham, NC | P146: Hong Kong - DECI NC | Q146: FLEX-254492-1 | R146: 43191 | S146: 43191 | T146: 5 | U146: =IF(T146=6,"June",IF(T146=5,"May",IF(T146=4,"April",IF(T146=3,"March",0)))) -> May | V146: =MONTH(S146) -> 4 | W146: =IF(V146=6,"June",IF(V146=5,"May",IF(V146=4,"April",IF(V146=3,"March",IF(V146=7,"July",IF(V146=2,"February",0)))))) -> April
A147: =U147&W147&P147 -> MayAprilHong Kong - Phillips WI | B147: Freight Inbound | C147: IN | D147: 3346310 | E147: 43222 | F147: 05-2018 | G147: Empty Green POD, Manual Gasket | H147: 000496 | I147: 513000 | J147: HCORP-CRP-4600-JUL | K147: 6205.66 | L147: 0 | M147: 6205.66 | N147: 3346309 | O147: Freight inbound Delivered 04/25/18 Hong Kong-Menomonie,WI | P147: Hong Kong - Phillips WI | Q147: FLEX-255566-1 | R147: 43191 | S147: 43191 | T147: 5 | U147: =IF(T147=6,"June",IF(T147=5,"May",IF(T147=4,"April",IF(T147=3,"March",0)))) -> May | V147: =MONTH(S147) -> 4 | W147: =IF(V147=6,"June",IF(V147=5,"May",IF(V147=4,"April",IF(V147=3,"March",IF(V147=7,"July",IF(V147=2,"February",0)))))) -> April
A148: =U148&W148&P148 -> MayAprilHong Kong - DCL KY | B148: Freight Inbound | C148: IN | D148: 3346314 | E148: 43222 | F148: 05-2018 | G148: Empty Yellow POD, Manual Gasket | H148: 000498 | I148: 513000 | J148: HCORP-CRP-4600-JUL | K148: 3875.53 | L148: 0 | M148: 3875.53 | N148: 3346313 | O148: Freight inbound Delivered 04/24/18 Hong Kong - Louisville,KY | P148: Hong Kong - DCL KY | Q148: FLEX-255554-1 | R148: 43191 | S148: 43191 | T148: 5 | U148: =IF(T148=6,"June",IF(T148=5,"May",IF(T148=4,"April",IF(T148=3,"March",0)))) -> May | V148: =MONTH(S148) -> 4 | W148: =IF(V148=6,"June",IF(V148=5,"May",IF(V148=4,"April",IF(V148=3,"March",IF(V148=7,"July",IF(V148=2,"February",0)))))) -> April
A149: =U149&W149&P149 -> MayAprilChina - DCL KY | B149: Freight Inbound | C149: IN | D149: 3346322 | E149: 43222 | F149: 05-2018 | G149: JUUL Basic Kit Slate | H149: 000502 | I149: 513000 | J149: HCORP-CRP-4600-JUL | K149: 2863.12 | L149: 0 | M149: 2863.12 | N149: 3346321 | O149: Freight inbound Delivered 04/24/18 China - Louisville,KY | P149: China - DCL KY | R149: 43191 | S149: 43191 | T149: 5 | U149: =IF(T149=6,"June",IF(T149=5,"May",IF(T149=4,"April",IF(T149=3,"March",0)))) -> May | V149: =MONTH(S149) -> 4 | W149: =IF(V149=6,"June",IF(V149=5,"May",IF(V149=4,"April",IF(V149=3,"March",IF(V149=7,"July",IF(V149=2,"February",0)))))) -> April
A150: =U150&W150&P150 -> MayAprilHong Kong - Phillips WI | B150: Freight Inbound | C150: IN | D150: 3346328 | E150: 43222 | F150: 05-2018 | G150: Empty Green POD, Manual Gasket | H150: 000505 | I150: 513000 | J150: HCORP-CRP-4600-JUL | K150: 13785.41 | L150: 0 | M150: 13785.41 | N150: 3346327 | O150: Freight inbound Delivered 04/25/18 Hong Kong - Menomonie,WI | P150: Hong Kong - Phillips WI | R150: 43191 | S150: 43191 | T150: 5 | U150: =IF(T150=6,"June",IF(T150=5,"May",IF(T150=4,"April",IF(T150=3,"March",0)))) -> May | V150: =MONTH(S150) -> 4 | W150: =IF(V150=6,"June",IF(V150=5,"May",IF(V150=4,"April",IF(V150=3,"March",IF(V150=7,"July",IF(V150=2,"February",0)))))) -> April
A151: =U151&W151&P151 -> MayAprilHong Kong - DCL KY | B151: Freight Inbound | C151: IN | D151: 3346336 | E151: 43222 | F151: 05-2018 | G151: Empty Yellow POD, Manual Gasket | H151: 000508 | I151: 513000 | J151: HCORP-CRP-4600-JUL | K151: 12411.51 | L151: 0 | M151: 12411.51 | N151: 3346335 | O151: Freight inbound Delivered 04/24/18 Hong Kong-Louisville,KY | P151: Hong Kong - DCL KY | R151: 43191 | S151: 43191 | T151: 5 | U151: =IF(T151=6,"June",IF(T151=5,"May",IF(T151=4,"April",IF(T151=3,"March",0)))) -> May | V151: =MONTH(S151) -> 4 | W151: =IF(V151=6,"June",IF(V151=5,"May",IF(V151=4,"April",IF(V151=3,"March",IF(V151=7,"July",IF(V151=2,"February",0)))))) -> April
A152: =U152&W152&P152 -> MayAprilHong Kong - DECI NC | B152: Freight Inbound | C152: IN | D152: 3346338 | E152: 43222 | F152: 05-2018 | G152: JUUL Basic Kit for Starter Kit | H152: 000509 | I152: 513000 | J152: HCORP-CRP-4600-JUL | K152: 9374.31 | L152: 0 | M152: 9374.31 | N152: 3346337 | O152: Freight inbound Delivered 04/25/18 Hong Kong - Durham, NC | P152: Hong Kong - DECI NC | R152: 43191 | S152: 43191 | T152: 5 | U152: =IF(T152=6,"June",IF(T152=5,"May",IF(T152=4,"April",IF(T152=3,"March",0)))) -> May | V152: =MONTH(S152) -> 4 | W152: =IF(V152=6,"June",IF(V152=5,"May",IF(V152=4,"April",IF(V152=3,"March",IF(V152=7,"July",IF(V152=2,"February",0)))))) -> April
A153: =U153&W153&P153 -> MayAprilChina - DCL KY | B153: Freight Inbound | C153: IN | D153: 3346342 | E153: 43222 | F153: 05-2018 | G153: JUUL Basic Kit Slate | H153: 000511 | I153: 513000 | J153: HCORP-CRP-4600-JUL | K153: 38343.42 | L153: 0 | M153: 38343.42 | N153: 3346341 | O153: Freight inbound Delivered 04/25/18 China - Louisville, KY | P153: China - DCL KY | R153: 43191 | S153: 43191 | T153: 5 | U153: =IF(T153=6,"June",IF(T153=5,"May",IF(T153=4,"April",IF(T153=3,"March",0)))) -> May | V153: =MONTH(S153) -> 4 | W153: =IF(V153=6,"June",IF(V153=5,"May",IF(V153=4,"April",IF(V153=3,"March",IF(V153=7,"July",IF(V153=2,"February",0)))))) -> April
A154: =U154&W154&P154 -> MayAprilHong Kong - DECI NC | B154: Freight Inbound | C154: IN | D154: 3346344 | E154: 43222 | F154: 05-2018 | G154: JUUL Basic Kit for Starter Kit | H154: 000512 | I154: 513000 | J154: HCORP-CRP-4600-JUL | K154: 74.64 | L154: 0 | M154: 74.64 | N154: 3346343 | O154: Freight inbound Delivered 04/25/18 Hong Kong - Durham, NC | P154: Hong Kong - DECI NC | R154: 43191 | S154: 43191 | T154: 5 | U154: =IF(T154=6,"June",IF(T154=5,"May",IF(T154=4,"April",IF(T154=3,"March",0)))) -> May | V154: =MONTH(S154) -> 4 | W154: =IF(V154=6,"June",IF(V154=5,"May",IF(V154=4,"April",IF(V154=3,"March",IF(V154=7,"July",IF(V154=2,"February",0)))))) -> April
A155: =U155&W155&P155 -> MayAprilHong Kong - DECI NC | B155: Freight Inbound | C155: IN | D155: 3346344 | E155: 43222 | F155: 05-2018 | G155: JUUL Basic Kit for Starter Kit | H155: 000512 | I155: 513000 | J155: HCORP-CRP-4600-JUL | K155: 10744.32 | L155: 0 | M155: 10744.32 | N155: 3346343 | O155: Freight inbound Delivered 04/25/18 Hong Kong - Durham, NC | P155: Hong Kong - DECI NC | R155: 43191 | S155: 43191 | T155: 5 | U155: =IF(T155=6,"June",IF(T155=5,"May",IF(T155=4,"April",IF(T155=3,"March",0)))) -> May | V155: =MONTH(S155) -> 4 | W155: =IF(V155=6,"June",IF(V155=5,"May",IF(V155=4,"April",IF(V155=3,"March",IF(V155=7,"July",IF(V155=2,"February",0)))))) -> April
A156: =U156&W156&P156 -> MayAprilChina - DCL KY | B156: Freight Inbound | C156: IN | D156: 3346348 | E156: 43222 | F156: 05-2018 | G156: JUUL Basic Kit Slate | H156: 000514 | I156: 513000 | J156: HCORP-CRP-4600-JUL | K156: 29221.5 | L156: 0 | M156: 29221.5 | N156: 3346347 | O156: Freight inbound Delivered 04/30/18 China - Louisville, KY | P156: China - DCL KY | R156: 43191 | S156: 43191 | T156: 5 | U156: =IF(T156=6,"June",IF(T156=5,"May",IF(T156=4,"April",IF(T156=3,"March",0)))) -> May | V156: =MONTH(S156) -> 4 | W156: =IF(V156=6,"June",IF(V156=5,"May",IF(V156=4,"April",IF(V156=3,"March",IF(V156=7,"July",IF(V156=2,"February",0)))))) -> April
...

Sheet Data Backup
A1: Code | B1: Type | C1: Module | D1: Batch Number | E1: Tran. Date | F1: Period | G1: Description | H1: Ref. Number | I1: Account | J1: Subaccount | K1: Debit Amount | L1: Credit Amount | M1: Net Activity | N1: Reclass. Batch | O1: Freight Full Comments | P1: Freight Code | Q1: Invoice | R1: Ship Month | S1: Rec Month | T1: Invoiced | U1: Month
A2: =U2&P2 -> JunePhillips WI - DCL KY | B2: Freight Inbound | C2: IN | D2: 3416738 | E2: 43255 | F2: 06-2018 | G2: JUUL Pods Classic Menthol 5.0% 2.8ml 4-pack | H2: 000636 | I2: 513000 | J2: HCORP-CRP-4600-JUL | K2: 195.69 | L2: 0 | M2: =K2-L2 -> 195.69 | N2: =VLOOKUP(D2,[1]Sheet1!$N:$O,2,0) -> 3416737 | O2: Freight Inbound ETA 6/1/18 ASTEELFLASH WI to Louisville KY | P2: Phillips WI - DCL KY | Q2: FLEX-290227-1 | R2: 43221 | S2: 43221 | T2: =MONTH(E2) -> 6 | U2: =IF(T2=6,"June",IF(T2=5,"May",IF(T2=4,"April",IF(T2=3,"March",0)))) -> June
A3: =U3&P3 -> JunePhillips WI - DCL KY | B3: Freight Inbound | C3: IN | D3: 3416738 | E3: 43255 | F3: 06-2018 | G3: JUUL Pods Cool Cucumber 5.0% 2.8ml 4-pack | H3: 000636 | I3: 513000 | J3: HCORP-CRP-4600-JUL | K3: 315.25 | L3: 0 | M3: =K3-L3 -> 315.25 | N3: =VLOOKUP(D3,[1]Sheet1!$N:$O,2,0) -> 3416737 | O3: Freight Inbound ETA 6/1/18 ASTEELFLASH WI to Louisville KY | P3: Phillips WI - DCL KY | Q3: FLEX-290227-1 | R3: 43221 | S3: 43221 | T3: =MONTH(E3) -> 6 | U3: =IF(T3=6,"June",IF(T3=5,"May",IF(T3=4,"April",IF(T3=3,"March",0)))) -> June
A4: =U4&P4 -> JunePhillips WI - DCL KY | B4: Freight Inbound | C4: IN | D4: 3416738 | E4: 43255 | F4: 06-2018 | G4: JUUL pods Virginia Tobacco 5% 2.8ml 4-pack | H4: 000636 | I4: 513000 | J4: HCORP-CRP-4600-CRP | K4: 10.44 | L4: 0 | M4: =K4-L4 -> 10.44 | N4: =VLOOKUP(D4,[1]Sheet1!$N:$O,2,0) -> 3416737 | O4: Freight Inbound ETA 6/1/18 ASTEELFLASH WI to Louisville KY | P4: Phillips WI - DCL KY | Q4: FLEX-290227-1 | R4: 43221 | S4: 43221 | T4: =MONTH(E4) -> 6 | U4: =IF(T4=6,"June",IF(T4=5,"May",IF(T4=4,"April",IF(T4=3,"March",0)))) -> June
A5: =U5&P5 -> JunePhillips WI - DCL KY | B5: Freight Inbound | C5: IN | D5: 3416738 | E5: 43255 | F5: 06-2018 | G5: JUUL Pods Classic Menthol 5.0% 2.8ml 4-pack | H5: 000636 | I5: 513000 | J5: HCORP-CRP-4600-JUL | K5: 538.89 | L5: 0 | M5: =K5-L5 -> 538.89 | N5: =VLOOKUP(D5,[1]Sheet1!$N:$O,2,0) -> 3416737 | O5: Freight Inbound ETA 6/1/18 ASTEELFLASH WI to Louisville KY | P5: Phillips WI - DCL KY | Q5: FLEX-290227-1 | R5: 43221 | S5: 43221 | T5: =MONTH(E5) -> 6 | U5: =IF(T5=6,"June",IF(T5=5,"May",IF(T5=4,"April",IF(T5=3,"March",0)))) -> June
A6: =U6&P6 -> JunePhillips WI - DCL KY | B6: Freight Inbound | C6: IN | D6: 3416738 | E6: 43255 | F6: 06-2018 | G6: JUUL Pods Cool Cucumber 5.0% 2.8ml 4-pack | H6: 000636 | I6: 513000 | J6: HCORP-CRP-4600-JUL | K6: 943.06 | L6: 0 | M6: =K6-L6 -> 943.06 | N6: =VLOOKUP(D6,[1]Sheet1!$N:$O,2,0) -> 3416737 | O6: Freight Inbound ETA 6/1/18 ASTEELFLASH WI to Louisville KY | P6: Phillips WI - DCL KY | Q6: FLEX-290227-1 | R6: 43221 | S6: 43221 | T6: =MONTH(E6) -> 6 | U6: =IF(T6=6,"June",IF(T6=5,"May",IF(T6=4,"April",IF(T6=3,"March",0)))) -> June
A7: =U7&P7 -> JunePhillips WI - DCL KY | B7: Freight Inbound | C7: IN | D7: 3416738 | E7: 43255 | F7: 06-2018 | G7: JUUL pods Cool Mint 5% 2.8ml 4-pack | H7: 000636 | I7: 513000 | J7: HCORP-CRP-4600-JUL | K7: 3579.03 | L7: 0 | M7: =K7-L7 -> 3579.03 | N7: =VLOOKUP(D7,[1]Sheet1!$N:$O,2,0) -> 3416737 | O7: Freight Inbound ETA 6/1/18 ASTEELFLASH WI to Louisville KY | P7: Phillips WI - DCL KY | Q7: FLEX-290227-1 | R7: 43221 | S7: 43221 | T7: =MONTH(E7) -> 6 | U7: =IF(T7=6,"June",IF(T7=5,"May",IF(T7=4,"April",IF(T7=3,"March",0)))) -> June
A8: =U8&P8 -> JuneHong Kong - DCL KY | B8: Freight Inbound | C8: IN | D8: 3400596 | E8: 43256 | F8: 06-2018 | G8: JUUL Basic Kit Slate | H8: 000623 | I8: 513000 | J8: HCORP-CRP-4600-JUL | K8: 8147.9 | L8: 0 | M8: =K8-L8 -> 8147.9 | N8: =VLOOKUP(D8,[1]Sheet1!$N:$O,2,0) -> 3400595 | O8: Freight Inbound Delivered 05/31/18 Hong Kong - Louisville,KY | P8: Hong Kong - DCL KY | Q8: FLEX-290211-1 | R8: 43221 | S8: 43221 | T8: =MONTH(E8) -> 6 | U8: =IF(T8=6,"June",IF(T8=5,"May",IF(T8=4,"April",IF(T8=3,"March",0)))) -> June
A9: =U9&P9 -> JuneHong Kong - DCL KY | B9: Freight Inbound | C9: IN | D9: 3400596 | E9: 43256 | F9: 06-2018 | G9: JUUL Basic Kit Slate | H9: 000623 | I9: 513000 | J9: HCORP-CRP-4600-JUL | K9: 1527.73 | L9: 0 | M9: =K9-L9 -> 1527.73 | N9: =VLOOKUP(D9,[1]Sheet1!$N:$O,2,0) -> 3400595 | O9: Freight Inbound Delivered 05/31/18 Hong Kong - Louisville,KY | P9: Hong Kong - DCL KY | Q9: FLEX-290211-1 | R9: 43221 | S9: 43221 | T9: =MONTH(E9) -> 6 | U9: =IF(T9=6,"June",IF(T9=5,"May",IF(T9=4,"April",IF(T9=3,"March",0)))) -> June
A10: =U10&P10 -> JuneHong Kong - DCL KY | B10: Freight Inbound | C10: IN | D10: 3400596 | E10: 43256 | F10: 06-2018 | G10: JUUL Basic Kit Slate | H10: 000623 | I10: 513000 | J10: HCORP-CRP-4600-JUL | K10: 1320.85 | L10: 0 | M10: =K10-L10 -> 1320.85 | N10: =VLOOKUP(D10,[1]Sheet1!$N:$O,2,0) -> 3400595 | O10: Freight Inbound Delivered 05/31/18 Hong Kong - Louisville,KY | P10: Hong Kong - DCL KY | Q10: FLEX-290211-1 | R10: 43221 | S10: 43221 | T10: =MONTH(E10) -> 6 | U10: =IF(T10=6,"June",IF(T10=5,"May",IF(T10=4,"April",IF(T10=3,"March",0)))) -> June
A11: =U11&P11 -> JuneShanghai - DCL KY | B11: Freight Inbound | C11: IN | D11: 3400599 | E11: 43256 | F11: 06-2018 | G11: JUUL Basic Kit Slate | H11: 000624 | I11: 513000 | J11: HCORP-CRP-4600-JUL | K11: 9825.71 | L11: 0 | M11: =K11-L11 -> 9825.71 | N11: =VLOOKUP(D11,[1]Sheet1!$N:$O,2,0) -> 3400598 | O11: Freight Inbound Delivered 05/31/18 Shanghai-Louisville,KY | P11: Shanghai - DCL KY | Q11: FLEX-284476-1 | R11: 43221 | S11: 43221 | T11: =MONTH(E11) -> 6 | U11: =IF(T11=6,"June",IF(T11=5,"May",IF(T11=4,"April",IF(T11=3,"March",0)))) -> June
A12: =U12&P12 -> JuneShanghai - DECI NC | B12: Freight Inbound | C12: IN | D12: 3400601 | E12: 43256 | F12: 06-2018 | G12: JUUL Basic Kit for Starter Kit | H12: 000625 | I12: 513000 | J12: HCORP-CRP-4600-JUL | K12: 42574.46 | L12: 0 | M12: =K12-L12 -> 42574.46 | N12: =VLOOKUP(D12,[1]Sheet1!$N:$O,2,0) -> 3400600 | O12: Freight Inbound Delivered 05/29/18 Shanghai-Durham,NC | P12: Shanghai - DECI NC | Q12: FLEX-284466-1 | R12: 43221 | S12: 43221 | T12: =MONTH(E12) -> 6 | U12: =IF(T12=6,"June",IF(T12=5,"May",IF(T12=4,"April",IF(T12=3,"March",0)))) -> June
A13: =U13&P13 -> JuneShanghai - DECI NC | B13: Freight Inbound | C13: IN | D13: 3400601 | E13: 43256 | F13: 06-2018 | G13: JUUL Basic Kit for Starter Kit | H13: 000625 | I13: 513000 | J13: HCORP-CRP-4600-JUL | K13: 8676.33 | L13: 0 | M13: =K13-L13 -> 8676.33 | N13: =VLOOKUP(D13,[1]Sheet1!$N:$O,2,0) -> 3400600 | O13: Freight Inbound Delivered 05/29/18 Shanghai-Durham,NC | P13: Shanghai - DECI NC | Q13: FLEX-284466-1 | R13: 43221 | S13: 43221 | T13: =MONTH(E13) -> 6 | U13: =IF(T13=6,"June",IF(T13=5,"May",IF(T13=4,"April",IF(T13=3,"March",0)))) -> June
... A46: =U46&P46 -> JuneHong Kong - DCL KY | B46: Freight Inbound | C46: IN | D46: 3418782 | E46: 43273 | F46: 06-2018 | G46: JUUL USB Charger | H46: 000651 | I46: 513000 | J46: HCORP-CRP-4600-JUL | K46: 4202.32 | L46: 0 | M46: =K46-L46 -> 4202.32 | N46: =VLOOKUP(D46,[1]Sheet1!$N:$O,2,0) -> 3418781 | O46: Freight Inbound Delivered 6/15/18 Hong Kong-Louisville,KY | P46: Hong Kong - DCL KY | Q46: FLEX-251679-2 | R46: 43191 | S46: 43191 | T46: =MONTH(E46) -> 6 | U46: =IF(T46=6,"June",IF(T46=5,"May",IF(T46=4,"April",IF(T46=3,"March",0)))) -> June
A47: =U47&P47 -> MarchGreensboro NC - Phillips WI | B47: Freight Inbound | C47: AP | D47: 3395916 | E47: 43164 | F47: 06-2018 | G47: Shipping and Handling | H47: 1011158 | I47: 515000 | J47: HCORP-CRP-4600-JUL | K47: 1700 | L47: 0 | M47: =K47-L47 -> 1700 | O47: Shipping and Handling | P47: Greensboro NC - Phillips WI | Q47: 0001445 | R47: 43160 | S47: 43160 | T47: =MONTH(E47) -> 3 | U47: =IF(T47=6,"June",IF(T47=5,"May",IF(T47=4,"April",IF(T47=3,"March",0)))) -> March
A48: =U48&P48 -> MarchGreensboro NC - Phillips WI | B48: Freight Inbound | C48: AP | D48: 3386028 | E48: 43186 | F48: 06-2018 | G48: Freight Charges | H48: 1010838 | I48: 515000 | J48: HCORP-CRP-4600-JUL | K48: 1422.8 | L48: 0 | M48: =K48-L48 -> 1422.8 | O48: Shipping and Handling | P48: Greensboro NC - Phillips WI | Q48: 0001512 | R48: 43160 | S48: 43160 | T48: =MONTH(E48) -> 3 | U48: =IF(T48=6,"June",IF(T48=5,"May",IF(T48=4,"April",IF(T48=3,"March",0)))) -> March
A49: =U49&P49 -> AprilHong Kong - DECI NC | B49: Freight Inbound | C49: AP | D49: 3368458 | E49: 43194 | F49: 06-2018 | G49: Pallet Charges | H49: 1010008 | I49: 515000 | J49: HCORP-CRP-4600-JUL | K49: 30 | L49: 0 | M49: =K49-L49 -> 30 | O49: Pallet Charges | P49: Hong Kong - DECI NC | Q49: W2D18DN0011 | R49: 43191 | S49: 43191 | T49: =MONTH(E49) -> 4 | U49: =IF(T49=6,"June",IF(T49=5,"May",IF(T49=4,"April",IF(T49=3,"March",0)))) -> April
A50: =U50&P50 -> AprilHong Kong - DCL KY | B50: Freight Inbound | C50: AP | D50: 3358408 | E50: 43196 | F50: 06-2018 | G50: Freight Inbound | H50: 1010011 | I50: 515000 | J50: HCORP-CRP-4600-JUL | K50: 132 | L50: 0 | M50: =K50-L50 -> 132 | O50: Pallet Charges | P50: Hong Kong - DCL KY | Q50: W2D18DN0022 | R50: 43191 | S50: 43191 | T50: =MONTH(E50) -> 4 | U50: =IF(T50=6,"June",IF(T50=5,"May",IF(T50=4,"April",IF(T50=3,"March",0)))) -> April
A51: =U51&P51 -> AprilHong Kong - DCL KY | B51: Freight Inbound | C51: AP | D51: 3372874 | E51: 43196 | F51: 06-2018 | G51: Pallet Charges | H51: 1010305 | I51: 515000 | J51: HCORP-CRP-4600-JUL | K51: 48 | L51: 0 | M51: =K51-L51 -> 48 | O51: Pallet Charges | P51: Hong Kong - DCL KY | Q51: A2D18DN0004 | R51: 43191 | S51: 43191 | T51: =MONTH(E51) -> 4 | U51: =IF(T51=6,"June",IF(T51=5,"May",IF(T51=4,"April",IF(T51=3,"March",0)))) -> April
A52: =U52&P52 -> AprilAFG NC - DCL KY | B52: Freight Inbound | C52: AP | D52: 3371286 | E52: 43199 | F52: 06-2018 | G52: Freight Inbound-Rec 04/06/18 Morrisville,NC to Louisville,KY | H52: 1008448 | I52: 515000 | J52: NAUSA-CRP-4600-JUL | K52: 1675 | L52: 0 | M52: =K52-L52 -> 1675 | O52: Freight Inbound-Rec 04/06/18 Morrisville,NC to Louisville,KY | P52: AFG NC - DCL KY | Q52: S01178205 | R52: 43191 | S52: 43191 | T52: =MONTH(E52) -> 4 | U52: =IF(T52=6,"June",IF(T52=5,"May",IF(T52=4,"April",IF(T52=3,"March",0)))) -> April
A53: =U53&P53 -> AprilDECI NC - DCL KY | B53: Freight Inbound | C53: AP | D53: 3386039 | E53: 43202 | F53: 06-2018 | G53: Freight Inbound - Rec 04/19/18 Durham, NC to Louisville, KY | H53: 1010612 | I53: 515000 | J53: NAUSA-CRP-4600-JUL | K53: 1450 | L53: 0 | M53: =K53-L53 -> 1450 | O53: Freight Inbound - Rec 04/19/18 Durham, NC to Louisville, KY | P53: DECI NC - DCL KY | Q53: S01181251 | R53: 43191 | S53: 43191 | T53: =MONTH(E53) -> 4 | U53: =IF(T53=6,"June",IF(T53=5,"May",IF(T53=4,"April",IF(T53=3,"March",0)))) -> April
A54: =U54&P54 -> AprilHong Kong - DECI NC | B54: Freight Inbound | C54: AP | D54: 3368437 | E54: 43204 | F54: 06-2018 | G54: Pallet Charges | H54: 1010274 | I54: 515000 | J54: HCORP-CRP-4600-JUL | K54: 45 | L54: 0 | M54: =K54-L54 -> 45 | O54: Pallet Charges | P54: Hong Kong - DECI NC | Q54: W2D18DN0037 | R54: 43191 | S54: 43191 | T54: =MONTH(E54) -> 4 | U54: =IF(T54=6,"June",IF(T54=5,"May",IF(T54=4,"April",IF(T54=3,"March",0)))) -> April
A55: =U55&P55 -> MayChicago IL - Phillips WI | B55: Freight Inbound | C55: AP | D55: 3364813 | E55: 43224 | F55: 06-2018 | G55: Bemis Lot Freight Charges | H55: 1010152 | I55: 515000 | J55: HCORP-CRP-4600-JUL | K55: 378.67 | L55: 0 | M55: =K55-L55 -> 378.67 | O55: Freight Charge | P55: Chicago IL - Phillips WI | Q55: 90924544 | R55: 43221 | S55: 43221 | T55: =MONTH(E55) -> 5 | U55: =IF(T55=6,"June",IF(T55=5,"May",IF(T55=4,"April",IF(T55=3,"March",0)))) -> May
A56: =U56&P56 -> MayHong Kong - DCL KY | B56: Freight Inbound | C56: AP | D56: 3368293 | E56: 43225 | F56: 06-2018 | G56: Pallet Charges | H56: 1010270 | I56: 515000 | J56: HCORP-CRP-4600-JUL | K56: 48 | L56: 0 | M56: =K56-L56 -> 48 | O56: Pallet Charges | P56: Hong Kong - DCL KY | Q56: W2E18DN0014 | R56: 43221 | S56: 43221 | T56: =MONTH(E56) -> 5 | U56: =IF(T56=6,"June",IF(T56=5,"May",IF(T56=4,"April",IF(T56=3,"March",0)))) -> May
A57: =U57&P57 -> MayHong Kong - Phillips WI | B57: Freight Inbound | C57: AP | D57: 3368372 | E57: 43225 | F57: 06-2018 | G57: Pallet Charges | H57: 1010272 | I57: 515000 | J57: HCORP-CRP-4600-JUL | K57: 72 | L57: 0 | M57: =K57-L57 -> 72 | O57: Pallet Charges | P57: Hong Kong - Phillips WI | Q57: W2E18DN0015 | R57: 43221 | S57: 43221 | T57: =MONTH(E57) -> 5 | U57: =IF(T57=6,"June",IF(T57=5,"May",IF(T57=4,"April",IF(T57=3,"March",0)))) -> May
A58: =U58&P58 -> MayHong Kong - DECI NC | B58: Freight Inbound | C58: AP | D58: 3400379 | E58: 43231 | F58: 06-2018 | G58: Pallets SD 5/13/18 | H58: 1011288 | I58: 515000 | J58: HCORP-CRP-6000-JUL | K58: 48 | L58: 0 | M58: =K58-L58 -> 48 | O58: Pallet Charges | P58: Hong Kong - DECI NC | Q58: W2EI8DN0028 | R58: 43221 | S58: 43221 | T58: =MONTH(E58) -> 5 | U58: =IF(T58=6,"June",IF(T58=5,"May",IF(T58=4,"April",IF(T58=3,"March",0)))) -> May
A59: =U59&P59 -> MayHong Kong - DCL KY | B59: Freight Inbound | C59: AP | D59: 3368424 | E59: 43235 | F59: 06-2018 | G59: Pallet Charges | H59: 1010266 | I59: 515000 | J59: HCORP-CRP-4600-JUL | K59: 96 | L59: 0 | M59: =K59-L59 -> 96 | O59: Pallet Charges | P59: Hong Kong - DCL KY | Q59: W2E18DN0029 | R59: 43221 | S59: 43221 | T59: =MONTH(E59) -> 5 | U59: =IF(T59=6,"June",IF(T59=5,"May",IF(T59=4,"April",IF(T59=3,"March",0)))) -> May
A60: =U60&P60 -> MayHong Kong - DCL KY | B60: Freight Inbound | C60: AP | D60: 3368666 | E60: 43245 | F60: 06-2018 | G60: Pallet Charges | H60: 1010022 | I60: 515000 | J60: HCORP-CRP-4600-JUL | K60: 60 | L60: 0 | M60: =K60-L60 -> 60 | O60: Pallet Charges | P60: Hong Kong - DCL KY | Q60: A2E18DN0048 | R60: 43221 | S60: 43221 | T60: =MONTH(E60) -> 5 | U60: =IF(T60=6,"June",IF(T60=5,"May",IF(T60=4,"April",IF(T60=3,"March",0)))) -> May
A61: =U61&P61 -> MayHong Kong - Phillips WI | B61: Freight Inbound | C61: AP | D61: 3368667 | E61: 43245 | F61: 06-2018 | G61: Pallet Charges | H61: 1010025 | I61: 515000 | J61: HCORP-CRP-4600-JUL | K61: 36 | L61: 0 | M61: =K61-L61 -> 36 | O61: Pallet Charges | P61: Hong Kong - Phillips WI | Q61: W2E18DN0049 | R61: 43221 | S61: 43221 | T61: =MONTH(E61) -> 5 | U61: =IF(T61=6,"June",IF(T61=5,"May",IF(T61=4,"April",IF(T61=3,"March",0)))) -> May
A62: =U62&P62 -> MayHong Kong - DCL KY | B62: Freight Inbound | C62: AP | D62: 3368668 | E62: 43245 | F62: 06-2018 | G62: Pallet Charges | H62: 1010034 | I62: 515000 | J62: HCORP-CRP-4600-JUL | K62: 72 | L62: 0 | M62: =K62-L62 -> 72 | O62: Pallet Charges | P62: Hong Kong - DCL KY | Q62: W2E18DN0048 | R62: 43221 | S62: 43221 | T62: =MONTH(E62) -> 5 | U62: =IF(T62=6,"June",IF(T62=5,"May",IF(T62=4,"April",IF(T62=3,"March",0)))) -> May
A63: =U63&P63 -> MayHong Kong - Phillips WI | B63: Freight Inbound | C63: AP | D63: 3368672 | E63: 43245 | F63: 06-2018 | G63: Pallet Charges | H63: 1010279 | I63: 515000 | J63: HCORP-CRP-4600-JUL | K63: 36 | L63: 0 | M63: =K63-L63 -> 36 | O63: Pallet Charges | P63: Hong Kong - Phillips WI | Q63: W2E18DN0047 | R63: 43221 | S63: 43221 | T63: =MONTH(E63) -> 5 | U63: =IF(T63=6,"June",IF(T63=5,"May",IF(T63=4,"April",IF(T63=3,"March",0)))) -> May
A64: =U64&P64 -> JuneHong Kong - DCL KY | B64: Freight Inbound | C64: AP | D64: 3381658 | E64: 43252 | F64: 06-2018 | G64: Freight Inbound | H64: 1010566 | I64: 515000 | J64: HCORP-CRP-4600-JUL | K64: 48 | L64: 0 | M64: =K64-L64 -> 48 | O64: Pallet Charges | P64: Hong Kong - DCL KY | Q64: A2F18DN0005 | R64: 43252 | S64: 43252 | T64: =MONTH(E64) -> 6 | U64: =IF(T64=6,"June",IF(T64=5,"May",IF(T64=4,"April",IF(T64=3,"March",0)))) -> June
A65: =U65&P65 -> JuneHong Kong - Phillips WI | B65: Freight Inbound | C65: AP | D65: 3381659 | E65: 43252 | F65: 06-2018 | G65: Pallet Charges | H65: 1010583 | I65: 515000 | J65: HCORP-CRP-4600-JUL | K65: 12 | L65: 0 | M65: =K65-L65 -> 12 | O65: Pallet Charges | P65: Hong Kong - Phillips WI | Q65: A2F18DN0006 | R65: 43252 | S65: 43252 | T65: =MONTH(E65) -> 6 | U65: =IF(T65=6,"June",IF(T65=5,"May",IF(T65=4,"April",IF(T65=3,"March",0)))) -> June
A66: =U66&P66 -> JuneHong Kong - Flex IL | B66: Freight Inbound | C66: AP | D66: 3381660 | E66: 43253 | F66: 06-2018 | G66: Pallet Charges | H66: 1010563 | I66: 515000 | J66: HCORP-CRP-4600-JUL | K66: 36 | L66: 0 | M66: =K66-L66 -> 36 | O66: Pallet Charges | P66: Hong Kong - Flex IL | Q66: W2F18DN0005 | R66: 43252 | S66: 43252 | T66: =MONTH(E66) -> 6 | U66: =IF(T66=6,"June",IF(T66=5,"May",IF(T66=4,"April",IF(T66=3,"March",0)))) -> June
A67: =U67&P67 -> JuneHong Kong - Phillips WI | B67: Freight Inbound | C67: AP | D67: 3381661 | E67: 43253 | F67: 06-2018 | G67: Pallet Charges | H67: 1010564 | I67: 515000 | J67: HCORP-CRP-4600-JUL | K67: 48 | L67: 0 | M67: =K67-L67 -> 48 | O67: Pallet Charges | P67: Hong Kong - Phillips WI | Q67: W2F18DN0003 | R67: 43252 | S67: 43252 | T67: =MONTH(E67) -> 6 | U67: =IF(T67=6,"June",IF(T67=5,"May",IF(T67=4,"April",IF(T67=3,"March",0)))) -> June
... A72: =U72&P72 -> JuneHong Kong - Flex IL | B72: Freight Inbound | C72: AP | D72: 3403192 | E72: 43266 | F72: 06-2018 | G72: Pallet Charges | H72: 1011193 | I72: 515000 | J72: HCORP-CRP-4600-JUL | K72: 48 | L72: 0 | M72: =K72-L72 -> 48 | O72: Pallet Charges | P72: Hong Kong - Flex IL | Q72: A2F18DN0017 | R72: 43252 | S72: 43252 | T72: =MONTH(E72) -> 6 | U72: =IF(T72=6,"June",IF(T72=5,"May",IF(T72=4,"April",IF(T72=3,"March",0)))) -> June
A73: =U73&P73 -> MayAFG Suzho - DECI NC | B73: Freight Inbound | C73: GL | D73: 3381526 | E73: 43230 | F73: 06-2018 | G73: May 2018 Freight and Fulfillment Accrual Adjustment | H73: FLEXPORT | I73: 515000 | J73: HCORP-CRP-4600-JUL | K73: 6065.83 | L73: 0 | M73: =K73-L73 -> 6065.83 | P73: AFG Suzho - DECI NC | Q73: FLEX-260024-2 | R73: 43191 | S73: 43221 | T73: =MONTH(E73) -> 5 | U73: =IF(T73=6,"June",IF(T73=5,"May",IF(T73=4,"April",IF(T73=3,"March",0)))) -> May
A74: =U74&P74 -> MayAFG Suzho - DCL KY | B74: Freight Inbound | C74: GL | D74: 3381526 | E74: 43239 | F74: 06-2018 | G74: May 2018 Freight and Fulfillment Accrual Adjustment | H74: FLEXPORT | I74: 515000 | J74: HCORP-CRP-4600-JUL | K74: 73190.63 | L74: 0 | M74: =K74-L74 -> 73190.63 | P74: AFG Suzho - DCL KY | Q74: FLEX-269916-1 | R74: 43221 | S74: 43221 | T74: =MONTH(E74) -> 5 | U74: =IF(T74=6,"June",IF(T74=5,"May",IF(T74=4,"April",IF(T74=3,"March",0)))) -> May
A75: =U75&P75 -> MayAFG Suzho - DCL KY | B75: Freight Inbound | C75: GL | D75: 3381526 | E75: 43246 | F75: 06-2018 | G75: May 2018 Freight and Fulfillment Accrual Adjustment | H75: FLEXPORT | I75: 515000 | J75: HCORP-CRP-4600-JUL | K75: 9984.53 | L75: 0 | M75: =K75-L75 -> 9984.53 | P75: AFG Suzho - DCL KY | Q75: FLEX-269924-1 | R75: 43221 | S75: 43221 | T75: =MONTH(E75) -> 5 | U75: =IF(T75=6,"June",IF(T75=5,"May",IF(T75=4,"April",IF(T75=3,"March",0)))) -> May
A76: =U76&P76 -> MayHong Kong - DECI NC | B76: Freight Inbound | C76: GL | D76: 3381526 | E76: 43246 | F76: 06-2018 | G76: May 2018 Freight and Fulfillment Accrual Adjustment | H76: FLEXPORT | I76: 515000 | J76: HCORP-CRP-4600-JUL | K76: 7102.8 | L76: 0 | M76: =K76-L76 -> 7102.8 | P76: Hong Kong - DECI NC | Q76: FLEX-275538-1 | R76: 43221 | S76: 43221 | T76: =MONTH(E76) -> 5 | U76: =IF(T76=6,"June",IF(T76=5,"May",IF(T76=4,"April",IF(T76=3,"March",0)))) -> May
A77: =U77&P77 -> MayAFG Suzho - DECI NC | B77: Freight Inbound | C77: GL | D77: 3381526 | E77: 43246 | F77: 06-2018 | G77: May 2018 Freight and Fulfillment Accrual Adjustment | H77: FLEXPORT | I77: 515000 | J77: HCORP-CRP-4600-JUL | K77: 57591.86 | L77: 0 | M77: =K77-L77 -> 57591.86 | P77: AFG Suzho - DECI NC | Q77: FLEX-276804-1 | R77: 43221 | S77: 43221 | T77: =MONTH(E77) -> 5 | U77: =IF(T77=6,"June",IF(T77=5,"May",IF(T77=4,"April",IF(T77=3,"March",0)))) -> May
A78: =U78&P78 -> MayAFG Suzho - DCL KY | B78: Freight Inbound | C78: GL | D78: 3381526 | E78: 43246 | F78: 06-2018 | G78: May 2018 Freight and Fulfillment Accrual Adjustment | H78: FLEXPORT | I78: 515000 | J78: HCORP-CRP-4600-JUL | K78: 18009.23 | L78: 0 | M78: =K78-L78 -> 18009.23 | P78: AFG Suzho - DCL KY | Q78: FLEX-276807-1 | R78: 43221 | S78: 43221 | T78: =MONTH(E78) -> 5 | U78: =IF(T78=6,"June",IF(T78=5,"May",IF(T78=4,"April",IF(T78=3,"March",0)))) -> May
A79: =U79&P79 -> MayAFG Suzho - DECI NC | B79: Freight Inbound | C79: GL | D79: 3381526 | E79: 43246 | F79: 06-2018 | G79: May 2018 Freight and Fulfillment Accrual Adjustment | H79: FLEXPORT | I79: 515000 | J79: HCORP-CRP-4600-JUL | K79: 49366.27 | L79: 0 | M79: =K79-L79 -> 49366.27 | P79: AFG Suzho - DECI NC | Q79: FLEX-276812-1 | R79: 43221 | S79: 43221 | T79: =MONTH(E79) -> 5 | U79: =IF(T79=6,"June",IF(T79=5,"May",IF(T79=4,"April",IF(T79=3,"March",0)))) -> May
A80: =U80&P80 -> JuneAFG Suzho - DECI NC | B80: Freight Inbound | C80: GL | D80: 3381526 | E80: 43263 | F80: 06-2018 | G80: May 2018 Freight and Fulfillment Accrual Adjustment | H80: FLEXPORT | I80: 515000 | J80: HCORP-CRP-4600-JUL | K80: 52338.18 | L80: 0 | M80: =K80-L80 -> 52338.18 | P80: AFG Suzho - DECI NC | Q80: FLEX-276828-1 | R80: 43221 | S80: 43221 | T80: =MONTH(E80) -> 6 | U80: =IF(T80=6,"June",IF(T80=5,"May",IF(T80=4,"April",IF(T80=3,"March",0)))) -> June
A81: =U81&P81 -> MayDCL KY - Ontario Can | B81: Freight Inbound | C81: GL | D81: 3381526 | E81: 43246 | F81: 06-2018 | G81: May 2018 Freight and Fulfillment Accrual Adjustment | H81: FLEXPORT | I81: 515000 | J81: HCORP-CRP-4600-JUL | K81: 3781.09 | L81: 0 | M81: =K81-L81 -> 3781.09 | P81: DCL KY - Ontario Can | Q81: FLEX-281123-1 | R81: 43221 | S81: 43221 | T81: =MONTH(E81) -> 5 | U81: =IF(T81=6,"June",IF(T81=5,"May",IF(T81=4,"April",IF(T81=3,"March",0)))) -> May
A82: =U82&P82 -> MayHong Kong - Phillips WI | B82: Freight Inbound | C82: GL | D82: 3381526 | E82: 43246 | F82: 06-2018 | G82: May 2018 Freight and Fulfillment Accrual Adjustment | H82: FLEXPORT | I82: 515000 | J82: HCORP-CRP-4600-JUL | K82: 16928.59 | L82: 0 | M82: =K82-L82 -> 16928.59 | P82: Hong Kong - Phillips WI | Q82: FLEX-282790-1 | R82: 43221 | S82: 43221 | T82: =MONTH(E82) -> 5 | U82: =IF(T82=6,"June",IF(T82=5,"May",IF(T82=4,"April",IF(T82=3,"March",0)))) -> May
A83: =U83&P83 -> JuneHong Kong - DECI NC | B83: Freight Inbound | C83: GL | D83: 3381526 | E83: 43263 | F83: 06-2018 | G83: May 2018 Freight and Fulfillment Accrual Adjustment | H83: FLEXPORT | I83: 515000 | J83: HCORP-CRP-4600-JUL | K83: 7412.97 | L83: 0 | M83: =K83-L83 -> 7412.97 | P83: Hong Kong - DECI NC | Q83: FLEX-282819-1 | R83: 43221 | S83: 43221 | T83: =MONTH(E83) -> 6 | U83: =IF(T83=6,"June",IF(T83=5,"May",IF(T83=4,"April",IF(T83=3,"March",0)))) -> June
A84: =U84&P84 -> MayHong Kong - Phillips WI | B84: Freight Inbound | C84: GL | D84: 3381526 | E84: 43246 | F84: 06-2018 | G84: May 2018 Freight and Fulfillment Accrual Adjustment | H84: FLEXPORT | I84: 515000 | J84: HCORP-CRP-4600-JUL | K84: 9461.81 | L84: 0 | M84: =K84-L84 -> 9461.81 | P84: Hong Kong - Phillips WI | Q84: FLEX-282827-1 | R84: 43221 | S84: 43221 | T84: =MONTH(E84) -> 5 | U84: =IF(T84=6,"June",IF(T84=5,"May",IF(T84=4,"April",IF(T84=3,"March",0)))) -> May
... A128: =U128&P128 -> MayPhillips WI - DCL KY | B128: Freight Inbound | C128: GL | D128: 3410206 | E128: 43244 | F128: 06-2018 | G128: June 2018 Freight and Fulfillment Accrual | H128: K+N | I128: 515000 | J128: NAUSA-CRP-4600-JUL | K128: -5825 | L128: 0 | M128: =K128-L128 -> -5825 | P128: Phillips WI - DCL KY | Q128: LAXFO18050287 | R128: 43221 | S128: 43221 | T128: =MONTH(E128) -> 5 | U128: =IF(T128=6,"June",IF(T128=5,"May",IF(T128=4,"April",IF(T128=3,"March",0)))) -> May
A129: =U129&P129 -> #VALUE! | C129: Module | D129: Batch Number | E129: Tran. Date | F129: Period | G129: Description | H129: Ref. Number | I129: Account | J129: Subaccount | K129: Debit Amount | L129: Credit Amount | M129: Net Activity | N129: Reclass. Batch Number | O129: Freight Full Comments | P129: Freight Code | Q129: Invoice | R129: Ship Month | S129: Rec Month | T129: =MONTH(E129) -> #VALUE! | U129: =IF(T129=6,"June",IF(T129=5,"May",IF(T129=4,"April",IF(T129=3,"March",0)))) -> #VALUE!
A130: =U130&P130 -> MarchHong Kong - AFG NC | B130: Freight Inbound | C130: AP | D130: 3353216 | E130: 43160 | F130: 05-2018 | G130: Freight Inbound | H130: 1006462 | I130: 515000 | J130: HCORP-CRP-4600-JUL | K130: 72 | L130: 0 | M130: =K130-L130 -> 72 | O130: =G130 -> Freight Inbound | P130: Hong Kong - AFG NC | Q130: W2B18DN0100 | R130: 43132 | S130: 43132 | T130: =MONTH(E130) -> 3 | U130: =IF(T130=6,"June",IF(T130=5,"May",IF(T130=4,"April",IF(T130=3,"March",0)))) -> March
A131: =U131&P131 -> MarchHong Kong - DCL KY | B131: Freight Inbound | C131: AP | D131: 3346582 | E131: 43161 | F131: 05-2018 | G131: Pallet Charges | H131: 1009610 | I131: 515000 | J131: HCORP-CRP-4600-JUL | K131: 48 | L131: 0 | M131: =K131-L131 -> 48 | O131: =G131 -> Pallet Charges | P131: Hong Kong - DCL KY | Q131: W2C18DN0019 | R131: 43160 | S131: 43160 | T131: =MONTH(E131) -> 3 | U131: =IF(T131=6,"June",IF(T131=5,"May",IF(T131=4,"April",IF(T131=3,"March",0)))) -> March
A132: =U132&P132 -> MarchHong Kong - DCL KY | B132: Freight Inbound | C132: AP | D132: 3342417 | E132: 43168 | F132: 05-2018 | G132: Freight Charge | H132: 1009360 | I132: 515000 | J132: HCORP-CRP-4600-JUL | K132: 741.66 | L132: 0 | M132: =K132-L132 -> 741.66 | O132: =G132 -> Freight Charge | P132: Hong Kong - DCL KY | R132: 43160 | S132: 43160 | T132: =MONTH(E132) -> 3 | U132: =IF(T132=6,"June",IF(T132=5,"May",IF(T132=4,"April",IF(T132=3,"March",0)))) -> March
A133: =U133&P133 -> MarchHong Kong - DCL KY | B133: Freight Inbound | C133: AP | D133: 3346584 | E133: 43168 | F133: 05-2018 | G133: Pallet Charges | H133: 1009614 | I133: 515000 | J133: HCORP-CRP-4600-JUL | K133: 24 | L133: 0 | M133: =K133-L133 -> 24 | O133: =G133 -> Pallet Charges | P133: Hong Kong - DCL KY | R133: 43160 | S133: 43160 | T133: =MONTH(E133) -> 3 | U133: =IF(T133=6,"June",IF(T133=5,"May",IF(T133=4,"April",IF(T133=3,"March",0)))) -> March
A134: =U134&P134 -> MarchAFG NC - DCL KY | B134: Freight Inbound | C134: AP | D134: 3346472 | E134: 43185 | F134: 05-2018 | G134: Freight Inbound-Rec 03/21/18 Morrisville,NC to Louisville,KY | H134: 1009618 | I134: 515000 | J134: NAUSA-CRP-4600-JUL | K134: 1725 | L134: 0 | M134: =K134-L134 -> 1725 | O134: =G134 -> Freight Inbound-Rec 03/21/18 Morrisville,NC to Louisville,KY | P134: AFG NC - DCL KY | R134: 43160 | S134: 43160 | T134: =MONTH(E134) -> 3 | U134: =IF(T134=6,"June",IF(T134=5,"May",IF(T134=4,"April",IF(T134=3,"March",0)))) -> March
A135: =U135&P135 -> AprilAFG NC - DCL KY | B135: Freight Inbound | C135: AP | D135: 3346451 | E135: 43214 | F135: 05-2018 | G135: Freight Inbound ETA 04/24/18 ASTEELFLASH NC to Louisville KY | H135: 1009535 | I135: 515000 | J135: NAUSA-CRP-4600-JUL | K135: 3100 | L135: 0 | M135: =K135-L135 -> 3100 | O135: =G135 -> Freight Inbound ETA 04/24/18 ASTEELFLASH NC to Louisville KY | P135: AFG NC - DCL KY | R135: 43191 | S135: 43191 | T135: =MONTH(E135) -> 4 | U135: =IF(T135=6,"June",IF(T135=5,"May",IF(T135=4,"April",IF(T135=3,"March",0)))) -> April
A136: =U136&P136 -> AprilAFG NC - DCL KY | B136: Freight Inbound | C136: AP | D136: 3346442 | E136: 43216 | F136: 05-2018 | G136: Freight Inbound ETA 04/26/18 ASTEELFLASH NC to Louisville KY | H136: 1009484 | I136: 515000 | J136: NAUSA-CRP-4600-JUL | K136: 4650 | L136: 0 | M136: =K136-L136 -> 4650 | O136: =G136 -> Freight Inbound ETA 04/26/18 ASTEELFLASH NC to Louisville KY | P136: AFG NC - DCL KY | R136: 43191 | S136: 43191 | T136: =MONTH(E136) -> 4 | U136: =IF(T136=6,"June",IF(T136=5,"May",IF(T136=4,"April",IF(T136=3,"March",0)))) -> April
A137: =U137&P137 -> AprilAFG NC - DCL KY | B137: Freight Inbound | C137: AP | D137: 3346446 | E137: 43216 | F137: 05-2018 | G137: Freight Inbound ETA 04/26/18 ASTEELFLASH NC to Louisville KY | H137: 1009526 | I137: 515000 | J137: NAUSA-CRP-4600-JUL | K137: 4650 | L137: 0 | M137: =K137-L137 -> 4650 | O137: =G137 -> Freight Inbound ETA 04/26/18 ASTEELFLASH NC to Louisville KY | P137: AFG NC - DCL KY | R137: 43191 | S137: 43191 | T137: =MONTH(E137) -> 4 | U137: =IF(T137=6,"June",IF(T137=5,"May",IF(T137=4,"April",IF(T137=3,"March",0)))) -> April
A138: =U138&P138 -> AprilAFG NC - DCL KY | B138: Freight Inbound | C138: AP | D138: 3346471 | E138: 43216 | F138: 05-2018 | G138: Freight Inbound-Rec 04/19/18 Morrisville,NC to Louisville,KY | H138: 1009616 | I138: 515000 | J138: NAUSA-CRP-4600-JUL | K138: 1675 | L138: 0 | M138: =K138-L138 -> 1675 | O138: =G138 -> Freight Inbound-Rec 04/19/18 Morrisville,NC to Louisville,KY | P138: AFG NC - DCL KY | R138: 43191 | S138: 43191 | T138: =MONTH(E138) -> 4 | U138: =IF(T138=6,"June",IF(T138=5,"May",IF(T138=4,"April",IF(T138=3,"March",0)))) -> April
A139: =U139&P139 -> AprilAFG NC - DCL KY | B139: Freight Inbound | C139: AP | D139: 3346467 | E139: 43217 | F139: 05-2018 | G139: Freight Inbound-Rec 04/24/18 Morrisville,NC to Louisville,KY | H139: 1009605 | I139: 515000 | J139: NAUSA-CRP-4600-JUL | K139: 1675 | L139: 0 | M139: =K139-L139 -> 1675 | O139: =G139 -> Freight Inbound-Rec 04/24/18 Morrisville,NC to Louisville,KY | P139: AFG NC - DCL KY | R139: 43191 | S139: 43191 | T139: =MONTH(E139) -> 4 | U139: =IF(T139=6,"June",IF(T139=5,"May",IF(T139=4,"April",IF(T139=3,"March",0)))) -> April
A140: =U140&P140 -> AprilAFG NC - DCL KY | B140: Freight Inbound | C140: AP | D140: 3346468 | E140: 43217 | F140: 05-2018 | G140: Freight Inbound-Rec 04/22/18 Morrisville,NC to Louisville,KY | H140: 1009606 | I140: 515000 | J140: NAUSA-CRP-4600-JUL | K140: 1675 | L140: 0 | M140: =K140-L140 -> 1675 | O140: =G140 -> Freight Inbound-Rec 04/22/18 Morrisville,NC to Louisville,KY | P140: AFG NC - DCL KY | R140: 43191 | S140: 43191 | T140: =MONTH(E140) -> 4 | U140: =IF(T140=6,"June",IF(T140=5,"May",IF(T140=4,"April",IF(T140=3,"March",0)))) -> April
A141: =U141&P141 -> AprilAFG NC - DCL KY | B141: Freight Inbound | C141: AP | D141: 3346469 | E141: 43217 | F141: 05-2018 | G141: Freight Inbound-Rec 04/21/18 Morrisville,NC to Louisville,KY | H141: 1009609 | I141: 515000 | J141: NAUSA-CRP-4600-JUL | K141: 1675 | L141: 0 | M141: =K141-L141 -> 1675 | O141: =G141 -> Freight Inbound-Rec 04/21/18 Morrisville,NC to Louisville,KY | P141: AFG NC - DCL KY | R141: 43191 | S141: 43191 | T141: =MONTH(E141) -> 4 | U141: =IF(T141=6,"June",IF(T141=5,"May",IF(T141=4,"April",IF(T141=3,"March",0)))) -> April
A142: =U142&P142 -> AprilAFG NC - DCL KY | B142: Freight Inbound | C142: AP | D142: 3346470 | E142: 43217 | F142: 05-2018 | G142: Freight Inbound-Rec 04/17/18 Morrisville,NC to Louisville,KY | H142: 1009611 | I142: 515000 | J142: NAUSA-CRP-4600-JUL | K142: 1675 | L142: 0 | M142: =K142-L142 -> 1675 | O142: =G142 -> Freight Inbound-Rec 04/17/18 Morrisville,NC to Louisville,KY | P142: AFG NC - DCL KY | R142: 43191 | S142: 43191 | T142: =MONTH(E142) -> 4 | U142: =IF(T142=6,"June",IF(T142=5,"May",IF(T142=4,"April",IF(T142=3,"March",0)))) -> April
A143: =U143&P143 -> AprilAFG NC - DCL KY | B143: Freight Inbound | C143: AP | D143: 3346438 | E143: 43220 | F143: 05-2018 | G143: Freight Inbound ETA 04/29/18 ASTEELFLASH NC to Louisville KY | H143: 1009477 | I143: 515000 | J143: NAUSA-CRP-4600-JUL | K143: 3100 | L143: 0 | M143: =K143-L143 -> 3100 | O143: =G143 -> Freight Inbound ETA 04/29/18 ASTEELFLASH NC to Louisville KY | P143: AFG NC - DCL KY | R143: 43191 | S143: 43191 | T143: =MONTH(E143) -> 4 | U143: =IF(T143=6,"June",IF(T143=5,"May",IF(T143=4,"April",IF(T143=3,"March",0)))) -> April
... A145: =U145&P145 -> AprilAFG NC - DCL KY | B145: Freight Inbound | C145: AP | D145: 3346450 | E145: 43220 | F145: 05-2018 | G145: Freight Inbound ETA 04/27/18 ASTEELFLASH NC to Louisville KY | H145: 1009534 | I145: 515000 | J145: NAUSA-CRP-4600-JUL | K145: 4650 | L145: 0 | M145: =K145-L145 -> 4650 | O145: =G145 -> Freight Inbound ETA 04/27/18 ASTEELFLASH NC to Louisville KY | P145: AFG NC - DCL KY | R145: 43191 | S145: 43191 | T145: =MONTH(E145) -> 4 | U145: =IF(T145=6,"June",IF(T145=5,"May",IF(T145=4,"April",IF(T145=3,"March",0)))) -> April
A146: =U146&P146 -> MayHong Kong - DECI NC | B146: Freight Inbound | C146: AP | D146: 3336225 | E146: 43223 | F146: 05-2018 | G146: Pallet Charges | H146: 1009123 | I146: 515000 | J146: HCORP-CRP-4600-JUL | K146: 60 | L146: 0 | M146: =K146-L146 -> 60 | O146: =G146 -> Pallet Charges | P146: Hong Kong - DECI NC | Q146: W2E18DN0008 | R146: 43221 | S146: 43221 | T146: =MONTH(E146) -> 5 | U146: =IF(T146=6,"June",IF(T146=5,"May",IF(T146=4,"April",IF(T146=3,"March",0)))) -> May
A147: =U147&P147 -> MayFlex IL - Flex IL | B147: Freight Inbound | C147: AP | D147: 3346449 | E147: 43223 | F147: 05-2018 | G147: Freight Inbound ETA 05/02/18 Chippewa/Flex Buffalo Grove, IL | H147: 1009533 | I147: 515000 | J147: NAUSA-CRP-4600-JUL | K147: 1250 | L147: 0 | M147: =K147-L147 -> 1250 | O147: =G147 -> Freight Inbound ETA 05/02/18 Chippewa/Flex Buffalo Grove, IL | P147: Flex IL - Flex IL | R147: 43221 | S147: 43221 | T147: =MONTH(E147) -> 5 | U147: =IF(T147=6,"June",IF(T147=5,"May",IF(T147=4,"April",IF(T147=3,"March",0)))) -> May
A148: =U148&P148 -> MayHong Kong - AFG NC | B148: Freight Inbound | C148: AP | D148: 3336158 | E148: 43231 | F148: 05-2018 | G148: Pallet Charges | H148: 1009213 | I148: 515000 | J148: HCORP-CRP-4600-JUL | K148: 48 | L148: 0 | M148: =K148-L148 -> 48 | O148: =G148 -> Pallet Charges | P148: Hong Kong - AFG NC | R148: 43221 | S148: 43221 | T148: =MONTH(E148) -> 5 | U148: =IF(T148=6,"June",IF(T148=5,"May",IF(T148=4,"April",IF(T148=3,"March",0)))) -> May
A149: =U149&P149 -> MayHong Kong - AFG NC | B149: Freight Inbound | C149: AP | D149: 3353218 | E149: 43231 | F149: 05-2018 | G149: Pallet Charges | H149: 1009784 | I149: 515000 | J149: HCORP-CRP-4600-JUL | K149: 60 | L149: 0 | M149: =K149-L149 -> 60 | O149: =G149 -> Pallet Charges | P149: Hong Kong - AFG NC | R149: 43221 | S149: 43221 | T149: =MONTH(E149) -> 5 | U149: =IF(T149=6,"June",IF(T149=5,"May",IF(T149=4,"April",IF(T149=3,"March",0)))) -> May
A150: =U150&P150 -> MayHong Kong - AFG NC | B150: Freight Inbound | C150: AP | D150: 3355368 | E150: 43231 | F150: 05-2018 | G150: Pallet Charges | H150: 1009814 | I150: 515000 | J150: HCORP-CRP-4600-JUL | K150: 60 | L150: 0 | M150: =K150-L150 -> 60 | O150: =G150 -> Pallet Charges | P150: Hong Kong - AFG NC | R150: 43221 | S150: 43221 | T150: =MONTH(E150) -> 5 | U150: =IF(T150=6,"June",IF(T150=5,"May",IF(T150=4,"April",IF(T150=3,"March",0)))) -> May
A151: =U151&P151 -> MayDECI NC - DCL KY | B151: Freight Inbound | C151: AP | D151: 3346435 | E151: 43234 | F151: 05-2018 | G151: Freight Inbound ETA 05/09/18 DECI NC to Louisville KY | H151: 1009463 | I151: 515000 | J151: NAUSA-CRP-4600-JUL | K151: 1725 | L151: 0 | M151: =K151-L151 -> 1725 | O151: =G151 -> Freight Inbound ETA 05/09/18 DECI NC to Louisville KY | P151: DECI NC - DCL KY | R151: 43221 | S151: 43221 | T151: =MONTH(E151) -> 5 | U151: =IF(T151=6,"June",IF(T151=5,"May",IF(T151=4,"April",IF(T151=3,"March",0)))) -> May
A152: =U152&P152 -> MayAFG NC - DCL KY | B152: Freight Inbound | C152: AP | D152: 3346436 | E152: 43234 | F152: 05-2018 | G152: Freight Inbound ETA 05/03/18 ASTEELFLASH NC to Louisville KY | H152: 1009469 | I152: 515000 | J152: NAUSA-CRP-4600-JUL | K152: 4650 | L152: 0 | M152: =K152-L152 -> 4650 | O152: =G152 -> Freight Inbound ETA 05/03/18 ASTEELFLASH NC to Louisville KY | P152: AFG NC - DCL KY | R152: 43221 | S152: 43221 | T152: =MONTH(E152) -> 5 | U152: =IF(T152=6,"June",IF(T152=5,"May",IF(T152=4,"April",IF(T152=3,"March",0)))) -> May
A153: =U153&P153 -> MayAFG NC - DCL KY | B153: Freight Inbound | C153: AP | D153: 3346437 | E153: 43234 | F153: 05-2018 | G153: Freight Inbound ETA 05/06/18 ASTEELFLASH NC to Louisville KY | H153: 1009471 | I153: 515000 | J153: NAUSA-CRP-4600-JUL | K153: 1550 | L153: 0 | M153: =K153-L153 -> 1550 | O153: =G153 -> Freight Inbound ETA 05/06/18 ASTEELFLASH NC to Louisville KY | P153: AFG NC - DCL KY | R153: 43221 | S153: 43221 | T153: =MONTH(E153) -> 5 | U153: =IF(T153=6,"June",IF(T153=5,"May",IF(T153=4,"April",IF(T153=3,"March",0)))) -> May
A154: =U154&P154 -> MayAFG NC - DCL KY | B154: Freight Inbound | C154: AP | D154: 3346439 | E154: 43234 | F154: 05-2018 | G154: Freight Inbound ETA 05/04/18 ASTEELFLASH NC to Louisville KY | H154: 1009478 | I154: 515000 | J154: NAUSA-CRP-4600-JUL | K154: 3100 | L154: 0 | M154: =K154-L154 -> 3100 | O154: =G154 -> Freight Inbound ETA 05/04/18 ASTEELFLASH NC to Louisville KY | P154: AFG NC - DCL KY | R154: 43221 | S154: 43221 | T154: =MONTH(E154) -> 5 | U154: =IF(T154=6,"June",IF(T154=5,"May",IF(T154=4,"April",IF(T154=3,"March",0)))) -> May
A155: =U155&P155 -> MayAFG NC - DCL KY | B155: Freight Inbound | C155: AP | D155: 3346440 | E155: 43234 | F155: 05-2018 | G155: Freight Inbound ETA 05/08/18 ASTEELFLASH NC to Louisville KY | H155: 1009480 | I155: 515000 | J155: NAUSA-CRP-4600-JUL | K155: 3100 | L155: 0 | M155: =K155-L155 -> 3100 | O155: =G155 -> Freight Inbound ETA 05/08/18 ASTEELFLASH NC to Louisville KY | P155: AFG NC - DCL KY | R155: 43221 | S155: 43221 | T155: =MONTH(E155) -> 5 | U155: =IF(T155=6,"June",IF(T155=5,"May",IF(T155=4,"April",IF(T155=3,"March",0)))) -> May
A156: =U156&P156 -> MayAFG NC - DCL KY | B156: Freight Inbound | C156: AP | D156: 3346443 | E156: 43234 | F156: 05-2018 | G156: Freight Inbound ETA 05/01/18 ASTEELFLASH NC to Louisville KY | H156: 1009485 | I156: 515000 | J156: NAUSA-CRP-4600-JUL | K156: 3100 | L156: 0 | M156: =K156-L156 -> 3100 | O156: =G156 -> Freight Inbound ETA 05/01/18 ASTEELFLASH NC to Louisville KY | P156: AFG NC - DCL KY | R156: 43221 | S156: 43221 | T156: =MONTH(E156) -> 5 | U156: =IF(T156=6,"June",IF(T156=5,"May",IF(T156=4,"April",IF(T156=3,"March",0)))) -> May
A157: =U157&P157 -> MayAFG NC - DCL KY | B157: Freight Inbound | C157: AP | D157: 3346444 | E157: 43234 | F157: 05-2018 | G157: Freight Inbound ETA 05/05/18 ASTEELFLASH NC to Louisville KY | H157: 1009520 | I157: 515000 | J157: NAUSA-CRP-4600-JUL | K157: 3100 | L157: 0 | M157: =K157-L157 -> 3100 | O157: =G157 -> Freight Inbound ETA 05/05/18 ASTEELFLASH NC to Louisville KY | P157: AFG NC - DCL KY | R157: 43221 | S157: 43221 | T157: =MONTH(E157) -> 5 | U157: =IF(T157=6,"June",IF(T157=5,"May",IF(T157=4,"April",IF(T157=3,"March",0)))) -> May
A158: =U158&P158 -> MayAFG NC - DCL KY | B158: Freight Inbound | C158: AP | D158: 3346445 | E158: 43234 | F158: 05-2018 | G158: Freight Inbound ETA 05/14/18 ASTEELFLASH NC to Louisville KY | H158: 1009524 | I158: 515000 | J158: NAUSA-CRP-4600-JUL | K158: 4650 | L158: 0 | M158: =K158-L158 -> 4650 | O158: =G158 -> Freight Inbound ETA 05/14/18 ASTEELFLASH NC to Louisville KY | P158: AFG NC - DCL KY | R158: 43221 | S158: 43221 | T158: =MONTH(E158) -> 5 | U158: =IF(T158=6,"June",IF(T158=5,"May",IF(T158=4,"April",IF(T158=3,"March",0)))) -> May
... A170: =U170&P170 -> MayHong Kong - AFG NC | B170: Freight Inbound | C170: AP | D170: 3346586 | E170: 43238 | F170: 05-2018 | G170: Pallet Charges | H170: 1009619 | I170: 515000 | J170: HCORP-CRP-4600-JUL | K170: 96 | L170: 0 | M170: =K170-L170 -> 96 | O170: =G170 -> Pallet Charges | P170: Hong Kong - AFG NC | R170: 43221 | S170: 43221 | T170: =MONTH(E170) -> 5 | U170: =IF(T170=6,"June",IF(T170=5,"May",IF(T170=4,"April",IF(T170=3,"March",0)))) -> May
A171: =U171&P171 -> MayHong Kong - DECI NC | B171: Freight Inbound | C171: IN | D171: 3346308 | E171: 43222 | F171: 05-2018 | G171: JUUL Basic Kit for Starter Kit | H171: 000495 | I171: 513000 | J171: HCORP-CRP-4600-JUL | K171: 791.13 | L171: 0 | M171: =K171-L171 -> 791.13 | N171: 3346307 | O171: Freight inbound Delivered 04/25/18 Hong Kong - Durham, NC | P171: Hong Kong - DECI NC | Q171: FLEX-254492-1 | R171: 43191 | S171: 43191 | T171: =MONTH(E171) -> 5 | U171: =IF(T171=6,"June",IF(T171=5,"May",IF(T171=4,"April",IF(T171=3,"March",0)))) -> May
A172: =U172&P172 -> MayHong Kong - DECI NC | B172: Freight Inbound | C172: IN | D172: 3346308 | E172: 43222 | F172: 05-2018 | G172: JUUL Basic Kit for Starter Kit | H172: 000495 | I172: 513000 | J172: HCORP-CRP-4600-JUL | K172: 9945.58 | L172: 0 | M172: =K172-L172 -> 9945.58 | N172: 3346307 | O172: Freight inbound Delivered 04/25/18 Hong Kong - Durham, NC | P172: Hong Kong - DECI NC | Q172: FLEX-254492-1 | R172: 43191 | S172: 43191 | T172: =MONTH(E172) -> 5 | U172: =IF(T172=6,"June",IF(T172=5,"May",IF(T172=4,"April",IF(T172=3,"March",0)))) -> May
A173: =U173&P173 -> MayHong Kong - DECI NC | B173: Freight Inbound | C173: IN | D173: 3346308 | E173: 43222 | F173: 05-2018 | G173: JUUL Basic Kit for Starter Kit | H173: 000495 | I173: 513000 | J173: HCORP-CRP-4600-JUL | K173: 59.33 | L173: 0 | M173: =K173-L173 -> 59.33 | N173: 3346307 | O173: Freight inbound Delivered 04/25/18 Hong Kong - Durham, NC | P173: Hong Kong - DECI NC | Q173: FLEX-254492-1 | R173: 43191 | S173: 43191 | T173: =MONTH(E173) -> 5 | U173: =IF(T173=6,"June",IF(T173=5,"May",IF(T173=4,"April",IF(T173=3,"March",0)))) -> May
A174: =U174&P174 -> MayHong Kong - Phillips WI | B174: Freight Inbound | C174: IN | D174: 3346310 | E174: 43222 | F174: 05-2018 | G174: Empty Green POD, Manual Gasket | H174: 000496 | I174: 513000 | J174: HCORP-CRP-4600-JUL | K174: 6205.66 | L174: 0 | M174: =K174-L174 -> 6205.66 | N174: 3346309 | O174: Freight inbound Delivered 04/25/18 Hong Kong-Menomonie,WI | P174: Hong Kong - Phillips WI | Q174: FLEX-255566-1 | R174: 43191 | S174: 43191 | T174: =MONTH(E174) -> 5 | U174: =IF(T174=6,"June",IF(T174=5,"May",IF(T174=4,"April",IF(T174=3,"March",0)))) -> May
A175: =U175&P175 -> MayHong Kong - DCL KY | B175: Freight Inbound | C175: IN | D175: 3346314 | E175: 43222 | F175: 05-2018 | G175: Empty Yellow POD, Manual Gasket | H175: 000498 | I175: 513000 | J175: HCORP-CRP-4600-JUL | K175: 3875.53 | L175: 0 | M175: =K175-L175 -> 3875.53 | N175: 3346313 | O175: Freight inbound Delivered 04/24/18 Hong Kong - Louisville,KY | P175: Hong Kong - DCL KY | Q175: FLEX-255554-1 | R175: 43191 | S175: 43191 | T175: =MONTH(E175) -> 5 | U175: =IF(T175=6,"June",IF(T175=5,"May",IF(T175=4,"April",IF(T175=3,"March",0)))) -> May
A176: =U176&P176 -> MayChina - DCL KY | B176: Freight Inbound | C176: IN | D176: 3346322 | E176: 43222 | F176: 05-2018 | G176: JUUL Basic Kit Slate | H176: 000502 | I176: 513000 | J176: HCORP-CRP-4600-JUL | K176: 2863.12 | L176: 0 | M176: =K176-L176 -> 2863.12 | N176: 3346321 | O176: Freight inbound Delivered 04/24/18 China - Louisville,KY | P176: China - DCL KY | R176: 43191 | S176: 43191 | T176: =MONTH(E176) -> 5 | U176: =IF(T176=6,"June",IF(T176=5,"May",IF(T176=4,"April",IF(T176=3,"March",0)))) -> May
A177: =U177&P177 -> MayHong Kong - Phillips WI | B177: Freight Inbound | C177: IN | D177: 3346328 | E177: 43222 | F177: 05-2018 | G177: Empty Green POD, Manual Gasket | H177: 000505 | I177: 513000 | J177: HCORP-CRP-4600-JUL | K177: 13785.41 | L177: 0 | M177: =K177-L177 -> 13785.41 | N177: 3346327 | O177: Freight inbound Delivered 04/25/18 Hong Kong - Menomonie,WI | P177: Hong Kong - Phillips WI | R177: 43191 | S177: 43191 | T177: =MONTH(E177) -> 5 | U177: =IF(T177=6,"June",IF(T177=5,"May",IF(T177=4,"April",IF(T177=3,"March",0)))) -> May
A178: =U178&P178 -> MayHong Kong - DCL KY | B178: Freight Inbound | C178: IN | D178: 3346336 | E178: 43222 | F178: 05-2018 | G178: Empty Yellow POD, Manual Gasket | H178: 000508 | I178: 513000 | J178: HCORP-CRP-4600-JUL | K178: 12411.51 | L178: 0 | M178: =K178-L178 -> 12411.51 | N178: 3346335 | O178: Freight inbound Delivered 04/24/18 Hong Kong-Louisville,KY | P178: Hong Kong - DCL KY | R178: 43191 | S178: 43191 | T178: =MONTH(E178) -> 5 | U178: =IF(T178=6,"June",IF(T178=5,"May",IF(T178=4,"April",IF(T178=3,"March",0)))) -> May
A179: =U179&P179 -> MayHong Kong - DECI NC | B179: Freight Inbound | C179: IN | D179: 3346338 | E179: 43222 | F179: 05-2018 | G179: JUUL Basic Kit for Starter Kit | H179: 000509 | I179: 513000 | J179: HCORP-CRP-4600-JUL | K179: 9374.31 | L179: 0 | M179: =K179-L179 -> 9374.31 | N179: 3346337 | O179: Freight inbound Delivered 04/25/18 Hong Kong - Durham, NC | P179: Hong Kong - DECI NC | R179: 43191 | S179: 43191 | T179: =MONTH(E179) -> 5 | U179: =IF(T179=6,"June",IF(T179=5,"May",IF(T179=4,"April",IF(T179=3,"March",0)))) -> May
A180: =U180&P180 -> MayChina - DCL KY | B180: Freight Inbound | C180: IN | D180: 3346342 | E180: 43222 | F180: 05-2018 | G180: JUUL Basic Kit Slate | H180: 000511 | I180: 513000 | J180: HCORP-CRP-4600-JUL | K180: 38343.42 | L180: 0 | M180: =K180-L180 -> 38343.42 | N180: 3346341 | O180: Freight inbound Delivered 04/25/18 China - Louisville, KY | P180: China - DCL KY | R180: 43191 | S180: 43191 | T180: =MONTH(E180) -> 5 | U180: =IF(T180=6,"June",IF(T180=5,"May",IF(T180=4,"April",IF(T180=3,"March",0)))) -> May
A181: =U181&P181 -> MayHong Kong - DECI NC | B181: Freight Inbound | C181: IN | D181: 3346344 | E181: 43222 | F181: 05-2018 | G181: JUUL Basic Kit for Starter Kit | H181: 000512 | I181: 513000 | J181: HCORP-CRP-4600-JUL | K181: 74.64 | L181: 0 | M181: =K181-L181 -> 74.64 | N181: 3346343 | O181: Freight inbound Delivered 04/25/18 Hong Kong - Durham, NC | P181: Hong Kong - DECI NC | R181: 43191 | S181: 43191 | T181: =MONTH(E181) -> 5 | U181: =IF(T181=6,"June",IF(T181=5,"May",IF(T181=4,"April",IF(T181=3,"March",0)))) -> May
A182: =U182&P182 -> MayHong Kong - DECI NC | B182: Freight Inbound | C182: IN | D182: 3346344 | E182: 43222 | F182: 05-2018 | G182: JUUL Basic Kit for Starter Kit | H182: 000512 | I182: 513000 | J182: HCORP-CRP-4600-JUL | K182: 10744.32 | L182: 0 | M182: =K182-L182 -> 10744.32 | N182: 3346343 | O182: Freight inbound Delivered 04/25/18 Hong Kong - Durham, NC | P182: Hong Kong - DECI NC | R182: 43191 | S182: 43191 | T182: =MONTH(E182) -> 5 | U182: =IF(T182=6,"June",IF(T182=5,"May",IF(T182=4,"April",IF(T182=3,"March",0)))) -> May
A183: =U183&P183 -> MayChina - DCL KY | B183: Freight Inbound | C183: IN | D183: 3346348 | E183: 43222 | F183: 05-2018 | G183: JUUL Basic Kit Slate | H183: 000514 | I183: 513000 | J183: HCORP-CRP-4600-JUL | K183: 29221.5 | L183: 0 | M183: =K183-L183 -> 29221.5 | N183: 3346347 | O183: Freight inbound Delivered 04/30/18 China - Louisville, KY | P183: China - DCL KY | R183: 43191 | S183: 43191 | T183: =MONTH(E183) -> 5 | U183: =IF(T183=6,"June",IF(T183=5,"May",IF(T183=4,"April",IF(T183=3,"March",0)))) -> May
A184: =U184&P184 -> MayChina - DCL KY | B184: Freight Inbound | C184: IN | D184: 3346359 | E184: 43222 | F184: 05-2018 | G184: JUUL Basic Kit Slate | H184: 000519 | I184: 513000 | J184: HCORP-CRP-4600-JUL | K184: 23144.15 | L184: 0 | M184: =K184-L184 -> 23144.15 | N184: 3346358 | O184: Freight inbound Delivered 04/24/18 China - Louisville, KY | P184: China - DCL KY | R184: 43191 | S184: 43191 | T184: =MONTH(E184) -> 5 | U184: =IF(T184=6,"June",IF(T184=5,"May",IF(T184=4,"April",IF(T184=3,"March",0)))) -> May
A185: =U185&P185 -> MayHong Kong - DCL KY | B185: Freight Inbound | C185: IN | D185: 3346365 | E185: 43222 | F185: 05-2018 | G185: JUUL Basic Kit Slate | H185: 000522 | I185: 513000 | J185: HCORP-CRP-4600-JUL | K185: 3536.71 | L185: 0 | M185: =K185-L185 -> 3536.71 | N185: 3346364 | O185: Freight inbound Delivered 04/30/18 Hong Kong - Louisville,KY | P185: Hong Kong - DCL KY | R185: 43191 | S185: 43191 | T185: =MONTH(E185) -> 5 | U185: =IF(T185=6,"June",IF(T185=5,"May",IF(T185=4,"April",IF(T185=3,"March",0)))) -> May
A186: =U186&P186 -> MayHong Kong - DECI NC | B186: Freight Inbound | C186: IN | D186: 3346367 | E186: 43222 | F186: 05-2018 | G186: JUUL Basic Kit for Starter Kit | H186: 000523 | I186: 513000 | J186: HCORP-CRP-4600-JUL | K186: 13035.37 | L186: 0 | M186: =K186-L186 -> 13035.37 | N186: 3346366 | O186: Freight inbound Delivered 05/01/18 Hong Kong - Durham, NC | P186: Hong Kong - DECI NC | Q186: FLEX-260945-1 | R186: 43191 | S186: 43191 | T186: =MONTH(E186) -> 5 | U186: =IF(T186=6,"June",IF(T186=5,"May",IF(T186=4,"April",IF(T186=3,"March",0)))) -> May
A187: =U187&P187 -> MayHong Kong - DECI NC | B187: Freight Inbound | C187: IN | D187: 3346367 | E187: 43222 | F187: 05-2018 | G187: JUUL Basic Kit for Starter Kit | H187: 000523 | I187: 513000 | J187: HCORP-CRP-4600-JUL | K187: 2673.92 | L187: 0 | M187: =K187-L187 -> 2673.92 | N187: 3346366 | O187: Freight inbound Delivered 05/01/18 Hong Kong - Durham, NC | P187: Hong Kong - DECI NC | Q187: FLEX-260945-1 | R187: 43191 | S187: 43191 | T187: =MONTH(E187) -> 5 | U187: =IF(T187=6,"June",IF(T187=5,"May",IF(T187=4,"April",IF(T187=3,"March",0)))) -> May
A188: =U188&P188 -> MayChina - DECI NC | B188: Freight Inbound | C188: IN | D188: 3346371 | E188: 43222 | F188: 05-2018 | G188: JUUL Basic Kit for Starter Kit | H188: 000525 | I188: 513000 | J188: HCORP-CRP-4600-JUL | K188: 22858.28 | L188: 0 | M188: =K188-L188 -> 22858.28 | N188: 3346370 | O188: Freight inbound Delivered 04/26/18 China - Durham, NC | P188: China - DECI NC | R188: 43191 | S188: 43191 | T188: =MONTH(E188) -> 5 | U188: =IF(T188=6,"June",IF(T188=5,"May",IF(T188=4,"April",IF(T188=3,"March",0)))) -> May
A189: =U189&P189 -> MayChina - DCL KY | B189: Freight Inbound | C189: IN | D189: 3346377 | E189: 43222 | F189: 05-2018 | G189: JUUL Basic Kit Slate | H189: 000528 | I189: 513000 | J189: HCORP-CRP-4600-JUL | K189: 25067.64 | L189: 0 | M189: =K189-L189 -> 25067.64 | N189: 3346376 | O189: Freight inbound Delivered 04/27/18 China - Louisville,KY | P189: China - DCL KY | R189: 43191 | S189: 43191 | T189: =MONTH(E189) -> 5 | U189: =IF(T189=6,"June",IF(T189=5,"May",IF(T189=4,"April",IF(T189=3,"March",0)))) -> May
A190: =U190&P190 -> MayHong Kong - DCL KY | B190: Freight Inbound | C190: IN | D190: 3346396 | E190: 43222 | F190: 05-2018 | G190: JUUL Basic Kit Slate | H190: 000537 | I190: 513000 | J190: HCORP-CRP-4600-JUL | K190: 2626.48 | L190: 0 | M190: =K190-L190 -> 2626.48 | N190: 3346395 | O190: Freight inbound Delivered 04/24/18 Hong Kong -Louisville, KY | P190: Hong Kong - DCL KY | R190: 43191 | S190: 43191 | T190: =MONTH(E190) -> 5 | U190: =IF(T190=6,"June",IF(T190=5,"May",IF(T190=4,"April",IF(T190=3,"March",0)))) -> May
A191: =U191&P191 -> MayChina - DECI NC | B191: Freight Inbound | C191: IN | D191: 3346316 | E191: 43227 | F191: 05-2018 | G191: JUUL Basic Kit for Starter Kit | H191: 000499 | I191: 513000 | J191: HCORP-CRP-4600-JUL | K191: 12159.81 | L191: 0 | M191: =K191-L191 -> 12159.81 | N191: 3346315 | O191: Freight inbound Delivered 04/25/18 China - Durham, NC | P191: China - DECI NC | R191: 43191 | S191: 43191 | T191: =MONTH(E191) -> 5 | U191: =IF(T191=6,"June",IF(T191=5,"May",IF(T191=4,"April",IF(T191=3,"March",0)))) -> May
...
