Workbook
Name EssAliasTable: "Default"
Name EssAliasTable: "Default"
Name EssAliasTable: "Default"
Name EssAliasTable: "Default"
Name EssfHasNonUnique: FALSE
Name EssfHasNonUnique: FALSE
Name EssfHasNonUnique: FALSE
Name EssfHasNonUnique: FALSE
Name EssLatest: "Beg Bal"
Name EssLatest: "Beg Bal"
Name EssLatest: "Beg Bal"
Name EssLatest: "Beg Bal"
Name EssOptions: "A3100000000111000000001100020_020 00"
Name EssOptions: "A3100000000111000000001100020_020 00"
Name EssOptions: "A1100000000111000000001100020_020 00"
Name EssOptions: "A1100000000111000000001100020_020 00"
Name EssSamplingValue: 100
Name EssSamplingValue: 100
Name EssSamplingValue: 100
Name EssSamplingValue: 100

Sheet Report
A1: Pharma Freight Actual VS Budget
B2: FY15 | C2: September | H2: Full Year
A3: This report is NOT total Mallinckrodt, OUS regions not converted to E1 are not included | C3: Budget | D3: Current Forecast | E3: Actual | H3: Budget | I3: Current Forecast | J3: Actual
A5: In Freight
A6: API | B6: STL StearPhos/Gateway
B7: Japan | D7: =+'FY15 Current Forecast'!N59+'FY15 Current Forecast'!N61+'FY15 Current Forecast'!N68+'FY15 Current Forecast'!N62+'FY15 Current Forecast'!N63+'FY15 Current Forecast'!N66+'FY15 Current Forecast'!N67+'FY15 Current Forecast'!N60 -> 0 | E7: =+'FY15 Working Forecast'!N59+'FY15 Working Forecast'!N61+'FY15 Working Forecast'!N68+'FY15 Working Forecast'!N62+'FY15 Working Forecast'!N63+'FY15 Working Forecast'!N66+'FY15 Working Forecast'!N67+'FY15 Working Forecast'!N60 -> -28487.97 | I7: =+'FY15 Current Forecast'!O59+'FY15 Current Forecast'!O61+'FY15 Current Forecast'!O68+'FY15 Current Forecast'!O62+'FY15 Current Forecast'!O63+'FY15 Current Forecast'!O66+'FY15 Current Forecast'!O67+'FY15 Current Forecast'!O60 -> 0 | J7: =+'FY15 Working Forecast'!O59+'FY15 Working Forecast'!O61+'FY15 Working Forecast'!O68+'FY15 Working Forecast'!O62+'FY15 Working Forecast'!O63+'FY15 Working Forecast'!O66+'FY15 Working Forecast'!O67+'FY15 Working Forecast'!O60 -> 65508.17
B8: UK PAP/APAP | C8: =+'FY15 Budget'!N51+'FY15 Budget'!N52+'FY15 Budget'!N55+'FY15 Budget'!N57 -> 111832.17 | D8: =+'FY15 Current Forecast'!N52+'FY15 Current Forecast'!N53+'FY15 Current Forecast'!N55+'FY15 Current Forecast'!N57+'FY15 Current Forecast'!N58 -> 0 | E8: =+'FY15 Working Forecast'!N52+'FY15 Working Forecast'!N53+'FY15 Working Forecast'!N55+'FY15 Working Forecast'!N57+'FY15 Working Forecast'!N58 -> 117207.46 | H8: =+'FY15 Budget'!O51+'FY15 Budget'!O52+'FY15 Budget'!O55+'FY15 Budget'!O57 -> 1453818.2 | I8: =+'FY15 Current Forecast'!O52+'FY15 Current Forecast'!O53+'FY15 Current Forecast'!O55+'FY15 Current Forecast'!O57+'FY15 Current Forecast'!O58 -> 0 | J8: =+'FY15 Working Forecast'!O52+'FY15 Working Forecast'!O53+'FY15 Working Forecast'!O55+'FY15 Working Forecast'!O57+'FY15 Working Forecast'!O58 -> 1222339.2
B9: UK Bulk Narcotics | C9: =+'FY15 Budget'!N50 -> 0 | D9: =+'FY15 Current Forecast'!N51 -> 0 | E9: =+'FY15 Working Forecast'!N51 -> 0 | H9: =+'FY15 Budget'!O50 -> 0 | I9: =+'FY15 Current Forecast'!O51 -> 0 | J9: =+'FY15 Working Forecast'!O51 -> 42.97
B10: UK Stear/Phos | C10: =+'FY15 Budget'!N53 -> 5425.1694 | D10: =+'FY15 Current Forecast'!N54 -> 0 | E10: =+'FY15 Working Forecast'!N54 -> 10916.78 | H10: =+'FY15 Budget'!O53 -> 70527.202 | I10: =+'FY15 Current Forecast'!O54 -> 0 | J10: =+'FY15 Working Forecast'!O54 -> 148747.95
B11: Canada PHM | C11: =+'FY15 Budget'!N59 -> 0 | D11: =+'FY15 Current Forecast'!N69+'FY15 Current Forecast'!N64+'FY15 Current Forecast'!N65 -> 0 | E11: =+'FY15 Working Forecast'!N69+'FY15 Working Forecast'!N64+'FY15 Working Forecast'!N65 -> 0 | H11: =+'FY15 Budget'!O59 -> 0 | I11: =+'FY15 Current Forecast'!O69+'FY15 Current Forecast'!O64+'FY15 Current Forecast'!O65 -> 0 | J11: =+'FY15 Working Forecast'!O69+'FY15 Working Forecast'!O64+'FY15 Working Forecast'!O65 -> 0
B12: Sub-Total API In Freight | C12: =SUM(C6:C11) -> 117257.34 | D12: =SUM(D6:D11) -> 0 | E12: =SUM(E6:E11) -> 99636.27 | H12: =SUM(H6:H11) -> 1524345.4 | I12: =SUM(I6:I11) -> 0 | J12: =SUM(J6:J11) -> 1436638.2
A14: Dosage | B14: Hobart | C14: =+SUM('FY15 Budget'!N8:N49)+'FY15 Budget'!N56 -> 25593.521 | D14: =+SUM('FY15 Current Forecast'!N8:N50)+'FY15 Current Forecast'!N56 -> 0 | E14: =+SUM('FY15 Working Forecast'!N8:N50)+'FY15 Working Forecast'!N56 -> -3 | H14: =+SUM('FY15 Budget'!O8:O49) -> 299030.65 | I14: =+SUM('FY15 Current Forecast'!O8:O50)+'FY15 Current Forecast'!O56 -> 0 | J14: =+SUM('FY15 Working Forecast'!O8:O50)+'FY15 Working Forecast'!O56 -> 76286
B15: External Manufacturing | C15: =+'FY15 Budget'!N66+'FY15 Budget'!N67+'FY15 Budget'!N60 -> 4323.0783 | D15: =+'FY15 Current Forecast'!N76+'FY15 Current Forecast'!N77+'FY15 Current Forecast'!N70 -> 0 | E15: =+'FY15 Working Forecast'!N76+'FY15 Working Forecast'!N77+'FY15 Working Forecast'!N70 -> 9357.36 | H15: =+'FY15 Budget'!O66+'FY15 Budget'!O67+'FY15 Budget'!O60 -> 51876.94 | I15: =+'FY15 Current Forecast'!O76+'FY15 Current Forecast'!O77+'FY15 Current Forecast'!O70 -> 0 | J15: =+'FY15 Working Forecast'!O76+'FY15 Working Forecast'!O77+'FY15 Working Forecast'!O70 -> 98812.31
B16: Sub-Total Dosage In Freight | C16: =SUM(C14:C15) -> 29916.599 | D16: =SUM(D14:D15) -> 0 | E16: =SUM(E14:E15) -> 9354.36 | H16: =SUM(H14:H15) -> 350907.59 | I16: =SUM(I14:I15) -> 0 | J16: =SUM(J14:J15) -> 175098.31
A18: Questcor | B18: Autoimmune | C18: =+'FY15 Budget'!N64+'FY15 Budget'!N65+'FY15 Budget'!N63+'FY15 Budget'!N62+'FY15 Budget'!N61 -> 0 | D18: =+'FY15 Current Forecast'!N74+'FY15 Current Forecast'!N75+'FY15 Current Forecast'!N71+'FY15 Current Forecast'!N72+'FY15 Current Forecast'!N73 -> 0 | E18: =+'FY15 Working Forecast'!N74+'FY15 Working Forecast'!N75+'FY15 Working Forecast'!N71+'FY15 Working Forecast'!N72+'FY15 Working Forecast'!N73 -> 25626.73 | H18: =+'FY15 Budget'!O64+'FY15 Budget'!O65+'FY15 Budget'!O63+'FY15 Budget'!O62+'FY15 Budget'!O61 -> 0 | I18: =+'FY15 Current Forecast'!O74+'FY15 Current Forecast'!O75+'FY15 Current Forecast'!O71+'FY15 Current Forecast'!O72+'FY15 Current Forecast'!O73 -> 0 | J18: =+'FY15 Working Forecast'!O74+'FY15 Working Forecast'!O75+'FY15 Working Forecast'!O71+'FY15 Working Forecast'!O72+'FY15 Working Forecast'!O73 -> 473068.11
B19: Sub-Total Autoimmune | C19: =SUM(C17:C18) -> 0 | D19: =SUM(D17:D18) -> 0 | E19: =SUM(E17:E18) -> 25626.73 | H19: =SUM(H17:H18) -> 0 | I19: =SUM(I17:I18) -> 0 | J19: =SUM(J17:J18) -> 473068.11
A21: Imaging | B21: KN/Cincinnati | C21: =+SUM('FY15 Budget'!N191:N196) -> 0 | D21: =+SUM('FY15 Current Forecast'!N222:N227) -> 0 | E21: =+SUM('FY15 Working Forecast'!N222:N227) -> 4494.95 | H21: =+SUM('FY15 Budget'!O191:O196) -> 0 | I21: =+SUM('FY15 Current Forecast'!O222:O227) -> 0 | J21: =+SUM('FY15 Working Forecast'!O222:O227) -> 122224.95
B22: Canada | C22: =+'FY15 Budget'!N279 -> 9328.358 | D22: =+'FY15 Current Forecast'!N310+'FY15 Current Forecast'!N312 -> 0 | E22: =+'FY15 Working Forecast'!N310+'FY15 Working Forecast'!N312 -> 6520.23 | H22: =+'FY15 Budget'!O279 -> 111940.3 | I22: =+'FY15 Current Forecast'!O310+'FY15 Current Forecast'!O312 -> 0 | J22: =+'FY15 Working Forecast'!O310+'FY15 Working Forecast'!O312 -> 105793.68
B23: Sub-Total Imaging In Freight | C23: =SUM(C21:C22) -> 9328.358 | D23: =SUM(D21:D22) -> 0 | E23: =SUM(E21:E22) -> 11015.18 | H23: =SUM(H21:H22) -> 111940.3 | I23: =SUM(I21:I22) -> 0 | J23: =SUM(J21:J22) -> 228018.63
B25: Total JDE and E1 In Freight | C25: =SUM(C12,C16,C23,C19) -> 156502.29 | D25: =SUM(D12,D16,D23,D19) -> 0 | E25: =SUM(E12,E16,E23,E19) -> 145632.54 | H25: =SUM(H12,H16,H23,H19) -> 1987193.3 | I25: =SUM(I12,I16,I23,I19) -> 0 | J25: =SUM(J12,J16,J23,J19) -> 2312823.3
A27: Out Freight
A28: API | B28: STL StearPhos/Gateway | C28: =+'FY15 Budget'!N105+'FY15 Budget'!N129+'FY15 Budget'!N131+'FY15 Budget'!N124+'FY15 Budget'!N110+'FY15 Budget'!N130+'FY15 Budget'!N132 -> 24240 | D28: =+'FY15 Current Forecast'!N160+'FY15 Current Forecast'!N161+'FY15 Current Forecast'!N162+'FY15 Current Forecast'!N142+'FY15 Current Forecast'!N113+'FY15 Current Forecast'!N125+'FY15 Current Forecast'!N163 -> 0 | E28: =+'FY15 Working Forecast'!N160+'FY15 Working Forecast'!N161+'FY15 Working Forecast'!N162+'FY15 Working Forecast'!N142+'FY15 Working Forecast'!N113+'FY15 Working Forecast'!N125+'FY15 Working Forecast'!N163 -> 62374.76 | H28: =+'FY15 Budget'!O105+'FY15 Budget'!O130+'FY15 Budget'!O129+'FY15 Budget'!O131+'FY15 Budget'!O124+'FY15 Budget'!O110+'FY15 Budget'!O129 -> 315120 | I28: =+'FY15 Current Forecast'!O160+'FY15 Current Forecast'!O161+'FY15 Current Forecast'!O162+'FY15 Current Forecast'!O142+'FY15 Current Forecast'!O113+'FY15 Current Forecast'!O125+'FY15 Current Forecast'!O163 -> 0 | J28: =+'FY15 Working Forecast'!O160+'FY15 Working Forecast'!O161+'FY15 Working Forecast'!O162+'FY15 Working Forecast'!O142+'FY15 Working Forecast'!O113+'FY15 Working Forecast'!O125+'FY15 Working Forecast'!O163 -> 193863.56
B29: STL Plant Narcotics | C29: =+'FY15 Budget'!N127+'FY15 Budget'!N123+'FY15 Budget'!N128 -> 44560 | D29: =+'FY15 Current Forecast'!N158+'FY15 Current Forecast'!N159+'FY15 Current Forecast'!N138+'FY15 Current Forecast'!N139+'FY15 Current Forecast'!N140+'FY15 Current Forecast'!N141+'FY15 Current Forecast'!N109+'FY15 Current Forecast'!N114+'FY15 Current Forecast'!N129+'FY15 Current Forecast'!N130+'FY15 Current Forecast'!N131+'FY15 Current Forecast'!N132+'FY15 Current Forecast'!N119+'FY15 Current Forecast'!N99+'FY15 Current Forecast'!N112+'FY15 Current Forecast'!N117+'FY15 Current Forecast'!N128 -> 0 | E29: =+'FY15 Working Forecast'!N158+'FY15 Working Forecast'!N159+'FY15 Working Forecast'!N138+'FY15 Working Forecast'!N139+'FY15 Working Forecast'!N140+'FY15 Working Forecast'!N141+'FY15 Working Forecast'!N109+'FY15 Working Forecast'!N114+'FY15 Working Forecast'!N129+'FY15 Working Forecast'!N130+'FY15 Working Forecast'!N131+'FY15 Working Forecast'!N132+'FY15 Working Forecast'!N119+'FY15 Working Forecast'!N99+'FY15 Working Forecast'!N112+'FY15 Working Forecast'!N117+'FY15 Working Forecast'!N128 -> 72243.14 | H29: =+'FY15 Budget'!O127+'FY15 Budget'!O123+'FY15 Budget'!O128 -> 579280 | I29: =+'FY15 Current Forecast'!O158+'FY15 Current Forecast'!O159+'FY15 Current Forecast'!O138+'FY15 Current Forecast'!O139+'FY15 Current Forecast'!O140+'FY15 Current Forecast'!O141+'FY15 Current Forecast'!O109+'FY15 Current Forecast'!O114+'FY15 Current Forecast'!O129+'FY15 Current Forecast'!O130+'FY15 Current Forecast'!O131+'FY15 Current Forecast'!O132+'FY15 Current Forecast'!O119+'FY15 Current Forecast'!O99+'FY15 Current Forecast'!O112+'FY15 Current Forecast'!O117+'FY15 Current Forecast'!O128 -> 0 | J29: =+'FY15 Working Forecast'!O158+'FY15 Working Forecast'!O159+'FY15 Working Forecast'!O138+'FY15 Working Forecast'!O139+'FY15 Working Forecast'!O140+'FY15 Working Forecast'!O141+'FY15 Working Forecast'!O109+'FY15 Working Forecast'!O114+'FY15 Working Forecast'!O129+'FY15 Working Forecast'!O130+'FY15 Working Forecast'!O131+'FY15 Working Forecast'!O132+'FY15 Working Forecast'!O119+'FY15 Working Forecast'!O99+'FY15 Working Forecast'!O112+'FY15 Working Forecast'!O117+'FY15 Working Forecast'!O128 -> 619274.9
B30: Peptides
B31: APAP/COMPAP | C31: =+'FY15 Budget'!N126+'FY15 Budget'!N109+'FY15 Budget'!N184+'FY15 Budget'!N102+'FY15 Budget'!N119+'FY15 Budget'!N183+'FY15 Budget'!N99+'FY15 Budget'!N124 -> 126920 | D31: =+'FY15 Current Forecast'!N157+'FY15 Current Forecast'!N215+'FY15 Current Forecast'!N133+'FY15 Current Forecast'!N123+'FY15 Current Forecast'!N126+'FY15 Current Forecast'!N97+'FY15 Current Forecast'!N127+'FY15 Current Forecast'!N116+'FY15 Current Forecast'!N120+'FY15 Current Forecast'!N164+'FY15 Current Forecast'!N122+'FY15 Current Forecast'!N124+'FY15 Current Forecast'!N121+'FY15 Current Forecast'!N115+'FY15 Current Forecast'!N137+'FY15 Current Forecast'!N134+'FY15 Current Forecast'!N98+'FY15 Current Forecast'!N118+'FY15 Current Forecast'!N108+'FY15 Current Forecast'!N106+'FY15 Current Forecast'!N107+'FY15 Current Forecast'!N110+'FY15 Current Forecast'!N111+'FY15 Current Forecast'!N144+'FY15 Current Forecast'!N145+'FY15 Current Forecast'!N146+'FY15 Current Forecast'!N147+'FY15 Current Forecast'!N148+'FY15 Current Forecast'!N149+'FY15 Current Forecast'!N150+'FY15 Current Forecast'!N151+'FY15 Current Forecast'!N152+'FY15 Current Forecast'!N153+'FY15 Current Forecast'!N154+'FY15 Current Forecast'!N155+'FY15 Current Forecast'!N143 -> 0 | E31: =+'FY15 Working Forecast'!N157+'FY15 Working Forecast'!N215+'FY15 Working Forecast'!N133+'FY15 Working Forecast'!N123+'FY15 Working Forecast'!N126+'FY15 Working Forecast'!N97+'FY15 Working Forecast'!N127+'FY15 Working Forecast'!N116+'FY15 Working Forecast'!N120+'FY15 Working Forecast'!N164+'FY15 Working Forecast'!N122+'FY15 Working Forecast'!N124+'FY15 Working Forecast'!N121+'FY15 Working Forecast'!N115+'FY15 Working Forecast'!N137+'FY15 Working Forecast'!N134+'FY15 Working Forecast'!N98+'FY15 Working Forecast'!N118+'FY15 Working Forecast'!N108+'FY15 Working Forecast'!N106+'FY15 Working Forecast'!N107+'FY15 Working Forecast'!N110+'FY15 Working Forecast'!N111+'FY15 Working Forecast'!N144+'FY15 Working Forecast'!N145+'FY15 Working Forecast'!N146+'FY15 Working Forecast'!N147+'FY15 Working Forecast'!N148+'FY15 Working Forecast'!N149+'FY15 Working Forecast'!N150+'FY15 Working Forecast'!N151+'FY15 Working Forecast'!N152+'FY15 Working Forecast'!N153+'FY15 Working Forecast'!N154+'FY15 Working Forecast'!N155+'FY15 Working Forecast'!N143 -> 235017.58 | H31: =+'FY15 Budget'!O126+'FY15 Budget'!O109+'FY15 Budget'!O184+'FY15 Budget'!O102+'FY15 Budget'!O119+'FY15 Budget'!O183+'FY15 Budget'!O99+'FY15 Budget'!O124 -> 1649960 | I31: =+'FY15 Current Forecast'!O157+'FY15 Current Forecast'!O215+'FY15 Current Forecast'!O133+'FY15 Current Forecast'!O123+'FY15 Current Forecast'!O126+'FY15 Current Forecast'!O97+'FY15 Current Forecast'!O127+'FY15 Current Forecast'!O116+'FY15 Current Forecast'!O120+'FY15 Current Forecast'!O164+'FY15 Current Forecast'!O122+'FY15 Current Forecast'!O124+'FY15 Current Forecast'!O121+'FY15 Current Forecast'!O115+'FY15 Current Forecast'!O137+'FY15 Current Forecast'!O134+'FY15 Current Forecast'!O98+'FY15 Current Forecast'!O118+'FY15 Current Forecast'!O108+'FY15 Current Forecast'!O106+'FY15 Current Forecast'!O107+'FY15 Current Forecast'!O110+'FY15 Current Forecast'!O111+'FY15 Current Forecast'!O144+'FY15 Current Forecast'!O145+'FY15 Current Forecast'!O146+'FY15 Current Forecast'!O147+'FY15 Current Forecast'!O148+'FY15 Current Forecast'!O149+'FY15 Current Forecast'!O150+'FY15 Current Forecast'!O151+'FY15 Current Forecast'!O152+'FY15 Current Forecast'!O153+'FY15 Current Forecast'!O154+'FY15 Current Forecast'!O155+'FY15 Current Forecast'!O143 -> 0 | J31: =+'FY15 Working Forecast'!O157+'FY15 Working Forecast'!O215+'FY15 Working Forecast'!O133+'FY15 Working Forecast'!O123+'FY15 Working Forecast'!O126+'FY15 Working Forecast'!O97+'FY15 Working Forecast'!O127+'FY15 Working Forecast'!O116+'FY15 Working Forecast'!O120+'FY15 Working Forecast'!O164+'FY15 Working Forecast'!O122+'FY15 Working Forecast'!O124+'FY15 Working Forecast'!O121+'FY15 Working Forecast'!O115+'FY15 Working Forecast'!O137+'FY15 Working Forecast'!O134+'FY15 Working Forecast'!O98+'FY15 Working Forecast'!O118+'FY15 Working Forecast'!O108+'FY15 Working Forecast'!O106+'FY15 Working Forecast'!O107+'FY15 Working Forecast'!O110+'FY15 Working Forecast'!O111+'FY15 Working Forecast'!O144+'FY15 Working Forecast'!O145+'FY15 Working Forecast'!O146+'FY15 Working Forecast'!O147+'FY15 Working Forecast'!O148+'FY15 Working Forecast'!O149+'FY15 Working Forecast'!O150+'FY15 Working Forecast'!O151+'FY15 Working Forecast'!O152+'FY15 Working Forecast'!O153+'FY15 Working Forecast'!O154+'FY15 Working Forecast'!O155+'FY15 Working Forecast'!O143 -> 2089495.9
B32: UK PAP/APAP | C32: =+'FY15 Budget'!N180 -> 124391.43 | D32: =+'FY15 Current Forecast'!N212+'FY15 Current Forecast'!N208+'FY15 Current Forecast'!N211 -> 0 | E32: =+'FY15 Working Forecast'!N212+'FY15 Working Forecast'!N208+'FY15 Working Forecast'!N211 -> 93276.07 | H32: =+'FY15 Budget'!O180 -> 1617088.6 | I32: =+'FY15 Current Forecast'!O212+'FY15 Current Forecast'!O208+'FY15 Current Forecast'!O211 -> 0 | J32: =+'FY15 Working Forecast'!O212+'FY15 Working Forecast'!O208+'FY15 Working Forecast'!O211 -> 1556832.6
B33: UK Bulk Narcotics | C33: =+'FY15 Budget'!N181 -> 13635.088 | D33: =+'FY15 Current Forecast'!N213+'FY15 Current Forecast'!N209 -> 0 | E33: =+'FY15 Working Forecast'!N213+'FY15 Working Forecast'!N209 -> 3459.34 | H33: =+'FY15 Budget'!O181 -> 177256.15 | I33: =+'FY15 Current Forecast'!O213+'FY15 Current Forecast'!O209 -> 0 | J33: =+'FY15 Working Forecast'!O213+'FY15 Working Forecast'!O209 -> 113669.54
B34: UK Stear/Phos | C34: =+'FY15 Budget'!N182 -> 5907.7515 | D34: =+'FY15 Current Forecast'!N214+'FY15 Current Forecast'!N210 -> 0 | E34: =+'FY15 Working Forecast'!N214+'FY15 Working Forecast'!N210 -> 6122.43 | H34: =+'FY15 Budget'!O182 -> 76800.769 | I34: =+'FY15 Current Forecast'!O214+'FY15 Current Forecast'!O210 -> 0 | J34: =+'FY15 Working Forecast'!O214+'FY15 Working Forecast'!O210 -> 185197.04
B35: Goaling | C35: =+'FY15 Budget'!N116 -> 0 | D35: =+'FY15 Current Forecast'!N135 -> 0 | E35: =+'FY15 Working Forecast'!N135 -> 0 | H35: =+'FY15 Budget'!O116 -> 0 | I35: =+'FY15 Current Forecast'!O135 -> 0 | J35: =+'FY15 Working Forecast'!O135 -> 0
B36: Sub-Total API Out Freight | C36: =SUM(C28:C35) -> 339654.27 | D36: =SUM(D28:D35) -> 0 | E36: =SUM(E28:E35) -> 472493.32 | H36: =SUM(H28:H35) -> 4415505.5 | I36: =SUM(I28:I35) -> 0 | J36: =SUM(J28:J35) -> 4758333.5
A38: Dosage | B38: Hobart | C38: =+SUM('FY15 Budget'!N134:N175)+'FY15 Budget'!N90+'FY15 Budget'!N91+'FY15 Budget'!N92+'FY15 Budget'!N93+'FY15 Budget'!N94 -> 432448.89 | D38: =+SUM('FY15 Current Forecast'!N165:N207)+'FY15 Current Forecast'!N100+'FY15 Current Forecast'!N101+'FY15 Current Forecast'!N102+'FY15 Current Forecast'!N103+'FY15 Current Forecast'!N104+'FY15 Current Forecast'!N156 -> 0 | E38: =+SUM('FY15 Working Forecast'!N165:N207)+'FY15 Working Forecast'!N100+'FY15 Working Forecast'!N101+'FY15 Working Forecast'!N102+'FY15 Working Forecast'!N103+'FY15 Working Forecast'!N104+'FY15 Working Forecast'!N156 -> 338194.03 | H38: =+SUM('FY15 Budget'!O134:O175)+'FY15 Budget'!O90+'FY15 Budget'!O91+'FY15 Budget'!O92+'FY15 Budget'!O93+'FY15 Budget'!O94 -> 5658751.8 | I38: =+SUM('FY15 Current Forecast'!O165:O207)+'FY15 Current Forecast'!O100+'FY15 Current Forecast'!O101+'FY15 Current Forecast'!O102+'FY15 Current Forecast'!O103+'FY15 Current Forecast'!O104+'FY15 Current Forecast'!O156 -> 0 | J38: =+SUM('FY15 Working Forecast'!O165:O207)+'FY15 Working Forecast'!O100+'FY15 Working Forecast'!O101+'FY15 Working Forecast'!O102+'FY15 Working Forecast'!O103+'FY15 Working Forecast'!O104+'FY15 Working Forecast'!O156 -> 4884686.8
B39: Canada | C39: =+'FY15 Budget'!N285+'FY15 Budget'!N95+'FY15 Budget'!N287 -> 0 | D39: =+'FY15 Current Forecast'!N318+'FY15 Current Forecast'!N105+'FY15 Current Forecast'!N320 -> 0 | E39: =+'FY15 Working Forecast'!N318+'FY15 Working Forecast'!N105+'FY15 Working Forecast'!N320 -> 14665.54 | H39: =+'FY15 Budget'!O285+'FY15 Budget'!O95+'FY15 Budget'!O287 -> 0 | I39: =+'FY15 Current Forecast'!O318+'FY15 Current Forecast'!O105+'FY15 Current Forecast'!O320 -> 0 | J39: =+'FY15 Working Forecast'!O318+'FY15 Working Forecast'!O105+'FY15 Working Forecast'!O320 -> 142597.77
B40: External Manufactuing | C40: =+'FY15 Budget'!N70+'FY15 Budget'!N71+'FY15 Budget'!N77+'FY15 Budget'!N78 -> 472831.58 | D40: =+'FY15 Current Forecast'!N80+'FY15 Current Forecast'!N81+'FY15 Current Forecast'!N87+'FY15 Current Forecast'!N88 -> 0 | E40: =+'FY15 Working Forecast'!N80+'FY15 Working Forecast'!N81+'FY15 Working Forecast'!N87+'FY15 Working Forecast'!N88 -> 59795.61 | H40: =+'FY15 Budget'!O70+'FY15 Budget'!O71+'FY15 Budget'!O77+'FY15 Budget'!O78 -> 3595668.5 | I40: =+'FY15 Current Forecast'!O80+'FY15 Current Forecast'!O81+'FY15 Current Forecast'!O87+'FY15 Current Forecast'!O88 -> 0 | J40: =+'FY15 Working Forecast'!O80+'FY15 Working Forecast'!O81+'FY15 Working Forecast'!O87+'FY15 Working Forecast'!O88 -> 1185220.3
B41: Sub-Total Dosage Out Freight | C41: =SUM(C38:C40) -> 905280.47 | D41: =SUM(D38:D40) -> 0 | E41: =SUM(E38:E40) -> 412655.18 | H41: =SUM(H38:H40) -> 9254420.3 | I41: =SUM(I38:I40) -> 0 | J41: =SUM(J38:J40) -> 6212504.9
A43: Ikeria | B43: INO Therapeutics | C43: =SUM('FY15 Budget'!N299:N315)+'FY15 Budget'!N318 -> 0 | D43: =SUM('FY15 Current Forecast'!N335:N351)+'FY15 Current Forecast'!N354 -> 0 | E43: =SUM('FY15 Working Forecast'!N335:N351)+'FY15 Working Forecast'!N354 -> 406649.98 | H43: =SUM('FY15 Budget'!O299:O315)+'FY15 Budget'!O318 -> 0 | I43: =SUM('FY15 Current Forecast'!O335:O351)+'FY15 Current Forecast'!O354 -> 0 | J43: =SUM('FY15 Working Forecast'!O335:O351)+'FY15 Working Forecast'!O354 -> 1620738
B44: Sub-Total Autoimmune | C44: =SUM(C43:C43) -> 0 | D44: =SUM(D43:D43) -> 0 | E44: =SUM(E43:E43) -> 406649.98 | H44: =SUM(H43:H43) -> 0 | I44: =SUM(I43:I43) -> 0 | J44: =SUM(J43:J43) -> 1620738
A46: Questcor | B46: Autoimmune | C46: =+'FY15 Budget'!N72+'FY15 Budget'!N73+'FY15 Budget'!N74+'FY15 Budget'!N75+'FY15 Budget'!N76 -> 2000 | D46: =+'FY15 Current Forecast'!N82+'FY15 Current Forecast'!N83+'FY15 Current Forecast'!N84+'FY15 Current Forecast'!N85+'FY15 Current Forecast'!N86+'FY15 Current Forecast'!N89 -> 0 | E46: =+'FY15 Working Forecast'!N82+'FY15 Working Forecast'!N83+'FY15 Working Forecast'!N84+'FY15 Working Forecast'!N85+'FY15 Working Forecast'!N86+'FY15 Working Forecast'!N89 -> 21853.26 | H46: =+'FY15 Budget'!O72+'FY15 Budget'!O73+'FY15 Budget'!O74+'FY15 Budget'!O75+'FY15 Budget'!O76 -> 24000 | I46: =+'FY15 Current Forecast'!O82+'FY15 Current Forecast'!O83+'FY15 Current Forecast'!O84+'FY15 Current Forecast'!O85+'FY15 Current Forecast'!O86+'FY15 Current Forecast'!O89 -> 0 | J46: =+'FY15 Working Forecast'!O82+'FY15 Working Forecast'!O83+'FY15 Working Forecast'!O84+'FY15 Working Forecast'!O85+'FY15 Working Forecast'!O86+'FY15 Working Forecast'!O89 -> 319100.91
B47: Sub-Total Autoimmune | C47: =SUM(C46:C46) -> 2000 | D47: =SUM(D46:D46) -> 0 | E47: =SUM(E46:E46) -> 21853.26 | H47: =SUM(H46:H46) -> 24000 | I47: =SUM(I46:I46) -> 0 | J47: =SUM(J46:J46) -> 319100.91
A49: Imaging | B49: Cincinnati | C49: =+SUM('FY15 Budget'!N202:N203) -> 37838 | D49: =+SUM('FY15 Current Forecast'!N234:N235) -> 0 | E49: =+SUM('FY15 Working Forecast'!N234:N235) -> 62108.37 | H49: =+SUM('FY15 Budget'!O202:O203) -> 491896 | I49: =+SUM('FY15 Current Forecast'!O234:O235) -> 0 | J49: =+SUM('FY15 Working Forecast'!O234:O235) -> 778207.05
B50: KN | C50: =+SUM('FY15 Budget'!N198:N201)+'FY15 Budget'!N86+'FY15 Budget'!N87+'FY15 Budget'!N88+'FY15 Budget'!N89 -> 109441 | D50: =+SUM('FY15 Current Forecast'!N229:N232)+'FY15 Current Forecast'!N96 -> 0 | E50: =+SUM('FY15 Working Forecast'!N229:N232)+'FY15 Working Forecast'!N96 -> 109236.66 | H50: =+SUM('FY15 Budget'!O198:O201)+'FY15 Budget'!O86+'FY15 Budget'!O87+'FY15 Budget'!O88+'FY15 Budget'!O89 -> 1422737 | I50: =+SUM('FY15 Current Forecast'!O229:O232)+'FY15 Current Forecast'!O96 -> 0 | J50: =+SUM('FY15 Working Forecast'!O229:O232)+'FY15 Working Forecast'!O96 -> 1448006.1
B51: Canada | C51: =+'FY15 Budget'!N283 -> 21571.828 | D51: =+'FY15 Current Forecast'!N315+'FY15 Current Forecast'!N316 -> 0 | E51: =+'FY15 Working Forecast'!N315+'FY15 Working Forecast'!N316 -> 6284.78 | H51: =+'FY15 Budget'!O283 -> 280431.9 | I51: =+'FY15 Current Forecast'!O315+'FY15 Current Forecast'!O316 -> 0 | J51: =+'FY15 Working Forecast'!O315+'FY15 Working Forecast'!O316 -> 239832.91
B52: Optison | C52: 0 | D52: =+'FY15 Current Forecast'!N233 -> 0 | E52: =+'FY15 Working Forecast'!N233 -> 0 | H52: 0 | I52: =+'FY15 Current Forecast'!O233 -> 0 | J52: =+'FY15 Working Forecast'!O233 -> 0
B53: Dublin | C53: =+'FY15 Budget'!N185 -> 0 | D53: =+'FY15 Current Forecast'!N216 -> 0 | E53: =+'FY15 Working Forecast'!N216 -> 0 | H53: =+'FY15 Budget'!O185 -> 0 | I53: =+'FY15 Current Forecast'!O216 -> 0 | J53: =+'FY15 Working Forecast'!O216 -> 0
B54: Sub-Total Contrast | C54: =SUM(C49:C53) -> 168850.83 | D54: =SUM(D49:D53) -> 0 | E54: =SUM(E49:E53) -> 177629.81 | H54: =SUM(H49:H53) -> 2195064.9 | I54: =SUM(I49:I53) -> 0 | J54: =SUM(J49:J53) -> 2466046.1
A56: Nuc Med | B56: Nuc Med Direct | C56: =+'FY15 Budget'!N293+'FY15 Budget'!N288+'FY15 Budget'!N292+'FY15 Budget'!N79+'FY15 Budget'!N80+'FY15 Budget'!N81+'FY15 Budget'!N82+'FY15 Budget'!N83+'FY15 Budget'!N84+'FY15 Budget'!N85+'FY15 Budget'!N289+'FY15 Budget'!N290 -> 1500000 | D56: =+'FY15 Current Forecast'!N326+'FY15 Current Forecast'!N327+'FY15 Current Forecast'!N329+'FY15 Current Forecast'!N90+'FY15 Current Forecast'!N91+'FY15 Current Forecast'!N92+'FY15 Current Forecast'!N93+'FY15 Current Forecast'!N94+'FY15 Current Forecast'!N95+'FY15 Current Forecast'!N322+'FY15 Current Forecast'!N323+'FY15 Current Forecast'!N324 -> 0 | E56: =+'FY15 Working Forecast'!N326+'FY15 Working Forecast'!N327+'FY15 Working Forecast'!N329+'FY15 Working Forecast'!N90+'FY15 Working Forecast'!N91+'FY15 Working Forecast'!N92+'FY15 Working Forecast'!N93+'FY15 Working Forecast'!N94+'FY15 Working Forecast'!N95+'FY15 Working Forecast'!N322+'FY15 Working Forecast'!N323+'FY15 Working Forecast'!N324+'FY15 Working Forecast'!N325 -> 910383.41 | H56: =+'FY15 Budget'!O293+'FY15 Budget'!O288+'FY15 Budget'!O292+'FY15 Budget'!O79+'FY15 Budget'!O80+'FY15 Budget'!O81+'FY15 Budget'!O82+'FY15 Budget'!O83+'FY15 Budget'!O84+'FY15 Budget'!O85+'FY15 Budget'!O289+'FY15 Budget'!O290 -> 19500000 | I56: =+'FY15 Current Forecast'!O326+'FY15 Current Forecast'!O327+'FY15 Current Forecast'!O329+'FY15 Current Forecast'!O90+'FY15 Current Forecast'!O91+'FY15 Current Forecast'!O92+'FY15 Current Forecast'!O93+'FY15 Current Forecast'!O94+'FY15 Current Forecast'!O95+'FY15 Current Forecast'!O322+'FY15 Current Forecast'!O323+'FY15 Current Forecast'!O324 -> 0 | J56: =+'FY15 Working Forecast'!O326+'FY15 Working Forecast'!O327+'FY15 Working Forecast'!O329+'FY15 Working Forecast'!O90+'FY15 Working Forecast'!O91+'FY15 Working Forecast'!O92+'FY15 Working Forecast'!O93+'FY15 Working Forecast'!O94+'FY15 Working Forecast'!O95+'FY15 Working Forecast'!O322+'FY15 Working Forecast'!O323+'FY15 Working Forecast'!O324+'FY15 Working Forecast'!O325 -> 13591257
B57: Petten | C57: =+'FY15 Budget'!N294+'FY15 Budget'!N295+'FY15 Budget'!N296+'FY15 Budget'!N297+'FY15 Budget'!N298 -> 0 | D57: =+'FY15 Current Forecast'!N330+'FY15 Current Forecast'!N331+'FY15 Current Forecast'!N332+'FY15 Current Forecast'!N333+'FY15 Current Forecast'!N334 -> 0 | E57: =+'FY15 Working Forecast'!N330+'FY15 Working Forecast'!N331+'FY15 Working Forecast'!N332+'FY15 Working Forecast'!N333+'FY15 Working Forecast'!N334 -> 8505.21 | H57: =+'FY15 Budget'!O294+'FY15 Budget'!O295+'FY15 Budget'!O296+'FY15 Budget'!O297+'FY15 Budget'!O298 -> 0 | I57: =+'FY15 Current Forecast'!O330+'FY15 Current Forecast'!O331+'FY15 Current Forecast'!O332+'FY15 Current Forecast'!O333+'FY15 Current Forecast'!O334 -> 0 | J57: =+'FY15 Working Forecast'!O330+'FY15 Working Forecast'!O331+'FY15 Working Forecast'!O332+'FY15 Working Forecast'!O333+'FY15 Working Forecast'!O334 -> 309960.97
B58: Canada | C58: =+'FY15 Budget'!N281-'FY15 Budget'!N285-'FY15 Budget'!N282 -> 229621.26 | D58: =+'FY15 Current Forecast'!N314-'FY15 Current Forecast'!N315-'FY15 Current Forecast'!N318+'FY15 Current Forecast'!N321+'FY15 Current Forecast'!N328 -> 0 | E58: =+'FY15 Working Forecast'!N314-'FY15 Working Forecast'!N315-'FY15 Working Forecast'!N318+'FY15 Working Forecast'!N321+'FY15 Working Forecast'!N328 -> 97233.16 | H58: =+'FY15 Budget'!O281-'FY15 Budget'!O285-'FY15 Budget'!O282 -> 2985074.6 | I58: =+'FY15 Current Forecast'!O314-'FY15 Current Forecast'!O315-'FY15 Current Forecast'!O318+'FY15 Current Forecast'!O321+'FY15 Current Forecast'!O328 -> 0 | J58: =+'FY15 Working Forecast'!O314-'FY15 Working Forecast'!O315-'FY15 Working Forecast'!O318+'FY15 Working Forecast'!O321+'FY15 Working Forecast'!O328 -> 1783202
B59: Sub-Total Maryland Heights | C59: =SUM(C56:C58) -> 1729621.3 | D59: =SUM(D56:D58) -> 0 | E59: =SUM(E56:E58) -> 1016121.8 | H59: =SUM(H56:H58) -> 22485075 | I59: =SUM(I56:I58) -> 0 | J59: =SUM(J56:J58) -> 15684420
B61: Total JDE and E1 Out Freight | C61: =SUM(C59,C54,C47,C44,C41,C36) -> 3145406.8 | D61: =SUM(D59,D54,D47,D44,D41,D36) -> 0 | E61: =SUM(E59,E54,E47,E44,E41,E36) -> 2507403.3 | H61: =SUM(H59,H54,H47,H44,H41,H36) -> 38374065 | I61: =SUM(I59,I54,I47,I44,I41,I36) -> 0 | J61: =SUM(J59,J54,J47,J44,J41,J36) -> 31061143
A63: International
B64: Puerto Rico | C64: =+'FY15 Budget'!N209 -> 0 | D64: =+'FY15 Current Forecast'!N240 -> 0 | E64: =+'FY15 Working Forecast'!N240 -> 52457.63 | H64: =+'FY15 Budget'!O209 -> 0 | I64: =+'FY15 Current Forecast'!O240 -> 0 | J64: =+'FY15 Working Forecast'!O240 -> -2123.51
B65: Austrailia | C65: =+'FY15 Budget'!N210 -> 0 | D65: =+'FY15 Current Forecast'!N241 -> 0 | E65: =+'FY15 Working Forecast'!N241 -> 118602.11 | H65: =+'FY15 Budget'!O210 -> 0 | I65: =+'FY15 Current Forecast'!O241 -> 0 | J65: =+'FY15 Working Forecast'!O241 -> 858793.88
B66: China | C66: =+'FY15 Budget'!N211+'FY15 Budget'!N213 -> 0 | D66: =+'FY15 Current Forecast'!N242+'FY15 Current Forecast'!N244 -> 0 | E66: =+'FY15 Working Forecast'!N242+'FY15 Working Forecast'!N244 -> 0 | H66: =+'FY15 Budget'!O211+'FY15 Budget'!O213 -> 0 | I66: =+'FY15 Current Forecast'!O242+'FY15 Current Forecast'!O244 -> 0 | J66: =+'FY15 Working Forecast'!O242+'FY15 Working Forecast'!O244 -> 215623.68
B67: Panama | C67: =+'FY15 Budget'!N207+'FY15 Budget'!N208 -> 0 | D67: =+'FY15 Current Forecast'!N238+'FY15 Current Forecast'!N239 -> 0 | E67: =+'FY15 Working Forecast'!N238+'FY15 Working Forecast'!N239 -> 1686.71 | H67: =+'FY15 Budget'!O207+'FY15 Budget'!O208 -> 0 | I67: =+'FY15 Current Forecast'!O238+'FY15 Current Forecast'!O239 -> 0 | J67: =+'FY15 Working Forecast'!O238+'FY15 Working Forecast'!O239 -> -114033.71
B68: Korea | D68: =+'FY15 Current Forecast'!N246 -> 0 | E68: =+'FY15 Working Forecast'!N246 -> 5207.92 | I68: =+'FY15 Current Forecast'!O246 -> 0 | J68: =+'FY15 Working Forecast'!O246 -> 79624.26
B69: Hong Kong | C69: =+'FY15 Budget'!N212 -> 0 | D69: =+'FY15 Current Forecast'!N243 -> 0 | E69: =+'FY15 Working Forecast'!N243 -> 83062.53 | H69: =+'FY15 Budget'!O212 -> 0 | I69: =+'FY15 Current Forecast'!O243 -> 0 | J69: =+'FY15 Working Forecast'!O243 -> 1253834.7
B70: Mexico | C70: =+'FY15 Budget'!N214 -> 0 | D70: =+'FY15 Current Forecast'!N245 -> 0 | E70: =+'FY15 Working Forecast'!N245 -> 161385.74 | H70: =+'FY15 Budget'!O214 -> 0 | I70: =+'FY15 Current Forecast'!O245 -> 0 | J70: =+'FY15 Working Forecast'!O245 -> 267551.24
B71: Brazil | C71: =+'FY15 Budget'!N216 -> 0 | D71: =+'FY15 Current Forecast'!N248 -> 0 | E71: =+'FY15 Working Forecast'!N248 -> 111481.67 | H71: =+'FY15 Budget'!O216 -> 0 | I71: =+'FY15 Current Forecast'!O248 -> 0 | J71: =+'FY15 Working Forecast'!O248 -> 2240337.3
B72: Chile | D72: =+'FY15 Current Forecast'!N249 -> 0 | E72: =+'FY15 Working Forecast'!N249 -> 5339.8 | I72: =+'FY15 Current Forecast'!O249 -> 0 | J72: =+'FY15 Working Forecast'!O249 -> 419048.57
B73: Columbia | C73: =+'FY15 Budget'!N215 -> 0 | D73: =+'FY15 Current Forecast'!N247 -> 0 | E73: =+'FY15 Working Forecast'!N247 -> 1864.99 | H73: =+'FY15 Budget'!O215 -> 0 | I73: =+'FY15 Current Forecast'!O247 -> 0 | J73: =+'FY15 Working Forecast'!O247 -> 131264.53
B74: Argentina | C74: =+'FY15 Budget'!N316+'FY15 Budget'!N317 -> 0 | D74: =+'FY15 Current Forecast'!N352+'FY15 Current Forecast'!N353 -> 0 | E74: =+'FY15 Working Forecast'!N352+'FY15 Working Forecast'!N353 -> 12305.59 | H74: =+'FY15 Budget'!O316+'FY15 Budget'!O317 -> 0 | I74: =+'FY15 Current Forecast'!O352+'FY15 Current Forecast'!O353 -> 0 | J74: =+'FY15 Working Forecast'!O352+'FY15 Working Forecast'!O353 -> 105632.64
B75: Japan | C75: =SUM('FY15 Budget'!N319:N327) -> 0 | D75: =SUM('FY15 Current Forecast'!N355:N363) -> 0 | E75: =SUM('FY15 Working Forecast'!N355:N363) -> 95795.5 | H75: =SUM('FY15 Budget'!O319:O327) -> 0 | I75: =SUM('FY15 Current Forecast'!O355:O363) -> 0 | J75: =SUM('FY15 Working Forecast'!O355:O363) -> 644980.37
B76: Europe sites on E1 | C76: =+'FY15 Budget'!N218+'FY15 Budget'!N247+'FY15 Budget'!N248+'FY15 Budget'!N249+'FY15 Budget'!N251+'FY15 Budget'!N252+'FY15 Budget'!N253+'FY15 Budget'!N254+'FY15 Budget'!N255+'FY15 Budget'!N256+'FY15 Budget'!N257+'FY15 Budget'!N258+'FY15 Budget'!N259+'FY15 Budget'!N260+'FY15 Budget'!N261+'FY15 Budget'!N262+'FY15 Budget'!N263+'FY15 Budget'!N264+'FY15 Budget'!N265+'FY15 Budget'!N266+'FY15 Budget'!N267+'FY15 Budget'!N268+'FY15 Budget'!N269+'FY15 Budget'!N270+'FY15 Budget'!N271+'FY15 Budget'!N272+'FY15 Budget'!N273+'FY15 Budget'!N274+'FY15 Budget'!N275+'FY15 Budget'!N276+'FY15 Budget'!N219+'FY15 Budget'!N220+'FY15 Budget'!N221+'FY15 Budget'!N245+'FY15 Budget'!N246+'FY15 Budget'!N243+'FY15 Budget'!N244+'FY15 Budget'!N222+'FY15 Budget'!N223+'FY15 Budget'!N224+'FY15 Budget'!N225+'FY15 Budget'!N226+'FY15 Budget'!N227+'FY15 Budget'!N228+'FY15 Budget'!N229+'FY15 Budget'!N230+'FY15 Budget'!N231+'FY15 Budget'!N232+'FY15 Budget'!N234+'FY15 Budget'!N235+'FY15 Budget'!N236+'FY15 Budget'!N237+'FY15 Budget'!N238+'FY15 Budget'!N239+'FY15 Budget'!N240+'FY15 Budget'!N241+'FY15 Budget'!N242+'FY15 Budget'!N328 -> 0 | D76: =+'FY15 Current Forecast'!N250+'FY15 Current Forecast'!N279+'FY15 Current Forecast'!N280+'FY15 Current Forecast'!N281+'FY15 Current Forecast'!N283+'FY15 Current Forecast'!N284+'FY15 Current Forecast'!N285+'FY15 Current Forecast'!N286+'FY15 Current Forecast'!N287+'FY15 Current Forecast'!N288+'FY15 Current Forecast'!N289+'FY15 Current Forecast'!N290+'FY15 Current Forecast'!N291+'FY15 Current Forecast'!N292+'FY15 Current Forecast'!N293+'FY15 Current Forecast'!N295+'FY15 Current Forecast'!N296+'FY15 Current Forecast'!N297+'FY15 Current Forecast'!N298+'FY15 Current Forecast'!N299+'FY15 Current Forecast'!N300+'FY15 Current Forecast'!N301+'FY15 Current Forecast'!N302+'FY15 Current Forecast'!N303+'FY15 Current Forecast'!N304+'FY15 Current Forecast'!N305+'FY15 Current Forecast'!N306+'FY15 Current Forecast'!N307+'FY15 Current Forecast'!N308+'FY15 Current Forecast'!N309+'FY15 Current Forecast'!N251+'FY15 Current Forecast'!N252+'FY15 Current Forecast'!N253+'FY15 Current Forecast'!N277+'FY15 Current Forecast'!N278+'FY15 Current Forecast'!N282+'FY15 Current Forecast'!N294+'FY15 Current Forecast'!N275+'FY15 Current Forecast'!N276+'FY15 Current Forecast'!N254+'FY15 Current Forecast'!N255+'FY15 Current Forecast'!N256+'FY15 Current Forecast'!N257+'FY15 Current Forecast'!N258+'FY15 Current Forecast'!N259+'FY15 Current Forecast'!N260+'FY15 Current Forecast'!N261+'FY15 Current Forecast'!N262+'FY15 Current Forecast'!N263+'FY15 Current Forecast'!N264+'FY15 Current Forecast'!N266+'FY15 Current Forecast'!N267+'FY15 Current Forecast'!N268+'FY15 Current Forecast'!N269+'FY15 Current Forecast'!N270+'FY15 Current Forecast'!N271+'FY15 Current Forecast'!N272+'FY15 Current Forecast'!N273+'FY15 Current Forecast'!N274+'FY15 Current Forecast'!N265 -> 0 | E76: =+'FY15 Working Forecast'!N250+'FY15 Working Forecast'!N279+'FY15 Working Forecast'!N280+'FY15 Working Forecast'!N281+'FY15 Working Forecast'!N283+'FY15 Working Forecast'!N284+'FY15 Working Forecast'!N285+'FY15 Working Forecast'!N286+'FY15 Working Forecast'!N287+'FY15 Working Forecast'!N288+'FY15 Working Forecast'!N289+'FY15 Working Forecast'!N290+'FY15 Working Forecast'!N291+'FY15 Working Forecast'!N292+'FY15 Working Forecast'!N293+'FY15 Working Forecast'!N295+'FY15 Working Forecast'!N296+'FY15 Working Forecast'!N297+'FY15 Working Forecast'!N298+'FY15 Working Forecast'!N299+'FY15 Working Forecast'!N300+'FY15 Working Forecast'!N301+'FY15 Working Forecast'!N302+'FY15 Working Forecast'!N303+'FY15 Working Forecast'!N304+'FY15 Working Forecast'!N305+'FY15 Working Forecast'!N306+'FY15 Working Forecast'!N307+'FY15 Working Forecast'!N308+'FY15 Working Forecast'!N309+'FY15 Working Forecast'!N251+'FY15 Working Forecast'!N252+'FY15 Working Forecast'!N253+'FY15 Working Forecast'!N277+'FY15 Working Forecast'!N278+'FY15 Working Forecast'!N282+'FY15 Working Forecast'!N294+'FY15 Working Forecast'!N275+'FY15 Working Forecast'!N276+'FY15 Working Forecast'!N254+'FY15 Working Forecast'!N255+'FY15 Working Forecast'!N256+'FY15 Working Forecast'!N257+'FY15 Working Forecast'!N258+'FY15 Working Forecast'!N259+'FY15 Working Forecast'!N260+'FY15 Working Forecast'!N261+'FY15 Working Forecast'!N262+'FY15 Working Forecast'!N263+'FY15 Working Forecast'!N264+'FY15 Working Forecast'!N266+'FY15 Working Forecast'!N267+'FY15 Working Forecast'!N268+'FY15 Working Forecast'!N269+'FY15 Working Forecast'!N270+'FY15 Working Forecast'!N271+'FY15 Working Forecast'!N272+'FY15 Working Forecast'!N273+'FY15 Working Forecast'!N274+'FY15 Working Forecast'!N364+'FY15 Current Forecast'!N364+'FY15 Working Forecast'!N265 -> 2133289.9 | H76: =+'FY15 Budget'!O218+'FY15 Budget'!O247+'FY15 Budget'!O248+'FY15 Budget'!O249+'FY15 Budget'!O251+'FY15 Budget'!O252+'FY15 Budget'!O253+'FY15 Budget'!O254+'FY15 Budget'!O255+'FY15 Budget'!O256+'FY15 Budget'!O257+'FY15 Budget'!O258+'FY15 Budget'!O259+'FY15 Budget'!O260+'FY15 Budget'!O261+'FY15 Budget'!O262+'FY15 Budget'!O263+'FY15 Budget'!O264+'FY15 Budget'!O265+'FY15 Budget'!O266+'FY15 Budget'!O267+'FY15 Budget'!O268+'FY15 Budget'!O269+'FY15 Budget'!O270+'FY15 Budget'!O271+'FY15 Budget'!O272+'FY15 Budget'!O273+'FY15 Budget'!O274+'FY15 Budget'!O275+'FY15 Budget'!O276+'FY15 Budget'!O219+'FY15 Budget'!O220+'FY15 Budget'!O221+'FY15 Budget'!O245+'FY15 Budget'!O246+'FY15 Budget'!O243+'FY15 Budget'!O244+'FY15 Budget'!O222+'FY15 Budget'!O223+'FY15 Budget'!O224+'FY15 Budget'!O225+'FY15 Budget'!O226+'FY15 Budget'!O227+'FY15 Budget'!O228+'FY15 Budget'!O229+'FY15 Budget'!O230+'FY15 Budget'!O231+'FY15 Budget'!O232+'FY15 Budget'!O234+'FY15 Budget'!O235+'FY15 Budget'!O236+'FY15 Budget'!O237+'FY15 Budget'!O238+'FY15 Budget'!O239+'FY15 Budget'!O240+'FY15 Budget'!O241+'FY15 Budget'!O242+'FY15 Budget'!O328 -> 0 | I76: =+'FY15 Current Forecast'!O250+'FY15 Current Forecast'!O279+'FY15 Current Forecast'!O280+'FY15 Current Forecast'!O281+'FY15 Current Forecast'!O283+'FY15 Current Forecast'!O284+'FY15 Current Forecast'!O285+'FY15 Current Forecast'!O286+'FY15 Current Forecast'!O287+'FY15 Current Forecast'!O288+'FY15 Current Forecast'!O289+'FY15 Current Forecast'!O290+'FY15 Current Forecast'!O291+'FY15 Current Forecast'!O292+'FY15 Current Forecast'!O293+'FY15 Current Forecast'!O295+'FY15 Current Forecast'!O296+'FY15 Current Forecast'!O297+'FY15 Current Forecast'!O298+'FY15 Current Forecast'!O299+'FY15 Current Forecast'!O300+'FY15 Current Forecast'!O301+'FY15 Current Forecast'!O302+'FY15 Current Forecast'!O303+'FY15 Current Forecast'!O304+'FY15 Current Forecast'!O305+'FY15 Current Forecast'!O306+'FY15 Current Forecast'!O307+'FY15 Current Forecast'!O308+'FY15 Current Forecast'!O309+'FY15 Current Forecast'!O251+'FY15 Current Forecast'!O252+'FY15 Current Forecast'!O253+'FY15 Current Forecast'!O277+'FY15 Current Forecast'!O278+'FY15 Current Forecast'!O282+'FY15 Current Forecast'!O294+'FY15 Current Forecast'!O275+'FY15 Current Forecast'!O276+'FY15 Current Forecast'!O254+'FY15 Current Forecast'!O255+'FY15 Current Forecast'!O256+'FY15 Current Forecast'!O257+'FY15 Current Forecast'!O258+'FY15 Current Forecast'!O259+'FY15 Current Forecast'!O260+'FY15 Current Forecast'!O261+'FY15 Current Forecast'!O262+'FY15 Current Forecast'!O263+'FY15 Current Forecast'!O264+'FY15 Current Forecast'!O266+'FY15 Current Forecast'!O267+'FY15 Current Forecast'!O268+'FY15 Current Forecast'!O269+'FY15 Current Forecast'!O270+'FY15 Current Forecast'!O271+'FY15 Current Forecast'!O272+'FY15 Current Forecast'!O273+'FY15 Current Forecast'!O274+'FY15 Current Forecast'!O364+'FY15 Current Forecast'!O265 -> 0 | J76: =SUM('FY15 Working Forecast'!O250:O309)+'FY15 Working Forecast'!O364+'FY15 Working Forecast'!O265 -> 20032474
B77: Total International | C77: =SUM(C64:C76) -> 0 | D77: =SUM(D64:D76) -> 0 | E77: =SUM(E64:E76) -> 2782480.1 | H77: =SUM(H64:H76) -> 0 | I77: =SUM(I64:I76) -> 0 | J77: =SUM(J64:J76) -> 26133008
B79: Total JDE and E1 Freight -Pharma | C79: =+C61+C25+C77 -> 3301909.1 | D79: =+D61+D25+D77 -> 0 | E79: =+E61+E25+E77 -> 5435515.9 | H79: =+H61+H25+H77 -> 40361259 | I79: =+I61+I25+I77 -> 0 | J79: =+J61+J25+J77 -> 59506974
B81: Global Pharma/Imaging - CYR | C81: =+check!C10 -> 3301909.1 | D81: =+check!D10 -> 0 | E81: =+check!B10 -> 5435515.9 | H81: =+check!G10 -> 40361259 | I81: =+check!H10 -> 0 | J81: =check!F10 -> 59506486
B82: difference | C82: =+C79-C81 -> 0 | D82: =+D79-D81 -> 0 | E82: =+E79-E81 -> 0 | H82: =+H79-H81 -> 0 | I82: =+I79-I81 -> 0 | J82: =+J79-J81 -> 488
A84: This report is NOT total Mallinckrodt, OUS regions not converted to E1 are not included in the numbers above.

Sheet Freight report
A1: Pharma Freight Actual VS Budget
B2: FY13 | C2: March | G2: YTD | K2: Full Year
C3: Actual | D3: Budget | E3: B/(W) | G3: Actual | H3: Budget | I3: B/(W) | K3: Budget | L3: Current Forecast | M3: B/(W)
A5: In Freight
A6: API | B6: STL StearPhos/Gateway | C6: =#REF! -> #REF! | E6: =+D6-C6 -> #REF! | G6: =#REF! -> #REF! | I6: =+H6-G6 -> #REF! | M6: =+L6-K6 -> 0
B7: Japan | C7: =+#REF!+#REF!+#REF!+#REF! -> #REF! | G7: =+#REF!+#REF!+#REF!+#REF! -> #REF! | L7: =+'FY15 Current Forecast'!O59+'FY15 Current Forecast'!O61 -> 0
B8: UK PAP/APAP | C8: =#REF! -> #REF! | D8: =+'FY15 Budget'!H51+'FY15 Budget'!H52+'FY15 Budget'!H55+'FY15 Budget'!H57 -> 111832.17 | E8: =+D8-C8 -> #REF! | G8: =#REF! -> #REF! | H8: =+'FY15 Budget'!C51+'FY15 Budget'!C52+'FY15 Budget'!C55+'FY15 Budget'!C57+'FY15 Budget'!D51+'FY15 Budget'!D52+'FY15 Budget'!D55+'FY15 Budget'!D57+'FY15 Budget'!E51+'FY15 Budget'!E52+'FY15 Budget'!E55+'FY15 Budget'!E57+'FY15 Budget'!F51+'FY15 Budget'!F52+'FY15 Budget'!F55+'FY15 Budget'!F57+'FY15 Budget'!G51+'FY15 Budget'!G52+'FY15 Budget'!G55+'FY15 Budget'!G57+'FY15 Budget'!H51+'FY15 Budget'!H52+'FY15 Budget'!H55+'FY15 Budget'!H57 -> 726909.09 | I8: =+H8-G8 -> #REF! | K8: =+'FY15 Budget'!O51+'FY15 Budget'!O52+'FY15 Budget'!O55+'FY15 Budget'!O57 -> 1453818.2 | L8: =+'FY15 Current Forecast'!O52+'FY15 Current Forecast'!O53+'FY15 Current Forecast'!O55+'FY15 Current Forecast'!O57 -> 0 | M8: =+L8-K8 -> -1453818.2
B9: UK Bulk Narcotics | C9: =+#REF! -> #REF! | D9: =+'FY15 Budget'!H50 -> 0 | E9: =+D9-C9 -> #REF! | G9: =#REF! -> #REF! | H9: =+'FY15 Budget'!C50+'FY15 Budget'!D50+'FY15 Budget'!E50+'FY15 Budget'!F50+'FY15 Budget'!G50+'FY15 Budget'!H50 -> 0 | I9: =+H9-G9 -> #REF! | K9: =+'FY15 Budget'!O50 -> 0 | L9: =+'FY15 Current Forecast'!O51 -> 0 | M9: =+L9-K9 -> 0
B10: UK Stear/Phos | C10: =#REF! -> #REF! | D10: =+'FY15 Budget'!H53 -> 5425.1694 | E10: =+D10-C10 -> #REF! | G10: =#REF! -> #REF! | H10: =+'FY15 Budget'!C53+'FY15 Budget'!D53+'FY15 Budget'!E53+'FY15 Budget'!F53+'FY15 Budget'!G53+'FY15 Budget'!H53 -> 35263.601 | I10: =+H10-G10 -> #REF! | K10: =+'FY15 Budget'!O53 -> 70527.202 | L10: =+'FY15 Current Forecast'!O54 -> 0 | M10: =+L10-K10 -> -70527.202
B11: Canada PHM | C11: =+#REF! -> #REF! | D11: =+'FY15 Budget'!H59 -> 0 | E11: =+D11-C11 -> #REF! | G11: =+#REF! -> #REF! | H11: =+'FY15 Budget'!C59+'FY15 Budget'!D59+'FY15 Budget'!E59+'FY15 Budget'!F59+'FY15 Budget'!G59+'FY15 Budget'!H59 -> 0 | I11: =+H11-G11 -> #REF! | K11: =+'FY15 Budget'!O59 -> 0 | L11: =+'FY15 Current Forecast'!O69 -> 0 | M11: =+L11-K11 -> 0
B12: Sub-Total API In Freight | C12: =SUM(C6:C11) -> #REF! | D12: =SUM(D6:D11) -> 117257.34 | E12: =SUM(E6:E11) -> #REF! | G12: =SUM(G6:G11) -> #REF! | H12: =SUM(H6:H11) -> 762172.69 | I12: =SUM(I6:I11) -> #REF! | K12: =SUM(K6:K11) -> 1524345.4 | L12: =SUM(L6:L11) -> 0 | M12: =SUM(M6:M11) -> -1524345.4
A14: Dosage | B14: Hobart | C14: =SUM(#REF!,#REF!) -> #REF! | D14: =+SUM('FY15 Budget'!H8:H49)+'FY15 Budget'!H56 -> 24803.452 | E14: =+D14-C14 -> #REF! | G14: =SUM(#REF!,#REF!) -> #REF! | H14: =+SUM('FY15 Budget'!C8:C49)+SUM('FY15 Budget'!D8:D49)+SUM('FY15 Budget'!E8:E49)+SUM('FY15 Budget'!F8:F49)+SUM('FY15 Budget'!G8:G49)+SUM('FY15 Budget'!H8:H49) -> 147671.62 | I14: =+H14-G14 -> #REF! | K14: =+SUM('FY15 Budget'!O8:O49) -> 299030.65 | L14: =+SUM('FY15 Current Forecast'!O8:O50)+'FY15 Current Forecast'!O56 -> 0 | M14: =+L14-K14 -> -299030.65
B15: CNS/Intrathecal | C15: =+#REF!+#REF! -> #REF! | D15: =+'FY15 Budget'!H66+'FY15 Budget'!H67 -> 4323.0783 | E15: =+D15-C15 -> #REF! | G15: =+#REF!+#REF! -> #REF! | H15: =+'FY15 Budget'!C66+'FY15 Budget'!C67+'FY15 Budget'!D66+'FY15 Budget'!D67+'FY15 Budget'!E66+'FY15 Budget'!E67+'FY15 Budget'!F66+'FY15 Budget'!F67+'FY15 Budget'!G66+'FY15 Budget'!G67+'FY15 Budget'!H66+'FY15 Budget'!H67 -> 25938.47 | I15: =+H15-G15 -> #REF! | K15: =+'FY15 Budget'!O66+'FY15 Budget'!O67 -> 51876.94 | L15: =+'FY15 Current Forecast'!O76+'FY15 Current Forecast'!O77 -> 0 | M15: =+L15-K15 -> -51876.94
B16: Sub-Total Dosage In Freight | C16: =SUM(C14:C15) -> #REF! | D16: =SUM(D14:D15) -> 29126.53 | E16: =SUM(E14:E15) -> #REF! | G16: =SUM(G14:G15) -> #REF! | H16: =SUM(H14:H15) -> 173610.09 | I16: =SUM(I14:I15) -> #REF! | K16: =SUM(K14:K15) -> 350907.59 | L16: =SUM(L14:L15) -> 0 | M16: =SUM(M14:M15) -> -350907.59
A18: Imaging | B18: Joliet/Cincinnati/KN | C18: =+#REF!+#REF!+#REF!+#REF!+#REF!+#REF! -> #REF! | D18: =+SUM('FY15 Budget'!H191:H196) -> 0 | E18: =+D18-C18 -> #REF! | G18: =+#REF!+#REF!+#REF!+#REF!+#REF!++#REF! -> #REF! | H18: =+SUM('FY15 Budget'!C191:C196)+SUM('FY15 Budget'!D191:D196)+SUM('FY15 Budget'!E191:E196)+SUM('FY15 Budget'!F191:F196)+SUM('FY15 Budget'!G191:G196)+SUM('FY15 Budget'!H191:H196) -> 0 | I18: =+H18-G18 -> #REF! | K18: =+SUM('FY15 Budget'!O191:O196) -> 0 | L18: =+SUM('FY15 Current Forecast'!O214:O218) -> 0 | M18: =+L18-K18 -> 0
B19: Canada | C19: =+#REF!-#REF! -> #REF! | D19: =+'FY15 Budget'!H277 -> 0 | E19: =+D19-C19 -> #REF! | G19: =+#REF!-#REF! -> #REF! | H19: =+'FY15 Budget'!C277+'FY15 Budget'!D277+'FY15 Budget'!E277+'FY15 Budget'!F277+'FY15 Budget'!G277+'FY15 Budget'!H277 -> 0 | I19: =+H19-G19 -> #REF! | K19: =+'FY15 Budget'!O277 -> 0 | L19: =+'FY15 Current Forecast'!O301 -> 0 | M19: =+L19-K19 -> 0
B20: Sub-Total Imaging In Freight | C20: =SUM(C18:C19) -> #REF! | D20: =SUM(D18:D19) -> 0 | E20: =SUM(E18:E19) -> #REF! | G20: =SUM(G18:G19) -> #REF! | H20: =SUM(H18:H19) -> 0 | I20: =SUM(I18:I19) -> #REF! | K20: =SUM(K18:K19) -> 0 | L20: =SUM(L18:L19) -> 0 | M20: =SUM(M18:M19) -> 0
B22: Total InFreight | C22: =SUM(C12,C16,C20) -> #REF! | D22: =SUM(D12,D16,D20) -> 146383.87 | E22: =SUM(E12,E16,E20) -> #REF! | G22: =SUM(G12,G16,G20) -> #REF! | H22: =SUM(H12,H16,H20) -> 935782.78 | I22: =SUM(I12,I16,I20) -> #REF! | K22: =SUM(K12,K16,K20) -> 1875253 | L22: =SUM(L12,L16,L20) -> 0 | M22: =SUM(M12,M16,M20) -> -1875253
A24: Out Freight
A25: API | B25: STL StearPhos/Gateway | C25: =+#REF!+#REF!+#REF!+#REF!+#REF!+#REF!+#REF!+#REF!+#REF!+#REF!+#REF!+#REF!+#REF! -> #REF! | D25: =+'FY15 Budget'!H105+'FY15 Budget'!H129+'FY15 Budget'!H131+'FY15 Budget'!H124+'FY15 Budget'!H110 -> 0 | E25: =+D25-C25 -> #REF! | G25: =+#REF!+#REF!+#REF!+#REF!+#REF!+#REF!+#REF!+#REF!+#REF!+#REF!+#REF!+#REF!+#REF! -> #REF! | H25: =+'FY15 Budget'!C105+'FY15 Budget'!C129+'FY15 Budget'!C131+'FY15 Budget'!C124+'FY15 Budget'!C110+'FY15 Budget'!D105+'FY15 Budget'!D129+'FY15 Budget'!D131+'FY15 Budget'!D124+'FY15 Budget'!D110+'FY15 Budget'!E105+'FY15 Budget'!E129+'FY15 Budget'!E131+'FY15 Budget'!E124+'FY15 Budget'!E110+'FY15 Budget'!F105+'FY15 Budget'!F129+'FY15 Budget'!F131+'FY15 Budget'!F124+'FY15 Budget'!F110+'FY15 Budget'!G105+'FY15 Budget'!G129+'FY15 Budget'!G131+'FY15 Budget'!G124+'FY15 Budget'!G110+'FY15 Budget'!H105+'FY15 Budget'!H129+'FY15 Budget'!H131+'FY15 Budget'!H124+'FY15 Budget'!H110 -> 0 | I25: =+H25-G25 -> #REF! | K25: =+'FY15 Budget'!O105+'FY15 Budget'!O129+'FY15 Budget'!O131+'FY15 Budget'!O124+'FY15 Budget'!O110 -> 0 | L25: =+'FY15 Current Forecast'!O152+'FY15 Current Forecast'!O154+'FY15 Current Forecast'!O148+'FY15 Current Forecast'!O60+'FY15 Current Forecast'!O116+'FY15 Current Forecast'!O128+'FY15 Current Forecast'!O147+'FY15 Current Forecast'!O132 -> 0 | M25: =+L25-K25 -> 0
B26: STL Plant Narcotics | C26: =+#REF!+#REF!+SUM(#REF!)+#REF!+#REF!+#REF!+#REF! -> #REF! | D26: =+'FY15 Budget'!H127+'FY15 Budget'!H123 -> 0 | E26: =+D26-C26 -> #REF! | G26: =+#REF!+#REF!+SUM(#REF!)+#REF!+#REF!+#REF!+#REF! -> #REF! | H26: =+'FY15 Budget'!C127+'FY15 Budget'!C123+'FY15 Budget'!D127+'FY15 Budget'!D123+'FY15 Budget'!E127+'FY15 Budget'!E123+'FY15 Budget'!F127+'FY15 Budget'!F123+'FY15 Budget'!G127+'FY15 Budget'!G123+'FY15 Budget'!H127+'FY15 Budget'!H123 -> 0 | I26: =+H26-G26 -> #REF! | K26: =+'FY15 Budget'!O127+'FY15 Budget'!O123 -> 0 | L26: =+'FY15 Current Forecast'!O150+'FY15 Current Forecast'!O142+'FY15 Current Forecast'!O144+'FY15 Current Forecast'!O145+'FY15 Current Forecast'!O146+'FY15 Current Forecast'!O111+'FY15 Current Forecast'!O117+'FY15 Current Forecast'!O133+'FY15 Current Forecast'!O134+'FY15 Current Forecast'!O135+'FY15 Current Forecast'!O136+'FY15 Current Forecast'!O122 -> 0 | M26: =+L26-K26 -> 0
B27: Peptides | C27: =+#REF!+#REF! -> #REF! | E27: =+D27-C27 -> #REF! | G27: =+#REF!+#REF! -> #REF! | I27: =+H27-G27 -> #REF! | M27: =+L27-K27 -> 0
B28: APAP/COMPAP | C28: =+#REF!+#REF!+#REF!+#REF!+#REF!+#REF!+#REF!+#REF!+#REF!+#REF!+#REF!+#REF!+#REF!+#REF!+#REF!+#REF!+#REF!+#REF!+#REF!+#REF!+#REF!+#REF!+#REF! -> #REF! | D28: =+'FY15 Budget'!H126+'FY15 Budget'!H109+'FY15 Budget'!H184+'FY15 Budget'!H102+'FY15 Budget'!H119+'FY15 Budget'!H183 -> 126920 | E28: =+D28-C28 -> #REF! | G28: =+#REF!+#REF!+#REF!+#REF!+#REF!+#REF!+#REF!+#REF!+#REF!+#REF!+#REF!+#REF!+#REF!+#REF!+#REF!+#REF!+#REF!+#REF!+#REF!+#REF!+#REF!+#REF!+#REF! -> #REF! | H28: =+'FY15 Budget'!C126+'FY15 Budget'!C109+'FY15 Budget'!C184+'FY15 Budget'!C102+'FY15 Budget'!C119+'FY15 Budget'!C183+'FY15 Budget'!D126+'FY15 Budget'!D109+'FY15 Budget'!D184+'FY15 Budget'!D102+'FY15 Budget'!D119+'FY15 Budget'!D183+'FY15 Budget'!E126+'FY15 Budget'!E109+'FY15 Budget'!E184+'FY15 Budget'!E102+'FY15 Budget'!E119+'FY15 Budget'!E183+'FY15 Budget'!F126+'FY15 Budget'!F109+'FY15 Budget'!F184+'FY15 Budget'!F102+'FY15 Budget'!F119+'FY15 Budget'!F183+'FY15 Budget'!G126+'FY15 Budget'!G109+'FY15 Budget'!G184+'FY15 Budget'!G102+'FY15 Budget'!G119+'FY15 Budget'!G183+'FY15 Budget'!H126+'FY15 Budget'!H109+'FY15 Budget'!H184+'FY15 Budget'!H102+'FY15 Budget'!H119+'FY15 Budget'!H183 -> 824980 | I28: =+H28-G28 -> #REF! | K28: =+'FY15 Budget'!O126+'FY15 Budget'!O109+'FY15 Budget'!O184+'FY15 Budget'!O102+'FY15 Budget'!O119+'FY15 Budget'!O183 -> 1649960 | L28: =+'FY15 Current Forecast'!O149+'FY15 Current Forecast'!#REF!+'FY15 Current Forecast'!O124+'FY15 Current Forecast'!O137+'FY15 Current Forecast'!O126+'FY15 Current Forecast'!O129+'FY15 Current Forecast'!O107+'FY15 Current Forecast'!O130+'FY15 Current Forecast'!O119+'FY15 Current Forecast'!#REF!+'FY15 Current Forecast'!O155+'FY15 Current Forecast'!O125+'FY15 Current Forecast'!O127+'FY15 Current Forecast'!O123+'FY15 Current Forecast'!O118+'FY15 Current Forecast'!O141+'FY15 Current Forecast'!O138 -> #REF! | M28: =+L28-K28 -> #REF!
B29: UK PAP/APAP | C29: =+#REF! -> #REF! | D29: =+'FY15 Budget'!H180 -> 124391.43 | E29: =+D29-C29 -> #REF! | G29: =+#REF! -> #REF! | H29: =+'FY15 Budget'!C180+'FY15 Budget'!D180+'FY15 Budget'!E180+'FY15 Budget'!F180+'FY15 Budget'!G180+'FY15 Budget'!H180 -> 808544.3 | I29: =+H29-G29 -> #REF! | K29: =+'FY15 Budget'!O180 -> 1617088.6 | L29: =+'FY15 Current Forecast'!O205 -> 0 | M29: =+L29-K29 -> -1617088.6
B30: UK Bulk Narcotics | C30: =+#REF! -> #REF! | D30: =+'FY15 Budget'!H181 -> 13635.088 | E30: =+D30-C30 -> #REF! | G30: =+#REF! -> #REF! | H30: =+'FY15 Budget'!C181+'FY15 Budget'!D181+'FY15 Budget'!E181+'FY15 Budget'!F181+'FY15 Budget'!G181+'FY15 Budget'!H181 -> 88628.073 | I30: =+H30-G30 -> #REF! | K30: =+'FY15 Budget'!O181 -> 177256.15 | L30: =+'FY15 Current Forecast'!O206 -> 0 | M30: =+L30-K30 -> -177256.15
B31: UK Stear/Phos | C31: =+#REF! -> #REF! | D31: =+'FY15 Budget'!H182 -> 5907.7515 | E31: =+D31-C31 -> #REF! | G31: =+#REF! -> #REF! | H31: =+'FY15 Budget'!C182+'FY15 Budget'!D182+'FY15 Budget'!E182+'FY15 Budget'!F182+'FY15 Budget'!G182+'FY15 Budget'!H182 -> 38400.385 | I31: =+H31-G31 -> #REF! | K31: =+'FY15 Budget'!O182 -> 76800.769 | L31: =+'FY15 Current Forecast'!O207 -> 0 | M31: =+L31-K31 -> -76800.769
B32: Goaling | D32: =+'FY15 Budget'!H116 -> 0 | E32: =+D32-C32 -> 0 | H32: =+'FY15 Budget'!C116+'FY15 Budget'!D116+'FY15 Budget'!E116+'FY15 Budget'!F116+'FY15 Budget'!G116+'FY15 Budget'!H116 -> 0 | I32: =+H32-G32 -> 0 | K32: =+'FY15 Budget'!O116 -> 0 | L32: =+'FY15 Current Forecast'!O139 -> 0 | M32: =+L32-K32 -> 0
B33: Sub-Total API Out Freight | C33: =SUM(C25:C32) -> #REF! | D33: =SUM(D25:D32) -> 270854.27 | E33: =SUM(E25:E32) -> #REF! | G33: =SUM(G25:G32) -> #REF! | H33: =SUM(H25:H32) -> 1760552.8 | I33: =SUM(I25:I32) -> #REF! | K33: =SUM(K25:K32) -> 3521105.5 | L33: =SUM(L25:L32) -> #REF! | M33: =SUM(M25:M32) -> #REF!
A35: Dosage | B35: Hobart | C35: =SUM(#REF!,#REF!)+#REF! -> #REF! | D35: =+SUM('FY15 Budget'!H134:H175) -> 438290.42 | E35: =+D35-C35 -> #REF! | G35: =SUM(#REF!,#REF!)+#REF! -> #REF! | H35: =+SUM('FY15 Budget'!C134:C175)+SUM('FY15 Budget'!D134:D175)+SUM('FY15 Budget'!E134:E175)+SUM('FY15 Budget'!F134:F175)+SUM('FY15 Budget'!G134:G175)+SUM('FY15 Budget'!H134:H175) -> 2856059.5 | I35: =+H35-G35 -> #REF! | K35: =+SUM('FY15 Budget'!O134:O175) -> 5658751.8 | L35: =+SUM('FY15 Current Forecast'!O156:O200) -> 0 | M35: =+L35-K35 -> -5658751.8
B36: CNS/Intrathecal | C36: =+#REF!+#REF! -> #REF! | D36: =+'FY15 Budget'!H70+'FY15 Budget'!H71 -> 25000 | E36: =+D36-C36 -> #REF! | G36: =+#REF!+#REF! -> #REF! | H36: =+'FY15 Budget'!C70+'FY15 Budget'!C71+'FY15 Budget'!D70+'FY15 Budget'!D71+'FY15 Budget'!E70+'FY15 Budget'!E71+'FY15 Budget'!F70+'FY15 Budget'!F71+'FY15 Budget'!G70+'FY15 Budget'!G71+'FY15 Budget'!H70+'FY15 Budget'!H71 -> 150000 | I36: =+H36-G36 -> #REF! | K36: =+'FY15 Budget'!O70+'FY15 Budget'!O71 -> 300000 | L36: =+'FY15 Current Forecast'!O80+'FY15 Current Forecast'!O81 -> 0 | M36: =+L36-K36 -> -300000
B37: Sub-Total Dosage Out Freight | C37: =SUM(C35:C36) -> #REF! | D37: =SUM(D35:D36) -> 463290.42 | E37: =SUM(E35:E36) -> #REF! | G37: =SUM(G35:G36) -> #REF! | H37: =SUM(H35:H36) -> 3006059.5 | I37: =SUM(I35:I36) -> #REF! | K37: =SUM(K35:K36) -> 5958751.8 | L37: =SUM(L35:L36) -> 0 | M37: =SUM(M35:M36) -> -5958751.8
A39: Imaging | B39: Cincinnati | C39: =+#REF!+#REF!+#REF!+#REF! -> #REF! | D39: =+SUM('FY15 Budget'!H202:H203) -> 37838 | E39: =+D39-C39 -> #REF! | G39: =+#REF!+#REF!+#REF! -> #REF! | H39: =+SUM('FY15 Budget'!C202:C203)+SUM('FY15 Budget'!D202:D203)+SUM('FY15 Budget'!E202:E203)+SUM('FY15 Budget'!F202:F203)+SUM('FY15 Budget'!G202:G203)+SUM('FY15 Budget'!H202:H203) -> 245948 | I39: =+H39-G39 -> #REF! | K39: =+SUM('FY15 Budget'!O202:O203) -> 491896 | L39: =+SUM('FY15 Current Forecast'!O224:O226) -> 0 | M39: =+L39-K39 -> -491896
B40: Contrast | C40: =+#REF!+#REF!+#REF!+#REF! -> #REF! | D40: =+SUM('FY15 Budget'!H200:H201) -> 109441 | E40: =+D40-C40 -> #REF! | G40: =+#REF!+#REF!+#REF!+#REF!+#REF! -> #REF! | H40: =+SUM('FY15 Budget'!C200:C201)+SUM('FY15 Budget'!D200:D201)+SUM('FY15 Budget'!E200:E201)+SUM('FY15 Budget'!F200:F201)+SUM('FY15 Budget'!G200:G201)+SUM('FY15 Budget'!H200:H201) -> 711368 | I40: =+H40-G40 -> #REF! | K40: =+SUM('FY15 Budget'!O200:O201) -> 1422737 | L40: =+SUM('FY15 Current Forecast'!O222:O223) -> 0 | M40: =+L40-K40 -> -1422737
B41: Canada | C41: =+#REF! -> #REF! | E41: =+D41-C41 -> #REF! | G41: =+#REF! -> #REF! | I41: =+H41-G41 -> #REF! | L41: =+'FY15 Current Forecast'!O306 -> 0 | M41: =+L41-K41 -> 0
B42: Sub-Total Contrast | C42: =SUM(C39:C41) -> #REF! | D42: =SUM(D39:D41) -> 147279 | E42: =SUM(E39:E41) -> #REF! | G42: =SUM(G39:G41) -> #REF! | H42: =SUM(H39:H41) -> 957316 | I42: =SUM(I39:I41) -> #REF! | K42: =SUM(K39:K41) -> 1914633 | L42: =SUM(L39:L41) -> 0 | M42: =SUM(M39:M41) -> -1914633
A44: Nuc Med | B44: Nuc Med Direct | C44: =SUM(#REF!)-C46 -> #REF! | D44: =+'FY15 Budget'!H292 -> 0 | E44: =+D44-C44 -> #REF! | G44: =SUM(#REF!)-G46 -> #REF! | H44: =+'FY15 Budget'!C292+'FY15 Budget'!D292+'FY15 Budget'!E292+'FY15 Budget'!F292+'FY15 Budget'!G292+'FY15 Budget'!H292 -> 0 | I44: =+H44-G44 -> #REF! | K44: =+'FY15 Budget'!O292 -> 0 | L44: =+'FY15 Current Forecast'!O312+'FY15 Current Forecast'!O227+'FY15 Current Forecast'!O313+'FY15 Current Forecast'!O315 -> 0 | M44: =+L44-K44 -> 0
B45: Canada | C45: =+#REF!+#REF!-#REF!+#REF!+#REF! -> #REF! | D45: =+'FY15 Budget'!H281 -> 229621.26 | E45: =+D45-C45 -> #REF! | G45: =+#REF!+#REF!-#REF!+#REF!+#REF! -> #REF! | H45: =+'FY15 Budget'!C281+'FY15 Budget'!D281+'FY15 Budget'!E281+'FY15 Budget'!F281+'FY15 Budget'!G281+'FY15 Budget'!H281 -> 1492537.3 | I45: =+H45-G45 -> #REF! | K45: =+'FY15 Budget'!O281 -> 2985074.6 | L45: =+'FY15 Current Forecast'!O305-'FY15 Current Forecast'!O306 -> 0 | M45: =+L45-K45 -> -2985074.6
B46: Freight Accrual | C46: 0 | E46: =+D46-C46 -> 0 | G46: =+C46 -> 0 | I46: =+H46-G46 -> 0 | M46: =+L46-K46 -> 0
B47: Sub-Total Maryland Heights | C47: =SUM(C44:C46) -> #REF! | D47: =SUM(D44:D46) -> 229621.26 | E47: =SUM(E44:E46) -> #REF! | G47: =SUM(G44:G46) -> #REF! | H47: =SUM(H44:H46) -> 1492537.3 | I47: =SUM(I44:I46) -> #REF! | K47: =SUM(K44:K46) -> 2985074.6 | L47: =SUM(L44:L46) -> 0 | M47: =SUM(M44:M46) -> -2985074.6
B49: Total Out Freight | C49: =SUM(C47,C42,C37,C33) -> #REF! | D49: =SUM(D47,D42,D37,D33) -> 1111045 | E49: =SUM(E47,E42,E37,E33) -> #REF! | G49: =SUM(G47,G42,G37,G33) -> #REF! | H49: =SUM(H47,H42,H37,H33) -> 7216465.6 | I49: =SUM(I47,I42,I37,I33) -> #REF! | K49: =SUM(K47,K42,K37,K33) -> 14379565 | L49: =SUM(L47,L42,L37,L33) -> #REF! | M49: =SUM(M47,M42,M37,M33) -> #REF!
A51: International
B52: Puerto Rico | C52: =+#REF! -> #REF! | D52: =+'FY15 Budget'!H209 -> 0 | E52: =+D52-C52 -> #REF! | G52: =+#REF! -> #REF! | H52: =+'FY15 Budget'!D209+'FY15 Budget'!E209+'FY15 Budget'!E209+'FY15 Budget'!F209+'FY15 Budget'!G209+'FY15 Budget'!H209 -> 0 | I52: =+H52-G52 -> #REF! | K52: =+'FY15 Budget'!O209 -> 0 | L52: =+'FY15 Current Forecast'!O232 -> 0 | M52: =+L52-K52 -> 0
B53: Austrailia | C53: =+#REF! -> #REF! | D53: =+'FY15 Budget'!H210 -> 0 | E53: =+D53-C53 -> #REF! | G53: =+#REF! -> #REF! | H53: =+'FY15 Budget'!C210+'FY15 Budget'!D210+'FY15 Budget'!E210+'FY15 Budget'!F210+'FY15 Budget'!G210+'FY15 Budget'!H210 -> 0 | I53: =+H53-G53 -> #REF! | K53: =+'FY15 Budget'!O210 -> 0 | L53: =+'FY15 Current Forecast'!O233 -> 0 | M53: =+L53-K53 -> 0
B54: Panama | C54: =+#REF!+#REF! -> #REF! | D54: =+'FY15 Budget'!H208+'FY15 Budget'!H209 -> 0 | G54: =+#REF!+#REF! -> #REF! | H54: =+'FY15 Budget'!C209+'FY15 Budget'!D209+'FY15 Budget'!E209+'FY15 Budget'!F209+'FY15 Budget'!G209+'FY15 Budget'!H209+'FY15 Budget'!C208+'FY15 Budget'!D208+'FY15 Budget'!E208+'FY15 Budget'!F208+'FY15 Budget'!G208+'FY15 Budget'!H208 -> 0 | K54: =+'FY15 Budget'!O207+'FY15 Budget'!O208 -> 0 | L54: =+'FY15 Current Forecast'!O230+'FY15 Current Forecast'!O231 -> 0
B55: Total International | C55: =SUM(C52:C54) -> #REF! | D55: =SUM(D52:D54) -> 0 | E55: =SUM(E52:E54) -> #REF! | G55: =SUM(G52:G54) -> #REF! | H55: =SUM(H52:H54) -> 0 | I55: =SUM(I52:I54) -> #REF! | K55: =SUM(K52:K54) -> 0 | L55: =SUM(L52:L54) -> 0 | M55: =SUM(M52:M54) -> 0
B57: Total Freight -Pharma | C57: =+C49+C22+C55 -> #REF! | D57: =+D49+D22+D55 -> 1257428.8 | E57: =+E49+E22+E55 -> #REF! | G57: =+G49+G22+G55 -> #REF! | H57: =+H49+H22+H55 -> 8152248.3 | I57: =+I49+I22+I55 -> #REF! | K57: =+K49+K22+K55 -> 16254818 | L57: =+L49+L22+L55 -> #REF! | M57: =+M49+M22+M55 -> #REF!
B59: divisional statement | C59: 3247692 | D59: 3272630 | G59: 20604189 | H59: 20964178 | K59: 42354674 | L59: 41206542
B60: difference | C60: =+C57-C59 -> #REF! | D60: =+D57-D59 -> -2015201.2 | G60: =+G57-G59 -> #REF! | H60: =+H57-H59 -> -12811930 | K60: =+K57-K59 -> -26099856 | L60: =+L57-L59 -> #REF!

Sheet Act vs Budget - revised format
A1: Pharma Freight Actual VS Budget
B2: FY12 | C2: Jan | G2: YTD | K2: Full Year
C3: Actual | D3: Budget | E3: B/(W) | G3: Actual | H3: Budget | I3: B/(W) | K3: Budget | L3: Current Forecast | M3: B/(W)
A5: PHARMA
B6: Net Sales | C6: 1.0957036e+08 | D6: 1.1892978e+08 | E6: =+D6-C6 -> 9359423.2 | G6: 4.6322965e+08 | H6: 4.6889988e+08 | I6: =+H6-G6 -> 5670226.1 | M6: =+L6-K6 -> 0
A7: In Freight
A8: API | B8: STL Plant Stear/Phos | C8: =#REF! -> #REF! | E8: =+D8-C8 -> #REF! | G8: =#REF! -> #REF! | I8: =+H8-G8 -> #REF! | K8: 0 | M8: =+L8-K8 -> 0
B9: STL Plant Narcotics | E9: =+D9-C9 -> 0 | I9: =+H9-G9 -> 0 | M9: =+L9-K9 -> 0
B10: Gateway | E10: =+D10-C10 -> 0 | I10: =+H10-G10 -> 0 | M10: =+L10-K10 -> 0
B11: Japan | C11: =+#REF!+#REF!+#REF!+#REF! -> #REF! | G11: =+#REF!+#REF!+#REF!+#REF! -> #REF! | K11: 0 | L11: =+'FY15 Current Forecast'!O56+'FY15 Current Forecast'!O59 -> 0
B12: UK PAP/APAP | C12: =#REF! -> #REF! | D12: =+'FY15 Budget'!F51+'FY15 Budget'!F52+'FY15 Budget'!F55+'FY15 Budget'!F57 -> 111832.17 | E12: =+D12-C12 -> #REF! | G12: =#REF! -> #REF! | H12: =+'FY15 Budget'!C51+'FY15 Budget'!C52+'FY15 Budget'!C55+'FY15 Budget'!C57+'FY15 Budget'!D51+'FY15 Budget'!D52+'FY15 Budget'!D55+'FY15 Budget'!D57+'FY15 Budget'!E51+'FY15 Budget'!E52+'FY15 Budget'!E55+'FY15 Budget'!E57+'FY15 Budget'!F51+'FY15 Budget'!F52+'FY15 Budget'!F55+'FY15 Budget'!F57 -> 475286.71 | I12: =+H12-G12 -> #REF! | K12: =+'FY15 Budget'!O51+'FY15 Budget'!O52+'FY15 Budget'!O55+'FY15 Budget'!O57 -> 1453818.2 | L12: =+'FY15 Current Forecast'!O50+'FY15 Current Forecast'!O51+'FY15 Current Forecast'!O53+'FY15 Current Forecast'!O55 -> 0 | M12: =+L12-K12 -> -1453818.2
B13: UK Bulk Narcotics | C13: =+#REF! -> #REF! | D13: =+'FY15 Budget'!F50 -> 0 | E13: =+D13-C13 -> #REF! | G13: =#REF! -> #REF! | H13: =+'FY15 Budget'!C50+'FY15 Budget'!D50+'FY15 Budget'!E50+'FY15 Budget'!F50 -> 0 | I13: =+H13-G13 -> #REF! | K13: =+'FY15 Budget'!O50 -> 0 | L13: =+'FY15 Current Forecast'!O49 -> 0 | M13: =+L13-K13 -> 0
B14: UK Stear/Phos | C14: =#REF! -> #REF! | D14: =+'FY15 Budget'!F53 -> 5425.1694 | E14: =+D14-C14 -> #REF! | G14: =#REF! -> #REF! | H14: =+'FY15 Budget'!C53+'FY15 Budget'!D53+'FY15 Budget'!E53+'FY15 Budget'!F53 -> 23056.97 | I14: =+H14-G14 -> #REF! | K14: =+'FY15 Budget'!O53 -> 70527.202 | L14: =+'FY15 Current Forecast'!O52 -> 0 | M14: =+L14-K14 -> -70527.202
B15: Canada PHM | C15: =+#REF! -> #REF! | D15: =+'FY15 Budget'!F59 -> 0 | E15: =+D15-C15 -> #REF! | G15: =+#REF! -> #REF! | H15: =+'FY15 Budget'!C59+'FY15 Budget'!D59+'FY15 Budget'!E59+'FY15 Budget'!F59 -> 0 | I15: =+H15-G15 -> #REF! | K15: =+'FY15 Budget'!O59 -> 0 | L15: =+'FY15 Current Forecast'!O67 -> 0 | M15: =+L15-K15 -> 0
B16: Sub-Total API In Freight | C16: =SUM(C8:C15) -> #REF! | D16: =SUM(D8:D15) -> 117257.34 | E16: =SUM(E8:E15) -> #REF! | G16: =SUM(G8:G15) -> #REF! | H16: =SUM(H8:H15) -> 498343.68 | I16: =SUM(I8:I15) -> #REF! | K16: =SUM(K8:K15) -> 1524345.4 | L16: =SUM(L8:L15) -> 0 | M16: =SUM(M8:M15) -> -1524345.4
A18: Dosage | B18: Hobart | C18: =SUM(#REF!,#REF!) -> #REF! | D18: =+SUM('FY15 Budget'!F8:F49)+'FY15 Budget'!F56 -> 24662.776 | E18: =+D18-C18 -> #REF! | G18: =SUM(#REF!,#REF!) -> #REF! | H18: =+SUM('FY15 Budget'!C8:C49)+'FY15 Budget'!C56+SUM('FY15 Budget'!D8:D49)+'FY15 Budget'!D56+SUM('FY15 Budget'!E8:E49)+'FY15 Budget'!E56+SUM('FY15 Budget'!F8:F49)+'FY15 Budget'!F56 -> 98138.307 | I18: =+H18-G18 -> #REF! | K18: =+SUM('FY15 Budget'!O8:O49)+'FY15 Budget'!O56 -> 299030.65 | L18: =+SUM('FY15 Current Forecast'!O7:O47)+'FY15 Current Forecast'!O54 -> 0 | M18: =+L18-K18 -> -299030.65
B19: Sub-Total Dosage In Freight | C19: =SUM(C18:C18) -> #REF! | D19: =SUM(D18:D18) -> 24662.776 | E19: =SUM(E18:E18) -> #REF! | G19: =SUM(G18:G18) -> #REF! | H19: =SUM(H18:H18) -> 98138.307 | I19: =SUM(I18:I18) -> #REF! | K19: =SUM(K18:K18) -> 299030.65 | L19: =SUM(L18:L18) -> 0 | M19: =SUM(M18:M18) -> -299030.65
A21: Imaging | B21: Joliet | C21: =+#REF!+#REF!+#REF!+#REF!+#REF!+#REF! -> #REF! | D21: =+SUM('FY15 Budget'!F191:F196) -> 0 | E21: =+D21-C21 -> #REF! | G21: =+#REF!+#REF!+#REF!+#REF!+#REF!++#REF! -> #REF! | H21: =+SUM('FY15 Budget'!C191:C196)+SUM('FY15 Budget'!D191:D196)+SUM('FY15 Budget'!E191:E196)+SUM('FY15 Budget'!F191:F196) -> 0 | I21: =+H21-G21 -> #REF! | K21: =+SUM('FY15 Budget'!O191:O196) -> 0 | L21: =+SUM('FY15 Current Forecast'!O209:O213) -> 0 | M21: =+L21-K21 -> 0
B22: Sub-Total Imaging In Freight | C22: =SUM(C21:C21) -> #REF! | D22: =SUM(D21:D21) -> 0 | E22: =SUM(E21:E21) -> #REF! | G22: =SUM(G21:G21) -> #REF! | H22: =SUM(H21:H21) -> 0 | I22: =SUM(I21:I21) -> #REF! | K22: =SUM(K21:K21) -> 0 | L22: =SUM(L21:L21) -> 0 | M22: =SUM(M21:M21) -> 0
B24: Total InFreight | C24: =SUM(C16,C19,C22) -> #REF! | D24: =SUM(D16,D19,D22) -> 141920.11 | E24: =SUM(E16,E19,E22) -> #REF! | G24: =SUM(G16,G19,G22) -> #REF! | H24: =SUM(H16,H19,H22) -> 596481.99 | I24: =SUM(I16,I19,I22) -> #REF! | K24: =SUM(K16,K19,K22) -> 1823376 | L24: =SUM(L16,L19,L22) -> 0 | M24: =SUM(M16,M19,M22) -> -1823376
C25: =C24/C6 -> #REF! | D25: =-D24/D6 -> -0.0011933101 | G25: =G24/G6 -> #REF! | H25: =-H24/H6 -> -0.0012720882 | K25: =-K24/K6 -> #DIV/0! | L25: =-L24/L6 -> #DIV/0!
A26: Out Freight
A27: API | B27: STL Plant Stear/Phos | C27: =+#REF!+#REF! -> #REF! | D27: =+'FY15 Budget'!F129+'FY15 Budget'!F131 -> 0 | E27: =+D27-C27 -> #REF! | G27: =+#REF!+#REF! -> #REF! | H27: =+'FY15 Budget'!C129+'FY15 Budget'!C131+'FY15 Budget'!D129+'FY15 Budget'!D131+'FY15 Budget'!E129+'FY15 Budget'!E131+'FY15 Budget'!F129+'FY15 Budget'!F131 -> 0 | I27: =+H27-G27 -> #REF! | K27: =+'FY15 Budget'!O129+'FY15 Budget'!O131 -> 0 | L27: =+'FY15 Current Forecast'!O149+'FY15 Current Forecast'!O150 -> 0 | M27: =+L27-K27 -> 0
B28: Canada | C28: =+#REF! -> #REF! | E28: =+D28-C28 -> #REF! | G28: =+#REF! -> #REF! | I28: =+H28-G28 -> #REF! | M28: =+L28-K28 -> 0
B29: LATAM | C29: =+#REF! -> #REF! | D29: =+'FY15 Budget'!F124 -> 0 | E29: =+D29-C29 -> #REF! | G29: =+#REF! -> #REF! | H29: =+'FY15 Budget'!C124+'FY15 Budget'!D124+'FY15 Budget'!E124+'FY15 Budget'!F124 -> 0 | I29: =+H29-G29 -> #REF! | K29: =+'FY15 Budget'!O124 -> 0 | L29: =+'FY15 Current Forecast'!O145 -> 0 | M29: =+L29-K29 -> 0
B30: EMEA | C30: =+#REF!+#REF!+#REF! -> #REF! | E30: =+D30-C30 -> #REF! | G30: =+#REF!+#REF!+#REF! -> #REF! | I30: =+H30-G30 -> #REF! | M30: =+L30-K30 -> 0
B31: Japan | C31: =+#REF!+#REF!+#REF!+#REF! -> #REF! | E31: =+D31-C31 -> #REF! | G31: =+#REF!+#REF!+#REF!+#REF! -> #REF! | I31: =+H31-G31 -> #REF! | L31: =+'FY15 Current Forecast'!O57 -> 0 | M31: =+L31-K31 -> 0
B32: APAC | C32: =+#REF! -> #REF! | E32: =+D32-C32 -> #REF! | G32: =+#REF! -> #REF! | I32: =+H32-G32 -> #REF! | L32: =+'FY15 Current Forecast'!O114 -> 0 | M32: =+L32-K32 -> 0
B33: STL Plant Narcotics | C33: =+#REF! -> #REF! | D33: =+'FY15 Budget'!F127 -> 0 | E33: =+D33-C33 -> #REF! | G33: =+#REF! -> #REF! | H33: =+'FY15 Budget'!C127+'FY15 Budget'!D127+'FY15 Budget'!E127+'FY15 Budget'!F127 -> 0 | I33: =+H33-G33 -> #REF! | K33: =+'FY15 Budget'!O127 -> 0 | L33: =+'FY15 Current Forecast'!O148 -> 0 | M33: =+L33-K33 -> 0
B34: Canada | C34: =+#REF! -> #REF! | D34: 0 | E34: =+D34-C34 -> #REF! | G34: =+#REF! -> #REF! | H34: 0 | I34: =+H34-G34 -> #REF! | K34: 0 | L34: 0 | M34: =+L34-K34 -> 0
B35: LATAM | C35: =SUM(#REF!) -> #REF! | E35: =+D35-C35 -> #REF! | G35: =SUM(#REF!) -> #REF! | I35: =+H35-G35 -> #REF! | L35: =+'FY15 Current Forecast'!O140+'FY15 Current Forecast'!O141+'FY15 Current Forecast'!O142+'FY15 Current Forecast'!O144 -> 0 | M35: =+L35-K35 -> 0
B36: EMEA | C36: =+#REF!+#REF! -> #REF! | E36: =+D36-C36 -> #REF! | G36: =+#REF!+#REF! -> #REF! | I36: =+H36-G36 -> #REF! | L36: =+'FY15 Current Forecast'!O107 -> 0 | M36: =+L36-K36 -> 0
B37: Japan | C37: =+#REF! -> #REF! | E37: =+D37-C37 -> #REF! | G37: =+#REF! -> #REF! | I37: =+H37-G37 -> #REF! | L37: =+'FY15 Current Forecast'!O129 -> 0 | M37: =+L37-K37 -> 0
B38: APAC | C38: =+#REF! -> #REF! | E38: =+D38-C38 -> #REF! | G38: =+#REF! -> #REF! | I38: =+H38-G38 -> #REF! | L38: =+'FY15 Current Forecast'!O115 -> 0 | M38: =+L38-K38 -> 0
B39: Peptides | C39: =+#REF!+#REF! -> #REF! | E39: =+D39-C39 -> #REF! | G39: =+#REF!+#REF! -> #REF! | I39: =+H39-G39 -> #REF! | M39: =+L39-K39 -> 0
B40: Gateway | C40: =+#REF!-(C57*0.04)-(C57*0.2) -> #REF! | E40: =+D40-C40 -> #REF! | G40: =+#REF! -> #REF! | I40: =+H40-G40 -> #REF! | L40: =+'FY15 Current Forecast'!O126 -> 0 | M40: =+L40-K40 -> 0
B41: Raleigh APAP | C41: =+#REF!-(C57*0.14) -> #REF! | D41: =+'FY15 Budget'!F126 -> 126920 | E41: =+D41-C41 -> #REF! | G41: =+#REF!-G57 -> #REF! | H41: =+'FY15 Budget'!C126+'FY15 Budget'!D126+'FY15 Budget'!E126+'FY15 Budget'!F126 -> 539410 | I41: =+H41-G41 -> #REF! | K41: =+'FY15 Budget'!O126 -> 1649960 | L41: =+'FY15 Current Forecast'!O146 -> 0 | M41: =+L41-K41 -> -1649960
B42: Canada | C42: =+#REF!+#REF!-(C57*0.06) -> #REF! | D42: =+'FY15 Budget'!F184 -> 0 | E42: =+D42-C42 -> #REF! | G42: =+#REF!+#REF! -> #REF! | H42: =+'FY15 Budget'!C184+'FY15 Budget'!D184+'FY15 Budget'!E184+'FY15 Budget'!F184 -> 0 | I42: =+H42-G42 -> #REF! | K42: =+'FY15 Budget'!O184 -> 0 | L42: =+'FY15 Current Forecast'!O206+'FY15 Current Forecast'!#REF! -> #REF! | M42: =+L42-K42 -> #REF!
B43: LATAM | C43: =+#REF!+#REF!+#REF!+#REF!+#REF!+#REF!-(C57*0.15) -> #REF! | E43: =+D43-C43 -> #REF! | G43: =+#REF!+#REF!+#REF!+#REF!+#REF!+#REF! -> #REF! | I43: =+H43-G43 -> #REF! | L43: =+'FY15 Current Forecast'!O135+'FY15 Current Forecast'!O124 -> 0 | M43: =+L43-K43 -> 0
B44: EMEA | C44: =+#REF!+#REF!+#REF!+#REF!+#REF! -> #REF! | E44: =+D44-C44 -> #REF! | G44: =+#REF!+#REF!+#REF!+#REF!+#REF! -> #REF! | I44: =+H44-G44 -> #REF! | L44: =+'FY15 Current Forecast'!O127+'FY15 Current Forecast'!O79 -> 0 | M44: =+L44-K44 -> 0
B45: Japan | C45: =+#REF!+#REF! -> #REF! | D45: =+'FY15 Budget'!F109 -> 0 | E45: =+D45-C45 -> #REF! | G45: =+#REF!+#REF! -> #REF! | H45: =+'FY15 Budget'!C109+'FY15 Budget'!D109+'FY15 Budget'!E109+'FY15 Budget'!F109 -> 0 | I45: =+H45-G45 -> #REF! | K45: =+'FY15 Budget'!O109 -> 0 | L45: =+'FY15 Current Forecast'!O128+'FY15 Current Forecast'!O117 -> 0 | M45: =+L45-K45 -> 0
B46: APAC | C46: =+#REF!-(C57*0.24)+#REF! -> #REF! | E46: =+D46-C46 -> #REF! | G46: =+#REF!+#REF! -> #REF! | I46: =+H46-G46 -> #REF! | L46: =+'FY15 Current Forecast'!O120 -> 0 | M46: =+L46-K46 -> 0
B47: Greenville COMPAP | C47: =#REF!-(C57*0.17) -> #REF! | E47: =+D47-C47 -> #REF! | G47: =#REF! -> #REF! | I47: =+H47-G47 -> #REF! | L47: =+'FY15 Current Forecast'!O152 -> 0 | M47: =+L47-K47 -> 0
B48: Canada | C48: =+#REF! -> #REF! | E48: =+D48-C48 -> #REF! | G48: =+#REF! -> #REF! | I48: =+H48-G48 -> #REF! | L48: =+'FY15 Current Forecast'!O123 -> 0 | M48: =+L48-K48 -> 0
B49: LATAM | C49: =+#REF! -> #REF! | E49: =+D49-C49 -> #REF! | G49: =+#REF! -> #REF! | I49: =+H49-G49 -> #REF! | L49: =+'FY15 Current Forecast'!O125 -> 0 | M49: =+L49-K49 -> 0
B50: EMEA | C50: =+#REF! -> #REF! | E50: =+D50-C50 -> #REF! | G50: =+#REF! -> #REF! | I50: =+H50-G50 -> #REF! | M50: =+L50-K50 -> 0
B51: Japan | C51: =+#REF! -> #REF! | E51: =+D51-C51 -> #REF! | G51: =+#REF! -> #REF! | I51: =+H51-G51 -> #REF! | M51: =+L51-K51 -> 0
B52: APAC | C52: =+#REF! -> #REF! | E52: =+D52-C52 -> #REF! | G52: =+#REF! -> #REF! | I52: =+H52-G52 -> #REF! | L52: =+'FY15 Current Forecast'!O122 -> 0 | M52: =+L52-K52 -> 0
B53: UK PAP/APAP | C53: =+#REF! -> #REF! | D53: =+'FY15 Budget'!F180 -> 124391.43 | E53: =+D53-C53 -> #REF! | G53: =+#REF! -> #REF! | H53: =+'FY15 Budget'!C180+'FY15 Budget'!D180+'FY15 Budget'!E180+'FY15 Budget'!F180 -> 528663.58 | I53: =+H53-G53 -> #REF! | K53: =+'FY15 Budget'!O180 -> 1617088.6 | L53: =+'FY15 Current Forecast'!O200 -> 0 | M53: =+L53-K53 -> -1617088.6
B54: UK Bulk Narcotics | C54: =+#REF! -> #REF! | D54: =+'FY15 Budget'!F181 -> 13635.088 | E54: =+D54-C54 -> #REF! | G54: =+#REF! -> #REF! | H54: =+'FY15 Budget'!C181+'FY15 Budget'!D181+'FY15 Budget'!E181+'FY15 Budget'!F181 -> 57949.124 | I54: =+H54-G54 -> #REF! | K54: =+'FY15 Budget'!O181 -> 177256.15 | L54: =+'FY15 Current Forecast'!O201 -> 0 | M54: =+L54-K54 -> -177256.15
B55: UK Stear/Phos | C55: =+#REF! -> #REF! | D55: =+'FY15 Budget'!F182 -> 5907.7515 | E55: =+D55-C55 -> #REF! | G55: =+#REF! -> #REF! | H55: =+'FY15 Budget'!C182+'FY15 Budget'!D182+'FY15 Budget'!E182+'FY15 Budget'!F182 -> 25107.944 | I55: =+H55-G55 -> #REF! | K55: =+'FY15 Budget'!O182 -> 76800.769 | L55: =+'FY15 Current Forecast'!O202 -> 0 | M55: =+L55-K55 -> -76800.769
B56: Goaling | D56: =+'FY15 Budget'!F116 -> 0 | E56: =+D56-C56 -> 0 | H56: =+'FY15 Budget'!C116+'FY15 Budget'!D116+'FY15 Budget'!E116+'FY15 Budget'!F116 -> 0 | I56: =+H56-G56 -> 0 | K56: =+'FY15 Budget'!O116 -> 0 | L56: =+'FY15 Current Forecast'!O137 -> 0 | M56: =+L56-K56 -> 0
B57: Freight Accrual-APAP | C57: 0 | E57: =+D57-C57 -> 0 | G57: =+C57 -> 0 | I57: =+H57-G57 -> 0 | M57: =+L57-K57 -> 0
B58: Sub-Total API Out Freight | C58: =SUM(C27:C57) -> #REF! | D58: =SUM(D27:D57) -> 270854.27 | E58: =SUM(E27:E57) -> #REF! | G58: =SUM(G27:G57) -> #REF! | H58: =SUM(H27:H57) -> 1151130.6 | I58: =SUM(I27:I57) -> #REF! | K58: =SUM(K27:K57) -> 3521105.5 | L58: =SUM(L27:L57) -> #REF! | M58: =SUM(M27:M57) -> #REF!
A60: Dosage | B60: Hobart | C60: =SUM(#REF!,#REF!)+#REF!-C61 -> #REF! | D60: =+SUM('FY15 Budget'!F134:F175) -> 442286.06 | E60: =+D60-C60 -> #REF! | G60: =SUM(#REF!,#REF!)+#REF!-G61 -> #REF! | H60: =+SUM('FY15 Budget'!C134:C175)+SUM('FY15 Budget'!D134:D175)+SUM('FY15 Budget'!E134:E175)+SUM('FY15 Budget'!F134:F175) -> 1879899.1 | I60: =+H60-G60 -> #REF! | K60: =+SUM('FY15 Budget'!O134:O175) -> 5658751.8 | L60: =+SUM('FY15 Current Forecast'!O154:O191) -> 0 | M60: =+L60-K60 -> -5658751.8
B61: Freight Accrual | C61: 0 | E61: =+D61-C61 -> 0 | G61: =+C61 -> 0 | I61: =+H61-G61 -> 0 | M61: =+L61-K61 -> 0
B62: Sub-Total Dosage Out Freight | C62: =SUM(C60:C61) -> #REF! | D62: =SUM(D60:D61) -> 442286.06 | E62: =SUM(E60:E61) -> #REF! | G62: =SUM(G60:G61) -> #REF! | H62: =SUM(H60:H61) -> 1879899.1 | I62: =SUM(I60:I61) -> #REF! | K62: =SUM(K60:K61) -> 5658751.8 | L62: =SUM(L60:L61) -> 0 | M62: =SUM(M60:M61) -> -5658751.8
A65: Imaging | B65: Cincinnati | C65: =+#REF!+#REF!+#REF! -> #REF! | D65: =+SUM('FY15 Budget'!F202:F203) -> 37838 | E65: =+D65-C65 -> #REF! | G65: =+#REF!+#REF!+#REF! -> #REF! | H65: =+SUM('FY15 Budget'!C202:C203)+SUM('FY15 Budget'!D202:D203)+SUM('FY15 Budget'!E202:E203)+SUM('FY15 Budget'!F202:F203) -> 160812 | I65: =+H65-G65 -> #REF! | K65: =+SUM('FY15 Budget'!O202:O203) -> 491896 | L65: =+SUM('FY15 Current Forecast'!O218:O221) -> 0 | M65: =+L65-K65 -> -491896
B66: Joliet | C66: =+#REF!+#REF!+#REF!+#REF!-C69 -> #REF! | D66: =+SUM('FY15 Budget'!F200:F201) -> 109441 | E66: =+D66-C66 -> #REF! | G66: =+#REF!+#REF!+#REF!+#REF!-G69 -> #REF! | H66: =+SUM('FY15 Budget'!C200:C201)+SUM('FY15 Budget'!D200:D201)+SUM('FY15 Budget'!E200:E201)+SUM('FY15 Budget'!F200:F201) -> 465125 | I66: =+H66-G66 -> #REF! | K66: =+SUM('FY15 Budget'!O200:O201) -> 1422737 | L66: =+SUM('FY15 Current Forecast'!O215:O217) -> 0 | M66: =+L66-K66 -> -1422737
B67: Dublin | C67: =+#REF! -> #REF! | D67: =+'FY15 Budget'!F185 -> 0 | E67: =+D67-C67 -> #REF! | G67: =+#REF! -> #REF! | H67: =+'FY15 Budget'!C185+'FY15 Budget'!D185+'FY15 Budget'!E185+'FY15 Budget'!F185 -> 0 | I67: =+H67-G67 -> #REF! | K67: =+'FY15 Budget'!O185 -> 0 | L67: =+'FY15 Current Forecast'!O207 -> 0 | M67: =+L67-K67 -> 0
B68: Canada | E68: =+D68-C68 -> 0 | I68: =+H68-G68 -> 0 | M68: =+L68-K68 -> 0
B69: Freight Accrual | C69: 0 | E69: =+D69-C69 -> 0 | G69: =+C69 -> 0 | I69: =+H69-G69 -> 0 | M69: =+L69-K69 -> 0
B70: Sub-Total Contrast | C70: =SUM(C65:C69) -> #REF! | D70: =SUM(D65:D69) -> 147279 | E70: =SUM(E65:E69) -> #REF! | G70: =SUM(G65:G69) -> #REF! | H70: =SUM(H65:H69) -> 625937 | I70: =SUM(I65:I69) -> #REF! | K70: =SUM(K65:K69) -> 1914633 | L70: =SUM(L65:L69) -> 0 | M70: =SUM(M65:M69) -> -1914633
A72: Nuc Med | B72: Nuc Med Direct | C72: =SUM(#REF!)-C74 -> #REF! | D72: =+'FY15 Budget'!F292 -> 0 | E72: =+D72-C72 -> #REF! | G72: =SUM(#REF!)-G74 -> #REF! | H72: =+'FY15 Budget'!C292+'FY15 Budget'!D292+'FY15 Budget'!E292+'FY15 Budget'!F292 -> 0 | I72: =+H72-G72 -> #REF! | K72: =+'FY15 Budget'!O292 -> 0 | L72: =+'FY15 Current Forecast'!O305+'FY15 Current Forecast'!O222+'FY15 Current Forecast'!O306 -> 0 | M72: =+L72-K72 -> 0
B73: Canada | C73: =+#REF!+#REF! -> #REF! | D73: =+'FY15 Budget'!F277 -> 0 | E73: =+D73-C73 -> #REF! | G73: =+#REF!+#REF! -> #REF! | H73: =+'FY15 Budget'!C277+'FY15 Budget'!D277+'FY15 Budget'!E277+'FY15 Budget'!F277 -> 0 | I73: =+H73-G73 -> #REF! | K73: =+'FY15 Budget'!O277 -> 0 | L73: =+'FY15 Current Forecast'!#REF!+'FY15 Current Forecast'!O304 -> #REF! | M73: =+L73-K73 -> #REF!
B74: Freight Accrual | C74: 0 | E74: =+D74-C74 -> 0 | G74: =+C74 -> 0 | I74: =+H74-G74 -> 0 | M74: =+L74-K74 -> 0
B75: Sub-Total Maryland Heights | C75: =SUM(C72:C74) -> #REF! | D75: =SUM(D72:D74) -> 0 | E75: =SUM(E72:E74) -> #REF! | G75: =SUM(G72:G74) -> #REF! | H75: =SUM(H72:H74) -> 0 | I75: =SUM(I72:I74) -> #REF! | K75: =SUM(K72:K74) -> 0 | L75: =SUM(L72:L74) -> #REF! | M75: =SUM(M72:M74) -> #REF!
B77: Total Out Freight | C77: =SUM(C75,C70,C62,C58) -> #REF! | D77: =SUM(D75,D70,D62,D58) -> 860419.33 | E77: =SUM(E75,E70,E62,E58) -> #REF! | G77: =SUM(G75,G70,G62,G58) -> #REF! | H77: =SUM(H75,H70,H62,H58) -> 3656966.7 | I77: =SUM(I75,I70,I62,I58) -> #REF! | K77: =SUM(K75,K70,K62,K58) -> 11094490 | L77: =SUM(L75,L70,L62,L58) -> #REF! | M77: =SUM(M75,M70,M62,M58) -> #REF!
B79: Total Freight -Pharma | C79: =+C77+C24 -> #REF! | D79: =+D77+D24 -> 1002339.4 | E79: =+D79-C79 -> #REF! | G79: =+G77+G24 -> #REF! | H79: =+H77+H24 -> 4253448.7 | I79: =+H79-G79 -> #REF! | K79: =+K77+K24 -> 12917866 | L79: =+L77+L24 -> #REF! | M79: =+L79-K79 -> #REF!
B81: prelim financial statement totals | C81: 3078785.4 | D81: 3111012.7 | G81: 12760406 | H81: 13588898 | K81: New cost centers added in January? Investigate Thursday.

Sheet Net Sales Actual
C2: Net Sales | D2: Net Sales | E2: Net Sales | F2: Net Sales | G2: Net Sales | H2: Net Sales | I2: Net Sales | J2: Net Sales | K2: Net Sales | L2: Net Sales | M2: Net Sales | N2: Net Sales | O2: Net Sales
C3: 2010 Actuals | D3: 2010 Actuals | E3: 2010 Actuals | F3: 2011 Actuals | G3: 2011 Actuals | H3: 2011 Actuals | I3: 2011 Actuals | J3: 2011 Actuals | K3: 2011 Actuals | L3: 2011 Actuals | M3: 2011 Actuals | N3: 2011 Actuals | O3: 2011 Actuals
C4: Oct | D4: Nov | E4: Dec | F4: Jan | G4: Feb | H4: Mar | I4: Apr | J4: May | K4: Jun | L4: Jul | M4: Aug | N4: Sep | O4: Annual
A6: Disisional Pharmaceuticals - CYR
A13: Nuclear Direct w/Grp Alloc - CYR | C13: 16691751 | D13: 18245665 | E13: 16257951 | F13: 0 | G13: 0 | H13: 0 | I13: 0 | J13: 0 | K13: 0 | L13: 0 | M13: 0 | N13: 0 | O13: 25560512
A15: Nuclear Pharmacies w/Grp Alloc - CYR | C15: 14855177 | D15: 17523774 | E15: 12800017 | F15: 0 | G15: 0 | H15: 0 | I15: 0 | J15: 0 | K15: 0 | L15: 0 | M15: 0 | N15: 0 | O15: -168.3
A16: Virtual Network w/Grp Alloc - CYR | C16: 4683542.8 | D16: 5714064 | E16: -10702907 | F16: 0 | G16: 0 | H16: 0 | I16: 0 | J16: 0 | K16: 0 | L16: 0 | M16: 0 | N16: 0 | O16: -366473.37

Sheet Net Sales Budget
C2: Net Sales | D2: Net Sales | E2: Net Sales | F2: Net Sales | G2: Net Sales | H2: Net Sales | I2: Net Sales | J2: Net Sales | K2: Net Sales | L2: Net Sales | M2: Net Sales | N2: Net Sales | O2: Net Sales
C3: 2010 Budget | D3: 2010 Budget | E3: 2010 Budget | F3: 2010 Budget | G3: 2010 Budget | H3: 2010 Budget | I3: 2010 Budget | J3: 2010 Budget | K3: 2010 Budget | L3: 2010 Budget | M3: 2010 Budget | N3: 2010 Budget | O3: 2010 Budget
C4: Oct | D4: Nov | E4: Dec | F4: Jan | G4: Feb | H4: Mar | I4: Apr | J4: May | K4: Jun | L4: Jul | M4: Aug | N4: Sep | O4: Annual
A6: WW Pharm (Excl L&M, Incl SS Alloc) - CYR | C6: 73513713 | D6: 78159268 | E6: 68800829 | F6: 86283804 | G6: 87038405 | H6: 81281779 | I6: 93553846 | J6: 88113337 | K6: 84918299 | L6: 80880852 | M6: 84118740 | N6: 1.130358e+08 | O6: 1.0196987e+09
A7: Total US Imaging Incl SS Alloc - CYR | C7: 54967378 | D7: 67446826 | E7: 52691264 | F7: 48628019 | G7: 66894936 | H7: 47213514 | I7: 47214790 | J7: 59485682 | K7: 49432716 | L7: 47634908 | M7: 61890011 | N7: 60462081 | O7: 6.6396212e+08
A12: Total US CM&DS (incl SS Alloc) - CYR | C12: 18821056 | D12: 24880983 | E12: 18310376 | F12: 15866627 | G12: 25772272 | H12: 16589457 | I12: 18120585 | J12: 22759272 | K12: 18746675 | L12: 18188737 | M12: 22989029 | N12: 18829509 | O12: =SUM(C12:N12) -> 2.3987458e+08
O13: =SUM(C13:N13) -> 0
O14: =SUM(C14:N14) -> 0
A15: Nuclear Direct w/Grp Alloc - CYR | C15: 36238322 | D15: 42674843 | E15: 34066025 | F15: 32822392 | G15: 41278664 | H15: 30056932 | I15: 29168205 | J15: 36819410 | K15: 27677916 | L15: 29520171 | M15: 38993982 | N15: 32574447 | O15: =SUM(C15:N15) -> 4.1189131e+08
O16: =SUM(C16:N16) -> 0

Sheet FY15 Budget
C2: FY 2015 | D2: FY 2015 | E2: FY 2015 | F2: FY 2015 | G2: FY 2015 | H2: FY 2015 | I2: FY 2015 | J2: FY 2015 | K2: FY 2015 | L2: FY 2015 | M2: FY 2015 | N2: FY 2015
C3: Budget Rate | D3: Budget Rate | E3: Budget Rate | F3: Budget Rate | G3: Budget Rate | H3: Budget Rate | I3: Budget Rate | J3: Budget Rate | K3: Budget Rate | L3: Budget Rate | M3: Budget Rate | N3: Budget Rate
C4: USD | D4: USD | E4: USD | F4: USD | G4: USD | H4: USD | I4: USD | J4: USD | K4: USD | L4: USD | M4: USD | N4: USD
C5: Budget | D5: Budget | E5: Budget | F5: Budget | G5: Budget | H5: Budget | I5: Budget | J5: Budget | K5: Budget | L5: Budget | M5: Budget | N5: Budget
C6: FDC 015 Out-Freight Expense | D6: FDC 015 Out-Freight Expense | E6: FDC 015 Out-Freight Expense | F6: FDC 015 Out-Freight Expense | G6: FDC 015 Out-Freight Expense | H6: FDC 015 Out-Freight Expense | I6: FDC 015 Out-Freight Expense | J6: FDC 015 Out-Freight Expense | K6: FDC 015 Out-Freight Expense | L6: FDC 015 Out-Freight Expense | M6: FDC 015 Out-Freight Expense | N6: FDC 015 Out-Freight Expense | O6: FDC 015 Out-Freight Expense
C7: Oct | D7: Nov | E7: Dec | F7: Jan | G7: Feb | H7: Mar | I7: Apr | J7: May | K7: Jun | L7: Jul | M7: Aug | N7: Sep | O7: Annual
A8: 157001150209 FREIGHT | B8: 7165i In-freight Expense | C8: 750 | D8: 750 | E8: 750 | F8: 750 | G8: 750 | H8: 750 | I8: 750 | J8: 750 | K8: 750 | L8: 750 | M8: 750 | N8: 750 | O8: =SUM(C8:N8) -> 9000
A9: 157001150210 Frt Exp-Oxycodone Products | B9: 7165i In-freight Expense | C9: 3000 | D9: 3000 | E9: 3000 | F9: 3000 | G9: 3000 | H9: 3000 | I9: 3000 | J9: 3000 | K9: 3000 | L9: 3000 | M9: 3000 | N9: 3000 | O9: =SUM(C9:N9) -> 36000
A10: 157001150211 Frt Exp-Hydrocodone Products | B10: 7165i In-freight Expense | C10: 6000 | D10: 6000 | E10: 6000 | F10: 6000 | G10: 6000 | H10: 6000 | I10: 6000 | J10: 6000 | K10: 6000 | L10: 6000 | M10: 6000 | N10: 6000 | O10: =SUM(C10:N10) -> 72000
A11: 157001150212 Frt Exp-Methylin Oral Solution | B11: 7165i In-freight Expense | C11: 150 | D11: 150 | E11: 150 | F11: 150 | G11: 150 | H11: 150 | I11: 150 | J11: 150 | K11: 150 | L11: 150 | M11: 150 | N11: 150 | O11: =SUM(C11:N11) -> 1800
A12: 157001150219 FREIGHT | B12: 7165i In-freight Expense | C12: 0 | D12: 0 | E12: 0 | F12: 0 | G12: 0 | H12: 0 | I12: 0 | J12: 0 | K12: 0 | L12: 0 | M12: 0 | N12: 0 | O12: =SUM(C12:N12) -> 0
A13: 157001150221 Frt Exp-ADDICTION TREATMENT | B13: 7165i In-freight Expense | C13: 3000 | D13: 3000 | E13: 3000 | F13: 3000 | G13: 3000 | H13: 3000 | I13: 3000 | J13: 3000 | K13: 3000 | L13: 3000 | M13: 3000 | N13: 3000 | O13: =SUM(C13:N13) -> 36000
A14: 157001150222 Frt Exp-Methylphenidate | B14: 7165i In-freight Expense | C14: 750 | D14: 750 | E14: 750 | F14: 750 | G14: 750 | H14: 750 | I14: 750 | J14: 750 | K14: 750 | L14: 750 | M14: 750 | N14: 750 | O14: =SUM(C14:N14) -> 9000
A15: 157001150224 Frt Exp-Other Brand Products | B15: 7165i In-freight Expense | C15: 0 | D15: 0 | E15: 0 | F15: 0 | G15: 0 | H15: 0 | I15: 0 | J15: 0 | K15: 0 | L15: 0 | M15: 0 | N15: 0 | O15: =SUM(C15:N15) -> 0
A16: 157001150225 Frt Exp-CNS Non-Promoted Prod | B16: 7165i In-freight Expense | C16: 216.86225 | D16: 191.03066 | E16: 200.98427 | F16: 200.48238 | G16: 196.76671 | H16: 203.08308 | I16: 202.44431 | J16: 199.05069 | K16: 201.80554 | L16: 201.34928 | M16: 197.95419 | N16: 197.74479 | O16: =SUM(C16:N16) -> 2409.5582
A17: 157001150226 Zydus Freight Expense | B17: 7165i In-freight Expense | C17: 0 | D17: 0 | E17: 0 | F17: 0 | G17: 0 | H17: 0 | I17: 0 | J17: 0 | K17: 0 | L17: 0 | M17: 0 | N17: 0 | O17: =SUM(C17:N17) -> 0
A18: 157001150227 Oxycodone ER Products Freight | B18: 7165i In-freight Expense | C18: 0 | D18: 0 | E18: 0 | F18: 0 | G18: 0 | H18: 0 | I18: 0 | J18: 0 | K18: 0 | L18: 0 | M18: 0 | N18: 0 | O18: =SUM(C18:N18) -> 0
A19: 157001150229 Morphine ER-Frt Exp | B19: 7165i In-freight Expense | C19: 1500 | D19: 1500 | E19: 1500 | F19: 1500 | G19: 1500 | H19: 1500 | I19: 1500 | J19: 1500 | K19: 1500 | L19: 1500 | M19: 1500 | N19: 1500 | O19: =SUM(C19:N19) -> 18000
A20: 157001150230 Hydromorphone-Frt Exp | B20: 7165i In-freight Expense | C20: 750 | D20: 750 | E20: 750 | F20: 750 | G20: 750 | H20: 750 | I20: 750 | J20: 750 | K20: 750 | L20: 750 | M20: 750 | N20: 750 | O20: =SUM(C20:N20) -> 9000
A21: 157001150231 Methadone Generics-Frt Exp | B21: 7165i In-freight Expense | C21: 1500 | D21: 1500 | E21: 1500 | F21: 1500 | G21: 1500 | H21: 1500 | I21: 1500 | J21: 1500 | K21: 1500 | L21: 1500 | M21: 1500 | N21: 1500 | O21: =SUM(C21:N21) -> 18000
A22: 157001150232 APAP Codeine-Frt Exp | B22: 7165i In-freight Expense | C22: 300 | D22: 300 | E22: 300 | F22: 300 | G22: 300 | H22: 300 | I22: 300 | J22: 300 | K22: 300 | L22: 300 | M22: 300 | N22: 300 | O22: =SUM(C22:N22) -> 3600
A23: 157001150233 APAP Propoxyphene-Frt Exp | B23: 7165i In-freight Expense | C23: 0 | D23: 0 | E23: 0 | F23: 0 | G23: 0 | H23: 0 | I23: 0 | J23: 0 | K23: 0 | L23: 0 | M23: 0 | N23: 0 | O23: =SUM(C23:N23) -> 0
A24: 157001150234 Fentanyl Lozenge-Frt Exp | B24: 7165i In-freight Expense | C24: 100 | D24: 100 | E24: 100 | F24: 100 | G24: 100 | H24: 100 | I24: 100 | J24: 100 | K24: 100 | L24: 100 | M24: 100 | N24: 100 | O24: =SUM(C24:N24) -> 1200
A25: 157001150235 Tussicaps-Frt Exp | B25: 7165i In-freight Expense | C25: 0 | D25: 0 | E25: 0 | F25: 0 | G25: 0 | H25: 0 | I25: 0 | J25: 0 | K25: 0 | L25: 0 | M25: 0 | N25: 0 | O25: =SUM(C25:N25) -> 0
A26: 157001150236 Fentanyl Patch-Frt Exp | B26: 7165i In-freight Expense | C26: 1500 | D26: 1500 | E26: 1500 | F26: 1500 | G26: 1500 | H26: 1500 | I26: 1500 | J26: 1500 | K26: 1500 | L26: 1500 | M26: 1500 | N26: 1500 | O26: =SUM(C26:N26) -> 18000
A27: 157001150237 Methylphenidate ER(MedadateCD) | B27: 7165i In-freight Expense | C27: 0 | D27: 150 | E27: 150 | F27: 150 | G27: 150 | H27: 150 | I27: 150 | J27: 150 | K27: 150 | L27: 150 | M27: 150 | N27: 150 | O27: =SUM(C27:N27) -> 1650
A28: 157001150238 Methylphenidate ER (Concerta) | B28: 7165i In-freight Expense | C28: 150 | D28: 150 | E28: 150 | F28: 150 | G28: 150 | H28: 150 | I28: 150 | J28: 150 | K28: 150 | L28: 150 | M28: 150 | N28: 150 | O28: =SUM(C28:N28) -> 1800
A29: 157001150240 Tussi Suspension-Frt Exp | B29: 7165i In-freight Expense | C29: 0 | D29: 0 | E29: 0 | F29: 0 | G29: 0 | H29: 0 | I29: 0 | J29: 0 | K29: 0 | L29: 0 | M29: 0 | N29: 0 | O29: =SUM(C29:N29) -> 0
A30: 157001150241 OxymorphoneER(OpanaER) Frt Exp | B30: 7165i In-freight Expense | C30: 0 | D30: 0 | E30: 0 | F30: 0 | G30: 0 | H30: 0 | I30: 0 | J30: 0 | K30: 0 | L30: 0 | M30: 0 | N30: 0 | O30: =SUM(C30:N30) -> 0
A31: 157001150242 New Brands (External)-Frt Exp | B31: 7165i In-freight Expense | C31: 0 | D31: 0 | E31: 0 | F31: 0 | G31: 0 | H31: 0 | I31: 0 | J31: 0 | K31: 0 | L31: 0 | M31: 0 | N31: 0 | O31: =SUM(C31:N31) -> 0
A32: 157001150244 Oxycodone APAP-Frt Exp | B32: 7165i In-freight Expense | C32: 3000 | D32: 3000 | E32: 3000 | F32: 3000 | G32: 3000 | H32: 3000 | I32: 3000 | J32: 3000 | K32: 3000 | L32: 3000 | M32: 3000 | N32: 3000 | O32: =SUM(C32:N32) -> 36000
A33: 157001150245 Tofranil-PM/ImipraPam Frt Exp | B33: 7165i In-freight Expense | C33: 0 | D33: 0 | E33: 0 | F33: 0 | G33: 0 | H33: 0 | I33: 0 | J33: 0 | K33: 0 | L33: 0 | M33: 0 | N33: 0 | O33: =SUM(C33:N33) -> 0
A34: 157001150247 Morphine Sulfate ER (Kadian) | B34: 7165i In-freight Expense | C34: 0 | D34: 0 | E34: 0 | F34: 0 | G34: 0 | H34: 0 | I34: 0 | J34: 0 | K34: 0 | L34: 0 | M34: 0 | N34: 0 | O34: =SUM(C34:N34) -> 0
A35: 157001150248 Oxymorphone IR (Opana IR) | B35: 7165i In-freight Expense | C35: 150 | D35: 150 | E35: 150 | F35: 150 | G35: 150 | H35: 150 | I35: 150 | J35: 150 | K35: 150 | L35: 150 | M35: 150 | N35: 150 | O35: =SUM(C35:N35) -> 1800
A36: 157001150249 Hydrocodone/APAP GR | B36: 7165i In-freight Expense | C36: 0 | D36: 0 | E36: 0 | F36: 0 | G36: 0 | H36: 0 | I36: 0 | J36: 67.753444 | K36: 135.63514 | L36: 219.07995 | M36: 417.11718 | N36: 448.30754 | O36: =SUM(C36:N36) -> 1287.8933
A37: 157001150250 Oxyocodone/APAP GR | B37: 7165i In-freight Expense | C37: 736.63741 | D37: 789.44359 | E37: 852.84657 | F37: 919.42345 | G37: 988.2476 | H37: 1057.5726 | I37: 1125.1255 | J37: 1188.5683 | K37: 1245.9681 | L37: 1296.1087 | M37: 1350.3752 | N37: 1404.9677 | O37: =SUM(C37:N37) -> 12955.285
A38: 157001150251 Pennsaid Frt Expense | B38: 7165i In-freight Expense | C38: 0 | D38: 0 | E38: 0 | F38: 0 | G38: 0 | H38: 0 | I38: 0 | J38: 0 | K38: 0 | L38: 0 | M38: 0 | N38: 0 | O38: =SUM(C38:N38) -> 0
A39: 157001150252 Exalgo Freight Exp | B39: 7165i In-freight Expense | C39: 12.94125 | D39: 13.38 | E39: 8.6768 | F39: 8.6275 | G39: 10.606295 | H39: 8.55355 | I39: 8.45495 | J39: 10.473717 | K39: 8.40565 | L39: 8.35635 | M39: 10.267188 | N39: 8.25775 | O39: =SUM(C39:N39) -> 117.001
A40: 157001150253 Temazepam-Frt Exp | B40: 7165i In-freight Expense | C40: 75 | D40: 75 | E40: 75 | F40: 75 | G40: 75 | H40: 75 | I40: 75 | J40: 75 | K40: 75 | L40: 75 | M40: 75 | N40: 75 | O40: =SUM(C40:N40) -> 900
A41: 157001150254 Imipramine Pamoate-Frt Exp | B41: 7165i In-freight Expense | C41: 50 | D41: 50 | E41: 50 | F41: 50 | G41: 50 | H41: 50 | I41: 50 | J41: 50 | K41: 50 | L41: 50 | M41: 50 | N41: 50 | O41: =SUM(C41:N41) -> 600
A42: 157001150255 Pennsaid 2% Pump Frt Expense | B42: 7165i In-freight Expense | C42: 0 | D42: 0 | E42: 0 | F42: 0 | G42: 0 | H42: 0 | I42: 0 | J42: 0 | K42: 0 | L42: 0 | M42: 0 | N42: 0 | O42: =SUM(C42:N42) -> 0
A43: 157001150260 Buprenorphine(Subutex) | B43: 7165i In-freight Expense | C43: 0 | D43: 0 | E43: 0 | F43: 0 | G43: 0 | H43: 0 | I43: 0 | J43: 0 | K43: 0 | L43: 0 | M43: 0 | N43: 0 | O43: =SUM(C43:N43) -> 0
A44: 157001150263 Dextroamphetamine Frt | B44: 7165i In-freight Expense | C44: 150 | D44: 150 | E44: 150 | F44: 150 | G44: 150 | H44: 150 | I44: 150 | J44: 150 | K44: 150 | L44: 150 | M44: 150 | N44: 150 | O44: =SUM(C44:N44) -> 1800
A45: 157001150264 Mxd Amphetamine Salt Combo-FRT | B45: 7165i In-freight Expense | C45: 150 | D45: 150 | E45: 150 | F45: 150 | G45: 150 | H45: 150 | I45: 150 | J45: 150 | K45: 150 | L45: 150 | M45: 150 | N45: 150 | O45: =SUM(C45:N45) -> 1800
A46: 157001150268 Roxicodone-Freight | B46: 7165i In-freight Expense | C46: 59.242835 | D46: 59.242835 | E46: 59.242835 | F46: 59.242835 | G46: 59.242835 | H46: 59.242835 | I46: 59.242835 | J46: 59.242835 | K46: 59.242835 | L46: 59.242835 | M46: 59.242835 | N46: 59.242835 | O46: =SUM(C46:N46) -> 710.91402
A47: 157001150269 Intrathecal-Freight | B47: 7165i In-freight Expense | C47: 0 | D47: 0 | E47: 0 | F47: 0 | G47: 0 | H47: 0 | I47: 0 | J47: 0 | K47: 0 | L47: 0 | M47: 0 | N47: 0 | O47: =SUM(C47:N47) -> 0
A48: 157001150270 Exalgo AG Freight | B48: 7165i In-freight Expense | C48: 150 | D48: 150 | E48: 150 | F48: 150 | G48: 150 | H48: 150 | I48: 150 | J48: 150 | K48: 150 | L48: 150 | M48: 150 | N48: 150 | O48: =SUM(C48:N48) -> 1800
A49: 157001150271 Frt Exp-AT-Ext Mfg Bup/Nal | B49: 7165i In-freight Expense | C49: 150 | D49: 150 | E49: 150 | F49: 150 | G49: 150 | H49: 150 | I49: 150 | J49: 150 | K49: 150 | L49: 150 | M49: 150 | N49: 150 | O49: =SUM(C49:N49) -> 1800
A50: 575000150052 Freight-BULK NARC | B50: 7165i In-freight Expense | C50: 0 | D50: 0 | E50: 0 | F50: 0 | G50: 0 | H50: 0 | I50: 0 | J50: 0 | K50: 0 | L50: 0 | M50: 0 | N50: 0 | O50: =SUM(C50:N50) -> 0
A51: 575000150054 MALL CHEM LTD - PROCESS CHEM | B51: 7165i In-freight Expense | C51: 0 | D51: 0 | E51: 0 | F51: 0 | G51: 0 | H51: 0 | I51: 0 | J51: 0 | K51: 0 | L51: 0 | M51: 0 | N51: 0 | O51: =SUM(C51:N51) -> 0
A52: 575000151151 MC UK Asia APAP Freight Exp | B52: 7165i In-freight Expense | C52: 0 | D52: 0 | E52: 0 | F52: 0 | G52: 0 | H52: 0 | I52: 0 | J52: 0 | K52: 0 | L52: 0 | M52: 0 | N52: 0 | O52: =SUM(C52:N52) -> 0
A53: 575199150992 Stearates & Phosphates | B53: 7165i In-freight Expense | C53: 5425.1694 | D53: 6781.4618 | E53: 5425.1694 | F53: 5425.1694 | G53: 6781.4618 | H53: 5425.1694 | I53: 5425.1694 | J53: 6781.4618 | K53: 5425.1694 | L53: 5425.1694 | M53: 6781.4618 | N53: 5425.1694 | O53: =SUM(C53:N53) -> 70527.202
A54: 575199150991 Bulk Narcotics | B54: 7165i In-freight Expense | C54: 0 | D54: 0 | E54: 0 | F54: 0 | G54: 0 | H54: 0 | I54: 0 | J54: 0 | K54: 0 | L54: 0 | M54: 0 | N54: 0 | O54: =SUM(C54:N54) -> 0
A55: 575199150990 PAP/APAP | B55: 7165i In-freight Expense | C55: 111832.17 | D55: 139790.21 | E55: 111832.17 | F55: 111832.17 | G55: 139790.21 | H55: 111832.17 | I55: 111832.17 | J55: 139790.21 | K55: 111832.17 | L55: 111832.17 | M55: 139790.21 | N55: 111832.17 | O55: =SUM(C55:N55) -> 1453818.2
A56: 166012150000 Hobart Production Freight | B56: 7165i In-freight Expense | C56: 0 | D56: 0 | E56: 0 | F56: 0 | G56: 0 | H56: 0 | I56: 0 | J56: 0 | K56: 0 | L56: 0 | M56: 0 | N56: 0 | O56: =SUM(C56:N56) -> 0
A57: 575000150051 Freight-APAP | B57: 7165i In-freight Expense | C57: 0 | D57: 0 | E57: 0 | F57: 0 | G57: 0 | H57: 0 | I57: 0 | J57: 0 | K57: 0 | L57: 0 | M57: 0 | N57: 0 | O57: =SUM(C57:N57) -> 0
A58: 670000150051 MALL JAPAN-APAP | B58: 7165i In-freight Expense | C58: 0 | D58: 0 | E58: 0 | F58: 0 | G58: 0 | H58: 0 | I58: 0 | J58: 0 | K58: 0 | L58: 0 | M58: 0 | N58: 0 | O58: =SUM(C58:N58) -> 0
A59: 695179159100 Canada Non Prod Spec-Freight | B59: 7165i In-freight Expense | C59: 0 | D59: 0 | E59: 0 | F59: 0 | G59: 0 | H59: 0 | I59: 0 | J59: 0 | K59: 0 | L59: 0 | M59: 0 | N59: 0 | O59: =SUM(C59:N59) -> 0
A60: 173041150256 Ofirmev Freight | B60: 7165i In-freight Expense | C60: 0 | D60: 0 | E60: 0 | F60: 0 | G60: 0 | H60: 0 | I60: 0 | J60: 0 | K60: 0 | L60: 0 | M60: 0 | N60: 0 | O60: =SUM(C60:N60) -> 0
A61: 174214150450 Acthar Freight | B61: 7165i In-freight Expense | C61: 0 | D61: 0 | E61: 0 | F61: 0 | G61: 0 | H61: 0 | I61: 0 | J61: 0 | K61: 0 | L61: 0 | M61: 0 | N61: 0 | O61: 0
A62: 594215150400 Operations-Hillstrom Freight | B62: 7165i In-freight Expense | C62: 0 | D62: 0 | E62: 0 | F62: 0 | G62: 0 | H62: 0 | I62: 0 | J62: 0 | K62: 0 | L62: 0 | M62: 0 | N62: 0 | O62: 0
A63: 594215150450 Operations-Aviation Freight | B63: 7165i In-freight Expense | C63: 0 | D63: 0 | E63: 0 | F63: 0 | G63: 0 | H63: 0 | I63: 0 | J63: 0 | K63: 0 | L63: 0 | M63: 0 | N63: 0 | O63: 0
A64: 594215150440 Operations-JT Ferric Freight | B64: 7165i In-freight Expense | C64: 0 | D64: 0 | E64: 0 | F64: 0 | G64: 0 | H64: 0 | I64: 0 | J64: 0 | K64: 0 | L64: 0 | M64: 0 | N64: 0 | O64: =SUM(C64:N64) -> 0
A65: 594215150475 Operations-Support Freight | B65: 7165i In-freight Expense | C65: 0 | D65: 0 | E65: 0 | F65: 0 | G65: 0 | H65: 0 | I65: 0 | J65: 0 | K65: 0 | L65: 0 | M65: 0 | N65: 0 | O65: =SUM(C65:N65) -> 0
A66: 157210151269 Intrathecal-Freight-General | B66: 7165i In-freight Expense | C66: 4323.0783 | D66: 4323.0783 | E66: 4323.0783 | F66: 4323.0783 | G66: 4323.0783 | H66: 4323.0783 | I66: 4323.0783 | J66: 4323.0783 | K66: 4323.0783 | L66: 4323.0783 | M66: 4323.0783 | N66: 4323.0783 | O66: =SUM(C66:N66) -> 51876.94
A67: 168210151269 Intrathecal-Freight-General | B67: 7165i In-freight Expense | C67: 0 | D67: 0 | E67: 0 | F67: 0 | G67: 0 | H67: 0 | I67: 0 | J67: 0 | K67: 0 | L67: 0 | M67: 0 | N67: 0 | O67: =SUM(C67:N67) -> 0
A68: In-Freight | C68: =SUM(C8:C67) -> 145931.1 | D68: =SUM(D8:D67) -> 175422.85 | E68: =SUM(E8:E67) -> 146177.17 | F68: =SUM(F8:F67) -> 146243.19 | G68: =SUM(G8:G67) -> 175624.61 | H68: =SUM(H8:H67) -> 146383.87 | I68: =SUM(I8:I67) -> 146450.68 | J68: =SUM(J8:J67) -> 175894.84 | ... O68: =SUM(O8:O67) -> 1875253
A70: 168210151269 Intrathecal-Freight-General | B70: 7171i Out-freight Expense (Used only with FDC 15. Also see object 6656 and 7170) | C70: 0 | D70: 0 | E70: 0 | F70: 0 | G70: 0 | H70: 0 | I70: 0 | J70: 0 | K70: 0 | L70: 0 | M70: 0 | N70: 0 | O70: =SUM(C70:N70) -> 0
A71: 157210151269 Intrathecal-Freight-General | B71: 7171i Out-freight Expense (Used only with FDC 15. Also see object 6656 and 7170) | C71: 25000 | D71: 25000 | E71: 25000 | F71: 25000 | G71: 25000 | H71: 25000 | I71: 25000 | J71: 25000 | K71: 25000 | L71: 25000 | M71: 25000 | N71: 25000 | O71: =SUM(C71:N71) -> 300000
A72: 594215150400 Operations-Hillstrom Freight | B72: 7171i Out-freight Expense (Used only with FDC 15. Also see object 6656 and 7170) | C72: 0 | D72: 0 | E72: 0 | F72: 0 | G72: 0 | H72: 0 | I72: 0 | J72: 0 | K72: 0 | L72: 0 | M72: 0 | N72: 0 | O72: =SUM(C72:N72) -> 0
A73: 594215150440 Operations-JT Ferric Freight | B73: 7171i Out-freight Expense (Used only with FDC 15. Also see object 6656 and 7170) | C73: 0 | D73: 0 | E73: 0 | F73: 0 | G73: 0 | H73: 0 | I73: 0 | J73: 0 | K73: 0 | L73: 0 | M73: 0 | N73: 0 | O73: =SUM(C73:N73) -> 0
A74: 594215150450 Operations-Aviation Freight | B74: 7171i Out-freight Expense (Used only with FDC 15. Also see object 6656 and 7170) | C74: 0 | D74: 0 | E74: 0 | F74: 0 | G74: 0 | H74: 0 | I74: 0 | J74: 0 | K74: 0 | L74: 0 | M74: 0 | N74: 0 | O74: =SUM(C74:N74) -> 0
A75: 594215150475 Operations-Support Freight | B75: 7171i Out-freight Expense (Used only with FDC 15. Also see object 6656 and 7170) | C75: 0 | D75: 0 | E75: 0 | F75: 0 | G75: 0 | H75: 0 | I75: 0 | J75: 0 | K75: 0 | L75: 0 | M75: 0 | N75: 0 | O75: =SUM(C75:N75) -> 0
A76: 174214150450 Acthar Freight | B76: 7171i Out-freight Expense (Used only with FDC 15. Also see object 6656 and 7170) | C76: 2000 | D76: 2000 | E76: 2000 | F76: 2000 | G76: 2000 | H76: 2000 | I76: 2000 | J76: 2000 | K76: 2000 | L76: 2000 | M76: 2000 | N76: 2000 | O76: =SUM(C76:N76) -> 24000
A77: 173041150256 Ofirmev Freight | B77: 7171i Out-freight Expense (Used only with FDC 15. Also see object 6656 and 7170) | C77: 0 | D77: 0 | E77: 0 | F77: 0 | G77: 0 | H77: 0 | I77: 0 | J77: 0 | K77: 0 | L77: 0 | M77: 0 | N77: 0 | O77: =SUM(C77:N77) -> 0
A78: 173041150256 Ofirmev Freight | B78: 7171.2000 | C78: 187590.13 | D78: 174161.14 | E78: 207190.98 | F78: 205023.4 | G78: 187397.84 | H78: 216782.51 | I78: 244179.4 | J78: 279074.9 | K78: 330304.16 | L78: 384255.12 | M78: 431877.4 | N78: 447831.58 | O78: =SUM(C78:N78) -> 3295668.5
A79: 011000150037 EUROPE NM I/C FREIGHT | B79: Net Spending | C79: 0 | D79: 0 | E79: 0 | F79: 0 | G79: 0 | H79: 0 | I79: 0 | J79: 0 | K79: 0 | L79: 0 | M79: 0 | N79: 0 | O79: =SUM(C79:N79) -> 0
A80: 011003150001 EUROPE NM I/C FREIGHT | B80: Net Spending | C80: 0 | D80: 0 | E80: 0 | F80: 0 | G80: 0 | H80: 0 | I80: 0 | J80: 0 | K80: 0 | L80: 0 | M80: 0 | N80: 0 | O80: =SUM(C80:N80) -> 0
A81: 011003155302 LAT AMER NM EXPORT FREIGHT | B81: Net Spending | C81: 0 | D81: 0 | E81: 0 | F81: 0 | G81: 0 | H81: 0 | I81: 0 | J81: 0 | K81: 0 | L81: 0 | M81: 0 | N81: 0 | O81: =SUM(C81:N81) -> 0
A82: 011003156701 MEXICO NUC MED FREIGHT | B82: Net Spending | C82: 0 | D82: 0 | E82: 0 | F82: 0 | G82: 0 | H82: 0 | I82: 0 | J82: 0 | K82: 0 | L82: 0 | M82: 0 | N82: 0 | O82: =SUM(C82:N82) -> 0
A83: 053003150002 LAT AMER NM EXPORT FREIGHT | B83: Net Spending | C83: 0 | D83: 0 | E83: 0 | F83: 0 | G83: 0 | H83: 0 | I83: 0 | J83: 0 | K83: 0 | L83: 0 | M83: 0 | N83: 0 | O83: =SUM(C83:N83) -> 0
A84: 060003150001 CARIBE NM I/C FREIGHT | B84: Net Spending | C84: 0 | D84: 0 | E84: 0 | F84: 0 | G84: 0 | H84: 0 | I84: 0 | J84: 0 | K84: 0 | L84: 0 | M84: 0 | N84: 0 | O84: =SUM(C84:N84) -> 0
A85: 067003150001 MEXICO NUC MED FREIGHT | B85: Net Spending | C85: 0 | D85: 0 | E85: 0 | F85: 0 | G85: 0 | H85: 0 | I85: 0 | J85: 0 | K85: 0 | L85: 0 | M85: 0 | N85: 0 | O85: =SUM(C85:N85) -> 0
A86: 140003151101 JAPAN Other - Domestic Related | B86: Net Spending | C86: 0 | D86: 0 | E86: 0 | F86: 0 | G86: 0 | H86: 0 | I86: 0 | J86: 0 | K86: 0 | L86: 0 | M86: 0 | N86: 0 | O86: =SUM(C86:N86) -> 0
A87: 140003151102 LATAM Other - Domestic Related | B87: Net Spending | C87: 0 | D87: 0 | E87: 0 | F87: 0 | G87: 0 | H87: 0 | I87: 0 | J87: 0 | K87: 0 | L87: 0 | M87: 0 | N87: 0 | O87: =SUM(C87:N87) -> 0
A88: 140003151103 EMEA Other - Domestic Related | B88: Net Spending | C88: 0 | D88: 0 | E88: 0 | F88: 0 | G88: 0 | H88: 0 | I88: 0 | J88: 0 | K88: 0 | L88: 0 | M88: 0 | N88: 0 | O88: =SUM(C88:N88) -> 0
A89: 140003151104 ASIA Other - Domestic Related | B89: Net Spending | C89: 0 | D89: 0 | E89: 0 | F89: 0 | G89: 0 | H89: 0 | I89: 0 | J89: 0 | K89: 0 | L89: 0 | M89: 0 | N89: 0 | O89: =SUM(C89:N89) -> 0
A90: 161001151644 Gen Export Freight-China | B90: Net Spending | C90: 0 | D90: 0 | E90: 0 | F90: 0 | G90: 0 | H90: 0 | I90: 0 | J90: 0 | K90: 0 | L90: 0 | M90: 0 | N90: 0 | O90: =SUM(C90:N90) -> 0
... A125: 100001154637 SPEC CHEM US EXPORT LAT AMER | B125: 7171i Out-freight Expense (Used only with FDC 15. Also see object 6656 and 7170) | C125: 0 | D125: 0 | E125: 0 | F125: 0 | G125: 0 | H125: 0 | I125: 0 | J125: 0 | K125: 0 | L125: 0 | M125: 0 | N125: 0 | O125: =SUM(C125:N125) -> 0
A126: 109001150208 FREIGHT | B126: 7171i Out-freight Expense (Used only with FDC 15. Also see object 6656 and 7170) | C126: 126920 | D126: 158650 | E126: 126920 | F126: 126920 | G126: 158650 | H126: 126920 | I126: 126920 | J126: 158650 | K126: 126920 | L126: 126920 | M126: 158650 | N126: 126920 | O126: =SUM(C126:N126) -> 1649960
A127: 109001150210 Freight | B127: 7171i Out-freight Expense (Used only with FDC 15. Also see object 6656 and 7170) | C127: 0 | D127: 0 | E127: 0 | F127: 0 | G127: 0 | H127: 0 | I127: 0 | J127: 0 | K127: 0 | L127: 0 | M127: 0 | N127: 0 | O127: =SUM(C127:N127) -> 0
A128: 107001150210 Freight | B128: 7171i Out-freight Expense (Used only with FDC 15. Also see object 6656 and 7170) | C128: 44560 | D128: 55700 | E128: 44560 | F128: 44560 | G128: 55700 | H128: 44560 | I128: 44560 | J128: 55700 | K128: 44560 | L128: 44560 | M128: 55700 | N128: 44560 | O128: =SUM(C128:N128) -> 579280
A129: 109001150300 REAGENTS | B129: 7171i Out-freight Expense (Used only with FDC 15. Also see object 6656 and 7170) | C129: 0 | D129: 0 | E129: 0 | F129: 0 | G129: 0 | H129: 0 | I129: 0 | J129: 0 | K129: 0 | L129: 0 | M129: 0 | N129: 0 | O129: =SUM(C129:N129) -> 0
A130: 107001150300 REAGENTS | B130: 7171i Out-freight Expense (Used only with FDC 15. Also see object 6656 and 7170) | C130: 24240 | D130: 30300 | E130: 24240 | F130: 24240 | G130: 30300 | H130: 24240 | I130: 24240 | J130: 30300 | K130: 24240 | L130: 24240 | M130: 30300 | N130: 24240 | O130: =SUM(C130:N130) -> 315120
A131: 109001150400 US Based Phosphates | B131: 7171i Out-freight Expense (Used only with FDC 15. Also see object 6656 and 7170) | C131: 0 | D131: 0 | E131: 0 | F131: 0 | G131: 0 | H131: 0 | I131: 0 | J131: 0 | K131: 0 | L131: 0 | M131: 0 | N131: 0 | O131: =SUM(C131:N131) -> 0
A132: 107001150400 US Based Phosphates | B132: 7171i Out-freight Expense (Used only with FDC 15. Also see object 6656 and 7170) | C132: 0 | D132: 0 | E132: 0 | F132: 0 | G132: 0 | H132: 0 | I132: 0 | J132: 0 | K132: 0 | L132: 0 | M132: 0 | N132: 0 | O132: =SUM(C132:N132) -> 0
A133: 109008150206 FREIGHT | B133: 7171i Out-freight Expense (Used only with FDC 15. Also see object 6656 and 7170) | C133: 0 | D133: 0 | E133: 0 | F133: 0 | G133: 0 | H133: 0 | I133: 0 | J133: 0 | K133: 0 | L133: 0 | M133: 0 | N133: 0 | O133: =SUM(C133:N133) -> 0
A134: 157001150250 Oxyocodone/APAP GR | B134: 7171i Out-freight Expense (Used only with FDC 15. Also see object 6656 and 7170) | C134: 4333.1612 | D134: 4643.7858 | E134: 5016.7446 | F134: 5408.3733 | G134: 5813.2212 | H134: 6221.0153 | I134: 6618.3851 | J134: 6991.5784 | K134: 7329.2242 | L134: 7624.1689 | M134: 7943.3835 | N134: 8264.5161 | O134: =SUM(C134:N134) -> 76207.557
A135: 157001150209 FREIGHT | B135: 7171i Out-freight Expense (Used only with FDC 15. Also see object 6656 and 7170) | C135: 10107.404 | D135: 11378.006 | E135: 9057.0283 | F135: 11501.51 | G135: 11214.127 | H135: 10283.454 | I135: 11096.889 | J135: 10857.317 | K135: 9789.354 | L135: 11518.986 | M135: 10892.917 | N135: 10150.186 | O135: =SUM(C135:N135) -> 127847.18
A136: 157001150210 Frt Exp-Oxycodone Products | B136: 7171i Out-freight Expense (Used only with FDC 15. Also see object 6656 and 7170) | C136: 37596.718 | D136: 45735.938 | E136: 37311.232 | F136: 36906.034 | G136: 44897.783 | H136: 36626.257 | I136: 36228.551 | J136: 44075.626 | K136: 35954.37 | L136: 35564.012 | M136: 43269.153 | N136: 35295.314 | O136: =SUM(C136:N136) -> 469460.99
...

Sheet FY15 Current Forecast
C2: FY 2015 | D2: FY 2015 | E2: FY 2015 | F2: FY 2015 | G2: FY 2015 | H2: FY 2015 | I2: FY 2015 | J2: FY 2015 | K2: FY 2015 | L2: FY 2015 | M2: FY 2015 | N2: FY 2015
C3: Forecast Rate | D3: Forecast Rate | E3: Forecast Rate | F3: Forecast Rate | G3: Forecast Rate | H3: Forecast Rate | I3: Forecast Rate | J3: Forecast Rate | K3: Forecast Rate | L3: Forecast Rate | M3: Forecast Rate | N3: Forecast Rate
C4: USD | D4: USD | E4: USD | F4: USD | G4: USD | H4: USD | I4: USD | J4: USD | K4: USD | L4: USD | M4: USD | N4: USD
C5: Current Forecast | D5: Current Forecast | E5: Current Forecast | F5: Current Forecast | G5: Current Forecast | H5: Current Forecast | I5: Current Forecast | J5: Current Forecast | K5: Current Forecast | L5: Current Forecast | M5: Current Forecast | N5: Current Forecast
C6: FDC 015 Out-Freight Expense | D6: FDC 015 Out-Freight Expense | E6: FDC 015 Out-Freight Expense | F6: FDC 015 Out-Freight Expense | G6: FDC 015 Out-Freight Expense | H6: FDC 015 Out-Freight Expense | I6: FDC 015 Out-Freight Expense | J6: FDC 015 Out-Freight Expense | K6: FDC 015 Out-Freight Expense | L6: FDC 015 Out-Freight Expense | M6: FDC 015 Out-Freight Expense | N6: FDC 015 Out-Freight Expense | O6: FDC 015 Out-Freight Expense
C7: Oct | D7: Nov | E7: Dec | F7: Jan | G7: Feb | H7: Mar | I7: Apr | J7: May | K7: Jun | L7: Jul | M7: Aug | N7: Sep | O7: Annual
A8: 157001150209 FREIGHT | B8: 7165i In-freight Expense | C8: 0 | D8: 0 | E8: 0 | F8: 0 | G8: 0 | H8: 0 | I8: 0 | J8: 0 | K8: 0 | L8: 0 | M8: 0 | N8: 0 | O8: =SUM(C8:N8) -> 0
A9: 157001150210 Frt Exp-Oxycodone Products | B9: 7165i In-freight Expense | C9: 0 | D9: 0 | E9: 0 | F9: 0 | G9: 0 | H9: 0 | I9: 0 | J9: 0 | K9: 0 | L9: 0 | M9: 0 | N9: 0 | O9: =SUM(C9:N9) -> 0
A10: 157001150211 Frt Exp-Hydrocodone Products | B10: 7165i In-freight Expense | C10: 0 | D10: 0 | E10: 0 | F10: 0 | G10: 0 | H10: 0 | I10: 0 | J10: 0 | K10: 0 | L10: 0 | M10: 0 | N10: 0 | O10: =SUM(C10:N10) -> 0
A11: 157001150212 Frt Exp-Methylin Oral Solution | B11: 7165i In-freight Expense | C11: 0 | D11: 0 | E11: 0 | F11: 0 | G11: 0 | H11: 0 | I11: 0 | J11: 0 | K11: 0 | L11: 0 | M11: 0 | N11: 0 | O11: =SUM(C11:N11) -> 0
A12: 157001150219 FREIGHT | B12: 7165i In-freight Expense | C12: 0 | D12: 0 | E12: 0 | F12: 0 | G12: 0 | H12: 0 | I12: 0 | J12: 0 | K12: 0 | L12: 0 | M12: 0 | N12: 0 | O12: =SUM(C12:N12) -> 0
A13: 157001150221 Frt Exp-ADDICTION TREATMENT | B13: 7165i In-freight Expense | C13: 0 | D13: 0 | E13: 0 | F13: 0 | G13: 0 | H13: 0 | I13: 0 | J13: 0 | K13: 0 | L13: 0 | M13: 0 | N13: 0 | O13: =SUM(C13:N13) -> 0
A14: 157001150222 Frt Exp-Methylphenidate | B14: 7165i In-freight Expense | C14: 0 | D14: 0 | E14: 0 | F14: 0 | G14: 0 | H14: 0 | I14: 0 | J14: 0 | K14: 0 | L14: 0 | M14: 0 | N14: 0 | O14: =SUM(C14:N14) -> 0
A15: 157001150224 Frt Exp-Other Brand Products | B15: 7165i In-freight Expense | C15: 0 | D15: 0 | E15: 0 | F15: 0 | G15: 0 | H15: 0 | I15: 0 | J15: 0 | K15: 0 | L15: 0 | M15: 0 | N15: 0 | O15: =SUM(C15:N15) -> 0
A16: 157001150225 Frt Exp-CNS Non-Promoted Prod | B16: 7165i In-freight Expense | C16: 0 | D16: 0 | E16: 0 | F16: 0 | G16: 0 | H16: 0 | I16: 0 | J16: 0 | K16: 0 | L16: 0 | M16: 0 | N16: 0 | O16: =SUM(C16:N16) -> 0
A17: 157001150226 Zydus Freight Expense | B17: 7165i In-freight Expense | C17: 0 | D17: 0 | E17: 0 | F17: 0 | G17: 0 | H17: 0 | I17: 0 | J17: 0 | K17: 0 | L17: 0 | M17: 0 | N17: 0 | O17: =SUM(C17:N17) -> 0
A18: 157001150227 Oxycodone ER Products Freight | B18: 7165i In-freight Expense | C18: 0 | D18: 0 | E18: 0 | F18: 0 | G18: 0 | H18: 0 | I18: 0 | J18: 0 | K18: 0 | L18: 0 | M18: 0 | N18: 0 | O18: =SUM(C18:N18) -> 0
A19: 157001150229 Morphine ER-Frt Exp | B19: 7165i In-freight Expense | C19: 0 | D19: 0 | E19: 0 | F19: 0 | G19: 0 | H19: 0 | I19: 0 | J19: 0 | K19: 0 | L19: 0 | M19: 0 | N19: 0 | O19: =SUM(C19:N19) -> 0
... A70: 173041150256 Ofirmev Freight | B70: 7165i In-freight Expense | C70: 0 | D70: 0 | E70: 0 | F70: 0 | G70: 0 | H70: 0 | I70: 0 | J70: 0 | K70: 0 | L70: 0 | M70: 0 | N70: 0 | O70: =SUM(C70:N70) -> 0
A71: 174214150450 Acthar Freight | B71: 7165i In-freight Expense | C71: 0 | D71: 0 | E71: 0 | F71: 0 | G71: 0 | H71: 0 | I71: 0 | J71: 0 | K71: 0 | L71: 0 | M71: 0 | N71: 0 | O71: 0
A72: 594215150400 Operations-Hillstrom Freight | B72: 7165i In-freight Expense | C72: 0 | D72: 0 | E72: 0 | F72: 0 | G72: 0 | H72: 0 | I72: 0 | J72: 0 | K72: 0 | L72: 0 | M72: 0 | N72: 0 | O72: 0
A73: 594215150450 Operations-Aviation Freight | B73: 7165i In-freight Expense | C73: 0 | D73: 0 | E73: 0 | F73: 0 | G73: 0 | H73: 0 | I73: 0 | J73: 0 | K73: 0 | L73: 0 | M73: 0 | N73: 0 | O73: 0
A74: 594215150440 Operations-JT Ferric Freight | B74: 7165i In-freight Expense | C74: 0 | D74: 0 | E74: 0 | F74: 0 | G74: 0 | H74: 0 | I74: 0 | J74: 0 | K74: 0 | L74: 0 | M74: 0 | N74: 0 | O74: =SUM(C74:N74) -> 0
A75: 594215150475 Operations-Support Freight | B75: 7165i In-freight Expense | C75: 0 | D75: 0 | E75: 0 | F75: 0 | G75: 0 | H75: 0 | I75: 0 | J75: 0 | K75: 0 | L75: 0 | M75: 0 | N75: 0 | O75: =SUM(C75:N75) -> 0
A76: 157210151269 Intrathecal-Freight-General | B76: 7165i In-freight Expense | C76: 0 | D76: 0 | E76: 0 | F76: 0 | G76: 0 | H76: 0 | I76: 0 | J76: 0 | K76: 0 | L76: 0 | M76: 0 | N76: 0 | O76: =SUM(C76:N76) -> 0
A77: 168210151269 Intrathecal-Freight-General | B77: 7165i In-freight Expense | C77: 0 | D77: 0 | E77: 0 | F77: 0 | G77: 0 | H77: 0 | I77: 0 | J77: 0 | K77: 0 | L77: 0 | M77: 0 | N77: 0 | O77: =SUM(C77:N77) -> 0
A78: In-Freight | C78: =SUM(C8:C77) -> 0 | D78: =SUM(D8:D77) -> 0 | E78: =SUM(E8:E77) -> 0 | F78: =SUM(F8:F77) -> 0 | G78: =SUM(G8:G77) -> 0 | H78: =SUM(H8:H77) -> 0 | I78: =SUM(I8:I77) -> 0 | J78: =SUM(J8:J77) -> 0 | ... O78: =SUM(O8:O77) -> 0
A80: 168210151269 Intrathecal-Freight-General | B80: 7171i Out-freight Expense (Used only with FDC 15. Also see object 6656 and 7170) | C80: 0 | D80: 0 | E80: 0 | F80: 0 | G80: 0 | H80: 0 | I80: 0 | J80: 0 | K80: 0 | L80: 0 | M80: 0 | N80: 0 | O80: =SUM(C80:N80) -> 0
A81: 157210151269 Intrathecal-Freight-General | B81: 7171i Out-freight Expense (Used only with FDC 15. Also see object 6656 and 7170) | C81: 0 | D81: 0 | E81: 0 | F81: 0 | G81: 0 | H81: 0 | I81: 0 | J81: 0 | K81: 0 | L81: 0 | M81: 0 | N81: 0 | O81: =SUM(C81:N81) -> 0
A82: 594215150400 Operations-Hillstrom Freight | B82: 7171i Out-freight Expense (Used only with FDC 15. Also see object 6656 and 7170) | C82: 0 | D82: 0 | E82: 0 | F82: 0 | G82: 0 | H82: 0 | I82: 0 | J82: 0 | K82: 0 | L82: 0 | M82: 0 | N82: 0 | O82: =SUM(C82:N82) -> 0
A83: 594215150440 Operations-JT Ferric Freight | B83: 7171i Out-freight Expense (Used only with FDC 15. Also see object 6656 and 7170) | C83: 0 | D83: 0 | E83: 0 | F83: 0 | G83: 0 | H83: 0 | I83: 0 | J83: 0 | K83: 0 | L83: 0 | M83: 0 | N83: 0 | O83: =SUM(C83:N83) -> 0
A84: 594215150450 Operations-Aviation Freight | B84: 7171i Out-freight Expense (Used only with FDC 15. Also see object 6656 and 7170) | C84: 0 | D84: 0 | E84: 0 | F84: 0 | G84: 0 | H84: 0 | I84: 0 | J84: 0 | K84: 0 | L84: 0 | M84: 0 | N84: 0 | O84: =SUM(C84:N84) -> 0
A85: 594215150475 Operations-Support Freight | B85: 7171i Out-freight Expense (Used only with FDC 15. Also see object 6656 and 7170) | C85: 0 | D85: 0 | E85: 0 | F85: 0 | G85: 0 | H85: 0 | I85: 0 | J85: 0 | K85: 0 | L85: 0 | M85: 0 | N85: 0 | O85: =SUM(C85:N85) -> 0
A86: 174214150450 Acthar Freight | B86: 7171i Out-freight Expense (Used only with FDC 15. Also see object 6656 and 7170) | C86: 0 | D86: 0 | E86: 0 | F86: 0 | G86: 0 | H86: 0 | I86: 0 | J86: 0 | K86: 0 | L86: 0 | M86: 0 | N86: 0 | O86: =SUM(C86:N86) -> 0
A87: 173041150256 Ofirmev Freight | B87: 7171i Out-freight Expense (Used only with FDC 15. Also see object 6656 and 7170) | C87: 0 | D87: 0 | E87: 0 | F87: 0 | G87: 0 | H87: 0 | I87: 0 | J87: 0 | K87: 0 | L87: 0 | M87: 0 | N87: 0 | O87: =SUM(C87:N87) -> 0
A88: 173041150256 Ofirmev Freight | B88: 7171.2000 | C88: 0 | D88: 0 | E88: 0 | F88: 0 | G88: 0 | H88: 0 | I88: 0 | J88: 0 | K88: 0 | L88: 0 | M88: 0 | N88: 0 | O88: =SUM(C88:N88) -> 0
A89: 752000157455 ARD Freight | B89: 7171i Out-freight Expense (Used only with FDC 15. Also see object 6656 and 7170) | C89: 0 | D89: 0 | E89: 0 | F89: 0 | G89: 0 | H89: 0 | I89: 0 | J89: 0 | K89: 0 | L89: 0 | M89: 0 | N89: 0 | O89: =SUM(C89:N89) -> 0
A90: 011000150037 EUROPE NM I/C FREIGHT | B90: Net Spending | C90: 0 | D90: 0 | E90: 0 | F90: 0 | G90: 0 | H90: 0 | I90: 0 | J90: 0 | K90: 0 | L90: 0 | M90: 0 | N90: 0 | O90: =SUM(C90:N90) -> 0
A91: 011003155302 LAT AMER NM FREIGHT | B91: Net Spending | C91: 0 | D91: 0 | E91: 0 | F91: 0 | G91: 0 | H91: 0 | I91: 0 | J91: 0 | K91: 0 | L91: 0 | M91: 0 | N91: 0 | O91: =SUM(C91:N91) -> 0
... A216: 712000150003 Dublin Freight Expense | B216: 7991 Non Cost Ctr Supported | C216: 0 | D216: 0 | E216: 0 | F216: 0 | G216: 0 | H216: 0 | I216: 0 | J216: 0 | K216: 0 | L216: 0 | M216: 0 | N216: 0 | O216: =SUM(C216:N216) -> 0
A217: Out-Freight | C217: =SUM(C80:C216) -> 0 | D217: =SUM(D80:D216) -> 0 | E217: =SUM(E80:E216) -> 0 | F217: =SUM(F80:F216) -> 0 | G217: =SUM(G80:G216) -> 0 | H217: =SUM(H80:H216) -> 0 | I217: =SUM(I80:I216) -> 0 | J217: =SUM(J80:J216) -> 0 | ... O217: =SUM(O80:O216) -> 0
A219: TOTAL PHARM | C219: =+C217+C78 -> 0 | D219: =+D217+D78 -> 0 | E219: =+E217+E78 -> 0 | F219: =+F217+F78 -> 0 | G219: =+G217+G78 -> 0 | H219: =+H217+H78 -> 0 | I219: =+I217+I78 -> 0 | J219: =+J217+J78 -> 0 | ... O219: =+O217+O78 -> 0
A222: 020019150419 DISTRIBUTION EXP-CONT MEDIA | B222: 7165i In-freight Expense | C222: 0 | D222: 0 | E222: 0 | F222: 0 | G222: 0 | H222: 0 | I222: 0 | J222: 0 | K222: 0 | L222: 0 | M222: 0 | N222: 0 | O222: =SUM(C222:N222) -> 0
A223: 140003151100 OPTIRAY-Freight | B223: 7165i In-freight Expense | C223: 0 | D223: 0 | E223: 0 | F223: 0 | G223: 0 | H223: 0 | I223: 0 | J223: 0 | K223: 0 | L223: 0 | M223: 0 | N223: 0 | O223: =SUM(C223:N223) -> 0
A224: 020003151100 OPTIRAY-Freight | B224: 7165i In-freight Expense | C224: 0 | D224: 0 | E224: 0 | F224: 0 | G224: 0 | H224: 0 | I224: 0 | J224: 0 | K224: 0 | L224: 0 | M224: 0 | N224: 0 | O224: =SUM(C224:N224) -> 0
A225: 020019150419 DISTRIBUTION EXP-CONT MEDIA | B225: 6656i Postage | C225: 0 | D225: 0 | E225: 0 | F225: 0 | G225: 0 | H225: 0 | I225: 0 | J225: 0 | K225: 0 | L225: 0 | M225: 0 | N225: 0 | O225: =SUM(C225:N225) -> 0
A226: 020019150419 DISTRIBUTION EXP-CONT MEDIA | B226: 7163i O/S-Supplier Restock | C226: 0 | D226: 0 | E226: 0 | F226: 0 | G226: 0 | H226: 0 | I226: 0 | J226: 0 | K226: 0 | L226: 0 | M226: 0 | N226: 0 | O226: =SUM(C226:N226) -> 0
A227: 140020150001 LF Income Statement-Freight | B227: 7165i In-freight Expense | C227: 0 | D227: 0 | E227: 0 | F227: 0 | G227: 0 | H227: 0 | I227: 0 | J227: 0 | K227: 0 | L227: 0 | M227: 0 | N227: 0 | O227: =SUM(C227:N227) -> 0
O228: =SUM(C228:N228) -> 0
A229: 140003151100 OPTIRAY-Freight | B229: 7171i Out-freight Expense (Used only with FDC 15. Also see object 6656 and 7170) | C229: 0 | D229: 0 | E229: 0 | F229: 0 | G229: 0 | H229: 0 | I229: 0 | J229: 0 | K229: 0 | L229: 0 | M229: 0 | N229: 0 | O229: =SUM(C229:N229) -> 0
A230: 140003151100 OPTIRAY-Freight | B230: 7556i TRSF-Miscellaneous | C230: 0 | D230: 0 | E230: 0 | F230: 0 | G230: 0 | H230: 0 | I230: 0 | J230: 0 | K230: 0 | L230: 0 | M230: 0 | N230: 0 | O230: =SUM(C230:N230) -> 0
A231: 020003151100 OPTIRAY-Freight | B231: 7171i Out-freight Expense (Used only with FDC 15. Also see object 6656 and 7170) | C231: 0 | D231: 0 | E231: 0 | F231: 0 | G231: 0 | H231: 0 | I231: 0 | J231: 0 | K231: 0 | L231: 0 | M231: 0 | N231: 0 | O231: =SUM(C231:N231) -> 0
A232: 020003151100 OPTIRAY-Freight | B232: 7556i TRSF-Miscellaneous | C232: 0 | D232: 0 | E232: 0 | F232: 0 | G232: 0 | H232: 0 | I232: 0 | J232: 0 | K232: 0 | L232: 0 | M232: 0 | N232: 0 | O232: =SUM(C232:N232) -> 0
A233: 020003153200 OPTISON-Freight | B233: 7171i Out-freight Expense (Used only with FDC 15. Also see object 6656 and 7170) | C233: 0 | D233: 0 | E233: 0 | F233: 0 | G233: 0 | H233: 0 | I233: 0 | J233: 0 | K233: 0 | L233: 0 | M233: 0 | N233: 0 | O233: =SUM(C233:N233) -> 0
A234: 140020150001 LF Income Statement-Freight | B234: 7171i Out-freight Expense (Used only with FDC 15. Also see object 6656 and 7170) | C234: 0 | D234: 0 | E234: 0 | F234: 0 | G234: 0 | H234: 0 | I234: 0 | J234: 0 | K234: 0 | L234: 0 | M234: 0 | N234: 0 | O234: =SUM(C234:N234) -> 0
A235: 140020150001 LF Income Statement-Freight | B235: 6759i Freight Interbranch | C235: 0 | D235: 0 | E235: 0 | F235: 0 | G235: 0 | H235: 0 | I235: 0 | J235: 0 | K235: 0 | L235: 0 | M235: 0 | N235: 0 | O235: =SUM(C235:N235) -> 0
A236: TOTAL CM&DS | C236: =SUM(C222:C235) -> 0 | D236: =SUM(D222:D235) -> 0 | E236: =SUM(E222:E235) -> 0 | F236: =SUM(F222:F235) -> 0 | G236: =SUM(G222:G235) -> 0 | H236: =SUM(H222:H235) -> 0 | I236: =SUM(I222:I235) -> 0 | J236: =SUM(J222:J235) -> 0 | ... O236: =SUM(O222:O235) -> 0
A238: 541000156080 Freight | B238: Net Spending | C238: 0 | D238: 0 | E238: 0 | F238: 0 | G238: 0 | H238: 0 | I238: 0 | J238: 0 | K238: 0 | L238: 0 | M238: 0 | N238: 0 | O238: =SUM(C238:N238) -> 0
A239: 537000156080 Freight | B239: Net Spending | C239: 0 | D239: 0 | E239: 0 | F239: 0 | G239: 0 | H239: 0 | I239: 0 | J239: 0 | K239: 0 | L239: 0 | M239: 0 | N239: 0 | O239: =SUM(C239:N239) -> 0
A240: 538000156080 Freight | B240: Net Spending | C240: 0 | D240: 0 | E240: 0 | F240: 0 | G240: 0 | H240: 0 | I240: 0 | J240: 0 | K240: 0 | L240: 0 | M240: 0 | N240: 0 | O240: =SUM(C240:N240) -> 0
A241: 802000156080 Freight | B241: Net Spending | C241: 0 | D241: 0 | E241: 0 | F241: 0 | G241: 0 | H241: 0 | I241: 0 | J241: 0 | K241: 0 | L241: 0 | M241: 0 | N241: 0 | O241: =SUM(C241:N241) -> 0
A242: 804000156080 Freight | B242: Net Spending | C242: 0 | D242: 0 | E242: 0 | F242: 0 | G242: 0 | H242: 0 | I242: 0 | J242: 0 | K242: 0 | L242: 0 | M242: 0 | N242: 0 | O242: =SUM(C242:N242) -> 0
A243: 805000156080 Freight | B243: Net Spending | C243: 0 | D243: 0 | E243: 0 | F243: 0 | G243: 0 | H243: 0 | I243: 0 | J243: 0 | K243: 0 | L243: 0 | M243: 0 | N243: 0 | O243: =SUM(C243:N243) -> 0
A244: 805000156472 Freight-China | B244: Net Spending | C244: 0 | D244: 0 | E244: 0 | F244: 0 | G244: 0 | H244: 0 | I244: 0 | J244: 0 | K244: 0 | L244: 0 | M244: 0 | N244: 0 | O244: =SUM(C244:N244) -> 0
A245: 540000156080 Freight | B245: Net Spending | C245: 0 | D245: 0 | E245: 0 | F245: 0 | G245: 0 | H245: 0 | I245: 0 | J245: 0 | K245: 0 | L245: 0 | M245: 0 | N245: 0 | O245: =SUM(C245:N245) -> 0
A246: 807000156080 Freight | B246: Net Spending | C246: 0 | D246: 0 | E246: 0 | F246: 0 | G246: 0 | H246: 0 | I246: 0 | J246: 0 | K246: 0 | L246: 0 | M246: 0 | N246: 0 | O246: =SUM(C246:N246) -> 0
A247: 535000156080 Freight | B247: Net Spending | C247: 0 | D247: 0 | E247: 0 | F247: 0 | G247: 0 | H247: 0 | I247: 0 | J247: 0 | K247: 0 | L247: 0 | M247: 0 | N247: 0 | O247: =SUM(C247:N247) -> 0
A248: 532000156080 Freight | B248: Net Spending | C248: 0 | D248: 0 | E248: 0 | F248: 0 | G248: 0 | H248: 0 | I248: 0 | J248: 0 | K248: 0 | L248: 0 | M248: 0 | N248: 0 | O248: =SUM(C248:N248) -> 0
A249: 534000156080 Freight | B249: Net Spending | C249: 0 | D249: 0 | E249: 0 | F249: 0 | G249: 0 | H249: 0 | I249: 0 | J249: 0 | K249: 0 | L249: 0 | M249: 0 | N249: 0 | O249: =SUM(C249:N249) -> 0
... A253: 734000156080 Freight | B253: Net Spending | C253: 0 | D253: 0 | E253: 0 | F253: 0 | G253: 0 | H253: 0 | I253: 0 | J253: 0 | K253: 0 | L253: 0 | M253: 0 | N253: 0 | O253: =SUM(C253:N253) -> 0
A254: 736538156080 Astri Freight | B254: Net Spending | C254: 0 | D254: 0 | E254: 0 | F254: 0 | G254: 0 | H254: 0 | I254: 0 | J254: 0 | K254: 0 | L254: 0 | M254: 0 | N254: 0 | O254: 0
A255: 736541156080 Belgm Freight | B255: Net Spending | C255: 0 | D255: 0 | E255: 0 | F255: 0 | G255: 0 | H255: 0 | I255: 0 | J255: 0 | K255: 0 | L255: 0 | M255: 0 | N255: 0 | O255: 0
A256: 736550156080 Switz Freight | B256: Net Spending | C256: 0 | D256: 0 | E256: 0 | F256: 0 | G256: 0 | H256: 0 | I256: 0 | J256: 0 | K256: 0 | L256: 0 | M256: 0 | N256: 0 | O256: 0
A257: 736556156080 Germa Freight | B257: Net Spending | C257: 0 | D257: 0 | E257: 0 | F257: 0 | G257: 0 | H257: 0 | I257: 0 | J257: 0 | K257: 0 | L257: 0 | M257: 0 | N257: 0 | O257: 0
A258: 736558156080 Dnmrk Freight | B258: Net Spending | C258: 0 | D258: 0 | E258: 0 | F258: 0 | G258: 0 | H258: 0 | I258: 0 | J258: 0 | K258: 0 | L258: 0 | M258: 0 | N258: 0 | O258: 0
A259: 736564156080 Spain Freight | B259: Net Spending | C259: 0 | D259: 0 | E259: 0 | F259: 0 | G259: 0 | H259: 0 | I259: 0 | J259: 0 | K259: 0 | L259: 0 | M259: 0 | N259: 0 | O259: 0
A260: 736566156080 Finlnd Freight | B260: Net Spending | C260: 0 | D260: 0 | E260: 0 | F260: 0 | G260: 0 | H260: 0 | I260: 0 | J260: 0 | K260: 0 | L260: 0 | M260: 0 | N260: 0 | O260: 0
A261: 736567156080 Franc Freight | B261: Net Spending | C261: 0 | D261: 0 | E261: 0 | F261: 0 | G261: 0 | H261: 0 | I261: 0 | J261: 0 | K261: 0 | L261: 0 | M261: 0 | N261: 0 | O261: 0
A262: 736569156080 UK Freight | B262: Net Spending | C262: 0 | D262: 0 | E262: 0 | F262: 0 | G262: 0 | H262: 0 | I262: 0 | J262: 0 | K262: 0 | L262: 0 | M262: 0 | N262: 0 | O262: 0
A263: 736581156080 Irela Freight | B263: Net Spending | C263: 0 | D263: 0 | E263: 0 | F263: 0 | G263: 0 | H263: 0 | I263: 0 | J263: 0 | K263: 0 | L263: 0 | M263: 0 | N263: 0 | O263: 0
A264: 736586156080 Italy Freight | B264: Net Spending | C264: 0 | D264: 0 | E264: 0 | F264: 0 | G264: 0 | H264: 0 | I264: 0 | J264: 0 | K264: 0 | L264: 0 | M264: 0 | N264: 0 | O264: 0
A265: 736591156080 Kazak Freight | B265: Net Spending | C265: 0 | D265: 0 | E265: 0 | F265: 0 | G265: 0 | H265: 0 | I265: 0 | J265: 0 | K265: 0 | L265: 0 | M265: 0 | N265: 0 | O265: 0
... A274: 736698156080 MidEa Freight | B274: Net Spending | C274: 0 | D274: 0 | E274: 0 | F274: 0 | G274: 0 | H274: 0 | I274: 0 | J274: 0 | K274: 0 | L274: 0 | M274: 0 | N274: 0 | O274: 0
A275: 736697154205 EHQ Freight | B275: Net Spending | C275: 0 | D275: 0 | E275: 0 | F275: 0 | G275: 0 | H275: 0 | I275: 0 | J275: 0 | K275: 0 | L275: 0 | M275: 0 | N275: 0 | O275: =SUM(C275:N275) -> 0
A276: 736697156080 EHQ Freight | B276: Net Spending | C276: 0 | D276: 0 | E276: 0 | F276: 0 | G276: 0 | H276: 0 | I276: 0 | J276: 0 | K276: 0 | L276: 0 | M276: 0 | N276: 0 | O276: =SUM(C276:N276) -> 0
A277: 741000156080 Freight | B277: Net Spending | C277: 0 | D277: 0 | E277: 0 | F277: 0 | G277: 0 | H277: 0 | I277: 0 | J277: 0 | K277: 0 | L277: 0 | M277: 0 | N277: 0 | O277: =SUM(C277:N277) -> 0
A278: 748000156080 Freight | B278: Net Spending | C278: 0 | D278: 0 | E278: 0 | F278: 0 | G278: 0 | H278: 0 | I278: 0 | J278: 0 | K278: 0 | L278: 0 | M278: 0 | N278: 0 | O278: =SUM(C278:N278) -> 0
A279: 735000156080 Freight | B279: Net Spending | C279: 0 | D279: 0 | E279: 0 | F279: 0 | G279: 0 | H279: 0 | I279: 0 | J279: 0 | K279: 0 | L279: 0 | M279: 0 | N279: 0 | O279: =SUM(C279:N279) -> 0
A280: 742000156080 Freight | B280: Net Spending | C280: 0 | D280: 0 | E280: 0 | F280: 0 | G280: 0 | H280: 0 | I280: 0 | J280: 0 | K280: 0 | L280: 0 | M280: 0 | N280: 0 | O280: =SUM(C280:N280) -> 0
A281: 745000156080 Freight | B281: Net Spending | C281: 0 | D281: 0 | E281: 0 | F281: 0 | G281: 0 | H281: 0 | I281: 0 | J281: 0 | K281: 0 | L281: 0 | M281: 0 | N281: 0 | O281: =SUM(C281:N281) -> 0
A282: 746000156080 Freight | B282: Net Spending | C282: 0 | D282: 0 | E282: 0 | F282: 0 | G282: 0 | H282: 0 | I282: 0 | J282: 0 | K282: 0 | L282: 0 | M282: 0 | N282: 0 | O282: =SUM(C282:N282) -> 0
A283: 747000156080 Freight | B283: Net Spending | C283: 0 | D283: 0 | E283: 0 | F283: 0 | G283: 0 | H283: 0 | I283: 0 | J283: 0 | K283: 0 | L283: 0 | M283: 0 | N283: 0 | O283: =SUM(C283:N283) -> 0
A284: 799000156080 Freight | B284: Net Spending | C284: 0 | D284: 0 | E284: 0 | F284: 0 | G284: 0 | H284: 0 | I284: 0 | J284: 0 | K284: 0 | L284: 0 | M284: 0 | N284: 0 | O284: =SUM(C284:N284) -> 0
A285: 799538156080 Astri Freight | B285: Net Spending | C285: 0 | D285: 0 | E285: 0 | F285: 0 | G285: 0 | H285: 0 | I285: 0 | J285: 0 | K285: 0 | L285: 0 | M285: 0 | N285: 0 | O285: =SUM(C285:N285) -> 0
A286: 799541156080 Belgm Freight | B286: Net Spending | C286: 0 | D286: 0 | E286: 0 | F286: 0 | G286: 0 | H286: 0 | I286: 0 | J286: 0 | K286: 0 | L286: 0 | M286: 0 | N286: 0 | O286: =SUM(C286:N286) -> 0
... A322: 011003150001 EUROPE NM I/C FREIGHT | B322: Net Spending | C322: 0 | D322: 0 | E322: 0 | F322: 0 | G322: 0 | H322: 0 | I322: 0 | J322: 0 | K322: 0 | L322: 0 | M322: 0 | N322: 0 | O322: =SUM(C322:N322) -> 0
A323: 011003158301 AUSTRALIA NM I/C FREIGHT | B323: Net Spending | C323: 0 | D323: 0 | E323: 0 | F323: 0 | G323: 0 | H323: 0 | I323: 0 | J323: 0 | K323: 0 | L323: 0 | M323: 0 | N323: 0 | O323: 0
A324: 011003157301 JAPAN - NUC MED Freight | B324: Net Spending | C324: 0 | D324: 0 | E324: 0 | F324: 0 | G324: 0 | H324: 0 | I324: 0 | J324: 0 | K324: 0 | L324: 0 | M324: 0 | N324: 0 | O324: 0
A325: 011003154301 Southeast Asia NM Freight | B325: Net Spending | C325: 0 | D325: 0 | E325: 0 | F325: 0 | G325: 0 | H325: 0 | I325: 0 | J325: 0 | K325: 0 | L325: 0 | M325: 0 | N325: 0 | O325: 0
A326: 011003157105 Nuc Freight Allocated Direct | B326: Net Spending | C326: 0 | D326: 0 | E326: 0 | F326: 0 | G326: 0 | H326: 0 | I326: 0 | J326: 0 | K326: 0 | L326: 0 | M326: 0 | N326: 0 | O326: =SUM(C326:N326) -> 0
...

Sheet FY15 Working Forecast
C2: FY 2015 | D2: FY 2015 | E2: FY 2015 | F2: FY 2015 | G2: FY 2015 | H2: FY 2015 | I2: FY 2015 | J2: FY 2015 | K2: FY 2015 | L2: FY 2015 | M2: FY 2015 | N2: FY 2015
C3: Actual Rate | D3: Actual Rate | E3: Actual Rate | F3: Actual Rate | G3: Actual Rate | H3: Actual Rate | I3: Actual Rate | J3: Actual Rate | K3: Actual Rate | L3: Actual Rate | M3: Actual Rate | N3: Actual Rate
C4: USD | D4: USD | E4: USD | F4: USD | G4: USD | H4: USD | I4: USD | J4: USD | K4: USD | L4: USD | M4: USD | N4: USD
C5: Actuals | D5: Actuals | E5: Actuals | F5: Actuals | G5: Actuals | H5: Actuals | I5: Actuals | J5: Actuals | K5: Actuals | L5: Actuals | M5: Actuals | N5: Actuals
C6: FDC 015 Out-Freight Expense | D6: FDC 015 Out-Freight Expense | E6: FDC 015 Out-Freight Expense | F6: FDC 015 Out-Freight Expense | G6: FDC 015 Out-Freight Expense | H6: FDC 015 Out-Freight Expense | I6: FDC 015 Out-Freight Expense | J6: FDC 015 Out-Freight Expense | K6: FDC 015 Out-Freight Expense | L6: FDC 015 Out-Freight Expense | M6: FDC 015 Out-Freight Expense | N6: FDC 015 Out-Freight Expense | O6: FDC 015 Out-Freight Expense
C7: Oct | D7: Nov | E7: Dec | F7: Jan | G7: Feb | H7: Mar | I7: Apr | J7: May | K7: Jun | L7: Jul | M7: Aug | N7: Sep | O7: Annual
A8: 157001150209 FREIGHT | B8: 7165i In-freight Expense | C8: 41 | D8: 38 | E8: -64 | F8: 27 | G8: 3895.98 | H8: -3895.98 | I8: 198 | J8: -203 | K8: 90 | L8: 26 | M8: 60 | N8: -210 | O8: =SUM(C8:N8) -> 3
A9: 157001150210 Frt Exp-Oxycodone Products | B9: 7165i In-freight Expense | C9: 216 | D9: 95 | E9: 98 | F9: 37 | G9: 977 | H9: 126 | I9: 1021 | J9: 181 | K9: 411 | L9: 109 | M9: 269 | N9: 13 | O9: =SUM(C9:N9) -> 3553
A10: 157001150211 Frt Exp-Hydrocodone Products | B10: 7165i In-freight Expense | C10: 1012 | D10: 783 | E10: 546 | F10: 492 | G10: 6627 | H10: 1274 | I10: 5549 | J10: 1110 | K10: 2545 | L10: 741 | M10: 1281 | N10: 56 | O10: =SUM(C10:N10) -> 22016
A11: 157001150212 Frt Exp-Methylin Oral Solution | B11: 7165i In-freight Expense | C11: 12 | D11: 6 | E11: 9 | F11: 4 | G11: 43 | H11: 16 | I11: 37 | J11: 11 | K11: 21 | L11: 3 | M11: 12 | N11: 1 | O11: =SUM(C11:N11) -> 175
A12: 157001150219 FREIGHT | B12: 7165i In-freight Expense | C12: 0 | D12: 0 | E12: 0 | F12: 0 | G12: 0 | H12: 0 | I12: 0 | J12: 0 | K12: 0 | L12: 0 | M12: 0 | N12: 0 | O12: =SUM(C12:N12) -> 0
A13: 157001150221 Frt Exp-ADDICTION TREATMENT | B13: 7165i In-freight Expense | C13: 3 | D13: 3 | E13: 33 | F13: 48 | G13: 412 | H13: 54 | I13: 336 | J13: 54 | K13: 114 | L13: 36 | M13: 78 | N13: 3 | O13: =SUM(C13:N13) -> 1174
A14: 157001150222 Frt Exp-Methylphenidate | B14: 7165i In-freight Expense | C14: 271 | D14: 177 | E14: 168 | F14: 112 | G14: 1698 | H14: 365 | I14: 1570 | J14: 357 | K14: 713 | L14: 184 | M14: 338 | N14: 16 | O14: =SUM(C14:N14) -> 5969
A15: 157001150224 Frt Exp-Other Brand Products | B15: 7165i In-freight Expense | C15: 0 | D15: 0 | E15: 0 | F15: 0 | G15: 0 | H15: 0 | I15: 0 | J15: 0 | K15: 0 | L15: 0 | M15: 0 | N15: 0 | O15: =SUM(C15:N15) -> 0
A16: 157001150225 Frt Exp-CNS Non-Promoted Prod | B16: 7165i In-freight Expense | C16: 72 | D16: 50 | E16: 38 | F16: 28 | G16: 276 | H16: 55 | I16: 529 | J16: 69 | K16: 129 | L16: 37 | M16: 98 | N16: 3 | O16: =SUM(C16:N16) -> 1384
A17: 157001150226 Zydus Freight Expense | B17: 7165i In-freight Expense | C17: 0 | D17: 0 | E17: 0 | F17: 0 | G17: 0 | H17: 0 | I17: 0 | J17: 0 | K17: 0 | L17: 0 | M17: 0 | N17: 0 | O17: =SUM(C17:N17) -> 0
A18: 157001150227 Oxycodone ER Products Freight | B18: 7165i In-freight Expense | C18: 0 | D18: 0 | E18: 0 | F18: 0 | G18: 0 | H18: 0 | I18: 0 | J18: 0 | K18: 0 | L18: 0 | M18: 0 | N18: 0 | O18: =SUM(C18:N18) -> 0
A19: 157001150229 Morphine ER-Frt Exp | B19: 7165i In-freight Expense | C19: 278 | D19: 399 | E19: 169 | F19: 155 | G19: 1977 | H19: 316 | I19: 1258 | J19: 303 | K19: 743 | L19: 180 | M19: 362 | N19: 19 | O19: =SUM(C19:N19) -> 6159
A20: 157001150230 Hydromorphone-Frt Exp | B20: 7165i In-freight Expense | C20: 36 | D20: 23 | E20: 18 | F20: 7 | G20: 211 | H20: 48 | I20: 186 | J20: 36 | K20: 84 | L20: 22 | M20: 60 | N20: 2 | O20: =SUM(C20:N20) -> 733
A21: 157001150231 Methadone Generics-Frt Exp | B21: 7165i In-freight Expense | C21: 83 | D21: 19 | E21: 29 | F21: 41 | G21: 226 | H21: 112 | I21: 327 | J21: 76 | K21: 204 | L21: 56 | M21: 98 | N21: 4 | O21: =SUM(C21:N21) -> 1275
A22: 157001150232 APAP Codeine-Frt Exp | B22: 7165i In-freight Expense | C22: 26 | D22: 13 | E22: 12 | F22: 19 | G22: 10 | H22: 0 | I22: 63 | J22: 31 | K22: 34 | L22: 11 | M22: 24 | N22: 6 | O22: =SUM(C22:N22) -> 249
A23: 157001150233 APAP Propoxyphene-Frt Exp | B23: 7165i In-freight Expense | C23: 0 | D23: 0 | E23: 0 | F23: 0 | G23: 0 | H23: 0 | I23: 0 | J23: 0 | K23: 0 | L23: 0 | M23: 0 | N23: 0 | O23: =SUM(C23:N23) -> 0
A24: 157001150234 Fentanyl Lozenge-Frt Exp | B24: 7165i In-freight Expense | C24: 40 | D24: 25 | E24: 33 | F24: 19 | G24: 170 | H24: 39 | I24: 231 | J24: 39 | K24: 91 | L24: 26 | M24: 60 | N24: 4 | O24: =SUM(C24:N24) -> 777
A25: 157001150235 Tussicaps-Frt Exp | B25: 7165i In-freight Expense | C25: 0 | D25: 0 | E25: 0 | F25: 0 | G25: 0 | H25: 0 | I25: 0 | J25: 0 | K25: 0 | L25: 0 | M25: 0 | N25: 0 | O25: =SUM(C25:N25) -> 0
A26: 157001150236 Fentanyl Patch-Frt Exp | B26: 7165i In-freight Expense | C26: 233 | D26: 142 | E26: 135 | F26: 112 | G26: 1020 | H26: 219 | I26: 1103 | J26: 210 | K26: 604 | L26: 131 | M26: 319 | N26: 14 | O26: =SUM(C26:N26) -> 4242
A27: 157001150237 Methylphenidate ER(MedadateCD) | B27: 7165i In-freight Expense | C27: 0 | D27: 0 | E27: 0 | F27: 0 | G27: 0 | H27: 0 | I27: 0 | J27: 0 | K27: 0 | L27: 0 | M27: 0 | N27: 0 | O27: =SUM(C27:N27) -> 0
A28: 157001150238 Methylphenidate ER (Concerta) | B28: 7165i In-freight Expense | C28: 973 | D28: 637 | E28: 327 | F28: 312 | G28: 2731 | H28: 573 | I28: 2443 | J28: 530 | K28: 1031 | L28: 218 | M28: 627 | N28: 28 | O28: =SUM(C28:N28) -> 10430
A29: 157001150240 Tussi Suspension-Frt Exp | B29: 7165i In-freight Expense | C29: 0 | D29: 0 | E29: 0 | F29: 0 | G29: 0 | H29: 0 | I29: 0 | J29: 0 | K29: 0 | L29: 0 | M29: 0 | N29: 0 | O29: =SUM(C29:N29) -> 0
A30: 157001150241 OxymorphoneER(OpanaER) Frt Exp | B30: 7165i In-freight Expense | C30: 0 | D30: 0 | E30: 0 | F30: 0 | G30: 0 | H30: 0 | I30: 0 | J30: 0 | K30: 0 | L30: 0 | M30: 0 | N30: 0 | O30: =SUM(C30:N30) -> 0
A31: 157001150242 New Brands (External)-Frt Exp | B31: 7165i In-freight Expense | C31: 0 | D31: 0 | E31: 0 | F31: 0 | G31: 0 | H31: 0 | I31: 0 | J31: 0 | K31: 0 | L31: 0 | M31: 0 | N31: 0 | O31: =SUM(C31:N31) -> 0
A32: 157001150243 Buprenorphine/Naloxone(Subxne) | B32: 7165i In-freight Expense | C32: 0 | D32: 0 | E32: 0 | F32: 0 | G32: 0 | H32: 0 | I32: 0 | J32: 0 | K32: 0 | L32: 0 | M32: 0 | N32: 0 | O32: =SUM(C32:N32) -> 0
A33: 157001150244 Oxycodone APAP-Frt Exp | B33: 7165i In-freight Expense | C33: 543 | D33: 462 | E33: 222 | F33: 353 | G33: 3608 | H33: 387 | I33: 1705 | J33: 398 | K33: 620 | L33: 163 | M33: 405 | N33: 18 | O33: =SUM(C33:N33) -> 8884
A34: 157001150245 Tofranil-PM/ImipraPam Frt Exp | B34: 7165i In-freight Expense | C34: 0 | D34: 0 | E34: 0 | F34: 0 | G34: 0 | H34: 0 | I34: 0 | J34: 0 | K34: 0 | L34: 0 | M34: 0 | N34: 0 | O34: =SUM(C34:N34) -> 0
A35: 157001150247 Morphine Sulfate ER (Kadian) | B35: 7165i In-freight Expense | C35: 0 | D35: 0 | E35: 0 | F35: 0 | G35: 0 | H35: 0 | I35: 0 | J35: 0 | K35: 0 | L35: 0 | M35: 0 | N35: 0 | O35: =SUM(C35:N35) -> 0
A36: 157001150248 Oxymorphone IR (Opana IR) | B36: 7165i In-freight Expense | C36: 6 | D36: 7 | E36: 7 | F36: 6 | G36: 43 | H36: 5 | I36: 27 | J36: 6 | K36: 18 | L36: 2 | M36: 7 | N36: 0 | O36: =SUM(C36:N36) -> 134
A37: 157001150249 Hydrocodone/APAP GR | B37: 7165i In-freight Expense | C37: 0 | D37: 0 | E37: 0 | F37: 0 | G37: 0 | H37: 0 | I37: 0 | J37: 0 | K37: 0 | L37: 0 | M37: 0 | N37: 0 | O37: =SUM(C37:N37) -> 0
A38: 157001150250 Oxyocodone/APAP GR | B38: 7165i In-freight Expense | C38: 24 | D38: 17 | E38: 10 | F38: 11 | G38: 66 | H38: 13 | I38: 54 | J38: 9 | K38: 16 | L38: 4 | M38: 7 | N38: 0 | O38: =SUM(C38:N38) -> 231
A39: 157001150251 Pennsaid Frt Expense | B39: 7165i In-freight Expense | C39: 0 | D39: 0 | E39: 0 | F39: 0 | G39: 0 | H39: 0 | I39: 0 | J39: 0 | K39: 0 | L39: 0 | M39: 0 | N39: 0 | O39: =SUM(C39:N39) -> 0
A40: 157001150252 Exalgo Freight Exp | B40: 7165i In-freight Expense | C40: 171 | D40: 64 | E40: 80 | F40: 75 | G40: 497 | H40: 112 | I40: 509 | J40: 99 | K40: 175 | L40: 57 | M40: 102 | N40: 5 | O40: =SUM(C40:N40) -> 1946
A41: 157001150253 Temazepam-Frt Exp | B41: 7165i In-freight Expense | C41: 29 | D41: 23 | E41: 16 | F41: 25 | G41: 103 | H41: 29 | I41: 199 | J41: 50 | K41: 99 | L41: 11 | M41: 55 | N41: 2 | O41: =SUM(C41:N41) -> 641
A42: 157001150254 Imipramine Pamoate-Frt Exp | B42: 7165i In-freight Expense | C42: 9 | D42: 4 | E42: 5 | F42: 1 | G42: 10 | H42: 4 | I42: 14 | J42: 3 | K42: 7 | L42: 1 | M42: 3 | N42: 0 | O42: =SUM(C42:N42) -> 61
A43: 157001150255 Pennsaid 2% Pump Frt Expense | B43: 7165i In-freight Expense | C43: 44 | D43: 47 | E43: 23 | F43: 11 | G43: 0 | H43: 0 | I43: 0 | J43: 0 | K43: 0 | L43: 0 | M43: 0 | N43: 0 | O43: =SUM(C43:N43) -> 125
A44: 157001150260 Buprenorphine(Subutex) | B44: 7165i In-freight Expense | C44: 0 | D44: 0 | E44: 0 | F44: 0 | G44: 0 | H44: 0 | I44: 0 | J44: 0 | K44: 0 | L44: 0 | M44: 0 | N44: 0 | O44: =SUM(C44:N44) -> 0
A45: 157001150263 Dextroamphetamine Frt | B45: 7165i In-freight Expense | C45: 40 | D45: 26 | E45: 10 | F45: 3 | G45: 125 | H45: 72 | I45: 128 | J45: 30 | K45: 150 | L45: 20 | M45: 89 | N45: 3 | O45: =SUM(C45:N45) -> 696
A46: 157001150264 Mxd Amphetamine Salt Combo-FRT | B46: 7165i In-freight Expense | C46: 29 | D46: 29 | E46: 9 | F46: 17 | G46: 138 | H46: 21 | I46: 111 | J46: 18 | K46: 52 | L46: 8 | M46: 19 | N46: 1 | O46: =SUM(C46:N46) -> 452
A47: 157001150268 Roxicodone-Freight | B47: 7165i In-freight Expense | C47: 47 | D47: 38 | E47: 28 | F47: 30 | G47: 274 | H47: 38 | I47: 276 | J47: 35 | K47: 71 | L47: 23 | M47: 52 | N47: 2 | O47: =SUM(C47:N47) -> 914
A48: 157001150269 Intrathecal-Freight | B48: 7165i In-freight Expense | C48: 0 | D48: 0 | E48: 0 | F48: 0 | G48: 0 | H48: 0 | I48: 0 | J48: 0 | K48: 0 | L48: 0 | M48: 0 | N48: 0 | O48: =SUM(C48:N48) -> 0
A49: 157001150270 Exalgo AG Freight | B49: 7165i In-freight Expense | C49: 199 | D49: 155 | E49: 122 | F49: 122 | G49: 1153 | H49: 208 | I49: 1041 | J49: 229 | K49: 450 | L49: 76 | M49: 141 | N49: 7 | O49: =SUM(C49:N49) -> 3903
A50: 157001150271 Frt Exp-AT-Ext Mfg Bup/Nal | B50: 7165i In-freight Expense | C50: 53 | D50: 58 | E50: 2 | F50: 3 | G50: 23 | H50: 2 | I50: 11 | J50: 2 | K50: 2 | L50: 1 | M50: 3 | N50: 0 | O50: =SUM(C50:N50) -> 160
A51: 575199150991 Bulk Narcotics | B51: 7165i In-freight Expense | C51: 0 | D51: 390.17 | E51: 1783.9 | F51: 1182.93 | G51: -3292.41 | H51: 0 | I51: 431.27 | J51: -448.07 | K51: 0 | L51: 6042.19 | M51: -6047.01 | N51: 0 | O51: =SUM(C51:N51) -> 42.97
A52: 575000150054 MALL CHEM LTD - PROCESS CHEM | B52: 7165i In-freight Expense | C52: 0 | D52: 0 | E52: 0 | F52: 0 | G52: 0 | H52: 0 | I52: 0 | J52: 0 | K52: 0 | L52: 0 | M52: 0 | N52: 0 | O52: =SUM(C52:N52) -> 0
A53: 575000151151 MC UK Asia APAP Freight Exp | B53: 7165i In-freight Expense | C53: 0 | D53: 0 | E53: 0 | F53: 0 | G53: 0 | H53: 0 | I53: 0 | J53: 0 | K53: 0 | L53: 0 | M53: 0 | N53: 0 | O53: =SUM(C53:N53) -> 0
A54: 575199150992 Stearates & Phosphates | B54: 7165i In-freight Expense | C54: 8453.03 | D54: 0 | E54: 718.07 | F54: 3486.69 | G54: 4041.46 | H54: 2952.7 | I54: 11947.24 | J54: -1938.67 | K54: 9494.83 | L54: 51131.81 | M54: 47544.01 | N54: 10916.78 | O54: =SUM(C54:N54) -> 148747.95
A55: 575199150990 PAP/APAP | B55: 7165i In-freight Expense | C55: 75363.4 | D55: 93038.25 | E55: 72252.2 | F55: 130651.69 | G55: 111563.03 | H55: 85706.63 | I55: 44872 | J55: 129439.3 | K55: 101956.16 | L55: 117390.56 | M55: 142898.48 | N55: 117207.46 | O55: =SUM(C55:N55) -> 1222339.2
A56: 166012150000 Hobart Production Freight | B56: 7165i In-freight Expense | C56: 0 | D56: 0 | E56: 0 | F56: 0 | G56: 0 | H56: 0 | I56: 0 | J56: 0 | K56: 0 | L56: 0 | M56: 0 | N56: 0 | O56: =SUM(C56:N56) -> 0
A57: 575000150051 Freight-APAP | B57: 7165i In-freight Expense | C57: 0 | D57: 0 | E57: 0 | F57: 0 | G57: 0 | H57: 0 | I57: 0 | J57: 0 | K57: 0 | L57: 0 | M57: 0 | N57: 0 | O57: =SUM(C57:N57) -> 0
A58: 097011151603 FREIGHT EUROPE GREENVILLE | B58: 7165i In-freight Expense | C58: 0 | D58: 0 | E58: 0 | F58: 0 | G58: 0 | H58: 0 | I58: 0 | J58: 0 | K58: 0 | L58: 0 | M58: 0 | N58: 0 | O58: =SUM(C58:N58) -> 0
A59: 098001150151 PAP/APAP FRT JAPAN RALEIGH | B59: 7165i In-freight Expense | C59: 0 | D59: 0 | E59: 0 | F59: 0 | G59: 0 | H59: 0 | I59: 0 | J59: 0 | K59: 0 | L59: 0 | M59: 0 | N59: 0 | O59: =SUM(C59:N59) -> 0
A60: 098001150154 SPEC CHEM Japan Freight | B60: 7165i In-freight Expense | C60: 0 | D60: 0 | E60: 0 | F60: 0 | G60: 0 | H60: 0 | I60: 0 | J60: -2153 | K60: 0 | L60: 0 | M60: -3325 | N60: 0 | O60: =SUM(C60:N60) -> -5478
A61: 098001150152 BULK NARCOTICS | B61: 7165i In-freight Expense | C61: 0 | D61: 0 | E61: -453.45 | F61: 0 | G61: 0 | H61: -2701.12 | I61: -606.38 | J61: -5039.82 | K61: -15520.43 | L61: -2381.04 | M61: -5143.3 | N61: -30948.59 | O61: =SUM(C61:N61) -> -62794.13
A62: 098001151681 Freight APAP ASIA PAC RALEIGH | B62: 7165i In-freight Expense | C62: 0 | D62: 0 | E62: 0 | F62: 0 | G62: 0 | H62: 0 | I62: 0 | J62: 0 | K62: 0 | L62: 0 | M62: 0 | N62: 0 | O62: =SUM(C62:N62) -> 0
A63: 098001151684 Freight APAP ASIA PAC GREENVLE | B63: 7165i In-freight Expense | C63: 0 | D63: 0 | E63: 0 | F63: 0 | G63: 0 | H63: 0 | I63: 0 | J63: 0 | K63: 0 | L63: 0 | M63: 0 | N63: 0 | O63: =SUM(C63:N63) -> 0
A64: 099001150051 FRT MC CANADA-APAP-RALEIGH | B64: 7165i In-freight Expense | C64: 0 | D64: 0 | E64: 0 | F64: 0 | G64: 0 | H64: 0 | I64: 0 | J64: 0 | K64: 0 | L64: 0 | M64: 0 | N64: 0 | O64: =SUM(C64:N64) -> 0
A65: 099001150053 FREIGHT CANADA-APAP-GREENVILLE | B65: 7165i In-freight Expense | C65: 0 | D65: 0 | E65: 0 | F65: 0 | G65: 0 | H65: 0 | I65: 0 | J65: 0 | K65: 0 | L65: 0 | M65: 0 | N65: 0 | O65: =SUM(C65:N65) -> 0
A66: 100001151635 APAP CENT AMER EXPORT RALEIGH | B66: 7165i In-freight Expense | C66: 0 | D66: 0 | E66: 0 | F66: 0 | G66: 0 | H66: 0 | I66: 0 | J66: 0 | K66: 0 | L66: 0 | M66: 0 | N66: 0 | O66: =SUM(C66:N66) -> 0
A67: 100001151636 APAP CEN AMER EXPORT GREENVILE | B67: 7165i In-freight Expense | C67: 0 | D67: 0 | E67: 0 | F67: 0 | G67: 0 | H67: 0 | I67: 0 | J67: 0 | K67: 0 | L67: 0 | M67: 0 | N67: 0 | O67: =SUM(C67:N67) -> 0
A68: 106187150000 REAGENTS-Gateway | B68: 7165i In-freight Expense | C68: 0 | D68: 4635.26 | E68: 16470.25 | F68: 10737.91 | G68: 71756.21 | H68: 15189.51 | I68: 2521.68 | J68: 4202.48 | K68: 5806.38 | L68: 0 | M68: 0 | N68: 2460.62 | O68: =SUM(C68:N68) -> 133780.3
A69: 695179159100 Canada Non Prod Spec-Freight | B69: 7165i In-freight Expense | C69: 0 | D69: 0 | E69: 0 | F69: 0 | G69: 0 | H69: 0 | I69: 0 | J69: 0 | K69: 0 | L69: 0 | M69: 0 | N69: 0 | O69: =SUM(C69:N69) -> 0
A70: 173041150256 Ofirmev Freight | B70: 7165i In-freight Expense | C70: 0 | D70: 27405.92 | E70: 601.45 | F70: 0 | G70: 22812.21 | H70: 3259.82 | I70: 14888.44 | J70: -1869.87 | K70: 2250 | L70: 9928.42 | M70: 0 | N70: -400 | O70: =SUM(C70:N70) -> 78876.39
A71: 174214150450 Acthar Freight | B71: 7165i In-freight Expense | C71: 0 | D71: 0 | E71: 0 | F71: 0 | G71: 0 | H71: 0 | I71: 0 | J71: 0 | K71: 0 | L71: 0 | M71: 0 | N71: 0 | O71: 0
A72: 594215150400 Operations-Hillstrom Freight | B72: 7165i In-freight Expense | C72: 0 | D72: 0 | E72: 0 | F72: 0 | G72: 0 | H72: 0 | I72: 0 | J72: 0 | K72: 0 | L72: 0 | M72: 0 | N72: 0 | O72: 0
A73: 594215150450 Operations-Aviation Freight | B73: 7165i In-freight Expense | C73: 0 | D73: 0 | E73: 0 | F73: 0 | G73: 0 | H73: 0 | I73: 0 | J73: 0 | K73: 0 | L73: 0 | M73: 0 | N73: 0 | O73: 0
A74: 594215150440 Operations-JT Ferric Freight | B74: 7165i In-freight Expense | C74: 2386.07 | D74: 0 | E74: 557.14 | F74: 0 | G74: 17.53 | H74: 0 | I74: 0 | J74: 25.54 | K74: 407.78 | L74: 122.28 | M74: 621.66 | N74: 126.58 | O74: =SUM(C74:N74) -> 4264.58
A75: 594215150475 Operations-Support Freight | B75: 7165i In-freight Expense | C75: 39854.99 | D75: 52893.08 | E75: 42451.47 | F75: 31666.24 | G75: 40928.81 | H75: 31236.41 | I75: 52973.18 | J75: 44443.25 | K75: 39111.46 | L75: 25919.23 | M75: 41825.26 | N75: 25500.15 | O75: =SUM(C75:N75) -> 468803.53
A76: 157210151269 Intrathecal-Freight-General | B76: 7165i In-freight Expense | C76: 1858.5 | D76: 0 | E76: 0 | F76: 0 | G76: 0 | H76: 45.84 | I76: 0 | J76: 0 | K76: 1089.02 | L76: 1873.3 | M76: 5311.9 | N76: 9757.36 | O76: =SUM(C76:N76) -> 19935.92
A77: 168210151269 Intrathecal-Freight-General | B77: 7165i In-freight Expense | C77: 0 | D77: 0 | E77: 0 | F77: 0 | G77: 0 | H77: 0 | I77: 0 | J77: 0 | K77: 0 | L77: 0 | M77: 0 | N77: 0 | O77: =SUM(C77:N77) -> 0
A78: In-Freight | C78: =SUM(C8:C77) -> 132405.99 | D78: =SUM(D8:D77) -> 181702.68 | E78: =SUM(E8:E77) -> 136466.03 | F78: =SUM(F8:F77) -> 179795.46 | G78: =SUM(G8:G77) -> 274140.82 | H78: =SUM(H8:H77) -> 135881.81 | I78: =SUM(I8:I77) -> 145953.43 | J78: =SUM(J8:J77) -> 170344.14 | ... O78: =SUM(O8:O77) -> 2084804.7
A80: 168210151269 Intrathecal-Freight-General | B80: 7171i Out-freight Expense (Used only with FDC 15. Also see object 6656 and 7170) | C80: 0 | D80: 0 | E80: 0 | F80: 0 | G80: 0 | H80: 0 | I80: 0 | J80: 0 | K80: 0 | L80: 0 | M80: 0 | N80: 0 | O80: =SUM(C80:N80) -> 0
A81: 157210151269 Intrathecal-Freight-General | B81: 7171i Out-freight Expense (Used only with FDC 15. Also see object 6656 and 7170) | C81: 5429.63 | D81: 34264.44 | E81: 1951.45 | F81: 13361.18 | G81: 18571.58 | H81: 17808.65 | I81: 17988.62 | J81: 16751.96 | K81: 16496.11 | L81: 13612.03 | M81: 15906.45 | N81: 12489.7 | O81: =SUM(C81:N81) -> 184631.8
A82: 594215150400 Operations-Hillstrom Freight | B82: 7171i Out-freight Expense (Used only with FDC 15. Also see object 6656 and 7170) | C82: 6710.79 | D82: 16753.05 | E82: 13784.23 | F82: 6548.99 | G82: 25449.83 | H82: 17691.97 | I82: 8574.67 | J82: 9284.1 | K82: 13090.94 | L82: 16408.89 | M82: 18206.89 | N82: 12351.43 | O82: =SUM(C82:N82) -> 164855.78
A83: 594215150440 Operations-JT Ferric Freight | B83: 7171i Out-freight Expense (Used only with FDC 15. Also see object 6656 and 7170) | C83: 107.32 | D83: 354.26 | E83: 0 | F83: 0 | G83: 54.46 | H83: 50.54 | I83: 82.39 | J83: 0 | K83: 0 | L83: 0 | M83: 0 | N83: 212.21 | O83: =SUM(C83:N83) -> 861.18
A84: 594215150450 Operations-Aviation Freight | B84: 7171i Out-freight Expense (Used only with FDC 15. Also see object 6656 and 7170) | C84: 483.04 | D84: 2808 | E84: 92.29 | F84: 8456.84 | G84: 2194.64 | H84: 1302.71 | I84: 4558.63 | J84: 5583.25 | K84: 2772.03 | L84: 1765.59 | M84: 5809.82 | N84: 5259.32 | O84: =SUM(C84:N84) -> 41086.16
A85: 594215150475 Operations-Support Freight | B85: 7171i Out-freight Expense (Used only with FDC 15. Also see object 6656 and 7170) | C85: 2102.89 | D85: 2982.56 | E85: 3649.98 | F85: 1002.56 | G85: 2544.51 | H85: 1592.96 | I85: 1748.16 | J85: 2133.77 | K85: 1923.2 | L85: 1987.61 | M85: 3129.73 | N85: 2023.87 | O85: =SUM(C85:N85) -> 26821.8
A86: 174214150450 Acthar Freight | B86: 7171i Out-freight Expense (Used only with FDC 15. Also see object 6656 and 7170) | C86: 1194.66 | D86: 173 | E86: 6590.53 | F86: 1933.72 | G86: 2938.4 | H86: 92.94 | I86: 12352.58 | J86: 31708.39 | K86: 6423.63 | L86: 10404.59 | M86: 3033 | N86: 6896.46 | O86: =SUM(C86:N86) -> 83741.9
A87: 173041150256 Ofirmev Freight | B87: 7171i Out-freight Expense (Used only with FDC 15. Also see object 6656 and 7170) | C87: 90284.32 | D87: 76941.88 | E87: 116623.44 | F87: 67355.38 | G87: 149581.18 | H87: 31358.8 | I87: 88585.47 | J87: 46234.03 | K87: 157237.71 | L87: 51518.68 | M87: 77561.71 | N87: 47305.91 | O87: =SUM(C87:N87) -> 1000588.5
A88: 173041150256 Ofirmev Freight | B88: 7171.2000 | C88: 0 | D88: 0 | E88: 0 | F88: 0 | G88: 0 | H88: 0 | I88: 0 | J88: 0 | K88: 0 | L88: 0 | M88: 0 | N88: 0 | O88: =SUM(C88:N88) -> 0
A89: 752000157455 ARD Freight | B89: 7171i Out-freight Expense (Used only with FDC 15. Also see object 6656 and 7170) | C89: 0 | D89: 0 | E89: 0 | F89: 0 | G89: 4968.09 | H89: 1656.03 | I89: 0 | J89: 0 | K89: 0 | L89: 0 | M89: 0 | N89: -4890.03 | O89: =SUM(C89:N89) -> 1734.09
A90: 011000150037 EUROPE NM I/C FREIGHT | B90: Net Spending | C90: 1233.6 | D90: 577.02 | E90: 656.58 | F90: 0 | G90: 2097.44 | H90: 0 | I90: 0 | J90: 0 | K90: 0 | L90: 0 | M90: 0 | N90: 0 | O90: =SUM(C90:N90) -> 4564.64
A91: 011003155302 LAT AMER NM FREIGHT | B91: Net Spending | C91: 116.15 | D91: 328.37 | E91: 0 | F91: -59.85 | G91: 308.96 | H91: 0 | I91: 0 | J91: 5313.95 | K91: 0 | L91: 0 | M91: 800 | N91: 0 | O91: =SUM(C91:N91) -> 6807.58
A92: 011003156701 MEXICO NUC MED FREIGHT | B92: Net Spending | C92: 157.52 | D92: 124.88 | E92: 59.78 | F92: 33.42 | G92: 36.36 | H92: 49.83 | I92: 0 | J92: 0 | K92: 0 | L92: 0 | M92: 0 | N92: 0 | O92: =SUM(C92:N92) -> 461.79
A93: 053003150002 LAT AMER NM EXPORT FREIGHT | B93: Net Spending | C93: 0 | D93: 0 | E93: 0 | F93: 0 | G93: 0 | H93: 0 | I93: 0 | J93: 0 | K93: 0 | L93: 0 | M93: 0 | N93: 0 | O93: =SUM(C93:N93) -> 0
A94: 060003150001 CARIBE NM I/C FREIGHT | B94: Net Spending | C94: 0 | D94: 0 | E94: 0 | F94: 0 | G94: 0 | H94: 0 | I94: 0 | J94: 0 | K94: 0 | L94: 0 | M94: 0 | N94: 0 | O94: =SUM(C94:N94) -> 0
A95: 067003150001 MEXICO NUC MED FREIGHT | B95: Net Spending | C95: 0 | D95: 0 | E95: 0 | F95: 0 | G95: 0 | H95: 0 | I95: 0 | J95: 0 | K95: 0 | L95: 0 | M95: 0 | N95: 0 | O95: =SUM(C95:N95) -> 0
A96: 140003151101 JAPAN Other - Domestic Related | B96: Net Spending | C96: 43 | D96: 53 | E96: 43 | F96: 43 | G96: 53 | H96: 43 | I96: 43 | J96: 53 | K96: 43 | L96: 43 | M96: 53 | N96: 43 | O96: =SUM(C96:N96) -> 556
A97: 140003151102 LATAM Other - Domestic Related | B97: Net Spending | C97: 723 | D97: 904 | E97: 723 | F97: 723 | G97: 904 | H97: 723 | I97: 1123 | J97: 904 | K97: 723 | L97: 723 | M97: 904 | N97: 723 | O97: =SUM(C97:N97) -> 9800
A98: 140003151103 EMEA Other - Domestic Related | B98: Net Spending | C98: 2085 | D98: 2606 | E98: 2085 | F98: 2085 | G98: 2606 | H98: 2085 | I98: 2085 | J98: 2606 | K98: 2085 | L98: 2085 | M98: 2606 | N98: 2085 | O98: =SUM(C98:N98) -> 27104
A99: 140003151104 ASIA Other - Domestic Related | B99: Net Spending | C99: 1404 | D99: 1755 | E99: 1404 | F99: 1404 | G99: 1755 | H99: 1404 | I99: 1404 | J99: 1755 | K99: 1404 | L99: 1404 | M99: 1755 | N99: 1404 | O99: =SUM(C99:N99) -> 18252
A100: 161001151644 Gen Export Freight-China | B100: Net Spending | C100: 51851.36 | D100: 0 | E100: 0 | F100: 0 | G100: 0 | H100: -215624.2 | I100: 0 | J100: 0 | K100: 0 | L100: 0 | M100: 0 | N100: 0 | O100: =SUM(C100:N100) -> -163772.84
A101: 161001151661 Gen Export Freight-Colombia | B101: Net Spending | C101: 0 | D101: 2047 | E101: 2583.85 | F101: 8383 | G101: 0 | H101: 0 | I101: 23124.9 | J101: 11624.7 | K101: 0 | L101: 1497.6 | M101: 0 | N101: 2225.25 | O101: =SUM(C101:N101) -> 51486.3
A102: 161001151662 Gen Export Freight-Venezuela | B102: Net Spending | C102: 0 | D102: 874.45 | E102: 1166.95 | F102: 0 | G102: 0 | H102: 0 | I102: 400.74 | J102: 0 | K102: 0 | L102: 0 | M102: 0 | N102: 0 | O102: =SUM(C102:N102) -> 2442.14
...

Sheet check
A3: Net Spending
A4: FDC 015 Out-Freight Expense
B5: Sep | C5: Sep | D5: Sep | E5: Sep | F5: Annual | G5: Annual | H5: Annual | I5: Annual
B6: FY 2015 | C6: FY 2015 | D6: FY 2015 | E6: FY 2015 | F6: FY 2015 | G6: FY 2015 | H6: FY 2015 | I6: FY 2015
B7: Actual Rate | C7: Budget Rate | D7: Forecast Rate | E7: Actual Rate | F7: Actual Rate | G7: Budget Rate | H7: Forecast Rate | I7: Actual Rate
B8: USD | C8: USD | D8: USD | E8: USD | F8: USD | G8: USD | H8: USD | I8: USD
B9: Actuals | C9: Budget | D9: Current Forecast | E9: Actuals | F9: Actuals | G9: Budget | H9: Current Forecast | I9: Actuals
A10: Global Pharma/Imaging - CYR | B10: 5435515.9 | C10: 3301909.1 | D10: 0 | E10: 5435515.9 | F10: 59506486 | G10: 40361259 | H10: 0 | I10: 59506486
A11: WW APIs - CYR | B11: 662491.46 | C11: 456911.61 | D11: 0 | E11: 662491.46 | F11: 6761392.7 | G11: 5939850.9 | H11: 0 | I11: 6761392.7
A12: U.S. Specialty Generics - CYR | B12: 347440.64 | C12: 444008.14 | D12: 0 | E12: 347440.64 | F12: 4991630.8 | G12: 5844127.1 | H12: 0 | I12: 4991630.8
A13: US Branded Pharmaceuticals - CYR | B13: 477389.16 | C13: 491188.93 | D13: 0 | E13: 477389.16 | F13: 2939341 | G13: 3761200.8 | H13: 0 | I13: 2939341
A14: Operations - CYR | B14: 47449.24 | C14: 0 | D14: 0 | E14: 47449.24 | F14: 764494.3 | G14: 0 | H14: 0 | I14: 764494.3
A15: US Contrast - CYR | B15: 175796.98 | C15: 147279 | D15: 0 | E15: 175796.98 | F15: 2347882.1 | G15: 1914633 | H15: 0 | I15: 2347882.1
A16: US Nuclear - CYR | B16: 910383.41 | C16: 1500000 | D16: 0 | E16: 910383.41 | F16: 13577297 | G16: 19500000 | H16: 0 | I16: 13577297
A17: Contract Manufacturing - CYR | B17: 45473.56 | C17: 0 | D17: 0 | E17: 45473.56 | F17: 706693.03 | G17: 0 | H17: 0 | I17: 706693.03
A18: Canada Pharma/Imaging - CYR | B18: 110038.17 | C18: 260521.45 | D18: 0 | E18: 110038.17 | F18: 2129807.2 | G18: 3377446.8 | H18: 0 | I18: 2129807.2
A19: Latin America Pharma/IMG - CYR | B19: 346522.13 | C19: 0 | D19: 0 | E19: 346522.13 | F19: 3047677.1 | G19: 0 | H19: 0 | I19: 3047677.1
A20: Asia Pac Pharma/IMG - CYR | B20: 206872.56 | C20: 0 | D20: 0 | E20: 206872.56 | F20: 2407876.5 | G20: 0 | H20: 0 | I20: 2407876.5
A21: EMEA Pharm/IMG - CYR | B21: 2133289.9 | C21: 0 | D21: 0 | E21: 2133289.9 | F21: 20031205 | G21: 0 | H21: 0 | I21: 20031205
A22: Autoimmune and Rare Disease - CYR | B22: 2006.43 | C22: 2000 | D22: 0 | E22: 2006.43 | F22: 85475.99 | G22: 24000 | H22: 0 | I22: 85475.99
A23: EMEA Pharma/Imaging - CYR | B23: 9470.16 | C23: 0 | D23: 0 | E23: 9470.16 | F23: 295812.28 | G23: 0 | H23: 0 | I23: 295812.28
A24: Latin America Pharma/ Imaging - CYR | B24: 3348.25 | C24: 0 | D24: 0 | E24: 3348.25 | F24: 72676.81 | G24: 0 | H24: 0 | I24: 72676.81
A25: Asia Pacific & Japan Pharma/Imaging - CYR | B25: 3017.47 | C25: 0 | D25: 0 | E25: 3017.47 | F25: 6973.62 | G25: 0 | H25: 0 | I25: 6973.62
A26: Canada Export-Sp Generic - CYR | B26: 0 | C26: 0 | D26: 0 | E26: 0 | F26: 46944.41 | G26: 0 | H26: 0 | I26: 46944.41
B28: =SUM(B11:B26) -> 5480989.5 | C28: =SUM(C11:C26) -> 3301909.1 | D28: =SUM(D11:D26) -> 0 | E28: =SUM(E11:E26) -> 5480989.5 | F28: =SUM(F11:F26) -> 60213179 | G28: =SUM(G11:G26) -> 40361259 | H28: =SUM(H11:H26) -> 0 | I28: =SUM(I11:I26) -> 60213179
B29: =+B28-B10-B17 -> -2.2700988e-09 | C29: =+C28-C10-C17 -> 0 | D29: =+D28-D10-D17 -> 0 | E29: =+E28-E10-E17 -> -2.2700988e-09 | F29: =+F28-F10-F17 -> 1.1641532e-09 | G29: =+G28-G10-G17 -> 7.4505806e-09 | H29: =+H28-H10-H17 -> 0 | I29: =+I28-I10-I17 -> 1.1641532e-09
